Workbook
Name Macrobond_Object1: Macrobond!$A$3:$PB$957

Sheet Print Summary
A1: ="CPI PRINT SUMMARY — "&UPPER(TEXT(Engine!$B$5,"mmmm yyyy")) -> CPI PRINT SUMMARY — MAY 2026
A2: 5-minute desk read | All figures seasonally adjusted | Detail: Momentum · Breadth · PCE Bridge tabs
B3: ="CORE: "&Engine!$AG$12&" | HEADLINE: "&Engine!$AG$11&" | SUPERCORE: "&Engine!$AG$19 -> CORE: ▼ TURN DN | HEADLINE: ▼ TURN DN | SUPERCORE: ▲▲ ACCEL
B5: HEADLINE M/M | D5: CORE M/M | F5: HEADLINE Y/Y | H5: CORE Y/Y | J5: CORE 3M SAAR | L5: IMPLIED CORE PCE M/M
B6: =Engine!$W$11 -> 0.0047291423 | D6: =Engine!$W$12 -> 0.0020809545 | F6: =Engine!$Z$11 -> 0.041666147 | H6: =Engine!$Z$12 -> 0.028229421 | J6: =Engine!$AC$12 -> 0.031660324 | L6: ='PCE Bridge'!$D$50 -> 0.0021865118
B8: MOMENTUM STACK (SAAR)
C9: 1m SAAR | D9: 3m SAAR | E9: 6m SAAR | F9: Y/Y | G9: Signal
B10: Headline CPI | C10: =Engine!$AB$11 -> 0.058249301 | D10: =Engine!$AC$11 -> 0.082040733 | E10: =Engine!$AD$11 -> 0.055609383 | F10: =Engine!$Z$11 -> 0.041666147 | G10: =Engine!$AG$11 -> ▼ TURN DN
B11: Core CPI | C11: =Engine!$AB$12 -> 0.02525925 | D11: =Engine!$AC$12 -> 0.031660324 | E11: =Engine!$AD$12 -> 0.030914091 | F11: =Engine!$Z$12 -> 0.028229421 | G11: =Engine!$AG$12 -> ▼ TURN DN
B12: Supercore (svcs ex shelter/energy) | C12: =Engine!$AB$19 -> 0.070995747 | D12: =Engine!$AC$19 -> 0.045879594 | E12: =Engine!$AD$19 -> 0.039115572 | F12: =Engine!$Z$19 -> 0.035482623 | G12: =Engine!$AG$19 -> ▲▲ ACCEL
B13: Core Goods ex Used Veh. | C13: =Engine!$AB$17 -> -0.017778419 | D13: =Engine!$AC$17 -> 0.0033956747 | E13: =Engine!$AD$17 -> 0.015289127 | F13: =Engine!$Z$17 -> 0.015732175 | G13: =Engine!$AG$17 -> ▼▼ DECEL
B14: Shelter | C14: =Engine!$AB$23 -> 0.038813528 | D14: =Engine!$AC$23 -> 0.048681725 | E14: =Engine!$AD$23 -> 0.041267773 | F14: =Engine!$Z$23 -> 0.033539479 | G14: =Engine!$AG$23 -> ▼ TURN DN
B16: TAKEAWAYS
B17: ="• Headline "&TEXT(Engine!$W$11,"+0.0%;-0.0%")&" m/m / "&TEXT(Engine!$Z$11,"0.0%")&" y/y; core "&TEXT(Engine!$W$12,"+0.00%;-0.00%")&" m/m / "&TEXT(Engine!$Z$12,"0.0%")&" y/y." -> • Headline +0.5% m/m / 4.2% y/y; core +0.21% m/m / 2.8% y/y.
B18: ="• Energy "&TEXT(Engine!$W$14,"+0.0%;-0.0%")&" m/m ("&TEXT(Engine!$AH$14,"+0.00;-0.00")&"pp of headline); food "&TEXT(Engine!$W$13,"+0.0%;-0.0%")&" ("&TEXT(Engine!$AH$13,"+0.00;-0.00")&"pp)." -> • Energy +3.8% m/m (+0.28pp of headline); food +0.2% (+0.02pp).
B19: ="• Core momentum: 1m SAAR "&TEXT(Engine!$AB$12,"0.0%")&" vs 3m "&TEXT(Engine!$AC$12,"0.0%")&" vs 6m "&TEXT(Engine!$AD$12,"0.0%")&"; supercore 1m "&TEXT(Engine!$AB$19,"0.0%")&" vs 3m "&TEXT(Engine!$AC$19,"0.0%")&"." -> • Core momentum: 1m SAAR 2.5% vs 3m 3.2% vs 6m 3.1%; supercore 1m 7.1% vs 3m 4.6%.
B20: ="• Breadth: "&TEXT(Breadth!$D$22,"0%")&" of components accelerating m/m (prior "&TEXT(Breadth!$E$22,"0%")&"); "&TEXT(Breadth!$D$25,"0%")&" running >4% on 3m SAAR; median m/m "&TEXT(Breadth!$D$26,"0.00%")&"." -> • Breadth: 32% of components accelerating m/m (prior 57%); 46% running >4% on 3m SAAR; median m/m 0.29%.
B21: ="• Top contributor: "&Breadth!$A$6&" ("&TEXT(Breadth!$D$6,"+0.000;-0.000")&"pp); top drag: "&Breadth!$G$6&" ("&TEXT(Breadth!$J$6,"+0.000;-0.000")&"pp). Top core: "&Breadth!$A$14&" ("&TEXT(Breadth!$D$14,"+0.000;-0.000")&"pp)." -> • Top contributor: Motor Fuel (+0.266pp); top drag: MV Insurance (-0.044pp). Top core: Owners' Equivalent Rent (+0.098pp).
B22: ="• PCE read-through: implied core PCE "&TEXT('PCE Bridge'!$D$50,"+0.00%;-0.00%")&" m/m ("&TEXT('PCE Bridge'!$D$51,"0.0%")&" annualized) — "&'PCE Bridge'!$D$54&"." -> • PCE read-through: implied core PCE +0.22% m/m (2.7% annualized) — WARM — modestly above 2% target pace.
B24: ="Auto-generated from Macrobond BLS pull (latest: "&TEXT(Engine!$B$5,"mmm-yy")&") and BEA nominal PCE (weights: "&TEXT('PCE Bridge'!$B$5,"mmm-yy")&"). New months flow through automatically. Weights: BLS RI Dec-2025; PCE = nominal core shares." -> Auto-generated from Macrobond BLS pull (latest: May-26) and BEA nominal PCE (weights: Mar-26). New months flow through automatically. Weights: BLS RI Dec-2025; PCE = nominal core shares.

Sheet Momentum
A1: CPI MOMENTUM & TREND TRACKER
A2: ="Latest print: "&TEXT(Engine!$B$5,"mmmm yyyy")&" | All SAAR figures are seasonally adjusted annualized rates | Heatmap = m/m % chg, trailing 13 months" -> Latest print: May 2026 | All SAAR figures are seasonally adjusted annualized rates | Heatmap = m/m % chg, trailing 13 months
N4: 1 | O4: 2 | P4: 3 | Q4: 4 | R4: 5 | S4: 6 | T4: 7 | U4: 8 | V4: 9 | W4: 10 | X4: 11 | Y4: 12 | Z4: 13
A5: Component | B5: Bucket | C5: Wt % | D5: M/M | E5: M/M -1 | F5: Y/Y | G5: Y/Y -1 | H5: 1m SAAR | I5: 3m SAAR | J5: 6m SAAR | K5: Δ 1m-3m | L5: Δ 3m-6m | M5: SIGNAL | N5: =TEXT(EDATE(Engine!$B$5,1-N$4),"mmm-yy") -> May-26 | O5: =TEXT(EDATE(Engine!$B$5,1-O$4),"mmm-yy") -> Apr-26 | P5: =TEXT(EDATE(Engine!$B$5,1-P$4),"mmm-yy") -> Mar-26 | Q5: =TEXT(EDATE(Engine!$B$5,1-Q$4),"mmm-yy") -> Feb-26 | R5: =TEXT(EDATE(Engine!$B$5,1-R$4),"mmm-yy") -> Jan-26 | S5: =TEXT(EDATE(Engine!$B$5,1-S$4),"mmm-yy") -> Dec-25 | T5: =TEXT(EDATE(Engine!$B$5,1-T$4),"mmm-yy") -> Nov-25 | U5: =TEXT(EDATE(Engine!$B$5,1-U$4),"mmm-yy") -> Oct-25 | ... Z5: =TEXT(EDATE(Engine!$B$5,1-Z$4),"mmm-yy") -> May-25
A6: =Engine!A11 -> All Items (CPI-U) | B6: =Engine!B11 -> AGG | C6: =Engine!V11 -> 100 | D6: =Engine!W11 -> 0.0047291423 | E6: =Engine!X11 -> 0.0064003778 | F6: =Engine!Z11 -> 0.041666147 | G6: =Engine!AA11 -> 0.037792458 | H6: =Engine!AB11 -> 0.058249301 | I6: =Engine!AC11 -> 0.082040733 | J6: =Engine!AD11 -> 0.055609383 | K6: =Engine!AE11 -> -0.023791432 | L6: =Engine!AF11 -> 0.026431351 | M6: =Engine!AG11 -> ▼ TURN DN | N6: {=INDEX(Engine!$H11:$U11,1,N$4)/INDEX(Engine!$H11:$U11,1,N$4+1)-1} -> 0.0047291423 | O6: {=INDEX(Engine!$H11:$U11,1,O$4)/INDEX(Engine!$H11:$U11,1,O$4+1)-1} -> 0.0064003778 | P6: {=INDEX(Engine!$H11:$U11,1,P$4)/INDEX(Engine!$H11:$U11,1,P$4+1)-1} -> 0.0086514383 | Q6: {=INDEX(Engine!$H11:$U11,1,Q$4)/INDEX(Engine!$H11:$U11,1,Q$4+1)-1} -> 0.0026700307 | R6: {=INDEX(Engine!$H11:$U11,1,R$4)/INDEX(Engine!$H11:$U11,1,R$4+1)-1} -> 0.0017084265 | S6: {=INDEX(Engine!$H11:$U11,1,S$4)/INDEX(Engine!$H11:$U11,1,S$4+1)-1} -> 0.0029778843 | T6: {=INDEX(Engine!$H11:$U11,1,T$4)/INDEX(Engine!$H11:$U11,1,T$4+1)-1} -> 0.0025227837 | U6: {=INDEX(Engine!$H11:$U11,1,U$4)/INDEX(Engine!$H11:$U11,1,U$4+1)-1} -> 0 | ... Z6: {=INDEX(Engine!$H11:$U11,1,Z$4)/INDEX(Engine!$H11:$U11,1,Z$4+1)-1} -> 0.00099281303
A7: =Engine!A12 -> Core CPI (ex Food & Energy) | B7: =Engine!B12 -> AGG | C7: =Engine!V12 -> 79.02977 | D7: =Engine!W12 -> 0.0020809545 | E7: =Engine!X12 -> 0.0037646073 | F7: =Engine!Z12 -> 0.028229421 | G7: =Engine!AA12 -> 0.027433094 | H7: =Engine!AB12 -> 0.02525925 | I7: =Engine!AC12 -> 0.031660324 | J7: =Engine!AD12 -> 0.030914091 | K7: =Engine!AE12 -> -0.0064010741 | L7: =Engine!AF12 -> 0.00074623331 | M7: =Engine!AG12 -> ▼ TURN DN | N7: {=INDEX(Engine!$H12:$U12,1,N$4)/INDEX(Engine!$H12:$U12,1,N$4+1)-1} -> 0.0020809545 | O7: {=INDEX(Engine!$H12:$U12,1,O$4)/INDEX(Engine!$H12:$U12,1,O$4+1)-1} -> 0.0037646073 | P7: {=INDEX(Engine!$H12:$U12,1,P$4)/INDEX(Engine!$H12:$U12,1,P$4+1)-1} -> 0.0019579505 | Q7: {=INDEX(Engine!$H12:$U12,1,Q$4)/INDEX(Engine!$H12:$U12,1,Q$4+1)-1} -> 0.0021605022 | R7: {=INDEX(Engine!$H12:$U12,1,R$4)/INDEX(Engine!$H12:$U12,1,R$4+1)-1} -> 0.0029504481 | S7: {=INDEX(Engine!$H12:$U12,1,S$4)/INDEX(Engine!$H12:$U12,1,S$4+1)-1} -> 0.0023290026 | T7: {=INDEX(Engine!$H12:$U12,1,T$4)/INDEX(Engine!$H12:$U12,1,T$4+1)-1} -> 0.0018915434 | U7: {=INDEX(Engine!$H12:$U12,1,U$4)/INDEX(Engine!$H12:$U12,1,U$4+1)-1} -> 0 | ... Z7: {=INDEX(Engine!$H12:$U12,1,Z$4)/INDEX(Engine!$H12:$U12,1,Z$4+1)-1} -> 0.0013048792
A8: =Engine!A13 -> Food | B8: =Engine!B13 -> FOOD | C8: =Engine!V13 -> 13.537308 | D8: =Engine!W13 -> 0.0015587816 | E8: =Engine!X13 -> 0.0050374636 | F8: =Engine!Z13 -> 0.030779321 | G8: =Engine!AA13 -> 0.032166593 | H8: =Engine!AB13 -> 0.018866582 | I8: =Engine!AC13 -> 0.026454138 | J8: =Engine!AD13 -> 0.038364964 | K8: =Engine!AE13 -> -0.0075875566 | L8: =Engine!AF13 -> -0.011910826 | M8: =Engine!AG13 -> ▼▼ DECEL | N8: {=INDEX(Engine!$H13:$U13,1,N$4)/INDEX(Engine!$H13:$U13,1,N$4+1)-1} -> 0.0015587816 | O8: {=INDEX(Engine!$H13:$U13,1,O$4)/INDEX(Engine!$H13:$U13,1,O$4+1)-1} -> 0.0050374636 | P8: {=INDEX(Engine!$H13:$U13,1,P$4)/INDEX(Engine!$H13:$U13,1,P$4+1)-1} -> -5.4814755e-05 | Q8: {=INDEX(Engine!$H13:$U13,1,Q$4)/INDEX(Engine!$H13:$U13,1,Q$4+1)-1} -> 0.0039128684 | R8: {=INDEX(Engine!$H13:$U13,1,R$4)/INDEX(Engine!$H13:$U13,1,R$4+1)-1} -> 0.0018541517 | S8: {=INDEX(Engine!$H13:$U13,1,S$4)/INDEX(Engine!$H13:$U13,1,S$4+1)-1} -> 0.0065598477 | T8: {=INDEX(Engine!$H13:$U13,1,T$4)/INDEX(Engine!$H13:$U13,1,T$4+1)-1} -> 0.00087697246 | U8: {=INDEX(Engine!$H13:$U13,1,U$4)/INDEX(Engine!$H13:$U13,1,U$4+1)-1} -> 0 | ... Z8: {=INDEX(Engine!$H13:$U13,1,Z$4)/INDEX(Engine!$H13:$U13,1,Z$4+1)-1} -> 0.002906727
A9: =Engine!A14 -> Energy (derived composite) | B9: =Engine!B14 -> ENERGY | C9: =Engine!V14 -> 7.3459231 | D9: =Engine!W14 -> 0.037692312 | E9: =Engine!X14 -> 0.037373436 | F9: =Engine!Z14 -> 0.22279599 | G9: =Engine!AA14 -> 0.1701922 | H9: =Engine!AB14 -> 0.55891771 | I9: =Engine!AC14 -> 1.002602 | J9: =Engine!AD14 -> 0.39999134 | K9: =Engine!AE14 -> -0.4436843 | L9: =Engine!AF14 -> 0.60261068 | M9: =Engine!AG14 -> ▼ TURN DN | N9: {=INDEX(Engine!$H14:$U14,1,N$4)/INDEX(Engine!$H14:$U14,1,N$4+1)-1} -> 0.037692312 | O9: {=INDEX(Engine!$H14:$U14,1,O$4)/INDEX(Engine!$H14:$U14,1,O$4+1)-1} -> 0.037373436 | P9: {=INDEX(Engine!$H14:$U14,1,P$4)/INDEX(Engine!$H14:$U14,1,P$4+1)-1} -> 0.10508311 | Q9: {=INDEX(Engine!$H14:$U14,1,Q$4)/INDEX(Engine!$H14:$U14,1,Q$4+1)-1} -> 0.0062895223 | R9: {=INDEX(Engine!$H14:$U14,1,R$4)/INDEX(Engine!$H14:$U14,1,R$4+1)-1} -> -0.015018152 | S9: {=INDEX(Engine!$H14:$U14,1,S$4)/INDEX(Engine!$H14:$U14,1,S$4+1)-1} -> 0.0034895044 | T9: {=INDEX(Engine!$H14:$U14,1,T$4)/INDEX(Engine!$H14:$U14,1,T$4+1)-1} -> 0.014070024 | U9: {=INDEX(Engine!$H14:$U14,1,U$4)/INDEX(Engine!$H14:$U14,1,U$4+1)-1} -> 0 | ... Z9: {=INDEX(Engine!$H14:$U14,1,Z$4)/INDEX(Engine!$H14:$U14,1,Z$4+1)-1} -> -0.0069484507
A10: =Engine!A15 -> All Items ex Shelter | B10: =Engine!B15 -> AGG | C10: =Engine!V15 -> 64.646156 | D10: =Engine!W15 -> 0.0055755185 | E10: =Engine!X15 -> 0.0065812274 | F10: =Engine!Z15 -> 0.046135496 | G10: =Engine!AA15 -> 0.040454487 | H10: =Engine!AB15 -> 0.068996539 | I10: =Engine!AC15 -> 0.10072847 | J10: =Engine!AD15 -> 0.063526498 | K10: =Engine!AE15 -> -0.031731927 | L10: =Engine!AF15 -> 0.037201968 | M10: =Engine!AG15 -> ▼ TURN DN | N10: {=INDEX(Engine!$H15:$U15,1,N$4)/INDEX(Engine!$H15:$U15,1,N$4+1)-1} -> 0.0055755185 | O10: {=INDEX(Engine!$H15:$U15,1,O$4)/INDEX(Engine!$H15:$U15,1,O$4+1)-1} -> 0.0065812274 | P10: {=INDEX(Engine!$H15:$U15,1,P$4)/INDEX(Engine!$H15:$U15,1,P$4+1)-1} -> 0.01194412 | Q10: {=INDEX(Engine!$H15:$U15,1,Q$4)/INDEX(Engine!$H15:$U15,1,Q$4+1)-1} -> 0.0028682549 | R10: {=INDEX(Engine!$H15:$U15,1,R$4)/INDEX(Engine!$H15:$U15,1,R$4+1)-1} -> 0.0014327627 | S10: {=INDEX(Engine!$H15:$U15,1,S$4)/INDEX(Engine!$H15:$U15,1,S$4+1)-1} -> 0.0025093415 | T10: {=INDEX(Engine!$H15:$U15,1,T$4)/INDEX(Engine!$H15:$U15,1,T$4+1)-1} -> 0.0025845655 | U10: {=INDEX(Engine!$H15:$U15,1,U$4)/INDEX(Engine!$H15:$U15,1,U$4+1)-1} -> 0 | ... Z10: {=INDEX(Engine!$H15:$U15,1,Z$4)/INDEX(Engine!$H15:$U15,1,Z$4+1)-1} -> 0.00011476944
A11: =Engine!A16 -> All ex Food, Shelter & Energy | B11: =Engine!B16 -> AGG | C11: =Engine!V16 -> 43.679279 | D11: =Engine!W16 -> 0.0011968902 | E11: =Engine!X16 -> 0.001920108 | F11: =Engine!Z16 -> 0.023990982 | G11: =Engine!AA16 -> 0.023053306 | H11: =Engine!AB16 -> 0.014457609 | I11: =Engine!AC16 -> 0.018181288 | J11: =Engine!AD16 -> 0.022689519 | K11: =Engine!AE16 -> -0.0037236798 | L11: =Engine!AF16 -> -0.0045082308 | M11: =Engine!AG16 -> ▼▼ DECEL | N11: {=INDEX(Engine!$H16:$U16,1,N$4)/INDEX(Engine!$H16:$U16,1,N$4+1)-1} -> 0.0011968902 | O11: {=INDEX(Engine!$H16:$U16,1,O$4)/INDEX(Engine!$H16:$U16,1,O$4+1)-1} -> 0.001920108 | P11: {=INDEX(Engine!$H16:$U16,1,P$4)/INDEX(Engine!$H16:$U16,1,P$4+1)-1} -> 0.0013910214 | Q11: {=INDEX(Engine!$H16:$U16,1,Q$4)/INDEX(Engine!$H16:$U16,1,Q$4+1)-1} -> 0.0020360849 | R11: {=INDEX(Engine!$H16:$U16,1,R$4)/INDEX(Engine!$H16:$U16,1,R$4+1)-1} -> 0.0035554548 | S11: {=INDEX(Engine!$H16:$U16,1,S$4)/INDEX(Engine!$H16:$U16,1,S$4+1)-1} -> 0.001130949 | T11: {=INDEX(Engine!$H16:$U16,1,T$4)/INDEX(Engine!$H16:$U16,1,T$4+1)-1} -> 0.0014734652 | U11: {=INDEX(Engine!$H16:$U16,1,U$4)/INDEX(Engine!$H16:$U16,1,U$4+1)-1} -> 0 | ... Z11: {=INDEX(Engine!$H16:$U16,1,Z$4)/INDEX(Engine!$H16:$U16,1,Z$4+1)-1} -> 0.0002800869
A12: =Engine!A17 -> Core Goods ex Used Vehicles | B12: =Engine!B17 -> AGG | C12: =Engine!V17 -> 16.122398 | D12: =Engine!W17 -> -0.0014937461 | E12: =Engine!X17 -> 0.00040209329 | F12: =Engine!Z17 -> 0.015732175 | G12: =Engine!AA17 -> 0.017698845 | H12: =Engine!AB17 -> -0.017778419 | I12: =Engine!AC17 -> 0.0033956747 | J12: =Engine!AD17 -> 0.015289127 | K12: =Engine!AE17 -> -0.021174094 | L12: =Engine!AF17 -> -0.011893453 | M12: =Engine!AG17 -> ▼▼ DECEL | N12: {=INDEX(Engine!$H17:$U17,1,N$4)/INDEX(Engine!$H17:$U17,1,N$4+1)-1} -> -0.0014937461 | O12: {=INDEX(Engine!$H17:$U17,1,O$4)/INDEX(Engine!$H17:$U17,1,O$4+1)-1} -> 0.00040209329 | P12: {=INDEX(Engine!$H17:$U17,1,P$4)/INDEX(Engine!$H17:$U17,1,P$4+1)-1} -> 0.0019422146 | Q12: {=INDEX(Engine!$H17:$U17,1,Q$4)/INDEX(Engine!$H17:$U17,1,Q$4+1)-1} -> 0.0015598087 | R12: {=INDEX(Engine!$H17:$U17,1,R$4)/INDEX(Engine!$H17:$U17,1,R$4+1)-1} -> 0.0035780338 | S12: {=INDEX(Engine!$H17:$U17,1,S$4)/INDEX(Engine!$H17:$U17,1,S$4+1)-1} -> 0.0016102865 | T12: {=INDEX(Engine!$H17:$U17,1,T$4)/INDEX(Engine!$H17:$U17,1,T$4+1)-1} -> -0.00039938519 | U12: {=INDEX(Engine!$H17:$U17,1,U$4)/INDEX(Engine!$H17:$U17,1,U$4+1)-1} -> 0 | ... Z12: {=INDEX(Engine!$H17:$U17,1,Z$4)/INDEX(Engine!$H17:$U17,1,Z$4+1)-1} -> 0.00043957117
A13: =Engine!A18 -> Services ex Rent of Shelter | B13: =Engine!B18 -> AGG | C13: =Engine!V18 -> 28.525555 | D13: =Engine!W18 -> 0.0054837393 | E13: =Engine!X18 -> 0.0038479559 | F13: =Engine!Z18 -> 0.037420901 | G13: =Engine!AA18 -> 0.035182765 | H13: =Engine!AB18 -> 0.067826314 | I13: =Engine!AC18 -> 0.051888458 | J13: =Engine!AD18 -> 0.04339725 | K13: =Engine!AE18 -> 0.015937856 | L13: =Engine!AF18 -> 0.0084912078 | M13: =Engine!AG18 -> ▲▲ ACCEL | N13: {=INDEX(Engine!$H18:$U18,1,N$4)/INDEX(Engine!$H18:$U18,1,N$4+1)-1} -> 0.0054837393 | O13: {=INDEX(Engine!$H18:$U18,1,O$4)/INDEX(Engine!$H18:$U18,1,O$4+1)-1} -> 0.0038479559 | P13: {=INDEX(Engine!$H18:$U18,1,P$4)/INDEX(Engine!$H18:$U18,1,P$4+1)-1} -> 0.0033430157 | Q13: {=INDEX(Engine!$H18:$U18,1,Q$4)/INDEX(Engine!$H18:$U18,1,Q$4+1)-1} -> 0.0028172286 | R13: {=INDEX(Engine!$H18:$U18,1,R$4)/INDEX(Engine!$H18:$U18,1,R$4+1)-1} -> 0.0034760709 | S13: {=INDEX(Engine!$H18:$U18,1,S$4)/INDEX(Engine!$H18:$U18,1,S$4+1)-1} -> 0.0023135793 | T13: {=INDEX(Engine!$H18:$U18,1,T$4)/INDEX(Engine!$H18:$U18,1,T$4+1)-1} -> 0.0042280575 | U13: {=INDEX(Engine!$H18:$U18,1,U$4)/INDEX(Engine!$H18:$U18,1,U$4+1)-1} -> 0 | ... Z13: {=INDEX(Engine!$H18:$U18,1,Z$4)/INDEX(Engine!$H18:$U18,1,Z$4+1)-1} -> 0.0033145045
A14: =Engine!A19 -> Supercore — Svcs ex Shelter & Energy (derived) | B14: =Engine!B19 -> AGG | C14: =Engine!V19 -> 25.252733 | D14: =Engine!W19 -> 0.0057321011 | E14: =Engine!X19 -> 0.0022658923 | F14: =Engine!Z19 -> 0.035482623 | G14: =Engine!AA19 -> 0.032820694 | H14: =Engine!AB19 -> 0.070995747 | I14: =Engine!AC19 -> 0.045879594 | J14: =Engine!AD19 -> 0.039115572 | K14: =Engine!AE19 -> 0.025116154 | L14: =Engine!AF19 -> 0.0067640223 | M14: =Engine!AG19 -> ▲▲ ACCEL | N14: {=INDEX(Engine!$H19:$U19,1,N$4)/INDEX(Engine!$H19:$U19,1,N$4+1)-1} -> 0.0057321011 | O14: {=INDEX(Engine!$H19:$U19,1,O$4)/INDEX(Engine!$H19:$U19,1,O$4+1)-1} -> 0.0022658923 | P14: {=INDEX(Engine!$H19:$U19,1,P$4)/INDEX(Engine!$H19:$U19,1,P$4+1)-1} -> 0.0032407378 | Q14: {=INDEX(Engine!$H19:$U19,1,Q$4)/INDEX(Engine!$H19:$U19,1,Q$4+1)-1} -> 0.0029607527 | R14: {=INDEX(Engine!$H19:$U19,1,R$4)/INDEX(Engine!$H19:$U19,1,R$4+1)-1} -> 0.0036736906 | S14: {=INDEX(Engine!$H19:$U19,1,S$4)/INDEX(Engine!$H19:$U19,1,S$4+1)-1} -> 0.0013479779 | T14: {=INDEX(Engine!$H19:$U19,1,T$4)/INDEX(Engine!$H19:$U19,1,T$4+1)-1} -> 0.0028706232 | U14: {=INDEX(Engine!$H19:$U19,1,U$4)/INDEX(Engine!$H19:$U19,1,U$4+1)-1} -> 0 | ... Z14: {=INDEX(Engine!$H19:$U19,1,Z$4)/INDEX(Engine!$H19:$U19,1,Z$4+1)-1} -> 0.0031466528
A15: =Engine!A20 -> Food at Home | B15: =Engine!B20 -> FOOD | C15: =Engine!V20 -> 8.2256925 | D15: =Engine!W20 -> 0.0006331226 | E15: =Engine!X20 -> 0.0068171399 | F15: =Engine!Z20 -> 0.027345851 | G15: =Engine!AA20 -> 0.029517724 | H15: =Engine!AB20 -> 0.0076239829 | I15: =Engine!AC20 -> 0.023413939 | J15: =Engine!AD20 -> 0.037397217 | K15: =Engine!AE20 -> -0.015789956 | L15: =Engine!AF20 -> -0.013983278 | M15: =Engine!AG20 -> ▼▼ DECEL | N15: {=INDEX(Engine!$H20:$U20,1,N$4)/INDEX(Engine!$H20:$U20,1,N$4+1)-1} -> 0.0006331226 | O15: {=INDEX(Engine!$H20:$U20,1,O$4)/INDEX(Engine!$H20:$U20,1,O$4+1)-1} -> 0.0068171399 | P15: {=INDEX(Engine!$H20:$U20,1,P$4)/INDEX(Engine!$H20:$U20,1,P$4+1)-1} -> -0.0016395755 | Q15: {=INDEX(Engine!$H20:$U20,1,Q$4)/INDEX(Engine!$H20:$U20,1,Q$4+1)-1} -> 0.0043956182 | R15: {=INDEX(Engine!$H20:$U20,1,R$4)/INDEX(Engine!$H20:$U20,1,R$4+1)-1} -> 0.0019149352 | S15: {=INDEX(Engine!$H20:$U20,1,S$4)/INDEX(Engine!$H20:$U20,1,S$4+1)-1} -> 0.0062920635 | T15: {=INDEX(Engine!$H20:$U20,1,T$4)/INDEX(Engine!$H20:$U20,1,T$4+1)-1} -> -0.001711352 | U15: {=INDEX(Engine!$H20:$U20,1,U$4)/INDEX(Engine!$H20:$U20,1,U$4+1)-1} -> 0 | ... Z15: {=INDEX(Engine!$H20:$U20,1,Z$4)/INDEX(Engine!$H20:$U20,1,Z$4+1)-1} -> 0.002748523
A16: =Engine!A21 -> Food Away from Home | B16: =Engine!B21 -> FOOD | C16: =Engine!V21 -> 5.3102324 | D16: =Engine!W21 -> 0.0030034608 | E16: =Engine!X21 -> 0.0022768253 | F16: =Engine!Z21 -> 0.03541188 | G16: =Engine!AA21 -> 0.035541089 | H16: =Engine!AB21 -> 0.036642902 | I16: =Engine!AC21 -> 0.031218845 | J16: =Engine!AD21 -> 0.039251559 | K16: =Engine!AE21 -> 0.0054240579 | L16: =Engine!AF21 -> -0.0080327141 | M16: =Engine!AG21 -> ▲ TURN UP | N16: {=INDEX(Engine!$H21:$U21,1,N$4)/INDEX(Engine!$H21:$U21,1,N$4+1)-1} -> 0.0030034608 | O16: {=INDEX(Engine!$H21:$U21,1,O$4)/INDEX(Engine!$H21:$U21,1,O$4+1)-1} -> 0.0022768253 | P16: {=INDEX(Engine!$H21:$U21,1,P$4)/INDEX(Engine!$H21:$U21,1,P$4+1)-1} -> 0.0024150766 | Q16: {=INDEX(Engine!$H21:$U21,1,Q$4)/INDEX(Engine!$H21:$U21,1,Q$4+1)-1} -> 0.0031628469 | R16: {=INDEX(Engine!$H21:$U21,1,R$4)/INDEX(Engine!$H21:$U21,1,R$4+1)-1} -> 0.0014927325 | S16: {=INDEX(Engine!$H21:$U21,1,S$4)/INDEX(Engine!$H21:$U21,1,S$4+1)-1} -> 0.0069395303 | T16: {=INDEX(Engine!$H21:$U21,1,T$4)/INDEX(Engine!$H21:$U21,1,T$4+1)-1} -> 0.0045427305 | U16: {=INDEX(Engine!$H21:$U21,1,U$4)/INDEX(Engine!$H21:$U21,1,U$4+1)-1} -> 0 | ... Z16: {=INDEX(Engine!$H21:$U21,1,Z$4)/INDEX(Engine!$H21:$U21,1,Z$4+1)-1} -> 0.0031286263
A17: =Engine!A22 -> Alcoholic Beverages | B17: =Engine!B22 -> CORE GOODS | C17: =Engine!V22 -> 0.82727496 | D17: =Engine!W22 -> 0.00056894745 | E17: =Engine!X22 -> 0.0027926251 | F17: =Engine!Z22 -> 0.021217205 | G17: =Engine!AA22 -> 0.019245117 | H17: =Engine!AB22 -> 0.0068487742 | I17: =Engine!AC22 -> 0.023975769 | J17: =Engine!AD22 -> 0.016263508 | K17: =Engine!AE22 -> -0.017126995 | L17: =Engine!AF22 -> 0.0077122611 | M17: =Engine!AG22 -> ▼ TURN DN | N17: {=INDEX(Engine!$H22:$U22,1,N$4)/INDEX(Engine!$H22:$U22,1,N$4+1)-1} -> 0.00056894745 | O17: {=INDEX(Engine!$H22:$U22,1,O$4)/INDEX(Engine!$H22:$U22,1,O$4+1)-1} -> 0.0027926251 | P17: {=INDEX(Engine!$H22:$U22,1,P$4)/INDEX(Engine!$H22:$U22,1,P$4+1)-1} -> 0.0025689915 | Q17: {=INDEX(Engine!$H22:$U22,1,Q$4)/INDEX(Engine!$H22:$U22,1,Q$4+1)-1} -> 0.0010950262 | R17: {=INDEX(Engine!$H22:$U22,1,R$4)/INDEX(Engine!$H22:$U22,1,R$4+1)-1} -> 0.0018048543 | S17: {=INDEX(Engine!$H22:$U22,1,S$4)/INDEX(Engine!$H22:$U22,1,S$4+1)-1} -> -0.00075424894 | T17: {=INDEX(Engine!$H22:$U22,1,T$4)/INDEX(Engine!$H22:$U22,1,T$4+1)-1} -> 0.0026990962 | U17: {=INDEX(Engine!$H22:$U22,1,U$4)/INDEX(Engine!$H22:$U22,1,U$4+1)-1} -> 0 | ... Z17: {=INDEX(Engine!$H22:$U22,1,Z$4)/INDEX(Engine!$H22:$U22,1,Z$4+1)-1} -> -0.0013632664
... A60: =Engine!A65 -> Misc Personal Services | B60: =Engine!B65 -> CORE SVCS | C60: =Engine!V65 -> 0.94741989 | D60: =Engine!W65 -> 0.02067842 | E60: =Engine!X65 -> 0.025607971 | F60: =Engine!Z65 -> 0.065204033 | G60: =Engine!AA65 -> 0.04700111 | H60: =Engine!AB65 -> 0.27840127 | I60: =Engine!AC65 -> 0.14193158 | J60: =Engine!AD65 -> 0.089866461 | K60: =Engine!AE65 -> 0.13646968 | L60: =Engine!AF65 -> 0.052065123 | M60: =Engine!AG65 -> ▲▲ ACCEL | N60: {=INDEX(Engine!$H65:$U65,1,N$4)/INDEX(Engine!$H65:$U65,1,N$4+1)-1} -> 0.02067842 | O60: {=INDEX(Engine!$H65:$U65,1,O$4)/INDEX(Engine!$H65:$U65,1,O$4+1)-1} -> 0.025607971 | P60: {=INDEX(Engine!$H65:$U65,1,P$4)/INDEX(Engine!$H65:$U65,1,P$4+1)-1} -> -0.012494095 | Q60: {=INDEX(Engine!$H65:$U65,1,Q$4)/INDEX(Engine!$H65:$U65,1,Q$4+1)-1} -> -0.004953548 | R60: {=INDEX(Engine!$H65:$U65,1,R$4)/INDEX(Engine!$H65:$U65,1,R$4+1)-1} -> 0.023336494 | S60: {=INDEX(Engine!$H65:$U65,1,S$4)/INDEX(Engine!$H65:$U65,1,S$4+1)-1} -> -0.0082212358 | T60: {=INDEX(Engine!$H65:$U65,1,T$4)/INDEX(Engine!$H65:$U65,1,T$4+1)-1} -> 0.01059225 | U60: {=INDEX(Engine!$H65:$U65,1,U$4)/INDEX(Engine!$H65:$U65,1,U$4+1)-1} -> 0 | ... Z60: {=INDEX(Engine!$H65:$U65,1,Z$4)/INDEX(Engine!$H65:$U65,1,Z$4+1)-1} -> 0.0032363804
A63: TOP 10 ACCELERATORS — ranked by Δ 1m vs 3m SAAR (non-overlapping components) | F63: TOP 10 DECELERATORS — ranked by Δ 1m vs 3m SAAR (non-overlapping components)
A64: Component | B64: 1m SAAR | C64: 3m SAAR | D64: Δ 1m-3m | F64: Component | G64: 1m SAAR | H64: 3m SAAR | I64: Δ 1m-3m
A65: {=_xlfn.TAKE(_xlfn.SORTBY(_xlfn._xlws.FILTER(_xlfn.HSTACK(Engine!$A$11:$A$65,Engine!$AB$11:$AB$65,Engine!$AC$11:$AC$65,Engine!$AE$11:$AE$65),Engine!$E$11:$E$65="Y"),_xlfn._xlws.FILTER(Engine!$AE$11:$AE$65,Engine!$E$11:$E$65="Y"),-1),10)} -> Communication | B65: 0.17049302 | C65: 0.050945337 | D65: 0.11954768 | F65: {=_xlfn.TAKE(_xlfn.SORTBY(_xlfn._xlws.FILTER(_xlfn.HSTACK(Engine!$A$11:$A$65,Engine!$AB$11:$AB$65,Engine!$AC$11:$AC$65,Engine!$AE$11:$AE$65),Engine!$E$11:$E$65="Y"),_xlfn._xlws.FILTER(Engine!$AE$11:$AE$65,Engine!$E$11:$E$65="Y"),1),10)} -> Motor Fuel | G65: 1.2125524 | H65: 2.5373237 | I65: -1.3247714
A66: Personal Care | B66: 0.12421365 | C66: 0.050478642 | D66: 0.073735007 | F66: Fuel Oil & Other Fuels | G66: 0.48434562 | H66: 1.6913584 | I66: -1.2070128
A67: Tobacco & Smoking Products | B67: 0.12780668 | C67: 0.063604542 | D67: 0.064202134 | F67: Car & Truck Rental | G67: -0.40344227 | H67: -0.23965128 | I67: -0.16379099
A68: Medical Care Services | B68: 0.065286115 | C68: 0.021506395 | D68: 0.04377972 | F68: MV Insurance | G68: -0.18481379 | H68: -0.06196998 | I68: -0.12284381
A69: Used Cars & Trucks | B69: 0.012280662 | C69: -0.012872838 | D69: 0.0251535 | F69: Public Transportation | G69: 0.040988797 | H69: 0.14809334 | I69: -0.10710454
A70: MV Maintenance & Repair | B70: 0.099505199 | C70: 0.076650214 | D70: 0.022854985 | F70: Household Furnishings & Ops | G70: -0.065072774 | H70: 0.014856503 | I70: -0.079929277
A71: Recreation | B71: 0.035038695 | C71: 0.013349801 | D71: 0.021688894 | F71: Lodging Away from Home | G71: 0.051340734 | H71: 0.13077298 | I71: -0.079432247
A72: Leased Cars & Trucks | B72: -0.00084839375 | C72: -0.0080579838 | D72: 0.00720959 | F72: Electricity | G72: 0.077942171 | H72: 0.15282887 | I72: -0.0748867
A73: Food Away from Home | B73: 0.036642902 | C73: 0.031218845 | D73: 0.0054240579 | F73: MV Parts & Equipment | G73: -0.085217783 | H73: -0.01067339 | I73: -0.074544393
A74: Rent of Primary Residence | B74: 0.044306235 | C74: 0.04476394 | D74: -0.00045770501 | F74: Apparel | G74: 0.035601329 | H74: 0.081220663 | I74: -0.045619334

Sheet Breadth
A1: CPI BREADTH & CONTRIBUTIONS
A2: {="Latest print: "&TEXT(Engine!$B$5,"mmmm yyyy")&" | Contributions use price-updated BLS relative-importance weights | Breadth measured over "&SUMPRODUCT((Engine!$E$11:$E$65="Y")*1)&" non-overlapping components"} -> Latest print: May 2026 | Contributions use price-updated BLS relative-importance weights | Breadth measured over 28 non-overlapping components
A4: TOP 5 CONTRIBUTORS — HEADLINE M/M (pp) | G4: TOP 5 DRAGS — HEADLINE M/M (pp)
A5: Component | B5: Wt % | C5: M/M | D5: Contrib | G5: Component | H5: Wt % | I5: M/M | J5: Contrib
A6: {=_xlfn.TAKE(_xlfn.SORTBY(_xlfn._xlws.FILTER(_xlfn.HSTACK(Engine!$A$11:$A$65,Engine!$V$11:$V$65,Engine!$W$11:$W$65,Engine!$AH$11:$AH$65),Engine!$E$11:$E$65="Y"),_xlfn._xlws.FILTER(Engine!$AH$11:$AH$65,Engine!$E$11:$E$65="Y"),-1),5)} -> Motor Fuel | B6: 3.8947123 | C6: 0.068417838 | D6: 0.26646779 | G6: {=_xlfn.TAKE(_xlfn.SORTBY(_xlfn._xlws.FILTER(_xlfn.HSTACK(Engine!$A$11:$A$65,Engine!$V$11:$V$65,Engine!$W$11:$W$65,Engine!$AH$11:$AH$65),Engine!$E$11:$E$65="Y"),_xlfn._xlws.FILTER(Engine!$AH$11:$AH$65,Engine!$E$11:$E$65="Y"),1),5)} -> MV Insurance | H6: 2.6255895 | I6: -0.016884065 | J6: -0.044330625
A7: Owners' Equivalent Rent | B7: 25.981247 | C7: 0.002967825 | D7: 0.077107795 | G7: Household Furnishings & Ops | H7: 4.223049 | I7: -0.0055915244 | J7: -0.023613282
A8: Communication | B8: 3.2070096 | C8: 0.013205182 | D8: 0.042349144 | G8: Medical Care Commodities | H8: 1.4226413 | I8: -0.0071164716 | J8: -0.010124186
A9: Medical Care Services | B9: 6.8701473 | C9: 0.005284197 | D9: 0.036303212 | G9: New Vehicles | H9: 3.7419316 | I9: -0.0025784991 | J9: -0.0096485673
A10: Rent of Primary Residence | B10: 7.7671333 | C10: 0.003619265 | D10: 0.028111314 | G10: Car & Truck Rental | H10: 0.13574905 | I10: -0.042134849 | J10: -0.0057197659
A12: TOP 5 CONTRIBUTORS — CORE M/M (pp) | G12: TOP 5 DRAGS — CORE M/M (pp)
A13: Component | B13: Wt % | C13: M/M | D13: Contrib | G13: Component | H13: Wt % | I13: M/M | J13: Contrib
A14: {=_xlfn.TAKE(_xlfn.SORTBY(_xlfn._xlws.FILTER(_xlfn.HSTACK(Engine!$A$11:$A$65,Engine!$V$11:$V$65,Engine!$W$11:$W$65,Engine!$AI$11:$AI$65),(Engine!$E$11:$E$65="Y")*(Engine!$C$11:$C$65="Y")),_xlfn._xlws.FILTER(Engine!$AI$11:$AI$65,(Engine!$E$11:$E$65="Y")*(Engine!$C$11:$C$65="Y")),-1),5)} -> Owners' Equivalent Rent | B14: 25.981247 | C14: 0.002967825 | D14: 0.097568037 | G14: {=_xlfn.TAKE(_xlfn.SORTBY(_xlfn._xlws.FILTER(_xlfn.HSTACK(Engine!$A$11:$A$65,Engine!$V$11:$V$65,Engine!$W$11:$W$65,Engine!$AI$11:$AI$65),(Engine!$E$11:$E$65="Y")*(Engine!$C$11:$C$65="Y")),_xlfn._xlws.FILTER(Engine!$AI$11:$AI$65,(Engine!$E$11:$E$65="Y")*(Engine!$C$11:$C$65="Y")),1),5)} -> MV Insurance | H14: 2.6255895 | I14: -0.016884065 | J14: -0.056093577
A15: Communication | B15: 3.2070096 | C15: 0.013205182 | D15: 0.053586319 | G15: Household Furnishings & Ops | H15: 4.223049 | I15: -0.0055915244 | J15: -0.029878971
A16: Medical Care Services | B16: 6.8701473 | C16: 0.005284197 | D16: 0.045936123 | G16: Medical Care Commodities | H16: 1.4226413 | I16: -0.0071164716 | J16: -0.012810598
A17: Rent of Primary Residence | B17: 7.7671333 | C17: 0.003619265 | D17: 0.035570537 | G17: New Vehicles | H17: 3.7419316 | I17: -0.0025784991 | J17: -0.012208776
A18: Personal Care | B18: 2.4522759 | C18: 0.009804739 | D18: 0.030423884 | G18: Car & Truck Rental | H18: 0.13574905 | I18: -0.042134849 | J18: -0.0072374826
A20: BREADTH OF THE PRINT | D20: Latest | E20: Prior mo
A21: % of components rising m/m | D21: {=SUMPRODUCT((Engine!$E$11:$E$65="Y")*(Engine!$W$11:$W$65>0))/SUMPRODUCT((Engine!$E$11:$E$65="Y")*1)} -> 0.71428571 | E21: {=SUMPRODUCT((Engine!$E$11:$E$65="Y")*(Engine!$X$11:$X$65>0))/SUMPRODUCT((Engine!$E$11:$E$65="Y")*1)} -> 0.67857143
A22: % of components accelerating m/m | D22: {=SUMPRODUCT((Engine!$E$11:$E$65="Y")*(Engine!$W$11:$W$65>Engine!$X$11:$X$65))/SUMPRODUCT((Engine!$E$11:$E$65="Y")*1)} -> 0.32142857 | E22: {=SUMPRODUCT((Engine!$E$11:$E$65="Y")*(Engine!$X$11:$X$65>Engine!$Y$11:$Y$65))/SUMPRODUCT((Engine!$E$11:$E$65="Y")*1)} -> 0.57142857
A23: Weighted share accelerating (by RI weight) | D23: {=SUMPRODUCT(Engine!$V$11:$V$65*(Engine!$W$11:$W$65>Engine!$X$11:$X$65)*(Engine!$E$11:$E$65="Y"))/SUMPRODUCT(Engine!$V$11:$V$65*(Engine!$E$11:$E$65="Y"))} -> 0.31215184 | E23: {=SUMPRODUCT(Engine!$V$11:$V$65*(Engine!$X$11:$X$65>Engine!$Y$11:$Y$65)*(Engine!$E$11:$E$65="Y"))/SUMPRODUCT(Engine!$V$11:$V$65*(Engine!$E$11:$E$65="Y"))} -> 0.68871876
A24: % running above 2% (3m SAAR) | D24: {=SUMPRODUCT((Engine!$E$11:$E$65="Y")*((Engine!$H$11:$H$65/Engine!$K$11:$K$65)^4-1>0.02))/SUMPRODUCT((Engine!$E$11:$E$65="Y")*1)} -> 0.64285714 | E24: {=SUMPRODUCT((Engine!$E$11:$E$65="Y")*((Engine!$I$11:$I$65/Engine!$L$11:$L$65)^4-1>0.02))/SUMPRODUCT((Engine!$E$11:$E$65="Y")*1)} -> 0.67857143
A25: % running above 4% (3m SAAR) | D25: {=SUMPRODUCT((Engine!$E$11:$E$65="Y")*((Engine!$H$11:$H$65/Engine!$K$11:$K$65)^4-1>0.04))/SUMPRODUCT((Engine!$E$11:$E$65="Y")*1)} -> 0.46428571 | E25: {=SUMPRODUCT((Engine!$E$11:$E$65="Y")*((Engine!$I$11:$I$65/Engine!$L$11:$L$65)^4-1>0.04))/SUMPRODUCT((Engine!$E$11:$E$65="Y")*1)} -> 0.39285714
A26: Median component m/m | D26: {=MEDIAN(_xlfn._xlws.FILTER(Engine!$W$11:$W$65,Engine!$E$11:$E$65="Y"))} -> 0.0028967321 | E26: {=MEDIAN(_xlfn._xlws.FILTER(Engine!$X$11:$X$65,Engine!$E$11:$E$65="Y"))} -> 0.0024447096
A29: BREADTH TREND — trailing 12 months
B30: =Momentum!N$5 -> May-26 | C30: =Momentum!O$5 -> Apr-26 | D30: =Momentum!P$5 -> Mar-26 | E30: =Momentum!Q$5 -> Feb-26 | F30: =Momentum!R$5 -> Jan-26 | G30: =Momentum!S$5 -> Dec-25 | H30: =Momentum!T$5 -> Nov-25 | I30: =Momentum!U$5 -> Oct-25 | ... M30: =Momentum!Y$5 -> Jun-25
A31: % rising m/m | B31: {=SUMPRODUCT((Engine!$E$11:$E$65="Y")*(Momentum!N$6:N$60>0))/SUMPRODUCT((Engine!$E$11:$E$65="Y")*1)} -> 0.71428571 | C31: {=SUMPRODUCT((Engine!$E$11:$E$65="Y")*(Momentum!O$6:O$60>0))/SUMPRODUCT((Engine!$E$11:$E$65="Y")*1)} -> 0.67857143 | D31: {=SUMPRODUCT((Engine!$E$11:$E$65="Y")*(Momentum!P$6:P$60>0))/SUMPRODUCT((Engine!$E$11:$E$65="Y")*1)} -> 0.71428571 | E31: {=SUMPRODUCT((Engine!$E$11:$E$65="Y")*(Momentum!Q$6:Q$60>0))/SUMPRODUCT((Engine!$E$11:$E$65="Y")*1)} -> 0.78571429 | F31: {=SUMPRODUCT((Engine!$E$11:$E$65="Y")*(Momentum!R$6:R$60>0))/SUMPRODUCT((Engine!$E$11:$E$65="Y")*1)} -> 0.67857143 | G31: {=SUMPRODUCT((Engine!$E$11:$E$65="Y")*(Momentum!S$6:S$60>0))/SUMPRODUCT((Engine!$E$11:$E$65="Y")*1)} -> 0.64285714 | H31: {=SUMPRODUCT((Engine!$E$11:$E$65="Y")*(Momentum!T$6:T$60>0))/SUMPRODUCT((Engine!$E$11:$E$65="Y")*1)} -> 0.64285714 | I31: {=SUMPRODUCT((Engine!$E$11:$E$65="Y")*(Momentum!U$6:U$60>0))/SUMPRODUCT((Engine!$E$11:$E$65="Y")*1)} -> 0.071428571 | ... M31: {=SUMPRODUCT((Engine!$E$11:$E$65="Y")*(Momentum!Y$6:Y$60>0))/SUMPRODUCT((Engine!$E$11:$E$65="Y")*1)} -> 0.85714286
A32: % accelerating m/m | B32: {=SUMPRODUCT((Engine!$E$11:$E$65="Y")*(Momentum!N$6:N$60>Momentum!O$6:O$60))/SUMPRODUCT((Engine!$E$11:$E$65="Y")*1)} -> 0.32142857 | C32: {=SUMPRODUCT((Engine!$E$11:$E$65="Y")*(Momentum!O$6:O$60>Momentum!P$6:P$60))/SUMPRODUCT((Engine!$E$11:$E$65="Y")*1)} -> 0.57142857 | D32: {=SUMPRODUCT((Engine!$E$11:$E$65="Y")*(Momentum!P$6:P$60>Momentum!Q$6:Q$60))/SUMPRODUCT((Engine!$E$11:$E$65="Y")*1)} -> 0.46428571 | E32: {=SUMPRODUCT((Engine!$E$11:$E$65="Y")*(Momentum!Q$6:Q$60>Momentum!R$6:R$60))/SUMPRODUCT((Engine!$E$11:$E$65="Y")*1)} -> 0.57142857 | F32: {=SUMPRODUCT((Engine!$E$11:$E$65="Y")*(Momentum!R$6:R$60>Momentum!S$6:S$60))/SUMPRODUCT((Engine!$E$11:$E$65="Y")*1)} -> 0.42857143 | G32: {=SUMPRODUCT((Engine!$E$11:$E$65="Y")*(Momentum!S$6:S$60>Momentum!T$6:T$60))/SUMPRODUCT((Engine!$E$11:$E$65="Y")*1)} -> 0.42857143 | H32: {=SUMPRODUCT((Engine!$E$11:$E$65="Y")*(Momentum!T$6:T$60>Momentum!U$6:U$60))/SUMPRODUCT((Engine!$E$11:$E$65="Y")*1)} -> 0.60714286 | I32: {=SUMPRODUCT((Engine!$E$11:$E$65="Y")*(Momentum!U$6:U$60>Momentum!V$6:V$60))/SUMPRODUCT((Engine!$E$11:$E$65="Y")*1)} -> 0.32142857 | ... M32: {=SUMPRODUCT((Engine!$E$11:$E$65="Y")*(Momentum!Y$6:Y$60>Momentum!Z$6:Z$60))/SUMPRODUCT((Engine!$E$11:$E$65="Y")*1)} -> 0.53571429

Sheet PCE Bridge
A1: CPI → CORE PCE PASS-THROUGH BRIDGE
A2: ="CPI print: "&TEXT(Engine!$B$5,"mmmm yyyy")&" | PCE weights = BEA nominal shares of CORE PCE (Macrobond cols KT:PB) | Source-index mapping per BEA Table 2.4.4U-D (see 'PCE Source Data' tab)" -> CPI print: May 2026 | PCE weights = BEA nominal shares of CORE PCE (Macrobond cols KT:PB) | Source-index mapping per BEA Table 2.4.4U-D (see 'PCE Source Data' tab)
A4: Last PCE nominal data row | B4: =COUNT(Macrobond!$KU:$KU)+4 -> 955
A5: PCE weight month (nominal vintage) | B5: {=INDEX(Macrobond!$A:$A,$B$4)} -> 46082
A6: Core PCE nominal denominator | B6: {=INDEX(Macrobond!$KU:$KU,$B$4)-INDEX(Macrobond!$LT:$LT,$B$4)-INDEX(Macrobond!$MD:$MD,$B$4)-INDEX(Macrobond!$MY:$MY,$B$4)} -> 6.4275123e+12 | C6: USD mm (total less food off-premises less energy goods & utilities)
A8: PCE Component (core PCE) | B8: BEA Col# | C8: Wt % of Core PCE | D8: Source index (per 2.4.4U-D) | E8: CPI Proxy (Engine) | F8: Eng Row | G8: CPI M/M | H8: CPI 3m SAAR | I8: Contrib to Core PCE M/M (pp)
A9: New motor vehicles | B9: 311 | C9: {=INDEX(Macrobond!$A:$PB,$B$4,$B9)/$B$6*100} -> 1.976939 | D9: CPI: New vehicles | E9: New Vehicles | F9: =MATCH($E9,Engine!$A$11:$A$65,0)+10 -> 35 | G9: {=INDEX(Engine!$W:$W,$F9)} -> -0.0025784991 | H9: {=INDEX(Engine!$AC:$AC,$F9)} -> -0.012568754 | I9: =$C9*$G9 -> -0.0050975355
A10: Net purchases of used motor vehicles | B10: 312 | C10: {=INDEX(Macrobond!$A:$PB,$B$4,$B10)/$B$6*100} -> 1.2188178 | D10: CPI: Used cars and trucks | E10: Used Cars & Trucks | F10: =MATCH($E10,Engine!$A$11:$A$65,0)+10 -> 36 | G10: {=INDEX(Engine!$W:$W,$F10)} -> 0.001017673 | H10: {=INDEX(Engine!$AC:$AC,$F10)} -> -0.012872838 | I10: =$C10*$G10 -> 0.001240358
A11: Motor vehicle parts & accessories | B11: 313 | C11: {=INDEX(Macrobond!$A:$PB,$B$4,$B11)/$B$6*100} -> 0.696231 | D11: CPI: MV parts & equipment | E11: MV Parts & Equipment | F11: =MATCH($E11,Engine!$A$11:$A$65,0)+10 -> 38 | G11: {=INDEX(Engine!$W:$W,$F11)} -> -0.0073949598 | H11: {=INDEX(Engine!$AC:$AC,$F11)} -> -0.01067339 | I11: =$C11*$G11 -> -0.0051486002
A12: Furnishings & durable household equip. | B12: 314 | C12: {=INDEX(Macrobond!$A:$PB,$B$4,$B12)/$B$6*100} -> 2.7065889 | D12: CPI: HH furnishings indexes | E12: Household Furnishings & Ops | F12: =MATCH($E12,Engine!$A$11:$A$65,0)+10 -> 41 | G12: {=INDEX(Engine!$W:$W,$F12)} -> -0.0055915244 | H12: {=INDEX(Engine!$AC:$AC,$F12)} -> 0.014856503 | I12: =$C12*$G12 -> -0.015133958
A13: Recreational goods & vehicles | B13: 319 | C13: {=INDEX(Macrobond!$A:$PB,$B$4,$B13)/$B$6*100} -> 3.8124651 | D13: CPI: video/audio/IT & rec goods (partial) | E13: Video & Audio | F13: =MATCH($E13,Engine!$A$11:$A$65,0)+10 -> 45 | G13: {=INDEX(Engine!$W:$W,$F13)} -> -0.0021687906 | H13: {=INDEX(Engine!$AC:$AC,$F13)} -> 0.019417953 | I13: =$C13*$G13 -> -0.0082684386
A14: Clothing & footwear | B14: 336 | C14: {=INDEX(Macrobond!$A:$PB,$B$4,$B14)/$B$6*100} -> 3.0337968 | D14: CPI: apparel indexes | E14: Apparel | F14: =MATCH($E14,Engine!$A$11:$A$65,0)+10 -> 34 | G14: {=INDEX(Engine!$W:$W,$F14)} -> 0.002919441 | H14: {=INDEX(Engine!$AC:$AC,$F14)} -> 0.081220663 | I14: =$C14*$G14 -> 0.0088569909
A15: Pharmaceutical & other medical products | B15: 346 | C15: {=INDEX(Macrobond!$A:$PB,$B$4,$B15)/$B$6*100} -> 3.8322758 | D15: CPI: medical care commodities | E15: Medical Care Commodities | F15: =MATCH($E15,Engine!$A$11:$A$65,0)+10 -> 40 | G15: {=INDEX(Engine!$W:$W,$F15)} -> -0.0071164716 | H15: {=INDEX(Engine!$AC:$AC,$F15)} -> -0.078736518 | I15: =$C15*$G15 -> -0.027272282
A16: Recreational items | B16: 347 | C16: {=INDEX(Macrobond!$A:$PB,$B$4,$B16)/$B$6*100} -> 1.8232819 | D16: CPI: recreation commodities (partial) | E16: Recreation | F16: =MATCH($E16,Engine!$A$11:$A$65,0)+10 -> 57 | G16: {=INDEX(Engine!$W:$W,$F16)} -> 0.0028740231 | H16: {=INDEX(Engine!$AC:$AC,$F16)} -> 0.013349801 | I16: =$C16*$G16 -> 0.0052401543
A17: Household supplies | B17: 348 | C17: {=INDEX(Macrobond!$A:$PB,$B$4,$B17)/$B$6*100} -> 1.0580091 | D17: CPI: housekeeping supplies | E17: Housekeeping Supplies | F17: =MATCH($E17,Engine!$A$11:$A$65,0)+10 -> 44 | G17: {=INDEX(Engine!$W:$W,$F17)} -> 0.0052710375 | H17: {=INDEX(Engine!$AC:$AC,$F17)} -> 0.013629784 | I17: =$C17*$G17 -> 0.0055768057
A18: Personal care products | B18: 349 | C18: {=INDEX(Macrobond!$A:$PB,$B$4,$B18)/$B$6*100} -> 1.1423652 | D18: CPI: personal care products | E18: Personal Care | F18: =MATCH($E18,Engine!$A$11:$A$65,0)+10 -> 64 | G18: {=INDEX(Engine!$W:$W,$F18)} -> 0.009804739 | H18: {=INDEX(Engine!$AC:$AC,$F18)} -> 0.050478642 | I18: =$C18*$G18 -> 0.011200593
A19: Tobacco | B19: 350 | C19: {=INDEX(Macrobond!$A:$PB,$B$4,$B19)/$B$6*100} -> 0.58397399 | D19: CPI: tobacco & smoking products | E19: Tobacco & Smoking Products | F19: =MATCH($E19,Engine!$A$11:$A$65,0)+10 -> 46 | G19: {=INDEX(Engine!$W:$W,$F19)} -> 0.010073293 | H19: {=INDEX(Engine!$AC:$AC,$F19)} -> 0.063604542 | I19: =$C19*$G19 -> 0.0058825413
A20: Rental of tenant-occupied housing | B20: 357 | C20: {=INDEX(Macrobond!$A:$PB,$B$4,$B20)/$B$6*100} -> 4.1102372 | D20: CPI: rent of primary residence | E20: Rent of Primary Residence | F20: =MATCH($E20,Engine!$A$11:$A$65,0)+10 -> 24 | G20: {=INDEX(Engine!$W:$W,$F20)} -> 0.003619265 | H20: {=INDEX(Engine!$AC:$AC,$F20)} -> 0.04476394 | I20: =$C20*$G20 -> 0.014876037
... A32: Personal care & clothing services | B32: 306 | C32: {=INDEX(Macrobond!$A:$PB,$B$4,$B32)/$B$6*100} -> 1.3425671 | D32: CPI: personal care & laundry svcs | E32: Personal Care | F32: =MATCH($E32,Engine!$A$11:$A$65,0)+10 -> 64 | G32: {=INDEX(Engine!$W:$W,$F32)} -> 0.009804739 | H32: {=INDEX(Engine!$AC:$AC,$F32)} -> 0.050478642 | I32: =$C32*$G32 -> 0.01316352
A33: CPI-MAPPED SUBTOTAL | C33: =SUM(C9:C32) -> 60.926962 | I33: =SUM(I9:I32) -> 0.12277879
A35: NON-CPI-SOURCED CORE PCE COMPONENTS — m/m assumptions in BLUE, update after PPI print
A36: Health care services | B36: 366 | C36: {=INDEX(Macrobond!$A:$PB,$B$4,$B36)/$B$6*100} -> 19.095817 | D36: PPI: hospitals/physicians; Medicare-Medicaid rates | G36: 0.0025 | H36: =(1+$G36)^12-1 -> 0.030415957 | I36: =$C36*$G36 -> 0.047739543
A37: Financial services & insurance | B37: 392 | C37: {=INDEX(Macrobond!$A:$PB,$B$4,$B37)/$B$6*100} -> 9.3176536 | D37: Imputed (FISIM)/PPI; portfolio mgmt tracks equities | G37: 0.003 | H37: =(1+$G37)^12-1 -> 0.03659998 | I37: =$C37*$G37 -> 0.027952961
A38: Other durable goods | B38: 325 | C38: {=INDEX(Macrobond!$A:$PB,$B$4,$B38)/$B$6*100} -> 1.6343752 | D38: CPI jewelry/therapeutic/books mix (unmapped) | G38: 0.0015 | H38: =(1+$G38)^12-1 -> 0.018149245 | I38: =$C38*$G38 -> 0.0024515628
A39: Professional & other services | B39: 410 | C39: {=INDEX(Macrobond!$A:$PB,$B$4,$B39)/$B$6*100} -> 1.5986641 | D39: PPI legal/accounting (partial CPI) | G39: 0.002 | H39: =(1+$G39)^12-1 -> 0.024265768 | I39: =$C39*$G39 -> 0.0031973282
A40: Social services & religious activities | B40: 411 | C40: {=INDEX(Macrobond!$A:$PB,$B$4,$B40)/$B$6*100} -> 1.8788606 | D40: Input-cost based | G40: 0.002 | H40: =(1+$G40)^12-1 -> 0.024265768 | I40: =$C40*$G40 -> 0.0037577213
A41: Household maintenance | B41: 412 | C41: {=INDEX(Macrobond!$A:$PB,$B$4,$B41)/$B$6*100} -> 0.64412167 | D41: Input-cost / partial CPI | G41: 0.0015 | H41: =(1+$G41)^12-1 -> 0.018149245 | I41: =$C41*$G41 -> 0.00096618251
A42: Net foreign travel | B42: 413 | C42: {=INDEX(Macrobond!$A:$PB,$B$4,$B42)/$B$6*100} -> 0.3743802 | D42: Foreign CPIs / FX (negative weight) | G42: 0.002 | H42: =(1+$G42)^12-1 -> 0.024265768 | I42: =$C42*$G42 -> 0.00074876039
A43: Final consumption of NPISHs | B43: 416 | C43: {=INDEX(Macrobond!$A:$PB,$B$4,$B43)/$B$6*100} -> 3.3473396 | D43: Input-cost based | G43: 0.002 | H43: =(1+$G43)^12-1 -> 0.024265768 | I43: =$C43*$G43 -> 0.0066946792
A44: Residual — unmapped core components | C44: =100-$C$33-SUM(C36:C43) -> 1.1818258 | D44: Group housing, employee meals, misc unmapped | G44: 0.002 | H44: =(1+$G44)^12-1 -> 0.024265768 | I44: =$C44*$G44 -> 0.0023636516
A45: NON-CPI SUBTOTAL | C45: =SUM(C36:C44) -> 39.073038 | I45: =SUM(I36:I44) -> 0.09587239
A47: IMPLIED CORE PCE M/M — WEIGHTED TOTAL | C47: =C33+C45 -> 100 | I47: =I33+I45 -> 0.21865118
A49: BOTTOM LINE — CORE PCE READ-THROUGH
A50: Implied core PCE m/m (CPI pass-through + assumptions) | D50: =$I$47/100 -> 0.0021865118
A51: Annualized pace | D51: =(1+$I$47/100)^12-1 -> 0.026555987
A52: CPI-mapped basket only — m/m | D52: =$I$33/$C$33 -> 0.0020151799
A53: CPI-mapped basket — 3m SAAR trend | D53: =SUMPRODUCT($C$9:$C$32,$H$9:$H$32)/$C$33 -> 0.033375975
A54: Directional bias for upcoming core PCE print | D54: =IF($I$47/100>=0.0025,"HOT — clear upside risk vs 2% pace",IF($I$47/100>=0.0017,"WARM — modestly above 2% target pace",IF($I$47/100>=0.0008,"ON TARGET — consistent with ~2% annualized","COOL — downside risk / disinflationary"))) -> WARM — modestly above 2% target pace
A57: ="• CPI pass-through implies core PCE ≈ "&TEXT($I$47/100,"0.00%")&" m/m ("&TEXT((1+$I$47/100)^12-1,"0.0%")&" annualized) for "&TEXT(Engine!$B$5,"mmm-yy")&"; CPI-sourced components cover "&TEXT($C$33/100,"0%")&" of the core basket." -> • CPI pass-through implies core PCE ≈ 0.22% m/m (2.7% annualized) for May-26; CPI-sourced components cover 61% of the core basket. | K57: =MATCH(MAX($I$9:$I$32),$I$9:$I$32,0) -> 13
A58: {="• Biggest pass-through boost: "&INDEX($A$9:$A$32,$K$57)&" ("&TEXT(INDEX($G$9:$G$32,$K$57),"+0.00%;-0.00%")&" m/m → "&TEXT(INDEX($I$9:$I$32,$K$57),"+0.000;-0.000")&"pp); biggest drag: "&INDEX($A$9:$A$32,$K$58)&" ("&TEXT(INDEX($G$9:$G$32,$K$58),"+0.00%;-0.00%")&" → "&TEXT(INDEX($I$9:$I$32,$K$58),"+0.000;-0.000")&"pp)."} -> • Biggest pass-through boost: Imputed rental of owner-occupied housing (+0.30% m/m → +0.040pp); biggest drag: Other motor vehicle services (-4.21% → -0.027pp). | K58: =MATCH(MIN($I$9:$I$32),$I$9:$I$32,0) -> 16
A59: ="• Shelter wedge: rent+OER = "&TEXT(($C$20+$C$21)/100,"0.0%")&" of core PCE vs "&TEXT(Engine!$V$23/Engine!$V$12,"0.0%")&" of core CPI — a shelter surprise passes through ~"&TEXT((($C$20+$C$21)/100)/(Engine!$V$23/Engine!$V$12),"0.0")&"x into core PCE." -> • Shelter wedge: rent+OER = 17.4% of core PCE vs 44.7% of core CPI — a shelter surprise passes through ~0.4x into core PCE.
A60: ="• "&TEXT($C$45/100,"0%")&" of core PCE is NOT CPI-sourced (health care "&TEXT($C$36/100,"0.0%")&", financial svcs "&TEXT($C$37/100,"0.0%")&") — blue assumptions contribute "&TEXT($I$45/100,"0.00%")&" of the estimate. Firm these up after the PPI print." -> • 39% of core PCE is NOT CPI-sourced (health care 19.1%, financial svcs 9.3%) — blue assumptions contribute 0.10% of the estimate. Firm these up after the PPI print.
A61: • Method note: BEA aggregates with a Fisher formula and scope-adjusts CPI inputs; this linear share-weighted bridge is an approximation — treat as directional bias, not a point forecast.

Sheet PCE Source Data
A1: Table 2.4.4 U-D. Price Indexes for PCE: Source Data | D1: 46073
A4: Item | B4: PCE Component | C4: Series Code | D4: Price index source data* | E4: Seasonal Status
A5: 1 | B5: Personal consumption expenditures by type of product | C5: E1PCE1
A6: 2 | B6: Goods | C6: E1GDS1
A7: 3 | B7: Durable goods | C7: E1DUR1
A8: 4 | B8: Motor vehicles and parts | C8: E1MOT1
A9: 5 | B9: New motor vehicles | C9: E1NMV1
A10: 6 | B10: New autos | C10: E1NEA1
A11: 7 | B11: New domestic autos | C11: E1NDC1 | D11: CPI New cars | E11: SA
A12: 8 | B12: New foreign autos | C12: E1NFC1 | D12: CPI New cars | E12: SA
A13: 9 | B13: New light trucks | C13: E1NWT1 | D13: CPI New trucks | E13: SA
A14: 10 | B14: New domestic light trucks | C14: E1DTN1 | D14: CPI New trucks | E14: SA
A15: 11 | B15: New foreign light trucks | C15: E1FTN1 | D15: CPI New trucks | E15: SA
A16: 12 | B16: Net purchases of used motor vehicles | C16: E1NPV1
A17: 13 | B17: Used autos | C17: E1NPU1
A18: 14 | B18: Net transactions in used autos | C18: E1NET1 | D18: CPI Used cars and trucks | E18: SA
A19: 15 | B19: Used auto margin | C19: E1MAR1 | D19: CPI Used cars and trucks | E19: SA
A20: 16 | B20: Employee reimbursement | C20: E1REE1 | D20: CPI Car and truck rental | E20: SA
A21: 17 | B21: Used light trucks | C21: E1UTR1
A22: 18 | B22: Net transactions in used trucks | C22: E1UTN1 | D22: CPI Used cars and trucks | E22: SA
A23: 19 | B23: Used truck margin | C23: E1UTM1 | D23: CPI Used cars and trucks | E23: SA
A24: 20 | B24: Motor vehicles parts and accessories | C24: E1MVP1
A25: 21 | B25: Tires | C25: E1TAT1 | D25: CPI Tires | E25: NSA
A26: 22 | B26: Accessories and parts | C26: E1PAA1 | D26: CPI Vehicle parts and equipment other than tires | E26: NSA
A27: 23 | B27: Furnishings and durable household equipment | C27: E1FDH1
A28: 24 | B28: Furniture and furnishings | C28: E1FFF1
A29: 25 | B29: Furniture | C29: E1FNR1 | D29: CPI Furniture and bedding | E29: NSA
A30: 26 | B30: Clocks, lamps, lighting fixtures, and other household decorative items | C30: E1CLF1 | D30: CPI Clocks, lamps, and decorator items | E30: NSA
A31: 27 | B31: Carpets and other floor coverings | C31: E1FLR1 | D31: CPI Floor coverings | E31: NSA
A32: 28 | B32: Window coverings | C32: E1WCT1 | D32: CPI Window coverings | E32: NSA
A33: 29 | B33: Household appliances | C33: E1APP1
A34: 30 | B34: Major household appliances | C34: E1MHA1 | D34: CPI Major appliances | E34: SA
A35: 31 | B35: Small electric household appliances | C35: E1SEA1 | D35: CPI Other appliances | E35: SA
A36: 32 | B36: Glassware, tableware, and household utensils | C36: E1UTE1
A37: 33 | B37: Dishes and flatware | C37: E1CHN1 | D37: CPI Dishes and flatware | E37: NSA
A38: 34 | B38: Nonelectric cookware and tableware | C38: E1NEC1 | D38: CPI Nonelectric cookware and tableware | E38: SA
A39: 35 | B39: Tools and equipment for house and garden | C39: E1TOO1
A40: 36 | B40: Tools, hardware, and supplies | C40: E1HDW1 | D40: CPI Tools, hardware, and supplies | E40: SA
A41: 37 | B41: Outdoor equipment and supplies | C41: E1LWN1 | D41: CPI Outdoor equipment and supplies | E41: NSA
A42: 38 | B42: Recreational goods and vehicles | C42: E1REQ1
A43: 39 | B43: Video, audio, photographic, and information processing equipment and media | C43: E1VAP1
A44: 40 | B44: Video and audio equipment | C44: E1VAA1
A45: 41 | B45: Televisions | C45: E1TVS1 | D45: CPI Televisions | E45: SA
A46: 42 | B46: Other video equipment | C46: E1OVA1 | D46: CPI Other video equipment | E46: SA
A47: 43 | B47: Audio equipment | C47: E1AUD1 | D47: CPI Audio equipment | E47: NSA
A48: 44 | B48: Recording media | C48: E1REC1
A49: 45 | B49: Audio discs, tapes, vinyl, and permanent digital downloads | C49: E1RTD1 | D49: CPI Recorded music and music subscriptions | E49: NSA
A50: 46 | B50: Video discs, tapes, and permanent digital downloads | C50: E1OVE1 | D50: CPI Video discs and other media | E50: NSA
A51: 47 | B51: Photographic equipment | C51: E1CAM1 | D51: CPI Photographic equipment | E51: NSA
A52: 48 | B52: Information processing equipment | C52: E1IPE1
A53: 49 | B53: Personal computers/tablets and peripheral equipment | C53: E1CPP1 | D53: CPI Computers, peripherals, and smart home assistants | E53: NSA
A54: 50 | B54: Computer software and accessories | C54: E1CPS1 | D54: CPI Computer software and accessories | E54: NSA
A55: 51 | B55: Calculators, typewriters, and other information processing equipment | C55: E1OIP1 | D55: CPI Telephone hardware, calculators, and other consumer information items | E55: SA
A56: 52 | B56: Sporting equipment, supplies, guns, and ammunition | C56: E1SPG1 | D56: CPI Sports equipment | E56: NSA
A57: 53 | B57: Sports and recreational vehicles | C57: E1WHL1
A58: 54 | B58: Motorcycles | C58: E1MCY1 | D58: CPI New motorcycles | E58: NSA
A59: 55 | B59: Bicycles and accessories | C59: E1BCY1 | D59: CPI Sports vehicles including bicycles | E59: NSA
A60: 56 | B60: Pleasure boats, aircraft, and other recreational vehicles | C60: E1BAR1
A61: 57 | B61: Pleasure boats | C61: E1BOA1 | D61: CPI Sports vehicles including bicycles | E61: NSA
A62: 58 | B62: Pleasure aircraft | C62: E1AIR1 | D62: CPI Sports vehicles including bicycles | E62: NSA
A63: 59 | B63: Other recreational vehicles | C63: E1REV1 | D63: CPI Sports vehicles including bicycles | E63: NSA
A64: 60 | B64: Recreational books | C64: E1RBK1 | D64: CPI Recreational books | E64: NSA
A65: 61 | B65: Musical instruments | C65: E1MSC1 | D65: CPI Music instruments and accessories | E65: NSA
A66: 62 | B66: Other durable goods | C66: E1ODG1
A67: 63 | B67: Jewelry and watches | C67: E1JRY1
A68: 64 | B68: Jewelry | C68: E1JLY1 | D68: CPI Jewelry | E68: SA
A69: 65 | B69: Watches | C69: E1WTC1 | D69: CPI Watches | E69: NSA
A70: 66 | B70: Therapeutic appliances and equipment | C70: E1TAE1
A71: 67 | B71: Therapeutic medical equipment | C71: E1TME1 | D71: CPI Medical equipment and supplies | E71: NSA
A72: 68 | B72: Corrective eyeglasses and contact lenses | C72: E1EYE1 | D72: CPI Eyeglasses and eyecare | E72: NSA
A73: 69 | B73: Educational books | C73: E1EBK1 | D73: CPI Educational books and supplies | E73: NSA
A74: 70 | B74: Luggage and similar personal items | C74: E1LUG1 | D74: CPI Miscellaneous personal goods | E74: SA
A75: 71 | B75: Telephone and related communication equipment | C75: E1TCE1 | D75: CPI Telephone hardware, calculators, and other consumer information items | E75: SA
A76: 72 | B76: Nondurable goods | C76: E1NDG1
A77: 73 | B77: Food and beverages purchased for off-premises consumption | C77: E1FXA1
A78: 74 | B78: Food and nonalcoholic beverages purchased for off-premises consumption | C78: E1TFD1
A79: 75 | B79: Food purchased for off-premises consumption | C79: E1FOF1
A80: 76 | B80: Cereals and bakery products | C80: E1CBP1
A81: 77 | B81: Cereals | C81: E1GRA1 | D81: CPI Cereals and cereal products | E81: SA
A82: 78 | B82: Bakery products | C82: E1BAK1 | D82: CPI Bakery products | E82: NSA
A83: 79 | B83: Meats and poultry | C83: E1MAP1
A84: 80 | B84: Beef and veal | C84: E1BEE1 | D84: CPI Beef and veal | E84: SA
A85: 81 | B85: Pork | C85: E1POR1 | D85: CPI Pork | E85: SA
A86: 82 | B86: Other meats | C86: E1MEA1 | D86: CPI Other meats | E86: SA
A87: 83 | B87: Poultry | C87: E1POU1 | D87: CPI Poultry | E87: SA
A88: 84 | B88: Fish and seafood | C88: E1FIS1 | D88: CPI Fish and seafood | E88: NSA
A89: 85 | B89: Milk, dairy products, and eggs | C89: E1MDE1
A90: 86 | B90: Fresh milk | C90: E1MIL1 | D90: CPI Milk | E90: NSA
A91: 87 | B91: Processed dairy products | C91: E1DAI1 | D91: BEA Composite index of CPIs (Fixed-weighted CPIs for Cheese and related products, for Ice cream and related products, and for Other dairy and related products) | E91: NSA CPI for cheese; SA CPI for ice cream; SA CPI Other dairy
A92: 88 | B92: Eggs | C92: E1GGS1 | D92: CPI Eggs | E92: SA
A93: 89 | B93: Fats and oils | C93: E1FAT1 | D93: CPI Fats and oils | E93: SA
A94: 90 | B94: Fresh fruits and vegetables | C94: E1FAV1
A95: 91 | B95: Fruit (fresh) | C95: E1FRU1 | D95: CPI Fresh fruits | E95: SA
A96: 92 | B96: Vegetables (fresh) | C96: E1VEG1 | D96: CPI Fresh vegetables | E96: SA
A97: 93 | B97: Processed fruits and vegetables | C97: E1PFV1 | D97: CPI Processed fruits and vegetables | E97: SA
A98: 94 | B98: Sugar and sweets | C98: E1SWE1 | D98: CPI Sugar and sweets | E98: SA
A99: 95 | B99: Food products, not elsewhere classified | C99: E1OFD1 | D99: Unpublished detailed categories deflated using the following CPIs below:
D100: CPI Soups | E100: SA
D101: CPI Frozen and freeze dried prepared foods | E101: SA
D102: CPI Snacks | E102: SA
...

Sheet Macrobond
A3: United States
B4: Consumer Price Index, All Urban Consumers, U.S. City Average, All Items, SA, Index | C4: Consumer Price Index, All Urban Consumers, U.S. City Average, Housing, SA, Index | D4: Consumer Price Index, All Urban Consumers, U.S. City Average, Housing, Shelter, SA, Index | E4: Consumer Price Index, All Urban Consumers, U.S. City Average, Rent of Shelter, SA, Index | F4: Consumer Price Index, All Urban Consumers, U.S. City Average, Housing, Shelter, Rent of Primary Residence, SA, Index | G4: Consumer Price Index, All Urban Consumers, U.S. City Average, Housing, Shelter, Lodging Away from Home, SA, Index | H4: Consumer Price Index, All Urban Consumers, U.S. City Average, Housing, Lodging While at School, SA, Index | I4: Consumer Price Index, All Urban Consumers, U.S. City Average, Housing, Shelter, Other Lodging Away from Home Including Hotels & Motels, SA, Index | J4: Consumer Price Index, All Urban Consumers, U.S. City Average, Housing, Shelter, Owners' Equivalent Rent of Residence, SA, Index | K4: BLS, All Urban Consumers (CPI-U), Total, Owners' Equivalent Rent of Primary Residence, SA | L4: Consumer Price Index, All Urban Consumers, U.S. City Average, Housing, Fuels & Utilities, SA, Index | M4: Consumer Price Index, All Urban Consumers, U.S. City Average, Housing, Fuels & Utilities, Household Energy, SA, Index | N4: Consumer Price Index, All Urban Consumers, U.S. City Average, Housing, Fuels & Utilities, Fuel Oil & Other Fuels, SA, Index | O4: Consumer Price Index, All Urban Consumers, U.S. City Average, Housing, Fuels & Utilities, Fuel Oil, SA, Index | P4: Consumer Price Index, All Urban Consumers, U.S. City Average, Housing, Fuels & Utilities, Propane, Kerosene & Firewood, SA, Index | Q4: Consumer Price Index, All Urban Consumers, U.S. City Average, Housing, Fuels & Utilities, Energy Services, SA, Index | R4: Consumer Price Index, All Urban Consumers, U.S. City Average, Housing, Fuels & Utilities, Electricity, SA, Index | S4: Consumer Price Index, All Urban Consumers, U.S. City Average, Housing, Fuels & Utilities, Utility (Piped) Gas Service, SA, Index | T4: Consumer Price Index, All Urban Consumers, U.S. City Average, Housing, Fuels & Utilities, Water & Sewer & Trash Collection Services, SA, Index | U4: Consumer Price Index, All Urban Consumers, U.S. City Average, Housing, Fuels & Utilities, Water & Sewerage Maintenance, SA, Index | V4: Consumer Price Index, All Urban Consumers, U.S. City Average, Housing, Fuels & Utilities, Garbage & Trash Collection, SA, Index | W4: Consumer Price Index, All Urban Consumers, U.S. City Average, Housing, Household Furnishings & Operations, SA, Index | X4: Consumer Price Index, All Urban Consumers, U.S. City Average, Housing, Household Furnishings & Supplies, SA, Index | Y4: Consumer Price Index, All Urban Consumers, U.S. City Average, Housing, Household Furnishings & Operations, Window & Floor Coverings & Other Linens, SA, Index | Z4: Consumer Price Index, All Urban Consumers, U.S. City Average, Housing, Household Furnishings & Operations, Window Coverings, SA, Index | AA4: Consumer Price Index, All Urban Consumers, U.S. City Average, Housing, Household Furnishings & Operations, Furniture & Bedding, SA, Index | AB4: Consumer Price Index, All Urban Consumers, U.S. City Average, Housing, Household Furnishings & Operations, Other Furniture, SA, Index | AC4: Consumer Price Index, All Urban Consumers, U.S. City Average, Housing, Household Furnishings & Operations, Appliances, SA, Index | AD4: BLS, All Urban Consumers (CPI-U), Total, Major Appliances, SA | AE4: BLS, All Urban Consumers (CPI-U), Total, Laundry Equipment, SA | AF4: Consumer Price Index, All Urban Consumers, U.S. City Average, Housing, Household Furnishings & Operations, Other Appliances, SA, Index | AG4: Consumer Price Index, All Urban Consumers, U.S. City Average, Housing, Household Furnishings & Operations, Other Household Equipment & Furnishings, SA, Index | AH4: Consumer Price Index, All Urban Consumers, U.S. City Average, Housing, Household Furnishings & Operations, Indoor Plants & Flowers, SA, Index | AI4: Consumer Price Index, All Urban Consumers, U.S. City Average, Housing, Household Furnishings & Operations, Nonelectric Cookware & Tableware, SA, Index | AJ4: Consumer Price Index, All Urban Consumers, U.S. City Average, Housing, Household Furnishings & Operations, Tools, Hardware, Outdoor Equipment & Supplies, SA, Index | AK4: Consumer Price Index, All Urban Consumers, U.S. City Average, Housing, Household Furnishings & Operations, Outdoor Equipment & Supplies, SA, Index | AL4: Consumer Price Index, All Urban Consumers, U.S. City Average, Housing, Household Furnishings & Operations, Housekeeping Supplies, SA, Index | AM4: BLS, All Urban Consumers (CPI-U), Total, Household Cleaning Products, SA | AN4: Consumer Price Index, All Urban Consumers, U.S. City Average, Housing, Household Furnishings & Operations, Miscellaneous Household Products, SA, Index | AO4: Consumer Price Index, All Urban Consumers, U.S. City Average, Housing, Household Furnishings & Operations, Moving, Storage, Freight Expense, SA, Index | AP4: Consumer Price Index, All Urban Consumers, U.S. City Average, Food & Beverages, SA, Index | AQ4: Consumer Price Index, All Urban Consumers, U.S. City Average, Food & Beverages, Food, SA, Index | AR4: Consumer Price Index, All Urban Consumers, U.S. City Average, Food & Beverages, Food at Home, SA, Index | AS4: Consumer Price Index, All Urban Consumers, U.S. City Average, Food & Beverages, Food at Home, Cereals & Bakery Products, SA, Index | AT4: Consumer Price Index, All Urban Consumers, U.S. City Average, Food & Beverages, Food at Home, Cereals & Cereal Products, SA, Index | AU4: Consumer Price Index, All Urban Consumers, U.S. City Average, Food & Beverages, Food at Home, Flour & Prepared Flour Mixes, SA, Index | AV4: Consumer Price Index, All Urban Consumers, U.S. City Average, Food & Beverages, Food at Home, Breakfast Cereal, SA, Index | AW4: Consumer Price Index, All Urban Consumers, U.S. City Average, Food & Beverages, Food at Home, Rice, Pasta, Cornmeal, SA, Index | AX4: Consumer Price Index, All Urban Consumers, U.S. City Average, Food & Beverages, Food at Home, Bakery Products, SA, Index | AY4: BLS, All Urban Consumers (CPI-U), Total, Bread, SA | AZ4: BLS, All Urban Consumers (CPI-U), Total, Fresh Biscuits, Rolls, Muffins, SA | BA4: BLS, All Urban Consumers (CPI-U), Total, Fresh Biscuits, Rolls, Muffins, SA | BB4: Consumer Price Index, All Urban Consumers, U.S. City Average, Food & Beverages, Food at Home, Cakes, Cupcakes & Cookies, SA, Index | BC4: Consumer Price Index, All Urban Consumers, U.S. City Average, Food & Beverages, Food at Home, Cookies, SA, Index | BD4: Consumer Price Index, All Urban Consumers, U.S. City Average, Food & Beverages, Food at Home, Other Bakery Products, SA, Index | BE4: Consumer Price Index, All Urban Consumers, U.S. City Average, Food & Beverages, Food at Home, Crackers, Bread & Cracker Products, SA, Index | BF4: Consumer Price Index, All Urban Consumers, U.S. City Average, Food & Beverages, Food at Home, Frozen & Refrigerated Bakery Products, Pies, Tarts, Turnovers, SA, Index | BG4: Consumer Price Index, All Urban Consumers, U.S. City Average, Food & Beverages, Food at Home, Meats, Poultry, Fish & Eggs, SA, Index | BH4: Consumer Price Index, All Urban Consumers, U.S. City Average, Food & Beverages, Food at Home, Meats, Poultry & Fish, SA, Index | BI4: Consumer Price Index, All Urban Consumers, U.S. City Average, Food & Beverages, Food at Home, Meats, SA, Index | BJ4: Consumer Price Index, All Urban Consumers, U.S. City Average, Food & Beverages, Food at Home, Beef & Veal, SA, Index | BK4: Consumer Price Index, All Urban Consumers, U.S. City Average, Food & Beverages, Food at Home, Uncooked Ground Beef, SA, Index | BL4: Consumer Price Index, All Urban Consumers, U.S. City Average, Food & Beverages, Food at Home, Uncooked Beef Steaks, SA, Index | BM4: Consumer Price Index, All Urban Consumers, U.S. City Average, Food & Beverages, Food at Home, Pork, SA, Index | BN4: Consumer Price Index, All Urban Consumers, U.S. City Average, Food & Beverages, Food at Home, Bacon, Breakfast Sausage & Related Products, SA, Index | BO4: Consumer Price Index, All Urban Consumers, U.S. City Average, Food & Beverages, Food at Home, Bacon & Related Products, SA, Index | BP4: Consumer Price Index, All Urban Consumers, U.S. City Average, Food & Beverages, Food at Home, Breakfast Sausage & Related Products, SA, Index | BQ4: Consumer Price Index, All Urban Consumers, U.S. City Average, Food & Beverages, Food at Home, Ham, SA, Index | BR4: Consumer Price Index, All Urban Consumers, U.S. City Average, Food & Beverages, Food at Home, Ham, Excluding Canned, SA, Index | BS4: Consumer Price Index, All Urban Consumers, U.S. City Average, Food & Beverages, Food at Home, Pork Chops, SA, Index | BT4: Consumer Price Index, All Urban Consumers, U.S. City Average, Food & Beverages, Food at Home, Other Pork Including Roasts, Steaks, Ribs, SA, Index | BU4: Consumer Price Index, All Urban Consumers, U.S. City Average, Food & Beverages, Food at Home, Other Meats, SA, Index | BV4: Consumer Price Index, All Urban Consumers, U.S. City Average, Food & Beverages, Food at Home, Frankfurters, SA, Index | BW4: BLS, All Urban Consumers (CPI-U), Total, Lunchmeats, SA | BX4: Consumer Price Index, All Urban Consumers, U.S. City Average, Food & Beverages, Food at Home, Poultry, SA, Index | BY4: BLS, All Urban Consumers (CPI-U), Total, Chicken, SA | BZ4: Consumer Price Index, All Urban Consumers, U.S. City Average, Food & Beverages, Food at Home, Fresh Whole Chicken, SA, Index | CA4: Consumer Price Index, All Urban Consumers, U.S. City Average, Food & Beverages, Food at Home, Other Uncooked Poultry Including Turkey, SA, Index | CB4: Consumer Price Index, All Urban Consumers, U.S. City Average, Food & Beverages, Food at Home, Fish & Seafood, SA, Index | CC4: BLS, All Urban Consumers (CPI-U), Total, Fresh Fish & Seafood, SA | CD4: Consumer Price Index, All Urban Consumers, U.S. City Average, Food & Beverages, Food at Home, Processed Fish & Seafood, SA, Index | CE4: Consumer Price Index, All Urban Consumers, U.S. City Average, Food & Beverages, Food at Home, Shelf Stable Fish & Seafood, SA, Index | CF4: Consumer Price Index, All Urban Consumers, U.S. City Average, Food & Beverages, Food at Home, Frozen Fish & Seafood, SA, Index | CG4: Consumer Price Index, All Urban Consumers, U.S. City Average, Food & Beverages, Food at Home, Eggs, SA, Index | CH4: Consumer Price Index, All Urban Consumers, U.S. City Average, Food & Beverages, Food at Home, Dairy & Related Products, SA, Index | CI4: Consumer Price Index, All Urban Consumers, U.S. City Average, Food & Beverages, Food at Home, Milk, SA, Index | CJ4: Consumer Price Index, All Urban Consumers, U.S. City Average, Food & Beverages, Food at Home, Fresh Whole Milk, SA, Index | CK4: BLS, All Urban Consumers (CPI-U), Total, Fresh Milk Other than Whole, SA | CL4: Consumer Price Index, All Urban Consumers, U.S. City Average, Food & Beverages, Food at Home, Cheese & Related Products, SA, Index | CM4: Consumer Price Index, All Urban Consumers, U.S. City Average, Food & Beverages, Food at Home, Ice Cream & Related Products, SA, Index | CN4: Consumer Price Index, All Urban Consumers, U.S. City Average, Food & Beverages, Food at Home, Other Dairy & Related Products, SA, Index | CO4: Consumer Price Index, All Urban Consumers, U.S. City Average, Food & Beverages, Food at Home, Fruits & Vegetables, SA, Index | CP4: Consumer Price Index, All Urban Consumers, U.S. City Average, Food & Beverages, Food at Home, Fresh Fruits & Vegetables, SA, Index | CQ4: Consumer Price Index, All Urban Consumers, U.S. City Average, Food & Beverages, Food at Home, Fresh Fruits, SA, Index | CR4: Consumer Price Index, All Urban Consumers, U.S. City Average, Food & Beverages, Food at Home, Apples, SA, Index | CS4: Consumer Price Index, All Urban Consumers, U.S. City Average, Food & Beverages, Food at Home, Bananas, SA, Index | CT4: Consumer Price Index, All Urban Consumers, U.S. City Average, Food & Beverages, Food at Home, Citrus Fruits, SA, Index | CU4: Consumer Price Index, All Urban Consumers, U.S. City Average, Food & Beverages, Food at Home, Oranges, Including Tangerines, SA, Index | CV4: Consumer Price Index, All Urban Consumers, U.S. City Average, Food & Beverages, Food at Home, Other Fresh Fruits, SA, Index | CW4: Consumer Price Index, All Urban Consumers, U.S. City Average, Food & Beverages, Food at Home, Fresh Vegetables, SA, Index | CX4: Consumer Price Index, All Urban Consumers, U.S. City Average, Food & Beverages, Food at Home, Potatoes, SA, Index | CY4: BLS, All Urban Consumers (CPI-U), Total, Lettuce, SA | CZ4: Consumer Price Index, All Urban Consumers, U.S. City Average, Food & Beverages, Food at Home, Tomatoes, SA, Index | DA4: Consumer Price Index, All Urban Consumers, U.S. City Average, Food & Beverages, Food at Home, Other Fresh Vegetables, SA, Index | DB4: Consumer Price Index, All Urban Consumers, U.S. City Average, Food & Beverages, Food at Home, Processed Fruits & Vegetables, SA, Index | DC4: Consumer Price Index, All Urban Consumers, U.S. City Average, Food & Beverages, Food at Home, Canned Fruits & Vegetables, SA, Index | DD4: Consumer Price Index, All Urban Consumers, U.S. City Average, Food & Beverages, Food at Home, Canned Fruits, SA, Index | DE4: Consumer Price Index, All Urban Consumers, U.S. City Average, Food & Beverages, Food at Home, Canned Vegetables, SA, Index | DF4: Consumer Price Index, All Urban Consumers, U.S. City Average, Food & Beverages, Food at Home, Frozen Fruits & Vegetables, SA, Index | DG4: Consumer Price Index, All Urban Consumers, U.S. City Average, Food & Beverages, Food at Home, Frozen Vegetables, SA, Index | DH4: Consumer Price Index, All Urban Consumers, U.S. City Average, Food & Beverages, Food at Home, Other Processed Fruits & Vegetables Including Dried, SA, Index | DI4: Consumer Price Index, All Urban Consumers, U.S. City Average, Food & Beverages, Food at Home, Nonalcoholic Beverages & Beverage Materials, SA, Index | DJ4: Consumer Price Index, All Urban Consumers, U.S. City Average, Food & Beverages, Food at Home, Juices & Nonalcoholic Drinks, SA, Index | DK4: Consumer Price Index, All Urban Consumers, U.S. City Average, Food & Beverages, Food at Home, Carbonated Drinks, SA, Index | DL4: BLS, All Urban Consumers (CPI-U), Total, Nonfrozen Noncarbonated Juices & Drinks, SA | DM4: Consumer Price Index, All Urban Consumers, U.S. City Average, Food & Beverages, Food at Home, Beverage Materials Including Coffee & Tea, SA, Index | DN4: Consumer Price Index, All Urban Consumers, U.S. City Average, Food & Beverages, Food at Home, Coffee, SA, Index | DO4: Consumer Price Index, All Urban Consumers, U.S. City Average, Food & Beverages, Food at Home, Roasted Coffee, SA, Index | DP4: Consumer Price Index, All Urban Consumers, U.S. City Average, Food & Beverages, Food at Home, Other Beverage Materials Including Tea, SA, Index | DQ4: Consumer Price Index, All Urban Consumers, U.S. City Average, Food & Beverages, Food at Home, Other Food at Home, SA, Index | DR4: Consumer Price Index, All Urban Consumers, U.S. City Average, Food & Beverages, Food at Home, Sugar & Sweets, SA, Index | DS4: Consumer Price Index, All Urban Consumers, U.S. City Average, Food & Beverages, Food at Home, Sugar & Artificial Sweeteners, SA, Index | DT4: Consumer Price Index, All Urban Consumers, U.S. City Average, Food & Beverages, Food at Home, Other Sweets, SA, Index | DU4: Consumer Price Index, All Urban Consumers, U.S. City Average, Food & Beverages, Food at Home, Other Sweets, SA, Index | DV4: Consumer Price Index, All Urban Consumers, U.S. City Average, Food & Beverages, Food at Home, Fats & Oils, SA, Index | DW4: Consumer Price Index, All Urban Consumers, U.S. City Average, Food & Beverages, Food at Home, Butter & Margarine, SA, Index | DX4: Consumer Price Index, All Urban Consumers, U.S. City Average, Food & Beverages, Food at Home, Butter, SA, Index | DY4: Consumer Price Index, All Urban Consumers, U.S. City Average, Food & Beverages, Food at Home, Margarine, SA, Index | DZ4: Consumer Price Index, All Urban Consumers, U.S. City Average, Food & Beverages, Food at Home, Salad Dressing, SA, Index | EA4: Consumer Price Index, All Urban Consumers, U.S. City Average, Food & Beverages, Food at Home, Other Fats & Oils Including Peanut Butter, SA, Index | EB4: Consumer Price Index, All Urban Consumers, U.S. City Average, Food & Beverages, Food at Home, Other Foods, SA, Index | EC4: Consumer Price Index, All Urban Consumers, U.S. City Average, Food & Beverages, Food at Home, Soups, SA, Index | ED4: Consumer Price Index, All Urban Consumers, U.S. City Average, Food & Beverages, Food at Home, Frozen & Freeze Dried Prepared Foods, SA, Index | EE4: Consumer Price Index, All Urban Consumers, U.S. City Average, Food & Beverages, Food at Home, Snacks, SA, Index | EF4: Consumer Price Index, All Urban Consumers, U.S. City Average, Food & Beverages, Food at Home, Spices, Seasonings, Condiments, Sauces, SA, Index | EG4: BLS, All Urban Consumers (CPI-U), Total, Salt & Other Seasonings & Spices, SA | EH4: BLS, All Urban Consumers (CPI-U), Total, Sauces & Gravies, SA | EI4: Consumer Price Index, All Urban Consumers, U.S. City Average, Food & Beverages, Food at Home, Other Condiments, SA, Index | EJ4: BLS, All Urban Consumers (CPI-U), Total, Other Miscellaneous Foods, SA | EK4: Consumer Price Index, All Urban Consumers, U.S. City Average, Food & Beverages, Food Away from Home, SA, Index | EL4: Consumer Price Index, All Urban Consumers, U.S. City Average, Food & Beverages, Food Away from Home, Full Service Meals & Snacks, SA, Index | EM4: Consumer Price Index, All Urban Consumers, U.S. City Average, Food & Beverages, Food Away from Home, Food at Employee Sites & Schools, SA, Index | EN4: BLS, All Urban Consumers (CPI-U), Total, Food at Elementary & Secondary Schools, SA | EO4: Consumer Price Index, All Urban Consumers, U.S. City Average, Food & Beverages, Food Away from Home, Other, SA, Index | EP4: Consumer Price Index, All Urban Consumers, U.S. City Average, Food & Beverages, Alcoholic Beverages, SA, Index | EQ4: Consumer Price Index, All Urban Consumers, U.S. City Average, Food & Beverages, Alcoholic Beverages at Home, SA, Index | ER4: Consumer Price Index, All Urban Consumers, U.S. City Average, Food & Beverages, Alcoholic Beverages at Home, Beer, Ale & Other Malt Beverages, SA, Index | ES4: Consumer Price Index, All Urban Consumers, U.S. City Average, Food & Beverages, Alcoholic Beverages at Home, Distilled Spirits, SA, Index | ET4: Consumer Price Index, All Urban Consumers, U.S. City Average, Food & Beverages, Alcoholic Beverages at Home, Whiskey, SA, Index | EU4: Consumer Price Index, All Urban Consumers, U.S. City Average, Food & Beverages, Alcoholic Beverages at Home, Distilled Spirits, Excluding Whiskey, SA, Index | EV4: Consumer Price Index, All Urban Consumers, U.S. City Average, Food & Beverages, Alcoholic Beverages at Home, Wine, SA, Index | EW4: Consumer Price Index, All Urban Consumers, U.S. City Average, Food & Beverages, Alcoholic Beverages Away from Home, SA, Index | EX4: Consumer Price Index, All Urban Consumers, U.S. City Average, Food & Beverages, Alcoholic Beverages Away from Home, Distilled Spirits, SA, Index | EY4: Consumer Price Index, All Urban Consumers, U.S. City Average, Apparel, SA, Index | EZ4: Consumer Price Index, All Urban Consumers, U.S. City Average, Apparel, Men's & Boys', SA, Index | FA4: Consumer Price Index, All Urban Consumers, U.S. City Average, Apparel, Men's, SA, Index | FB4: Consumer Price Index, All Urban Consumers, U.S. City Average, Apparel, Men's Suits, Sport Coats & Outerwear, SA, Index | FC4: Consumer Price Index, All Urban Consumers, U.S. City Average, Apparel, Men's Furnishings, SA, Index | FD4: Consumer Price Index, All Urban Consumers, U.S. City Average, Apparel, Men's Shirts & Sweaters, SA, Index | FE4: Consumer Price Index, All Urban Consumers, U.S. City Average, Apparel, Men's Pants & Shorts, SA, Index | FF4: Consumer Price Index, All Urban Consumers, U.S. City Average, Apparel, Boys', SA, Index | FG4: Consumer Price Index, All Urban Consumers, U.S. City Average, Apparel, Women's & Girls', SA, Index | FH4: Consumer Price Index, All Urban Consumers, U.S. City Average, Apparel, Women's, SA, Index | FI4: Consumer Price Index, All Urban Consumers, U.S. City Average, Apparel, Women's Outerwear, SA, Index | FJ4: Consumer Price Index, All Urban Consumers, U.S. City Average, Apparel, Women's Dresses, SA, Index | FK4: Consumer Price Index, All Urban Consumers, U.S. City Average, Apparel, Women's Suits & Separates, SA, Index | FL4: Consumer Price Index, All Urban Consumers, U.S. City Average, Apparel, Women's Underwear, Nightwear, Sportswear & Accessories, SA, Index | FM4: Consumer Price Index, All Urban Consumers, U.S. City Average, Apparel, Girls', SA, Index | FN4: Consumer Price Index, All Urban Consumers, U.S. City Average, Transport, Private, Car & Truck Rental, SA, Index | FO4: Consumer Price Index, All Urban Consumers, U.S. City Average, Apparel, Girls', SA, Index | FP4: Consumer Price Index, All Urban Consumers, U.S. City Average, Apparel, Footwear, SA, Index | FQ4: Consumer Price Index, All Urban Consumers, U.S. City Average, Apparel, Footwear, Men's, SA, Index | FR4: Consumer Price Index, All Urban Consumers, U.S. City Average, Apparel, Footwear, Boys' & Girls', SA, Index | FS4: Consumer Price Index, All Urban Consumers, U.S. City Average, Apparel, Footwear, Women's, SA, Index | FT4: Consumer Price Index, All Urban Consumers, U.S. City Average, Apparel, Infants' & Toddlers', SA, Index | FU4: Consumer Price Index, All Urban Consumers, U.S. City Average, Apparel, Jewelry & Watches, SA, Index | FV4: Consumer Price Index, All Urban Consumers, U.S. City Average, Apparel, Watches, SA, Index | FW4: Consumer Price Index, All Urban Consumers, U.S. City Average, Apparel, Jewelry, SA, Index | FX4: Consumer Price Index, All Urban Consumers, U.S. City Average, Transport, SA, Index | FY4: Consumer Price Index, All Urban Consumers, U.S. City Average, Transport, Private, SA, Index | FZ4: Consumer Price Index, All Urban Consumers, U.S. City Average, Transport, Private, New & Used Motor Vehicles, SA, Index | GA4: Consumer Price Index, All Urban Consumers, U.S. City Average, Transport, Private, New Vehicles, SA, Index | GB4: Consumer Price Index, All Urban Consumers, U.S. City Average, Transport, Private, New Cars & Trucks, SA, Index | GC4: Consumer Price Index, All Urban Consumers, U.S. City Average, Transport, Private, New Cars, SA, Index | GD4: Consumer Price Index, All Urban Consumers, U.S. City Average, Transport, Private, New Trucks, SA, Index | GE4: Consumer Price Index, All Urban Consumers, U.S. City Average, Transport, Private, New Motorcycles, SA, Index | GF4: Consumer Price Index, All Urban Consumers, U.S. City Average, Transport, Private, Used Cars & Trucks, SA, Index | GG4: Consumer Price Index, All Urban Consumers, U.S. City Average, Transport, Private, Leased Cars & Trucks, SA, Index | GH4: Consumer Price Index, All Urban Consumers, U.S. City Average, Transport, Private, Motor Fuel, SA, Index | GI4: Consumer Price Index, All Urban Consumers, U.S. City Average, Transport, Private, Gasoline, All Types, SA, Index | GJ4: Consumer Price Index, All Urban Consumers, U.S. City Average, Transport, Private, Gasoline, Unleaded Regular, SA, Index | GK4: Consumer Price Index, All Urban Consumers, U.S. City Average, Transport, Private, Gasoline, Unleaded Midgrade, SA, Index | GL4: Consumer Price Index, All Urban Consumers, U.S. City Average, Transport, Private, Gasoline, Unleaded Premium, SA, Index | GM4: BLS, All Urban Consumers (CPI-U), Total, Other Motor Fuels, SA | GN4: Consumer Price Index, All Urban Consumers, U.S. City Average, Transport, Private, Motor Vehicle Parts & Equipment, SA, Index | GO4: Consumer Price Index, All Urban Consumers, U.S. City Average, Transport, Private, Tires, SA, Index | GP4: Consumer Price Index, All Urban Consumers, U.S. City Average, Transport, Private, Motor Vehicle Maintenance & Repair, SA, Index | GQ4: Consumer Price Index, All Urban Consumers, U.S. City Average, Transport, Private, Motor Vehicle Repair, SA, Index | GR4: Consumer Price Index, All Urban Consumers, U.S. City Average, Transport, Private, Motor Vehicle Insurance, SA, Index | GS4: BLS, All Urban Consumers (CPI-U), Total, Parking & Other Fees, SA | GT4: BLS, All Urban Consumers (CPI-U), Total, Parking Fees & Tolls, SA | GU4: Consumer Price Index, All Urban Consumers, U.S. City Average, Transport, Public, SA, Index | GV4: Consumer Price Index, All Urban Consumers, U.S. City Average, Transport, Public, Airline Fare, SA, Index | GW4: Consumer Price Index, All Urban Consumers, U.S. City Average, Transport, Public, Other Intercity Transportation, SA, Index | GX4: BLS, All Urban Consumers (CPI-U), Total, Intercity Train Fare, SA | GY4: Consumer Price Index, All Urban Consumers, U.S. City Average, Transport, Public, Ship Fare, SA, Index | GZ4: Consumer Price Index, All Urban Consumers, U.S. City Average, Medical Care, SA, Index | HA4: Consumer Price Index, All Urban Consumers, U.S. City Average, Medical Care, Commodities, SA, Index | HB4: BLS, All Urban Consumers (CPI-U), Total, Prescription Drugs, SA | HC4: Consumer Price Index, All Urban Consumers, U.S. City Average, Medical Care, Services, SA, Index | HD4: Consumer Price Index, All Urban Consumers, U.S. City Average, Medical Care, Professional Services, SA, Index | HE4: Consumer Price Index, All Urban Consumers, U.S. City Average, Medical Care, Physicians' Services, SA, Index | HF4: Consumer Price Index, All Urban Consumers, U.S. City Average, Medical Care, Dental Services, SA, Index | HG4: Consumer Price Index, All Urban Consumers, U.S. City Average, Medical Care, Eyeglasses & Eye Care, SA, Index | HH4: Consumer Price Index, All Urban Consumers, U.S. City Average, Medical Care, Services by Other Medical Professionals, SA, Index | HI4: Consumer Price Index, All Urban Consumers, U.S. City Average, Medical Care, Hospital & Related Services, SA, Index | HJ4: Consumer Price Index, All Urban Consumers, U.S. City Average, Medical Care, Hospital Services, SA, Index | HK4: Consumer Price Index, All Urban Consumers, U.S. City Average, Medical Care, Inpatient Hospital Services, SA, Index | HL4: Consumer Price Index, All Urban Consumers, U.S. City Average, Medical Care, Outpatient Hospital Services, SA, Index | HM4: Consumer Price Index, All Urban Consumers, U.S. City Average, Medical Care, Nursing Homes & Adult Day Services, SA, Index | HN4: Consumer Price Index, All Urban Consumers, U.S. City Average, Recreation, SA, Index | HO4: Consumer Price Index, All Urban Consumers, U.S. City Average, Recreation, Video & Audio, SA, Index | HP4: Consumer Price Index, All Urban Consumers, U.S. City Average, Recreation, Televisions, SA, Index | HQ4: Consumer Price Index, All Urban Consumers, U.S. City Average, Recreation, Cable, Satellite & Live Streaming Television Service, SA, Index | HR4: Consumer Price Index, All Urban Consumers, U.S. City Average, Recreation, Other Video Equipment, SA, Index | HS4: BLS, All Urban Consumers (CPI-U), Total, Audio Equipment, SA | HT4: Consumer Price Index, All Urban Consumers, U.S. City Average, Recreation, Pets, Pet Products & Services, SA, Index | HU4: Consumer Price Index, All Urban Consumers, U.S. City Average, Recreation, Pets & Pet Products, SA, Index | HV4: Consumer Price Index, All Urban Consumers, U.S. City Average, Recreation, Pet Food & Treats, SA, Index | HW4: Consumer Price Index, All Urban Consumers, U.S. City Average, Recreation, Purchase of Pets, Pet Supplies, Accessories, SA, Index | HX4: Consumer Price Index, All Urban Consumers, U.S. City Average, Recreation, Pet Services Including Veterinary, SA, Index | HY4: Consumer Price Index, All Urban Consumers, U.S. City Average, Recreation, Pet Services, SA, Index | HZ4: Consumer Price Index, All Urban Consumers, U.S. City Average, Recreation, Veterinarian Services, SA, Index | IA4: Consumer Price Index, All Urban Consumers, U.S. City Average, Recreation, Sporting Goods, SA, Index | IB4: Consumer Price Index, All Urban Consumers, U.S. City Average, Recreation, Sports Vehicles Including Bicycles, SA, Index | IC4: BLS, All Urban Consumers (CPI-U), Total, Sports Equipment, SA | ID4: BLS, All Urban Consumers (CPI-U), Total, Photography, SA | IE4: Consumer Price Index, All Urban Consumers, U.S. City Average, Recreation, Photographic Equipment & Supplies, SA, Index | IF4: BLS, All Urban Consumers (CPI-U), Total, Photographic Equipment, SA | IG4: Consumer Price Index, All Urban Consumers, U.S. City Average, Recreation, Other Recreational Goods, SA, Index | IH4: Consumer Price Index, All Urban Consumers, U.S. City Average, Recreation, Toys, SA, Index | II4: BLS, All Urban Consumers (CPI-U), Total, Toys, Games, Hobbies & Playground Equipment, SA | IJ4: Consumer Price Index, All Urban Consumers, U.S. City Average, Recreation, Sewing Machines, Fabric & Supplies, SA, Index | IK4: BLS, All Urban Consumers (CPI-U), Total, Music Instruments & Accessories, SA | IL4: Consumer Price Index, All Urban Consumers, U.S. City Average, Recreation, Other Services, SA, Index | IM4: BLS, All Urban Consumers (CPI-U), Total, Club Membership for Shopping Clubs, Fraternal, or Other Organizations, or Participant Sports Fees, SA | IN4: BLS, All Urban Consumers (CPI-U), Total, Admissions, SA | IO4: BLS, All Urban Consumers (CPI-U), Total, Admission to Movies, Theaters, & Concerts, SA | IP4: BLS, All Urban Consumers (CPI-U), Total, Admission to Sporting Events, SA | IQ4: BLS, All Urban Consumers (CPI-U), Total, Fees for Lessons or Instructions, SA | IR4: BLS, All Urban Consumers (CPI-U), Total, Recreational Reading Materials, SA | IS4: Consumer Price Index, All Urban Consumers, U.S. City Average, Education & Communication, SA, Index | IT4: Consumer Price Index, All Urban Consumers, U.S. City Average, Education & Communication, Education, SA, Index | IU4: Consumer Price Index, All Urban Consumers, U.S. City Average, Education & Communication, Educational Books & Supplies, SA, Index | IV4: Consumer Price Index, All Urban Consumers, U.S. City Average, Education & Communication, Tuition, Other School Fees & Childcare, SA, Index | IW4: Consumer Price Index, All Urban Consumers, U.S. City Average, Education & Communication, College Tuition & Fees, SA, Index | IX4: Consumer Price Index, All Urban Consumers, U.S. City Average, Education & Communication, Elementary & High School Tuition & Fees, SA, Index | IY4: Consumer Price Index, All Urban Consumers, U.S. City Average, Education & Communication, Day Care & Preschool, SA, Index | IZ4: Consumer Price Index, All Urban Consumers, U.S. City Average, Education & Communication, Technical & Vocational School Tuition & Fixed Fees, SA, Index | JA4: Consumer Price Index, All Urban Consumers, U.S. City Average, Education & Communication, Communication, SA, Index | JB4: Consumer Price Index, All Urban Consumers, U.S. City Average, Education & Communication, Postage & Delivery Services, SA, Index | JC4: BLS, All Urban Consumers (CPI-U), Total, Postage, SA | JD4: Consumer Price Index, All Urban Consumers, U.S. City Average, Education & Communication, Delivery Services, SA, Index | JE4: BLS, All Urban Consumers (CPI-U), Total, Information & Information Processing, SA | JF4: BLS, All Urban Consumers (CPI-U), Total, Information Technology, Hardware & Services, SA | JG4: BLS, All Urban Consumers (CPI-U), Total, Computers, Peripherals, & Smart Home Assistants, SA | JH4: BLS, All Urban Consumers (CPI-U), Total, Telephone Hardware, Calculators, & Other Consumer Information Items, SA | JI4: BLS, All Urban Consumers (CPI-U), Total, Internet Services & Electronic Information Providers, SA | JJ4: Consumer Price Index, All Urban Consumers, U.S. City Average, Other Goods & Services, SA, Index | JK4: Consumer Price Index, All Urban Consumers, U.S. City Average, Other Goods, SA, Index | JL4: Consumer Price Index, All Urban Consumers, U.S. City Average, Other Goods & Services, Tobacco & Smoking Products, SA, Index | JM4: BLS, All Urban Consumers (CPI-U), Total, Cigarettes, SA | JN4: Consumer Price Index, All Urban Consumers, U.S. City Average, Other Goods & Services, Personal Care, SA, Index | JO4: Consumer Price Index, All Urban Consumers, U.S. City Average, Other Goods & Services, Miscellaneous Personal Goods, SA, Index | JP4: BLS, All Urban Consumers (CPI-U), Total, Stationery, Stationery Supplies, Gift Wrap, SA | JQ4: BLS, All Urban Consumers (CPI-U), Total, Other Services, SA | JR4: Consumer Price Index, All Urban Consumers, U.S. City Average, Other Goods & Services, Miscellaneous Personal Services, SA, Index | JS4: Consumer Price Index, All Urban Consumers, U.S. City Average, Other Goods & Services, Legal Services, SA, Index | JT4: Consumer Price Index, All Urban Consumers, U.S. City Average, Other Goods & Services, Funeral Expenses, SA, Index | JU4: BLS, All Urban Consumers (CPI-U), Total, Laundry & Dry Cleaning Services, SA | JV4: Consumer Price Index, All Urban Consumers, U.S. City Average, Other Goods & Services, Financial Services, SA, Index | JW4: BLS, All Urban Consumers (CPI-U), Total, Tax Return Preparation & Other Accounting Fees, SA | JX4: Consumer Price Index, All Urban Consumers, U.S. City Average, All Items Less Food & Energy, SA, Index | JY4: Consumer Price Index, All Urban Consumers, U.S. City Average, All Items Less Energy, SA, Index | JZ4: Consumer Price Index, All Urban Consumers, U.S. City Average, All Items Less Food, SA, Index | KA4: Consumer Price Index, All Urban Consumers, U.S. City Average, All Items Less Food & Shelter, SA, Index | KB4: Consumer Price Index, All Urban Consumers, U.S. City Average, All Items Less Food, Shelter & Energy, SA, Index | KC4: Consumer Price Index, All Urban Consumers, U.S. City Average, All Items Less Food, Shelter, Energy & Used Cars & Trucks, SA, Index | KD4: Consumer Price Index, All Urban Consumers, U.S. City Average, All Items Less Medical Care, SA, Index | KE4: Consumer Price Index, All Urban Consumers, U.S. City Average, All Items Less Shelter, SA, Index | KF4: BLS, Urban Wage Earners & Clerical Workers (CPI-W), Total, All Items - Old Base | KG4: Consumer Price Index, All Urban Consumers, U.S. City Average, Apparel Less Footwear, SA, Index | KH4: Consumer Price Index, All Urban Consumers, U.S. City Average, Utilities & Public Transportation, SA, Index | KI4: Consumer Price Index, All Urban Consumers, U.S. City Average, Domestically Produced Farm Food, SA, Index | KJ4: Consumer Price Index, All Urban Consumers, U.S. City Average, Commodities Less Food, SA, Index | KK4: Consumer Price Index, All Urban Consumers, U.S. City Average, Commodities Less Food & Beverages, SA, Index | KL4: Consumer Price Index, All Urban Consumers, U.S. City Average, Commodities Less Food, Energy & Used Cars & Trucks, SA, Index | KM4: Consumer Price Index, All Urban Consumers, U.S. City Average, Nondurables Less Food, SA, Index | KN4: Consumer Price Index, All Urban Consumers, U.S. City Average, Nondurables Less Food & Beverages, SA, Index | KO4: Consumer Price Index, All Urban Consumers, U.S. City Average, Nondurables Less Food, Beverages & Apparel, SA, Index | KP4: Consumer Price Index, All Urban Consumers, U.S. City Average, Nondurables Less Food & Apparel, SA, Index | KQ4: Consumer Price Index, All Urban Consumers, U.S. City Average, Services Less Medical Care Services, SA, Index | KR4: Consumer Price Index, All Urban Consumers, U.S. City Average, Services Less Rent of Shelter, SA, Index | KS4: Consumer Price Index, All Urban Consumers, U.S. City Average, Transportation Commodities less Motor Fuel, SA, Index | KT4: BEA, Personal Consumption Expenditures, Services, Other Services, Personal Care & Clothing Services (14 & Parts of 17 & 118), USD | KU4: BEA, Personal Consumption Expenditures, Total, USD | KV4: BEA, Personal Consumption Expenditures, Goods, USD | KW4: BEA, Personal Consumption Expenditures, Durable Goods, USD | KX4: BEA, Personal Consumption Expenditures, Durable Goods, Motor Vehicles & Parts, USD | KY4: BEA, Personal Consumption Expenditures, Durable Goods, Motor Vehicles & Parts, New Motor Vehicles (55), USD | KZ4: BEA, Personal Consumption Expenditures, Durable Goods, Motor Vehicles & Parts, Net Purchases of Used Motor Vehicles (56), USD | LA4: BEA, Personal Consumption Expenditures, Durable Goods, Motor Vehicles & Parts, Motor Vehicle Parts & Accessories (58), USD | LB4: BEA, Personal Consumption Expenditures, Durable Goods, Furnishings & Durable Household Equipment, USD | LC4: BEA, Personal Consumption Expenditures, Durable Goods, Furnishings & Durable Household Equipment, Furniture & Furnishings (Parts of 31 & 32), USD | LD4: BEA, Personal Consumption Expenditures, Durable Goods, Furnishings & Durable Household Equipment, Household Appliances (Part of 33), USD | LE4: BEA, Personal Consumption Expenditures, Durable Goods, Furnishings & Durable Household Equipment, Glassware, Tableware & Household Utensils (34), USD | LF4: BEA, Personal Consumption Expenditures, Durable Goods, Furnishings & Durable Household Equipment, Tools & Equipment for House & Garden (35), USD | LG4: BEA, Personal Consumption Expenditures, Durable Goods, Recreational Goods & Vehicles, USD | LH4: BEA, Personal Consumption Expenditures, Durable Goods, Recreational Goods & Vehicles, Video, Audio, Photographic & Information Processing Equipment & Media (75, 76 & Part of 93), USD | LI4: BEA, Personal Consumption Expenditures, Durable Goods, Recreational Goods & Vehicles, Sporting Equipment, Supplies, Guns & Ammunition (Part of 80), USD | LJ4: BEA, Personal Consumption Expenditures, Durable Goods, Recreational Goods & Vehicles, Sports & Recreational Vehicles (79), USD | LK4: BEA, Personal Consumption Expenditures, Durable Goods, Recreational Goods & Vehicles, Recreational Books (Part of 90), USD | LL4: BEA, Personal Consumption Expenditures, Durable Goods, Recreational Goods & Vehicles, Musical Instruments (Part of 80), USD | LM4: BEA, Personal Consumption Expenditures, Durable Goods, Other Durable Goods, USD | LN4: BEA, Personal Consumption Expenditures, Durable Goods, Other Durable Goods, Jewelry & Watches (Part of 119), USD | LO4: BEA, Personal Consumption Expenditures, Durable Goods, Other Durable Goods, Therapeutic Appliances & Equipment (42), USD | LP4: BEA, Personal Consumption Expenditures, Durable Goods, Other Durable Goods, Educational Books (96), USD | LQ4: BEA, Personal Consumption Expenditures, Durable Goods, Other Durable Goods, Luggage & Similar Personal Items (Part of 119), USD | LR4: BEA, Personal Consumption Expenditures, Durable Goods, Other Durable Goods, Telephone & Related Communication Equipment, USD | LS4: BEA, Personal Consumption Expenditures, Nondurable Goods, USD | LT4: BEA, Personal Consumption Expenditures, Nondurable Goods, Food & Beverages Purchased for Off-Premises Consumption, USD | LU4: BEA, Personal Consumption Expenditures, Nondurable Goods, Food & Beverages Purchased for Off-Premises Consumption, Food & Nonalcoholic Beverages Purchased for Off-Premises Consumption (4), USD | LV4: BEA, Personal Consumption Expenditures, Nondurable Goods, Food & Beverages Purchased for Off-Premises Consumption, Alcoholic Beverages Purchased for Off-Premises Consumption (5), USD | LW4: BEA, Personal Consumption Expenditures, Nondurable Goods, Food & Beverages Purchased for Off-Premises Consumption, Food Produced & Consumed on Farms (6), USD | LX4: BEA, Personal Consumption Expenditures, Nondurable Goods, Clothing & Footwear, USD | LY4: BEA, Personal Consumption Expenditures, Nondurable Goods, Clothing & Footwear, Garments, USD | LZ4: BEA, Personal Consumption Expenditures, Nondurable Goods, Clothing & Footwear, Garments, Women's & Girls' Clothing (10), USD | MA4: BEA, Personal Consumption Expenditures, Nondurable Goods, Clothing & Footwear, Garments, Men's & Boys' Clothing (11), USD | MB4: BEA, Personal Consumption Expenditures, Nondurable Goods, Clothing & Footwear, Garments, Children's & Infants' Clothing (12), USD | MC4: BEA, Personal Consumption Expenditures, Nondurable Goods, Clothing & Footwear, Other Clothing Materials & Footwear (13 & 17), USD | MD4: BEA, Personal Consumption Expenditures, Nondurable Goods, Gasoline & Other Energy Goods, USD | ME4: BEA, Personal Consumption Expenditures, Nondurable Goods, Gasoline & Other Energy Goods, Motor Vehicle Fuels, Lubricants & Fluids (59), USD | MF4: BEA, Personal Consumption Expenditures, Nondurable Goods, Gasoline & Other Energy Goods, Fuel Oil & Other Fuels (29), USD | MG4: BEA, Personal Consumption Expenditures, Nondurable Goods, Other Nondurable Goods, USD | MH4: BEA, Personal Consumption Expenditures, Nondurable Goods, Other Nondurable Goods, Pharmaceutical & Other Medical Products (40 & 41), USD | MI4: BEA, Personal Consumption Expenditures, Nondurable Goods, Other Nondurable Goods, Recreational Items (Parts of 80, 92 & 93), USD | MJ4: BEA, Personal Consumption Expenditures, Nondurable Goods, Other Nondurable Goods, Household Supplies (Parts of 32 & 36), USD | MK4: BEA, Personal Consumption Expenditures, Nondurable Goods, Other Nondurable Goods, Personal Care Products (Part of 118), USD | ML4: BEA, Personal Consumption Expenditures, Nondurable Goods, Other Nondurable Goods, Tobacco (127), USD | MM4: BEA, Personal Consumption Expenditures, Nondurable Goods, Other Nondurable Goods, Magazines, Newspapers & Stationery (Part of 90), USD | MN4: BEA, Personal Consumption Expenditures, Nondurable Goods, Other Nondurable Goods, Net Expenditures Abroad by U.S. Residents (131), USD | MO4: BEA, Personal Consumption Expenditures, Services, USD | MP4: BEA, Personal Consumption Expenditures, Household Consumption Expenditures (for Services), USD | MQ4: BEA, Personal Consumption Expenditures, Services, Housing & Utilities, USD | MR4: BEA, Personal Consumption Expenditures, Services, Housing & Utilities, Housing, USD | MS4: BEA, Personal Consumption Expenditures, Services, Housing & Utilities, Housing, Rental of Tenant-Occupied Nonfarm Housing (20), USD | MT4: BEA, Personal Consumption Expenditures, Services, Housing & Utilities, Housing, Imputed Rental of Owner-Occupied Nonfarm Housing (21), USD | MU4: BEA, Personal Consumption Expenditures, Services, Housing & Utilities, Housing, Rental Value of Farm Dwellings (22), USD | MV4: BEA, Personal Consumption Expenditures, Services, Housing & Utilities, Housing, Group Housing (23), USD | MW4: BEA, Personal Consumption Expenditures, Services, Housing & Utilities, Household Utilities, USD | MX4: BEA, Personal Consumption Expenditures, Services, Housing & Utilities, Household Utilities, Water Supply & Sanitation (25), USD | MY4: BEA, Personal Consumption Expenditures, Services, Housing & Utilities, Household Utilities, Electricity & Gas, USD | MZ4: BEA, Personal Consumption Expenditures, Services, Housing & Utilities, Household Utilities, Electricity & Gas, Electricity (27), USD | NA4: BEA, Personal Consumption Expenditures, Services, Housing & Utilities, Household Utilities, Electricity & Gas, Natural Gas (28), USD | NB4: BEA, Personal Consumption Expenditures, Services, Health Care, USD | NC4: BEA, Personal Consumption Expenditures, Services, Health Care, Outpatient Services, USD | ND4: BEA, Personal Consumption Expenditures, Services, Health Care, Outpatient Services, Physician Services (44), USD | NE4: BEA, Personal Consumption Expenditures, Services, Health Care, Outpatient Services, Dental Services (45), USD | NF4: BEA, Personal Consumption Expenditures, Services, Health Care, Outpatient Services, Paramedical Services (46), USD | NG4: BEA, Personal Consumption Expenditures, Services, Health Care, Hospital & Nursing Home Services, USD | NH4: BEA, Personal Consumption Expenditures, Services, Health Care, Hospital & Nursing Home Services, Hospitals (51), USD | NI4: BEA, Personal Consumption Expenditures, Services, Health Care, Hospital & Nursing Home Services, Nursing Homes (52), USD | NJ4: BEA, Personal Consumption Expenditures, Services, Transportation Services, USD | NK4: BEA, Personal Consumption Expenditures, Services, Transportation Services, Motor Vehicle Services, USD | NL4: BEA, Personal Consumption Expenditures, Services, Transportation Services, Motor Vehicle Services, Motor Vehicle Maintenance & Repair (60), USD | NM4: BEA, Personal Consumption Expenditures, Services, Transportation Services, Motor Vehicle Services, Other Motor Vehicle Services (61), USD | NN4: BEA, Personal Consumption Expenditures, Services, Transportation Services, Public Transportation, USD | NO4: BEA, Personal Consumption Expenditures, Services, Transportation Services, Public Transportation, Ground Transportation (63), USD | NP4: BEA, Personal Consumption Expenditures, Services, Transportation Services, Public Transportation, Air Transportation (64), USD | NQ4: BEA, Personal Consumption Expenditures, Services, Transportation Services, Public Transportation, Water Transportation (65), USD | NR4: BEA, Personal Consumption Expenditures, Services, Recreation Services, USD | NS4: BEA, Personal Consumption Expenditures, Services, Recreation Services, Membership Clubs, Sports Centers, Parks, Theaters & Museums (82), USD | NT4: BEA, Personal Consumption Expenditures, Services, Recreation Services, Audio-Video, Photographic & Information Processing Equipment Services (Parts of 77 & 93), USD | NU4: BEA, Personal Consumption Expenditures, Services, Recreation Services, Gambling (91), USD | NV4: BEA, Personal Consumption Expenditures, Services, Recreation Services, Other Recreational Services (81, 94 & Part of 92), USD | NW4: BEA, Personal Consumption Expenditures, Services, Food Services & Accommodations, USD | NX4: BEA, Personal Consumption Expenditures, Services, Food Services & Accommodations, Food Services, USD | NY4: BEA, Personal Consumption Expenditures, Services, Food Services & Accommodations, Food Services, Purchased Meals & Beverages (102), USD | NZ4: BEA, Personal Consumption Expenditures, Services, Food Services & Accommodations, Food Services, Food Furnished to Employees (Including Military) (103), USD | OA4: BEA, Personal Consumption Expenditures, Services, Food Services & Accommodations, Accommodations (104), USD | OB4: BEA, Personal Consumption Expenditures, Services, Financial Services & Insurance, USD | OC4: BEA, Personal Consumption Expenditures, Services, Financial Services & Insurance, Financial Services, USD | OD4: BEA, Personal Consumption Expenditures, Services, Financial Services & Insurance, Financial Services, Financial Services Furnished without Payment (107), USD | OE4: BEA, Personal Consumption Expenditures, Services, Financial Services & Insurance, Financial Services, Financial Service Charges, Fees & Commissions (108), USD | OF4: BEA, Personal Consumption Expenditures, Services, Financial Services & Insurance, Insurance, USD | OG4: BEA, Personal Consumption Expenditures, Services, Financial Services & Insurance, Insurance, Life Insurance (110), USD | OH4: BEA, Personal Consumption Expenditures, Services, Financial Services & Insurance, Insurance, Net Household Insurance (111), USD | OI4: BEA, Personal Consumption Expenditures, Services, Financial Services & Insurance, Insurance, Net Health Insurance (112), USD | OJ4: BEA, Personal Consumption Expenditures, Services, Financial Services & Insurance, Insurance, Net Motor Vehicle & Other Transportation Insurance (116), USD | OK4: BEA, Personal Consumption Expenditures, Services, Other Services, USD | OL4: BEA, Personal Consumption Expenditures, Services, Other Services, Communication, USD | OM4: BEA, Personal Consumption Expenditures, Services, Other Services, Communication, Telecommunication Services (71), USD | ON4: BEA, Personal Consumption Expenditures, Services, Other Services, Communication, Postal & Delivery Services (68), USD | OO4: BEA, Personal Consumption Expenditures, Services, Other Services, Communication, Internet Access (72), USD | OP4: BEA, Personal Consumption Expenditures, Services, Other Services, Education Services, USD | OQ4: BEA, Personal Consumption Expenditures, Services, Other Services, Education Services, Higher Education (97), USD | OR4: BEA, Personal Consumption Expenditures, Services, Other Services, Education Services, Nursery, Elementary & Secondary Schools (98), USD | OS4: BEA, Personal Consumption Expenditures, Services, Other Services, Education Services, Commercial & Vocational Schools (99), USD | OT4: BEA, Personal Consumption Expenditures, Services, Other Services, Professional & Other Services (121), USD | OU4: BEA, Personal Consumption Expenditures, Services, Other Services, Social Services & Religious Activities (120), USD | OV4: BEA, Personal Consumption Expenditures, Services, Other Services, Household Maintenance (Parts of 31, 33 & 36), USD | OW4: BEA, Personal Consumption Expenditures, Services, Other Services, Net Foreign Travel, USD | OX4: BEA, Personal Consumption Expenditures, Services, Other Services, Net Foreign Travel, Foreign Travel by U.S. Residents (129), USD | OY4: BEA, Personal Consumption Expenditures, Services, Other Services, Net Foreign Travel, Less: Expenditures in the United States by Nonresidents (130), USD | OZ4: BEA, Personal Consumption Expenditures, Services, Final Consumption Expenditures of Nonprofit Institutions Serving Households (NPISHs), USD | PA4: BEA, Personal Consumption Expenditures, Services, Final Consumption Expenditures of Nonprofit Institutions Serving Households (NPISHs), Gross Output of Nonprofit Institutions (133), USD | PB4: BEA, Personal Consumption Expenditures, Services, Final Consumption Expenditures of Nonprofit Institutions Serving Households (NPISHs), Less: Receipts from Sales of Goods & Services by Nonprofit Institutions (134), USD
A5: 17168 | B5: 21.48 | N5: 8.5 | Q5: 18.3 | AQ5: 22.8 | BH5: 26.5 | BI5: 24.5 | BJ5: 22.7 | BK5: 26.5 | BM5: 29.9 | BO5: 30.8 | BS5: 26.8 | CB5: 16.6 | CG5: 66.5 | CJ5: 31.7 | CO5: 20.8 | CP5: 17.5 | CQ5: 21.6 | CR5: 20.1 | CS5: 35.6 | CU5: 14.2 | CW5: 16 | CX5: 16.8 | DI5: 11.1 | DX5: 34.9 | EY5: 38.4 | EZ5: 40.7 | FG5: 53.6 | FP5: 26.4 | FX5: 17.9 | FY5: 20.1 | GZ5: 13.2 | JZ5: 21 | KE5: 23.2 | KG5: 46.1 | KU5: 5.2053667e+10 | KV5: 3.1864667e+10 | KW5: 6.9073333e+09 | KX5: 2.1063333e+09 | LB5: 2948000000 | LG5: 9.3633333e+08 | LM5: 9.1633333e+08 | LS5: 2.4957333e+10 | LT5: 1.3026333e+10 | LX5: 5.8743333e+09 | MD5: 2.1383333e+09 | MG5: 3.9183333e+09 | MO5: 20189000000
A6: 17199 | B6: 21.62 | N6: 8.5 | Q6: 18.3 | AQ6: 23.1 | BH6: 26.9 | BI6: 24.9 | BJ6: 23.1 | BK6: 26.3 | BM6: 30 | BO6: 30.2 | BS6: 28 | CB6: 16.1 | CG6: 69.7 | CJ6: 30.7 | CO6: 21.1 | CP6: 17.8 | CQ6: 21.5 | CR6: 20.2 | CS6: 35.4 | CU6: 13.7 | CW6: 16.4 | CX6: 16.4 | DI6: 11.4 | DX6: 33.7 | EY6: 38.8 | EZ6: 41 | FG6: 54.2 | FP6: 26.7 | FX6: 17.9 | FY6: 20.1 | GZ6: 13.3 | JZ6: 21.1 | KE6: 23.3 | KG6: 46.5 | KU6: 5.2053667e+10 | KV6: 3.1864667e+10 | KW6: 6.9073333e+09 | KX6: 2.1063333e+09 | LB6: 2948000000 | LG6: 9.3633333e+08 | LM6: 9.1633333e+08 | LS6: 2.4957333e+10 | LT6: 1.3026333e+10 | LX6: 5.8743333e+09 | MD6: 2.1383333e+09 | MG6: 3.9183333e+09 | MO6: 20189000000
A7: 17227 | B7: 22 | N7: 8.5 | Q7: 18.3 | AQ7: 23.8 | BH7: 27.7 | BI7: 26.1 | BJ7: 23.7 | BK7: 26.5 | BM7: 33.1 | BO7: 33.4 | BS7: 30.6 | CB7: 16.5 | CG7: 69.5 | CJ7: 30.4 | CO7: 22.2 | CP7: 19.1 | CQ7: 22.3 | CR7: 20.4 | CS7: 35.4 | CU7: 15.2 | CW7: 18.1 | CX7: 17.6 | DI7: 11.7 | DX7: 36.7 | EY7: 39.4 | EZ7: 41.3 | FG7: 55.2 | FP7: 27.4 | FX7: 18.1 | FY7: 20.3 | GZ7: 13.3 | JZ7: 21.3 | KE7: 23.8 | KG7: 47.1 | KU7: 5.2053667e+10 | KV7: 3.1864667e+10 | KW7: 6.9073333e+09 | KX7: 2.1063333e+09 | LB7: 2948000000 | LG7: 9.3633333e+08 | LM7: 9.1633333e+08 | LS7: 2.4957333e+10 | LT7: 1.3026333e+10 | LX7: 5.8743333e+09 | MD7: 2.1383333e+09 | MG7: 3.9183333e+09 | MO7: 20189000000
A8: 17258 | B8: 22 | N8: 8.7 | Q8: 18.3 | AQ8: 23.5 | BH8: 27.1 | BI8: 25.5 | BJ8: 23.8 | BK8: 26.7 | BM8: 30.9 | BO8: 31.5 | BS8: 28 | CB8: 16.4 | CG8: 70.3 | CJ8: 30.7 | CO8: 21.8 | CP8: 18.7 | CQ8: 23 | CR8: 20.9 | CS8: 36.1 | CU8: 15.6 | CW8: 17 | CX8: 18.5 | DI8: 12 | DX8: 32.9 | EY8: 39.7 | EZ8: 41.5 | FG8: 55.5 | FP8: 27.5 | FX8: 18.3 | FY8: 20.5 | GZ8: 13.4 | JZ8: 21.4 | KE8: 23.8 | KG8: 47.5 | KU8: 5.3343667e+10 | KV8: 3.2749333e+10 | KW8: 7117000000 | KX8: 2.1456667e+09 | LB8: 3078000000 | LG8: 971000000 | LM8: 9.2266667e+08 | LS8: 2.5632333e+10 | LT8: 1.3321333e+10 | LX8: 5918000000 | MD8: 2274000000 | MG8: 4.1193333e+09 | MO8: 2.0594333e+10
A9: 17288 | B9: 21.95 | N9: 8.7 | Q9: 18.3 | AQ9: 23.4 | BH9: 27 | BI9: 25.3 | BJ9: 23.7 | BK9: 26.3 | BM9: 30.6 | BO9: 30.7 | BS9: 28.2 | CB9: 16.3 | CG9: 70.9 | CJ9: 30.5 | CO9: 22.2 | CP9: 19.1 | CQ9: 22.5 | CR9: 19.9 | CS9: 36.3 | CU9: 14.9 | CW9: 18 | CX9: 18.6 | DI9: 12.1 | DX9: 31.6 | EY9: 39.8 | EZ9: 41.5 | FG9: 55.6 | FP9: 27.6 | FX9: 18.3 | FY9: 20.6 | GZ9: 13.5 | JZ9: 21.5 | KE9: 23.7 | KG9: 47.6 | KU9: 5.3343667e+10 | KV9: 3.2749333e+10 | KW9: 7117000000 | KX9: 2.1456667e+09 | LB9: 3078000000 | LG9: 971000000 | LM9: 9.2266667e+08 | LS9: 2.5632333e+10 | LT9: 1.3321333e+10 | LX9: 5918000000 | MD9: 2274000000 | MG9: 4.1193333e+09 | MO9: 2.0594333e+10
A10: 17319 | B10: 22.08 | N10: 8.7 | Q10: 18.2 | AQ10: 23.5 | BH10: 27.8 | BI10: 26 | BJ10: 24.7 | BK10: 27.5 | BM10: 30.9 | BO10: 31.3 | BS10: 28.6 | CB10: 16.4 | CG10: 70 | CJ10: 30.1 | CO10: 22.1 | CP10: 19.1 | CQ10: 21.7 | CR10: 18.8 | CS10: 36.3 | CU10: 14.4 | CW10: 18.2 | CX10: 19.8 | DI10: 11.8 | DX10: 32.2 | EY10: 40 | EZ10: 41.6 | FG10: 55.8 | FP10: 27.8 | FX10: 18.4 | FY10: 20.6 | GZ10: 13.5 | JZ10: 21.6 | KE10: 23.8 | KG10: 47.7 | KU10: 5.3343667e+10 | KV10: 3.2749333e+10 | KW10: 7117000000 | KX10: 2.1456667e+09 | LB10: 3078000000 | LG10: 971000000 | LM10: 9.2266667e+08 | LS10: 2.5632333e+10 | LT10: 1.3321333e+10 | LX10: 5918000000 | MD10: 2274000000 | MG10: 4.1193333e+09 | MO10: 2.0594333e+10
A11: 17349 | B11: 22.23 | N11: 8.9 | Q11: 18.2 | AQ11: 23.8 | BH11: 27.9 | BI11: 26.2 | BJ11: 25.1 | BK11: 27.9 | BM11: 31.2 | BO11: 31.4 | BS11: 29 | CB11: 16.8 | CG11: 72.5 | CJ11: 30.7 | CO11: 22.2 | CP11: 19.4 | CQ11: 20.2 | CR11: 17.8 | CS11: 35.6 | CU11: 13.5 | CW11: 19 | CX11: 21.3 | DI11: 11.9 | DX11: 34.5 | EY11: 40 | EZ11: 41.6 | FG11: 55.8 | FP11: 27.8 | FX11: 18.5 | FY11: 20.8 | GZ11: 13.5 | JZ11: 21.7 | KE11: 24 | KG11: 47.8 | KU11: 5.4514333e+10 | KV11: 33473000000 | KW11: 7.2566667e+09 | KX11: 2.0603333e+09 | LB11: 3.2556667e+09 | LG11: 1.0073333e+09 | LM11: 9.3333333e+08 | LS11: 2.6216333e+10 | LT11: 1.3550667e+10 | LX11: 6.0716667e+09 | MD11: 2.3676667e+09 | MG11: 4226000000 | MO11: 2.1041333e+10
A12: 17380 | B12: 22.4 | N12: 9.5 | Q12: 18.3 | AQ12: 24.1 | BH12: 28.5 | BI12: 27 | BJ12: 25.9 | BK12: 28.6 | BM12: 31.3 | BO12: 32.4 | BS12: 28.9 | CB12: 16.9 | CG12: 70.4 | CJ12: 30.7 | CO12: 23 | CP12: 20.2 | CQ12: 21.8 | CR12: 17.6 | CS12: 36.2 | CU12: 15.9 | CW12: 20.3 | CX12: 19.7 | DI12: 11.9 | DX12: 36 | EY12: 40.1 | EZ12: 41.7 | FG12: 56.2 | FP12: 28 | FX12: 18.5 | FY12: 20.9 | GZ12: 13.6 | JZ12: 21.8 | KE12: 24.2 | KG12: 47.9 | KU12: 5.4514333e+10 | KV12: 33473000000 | KW12: 7.2566667e+09 | KX12: 2.0603333e+09 | LB12: 3.2556667e+09 | LG12: 1.0073333e+09 | LM12: 9.3333333e+08 | LS12: 2.6216333e+10 | LT12: 1.3550667e+10 | LX12: 6.0716667e+09 | MD12: 2.3676667e+09 | MG12: 4226000000 | MO12: 2.1041333e+10
A13: 17411 | B13: 22.84 | N13: 9.5 | Q13: 18.3 | AQ13: 24.8 | BH13: 29.8 | BI13: 28.2 | BJ13: 27.3 | BK13: 29.7 | BM13: 32.6 | BO13: 33.8 | BS13: 29.8 | CB13: 17.4 | CG13: 73.8 | CJ13: 31.3 | CO13: 23.3 | CP13: 20.8 | CQ13: 22.3 | CR13: 18.9 | CS13: 36.9 | CU13: 15.4 | CW13: 20.9 | CX13: 20 | DI13: 12.1 | DX13: 41.1 | EY13: 40.2 | EZ13: 41.7 | FG13: 56.1 | FP13: 28 | FX13: 18.7 | FY13: 21.1 | GZ13: 13.7 | JZ13: 22 | KE13: 24.6 | KG13: 48 | KU13: 5.4514333e+10 | KV13: 33473000000 | KW13: 7.2566667e+09 | KX13: 2.0603333e+09 | LB13: 3.2556667e+09 | LG13: 1.0073333e+09 | LM13: 9.3333333e+08 | LS13: 2.6216333e+10 | LT13: 1.3550667e+10 | LX13: 6.0716667e+09 | MD13: 2.3676667e+09 | MG13: 4226000000 | MO13: 2.1041333e+10
A14: 17441 | B14: 22.91 | N14: 9.5 | Q14: 18.3 | AQ14: 24.9 | BH14: 30.1 | BI14: 28.2 | BJ14: 26.9 | BK14: 29.9 | BM14: 33.5 | BO14: 34.5 | BS14: 30.8 | CB14: 17.7 | CG14: 71.3 | CJ14: 31.7 | CO14: 23.3 | CP14: 20.9 | CQ14: 21.9 | CR14: 19.8 | CS14: 37.3 | CU14: 14.8 | CW14: 21.2 | CX14: 20.7 | DI14: 12.2 | DX14: 36.9 | EY14: 40.4 | EZ14: 41.9 | FG14: 56.3 | FP14: 28.2 | FX14: 18.8 | FY14: 21.3 | GZ14: 13.8 | JZ14: 22.1 | KE14: 24.7 | KG14: 48.2 | KU14: 5.5890667e+10 | KV14: 3.4484333e+10 | KW14: 7.8293333e+09 | KX14: 2.3796667e+09 | LB14: 3461000000 | LG14: 1.0456667e+09 | LM14: 9.4266667e+08 | LS14: 26655000000 | LT14: 13691000000 | LX14: 6186000000 | MD14: 2.4693333e+09 | MG14: 4309000000 | MO14: 2.1406333e+10
A15: 17472 | B15: 23.06 | N15: 9.7 | Q15: 18.3 | AQ15: 25.2 | BH15: 29.9 | BI15: 28 | BJ15: 26.6 | BK15: 29.9 | BM15: 33.4 | BO15: 35.1 | BS15: 30.6 | CB15: 18.8 | CG15: 70.7 | CJ15: 32.2 | CO15: 23.2 | CP15: 20.8 | CQ15: 21.8 | CR15: 19.4 | CS15: 37.3 | CU15: 14.4 | CW15: 21.2 | CX15: 21.7 | DI15: 12.5 | DX15: 39.8 | EY15: 40.6 | EZ15: 42.2 | FG15: 56.5 | FP15: 28.4 | FX15: 19 | FY15: 21.6 | GZ15: 13.8 | JZ15: 22.3 | KE15: 24.9 | KG15: 48.5 | KU15: 5.5890667e+10 | KV15: 3.4484333e+10 | KW15: 7.8293333e+09 | KX15: 2.3796667e+09 | LB15: 3461000000 | LG15: 1.0456667e+09 | LM15: 9.4266667e+08 | LS15: 26655000000 | LT15: 13691000000 | LX15: 6186000000 | MD15: 2.4693333e+09 | MG15: 4309000000 | MO15: 2.1406333e+10
A16: 17502 | B16: 23.41 | N16: 9.8 | Q16: 18.4 | AQ16: 25.7 | BH16: 30.4 | BI16: 28.4 | BJ16: 27.1 | BK16: 30.3 | BM16: 34.1 | BO16: 37.1 | BS16: 31.4 | CB16: 18.7 | CG16: 80.6 | CJ16: 32.5 | CO16: 23.5 | CP16: 21.1 | CQ16: 21.8 | CR16: 19.3 | CS16: 37.6 | CU16: 14.4 | CW16: 21.7 | CX16: 22.1 | DI16: 12.6 | DX16: 42.7 | EY16: 41 | EZ16: 42.4 | FG16: 56.9 | FP16: 28.9 | FX16: 19.1 | FY16: 21.7 | GZ16: 13.9 | JZ16: 22.4 | KE16: 25.3 | KG16: 48.8 | KU16: 5.5890667e+10 | KV16: 3.4484333e+10 | KW16: 7.8293333e+09 | KX16: 2.3796667e+09 | LB16: 3461000000 | LG16: 1.0456667e+09 | LM16: 9.4266667e+08 | LS16: 26655000000 | LT16: 13691000000 | LX16: 6186000000 | MD16: 2.4693333e+09 | MG16: 4309000000 | MO16: 2.1406333e+10
... A64: 18963 | B64: 26.47 | N64: 11.8 | Q64: 19.4 | AQ64: 28.9 | BH64: 36 | BI64: 34.8 | BJ64: 37.4 | BK64: 43.1 | BM64: 32.1 | BO64: 27.1 | BS64: 33.3 | CB64: 22 | CG64: 74.6 | CJ64: 36.5 | CO64: 27.1 | CP64: 25.5 | CQ64: 22.9 | CR64: 18.2 | CS64: 39.1 | CU64: 17.2 | CW64: 27.9 | CX64: 26.1 | DI64: 22.3 | DX64: 38.8 | EY64: 44.3 | EZ64: 47 | FG64: 58.1 | FP64: 34.5 | FX64: 24.9 | FY64: 26.5 | GZ64: 16.3 | JZ64: 25.7 | KE64: 28.4 | KG64: 51.4 | KU64: 70530000000 | KV64: 4.1948333e+10 | KW64: 1.0130333e+10 | KX64: 3613000000 | LB64: 4.0606667e+09 | LG64: 1.3746667e+09 | LM64: 1.0816667e+09 | LS64: 31818000000 | LT64: 15662000000 | LX64: 6915000000 | MD64: 3.2963333e+09 | MG64: 5.9446667e+09 | MO64: 2.8581667e+10
A65: 18994 | B65: 26.45 | N65: 11.8 | O65: 11.4 | Q65: 19.4 | R65: 27.5 | S65: 13.2 | AQ65: 28.9 | AR65: 31.2 | BH65: 36 | BI65: 34.6 | BJ65: 37.4 | BK65: 43.1 | BM65: 31.6 | BO65: 27 | BS65: 33.3 | CB65: 21.8 | CG65: 67.6 | CJ65: 36.9 | CO65: 26.9 | CP65: 25.2 | CQ65: 22.9 | CR65: 18.8 | CS65: 39.7 | CU65: 17.3 | CW65: 26.9 | CX65: 27.5 | DI65: 21.9 | DX65: 40.6 | EY65: 43.9 | EZ65: 46.8 | FG65: 57.8 | FP65: 34.3 | FX65: 25 | FY65: 26.6 | GZ65: 16.3 | JZ65: 25.6 | KE65: 28.4 | KG65: 51.1 | KU65: 7.0989667e+10 | KV65: 41846000000 | KW65: 1.0258667e+10 | KX65: 3.7473333e+09 | LB65: 4.0223333e+09 | LG65: 1.4046667e+09 | LM65: 1.0843333e+09 | LS65: 3.1587333e+10 | LT65: 1.5654333e+10 | LX65: 6813000000 | MD65: 3305000000 | MG65: 5815000000 | MO65: 2.9143667e+10
A66: 19025 | B66: 26.41 | N66: 11.8 | O66: 11.4 | Q66: 19.4 | R66: 27.5 | S66: 13.3 | AQ66: 28.6 | AR66: 30.7 | BH66: 36.2 | BI66: 34.4 | BJ66: 37.3 | BK66: 43.1 | BM66: 30.8 | BO66: 26.7 | BS66: 31.9 | CB66: 22 | CG66: 68.2 | CJ66: 37.2 | CO66: 25.1 | CP66: 22.8 | CQ66: 22.5 | CR66: 19.1 | CS66: 39.6 | CU66: 16.4 | CW66: 23.5 | CX66: 25.6 | DI66: 22 | DX66: 41.5 | EY66: 43.9 | EZ66: 46.5 | FG66: 57.8 | FP66: 34.2 | FX66: 25.2 | FY66: 26.8 | GZ66: 16.4 | JZ66: 25.7 | KE66: 28.3 | KG66: 51 | KU66: 7.0989667e+10 | KV66: 41846000000 | KW66: 1.0258667e+10 | KX66: 3.7473333e+09 | LB66: 4.0223333e+09 | LG66: 1.4046667e+09 | LM66: 1.0843333e+09 | LS66: 3.1587333e+10 | LT66: 1.5654333e+10 | LX66: 6813000000 | MD66: 3305000000 | MG66: 5815000000 | MO66: 2.9143667e+10
A67: 19054 | B67: 26.39 | N67: 11.9 | O67: 11.4 | Q67: 19.4 | R67: 27.5 | S67: 13.3 | AQ67: 28.5 | AR67: 30.7 | BH67: 35.6 | BI67: 34.2 | BJ67: 37.6 | BK67: 43 | BM67: 30.5 | BO67: 26.5 | BS67: 31.4 | CB67: 21.7 | CG67: 63.4 | CJ67: 37.4 | CO67: 26.1 | CP67: 24.2 | CQ67: 22.7 | CR67: 19.3 | CS67: 40.4 | CU67: 16.4 | CW67: 25.9 | CX67: 27 | DI67: 22.1 | DX67: 39.5 | EY67: 43.7 | EZ67: 46.4 | FG67: 57.5 | FP67: 34.1 | FX67: 25.3 | FY67: 27 | GZ67: 16.5 | JZ67: 25.7 | KE67: 28.3 | KG67: 50.8 | KU67: 7.0989667e+10 | KV67: 41846000000 | KW67: 1.0258667e+10 | KX67: 3.7473333e+09 | LB67: 4.0223333e+09 | LG67: 1.4046667e+09 | LM67: 1.0843333e+09 | LS67: 3.1587333e+10 | LT67: 1.5654333e+10 | LX67: 6813000000 | MD67: 3305000000 | MG67: 5815000000 | MO67: 2.9143667e+10
A68: 19085 | B68: 26.46 | N68: 11.9 | O68: 11.5 | Q68: 19.4 | R68: 27.5 | S68: 13.3 | AQ68: 28.7 | AR68: 30.8 | BH68: 35.2 | BI68: 33.9 | BJ68: 37.4 | BK68: 42.6 | BM68: 30.1 | BO68: 26.4 | BS68: 30.8 | CB68: 21.8 | CG68: 64.5 | CJ68: 37.6 | CO68: 27.3 | CP68: 25.8 | CQ68: 22.9 | CR68: 21.3 | CS68: 40.9 | CU68: 16.4 | CW68: 28.5 | CX68: 28.5 | DI68: 22.1 | DX68: 37.9 | EY68: 43.6 | EZ68: 46.4 | FG68: 57.4 | FP68: 34 | FX68: 25.5 | FY68: 27.1 | GZ68: 16.5 | JZ68: 25.8 | KE68: 28.3 | KG68: 50.7 | KU68: 7.2362667e+10 | KV68: 42536000000 | KW68: 1.0335667e+10 | KX68: 3839000000 | LB68: 3976000000 | LG68: 1.4116667e+09 | LM68: 1.1086667e+09 | LS68: 3.2200333e+10 | LT68: 16081000000 | LX68: 6.9233333e+09 | MD68: 3359000000 | MG68: 5.8366667e+09 | MO68: 2.9826667e+10
A69: 19115 | B69: 26.47 | N69: 12 | O69: 11.7 | Q69: 19.5 | R69: 27.5 | S69: 13.3 | AQ69: 28.7 | AR69: 30.8 | BH69: 34.9 | BI69: 33.7 | BJ69: 37 | BK69: 41.9 | BM69: 30.7 | BO69: 26.3 | BS69: 31.9 | CB69: 21.8 | CG69: 64.2 | CJ69: 37.7 | CO69: 27.3 | CP69: 25.8 | CQ69: 23.1 | CR69: 21.9 | CS69: 40.5 | CU69: 16.3 | CW69: 28.3 | CX69: 29.3 | DI69: 22.2 | DX69: 37.3 | EY69: 43.6 | EZ69: 46.3 | FG69: 57.3 | FP69: 34 | FX69: 25.6 | FY69: 27.2 | GZ69: 16.5 | JZ69: 25.8 | KE69: 28.4 | KG69: 50.6 | KU69: 7.2362667e+10 | KV69: 42536000000 | KW69: 1.0335667e+10 | KX69: 3839000000 | LB69: 3976000000 | LG69: 1.4116667e+09 | LM69: 1.1086667e+09 | LS69: 3.2200333e+10 | LT69: 16081000000 | LX69: 6.9233333e+09 | MD69: 3359000000 | MG69: 5.8366667e+09 | MO69: 2.9826667e+10
A70: 19146 | B70: 26.53 | N70: 12 | O70: 11.8 | Q70: 19.5 | R70: 27.5 | S70: 13.4 | AQ70: 28.6 | AR70: 30.6 | BH70: 34.9 | BI70: 33.5 | BJ70: 36.4 | BK70: 41.7 | BM70: 31.1 | BO70: 26.8 | BS70: 32.2 | CB70: 21.7 | CG70: 65 | CJ70: 37.5 | CO70: 26.8 | CP70: 25.2 | CQ70: 23.4 | CR70: 25.4 | CS70: 40.3 | CU70: 16.3 | CW70: 27.2 | CX70: 28.4 | DI70: 22.4 | DX70: 37 | EY70: 43.5 | EZ70: 46.3 | FG70: 57.4 | FP70: 33.9 | FX70: 25.8 | FY70: 27.3 | GZ70: 16.8 | JZ70: 25.9 | KE70: 28.4 | KG70: 50.7 | KU70: 7.2362667e+10 | KV70: 42536000000 | KW70: 1.0335667e+10 | KX70: 3839000000 | LB70: 3976000000 | LG70: 1.4116667e+09 | LM70: 1.1086667e+09 | LS70: 3.2200333e+10 | LT70: 16081000000 | LX70: 6.9233333e+09 | MD70: 3359000000 | MG70: 5.8366667e+09 | MO70: 2.9826667e+10
A71: 19176 | B71: 26.68 | N71: 12.3 | O71: 12.3 | Q71: 19.5 | R71: 27.5 | S71: 13.4 | AQ71: 28.9 | AR71: 30.8 | BH71: 34.7 | BI71: 33.2 | BJ71: 35.8 | BK71: 40.4 | BM71: 31.1 | BO71: 26.9 | BS71: 32.1 | CB71: 21.7 | CG71: 75.3 | CJ71: 37.5 | CO71: 27.2 | CP71: 25.7 | CQ71: 23.4 | CR71: 23.4 | CS71: 38.6 | CU71: 16.7 | CW71: 28.3 | CX71: 29.7 | DI71: 22.5 | DX71: 37.9 | EY71: 43.5 | EZ71: 46.3 | FG71: 57.3 | FP71: 33.8 | FX71: 26 | FY71: 27.5 | GZ71: 16.9 | JZ71: 26 | KE71: 28.6 | KG71: 50.6 | KU71: 7.3184333e+10 | KV71: 42647000000 | KW71: 9.8223333e+09 | KX71: 3.2243333e+09 | LB71: 4031000000 | LG71: 1435000000 | LM71: 1132000000 | LS71: 3.2824667e+10 | LT71: 16392000000 | LX71: 7.0626667e+09 | MD71: 3435000000 | MG71: 5935000000 | MO71: 3.0537333e+10
A72: 19207 | B72: 26.69 | N72: 12.2 | O72: 12.3 | Q72: 19.6 | R72: 27.8 | S72: 13.4 | AQ72: 28.9 | AR72: 30.9 | BH72: 35.1 | BI72: 33.5 | BJ72: 35.6 | BK72: 40.3 | BM72: 32.8 | BO72: 28.4 | BS72: 34.5 | CB72: 21.5 | CG72: 71.1 | CJ72: 37.5 | CO72: 27.6 | CP72: 26.2 | CQ72: 24.1 | CR72: 22.5 | CS72: 39.4 | CU72: 17.1 | CW72: 29 | CX72: 31.2 | DI72: 22.4 | DX72: 38 | EY72: 43.4 | EZ72: 46.3 | FG72: 57.1 | FP72: 33.6 | FX72: 25.9 | FY72: 27.5 | GZ72: 16.9 | JZ72: 26 | KE72: 28.6 | KG72: 50.6 | KU72: 7.3184333e+10 | KV72: 42647000000 | KW72: 9.8223333e+09 | KX72: 3.2243333e+09 | LB72: 4031000000 | LG72: 1435000000 | LM72: 1132000000 | LS72: 3.2824667e+10 | LT72: 16392000000 | LX72: 7.0626667e+09 | MD72: 3435000000 | MG72: 5935000000 | MO72: 3.0537333e+10
A73: 19238 | B73: 26.63 | N73: 12.2 | O73: 12.3 | Q73: 19.6 | R73: 27.8 | S73: 13.4 | AQ73: 28.7 | AR73: 30.8 | BH73: 35 | BI73: 33.1 | BJ73: 35.5 | BK73: 40.1 | BM73: 31.9 | BO73: 28.3 | BS73: 32.6 | CB73: 21.4 | CG73: 70.1 | CJ73: 37.8 | CO73: 26.9 | CP73: 25.2 | CQ73: 24.7 | CR73: 21.6 | CS73: 39.1 | CU73: 17.7 | CW73: 27.3 | CX73: 30.4 | DI73: 22.2 | DX73: 38.8 | EY73: 43.3 | EZ73: 46.1 | FG73: 57.3 | FP73: 33.6 | FX73: 26 | FY73: 27.6 | GZ73: 16.9 | JZ73: 26 | KE73: 28.6 | KG73: 50.5 | KU73: 7.3184333e+10 | KV73: 42647000000 | KW73: 9.8223333e+09 | KX73: 3.2243333e+09 | LB73: 4031000000 | LG73: 1435000000 | LM73: 1132000000 | LS73: 3.2824667e+10 | LT73: 16392000000 | LX73: 7.0626667e+09 | MD73: 3435000000 | MG73: 5935000000 | MO73: 3.0537333e+10
A74: 19268 | B74: 26.69 | N74: 12.3 | O74: 12.2 | Q74: 19.7 | R74: 27.8 | S74: 13.4 | AQ74: 28.8 | AR74: 30.8 | BH74: 35 | BI74: 33.3 | BJ74: 35.1 | BK74: 39 | BM74: 32.4 | BO74: 28.2 | BS74: 33.5 | CB74: 21.1 | CG74: 71.3 | CJ74: 37.8 | CO74: 26.8 | CP74: 25 | CQ74: 25.2 | CR74: 23.9 | CS74: 37.2 | CU74: 18.4 | CW74: 26.3 | CX74: 29.6 | DI74: 22.1 | DX74: 37.9 | EY74: 43.1 | EZ74: 45.9 | FG74: 57 | FP74: 33.5 | FX74: 26.1 | FY74: 27.7 | GZ74: 16.9 | JZ74: 26 | KE74: 28.5 | KG74: 50.2 | KU74: 75890000000 | KV74: 44685000000 | KW74: 11241000000 | KX74: 4324000000 | LB74: 4.2263333e+09 | LG74: 1.5053333e+09 | LM74: 1.1853333e+09 | LS74: 3.3443667e+10 | LT74: 16431000000 | LX74: 7.4436667e+09 | MD74: 3.4796667e+09 | MG74: 6.0893333e+09 | MO74: 3.1205333e+10
A75: 19299 | B75: 26.69 | N75: 12.3 | O75: 12.2 | Q75: 19.7 | R75: 27.9 | S75: 13.5 | AQ75: 28.8 | AR75: 31.2 | BH75: 34.9 | BI75: 32.8 | BJ75: 34.6 | BK75: 37.9 | BM75: 31.8 | BO75: 28 | BS75: 32.5 | CB75: 21 | CG75: 72 | CJ75: 37.8 | CO75: 27.3 | CP75: 25.7 | CQ75: 25.3 | CR75: 24.8 | CS75: 37.8 | CU75: 18.6 | CW75: 27 | CX75: 30.3 | DI75: 22.3 | DX75: 37.2 | EY75: 43 | EZ75: 45.8 | FG75: 56.5 | FP75: 33.4 | FX75: 26.2 | FY75: 27.7 | GZ75: 16.9 | JZ75: 26.1 | KE75: 28.6 | KG75: 50.1 | KU75: 75890000000 | KV75: 44685000000 | KW75: 11241000000 | KX75: 4324000000 | LB75: 4.2263333e+09 | LG75: 1.5053333e+09 | LM75: 1.1853333e+09 | LS75: 3.3443667e+10 | LT75: 16431000000 | LX75: 7.4436667e+09 | MD75: 3.4796667e+09 | MG75: 6.0893333e+09 | MO75: 3.1205333e+10
A76: 19329 | B76: 26.71 | N76: 12.4 | O76: 12.2 | Q76: 19.8 | R76: 28 | S76: 13.5 | AQ76: 28.6 | AR76: 30.9 | BH76: 35 | BI76: 32.6 | BJ76: 34.5 | BK76: 37 | BM76: 32 | BO76: 28 | BS76: 32.2 | CB76: 20.9 | CG76: 69.1 | CJ76: 37.6 | CO76: 27 | CP76: 25.3 | CQ76: 24.5 | CR76: 25 | CS76: 38.8 | CU76: 17 | CW76: 26.8 | CX76: 29.4 | DI76: 22.3 | DX76: 36.1 | EY76: 43 | EZ76: 45.7 | FG76: 56.6 | FP76: 33.5 | FX76: 26.2 | FY76: 27.7 | GZ76: 17 | JZ76: 26.1 | KE76: 28.5 | KG76: 50 | KU76: 75890000000 | KV76: 44685000000 | KW76: 11241000000 | KX76: 4324000000 | LB76: 4.2263333e+09 | LG76: 1.5053333e+09 | LM76: 1.1853333e+09 | LS76: 3.3443667e+10 | LT76: 16431000000 | LX76: 7.4436667e+09 | MD76: 3.4796667e+09 | MG76: 6.0893333e+09 | MO76: 3.1205333e+10
A77: 19360 | B77: 26.64 | D77: 21.7 | L77: 22.1 | N77: 12.4 | O77: 12 | Q77: 19.8 | R77: 28.1 | S77: 13.6 | AQ77: 28.4 | AR77: 30.6 | BH77: 34.1 | BI77: 32 | BJ77: 33 | BK77: 35.8 | BM77: 32 | BO77: 28.6 | BS77: 32.8 | CB77: 20.8 | CG77: 71.9 | CJ77: 37.4 | CO77: 26.6 | CP77: 24.6 | CQ77: 24.1 | CR77: 25 | CS77: 38.8 | CU77: 16.4 | CW77: 25.9 | CX77: 28.2 | CZ77: 30.6 | DI77: 22 | DX77: 35.7 | EK77: 21.4 | EY77: 43 | EZ77: 45.8 | FG77: 56.7 | FP77: 33.5 | FX77: 26.3 | FY77: 27.8 | GA77: 46.3 | GC77: 46.3 | GF77: 28.7 | GZ77: 17 | JZ77: 26.1 | KE77: 28.5 | KG77: 50.1 | KU77: 7.7073333e+10 | KV77: 4.5234667e+10 | KW77: 1.1728667e+10 | KX77: 4847000000 | LB77: 4.1333333e+09 | LG77: 1565000000 | LM77: 1183000000 | LS77: 3.3505667e+10 | LT77: 16538000000 | LX77: 7195000000 | MD77: 3527000000 | MG77: 6.2456667e+09 | MO77: 3.1838667e+10
A78: 19391 | B78: 26.59 | D78: 21.8 | L78: 22.2 | N78: 12.4 | O78: 12 | Q78: 19.8 | R78: 28 | S78: 13.6 | AQ78: 28.3 | AR78: 30.2 | BH78: 33.3 | BI78: 31.3 | BJ78: 30 | BK78: 32.9 | BM78: 32.8 | BO78: 29.7 | BS78: 33.3 | CB78: 20.7 | CG78: 72.4 | CJ78: 37.2 | CO78: 26.8 | CP78: 24.9 | CQ78: 24.7 | CR78: 25.7 | CS78: 39.6 | CU78: 16.8 | CW78: 25.3 | CX78: 26.4 | CZ78: 29.8 | DI78: 22.1 | DX78: 35.3 | EK78: 21.4 | EY78: 43 | EZ78: 45.9 | FG78: 56.4 | FP78: 33.6 | FX78: 26.2 | FY78: 27.7 | GA78: 46.8 | GC78: 46.7 | GF78: 28.7 | GZ78: 17 | JZ78: 26.1 | KE78: 28.4 | KG78: 50 | KU78: 7.7073333e+10 | KV78: 4.5234667e+10 | KW78: 1.1728667e+10 | KX78: 4847000000 | LB78: 4.1333333e+09 | LG78: 1565000000 | LM78: 1183000000 | LS78: 3.3505667e+10 | LT78: 16538000000 | LX78: 7195000000 | MD78: 3527000000 | MG78: 6.2456667e+09 | MO78: 3.1838667e+10
A79: 19419 | B79: 26.63 | D79: 21.8 | L79: 22.3 | N79: 12.5 | O79: 12.3 | Q79: 19.9 | R79: 28 | S79: 13.7 | AQ79: 28.3 | AR79: 30.3 | BH79: 33.1 | BI79: 31.2 | BJ79: 29 | BK79: 31.8 | BM79: 33.7 | BO79: 30.5 | BS79: 34.1 | CB79: 20.7 | CG79: 73.8 | CJ79: 37.2 | CO79: 26.7 | CP79: 24.7 | CQ79: 24.7 | CR79: 25.7 | CS79: 39.6 | CU79: 16.9 | CW79: 25 | CX79: 24.5 | CZ79: 28.9 | DI79: 22.2 | DX79: 35.4 | EK79: 21.5 | EY79: 43 | EZ79: 45.9 | FG79: 56.6 | FP79: 33.5 | FX79: 26.3 | FY79: 27.8 | GA79: 46.9 | GC79: 46.9 | GF79: 28.4 | GZ79: 17 | JZ79: 26.2 | KE79: 28.5 | KG79: 50.1 | KU79: 7.7073333e+10 | KV79: 4.5234667e+10 | KW79: 1.1728667e+10 | KX79: 4847000000 | LB79: 4.1333333e+09 | LG79: 1565000000 | LM79: 1183000000 | LS79: 3.3505667e+10 | LT79: 16538000000 | LX79: 7195000000 | MD79: 3527000000 | MG79: 6.2456667e+09 | MO79: 3.1838667e+10
A80: 19450 | B80: 26.69 | D80: 21.9 | L80: 22.4 | N80: 12.5 | O80: 12.4 | Q80: 19.9 | R80: 28.1 | S80: 13.7 | AQ80: 28.1 | AR80: 30.1 | BH80: 32.8 | BI80: 30.8 | BJ80: 28.4 | BK80: 30.7 | BM80: 33.7 | BO80: 31.2 | BS80: 33.6 | CB80: 20.8 | CG80: 74.7 | CJ80: 37.2 | CO80: 26 | CP80: 23.9 | CQ80: 24.5 | CR80: 25.2 | CS80: 39.7 | CU80: 16.8 | CW80: 23.6 | CX80: 22.7 | CZ80: 29.6 | DI80: 22.7 | DX80: 35.8 | EK80: 21.4 | EY80: 43.1 | EZ80: 45.9 | FG80: 56.6 | FP80: 33.6 | FX80: 26.4 | FY80: 27.8 | GA80: 47.3 | GC80: 47.3 | GF80: 28.3 | GZ80: 17.1 | JZ80: 26.3 | KE80: 28.5 | KG80: 50.1 | KU80: 7.7653333e+10 | KV80: 4.5191333e+10 | KW80: 11673000000 | KX80: 4742000000 | LB80: 4.2013333e+09 | LG80: 1.5643333e+09 | LM80: 1.1653333e+09 | LS80: 3.3518667e+10 | LT80: 16444000000 | LX80: 7.2336667e+09 | MD80: 3.5593333e+09 | MG80: 6.2816667e+09 | MO80: 32462000000
A81: 19480 | B81: 26.7 | D81: 21.9 | L81: 22.4 | N81: 12.6 | O81: 12.5 | Q81: 19.9 | R81: 28.1 | S81: 13.7 | AQ81: 28.2 | AR81: 30.1 | BH81: 33.2 | BI81: 31.2 | BJ81: 27.8 | BK81: 29.9 | BM81: 35 | BO81: 32.9 | BS81: 35.1 | CB81: 20.8 | CG81: 75.6 | CJ81: 37 | CO81: 25.4 | CP81: 22.9 | CQ81: 24.5 | CR81: 25 | CS81: 39.5 | CU81: 17 | CW81: 21.8 | CX81: 20.6 | CZ81: 26 | DI81: 22.7 | DX81: 35.8 | EK81: 21.4 | EY81: 43.2 | EZ81: 45.9 | FG81: 56.7 | FP81: 33.7 | FX81: 26.4 | FY81: 27.9 | GA81: 47.5 | GC81: 47.5 | GF81: 27.5 | GZ81: 17.2 | JZ81: 26.4 | KE81: 28.5 | KG81: 50.1 | KU81: 7.7653333e+10 | KV81: 4.5191333e+10 | KW81: 11673000000 | KX81: 4742000000 | LB81: 4.2013333e+09 | LG81: 1.5643333e+09 | LM81: 1.1653333e+09 | LS81: 3.3518667e+10 | LT81: 16444000000 | LX81: 7.2336667e+09 | MD81: 3.5593333e+09 | MG81: 6.2816667e+09 | MO81: 32462000000
A82: 19511 | B82: 26.77 | D82: 21.9 | L82: 22.5 | N82: 12.6 | O82: 12.5 | Q82: 19.9 | R82: 28 | S82: 13.8 | AQ82: 28.4 | AR82: 30.4 | BH82: 33.3 | BI82: 31.4 | BJ82: 27.6 | BK82: 28.9 | BM82: 35.8 | BO82: 34.9 | BS82: 34.5 | CB82: 20.8 | CG82: 76.5 | CJ82: 37 | CO82: 26.6 | CP82: 24.6 | CQ82: 24.4 | CR82: 25.3 | CS82: 39.6 | CU82: 18.3 | CW82: 24.3 | CX82: 18.1 | CZ82: 41 | DI82: 22.7 | DX82: 35.7 | EK82: 21.5 | EY82: 43.3 | EZ82: 45.9 | FG82: 56.6 | FP82: 33.8 | FX82: 26.5 | FY82: 27.9 | GA82: 47.6 | GC82: 47.5 | GF82: 26.9 | GZ82: 17.3 | JZ82: 26.4 | KE82: 28.6 | KG82: 50.2 | KU82: 7.7653333e+10 | KV82: 4.5191333e+10 | KW82: 11673000000 | KX82: 4742000000 | LB82: 4.2013333e+09 | LG82: 1.5643333e+09 | LM82: 1.1653333e+09 | LS82: 3.3518667e+10 | LT82: 16444000000 | LX82: 7.2336667e+09 | MD82: 3.5593333e+09 | MG82: 6.2816667e+09 | MO82: 32462000000
A83: 19541 | B83: 26.79 | D83: 22 | L83: 22.5 | N83: 12.8 | O83: 12.7 | Q83: 19.9 | R83: 27.9 | S83: 13.8 | AQ83: 28.2 | AR83: 30.1 | BH83: 33.3 | BI83: 31.5 | BJ83: 27 | BK83: 27.8 | BM83: 36.5 | BO83: 35.3 | BS83: 35.1 | CB83: 20.9 | CG83: 74.7 | CJ83: 37.1 | CO83: 25.8 | CP83: 23.5 | CQ83: 24 | CR83: 25.5 | CS83: 40 | CU83: 17 | CW83: 22.7 | CX83: 18.4 | CZ83: 32 | DI83: 22.9 | DX83: 35.8 | EK83: 21.5 | EY83: 43.3 | EZ83: 46 | FG83: 56.6 | FP83: 33.8 | FX83: 26.6 | FY83: 28 | GA83: 48.4 | GC83: 48.4 | GF83: 26.5 | GZ83: 17.3 | JZ83: 26.4 | KE83: 28.6 | KG83: 50.1 | KU83: 7.7888667e+10 | KV83: 4.4806667e+10 | KW83: 1.1525667e+10 | KX83: 4.5856667e+09 | LB83: 4217000000 | LG83: 1.5646667e+09 | LM83: 1.1583333e+09 | LS83: 3.3280667e+10 | LT83: 1.6361333e+10 | LX83: 7065000000 | MD83: 3.6736667e+09 | MG83: 6181000000 | MO83: 3.3082333e+10
A84: 19572 | B84: 26.85 | D84: 22 | L84: 22.6 | N84: 12.7 | O84: 12.7 | Q84: 20 | R84: 27.9 | S84: 13.9 | AQ84: 28.3 | AR84: 30.3 | BH84: 33.6 | BI84: 31.8 | BJ84: 28.5 | BK84: 28.8 | BM84: 36.2 | BO84: 35.8 | BS84: 33.8 | CB84: 20.8 | CG84: 71.8 | CJ84: 37.1 | CO84: 26 | CP84: 23.5 | CQ84: 23.6 | CR84: 25 | CS84: 40.3 | CU84: 16.2 | CW84: 23.3 | CX84: 17.9 | CZ84: 30.5 | DI84: 23.1 | DX84: 35.7 | EK84: 21.5 | EY84: 43.2 | EZ84: 46 | FG84: 56.5 | FP84: 33.8 | FX84: 26.7 | FY84: 28.1 | GA84: 48.8 | GC84: 48.7 | GF84: 26 | GZ84: 17.4 | JZ84: 26.5 | KE84: 28.6 | KG84: 50.1 | KU84: 7.7888667e+10 | KV84: 4.4806667e+10 | KW84: 1.1525667e+10 | KX84: 4.5856667e+09 | LB84: 4217000000 | LG84: 1.5646667e+09 | LM84: 1.1583333e+09 | LS84: 3.3280667e+10 | LT84: 1.6361333e+10 | LX84: 7065000000 | MD84: 3.6736667e+09 | MG84: 6181000000 | MO84: 3.3082333e+10
A85: 19603 | B85: 26.89 | D85: 22.1 | L85: 22.7 | N85: 12.7 | O85: 12.7 | Q85: 20 | R85: 27.9 | S85: 13.9 | AQ85: 28.4 | AR85: 30.4 | BH85: 33.4 | BI85: 31.5 | BJ85: 28.2 | BK85: 28.2 | BM85: 36 | BO85: 35.9 | BS85: 34 | CB85: 20.8 | CG85: 72.7 | CJ85: 37 | CO85: 25.6 | CP85: 22.9 | CQ85: 22.8 | CR85: 23.4 | CS85: 40 | CU85: 15.7 | CW85: 22.6 | CX85: 19.3 | CZ85: 28.1 | DI85: 23.2 | DX85: 35.6 | EK85: 21.6 | EY85: 43.2 | EZ85: 45.9 | FG85: 56.6 | FP85: 33.9 | FX85: 26.7 | FY85: 28 | GA85: 49.5 | GC85: 49.4 | GF85: 25.5 | GZ85: 17.5 | JZ85: 26.5 | KE85: 28.6 | KG85: 50.1 | KU85: 7.7888667e+10 | KV85: 4.4806667e+10 | KW85: 1.1525667e+10 | KX85: 4.5856667e+09 | LB85: 4217000000 | LG85: 1.5646667e+09 | LM85: 1.1583333e+09 | LS85: 3.3280667e+10 | LT85: 1.6361333e+10 | LX85: 7065000000 | MD85: 3.6736667e+09 | MG85: 6181000000 | MO85: 3.3082333e+10
A86: 19633 | B86: 26.95 | D86: 22.2 | L86: 22.7 | N86: 12.7 | O86: 12.8 | Q86: 20 | R86: 28 | S86: 13.9 | AQ86: 28.4 | AR86: 30.4 | BH86: 33.3 | BI86: 31.3 | BJ86: 28 | BK86: 28 | BM86: 35.5 | BO86: 35.6 | BS86: 33.2 | CB86: 20.7 | CG86: 72.7 | CJ86: 36.9 | CO86: 25.8 | CP86: 23.2 | CQ86: 22.6 | CR86: 25.3 | CS86: 39.9 | CU86: 15.2 | CW86: 23.3 | CX86: 20.3 | CZ86: 29.4 | DI86: 23.3 | DX86: 35.4 | EK86: 21.7 | EY86: 43.2 | EZ86: 45.9 | FG86: 56.5 | FP86: 34 | FX86: 26.6 | FY86: 27.9 | GA86: 48.1 | GC86: 48.1 | GF86: 25.2 | GZ86: 17.5 | JZ86: 26.6 | KE86: 28.7 | KG86: 50.1 | KU86: 77704000000 | KV86: 4.4547333e+10 | KW86: 1.1227667e+10 | KX86: 4.2873333e+09 | LB86: 4227000000 | LG86: 1.5626667e+09 | LM86: 1.1503333e+09 | LS86: 3.3319667e+10 | LT86: 16371000000 | LX86: 6934000000 | MD86: 3.6976667e+09 | MG86: 6317000000 | MO86: 3.3156667e+10
A87: 19664 | B87: 26.85 | D87: 22.2 | L87: 22.7 | N87: 12.7 | O87: 12.9 | Q87: 20.1 | R87: 28 | S87: 14 | AQ87: 28.1 | AR87: 30.2 | BH87: 32.7 | BI87: 30.7 | BJ87: 27.4 | BK87: 27.6 | BM87: 34.8 | BO87: 33.2 | BS87: 34.4 | CB87: 20.6 | CG87: 68.6 | CJ87: 37 | CO87: 25.3 | CP87: 22.6 | CQ87: 23.4 | CR87: 25.8 | CS87: 39.9 | CU87: 16.3 | CW87: 21.7 | CX87: 19.5 | CZ87: 28.2 | DI87: 23.4 | DX87: 35.8 | EK87: 21.7 | EY87: 43.3 | EZ87: 45.9 | FG87: 56.6 | FP87: 34.1 | FX87: 26.3 | FY87: 27.7 | GA87: 45.2 | GC87: 45.1 | GF87: 24.8 | GZ87: 17.6 | JZ87: 26.6 | KE87: 28.6 | KG87: 50.1 | KU87: 77704000000 | KV87: 4.4547333e+10 | KW87: 1.1227667e+10 | KX87: 4.2873333e+09 | LB87: 4227000000 | LG87: 1.5626667e+09 | LM87: 1.1503333e+09 | LS87: 3.3319667e+10 | LT87: 16371000000 | LX87: 6934000000 | MD87: 3.6976667e+09 | MG87: 6317000000 | MO87: 3.3156667e+10
A88: 19694 | B88: 26.87 | D88: 22.3 | L88: 22.7 | N88: 12.6 | O88: 12.6 | Q88: 20 | R88: 27.9 | S88: 14 | AQ88: 28.3 | AR88: 30.3 | BH88: 33.4 | BI88: 31.5 | BJ88: 27.6 | BK88: 27.4 | BM88: 37.2 | BO88: 34.7 | BS88: 36.6 | CB88: 20.6 | CG88: 69.2 | CJ88: 36.9 | CO88: 25.5 | CP88: 22.9 | CQ88: 24.3 | CR88: 25.3 | CS88: 39.9 | CU88: 17.8 | CW88: 22 | CX88: 19 | CZ88: 32.7 | DI88: 23.5 | DX88: 35.3 | EK88: 21.8 | EY88: 43.2 | EZ88: 45.9 | FG88: 56.6 | FP88: 34 | FX88: 26.2 | FY88: 27.4 | GA88: 45 | GC88: 45 | GF88: 24.7 | GZ88: 17.6 | JZ88: 26.5 | KE88: 28.6 | KG88: 50 | KU88: 77704000000 | KV88: 4.4547333e+10 | KW88: 1.1227667e+10 | KX88: 4.2873333e+09 | LB88: 4227000000 | LG88: 1.5626667e+09 | LM88: 1.1503333e+09 | LS88: 3.3319667e+10 | LT88: 16371000000 | LX88: 6934000000 | MD88: 3.6976667e+09 | MG88: 6317000000 | MO88: 3.3156667e+10
... A112: 20424 | B112: 26.87 | D112: 22.9 | L112: 23.3 | N112: 12.9 | O112: 13.2 | Q112: 20.8 | R112: 28.5 | S112: 14.8 | AQ112: 27.6 | AR112: 29.3 | BH112: 29.3 | BI112: 27.3 | BJ112: 26.3 | BK112: 25.6 | BM112: 28.9 | BO112: 25.2 | BS112: 29.8 | CB112: 20.5 | CG112: 68.3 | CJ112: 36.5 | CO112: 26 | CP112: 23.3 | CQ112: 23.9 | CR112: 23.4 | CS112: 38.7 | CU112: 19.3 | CW112: 23.3 | CX112: 20.3 | CZ112: 28 | DI112: 24.1 | DX112: 31.7 | EK112: 22.3 | EY112: 43.1 | EZ112: 45.2 | FG112: 55.7 | FP112: 35.1 | FX112: 25.8 | FY112: 26.7 | GA112: 44.5 | GC112: 44.5 | GF112: 20.5 | GZ112: 18.6 | JZ112: 26.8 | KE112: 28.4 | KG112: 49.3 | KU112: 88213000000 | KV112: 50153000000 | KW112: 1.3804333e+10 | KX112: 5.9013333e+09 | LB112: 4.7733333e+09 | LG112: 1.8336667e+09 | LM112: 1296000000 | LS112: 3.6348667e+10 | LT112: 17557000000 | LX112: 7.6106667e+09 | MD112: 4.2903333e+09 | MG112: 6891000000 | MO112: 3.8059667e+10
A113: 20455 | B113: 26.83 | D113: 22.9 | L113: 23.4 | N113: 13 | O113: 13.2 | Q113: 20.9 | R113: 28.6 | S113: 14.8 | AQ113: 27.5 | AR113: 29.1 | BH113: 28.7 | BI113: 26.7 | BJ113: 26 | BK113: 25.5 | BM113: 27.2 | BO113: 24.1 | BS113: 28.6 | CB113: 20.5 | CG113: 70.9 | CJ113: 36.6 | CO113: 26.1 | CP113: 23.5 | CQ113: 23.9 | CR113: 23.8 | CS113: 40.1 | CU113: 18.9 | CW113: 23.3 | CX113: 21.3 | CZ113: 32 | DI113: 24 | DX113: 31.8 | EK113: 22.3 | EY113: 43.2 | EZ113: 45.3 | FG113: 55.8 | FP113: 35.3 | FX113: 25.8 | FY113: 26.5 | GA113: 44.5 | GC113: 44.4 | GF113: 20.1 | GZ113: 18.6 | HC113: 16.1 | JZ113: 26.7 | KE113: 28.3 | KG113: 49.4 | KJ113: 33.6 | KU113: 8.8718667e+10 | KV113: 50072000000 | KW113: 1.3224667e+10 | KX113: 5.2876667e+09 | LB113: 4.8236667e+09 | LG113: 1.8366667e+09 | LM113: 1.2763333e+09 | LS113: 36847000000 | LT113: 17805000000 | LX113: 7665000000 | MD113: 4354000000 | MG113: 7.0233333e+09 | MO113: 3.8646667e+10
A114: 20486 | B114: 26.86 | D114: 22.9 | L114: 23.4 | N114: 13 | O114: 13.3 | Q114: 20.8 | R114: 28.5 | S114: 14.8 | AQ114: 27.5 | AR114: 29.1 | BH114: 28.8 | BI114: 26.8 | BJ114: 25.7 | BK114: 25.3 | BM114: 28.1 | BO114: 23.8 | BS114: 30.1 | CB114: 20.4 | CG114: 65.1 | CJ114: 36.6 | CO114: 26.3 | CP114: 23.8 | CQ114: 24 | CR114: 23.7 | CS114: 40.7 | CU114: 19.1 | CW114: 23.7 | CX114: 22.2 | CZ114: 32.2 | DI114: 24.1 | DX114: 31.9 | EK114: 22.3 | EY114: 43.5 | EZ114: 45.5 | FG114: 56 | FP114: 35.6 | FX114: 25.8 | FY114: 26.6 | GA114: 44.7 | GC114: 44.6 | GF114: 20.5 | GZ114: 18.7 | HC114: 16 | JZ114: 26.8 | KE114: 28.4 | KG114: 49.6 | KJ114: 33.6 | KU114: 8.8718667e+10 | KV114: 50072000000 | KW114: 1.3224667e+10 | KX114: 5.2876667e+09 | LB114: 4.8236667e+09 | LG114: 1.8366667e+09 | LM114: 1.2763333e+09 | LS114: 36847000000 | LT114: 17805000000 | LX114: 7665000000 | MD114: 4354000000 | MG114: 7.0233333e+09 | MO114: 3.8646667e+10
A115: 20515 | B115: 26.89 | D115: 22.9 | L115: 23.4 | N115: 13.1 | O115: 13.4 | Q115: 20.9 | R115: 28.6 | S115: 14.8 | AQ115: 27.5 | AR115: 29.1 | BH115: 28.5 | BI115: 26.7 | BJ115: 25.5 | BK115: 25.1 | BM115: 27.8 | BO115: 23.4 | BS115: 29.6 | CB115: 20.5 | CG115: 65.1 | CJ115: 36.7 | CO115: 26.6 | CP115: 24.1 | CQ115: 23.6 | CR115: 23.5 | CS115: 39.6 | CU115: 18.7 | CW115: 25 | CX115: 23.6 | CZ115: 39.9 | DI115: 24.6 | DX115: 32 | EK115: 22.4 | EY115: 43.5 | EZ115: 45.6 | FG115: 56 | FP115: 35.8 | FX115: 25.8 | FY115: 26.6 | GA115: 45.3 | GC115: 45.2 | GF115: 20 | GZ115: 18.7 | HC115: 16.2 | JZ115: 26.8 | KE115: 28.5 | KG115: 49.6 | KJ115: 33.7 | KU115: 8.8718667e+10 | KV115: 50072000000 | KW115: 1.3224667e+10 | KX115: 5.2876667e+09 | LB115: 4.8236667e+09 | LG115: 1.8366667e+09 | LM115: 1.2763333e+09 | LS115: 36847000000 | LT115: 17805000000 | LX115: 7665000000 | MD115: 4354000000 | MG115: 7.0233333e+09 | MO115: 3.8646667e+10
A116: 20546 | B116: 26.93 | D116: 22.9 | L116: 23.5 | N116: 13.1 | O116: 13.5 | Q116: 20.9 | R116: 28.6 | S116: 14.8 | AQ116: 27.6 | AR116: 29.2 | BH116: 28.6 | BI116: 26.9 | BJ116: 25.5 | BK116: 25.1 | BM116: 28.6 | BO116: 23.5 | BS116: 31.1 | CB116: 20.4 | CG116: 65.3 | CJ116: 36.8 | CO116: 26.6 | CP116: 24.1 | CQ116: 23.3 | CR116: 23.7 | CS116: 37.8 | CU116: 18.3 | CW116: 25.1 | CX116: 26.3 | CZ116: 31.6 | DI116: 24.6 | DX116: 32.2 | EK116: 22.4 | EY116: 43.6 | EZ116: 45.5 | FG116: 56 | FP116: 36.1 | FX116: 25.8 | FY116: 26.6 | GA116: 45.1 | GC116: 45 | GF116: 20 | GZ116: 18.8 | HC116: 16.2 | JZ116: 26.9 | KE116: 28.5 | KG116: 49.6 | KJ116: 33.7 | KU116: 8.9611333e+10 | KV116: 5.0370333e+10 | KW116: 13273000000 | KX116: 5.0866667e+09 | LB116: 4.9926667e+09 | LG116: 1.8933333e+09 | LM116: 1.3003333e+09 | LS116: 37097000000 | LT116: 17949000000 | LX116: 7.7446667e+09 | MD116: 4.3913333e+09 | MG116: 7.0123333e+09 | MO116: 39241000000
A117: 20576 | B117: 27.03 | D117: 22.9 | L117: 23.6 | N117: 13.2 | O117: 13.7 | Q117: 20.9 | R117: 28.6 | S117: 14.9 | AQ117: 27.8 | AR117: 29.4 | BH117: 28.9 | BI117: 27.2 | BJ117: 25.8 | BK117: 25 | BM117: 28.7 | BO117: 23.4 | BS117: 31.7 | CB117: 20.3 | CG117: 65.7 | CJ117: 37.7 | CO117: 26.9 | CP117: 24.4 | CQ117: 24 | CR117: 23.6 | CS117: 40.6 | CU117: 19.3 | CW117: 24.9 | CX117: 28.5 | CZ117: 25.3 | DI117: 24.8 | DX117: 32.8 | EK117: 22.5 | EY117: 43.6 | EZ117: 45.7 | FG117: 55.8 | FP117: 36 | FX117: 26 | FY117: 26.8 | GA117: 45.4 | GC117: 45.3 | GF117: 20.6 | GZ117: 18.8 | HC117: 16.2 | JZ117: 27 | KE117: 28.6 | KG117: 49.6 | KJ117: 33.8 | KU117: 8.9611333e+10 | KV117: 5.0370333e+10 | KW117: 13273000000 | KX117: 5.0866667e+09 | LB117: 4.9926667e+09 | LG117: 1.8933333e+09 | LM117: 1.3003333e+09 | LS117: 37097000000 | LT117: 17949000000 | LX117: 7.7446667e+09 | MD117: 4.3913333e+09 | MG117: 7.0123333e+09 | MO117: 39241000000
A118: 20607 | B118: 27.15 | D118: 23.1 | L118: 23.6 | N118: 13.3 | O118: 13.8 | Q118: 20.9 | R118: 28.6 | S118: 14.8 | AQ118: 28.1 | AR118: 29.9 | BH118: 29.2 | BI118: 27.6 | BJ118: 25.9 | BK118: 25 | BM118: 29.6 | BO118: 23.7 | BS118: 33.5 | CB118: 20.3 | CG118: 64.9 | CJ118: 37.8 | CO118: 28.4 | CP118: 26.6 | CQ118: 24.4 | CR118: 23.4 | CS118: 40.5 | CU118: 20.5 | CW118: 28.3 | CX118: 30.3 | CZ118: 34.9 | DI118: 25.1 | DX118: 32.9 | EK118: 22.5 | EY118: 43.6 | EZ118: 45.9 | FG118: 55.7 | FP118: 36.1 | FX118: 26 | FY118: 26.7 | GA118: 45.4 | GC118: 45.3 | GF118: 20.2 | GZ118: 18.8 | HC118: 16.3 | JZ118: 27 | KE118: 28.7 | KG118: 49.6 | KJ118: 33.8 | KU118: 8.9611333e+10 | KV118: 5.0370333e+10 | KW118: 13273000000 | KX118: 5.0866667e+09 | LB118: 4.9926667e+09 | LG118: 1.8933333e+09 | LM118: 1.3003333e+09 | LS118: 37097000000 | LT118: 17949000000 | LX118: 7.7446667e+09 | MD118: 4.3913333e+09 | MG118: 7.0123333e+09 | MO118: 39241000000
A119: 20637 | B119: 27.29 | D119: 23.2 | L119: 23.7 | N119: 13.3 | O119: 13.8 | Q119: 20.9 | R119: 28.6 | S119: 14.9 | AQ119: 28.4 | AR119: 30.1 | BH119: 29.4 | BI119: 27.7 | BJ119: 26.2 | BK119: 25.2 | BM119: 29.6 | BO119: 24 | BS119: 33.3 | CB119: 20.3 | CG119: 62.2 | CJ119: 37.9 | CO119: 29.3 | CP119: 27.8 | CQ119: 24.9 | CR119: 22.9 | CS119: 38.9 | CU119: 21.3 | CW119: 31.9 | CX119: 39.2 | CZ119: 33.5 | DI119: 25.7 | DX119: 33 | EK119: 22.5 | EY119: 43.8 | EZ119: 46.1 | FG119: 56 | FP119: 36.5 | FX119: 26.2 | FY119: 27 | GA119: 45.7 | GC119: 45.7 | GF119: 20.5 | GZ119: 18.9 | HC119: 16.3 | JZ119: 27.1 | KE119: 28.9 | KG119: 49.8 | KJ119: 33.9 | KU119: 9.0691667e+10 | KV119: 5.0705667e+10 | KW119: 1.3228333e+10 | KX119: 5.0516667e+09 | LB119: 4935000000 | LG119: 1.9073333e+09 | LM119: 1.3343333e+09 | LS119: 3.7477333e+10 | LT119: 18141000000 | LX119: 7882000000 | MD119: 4423000000 | MG119: 7031000000 | MO119: 39986000000
A120: 20668 | B120: 27.31 | D120: 23.3 | L120: 23.7 | N120: 13.3 | O120: 13.8 | Q120: 21 | R120: 28.6 | S120: 14.9 | AQ120: 28.2 | AR120: 29.9 | BH120: 29.8 | BI120: 28.2 | BJ120: 27.3 | BK120: 25.6 | BM120: 30 | BO120: 24.4 | BS120: 33.9 | CB120: 20.3 | CG120: 59.7 | CJ120: 37.8 | CO120: 27.6 | CP120: 25.4 | CQ120: 24.1 | CR120: 23.4 | CS120: 39.3 | CU120: 20.5 | CW120: 27.1 | CX120: 28.4 | CZ120: 32.7 | DI120: 25.8 | DX120: 33 | EK120: 22.6 | EY120: 43.9 | EZ120: 46.1 | FG120: 56 | FP120: 36.6 | FX120: 26.3 | FY120: 27.1 | GA120: 46.1 | GC120: 46.1 | GF120: 20.8 | GZ120: 19 | HC120: 16.4 | JZ120: 27.2 | KE120: 28.9 | KG120: 49.8 | KJ120: 34 | KU120: 9.0691667e+10 | KV120: 5.0705667e+10 | KW120: 1.3228333e+10 | KX120: 5.0516667e+09 | LB120: 4935000000 | LG120: 1.9073333e+09 | LM120: 1.3343333e+09 | LS120: 3.7477333e+10 | LT120: 18141000000 | LX120: 7882000000 | MD120: 4423000000 | MG120: 7031000000 | MO120: 39986000000
A121: 20699 | B121: 27.35 | D121: 23.3 | L121: 23.7 | N121: 13.3 | O121: 13.8 | Q121: 21 | R121: 28.6 | S121: 14.9 | AQ121: 28.2 | AR121: 29.9 | BH121: 30.1 | BI121: 28.6 | BJ121: 28.5 | BK121: 26 | BM121: 30.2 | BO121: 24.8 | BS121: 34.5 | CB121: 20.4 | CG121: 58.9 | CJ121: 37.8 | CO121: 27.3 | CP121: 25 | CQ121: 25.2 | CR121: 25.7 | CS121: 39.9 | CU121: 20.9 | CW121: 24.5 | CX121: 24.3 | CZ121: 28.8 | DI121: 26.3 | DX121: 32.9 | EK121: 22.7 | EY121: 44 | EZ121: 46.2 | FG121: 56.2 | FP121: 37.1 | FX121: 26.4 | FY121: 27.2 | GA121: 46.3 | GC121: 46.2 | GF121: 20.8 | GZ121: 19.1 | HC121: 16.5 | JZ121: 27.2 | KE121: 28.9 | KG121: 49.9 | KJ121: 34.1 | KU121: 9.0691667e+10 | KV121: 5.0705667e+10 | KW121: 1.3228333e+10 | KX121: 5.0516667e+09 | LB121: 4935000000 | LG121: 1.9073333e+09 | LM121: 1.3343333e+09 | LS121: 3.7477333e+10 | LT121: 18141000000 | LX121: 7882000000 | MD121: 4423000000 | MG121: 7031000000 | MO121: 39986000000
A122: 20729 | B122: 27.51 | D122: 23.3 | L122: 23.8 | N122: 13.5 | O122: 13.9 | Q122: 20.9 | R122: 28.5 | S122: 14.9 | AQ122: 28.3 | AR122: 30 | BH122: 30.3 | BI122: 29 | BJ122: 28.7 | BK122: 26.3 | BM122: 30.8 | BO122: 25.8 | BS122: 34.5 | CB122: 20.4 | CG122: 58.8 | CJ122: 37.9 | CO122: 27.1 | CP122: 24.7 | CQ122: 25.3 | CR122: 25.6 | CS122: 39.7 | CU122: 21.2 | CW122: 23.9 | CX122: 22.5 | CZ122: 30.8 | DI122: 26.4 | DX122: 33 | EK122: 22.8 | EY122: 44 | EZ122: 46.2 | FG122: 56 | FP122: 37.1 | FX122: 27 | FY122: 27.9 | GA122: 49.3 | GC122: 49.2 | GF122: 21.4 | GZ122: 19.1 | HC122: 16.5 | JZ122: 27.4 | KE122: 29.1 | KG122: 50 | KJ122: 34.3 | KU122: 9.2481667e+10 | KV122: 5.1724333e+10 | KW122: 1.3832333e+10 | KX122: 5522000000 | LB122: 5.0003333e+09 | LG122: 1.9473333e+09 | LM122: 1.3626667e+09 | LS122: 37892000000 | LT122: 1.8326333e+10 | LX122: 7905000000 | MD122: 4.5516667e+09 | MG122: 7109000000 | MO122: 4.0757333e+10
A123: 20760 | B123: 27.51 | D123: 23.3 | L123: 23.9 | N123: 13.6 | O123: 13.9 | Q123: 20.9 | R123: 28.5 | S123: 14.9 | AQ123: 28.4 | AR123: 30.1 | BH123: 30.2 | BI123: 28.9 | BJ123: 28 | BK123: 26.1 | BM123: 30.8 | BO123: 26.5 | BS123: 33.9 | CB123: 20.4 | CG123: 58.4 | CJ123: 37.9 | CO123: 27.5 | CP123: 25.4 | CQ123: 25.3 | CR123: 26.1 | CS123: 40.3 | CU123: 20.7 | CW123: 25.5 | CX123: 22.5 | CZ123: 32.3 | DI123: 26.5 | DX123: 33.4 | EK123: 22.8 | EY123: 44.1 | EZ123: 46.2 | FG123: 56.2 | FP123: 37 | FX123: 26.9 | FY123: 27.8 | GA123: 47.5 | GC123: 47.4 | GF123: 21.5 | GZ123: 19.1 | HC123: 16.6 | JZ123: 27.4 | KE123: 29.1 | KG123: 50.1 | KJ123: 34.3 | KU123: 9.2481667e+10 | KV123: 5.1724333e+10 | KW123: 1.3832333e+10 | KX123: 5522000000 | LB123: 5.0003333e+09 | LG123: 1.9473333e+09 | LM123: 1.3626667e+09 | LS123: 37892000000 | LT123: 1.8326333e+10 | LX123: 7905000000 | MD123: 4.5516667e+09 | MG123: 7109000000 | MO123: 4.0757333e+10
A124: 20790 | B124: 27.63 | D124: 23.5 | L124: 24 | N124: 13.7 | O124: 13.8 | Q124: 21 | R124: 28.6 | S124: 14.9 | AQ124: 28.5 | AR124: 30.1 | BH124: 30.3 | BI124: 29 | BJ124: 27.5 | BK124: 26 | BM124: 31.7 | BO124: 27.1 | BS124: 34.3 | CB124: 20.5 | CG124: 57.8 | CJ124: 38.1 | CO124: 27.6 | CP124: 25.5 | CQ124: 25.6 | CR124: 26.8 | CS124: 41.1 | CU124: 20.3 | CW124: 25.9 | CX124: 22.8 | CZ124: 35.2 | DI124: 26.4 | DX124: 33.4 | EK124: 22.9 | EY124: 44.3 | EZ124: 46.3 | FG124: 56.4 | FP124: 37.1 | FX124: 27 | FY124: 27.9 | GA124: 48.1 | GC124: 48.1 | GF124: 21.7 | GZ124: 19.2 | HC124: 16.6 | JZ124: 27.5 | KE124: 29.2 | KG124: 50.2 | KJ124: 34.4 | KU124: 9.2481667e+10 | KV124: 5.1724333e+10 | KW124: 1.3832333e+10 | KX124: 5522000000 | LB124: 5.0003333e+09 | LG124: 1.9473333e+09 | LM124: 1.3626667e+09 | LS124: 37892000000 | LT124: 1.8326333e+10 | LX124: 7905000000 | MD124: 4.5516667e+09 | MG124: 7109000000 | MO124: 4.0757333e+10
A125: 20821 | B125: 27.67 | D125: 23.5 | L125: 24.1 | N125: 13.9 | O125: 14.2 | Q125: 21 | R125: 28.6 | S125: 14.9 | AQ125: 28.4 | AR125: 30.1 | BH125: 30.5 | BI125: 29.2 | BJ125: 27.1 | BK125: 26 | BM125: 32 | BO125: 28.5 | BS125: 34.8 | CB125: 20.5 | CG125: 55.9 | CJ125: 38.3 | CO125: 27.2 | CP125: 25 | CQ125: 25.5 | CR125: 26.7 | CS125: 40.8 | CU125: 20.3 | CW125: 24.6 | CX125: 23.2 | CZ125: 30.1 | DI125: 26.4 | DX125: 33.4 | EK125: 23 | EY125: 44.3 | EZ125: 46.3 | FG125: 56.3 | FP125: 37.2 | FX125: 27.2 | FY125: 28.1 | GA125: 48.4 | GC125: 48.4 | GF125: 22.3 | GZ125: 19.3 | HC125: 16.7 | JX125: 28.5 | JY125: 28.4 | JZ125: 27.6 | KD125: 28.3 | KE125: 29.3 | KG125: 50.1 | KH125: 24.7 | KJ125: 34.6 | KU125: 93963000000 | KV125: 5.2671333e+10 | KW125: 14199000000 | KX125: 6.0213333e+09 | LB125: 4.9466667e+09 | LG125: 1911000000 | LM125: 1.3203333e+09 | LS125: 3.8472333e+10 | LT125: 1.8631333e+10 | LX125: 7.8286667e+09 | MD125: 4.7106667e+09 | MG125: 7301000000 | MO125: 41292000000
A126: 20852 | B126: 27.8 | D126: 23.7 | L126: 24.1 | N126: 13.9 | O126: 14.4 | Q126: 21 | R126: 28.7 | S126: 14.9 | AQ126: 28.7 | AR126: 30.4 | BH126: 31.1 | BI126: 29.9 | BJ126: 27.3 | BK126: 26.1 | BM126: 33.7 | BO126: 30.6 | BS126: 35.9 | CB126: 20.5 | CG126: 57.9 | CJ126: 38.3 | CO126: 27.1 | CP126: 25 | CQ126: 25.8 | CR126: 27 | CS126: 40.1 | CU126: 20.7 | CW126: 24.2 | CX126: 22.8 | CZ126: 27.2 | DI126: 26.4 | DX126: 33.4 | EK126: 23.1 | EY126: 44.3 | EZ126: 46.4 | FG126: 55.9 | FP126: 37.3 | FX126: 27.4 | FY126: 28.3 | GA126: 48.5 | GC126: 48.5 | GF126: 22.3 | GZ126: 19.3 | HC126: 16.7 | JX126: 28.6 | JY126: 28.5 | JZ126: 27.7 | KD126: 28.5 | KE126: 29.4 | KG126: 50 | KH126: 24.7 | KJ126: 34.7 | KU126: 93963000000 | KV126: 5.2671333e+10 | KW126: 14199000000 | KX126: 6.0213333e+09 | LB126: 4.9466667e+09 | LG126: 1911000000 | LM126: 1.3203333e+09 | LS126: 3.8472333e+10 | LT126: 1.8631333e+10 | LX126: 7.8286667e+09 | MD126: 4.7106667e+09 | MG126: 7301000000 | MO126: 41292000000
A127: 20880 | B127: 27.86 | D127: 23.8 | L127: 24.1 | N127: 13.9 | O127: 14.4 | Q127: 21 | R127: 28.7 | S127: 14.9 | AQ127: 28.6 | AR127: 30.2 | BH127: 30.9 | BI127: 29.7 | BJ127: 27.2 | BK127: 26.3 | BM127: 33.2 | BO127: 30 | BS127: 35.7 | CB127: 20.4 | CG127: 55 | CJ127: 38.3 | CO127: 27 | CP127: 24.8 | CQ127: 25.4 | CR127: 26.8 | CS127: 39 | CU127: 20.4 | CW127: 24.4 | CX127: 22.7 | CZ127: 31.2 | DI127: 26.1 | DX127: 33.6 | EK127: 23.2 | EY127: 44.5 | EZ127: 46.5 | FG127: 56.5 | FP127: 37.4 | FX127: 27.5 | FY127: 28.5 | GA127: 48.4 | GC127: 48.4 | GF127: 23.1 | GZ127: 19.4 | HC127: 16.8 | JX127: 28.7 | JY127: 28.6 | JZ127: 27.8 | KD127: 28.5 | KE127: 29.5 | KG127: 50.3 | KH127: 24.7 | KJ127: 34.8 | KU127: 93963000000 | KV127: 5.2671333e+10 | KW127: 14199000000 | KX127: 6.0213333e+09 | LB127: 4.9466667e+09 | LG127: 1911000000 | LM127: 1.3203333e+09 | LS127: 3.8472333e+10 | LT127: 1.8631333e+10 | LX127: 7.8286667e+09 | MD127: 4.7106667e+09 | MG127: 7301000000 | MO127: 41292000000
A128: 20911 | B128: 27.93 | D128: 23.9 | L128: 24.2 | N128: 14 | O128: 14.5 | Q128: 21 | R128: 28.7 | S128: 15 | AQ128: 28.6 | AR128: 30.3 | BH128: 31.1 | BI128: 29.9 | BJ128: 27.9 | BK128: 26.7 | BM128: 32.9 | BO128: 29.8 | BS128: 35.3 | CB128: 20.4 | CG128: 56.5 | CJ128: 38.7 | CO128: 27 | CP128: 24.9 | CQ128: 25.2 | CR128: 27.6 | CS128: 40.1 | CU128: 19.8 | CW128: 24.6 | CX128: 21.7 | CZ128: 33.4 | DI128: 25.7 | DX128: 33.8 | EK128: 23.2 | EY128: 44.4 | EZ128: 46.5 | FG128: 56.3 | FP128: 37.4 | FX128: 27.7 | FY128: 28.7 | GA128: 48.8 | GC128: 48.7 | GF128: 23.2 | GZ128: 19.5 | HC128: 16.9 | JX128: 28.8 | JY128: 28.6 | JZ128: 27.9 | KD128: 28.5 | KE128: 29.6 | KG128: 50.2 | KH128: 24.8 | KJ128: 34.9 | KU128: 9.4725333e+10 | KV128: 52883000000 | KW128: 1.4056667e+10 | KX128: 5.9013333e+09 | LB128: 4.9636667e+09 | LG128: 1.8943333e+09 | LM128: 1297000000 | LS128: 3.8826333e+10 | LT128: 18881000000 | LX128: 7.8083333e+09 | MD128: 4.7093333e+09 | MG128: 7.4276667e+09 | MO128: 4.1842667e+10
A129: 20941 | B129: 28 | D129: 23.9 | L129: 24.3 | N129: 14 | O129: 14.6 | Q129: 21 | R129: 28.7 | S129: 15 | AQ129: 28.7 | AR129: 30.4 | BH129: 31.4 | BI129: 30.3 | BJ129: 28.3 | BK129: 27.1 | BM129: 33.3 | BO129: 30.8 | BS129: 35.3 | CB129: 20.6 | CG129: 55.9 | CJ129: 38.7 | CO129: 27.1 | CP129: 25 | CQ129: 25.4 | CR129: 28.5 | CS129: 40.2 | CU129: 19.2 | CW129: 24.6 | CX129: 20.2 | CZ129: 35.1 | DI129: 25.5 | DX129: 33.9 | EK129: 23.3 | EY129: 44.5 | EZ129: 46.6 | FG129: 56.3 | FP129: 37.5 | FX129: 27.6 | FY129: 28.7 | GA129: 48.6 | GC129: 48.5 | GF129: 23.3 | GZ129: 19.6 | HC129: 16.9 | JX129: 28.8 | JY129: 28.7 | JZ129: 28 | KD129: 28.7 | KE129: 29.6 | KG129: 50.2 | KH129: 25 | KJ129: 34.9 | KU129: 9.4725333e+10 | KV129: 52883000000 | KW129: 1.4056667e+10 | KX129: 5.9013333e+09 | LB129: 4.9636667e+09 | LG129: 1.8943333e+09 | LM129: 1297000000 | LS129: 3.8826333e+10 | LT129: 18881000000 | LX129: 7.8083333e+09 | MD129: 4.7093333e+09 | MG129: 7.4276667e+09 | MO129: 4.1842667e+10
A130: 20972 | B130: 28.11 | D130: 23.9 | L130: 24.3 | N130: 14 | O130: 14.6 | Q130: 21 | R130: 28.7 | S130: 15 | AQ130: 28.9 | AR130: 30.6 | BH130: 31.9 | BI130: 30.9 | BJ130: 28.7 | BK130: 27.8 | BM130: 33.9 | BO130: 31.4 | BS130: 36.4 | CB130: 20.5 | CG130: 55.7 | CJ130: 38.6 | CO130: 27.4 | CP130: 25.5 | CQ130: 25.7 | CR130: 29.3 | CS130: 42.6 | CU130: 19.1 | CW130: 24.7 | CX130: 19.4 | CZ130: 35.3 | DI130: 25.5 | DX130: 33.8 | EK130: 23.4 | EY130: 44.5 | EZ130: 46.6 | FG130: 56.3 | FP130: 37.5 | FX130: 27.7 | FY130: 28.7 | GA130: 48.5 | GC130: 48.4 | GF130: 23.2 | GZ130: 19.7 | HC130: 17 | JX130: 28.9 | JY130: 28.8 | JZ130: 28 | KD130: 28.7 | KE130: 29.7 | KG130: 50.2 | KH130: 25 | KJ130: 34.9 | KU130: 9.4725333e+10 | KV130: 52883000000 | KW130: 1.4056667e+10 | KX130: 5.9013333e+09 | LB130: 4.9636667e+09 | LG130: 1.8943333e+09 | LM130: 1297000000 | LS130: 3.8826333e+10 | LT130: 18881000000 | LX130: 7.8083333e+09 | MD130: 4.7093333e+09 | MG130: 7.4276667e+09 | MO130: 4.1842667e+10
A131: 21002 | B131: 28.19 | D131: 24 | L131: 24.4 | N131: 14.1 | O131: 14.5 | Q131: 21.1 | R131: 28.7 | S131: 15 | AQ131: 29.1 | AR131: 30.8 | BH131: 32.5 | BI131: 31.5 | BJ131: 29.3 | BK131: 28.6 | BM131: 34.6 | BO131: 33.1 | BS131: 36.1 | CB131: 20.7 | CG131: 58.3 | CJ131: 38.3 | CO131: 27.5 | CP131: 25.7 | CQ131: 26.8 | CR131: 28.1 | CS131: 43.4 | CU131: 19.1 | CW131: 25.1 | CX131: 20.4 | CZ131: 30.6 | DI131: 25.1 | DX131: 33.8 | EK131: 23.4 | EY131: 44.5 | EZ131: 46.5 | FG131: 56.3 | FP131: 37.6 | FX131: 27.8 | FY131: 28.7 | GA131: 48.6 | GC131: 48.5 | GF131: 23.1 | GZ131: 19.7 | HC131: 17.1 | JX131: 29 | JY131: 29 | JZ131: 28.1 | KD131: 28.8 | KE131: 29.8 | KG131: 50.2 | KH131: 25.1 | KJ131: 35 | KU131: 96250000000 | KV131: 53743000000 | KW131: 1.3958667e+10 | KX131: 5.6916667e+09 | LB131: 4947000000 | LG131: 1.9466667e+09 | LM131: 1.3726667e+09 | LS131: 3.9784333e+10 | LT131: 1.9326667e+10 | LX131: 7.9896667e+09 | MD131: 4.7936667e+09 | MG131: 7.6746667e+09 | MO131: 42507000000
A132: 21033 | B132: 28.28 | D132: 24 | L132: 24.5 | N132: 14 | O132: 14.3 | Q132: 21.2 | R132: 28.7 | S132: 15.3 | AQ132: 29.4 | AR132: 31.2 | BH132: 33.4 | BI132: 32.5 | BJ132: 29.8 | BK132: 29.3 | BM132: 36.4 | BO132: 35.6 | BS132: 37 | CB132: 20.8 | CG132: 59.8 | CJ132: 38.6 | CO132: 27.7 | CP132: 26.2 | CQ132: 26.2 | CR132: 28.4 | CS132: 44.1 | CU132: 19.7 | CW132: 26.2 | CX132: 21.7 | CZ132: 33.2 | DI132: 25.1 | DX132: 33.8 | EK132: 23.5 | EY132: 44.6 | EZ132: 46.5 | FG132: 56.3 | FP132: 37.6 | FX132: 27.8 | FY132: 28.7 | GA132: 48.8 | GC132: 48.7 | GF132: 23.3 | GZ132: 19.8 | HC132: 17.1 | JX132: 29 | JY132: 29.1 | JZ132: 28.1 | KD132: 28.9 | KE132: 29.9 | KG132: 50.2 | KH132: 25.2 | KJ132: 35 | KU132: 96250000000 | KV132: 53743000000 | KW132: 1.3958667e+10 | KX132: 5.6916667e+09 | LB132: 4947000000 | LG132: 1.9466667e+09 | LM132: 1.3726667e+09 | LS132: 3.9784333e+10 | LT132: 1.9326667e+10 | LX132: 7.9896667e+09 | MD132: 4.7936667e+09 | MG132: 7.6746667e+09 | MO132: 42507000000
A133: 21064 | B133: 28.32 | D133: 24.1 | L133: 24.5 | N133: 14 | O133: 14.3 | Q133: 21.2 | R133: 28.7 | S133: 15.3 | AQ133: 29.2 | AR133: 30.9 | BH133: 32.8 | BI133: 31.9 | BJ133: 29.9 | BK133: 29 | BM133: 35.2 | BO133: 35 | BS133: 35.8 | CB133: 20.8 | CG133: 61.4 | CJ133: 39.2 | CO133: 27.2 | CP133: 25.4 | CQ133: 24.9 | CR133: 24.9 | CS133: 42.2 | CU133: 19.8 | CW133: 25.9 | CX133: 23.7 | CZ133: 33.9 | DI133: 24.6 | DX133: 33.9 | EK133: 23.6 | EY133: 44.5 | EZ133: 46.6 | FG133: 56.2 | FP133: 37.6 | FX133: 27.9 | FY133: 28.8 | GA133: 48.9 | GC133: 48.8 | GF133: 23.4 | GZ133: 19.8 | HC133: 17.1 | JX133: 29.1 | JY133: 29.1 | JZ133: 28.1 | KD133: 29 | KE133: 29.9 | KG133: 50.2 | KH133: 25.2 | KJ133: 35.1 | KU133: 96250000000 | KV133: 53743000000 | KW133: 1.3958667e+10 | KX133: 5.6916667e+09 | LB133: 4947000000 | LG133: 1.9466667e+09 | LM133: 1.3726667e+09 | LS133: 3.9784333e+10 | LT133: 1.9326667e+10 | LX133: 7.9896667e+09 | MD133: 4.7936667e+09 | MG133: 7.6746667e+09 | MO133: 42507000000
A134: 21094 | B134: 28.32 | D134: 24.2 | L134: 24.4 | N134: 14 | O134: 14.2 | Q134: 21.3 | R134: 28.8 | S134: 15.3 | AQ134: 29.2 | AR134: 30.8 | BH134: 32.1 | BI134: 31.2 | BJ134: 29.5 | BK134: 28.7 | BM134: 33.9 | BO134: 31.5 | BS134: 35.6 | CB134: 20.8 | CG134: 64.8 | CJ134: 39.3 | CO134: 27.2 | CP134: 25.4 | CQ134: 24.7 | CR134: 24.1 | CS134: 42.5 | CU134: 20 | CW134: 26.2 | CX134: 24.6 | CZ134: 34.1 | DI134: 24.1 | DX134: 33.8 | EK134: 23.7 | EY134: 44.6 | EZ134: 46.6 | FG134: 56.3 | FP134: 37.6 | FX134: 27.5 | FY134: 28.4 | GA134: 46.2 | GC134: 46.2 | GF134: 23.5 | GZ134: 19.9 | HC134: 17.2 | JX134: 29.2 | JY134: 29.1 | JZ134: 28.2 | KD134: 29 | KE134: 29.9 | KG134: 50.3 | KH134: 25.2 | KJ134: 34.9 | KU134: 9.6789333e+10 | KV134: 5.3506333e+10 | KW134: 1.3822333e+10 | KX134: 5.6943333e+09 | LB134: 4844000000 | LG134: 1.9213333e+09 | LM134: 1.3623333e+09 | LS134: 39684000000 | LT134: 1.9341667e+10 | LX134: 7.8116667e+09 | MD134: 4.7803333e+09 | MG134: 7.7506667e+09 | MO134: 4.3283333e+10
A135: 21125 | B135: 28.41 | D135: 24.2 | L135: 24.5 | N135: 14 | O135: 14.2 | Q135: 21.4 | R135: 28.8 | S135: 15.4 | AQ135: 29.2 | AR135: 30.8 | BH135: 32 | BI135: 31.1 | BJ135: 29.3 | BK135: 28.9 | BM135: 33.5 | BO135: 30.5 | BS135: 36.1 | CB135: 21 | CG135: 65.1 | CJ135: 39.5 | CO135: 27.2 | CP135: 25.4 | CQ135: 25.2 | CR135: 24.2 | CS135: 41.1 | CU135: 21 | CW135: 25.7 | CX135: 24.3 | CZ135: 32.5 | DI135: 24 | DX135: 33.6 | EK135: 23.8 | EY135: 44.7 | EZ135: 46.6 | FG135: 56.5 | FP135: 37.8 | FX135: 28.3 | FY135: 29.2 | GA135: 49.6 | GC135: 49.6 | GF135: 23.7 | GZ135: 20 | HC135: 17.3 | JX135: 29.3 | JY135: 29.2 | JZ135: 28.3 | KD135: 29 | KE135: 30 | KG135: 50.3 | KH135: 25.4 | KJ135: 35.2 | KU135: 9.6789333e+10 | KV135: 5.3506333e+10 | KW135: 1.3822333e+10 | KX135: 5.6943333e+09 | LB135: 4844000000 | LG135: 1.9213333e+09 | LM135: 1.3623333e+09 | LS135: 39684000000 | LT135: 1.9341667e+10 | LX135: 7.8116667e+09 | MD135: 4.7803333e+09 | MG135: 7.7506667e+09 | MO135: 4.3283333e+10
A136: 21155 | B136: 28.47 | D136: 24.3 | L136: 24.5 | N136: 13.9 | O136: 14 | Q136: 21.4 | R136: 28.8 | S136: 15.4 | AQ136: 29.2 | AR136: 30.9 | BH136: 32.6 | BI136: 31.8 | BJ136: 30 | BK136: 29.5 | BM136: 34.6 | BO136: 31 | BS136: 37.3 | CB136: 21.1 | CG136: 65.6 | CJ136: 39.6 | CO136: 26.8 | CP136: 24.8 | CQ136: 24.8 | CR136: 24.3 | CS136: 37.8 | CU136: 20.8 | CW136: 25.1 | CX136: 24.6 | CZ136: 33.9 | DI136: 24.1 | DX136: 33.6 | EK136: 23.8 | EY136: 44.6 | EZ136: 46.7 | FG136: 56.3 | FP136: 37.8 | FX136: 28.1 | FY136: 29.1 | GA136: 49.1 | GC136: 49 | GF136: 23.5 | GZ136: 20.1 | HC136: 17.4 | JX136: 29.3 | JY136: 29.3 | JZ136: 28.3 | KD136: 29.1 | KE136: 30.1 | KG136: 50.2 | KH136: 25.5 | KJ136: 35.2 | KU136: 9.6789333e+10 | KV136: 5.3506333e+10 | KW136: 1.3822333e+10 | KX136: 5.6943333e+09 | LB136: 4844000000 | LG136: 1.9213333e+09 | LM136: 1.3623333e+09 | LS136: 39684000000 | LT136: 1.9341667e+10 | LX136: 7.8116667e+09 | MD136: 4.7803333e+09 | MG136: 7.7506667e+09 | MO136: 4.3283333e+10
... A148: 21520 | B148: 28.97 | D148: 24.5 | L148: 25 | N148: 13.8 | O148: 13.7 | Q148: 22.1 | R148: 29.2 | S148: 16.2 | AQ148: 29.9 | AR148: 31.6 | BH148: 34.7 | BI148: 34.4 | BJ148: 33.7 | BK148: 36.2 | BM148: 35.8 | BO148: 32 | BS148: 38.7 | CB148: 22.5 | CG148: 57.9 | CJ148: 39.5 | CO148: 28.2 | CP148: 25.2 | CQ148: 26.2 | CR148: 24.1 | CS148: 42 | CU148: 25.2 | CW148: 24.5 | CX148: 21.8 | CZ148: 32.2 | DI148: 22.5 | DX148: 33.4 | EK148: 24.3 | EY148: 44.7 | EZ148: 46.2 | FG148: 56.3 | FP148: 38.2 | FX148: 29.2 | FY148: 30.1 | GA148: 52.3 | GC148: 52.2 | GF148: 25.6 | GZ148: 21.1 | HC148: 18.3 | JX148: 29.9 | JY148: 29.8 | JZ148: 28.8 | KD148: 29.6 | KE148: 30.7 | KG148: 50.1 | KH148: 26.4 | KJ148: 35.5 | KU148: 1.0060767e+11 | KV148: 5.4924333e+10 | KW148: 1.3564333e+10 | KX148: 5.2263333e+09 | LB148: 4.9453333e+09 | LG148: 2.0043333e+09 | LM148: 1.3883333e+09 | LS148: 41360000000 | LT148: 2.0082667e+10 | LX148: 8.1996667e+09 | MD148: 4.9443333e+09 | MG148: 8133000000 | MO148: 45683000000
A149: 21551 | B149: 29.01 | D149: 24.5 | L149: 25.1 | N149: 13.9 | O149: 13.8 | Q149: 22.1 | R149: 29.2 | S149: 16.2 | AQ149: 30 | AR149: 31.7 | BH149: 34.8 | BI149: 34.5 | BJ149: 34.3 | BK149: 36.8 | BM149: 35.1 | BO149: 31.7 | BS149: 38.1 | CB149: 22.7 | CG149: 59.5 | CJ149: 39.4 | CO149: 28.4 | CP149: 25.4 | CQ149: 25.5 | CR149: 24.2 | CS149: 40.7 | CU149: 23.9 | CW149: 25.3 | CX149: 22.3 | CZ149: 32.8 | DI149: 22.1 | DX149: 33.6 | EK149: 24.4 | EY149: 44.8 | EZ149: 46.3 | FG149: 56.3 | FP149: 38.4 | FX149: 29.3 | FY149: 30.2 | GA149: 51.9 | GC149: 51.9 | GF149: 25.9 | GZ149: 21.1 | HC149: 18.3 | JX149: 29.9 | JY149: 29.8 | JZ149: 28.9 | KD149: 29.6 | KE149: 30.7 | KG149: 50.1 | KH149: 26.4 | KJ149: 35.5 | KT149: 2000000000 | KU149: 1.0314967e+11 | KV149: 5.6574333e+10 | KW149: 1.4549667e+10 | KX149: 6030000000 | KY149: 4.4496667e+09 | KZ149: 8.0866667e+08 | LA149: 7.7166667e+08 | LB149: 5.0476667e+09 | LC149: 2.8286667e+09 | LD149: 1.4163333e+09 | LE149: 5.9166667e+08 | LF149: 2.1133333e+08 | LG149: 2.0966667e+09 | LH149: 1.0716667e+09 | LI149: 4.0466667e+08 | LJ149: 283000000 | LK149: 265000000 | LL149: 72000000 | LM149: 1375000000 | LN149: 6.4333333e+08 | LO149: 264000000 | LP149: 89666667 | LQ149: 3.7533333e+08 | LR149: 3000000 | LS149: 4.2024667e+10 | LT149: 2.0413333e+10 | LU149: 17880000000 | LV149: 2.0993333e+09 | LW149: 434000000 | LX149: 8.2616667e+09 | LY149: 6.5706667e+09 | LZ149: 4.0956667e+09 | MA149: 2.3806667e+09 | MB149: 94333333 | MC149: 1691000000 | MD149: 5.0423333e+09 | ME149: 3.6483333e+09 | MF149: 1394000000 | MG149: 8.3073333e+09 | MH149: 1.0136667e+09 | MI149: 1.0216667e+09 | MJ149: 1.7296667e+09 | MK149: 9.5233333e+08 | ML149: 2.1283333e+09 | MM149: 1119000000 | MN149: 3.4266667e+08 | MO149: 4.6575333e+10 | MP149: 4.5021333e+10 | MQ149: 17104000000 | MR149: 1.4221333e+10 | MS149: 4.0813333e+09 | MT149: 9.3676667e+09 | MU149: 6.4933333e+08 | MV149: 123000000 | MW149: 2.8826667e+09 | MX149: 3.7733333e+08 | MY149: 2.5053333e+09 | MZ149: 1.5293333e+09 | NA149: 976000000 | NB149: 4821000000 | NC149: 2.8163333e+09 | ND149: 1.8063333e+09 | NE149: 6.4766667e+08 | NF149: 3.6233333e+08 | NG149: 2.0046667e+09 | NH149: 1906000000 | NI149: 99000000 | NJ149: 2.7956667e+09 | NK149: 1.7496667e+09 | NL149: 1.5413333e+09 | NM149: 2.0833333e+08 | NN149: 1046000000 | NO149: 8.6366667e+08 | NP149: 1.8166667e+08 | NQ149: 333333.33 | NR149: 1.8806667e+09 | NS149: 1.1033333e+09 | NT149: 4.9966667e+08 | NU149: 2.0333333e+08 | NV149: 74333333 | NW149: 6.3163333e+09 | NX149: 5.9806667e+09 | NY149: 5.5793333e+09 | NZ149: 4.0133333e+08 | OA149: 3.3566667e+08 | OB149: 3856000000 | OC149: 1.6823333e+09 | OD149: 9.6866667e+08 | OE149: 7.1366667e+08 | OF149: 2.1736667e+09 | OG149: 1047000000 | OH149: 42333333 | OI149: 5.2033333e+08 | OJ149: 5.6433333e+08 | OK149: 8.2476667e+09 | OL149: 1.5753333e+09 | OM149: 1.3626667e+09 | ON149: 213000000 | OP149: 924000000 | OQ149: 4.4766667e+08 | OR149: 288000000 | OS149: 1.8833333e+08 | OT149: 1.3996667e+09 | OU149: 5.1133333e+08 | OV149: 1.5043333e+09 | OW149: 333000000 | OX149: 6.8933333e+08 | OY149: 3.5633333e+08 | OZ149: 1554000000 | PA149: 4491000000 | PB149: 2.9373333e+09
A150: 21582 | B150: 29 | D150: 24.5 | L150: 25.2 | N150: 13.9 | O150: 13.9 | Q150: 22.1 | R150: 29.2 | S150: 16.3 | AQ150: 29.8 | AR150: 31.4 | BH150: 34.3 | BI150: 34 | BJ150: 34.6 | BK150: 37 | BM150: 33.9 | BO150: 30.4 | BS150: 36.4 | CB150: 22.6 | CG150: 59 | CJ150: 39.6 | CO150: 28.2 | CP150: 25.2 | CQ150: 24.9 | CR150: 24.2 | CS150: 40.4 | CU150: 22.7 | CW150: 25.4 | CX150: 22.1 | CZ150: 31.5 | DI150: 21.6 | DX150: 33.7 | EK150: 24.5 | EY150: 44.7 | EZ150: 46.2 | FG150: 56.3 | FP150: 38.5 | FX150: 29.4 | FY150: 30.3 | GA150: 52 | GC150: 51.9 | GF150: 26.1 | GZ150: 21.2 | HC150: 18.4 | JX150: 29.9 | JY150: 29.8 | JZ150: 28.9 | KD150: 29.6 | KE150: 30.7 | KG150: 50.1 | KH150: 26.4 | KJ150: 35.5 | KT150: 2000000000 | KU150: 1.0314967e+11 | KV150: 5.6574333e+10 | KW150: 1.4549667e+10 | KX150: 6030000000 | KY150: 4.4496667e+09 | KZ150: 8.0866667e+08 | LA150: 7.7166667e+08 | LB150: 5.0476667e+09 | LC150: 2.8286667e+09 | LD150: 1.4163333e+09 | LE150: 5.9166667e+08 | LF150: 2.1133333e+08 | LG150: 2.0966667e+09 | LH150: 1.0716667e+09 | LI150: 4.0466667e+08 | LJ150: 283000000 | LK150: 265000000 | LL150: 72000000 | LM150: 1375000000 | LN150: 6.4333333e+08 | LO150: 264000000 | LP150: 89666667 | LQ150: 3.7533333e+08 | LR150: 3000000 | LS150: 4.2024667e+10 | LT150: 2.0413333e+10 | LU150: 17880000000 | LV150: 2.0993333e+09 | LW150: 434000000 | LX150: 8.2616667e+09 | LY150: 6.5706667e+09 | LZ150: 4.0956667e+09 | MA150: 2.3806667e+09 | MB150: 94333333 | MC150: 1691000000 | MD150: 5.0423333e+09 | ME150: 3.6483333e+09 | MF150: 1394000000 | MG150: 8.3073333e+09 | MH150: 1.0136667e+09 | MI150: 1.0216667e+09 | MJ150: 1.7296667e+09 | MK150: 9.5233333e+08 | ML150: 2.1283333e+09 | MM150: 1119000000 | MN150: 3.4266667e+08 | MO150: 4.6575333e+10 | MP150: 4.5021333e+10 | MQ150: 17104000000 | MR150: 1.4221333e+10 | MS150: 4.0813333e+09 | MT150: 9.3676667e+09 | MU150: 6.4933333e+08 | MV150: 123000000 | MW150: 2.8826667e+09 | MX150: 3.7733333e+08 | MY150: 2.5053333e+09 | MZ150: 1.5293333e+09 | NA150: 976000000 | NB150: 4821000000 | NC150: 2.8163333e+09 | ND150: 1.8063333e+09 | NE150: 6.4766667e+08 | NF150: 3.6233333e+08 | NG150: 2.0046667e+09 | NH150: 1906000000 | NI150: 99000000 | NJ150: 2.7956667e+09 | NK150: 1.7496667e+09 | NL150: 1.5413333e+09 | NM150: 2.0833333e+08 | NN150: 1046000000 | NO150: 8.6366667e+08 | NP150: 1.8166667e+08 | NQ150: 333333.33 | NR150: 1.8806667e+09 | NS150: 1.1033333e+09 | NT150: 4.9966667e+08 | NU150: 2.0333333e+08 | NV150: 74333333 | NW150: 6.3163333e+09 | NX150: 5.9806667e+09 | NY150: 5.5793333e+09 | NZ150: 4.0133333e+08 | OA150: 3.3566667e+08 | OB150: 3856000000 | OC150: 1.6823333e+09 | OD150: 9.6866667e+08 | OE150: 7.1366667e+08 | OF150: 2.1736667e+09 | OG150: 1047000000 | OH150: 42333333 | OI150: 5.2033333e+08 | OJ150: 5.6433333e+08 | OK150: 8.2476667e+09 | OL150: 1.5753333e+09 | OM150: 1.3626667e+09 | ON150: 213000000 | OP150: 924000000 | OQ150: 4.4766667e+08 | OR150: 288000000 | OS150: 1.8833333e+08 | OT150: 1.3996667e+09 | OU150: 5.1133333e+08 | OV150: 1.5043333e+09 | OW150: 333000000 | OX150: 6.8933333e+08 | OY150: 3.5633333e+08 | OZ150: 1554000000 | PA150: 4491000000 | PB150: 2.9373333e+09
A151: 21610 | B151: 28.97 | D151: 24.6 | L151: 25.3 | N151: 14 | O151: 14.1 | Q151: 22.2 | R151: 29.2 | S151: 16.3 | AQ151: 29.7 | AR151: 31.2 | BH151: 34 | BI151: 33.6 | BJ151: 34.6 | BK151: 36.8 | BM151: 33.1 | BO151: 29.7 | BS151: 35.3 | CB151: 22.6 | CG151: 57.9 | CJ151: 39.8 | CO151: 28 | CP151: 24.8 | CQ151: 24.8 | CR151: 24.5 | CS151: 40.3 | CU151: 22.4 | CW151: 25.2 | CX151: 21.6 | CZ151: 31.5 | DI151: 21.6 | DX151: 33.7 | EK151: 24.5 | EY151: 44.7 | EZ151: 46.2 | FG151: 56.3 | FP151: 38.7 | FX151: 29.6 | FY151: 30.6 | GA151: 52.2 | GC151: 52.1 | GF151: 26.4 | GZ151: 21.3 | HC151: 18.5 | JX151: 30 | JY151: 29.7 | JZ151: 28.9 | KD151: 29.6 | KE151: 30.7 | KG151: 50 | KH151: 26.5 | KJ151: 35.6 | KT151: 2000000000 | KU151: 1.0314967e+11 | KV151: 5.6574333e+10 | KW151: 1.4549667e+10 | KX151: 6030000000 | KY151: 4.4496667e+09 | KZ151: 8.0866667e+08 | LA151: 7.7166667e+08 | LB151: 5.0476667e+09 | LC151: 2.8286667e+09 | LD151: 1.4163333e+09 | LE151: 5.9166667e+08 | LF151: 2.1133333e+08 | LG151: 2.0966667e+09 | LH151: 1.0716667e+09 | LI151: 4.0466667e+08 | LJ151: 283000000 | LK151: 265000000 | LL151: 72000000 | LM151: 1375000000 | LN151: 6.4333333e+08 | LO151: 264000000 | LP151: 89666667 | LQ151: 3.7533333e+08 | LR151: 3000000 | LS151: 4.2024667e+10 | LT151: 2.0413333e+10 | LU151: 17880000000 | LV151: 2.0993333e+09 | LW151: 434000000 | LX151: 8.2616667e+09 | LY151: 6.5706667e+09 | LZ151: 4.0956667e+09 | MA151: 2.3806667e+09 | MB151: 94333333 | MC151: 1691000000 | MD151: 5.0423333e+09 | ME151: 3.6483333e+09 | MF151: 1394000000 | MG151: 8.3073333e+09 | MH151: 1.0136667e+09 | MI151: 1.0216667e+09 | MJ151: 1.7296667e+09 | MK151: 9.5233333e+08 | ML151: 2.1283333e+09 | MM151: 1119000000 | MN151: 3.4266667e+08 | MO151: 4.6575333e+10 | MP151: 4.5021333e+10 | MQ151: 17104000000 | MR151: 1.4221333e+10 | MS151: 4.0813333e+09 | MT151: 9.3676667e+09 | MU151: 6.4933333e+08 | MV151: 123000000 | MW151: 2.8826667e+09 | MX151: 3.7733333e+08 | MY151: 2.5053333e+09 | MZ151: 1.5293333e+09 | NA151: 976000000 | NB151: 4821000000 | NC151: 2.8163333e+09 | ND151: 1.8063333e+09 | NE151: 6.4766667e+08 | NF151: 3.6233333e+08 | NG151: 2.0046667e+09 | NH151: 1906000000 | NI151: 99000000 | NJ151: 2.7956667e+09 | NK151: 1.7496667e+09 | NL151: 1.5413333e+09 | NM151: 2.0833333e+08 | NN151: 1046000000 | NO151: 8.6366667e+08 | NP151: 1.8166667e+08 | NQ151: 333333.33 | NR151: 1.8806667e+09 | NS151: 1.1033333e+09 | NT151: 4.9966667e+08 | NU151: 2.0333333e+08 | NV151: 74333333 | NW151: 6.3163333e+09 | NX151: 5.9806667e+09 | NY151: 5.5793333e+09 | NZ151: 4.0133333e+08 | OA151: 3.3566667e+08 | OB151: 3856000000 | OC151: 1.6823333e+09 | OD151: 9.6866667e+08 | OE151: 7.1366667e+08 | OF151: 2.1736667e+09 | OG151: 1047000000 | OH151: 42333333 | OI151: 5.2033333e+08 | OJ151: 5.6433333e+08 | OK151: 8.2476667e+09 | OL151: 1.5753333e+09 | OM151: 1.3626667e+09 | ON151: 213000000 | OP151: 924000000 | OQ151: 4.4766667e+08 | OR151: 288000000 | OS151: 1.8833333e+08 | OT151: 1.3996667e+09 | OU151: 5.1133333e+08 | OV151: 1.5043333e+09 | OW151: 333000000 | OX151: 6.8933333e+08 | OY151: 3.5633333e+08 | OZ151: 1554000000 | PA151: 4491000000 | PB151: 2.9373333e+09
A152: 21641 | B152: 28.98 | D152: 24.6 | L152: 25.3 | N152: 14 | O152: 14 | Q152: 22.2 | R152: 29.2 | S152: 16.3 | AQ152: 29.5 | AR152: 31.1 | BH152: 33.9 | BI152: 33.5 | BJ152: 34.5 | BK152: 36.5 | BM152: 33 | BO152: 29.7 | BS152: 35.8 | CB152: 22.7 | CG152: 54 | CJ152: 39.8 | CO152: 28 | CP152: 24.9 | CQ152: 24.7 | CR152: 24.3 | CS152: 40.3 | CU152: 21.7 | CW152: 25.1 | CX152: 21.4 | CZ152: 29.5 | DI152: 21.5 | DX152: 33.9 | EK152: 24.6 | EY152: 44.8 | EZ152: 46.2 | FG152: 56.4 | FP152: 38.9 | FX152: 29.7 | FY152: 30.7 | GA152: 52.1 | GC152: 52 | GF152: 26.6 | GZ152: 21.3 | HC152: 18.6 | JX152: 30 | JY152: 29.8 | JZ152: 29 | KD152: 29.6 | KE152: 30.7 | KG152: 50.1 | KH152: 26.5 | KJ152: 35.7 | KT152: 2.0373333e+09 | KU152: 1.0516833e+11 | KV152: 57539000000 | KW152: 15155000000 | KX152: 6445000000 | KY152: 4.6923333e+09 | KZ152: 966000000 | LA152: 7.8666667e+08 | LB152: 5.1826667e+09 | LC152: 2914000000 | LD152: 1.4583333e+09 | LE152: 5.9366667e+08 | LF152: 2.1633333e+08 | LG152: 2.1246667e+09 | LH152: 1097000000 | LI152: 403000000 | LJ152: 2.8033333e+08 | LK152: 2.7066667e+08 | LL152: 73666667 | LM152: 1.4026667e+09 | LN152: 6.4433333e+08 | LO152: 283000000 | LP152: 91333333 | LQ152: 381000000 | LR152: 3000000 | LS152: 42384000000 | LT152: 2.0420333e+10 | LU152: 1.7887667e+10 | LV152: 2.0953333e+09 | LW152: 4.3733333e+08 | LX152: 8500000000 | LY152: 6768000000 | LZ152: 4.1706667e+09 | MA152: 2.5013333e+09 | MB152: 96000000 | MC152: 1.7323333e+09 | MD152: 5.0916667e+09 | ME152: 3.7366667e+09 | MF152: 1.3553333e+09 | MG152: 8372000000 | MH152: 1.0446667e+09 | MI152: 1.0026667e+09 | MJ152: 1.7963333e+09 | MK152: 9.5566667e+08 | ML152: 2147000000 | MM152: 1111000000 | MN152: 3.1466667e+08 | MO152: 4.7629333e+10 | MP152: 4.6030667e+10 | MQ152: 1.7390333e+10 | MR152: 1.4498333e+10 | MS152: 4144000000 | MT152: 9.5656667e+09 | MU152: 6.6866667e+08 | MV152: 120000000 | MW152: 2892000000 | MX152: 3.9366667e+08 | MY152: 2.4983333e+09 | MZ152: 1.5533333e+09 | NA152: 945000000 | NB152: 4909000000 | NC152: 2.8636667e+09 | ND152: 1835000000 | NE152: 649000000 | NF152: 3.7966667e+08 | NG152: 2.0453333e+09 | NH152: 1946000000 | NI152: 99666667 | NJ152: 2.8616667e+09 | NK152: 1.7996667e+09 | NL152: 1585000000 | NM152: 2.1466667e+08 | NN152: 1062000000 | NO152: 8.7033333e+08 | NP152: 1.9133333e+08 | NQ152: 333333.33 | NR152: 1958000000 | NS152: 1.1393333e+09 | NT152: 5.3033333e+08 | NU152: 2.1033333e+08 | NV152: 78000000 | NW152: 6.4883333e+09 | NX152: 6137000000 | NY152: 5.7383333e+09 | NZ152: 3.9866667e+08 | OA152: 3.5133333e+08 | OB152: 3.9833333e+09 | OC152: 1.7436667e+09 | OD152: 1.0216667e+09 | OE152: 722000000 | OF152: 2.2396667e+09 | OG152: 1.0363333e+09 | OH152: 46333333 | OI152: 5.4033333e+08 | OJ152: 6.1633333e+08 | OK152: 8440000000 | OL152: 1593000000 | OM152: 1383000000 | ON152: 210000000 | OP152: 9.3633333e+08 | OQ152: 4.5333333e+08 | OR152: 2.9266667e+08 | OS152: 1.9033333e+08 | OT152: 1429000000 | OU152: 5.1633333e+08 | OV152: 1.5666667e+09 | OW152: 3.6166667e+08 | OX152: 6.8533333e+08 | OY152: 3.2366667e+08 | OZ152: 1.5986667e+09 | PA152: 4593000000 | PB152: 2.9943333e+09
A153: 21671 | B153: 29.04 | D153: 24.7 | L153: 25.3 | N153: 14 | O153: 13.9 | Q153: 22.2 | R153: 29.4 | S153: 16.3 | AQ153: 29.5 | AR153: 31 | BH153: 33.9 | BI153: 33.5 | BJ153: 34.6 | BK153: 36.5 | BM153: 33 | BO153: 29.5 | BS153: 36 | CB153: 22.5 | CG153: 51.5 | CJ153: 39.8 | CO153: 27.9 | CP153: 24.7 | CQ153: 24.6 | CR153: 22.7 | CS153: 40.9 | CU153: 22.9 | CW153: 24.7 | CX153: 22.2 | CZ153: 30.4 | DI153: 21.2 | DX153: 33.8 | EK153: 24.7 | EY153: 44.9 | EZ153: 46.2 | FG153: 56.5 | FP153: 39.2 | FX153: 29.7 | FY153: 30.7 | GA153: 52.3 | GC153: 52.2 | GF153: 26.6 | GZ153: 21.4 | HC153: 18.6 | JX153: 30.1 | JY153: 29.8 | JZ153: 29.1 | KD153: 29.6 | KE153: 30.7 | KG153: 50.2 | KH153: 26.6 | KJ153: 35.8 | KT153: 2.0373333e+09 | KU153: 1.0516833e+11 | KV153: 57539000000 | KW153: 15155000000 | KX153: 6445000000 | KY153: 4.6923333e+09 | KZ153: 966000000 | LA153: 7.8666667e+08 | LB153: 5.1826667e+09 | LC153: 2914000000 | LD153: 1.4583333e+09 | LE153: 5.9366667e+08 | LF153: 2.1633333e+08 | LG153: 2.1246667e+09 | LH153: 1097000000 | LI153: 403000000 | LJ153: 2.8033333e+08 | LK153: 2.7066667e+08 | LL153: 73666667 | LM153: 1.4026667e+09 | LN153: 6.4433333e+08 | LO153: 283000000 | LP153: 91333333 | LQ153: 381000000 | LR153: 3000000 | LS153: 42384000000 | LT153: 2.0420333e+10 | LU153: 1.7887667e+10 | LV153: 2.0953333e+09 | LW153: 4.3733333e+08 | LX153: 8500000000 | LY153: 6768000000 | LZ153: 4.1706667e+09 | MA153: 2.5013333e+09 | MB153: 96000000 | MC153: 1.7323333e+09 | MD153: 5.0916667e+09 | ME153: 3.7366667e+09 | MF153: 1.3553333e+09 | MG153: 8372000000 | MH153: 1.0446667e+09 | MI153: 1.0026667e+09 | MJ153: 1.7963333e+09 | MK153: 9.5566667e+08 | ML153: 2147000000 | MM153: 1111000000 | MN153: 3.1466667e+08 | MO153: 4.7629333e+10 | MP153: 4.6030667e+10 | MQ153: 1.7390333e+10 | MR153: 1.4498333e+10 | MS153: 4144000000 | MT153: 9.5656667e+09 | MU153: 6.6866667e+08 | MV153: 120000000 | MW153: 2892000000 | MX153: 3.9366667e+08 | MY153: 2.4983333e+09 | MZ153: 1.5533333e+09 | NA153: 945000000 | NB153: 4909000000 | NC153: 2.8636667e+09 | ND153: 1835000000 | NE153: 649000000 | NF153: 3.7966667e+08 | NG153: 2.0453333e+09 | NH153: 1946000000 | NI153: 99666667 | NJ153: 2.8616667e+09 | NK153: 1.7996667e+09 | NL153: 1585000000 | NM153: 2.1466667e+08 | NN153: 1062000000 | NO153: 8.7033333e+08 | NP153: 1.9133333e+08 | NQ153: 333333.33 | NR153: 1958000000 | NS153: 1.1393333e+09 | NT153: 5.3033333e+08 | NU153: 2.1033333e+08 | NV153: 78000000 | NW153: 6.4883333e+09 | NX153: 6137000000 | NY153: 5.7383333e+09 | NZ153: 3.9866667e+08 | OA153: 3.5133333e+08 | OB153: 3.9833333e+09 | OC153: 1.7436667e+09 | OD153: 1.0216667e+09 | OE153: 722000000 | OF153: 2.2396667e+09 | OG153: 1.0363333e+09 | OH153: 46333333 | OI153: 5.4033333e+08 | OJ153: 6.1633333e+08 | OK153: 8440000000 | OL153: 1593000000 | OM153: 1383000000 | ON153: 210000000 | OP153: 9.3633333e+08 | OQ153: 4.5333333e+08 | OR153: 2.9266667e+08 | OS153: 1.9033333e+08 | OT153: 1429000000 | OU153: 5.1633333e+08 | OV153: 1.5666667e+09 | OW153: 3.6166667e+08 | OX153: 6.8533333e+08 | OY153: 3.2366667e+08 | OZ153: 1.5986667e+09 | PA153: 4593000000 | PB153: 2.9943333e+09
A154: 21702 | B154: 29.11 | D154: 24.7 | L154: 25.3 | N154: 13.9 | O154: 13.7 | Q154: 22.3 | R154: 29.6 | S154: 16.4 | AQ154: 29.7 | AR154: 31.2 | BH154: 33.6 | BI154: 33.3 | BJ154: 34.6 | BK154: 36.5 | BM154: 32.5 | BO154: 28.8 | BS154: 35 | CB154: 22.5 | CG154: 51.6 | CJ154: 39.8 | CO154: 28.9 | CP154: 26.2 | CQ154: 25.3 | CR154: 22.1 | CS154: 39.6 | CU154: 24 | CW154: 26.8 | CX154: 30.7 | CZ154: 30.9 | DI154: 21 | DX154: 33.9 | EK154: 24.8 | EY154: 45 | EZ154: 46.2 | FG154: 56.4 | FP154: 39.5 | FX154: 29.8 | FY154: 30.8 | GA154: 52.4 | GC154: 52.3 | GF154: 26.8 | GZ154: 21.5 | HC154: 18.7 | JX154: 30.2 | JY154: 29.9 | JZ154: 29.2 | KD154: 29.7 | KE154: 30.8 | KG154: 50.2 | KH154: 26.6 | KJ154: 35.8 | KT154: 2.0373333e+09 | KU154: 1.0516833e+11 | KV154: 57539000000 | KW154: 15155000000 | KX154: 6445000000 | KY154: 4.6923333e+09 | KZ154: 966000000 | LA154: 7.8666667e+08 | LB154: 5.1826667e+09 | LC154: 2914000000 | LD154: 1.4583333e+09 | LE154: 5.9366667e+08 | LF154: 2.1633333e+08 | LG154: 2.1246667e+09 | LH154: 1097000000 | LI154: 403000000 | LJ154: 2.8033333e+08 | LK154: 2.7066667e+08 | LL154: 73666667 | LM154: 1.4026667e+09 | LN154: 6.4433333e+08 | LO154: 283000000 | LP154: 91333333 | LQ154: 381000000 | LR154: 3000000 | LS154: 42384000000 | LT154: 2.0420333e+10 | LU154: 1.7887667e+10 | LV154: 2.0953333e+09 | LW154: 4.3733333e+08 | LX154: 8500000000 | LY154: 6768000000 | LZ154: 4.1706667e+09 | MA154: 2.5013333e+09 | MB154: 96000000 | MC154: 1.7323333e+09 | MD154: 5.0916667e+09 | ME154: 3.7366667e+09 | MF154: 1.3553333e+09 | MG154: 8372000000 | MH154: 1.0446667e+09 | MI154: 1.0026667e+09 | MJ154: 1.7963333e+09 | MK154: 9.5566667e+08 | ML154: 2147000000 | MM154: 1111000000 | MN154: 3.1466667e+08 | MO154: 4.7629333e+10 | MP154: 4.6030667e+10 | MQ154: 1.7390333e+10 | MR154: 1.4498333e+10 | MS154: 4144000000 | MT154: 9.5656667e+09 | MU154: 6.6866667e+08 | MV154: 120000000 | MW154: 2892000000 | MX154: 3.9366667e+08 | MY154: 2.4983333e+09 | MZ154: 1.5533333e+09 | NA154: 945000000 | NB154: 4909000000 | NC154: 2.8636667e+09 | ND154: 1835000000 | NE154: 649000000 | NF154: 3.7966667e+08 | NG154: 2.0453333e+09 | NH154: 1946000000 | NI154: 99666667 | NJ154: 2.8616667e+09 | NK154: 1.7996667e+09 | NL154: 1585000000 | NM154: 2.1466667e+08 | NN154: 1062000000 | NO154: 8.7033333e+08 | NP154: 1.9133333e+08 | NQ154: 333333.33 | NR154: 1958000000 | NS154: 1.1393333e+09 | NT154: 5.3033333e+08 | NU154: 2.1033333e+08 | NV154: 78000000 | NW154: 6.4883333e+09 | NX154: 6137000000 | NY154: 5.7383333e+09 | NZ154: 3.9866667e+08 | OA154: 3.5133333e+08 | OB154: 3.9833333e+09 | OC154: 1.7436667e+09 | OD154: 1.0216667e+09 | OE154: 722000000 | OF154: 2.2396667e+09 | OG154: 1.0363333e+09 | OH154: 46333333 | OI154: 5.4033333e+08 | OJ154: 6.1633333e+08 | OK154: 8440000000 | OL154: 1593000000 | OM154: 1383000000 | ON154: 210000000 | OP154: 9.3633333e+08 | OQ154: 4.5333333e+08 | OR154: 2.9266667e+08 | OS154: 1.9033333e+08 | OT154: 1429000000 | OU154: 5.1633333e+08 | OV154: 1.5666667e+09 | OW154: 3.6166667e+08 | OX154: 6.8533333e+08 | OY154: 3.2366667e+08 | OZ154: 1.5986667e+09 | PA154: 4593000000 | PB154: 2.9943333e+09
A155: 21732 | B155: 29.15 | D155: 24.7 | L155: 25.4 | N155: 13.9 | O155: 13.6 | Q155: 22.4 | R155: 29.6 | S155: 16.5 | AQ155: 29.6 | AR155: 31.2 | BH155: 33.4 | BI155: 33 | BJ155: 34.7 | BK155: 36.5 | BM155: 31.9 | BO155: 28.1 | BS155: 34.8 | CB155: 22.5 | CG155: 56.9 | CJ155: 39.9 | CO155: 28.4 | CP155: 25.4 | CQ155: 25.2 | CR155: 20.6 | CS155: 40.1 | CU155: 22.5 | CW155: 25.9 | CX155: 27 | CZ155: 28.9 | DI155: 20.9 | DX155: 34 | EK155: 24.9 | EY155: 45.1 | EZ155: 46.3 | FG155: 56.3 | FP155: 39.8 | FX155: 29.9 | FY155: 30.9 | GA155: 52.4 | GC155: 52.3 | GF155: 27.3 | GZ155: 21.5 | HC155: 18.7 | JX155: 30.2 | JY155: 30 | JZ155: 29.2 | KD155: 29.8 | KE155: 30.9 | KG155: 50.2 | KH155: 26.7 | KJ155: 35.9 | KT155: 2.0886667e+09 | KU155: 1.0690833e+11 | KV155: 5.8174667e+10 | KW155: 1.5445333e+10 | KX155: 6691000000 | KY155: 4.9873333e+09 | KZ155: 8.9066667e+08 | LA155: 813000000 | LB155: 5.2156667e+09 | LC155: 2.8996667e+09 | LD155: 1.5033333e+09 | LE155: 592000000 | LF155: 221000000 | LG155: 2.1306667e+09 | LH155: 1100000000 | LI155: 4.0633333e+08 | LJ155: 2.7966667e+08 | LK155: 270000000 | LL155: 74666667 | LM155: 1408000000 | LN155: 651000000 | LO155: 283000000 | LP155: 91000000 | LQ155: 3.7966667e+08 | LR155: 3000000 | LS155: 4.2729333e+10 | LT155: 2.0589333e+10 | LU155: 1.8020333e+10 | LV155: 2139000000 | LW155: 4.3033333e+08 | LX155: 8480000000 | LY155: 6.7463333e+09 | LZ155: 4146000000 | MA155: 2.5043333e+09 | MB155: 96000000 | MC155: 1.7336667e+09 | MD155: 5.0693333e+09 | ME155: 3.7496667e+09 | MF155: 1.3196667e+09 | MG155: 8.5906667e+09 | MH155: 1.0753333e+09 | MI155: 1.0343333e+09 | MJ155: 1.8336667e+09 | MK155: 9.7033333e+08 | ML155: 2195000000 | MM155: 1157000000 | MN155: 3.2533333e+08 | MO155: 4.8733667e+10 | MP155: 47089000000 | MQ155: 1.7799333e+10 | MR155: 14791000000 | MS155: 4.2076667e+09 | MT155: 9.7866667e+09 | MU155: 6.8733333e+08 | MV155: 1.0933333e+08 | MW155: 3.0083333e+09 | MX155: 4.1433333e+08 | MY155: 2594000000 | MZ155: 1584000000 | NA155: 1010000000 | NB155: 4.9796667e+09 | NC155: 2.9073333e+09 | ND155: 1858000000 | NE155: 6.5033333e+08 | NF155: 3.9933333e+08 | NG155: 2.0723333e+09 | NH155: 1966000000 | NI155: 106000000 | NJ155: 2.9433333e+09 | NK155: 1851000000 | NL155: 1.6296667e+09 | NM155: 2.2133333e+08 | NN155: 1.0923333e+09 | NO155: 890000000 | NP155: 202000000 | NQ155: 333333.33 | NR155: 2.0033333e+09 | NS155: 1175000000 | NT155: 5.2766667e+08 | NU155: 2.1833333e+08 | NV155: 82333333 | NW155: 6.6976667e+09 | NX155: 6.3296667e+09 | NY155: 5.9256667e+09 | NZ155: 404000000 | OA155: 368000000 | OB155: 4.0873333e+09 | OC155: 1.7736667e+09 | OD155: 1.0666667e+09 | OE155: 707000000 | OF155: 2314000000 | OG155: 1048000000 | OH155: 49333333 | OI155: 5.6266667e+08 | OJ155: 654000000 | OK155: 8.5783333e+09 | OL155: 1.6176667e+09 | OM155: 1.4063333e+09 | ON155: 2.1133333e+08 | OP155: 9.5066667e+08 | OQ155: 461000000 | OR155: 298000000 | OS155: 1.9166667e+08 | OT155: 1.4553333e+09 | OU155: 5.2666667e+08 | OV155: 1.5913333e+09 | OW155: 348000000 | OX155: 7.0933333e+08 | OY155: 3.6133333e+08 | OZ155: 1645000000 | PA155: 4.6826667e+09 | PB155: 3.0376667e+09
A156: 21763 | B156: 29.18 | D156: 24.8 | L156: 25.4 | N156: 13.8 | O156: 13.5 | Q156: 22.5 | R156: 29.6 | S156: 16.6 | AQ156: 29.6 | AR156: 31.1 | BH156: 33 | BI156: 32.4 | BJ156: 34.3 | BK156: 36.2 | BM156: 30.8 | BO156: 26.9 | BS156: 34 | CB156: 22.4 | CG156: 55.8 | CJ156: 40 | CO156: 28.7 | CP156: 25.7 | CQ156: 25.4 | CR156: 22.2 | CS156: 39.9 | CU156: 22.6 | CW156: 26.2 | CX156: 25.1 | CZ156: 33.7 | DI156: 21 | DX156: 34 | EK156: 24.9 | EY156: 45.2 | EZ156: 46.6 | FG156: 56.3 | FP156: 40.3 | FX156: 29.9 | FY156: 30.9 | GA156: 52.3 | GC156: 52.2 | GF156: 27.2 | GZ156: 21.6 | HC156: 18.8 | JX156: 30.2 | JY156: 30 | JZ156: 29.3 | KD156: 29.8 | KE156: 30.9 | KG156: 50.3 | KH156: 26.8 | KJ156: 35.9 | KT156: 2.0886667e+09 | KU156: 1.0690833e+11 | KV156: 5.8174667e+10 | KW156: 1.5445333e+10 | KX156: 6691000000 | KY156: 4.9873333e+09 | KZ156: 8.9066667e+08 | LA156: 813000000 | LB156: 5.2156667e+09 | LC156: 2.8996667e+09 | LD156: 1.5033333e+09 | LE156: 592000000 | LF156: 221000000 | LG156: 2.1306667e+09 | LH156: 1100000000 | LI156: 4.0633333e+08 | LJ156: 2.7966667e+08 | LK156: 270000000 | LL156: 74666667 | LM156: 1408000000 | LN156: 651000000 | LO156: 283000000 | LP156: 91000000 | LQ156: 3.7966667e+08 | LR156: 3000000 | LS156: 4.2729333e+10 | LT156: 2.0589333e+10 | LU156: 1.8020333e+10 | LV156: 2139000000 | LW156: 4.3033333e+08 | LX156: 8480000000 | LY156: 6.7463333e+09 | LZ156: 4146000000 | MA156: 2.5043333e+09 | MB156: 96000000 | MC156: 1.7336667e+09 | MD156: 5.0693333e+09 | ME156: 3.7496667e+09 | MF156: 1.3196667e+09 | MG156: 8.5906667e+09 | MH156: 1.0753333e+09 | MI156: 1.0343333e+09 | MJ156: 1.8336667e+09 | MK156: 9.7033333e+08 | ML156: 2195000000 | MM156: 1157000000 | MN156: 3.2533333e+08 | MO156: 4.8733667e+10 | MP156: 47089000000 | MQ156: 1.7799333e+10 | MR156: 14791000000 | MS156: 4.2076667e+09 | MT156: 9.7866667e+09 | MU156: 6.8733333e+08 | MV156: 1.0933333e+08 | MW156: 3.0083333e+09 | MX156: 4.1433333e+08 | MY156: 2594000000 | MZ156: 1584000000 | NA156: 1010000000 | NB156: 4.9796667e+09 | NC156: 2.9073333e+09 | ND156: 1858000000 | NE156: 6.5033333e+08 | NF156: 3.9933333e+08 | NG156: 2.0723333e+09 | NH156: 1966000000 | NI156: 106000000 | NJ156: 2.9433333e+09 | NK156: 1851000000 | NL156: 1.6296667e+09 | NM156: 2.2133333e+08 | NN156: 1.0923333e+09 | NO156: 890000000 | NP156: 202000000 | NQ156: 333333.33 | NR156: 2.0033333e+09 | NS156: 1175000000 | NT156: 5.2766667e+08 | NU156: 2.1833333e+08 | NV156: 82333333 | NW156: 6.6976667e+09 | NX156: 6.3296667e+09 | NY156: 5.9256667e+09 | NZ156: 404000000 | OA156: 368000000 | OB156: 4.0873333e+09 | OC156: 1.7736667e+09 | OD156: 1.0666667e+09 | OE156: 707000000 | OF156: 2314000000 | OG156: 1048000000 | OH156: 49333333 | OI156: 5.6266667e+08 | OJ156: 654000000 | OK156: 8.5783333e+09 | OL156: 1.6176667e+09 | OM156: 1.4063333e+09 | ON156: 2.1133333e+08 | OP156: 9.5066667e+08 | OQ156: 461000000 | OR156: 298000000 | OS156: 1.9166667e+08 | OT156: 1.4553333e+09 | OU156: 5.2666667e+08 | OV156: 1.5913333e+09 | OW156: 348000000 | OX156: 7.0933333e+08 | OY156: 3.6133333e+08 | OZ156: 1645000000 | PA156: 4.6826667e+09 | PB156: 3.0376667e+09
A157: 21794 | B157: 29.25 | D157: 24.8 | L157: 25.5 | N157: 13.8 | O157: 13.5 | Q157: 22.7 | R157: 29.7 | S157: 16.9 | AQ157: 29.7 | AR157: 31.1 | BH157: 33 | BI157: 32.4 | BJ157: 34.4 | BK157: 36.1 | BM157: 31.1 | BO157: 26.7 | BS157: 35.4 | CB157: 22.4 | CG157: 55.1 | CJ157: 40.1 | CO157: 29.3 | CP157: 26.6 | CQ157: 26.1 | CR157: 24.7 | CS157: 40.6 | CU157: 21.6 | CW157: 27.4 | CX157: 24.4 | CZ157: 35.8 | DI157: 21 | DX157: 34.8 | EK157: 25 | EY157: 45.3 | EZ157: 46.5 | FG157: 56.6 | FP157: 40.4 | FX157: 30 | FY157: 30.9 | GA157: 52.5 | GC157: 52.4 | GF157: 27.5 | GZ157: 21.7 | HC157: 18.9 | JX157: 30.3 | JY157: 30.1 | JZ157: 29.3 | KD157: 29.9 | KE157: 31 | KG157: 50.3 | KH157: 26.9 | KJ157: 35.9 | KT157: 2.0886667e+09 | KU157: 1.0690833e+11 | KV157: 5.8174667e+10 | KW157: 1.5445333e+10 | KX157: 6691000000 | KY157: 4.9873333e+09 | KZ157: 8.9066667e+08 | LA157: 813000000 | LB157: 5.2156667e+09 | LC157: 2.8996667e+09 | LD157: 1.5033333e+09 | LE157: 592000000 | LF157: 221000000 | LG157: 2.1306667e+09 | LH157: 1100000000 | LI157: 4.0633333e+08 | LJ157: 2.7966667e+08 | LK157: 270000000 | LL157: 74666667 | LM157: 1408000000 | LN157: 651000000 | LO157: 283000000 | LP157: 91000000 | LQ157: 3.7966667e+08 | LR157: 3000000 | LS157: 4.2729333e+10 | LT157: 2.0589333e+10 | LU157: 1.8020333e+10 | LV157: 2139000000 | LW157: 4.3033333e+08 | LX157: 8480000000 | LY157: 6.7463333e+09 | LZ157: 4146000000 | MA157: 2.5043333e+09 | MB157: 96000000 | MC157: 1.7336667e+09 | MD157: 5.0693333e+09 | ME157: 3.7496667e+09 | MF157: 1.3196667e+09 | MG157: 8.5906667e+09 | MH157: 1.0753333e+09 | MI157: 1.0343333e+09 | MJ157: 1.8336667e+09 | MK157: 9.7033333e+08 | ML157: 2195000000 | MM157: 1157000000 | MN157: 3.2533333e+08 | MO157: 4.8733667e+10 | MP157: 47089000000 | MQ157: 1.7799333e+10 | MR157: 14791000000 | MS157: 4.2076667e+09 | MT157: 9.7866667e+09 | MU157: 6.8733333e+08 | MV157: 1.0933333e+08 | MW157: 3.0083333e+09 | MX157: 4.1433333e+08 | MY157: 2594000000 | MZ157: 1584000000 | NA157: 1010000000 | NB157: 4.9796667e+09 | NC157: 2.9073333e+09 | ND157: 1858000000 | NE157: 6.5033333e+08 | NF157: 3.9933333e+08 | NG157: 2.0723333e+09 | NH157: 1966000000 | NI157: 106000000 | NJ157: 2.9433333e+09 | NK157: 1851000000 | NL157: 1.6296667e+09 | NM157: 2.2133333e+08 | NN157: 1.0923333e+09 | NO157: 890000000 | NP157: 202000000 | NQ157: 333333.33 | NR157: 2.0033333e+09 | NS157: 1175000000 | NT157: 5.2766667e+08 | NU157: 2.1833333e+08 | NV157: 82333333 | NW157: 6.6976667e+09 | NX157: 6.3296667e+09 | NY157: 5.9256667e+09 | NZ157: 404000000 | OA157: 368000000 | OB157: 4.0873333e+09 | OC157: 1.7736667e+09 | OD157: 1.0666667e+09 | OE157: 707000000 | OF157: 2314000000 | OG157: 1048000000 | OH157: 49333333 | OI157: 5.6266667e+08 | OJ157: 654000000 | OK157: 8.5783333e+09 | OL157: 1.6176667e+09 | OM157: 1.4063333e+09 | ON157: 2.1133333e+08 | OP157: 9.5066667e+08 | OQ157: 461000000 | OR157: 298000000 | OS157: 1.9166667e+08 | OT157: 1.4553333e+09 | OU157: 5.2666667e+08 | OV157: 1.5913333e+09 | OW157: 348000000 | OX157: 7.0933333e+08 | OY157: 3.6133333e+08 | OZ157: 1645000000 | PA157: 4.6826667e+09 | PB157: 3.0376667e+09
A158: 21824 | B158: 29.35 | D158: 24.9 | L158: 25.5 | N158: 13.8 | O158: 13.4 | Q158: 22.7 | R158: 29.7 | S158: 16.9 | AQ158: 29.7 | AR158: 31.2 | BH158: 32.8 | BI158: 32.3 | BJ158: 34.4 | BK158: 36 | BM158: 31.2 | BO158: 26.4 | BS158: 35.1 | CB158: 22.3 | CG158: 52.4 | CJ158: 40.1 | CO158: 29.5 | CP158: 27.1 | CQ158: 26.2 | CR158: 25.1 | CS158: 42.9 | CU158: 21.9 | CW158: 28.2 | CX158: 25.2 | CZ158: 39.1 | DI158: 21.1 | DX158: 34.6 | EK158: 25 | EY158: 45.3 | EZ158: 46.4 | FG158: 56.6 | FP158: 40.6 | FX158: 30.1 | FY158: 31 | GA158: 52.4 | GC158: 52.3 | GF158: 27 | GZ158: 21.7 | HC158: 19 | JX158: 30.4 | JY158: 30.2 | JZ158: 29.4 | KD158: 29.9 | KE158: 31 | KG158: 50.4 | KH158: 27 | KJ158: 36 | KT158: 2.1416667e+09 | KU158: 107614000000 | KV158: 5.7854667e+10 | KW158: 14701000000 | KX158: 5886000000 | KY158: 4.0343333e+09 | KZ158: 1.0456667e+09 | LA158: 806000000 | LB158: 5.2443333e+09 | LC158: 2.9086667e+09 | LD158: 1.5153333e+09 | LE158: 5.9633333e+08 | LF158: 224000000 | LG158: 2140000000 | LH158: 1.0936667e+09 | LI158: 411000000 | LJ158: 279000000 | LK158: 282000000 | LL158: 74333333 | LM158: 1431000000 | LN158: 6.6266667e+08 | LO158: 2.8733333e+08 | LP158: 95000000 | LQ158: 3.8266667e+08 | LR158: 3000000 | LS158: 4.3153667e+10 | LT158: 20706000000 | LU158: 1.8147667e+10 | LV158: 2.1413333e+09 | LW158: 4.1733333e+08 | LX158: 8580000000 | LY158: 6817000000 | LZ158: 4.1923333e+09 | MA158: 2.5266667e+09 | MB158: 97666667 | MC158: 1763000000 | MD158: 5.1826667e+09 | ME158: 3.9066667e+09 | MF158: 1276000000 | MG158: 8685000000 | MH158: 1.0883333e+09 | MI158: 1050000000 | MJ158: 1862000000 | MK158: 9.8566667e+08 | ML158: 2.2683333e+09 | MM158: 1.1346667e+09 | MN158: 296000000 | MO158: 49759000000 | MP158: 4.8071667e+10 | MQ158: 1.8170667e+10 | MR158: 1.5094333e+10 | MS158: 4.2763333e+09 | MT158: 1.0009333e+10 | MU158: 7.0266667e+08 | MV158: 106000000 | MW158: 3.0763333e+09 | MX158: 4.3333333e+08 | MY158: 2643000000 | MZ158: 1.6186667e+09 | NA158: 1.0243333e+09 | NB158: 5.0653333e+09 | NC158: 2.9493333e+09 | ND158: 1.8776667e+09 | NE158: 653000000 | NF158: 4.1866667e+08 | NG158: 2116000000 | NH158: 1.9996667e+09 | NI158: 116000000 | NJ158: 2.9943333e+09 | NK158: 1889000000 | NL158: 1662000000 | NM158: 227000000 | NN158: 1.1053333e+09 | NO158: 8.9233333e+08 | NP158: 2.1266667e+08 | NQ158: 333333.33 | NR158: 2.0523333e+09 | NS158: 1.2163333e+09 | NT158: 5.2466667e+08 | NU158: 2.2533333e+08 | NV158: 86000000 | NW158: 6.8153333e+09 | NX158: 6433000000 | NY158: 6029000000 | NZ158: 404000000 | OA158: 3.8233333e+08 | OB158: 4216000000 | OC158: 1.8353333e+09 | OD158: 1.1033333e+09 | OE158: 732000000 | OF158: 2.3806667e+09 | OG158: 1.0726667e+09 | OH158: 51000000 | OI158: 5.8266667e+08 | OJ158: 6.7433333e+08 | OK158: 8.7573333e+09 | OL158: 1.6473333e+09 | OM158: 1.4293333e+09 | ON158: 218000000 | OP158: 9.6566667e+08 | OQ158: 4.7033333e+08 | OR158: 303000000 | OS158: 1.9233333e+08 | OT158: 1.4793333e+09 | OU158: 5.3866667e+08 | OV158: 1614000000 | OW158: 3.7066667e+08 | OX158: 7.3066667e+08 | OY158: 360000000 | OZ158: 1.6873333e+09 | PA158: 4.7776667e+09 | PB158: 3090000000
A159: 21855 | B159: 29.35 | D159: 25 | L159: 25.5 | N159: 13.8 | O159: 13.5 | Q159: 22.8 | R159: 29.7 | S159: 16.9 | AQ159: 29.7 | AR159: 31.1 | BH159: 32.8 | BI159: 32.3 | BJ159: 34 | BK159: 35.7 | BM159: 30.8 | BO159: 26.3 | BS159: 35 | CB159: 22.4 | CG159: 52.5 | CJ159: 40.1 | CO159: 29.3 | CP159: 26.8 | CQ159: 26.3 | CR159: 25.1 | CS159: 40 | CU159: 22.7 | CW159: 27.5 | CX159: 26 | CZ159: 34.6 | DI159: 21.1 | DX159: 34.7 | EK159: 25.1 | EY159: 45.3 | EZ159: 46.4 | FG159: 56.5 | FP159: 40.8 | FX159: 30.1 | FY159: 31 | GA159: 52.3 | GC159: 52.2 | GF159: 27 | GZ159: 21.8 | HC159: 19 | JX159: 30.4 | JY159: 30.2 | JZ159: 29.4 | KD159: 29.9 | KE159: 31 | KG159: 50.3 | KH159: 27 | KJ159: 36 | KT159: 2.1416667e+09 | KU159: 107614000000 | KV159: 5.7854667e+10 | KW159: 14701000000 | KX159: 5886000000 | KY159: 4.0343333e+09 | KZ159: 1.0456667e+09 | LA159: 806000000 | LB159: 5.2443333e+09 | LC159: 2.9086667e+09 | LD159: 1.5153333e+09 | LE159: 5.9633333e+08 | LF159: 224000000 | LG159: 2140000000 | LH159: 1.0936667e+09 | LI159: 411000000 | LJ159: 279000000 | LK159: 282000000 | LL159: 74333333 | LM159: 1431000000 | LN159: 6.6266667e+08 | LO159: 2.8733333e+08 | LP159: 95000000 | LQ159: 3.8266667e+08 | LR159: 3000000 | LS159: 4.3153667e+10 | LT159: 20706000000 | LU159: 1.8147667e+10 | LV159: 2.1413333e+09 | LW159: 4.1733333e+08 | LX159: 8580000000 | LY159: 6817000000 | LZ159: 4.1923333e+09 | MA159: 2.5266667e+09 | MB159: 97666667 | MC159: 1763000000 | MD159: 5.1826667e+09 | ME159: 3.9066667e+09 | MF159: 1276000000 | MG159: 8685000000 | MH159: 1.0883333e+09 | MI159: 1050000000 | MJ159: 1862000000 | MK159: 9.8566667e+08 | ML159: 2.2683333e+09 | MM159: 1.1346667e+09 | MN159: 296000000 | MO159: 49759000000 | MP159: 4.8071667e+10 | MQ159: 1.8170667e+10 | MR159: 1.5094333e+10 | MS159: 4.2763333e+09 | MT159: 1.0009333e+10 | MU159: 7.0266667e+08 | MV159: 106000000 | MW159: 3.0763333e+09 | MX159: 4.3333333e+08 | MY159: 2643000000 | MZ159: 1.6186667e+09 | NA159: 1.0243333e+09 | NB159: 5.0653333e+09 | NC159: 2.9493333e+09 | ND159: 1.8776667e+09 | NE159: 653000000 | NF159: 4.1866667e+08 | NG159: 2116000000 | NH159: 1.9996667e+09 | NI159: 116000000 | NJ159: 2.9943333e+09 | NK159: 1889000000 | NL159: 1662000000 | NM159: 227000000 | NN159: 1.1053333e+09 | NO159: 8.9233333e+08 | NP159: 2.1266667e+08 | NQ159: 333333.33 | NR159: 2.0523333e+09 | NS159: 1.2163333e+09 | NT159: 5.2466667e+08 | NU159: 2.2533333e+08 | NV159: 86000000 | NW159: 6.8153333e+09 | NX159: 6433000000 | NY159: 6029000000 | NZ159: 404000000 | OA159: 3.8233333e+08 | OB159: 4216000000 | OC159: 1.8353333e+09 | OD159: 1.1033333e+09 | OE159: 732000000 | OF159: 2.3806667e+09 | OG159: 1.0726667e+09 | OH159: 51000000 | OI159: 5.8266667e+08 | OJ159: 6.7433333e+08 | OK159: 8.7573333e+09 | OL159: 1.6473333e+09 | OM159: 1.4293333e+09 | ON159: 218000000 | OP159: 9.6566667e+08 | OQ159: 4.7033333e+08 | OR159: 303000000 | OS159: 1.9233333e+08 | OT159: 1.4793333e+09 | OU159: 5.3866667e+08 | OV159: 1614000000 | OW159: 3.7066667e+08 | OX159: 7.3066667e+08 | OY159: 360000000 | OZ159: 1.6873333e+09 | PA159: 4.7776667e+09 | PB159: 3090000000
A160: 21885 | B160: 29.41 | D160: 25 | L160: 25.7 | N160: 13.8 | O160: 13.5 | Q160: 23 | R160: 29.8 | S160: 17.1 | AQ160: 29.6 | AR160: 31.1 | BH160: 32.7 | BI160: 31.9 | BJ160: 33.9 | BK160: 35.5 | BM160: 30.3 | BO160: 25.6 | BS160: 34 | CB160: 22.4 | CG160: 52.1 | CJ160: 40.3 | CO160: 29.5 | CP160: 27.3 | CQ160: 27 | CR160: 25.5 | CS160: 38.7 | CU160: 24.2 | CW160: 28 | CX160: 26.3 | CZ160: 36 | DI160: 21.1 | DX160: 35.4 | EK160: 25.1 | EY160: 45.3 | EZ160: 46.4 | FG160: 56.4 | FP160: 40.9 | FX160: 30.1 | FY160: 31.1 | GA160: 52.4 | GC160: 52.3 | GF160: 27.2 | GZ160: 21.8 | HC160: 19.1 | JX160: 30.5 | JY160: 30.2 | JZ160: 29.5 | KD160: 30 | KE160: 31.1 | KG160: 50.3 | KH160: 27.2 | KJ160: 36 | KT160: 2.1416667e+09 | KU160: 107614000000 | KV160: 5.7854667e+10 | KW160: 14701000000 | KX160: 5886000000 | KY160: 4.0343333e+09 | KZ160: 1.0456667e+09 | LA160: 806000000 | LB160: 5.2443333e+09 | LC160: 2.9086667e+09 | LD160: 1.5153333e+09 | LE160: 5.9633333e+08 | LF160: 224000000 | LG160: 2140000000 | LH160: 1.0936667e+09 | LI160: 411000000 | LJ160: 279000000 | LK160: 282000000 | LL160: 74333333 | LM160: 1431000000 | LN160: 6.6266667e+08 | LO160: 2.8733333e+08 | LP160: 95000000 | LQ160: 3.8266667e+08 | LR160: 3000000 | LS160: 4.3153667e+10 | LT160: 20706000000 | LU160: 1.8147667e+10 | LV160: 2.1413333e+09 | LW160: 4.1733333e+08 | LX160: 8580000000 | LY160: 6817000000 | LZ160: 4.1923333e+09 | MA160: 2.5266667e+09 | MB160: 97666667 | MC160: 1763000000 | MD160: 5.1826667e+09 | ME160: 3.9066667e+09 | MF160: 1276000000 | MG160: 8685000000 | MH160: 1.0883333e+09 | MI160: 1050000000 | MJ160: 1862000000 | MK160: 9.8566667e+08 | ML160: 2.2683333e+09 | MM160: 1.1346667e+09 | MN160: 296000000 | MO160: 49759000000 | MP160: 4.8071667e+10 | MQ160: 1.8170667e+10 | MR160: 1.5094333e+10 | MS160: 4.2763333e+09 | MT160: 1.0009333e+10 | MU160: 7.0266667e+08 | MV160: 106000000 | MW160: 3.0763333e+09 | MX160: 4.3333333e+08 | MY160: 2643000000 | MZ160: 1.6186667e+09 | NA160: 1.0243333e+09 | NB160: 5.0653333e+09 | NC160: 2.9493333e+09 | ND160: 1.8776667e+09 | NE160: 653000000 | NF160: 4.1866667e+08 | NG160: 2116000000 | NH160: 1.9996667e+09 | NI160: 116000000 | NJ160: 2.9943333e+09 | NK160: 1889000000 | NL160: 1662000000 | NM160: 227000000 | NN160: 1.1053333e+09 | NO160: 8.9233333e+08 | NP160: 2.1266667e+08 | NQ160: 333333.33 | NR160: 2.0523333e+09 | NS160: 1.2163333e+09 | NT160: 5.2466667e+08 | NU160: 2.2533333e+08 | NV160: 86000000 | NW160: 6.8153333e+09 | NX160: 6433000000 | NY160: 6029000000 | NZ160: 404000000 | OA160: 3.8233333e+08 | OB160: 4216000000 | OC160: 1.8353333e+09 | OD160: 1.1033333e+09 | OE160: 732000000 | OF160: 2.3806667e+09 | OG160: 1.0726667e+09 | OH160: 51000000 | OI160: 5.8266667e+08 | OJ160: 6.7433333e+08 | OK160: 8.7573333e+09 | OL160: 1.6473333e+09 | OM160: 1.4293333e+09 | ON160: 218000000 | OP160: 9.6566667e+08 | OQ160: 4.7033333e+08 | OR160: 303000000 | OS160: 1.9233333e+08 | OT160: 1.4793333e+09 | OU160: 5.3866667e+08 | OV160: 1614000000 | OW160: 3.7066667e+08 | OX160: 7.3066667e+08 | OY160: 360000000 | OZ160: 1.6873333e+09 | PA160: 4.7776667e+09 | PB160: 3090000000
... A244: 24442 | B244: 32.92 | D244: 28.3 | L244: 26.8 | N244: 15.2 | O244: 14.8 | Q244: 23.5 | R244: 29.7 | S244: 18 | AQ244: 34 | AR244: 35.3 | BH244: 37.3 | BI244: 37.4 | BJ244: 36.2 | BK244: 38.2 | BM244: 39.8 | BO244: 37.4 | BS244: 42.2 | CB244: 26.5 | CG244: 61.5 | CJ244: 44.6 | CO244: 33.2 | CP244: 32.3 | CQ244: 32 | CR244: 34.4 | CS244: 38.6 | CU244: 27 | CW244: 32.4 | CX244: 33.1 | CZ244: 36.9 | DI244: 23.3 | DX244: 39.6 | EK244: 30.4 | EY244: 49.9 | EZ244: 52 | FG244: 60.2 | FP244: 47.1 | FX244: 32.6 | FY244: 33.1 | GA244: 48.9 | GC244: 48.8 | GF244: 28.2 | GZ244: 27.2 | HC244: 24.9 | JX244: 34.1 | JY244: 33.9 | JZ244: 32.8 | KD244: 33.4 | KE244: 34.7 | KG244: 54.2 | KH244: 29.5 | KJ244: 38 | KT244: 3.0786667e+09 | KU244: 1.6335333e+11 | KV244: 84340000000 | KW244: 2.4208333e+10 | KX244: 9861000000 | KY244: 7.2206667e+09 | KZ244: 1.3563333e+09 | LA244: 1284000000 | LB244: 7.6943333e+09 | LC244: 4496000000 | LD244: 1806000000 | LE244: 9.7266667e+08 | LF244: 4.1933333e+08 | LG244: 4.3533333e+09 | LH244: 2.3516667e+09 | LI244: 7.7433333e+08 | LJ244: 610000000 | LK244: 4.5333333e+08 | LL244: 1.6433333e+08 | LM244: 2300000000 | LN244: 1.0743333e+09 | LO244: 455000000 | LP244: 153000000 | LQ244: 612000000 | LR244: 5666666.7 | LS244: 6.0131333e+10 | LT244: 2.7030667e+10 | LU244: 23897000000 | LV244: 2.8656667e+09 | LW244: 268000000 | LX244: 1.2109333e+10 | LY244: 9738000000 | LZ244: 5943000000 | MA244: 3.6286667e+09 | MB244: 1.6633333e+08 | MC244: 2.3713333e+09 | MD244: 7113000000 | ME244: 5.5056667e+09 | MF244: 1.6073333e+09 | MG244: 1.3878667e+10 | MH244: 1.6576667e+09 | MI244: 2.0356667e+09 | MJ244: 3235000000 | MK244: 1.8353333e+09 | ML244: 2.8816667e+09 | MM244: 1771000000 | MN244: 4.6266667e+08 | MO244: 7.9013333e+10 | MP244: 7.6555667e+10 | MQ244: 2.7696333e+10 | MR244: 2.3048667e+10 | MS244: 6.5656667e+09 | MT244: 1.5495333e+10 | MU244: 8.7366667e+08 | MV244: 114000000 | MW244: 4648000000 | MX244: 718000000 | MY244: 3930000000 | MZ244: 2396000000 | NA244: 1534000000 | NB244: 1.0205333e+10 | NC244: 5.5063333e+09 | ND244: 3285000000 | NE244: 1.0816667e+09 | NF244: 1.1396667e+09 | NG244: 4699000000 | NH244: 3.9833333e+09 | NI244: 7.1566667e+08 | NJ244: 4537000000 | NK244: 2.9636667e+09 | NL244: 2.6016667e+09 | NM244: 362000000 | NN244: 1.5733333e+09 | NO244: 1022000000 | NP244: 5.5066667e+08 | NQ244: 1000000 | NR244: 3424000000 | NS244: 1.8946667e+09 | NT244: 9.0066667e+08 | NU244: 4.1066667e+08 | NV244: 218000000 | NW244: 1.0036667e+10 | NX244: 9.3706667e+09 | NY244: 8.7386667e+09 | NZ244: 632000000 | OA244: 666000000 | OB244: 6.8586667e+09 | OC244: 3.0153333e+09 | OD244: 1.7743333e+09 | OE244: 1241000000 | OF244: 3843000000 | OG244: 1.7706667e+09 | OH244: 76000000 | OI244: 9.8666667e+08 | OJ244: 1.0096667e+09 | OK244: 1.3797667e+10 | OL244: 2.8176667e+09 | OM244: 2445000000 | ON244: 3.7266667e+08 | OP244: 2.0136667e+09 | OQ244: 1.0863333e+09 | OR244: 5.8233333e+08 | OS244: 345000000 | OT244: 2341000000 | OU244: 9.0833333e+08 | OV244: 2.0033333e+09 | OW244: 6.3466667e+08 | OX244: 1244000000 | OY244: 6.0933333e+08 | OZ244: 2.4576667e+09 | PA244: 8330000000 | PB244: 5.8723333e+09
A245: 24473 | B245: 32.9 | C245: 30.5 | D245: 28.4 | I245: 26.4 | L245: 27 | M245: 21.3 | N245: 15.3 | O245: 15 | Q245: 23.6 | R245: 29.8 | S245: 18 | W245: 41.6 | AL245: 33.7 | AP245: 34.8 | AQ245: 33.9 | AR245: 35.1 | BG245: 38.1 | BH245: 37.1 | BI245: 37.3 | BJ245: 36.1 | BK245: 38.2 | BM245: 39.7 | BO245: 37 | BS245: 42.8 | CB245: 26.7 | CG245: 55.3 | CJ245: 44.6 | CO245: 32.8 | CP245: 31.5 | CQ245: 32.1 | CR245: 33.6 | CS245: 40.1 | CU245: 26.2 | CW245: 31.2 | CX245: 33.6 | CZ245: 40.9 | DI245: 23.2 | DQ245: 29.3 | DX245: 39.3 | EK245: 30.6 | EP245: 45.8 | EY245: 50.1 | EZ245: 52.1 | FG245: 60.6 | FP245: 47.4 | FX245: 32.6 | FY245: 33.1 | GA245: 48.6 | GC245: 48.5 | GF245: 28.6 | GH245: 26.2 | GI245: 26.3 | GP245: 29.8 | GZ245: 27.4 | HA245: 45.1 | HC245: 25.1 | IU245: 32.9 | JJ245: 34.5 | JQ245: 35.3 | JX245: 34.2 | JY245: 34 | JZ245: 32.9 | KA245: 35.2 | KB245: 38 | KC245: 38.9 | KD245: 33.3 | KE245: 34.8 | KG245: 54.4 | KH245: 29.5 | KJ245: 38.1 | KK245: 37.8 | KL245: 42.2 | KT245: 3089000000 | KU245: 1.6477233e+11 | KV245: 8.4492333e+10 | KW245: 2.3700667e+10 | KX245: 9.2626667e+09 | KY245: 6.5996667e+09 | KZ245: 1.3753333e+09 | LA245: 1.2876667e+09 | LB245: 7748000000 | LC245: 4.5116667e+09 | LD245: 1827000000 | LE245: 9.7233333e+08 | LF245: 437000000 | LG245: 4.3746667e+09 | LH245: 2.3756667e+09 | LI245: 778000000 | LJ245: 597000000 | LK245: 460000000 | LL245: 1.6466667e+08 | LM245: 2315000000 | LN245: 1.0916667e+09 | LO245: 446000000 | LP245: 1.5533333e+08 | LQ245: 6.1666667e+08 | LR245: 5666666.7 | LS245: 6.0791667e+10 | LT245: 2.7289333e+10 | LU245: 2.4096667e+10 | LV245: 2935000000 | LW245: 258000000 | LX245: 1.2253333e+10 | LY245: 9.8383333e+09 | LZ245: 5.9833333e+09 | MA245: 3.6833333e+09 | MB245: 1.7166667e+08 | MC245: 2.4146667e+09 | MD245: 7.1503333e+09 | ME245: 5.5593333e+09 | MF245: 1591000000 | MG245: 1.4098667e+10 | MH245: 1.6906667e+09 | MI245: 2.0676667e+09 | MJ245: 3.2463333e+09 | MK245: 1863000000 | ML245: 2.8716667e+09 | MM245: 1.8996667e+09 | MN245: 460000000 | MO245: 8.0280333e+10 | MP245: 77771000000 | MQ245: 28024000000 | MR245: 23369000000 | MS245: 6.6483333e+09 | MT245: 1.5714333e+10 | MU245: 8.8733333e+08 | MV245: 119000000 | MW245: 4655000000 | MX245: 723000000 | MY245: 3932000000 | MZ245: 2432000000 | NA245: 1500000000 | NB245: 1.0397667e+10 | NC245: 5557000000 | ND245: 3357000000 | NE245: 1.1123333e+09 | NF245: 1.0876667e+09 | NG245: 4.8406667e+09 | NH245: 4.0946667e+09 | NI245: 746000000 | NJ245: 4.6286667e+09 | NK245: 3.0256667e+09 | NL245: 2659000000 | NM245: 3.6666667e+08 | NN245: 1603000000 | NO245: 1.0333333e+09 | NP245: 5.6866667e+08 | NQ245: 1000000 | NR245: 3.4723333e+09 | NS245: 1.9023333e+09 | NT245: 9.3066667e+08 | NU245: 418000000 | NV245: 2.2133333e+08 | NW245: 1.0111667e+10 | NX245: 9.4166667e+09 | NY245: 8.7673333e+09 | NZ245: 6.4933333e+08 | OA245: 695000000 | OB245: 7.0963333e+09 | OC245: 3.2493333e+09 | OD245: 1817000000 | OE245: 1.4323333e+09 | OF245: 3847000000 | OG245: 1.7606667e+09 | OH245: 78000000 | OI245: 9.6666667e+08 | OJ245: 1.0416667e+09 | OK245: 1.4040667e+10 | OL245: 2.8726667e+09 | OM245: 2.4873333e+09 | ON245: 385000000 | OP245: 2.0666667e+09 | OQ245: 1.1093333e+09 | OR245: 5.9466667e+08 | OS245: 3.6266667e+08 | OT245: 2.3393333e+09 | OU245: 9.3733333e+08 | OV245: 2009000000 | OW245: 7.2666667e+08 | OX245: 1336000000 | OY245: 6.0933333e+08 | OZ245: 2.5093333e+09 | PA245: 8.5156667e+09 | PB245: 6.0063333e+09
