Workbook
Name Macrobond_Object1: Macrobond!$A$3:$BP$1052
Name Macrobond_Object2: Macrobond!$C$4:$WW$1054

Sheet Dashboard
B1: U.S. EMPLOYMENT SITUATION DASHBOARD
B2: ="Latest: "&TEXT(Engine!$B$4,"mmmm yyyy")&" • Auto-updates when a new vintage lands in the Macrobond tab • Seasonally adjusted unless noted" -> Latest: May 2026 • Auto-updates when a new vintage lands in the Macrobond tab • Seasonally adjusted unless noted
B3: ="U-3 "&TEXT($B$7,"0.0")&"% (unrounded "&TEXT($D$7,"0.000")&", MoM "&TEXT($D$8,"+0.000;-0.000")&") • EPOP "&TEXT($F$7,"0.0")&" ("&TEXT($F$8,"+0.0;-0.0")&"pp) • HH emp "&TEXT($L$8,"+#,##0;-#,##0")&"k MoM • Sahm "&TEXT($C$57,"0.00")&IF($C$57>=0.5," ⚠ TRIGGERED"," (no trigger)") -> U-3 4.3% (unrounded 4.296, MoM -0.041) • EPOP 59.2 (+0.1pp) • HH emp +149k MoM • Sahm 0.10 (no trigger) | T3: ="HH vs CES YoY: "&TEXT($T$7,"+#,##0;-#,##0")&"k vs "&TEXT($W$7,"+#,##0;-#,##0")&"k → gap "&TEXT($Z$7,"+#,##0;-#,##0")&"k" -> HH vs CES YoY: -473k vs +435k → gap -908k | AK3: ="NFP "&TEXT($AK$7,"+#,##0;-#,##0")&"k • 3M "&TEXT($AQ$7,"+#,##0;-#,##0")&"k • YoY "&TEXT($AT$7,"+#,##0;-#,##0")&"k • AWE "&TEXT($AZ$7,"+0.0%;-0.0%")&" YoY • breadth "&TEXT($AY$79,"0%")&" • best: "&LEFT($AL$56,38)&" • worst: "&LEFT($AL$67,38) -> NFP +172k • 3M +188k • YoY +503k • AWE +3.7% YoY • breadth 58% • best: Trade, Transportation & Utilities, Tra • worst: Trade, Transportation & Utilities, Tra
B4: HOUSEHOLD SURVEY (CPS) | T4: CONCEPT RECONCILIATION — CPS vs CES | AK4: ESTABLISHMENT SURVEY (CES) — seasonally adjusted
B6: U-3 headline | D6: U-3 unrounded (3dp) | F6: EPOP | H6: LFPR | J6: Labor force (mn) | L6: Employed (mn) | T6: HH employ YoY (k) | W6: Payrolls YoY (k) | Z6: HH−CES YoY gap (k) | AK6: Nonfarm payrolls Δ (k) | AN6: Private Δ (k) | AQ6: 3M avg pace (k) | AT6: Payrolls YoY (k) | AW6: Avg wkly hrs (priv) | AZ6: Avg wkly earn YoY
B7: {=INDEX(Macrobond!$IT:$IT,Engine!$B$3)} -> 4.3 | D7: {=INDEX(Macrobond!$IS:$IS,Engine!$B$3)/INDEX(Macrobond!$IO:$IO,Engine!$B$3)*100} -> 4.2962641 | F7: {=INDEX(Macrobond!$IR:$IR,Engine!$B$3)} -> 59.2 | H7: {=INDEX(Macrobond!$IP:$IP,Engine!$B$3)} -> 61.8 | J7: {=INDEX(Macrobond!$IO:$IO,Engine!$B$3)/1000000} -> 170.078 | L7: {=INDEX(Macrobond!$IQ:$IQ,Engine!$B$3)/1000000} -> 162.771 | T7: {=(INDEX(Macrobond!$IQ:$IQ,Engine!$B$3)-INDEX(Macrobond!$IQ:$IQ,Engine!$B$3-12))/1000} -> -473 | W7: {=(INDEX(Macrobond!$AI:$AI,Engine!$B$3)-INDEX(Macrobond!$AI:$AI,Engine!$B$3-12))/1000} -> 435 | Z7: =$T$7-$W$7 -> -908 | AK7: {=(INDEX(Macrobond!$QG:$QG,Engine!$B$3)-INDEX(Macrobond!$QG:$QG,Engine!$B$3-1))/1000} -> 172 | AN7: {=(INDEX(Macrobond!$QH:$QH,Engine!$B$3)-INDEX(Macrobond!$QH:$QH,Engine!$B$3-1))/1000} -> 120 | AQ7: {=(INDEX(Macrobond!$QG:$QG,Engine!$B$3)-INDEX(Macrobond!$QG:$QG,Engine!$B$3-3))/3/1000} -> 188.33333 | AT7: {=(INDEX(Macrobond!$QG:$QG,Engine!$B$3)-INDEX(Macrobond!$QG:$QG,Engine!$B$3-12))/1000} -> 503 | AW7: {=INDEX(Macrobond!$GZ:$GZ,Engine!$B$3)} -> 34.3 | AZ7: {=INDEX(Macrobond!$HV:$HV,Engine!$B$3)/INDEX(Macrobond!$HV:$HV,Engine!$B$3-12)-1} -> 0.037476426
B8: {=INDEX(Macrobond!$IT:$IT,Engine!$B$3)-INDEX(Macrobond!$IT:$IT,Engine!$B$3-1)} -> 0 | D8: {=D7-INDEX(Macrobond!$IS:$IS,Engine!$B$3-1)/INDEX(Macrobond!$IO:$IO,Engine!$B$3-1)*100} -> -0.040922321 | F8: {=INDEX(Macrobond!$IR:$IR,Engine!$B$3)-INDEX(Macrobond!$IR:$IR,Engine!$B$3-1)} -> 0.1 | H8: {=INDEX(Macrobond!$IP:$IP,Engine!$B$3)-INDEX(Macrobond!$IP:$IP,Engine!$B$3-1)} -> 0 | J8: {=(INDEX(Macrobond!$IO:$IO,Engine!$B$3)-INDEX(Macrobond!$IO:$IO,Engine!$B$3-1))/1000} -> 83 | L8: {=(INDEX(Macrobond!$IQ:$IQ,Engine!$B$3)-INDEX(Macrobond!$IQ:$IQ,Engine!$B$3-1))/1000} -> 149
T9: YoY basis (seasonally neutral): CES here is NSA, so 12M change is the clean lens. Divergence reflects measurement (CPS counts persons incl. self-employed/ag; CES counts payroll jobs). MoM SA prints wire in once SA columns are added.
B10: Headline — rates & levels | C10: =Engine!B$10 -> 45778 | D10: =Engine!C$10 -> 45809 | E10: =Engine!D$10 -> 45839 | F10: =Engine!E$10 -> 45870 | G10: =Engine!F$10 -> 45901 | H10: =Engine!G$10 -> 45931 | I10: =Engine!H$10 -> 45962 | J10: =Engine!I$10 -> 45992 | ... O10: =Engine!N$10 -> 46143 | P10: MoM | Q10: 3M | R10: YoY | T10: YoY change (000s) | U10: =Engine!B$10 -> 45778 | V10: =Engine!C$10 -> 45809 | W10: =Engine!D$10 -> 45839 | X10: =Engine!E$10 -> 45870 | Y10: =Engine!F$10 -> 45901 | Z10: =Engine!G$10 -> 45931 | AA10: =Engine!H$10 -> 45962 | AB10: =Engine!I$10 -> 45992 | ... AG10: =Engine!N$10 -> 46143 | AH10: Latest | AK10: Sector employment, SA (000s) | AL10: =Engine!B$10 -> 45778 | AM10: =Engine!C$10 -> 45809 | AN10: =Engine!D$10 -> 45839 | AO10: =Engine!E$10 -> 45870 | AP10: =Engine!F$10 -> 45901 | AQ10: =Engine!G$10 -> 45931 | AR10: =Engine!H$10 -> 45962 | AS10: =Engine!I$10 -> 45992 | ... AX10: =Engine!N$10 -> 46143 | AY10: MoM(k) | AZ10: 3Mavg(k) | BA10: YoY(k) | BB10: %NFPΔ
B11: U-3 unemployment rate (%) | C11: {=INDEX(Macrobond!$IT:$IT,Engine!B$9)} -> 4.3 | D11: {=INDEX(Macrobond!$IT:$IT,Engine!C$9)} -> 4.1 | E11: {=INDEX(Macrobond!$IT:$IT,Engine!D$9)} -> 4.3 | F11: {=INDEX(Macrobond!$IT:$IT,Engine!E$9)} -> 4.3 | G11: {=INDEX(Macrobond!$IT:$IT,Engine!F$9)} -> 4.4 | H11: {=INDEX(Macrobond!$IT:$IT,Engine!G$9)} -> 4.4 | I11: {=INDEX(Macrobond!$IT:$IT,Engine!H$9)} -> 4.5 | J11: {=INDEX(Macrobond!$IT:$IT,Engine!I$9)} -> 4.4 | ... O11: {=INDEX(Macrobond!$IT:$IT,Engine!N$9)} -> 4.3 | P11: =$O11-$N11 -> 0 | Q11: =$O11-$L11 -> -0.1 | R11: =$O11-$C11 -> 0 | T11: HH employment YoY | U11: {=(INDEX(Macrobond!$IQ:$IQ,Engine!B$9)-INDEX(Macrobond!$IQ:$IQ,Engine!B$9-12))/1000} -> 2064 | V11: {=(INDEX(Macrobond!$IQ:$IQ,Engine!C$9)-INDEX(Macrobond!$IQ:$IQ,Engine!C$9-12))/1000} -> 2175 | W11: {=(INDEX(Macrobond!$IQ:$IQ,Engine!D$9)-INDEX(Macrobond!$IQ:$IQ,Engine!D$9-12))/1000} -> 1843 | X11: {=(INDEX(Macrobond!$IQ:$IQ,Engine!E$9)-INDEX(Macrobond!$IQ:$IQ,Engine!E$9-12))/1000} -> 1941 | Y11: {=(INDEX(Macrobond!$IQ:$IQ,Engine!F$9)-INDEX(Macrobond!$IQ:$IQ,Engine!F$9-12))/1000} -> 1843 | Z11: {=(INDEX(Macrobond!$IQ:$IQ,Engine!G$9)-INDEX(Macrobond!$IQ:$IQ,Engine!G$9-12))/1000} -> 2212 | AA11: {=(INDEX(Macrobond!$IQ:$IQ,Engine!H$9)-INDEX(Macrobond!$IQ:$IQ,Engine!H$9-12))/1000} -> 2601 | AB11: {=(INDEX(Macrobond!$IQ:$IQ,Engine!I$9)-INDEX(Macrobond!$IQ:$IQ,Engine!I$9-12))/1000} -> 2406 | ... AG11: {=(INDEX(Macrobond!$IQ:$IQ,Engine!N$9)-INDEX(Macrobond!$IQ:$IQ,Engine!N$9-12))/1000} -> -473 | AH11: =$AG11 -> -473 | AK11: Total nonfarm | AL11: {=INDEX(Macrobond!$QG:$QG,Engine!B$9)/1000} -> 158498 | AM11: {=INDEX(Macrobond!$QG:$QG,Engine!C$9)/1000} -> 158478 | AN11: {=INDEX(Macrobond!$QG:$QG,Engine!D$9)/1000} -> 158542 | AO11: {=INDEX(Macrobond!$QG:$QG,Engine!E$9)/1000} -> 158472 | AP11: {=INDEX(Macrobond!$QG:$QG,Engine!F$9)/1000} -> 158548 | AQ11: {=INDEX(Macrobond!$QG:$QG,Engine!G$9)/1000} -> 158408 | AR11: {=INDEX(Macrobond!$QG:$QG,Engine!H$9)/1000} -> 158449 | AS11: {=INDEX(Macrobond!$QG:$QG,Engine!I$9)/1000} -> 158432 | ... AX11: {=INDEX(Macrobond!$QG:$QG,Engine!N$9)/1000} -> 159001 | AY11: =AX11-AW11 -> 172 | AZ11: =(AX11-AU11)/3 -> 188.33333 | BA11: =AX11-AL11 -> 503 | BB11: =IF($AY$11=0,"",AY11/$AY$11) -> 1
B12: U-3 unrounded (3dp) | C12: {=INDEX(Macrobond!$IS:$IS,Engine!B$9)/INDEX(Macrobond!$IO:$IO,Engine!B$9)*100} -> 4.2512259 | D12: {=INDEX(Macrobond!$IS:$IS,Engine!C$9)/INDEX(Macrobond!$IO:$IO,Engine!C$9)*100} -> 4.1401573 | E12: {=INDEX(Macrobond!$IS:$IS,Engine!D$9)/INDEX(Macrobond!$IO:$IO,Engine!D$9)*100} -> 4.2673051 | F12: {=INDEX(Macrobond!$IS:$IS,Engine!E$9)/INDEX(Macrobond!$IO:$IO,Engine!E$9)*100} -> 4.3221083 | G12: {=INDEX(Macrobond!$IS:$IS,Engine!F$9)/INDEX(Macrobond!$IO:$IO,Engine!F$9)*100} -> 4.4405907 | H12: {=INDEX(Macrobond!$IS:$IS,Engine!G$9)/INDEX(Macrobond!$IO:$IO,Engine!G$9)*100} -> 4.4405907 | I12: {=INDEX(Macrobond!$IS:$IS,Engine!H$9)/INDEX(Macrobond!$IO:$IO,Engine!H$9)*100} -> 4.5359418 | J12: {=INDEX(Macrobond!$IS:$IS,Engine!I$9)/INDEX(Macrobond!$IO:$IO,Engine!I$9)*100} -> 4.3750547 | ... O12: {=INDEX(Macrobond!$IS:$IS,Engine!N$9)/INDEX(Macrobond!$IO:$IO,Engine!N$9)*100} -> 4.2962641 | P12: =$O12-$N12 -> -0.040922321 | Q12: =$O12-$L12 -> -0.14464793 | R12: =$O12-$C12 -> 0.045038203 | T12: Nonfarm payrolls YoY | U12: {=(INDEX(Macrobond!$AI:$AI,Engine!B$9)-INDEX(Macrobond!$AI:$AI,Engine!B$9-12))/1000} -> 915 | V12: {=(INDEX(Macrobond!$AI:$AI,Engine!C$9)-INDEX(Macrobond!$AI:$AI,Engine!C$9-12))/1000} -> 786 | W12: {=(INDEX(Macrobond!$AI:$AI,Engine!D$9)-INDEX(Macrobond!$AI:$AI,Engine!D$9-12))/1000} -> 782 | X12: {=(INDEX(Macrobond!$AI:$AI,Engine!E$9)-INDEX(Macrobond!$AI:$AI,Engine!E$9-12))/1000} -> 712 | Y12: {=(INDEX(Macrobond!$AI:$AI,Engine!F$9)-INDEX(Macrobond!$AI:$AI,Engine!F$9-12))/1000} -> 618 | Z12: {=(INDEX(Macrobond!$AI:$AI,Engine!G$9)-INDEX(Macrobond!$AI:$AI,Engine!G$9-12))/1000} -> 502 | AA12: {=(INDEX(Macrobond!$AI:$AI,Engine!H$9)-INDEX(Macrobond!$AI:$AI,Engine!H$9-12))/1000} -> 264 | AB12: {=(INDEX(Macrobond!$AI:$AI,Engine!I$9)-INDEX(Macrobond!$AI:$AI,Engine!I$9-12))/1000} -> 69 | ... AG12: {=(INDEX(Macrobond!$AI:$AI,Engine!N$9)-INDEX(Macrobond!$AI:$AI,Engine!N$9-12))/1000} -> 435 | AH12: =$AG12 -> 435 | AK12: Total private | AL12: {=INDEX(Macrobond!$QH:$QH,Engine!B$9)/1000} -> 134937 | AM12: {=INDEX(Macrobond!$QH:$QH,Engine!C$9)/1000} -> 134892 | AN12: {=INDEX(Macrobond!$QH:$QH,Engine!D$9)/1000} -> 134957 | AO12: {=INDEX(Macrobond!$QH:$QH,Engine!E$9)/1000} -> 134937 | AP12: {=INDEX(Macrobond!$QH:$QH,Engine!F$9)/1000} -> 135005 | AQ12: {=INDEX(Macrobond!$QH:$QH,Engine!G$9)/1000} -> 135018 | AR12: {=INDEX(Macrobond!$QH:$QH,Engine!H$9)/1000} -> 135090 | AS12: {=INDEX(Macrobond!$QH:$QH,Engine!I$9)/1000} -> 135083 | ... AX12: {=INDEX(Macrobond!$QH:$QH,Engine!N$9)/1000} -> 135614 | AY12: =AX12-AW12 -> 120 | AZ12: =(AX12-AU12)/3 -> 166.33333 | BA12: =AX12-AL12 -> 677 | BB12: =IF($AY$11=0,"",AY12/$AY$11) -> 0.69767442
B13: Employment-population ratio (%) | C13: {=INDEX(Macrobond!$IR:$IR,Engine!B$9)} -> 59.7 | D13: {=INDEX(Macrobond!$IR:$IR,Engine!C$9)} -> 59.7 | E13: {=INDEX(Macrobond!$IR:$IR,Engine!D$9)} -> 59.6 | F13: {=INDEX(Macrobond!$IR:$IR,Engine!E$9)} -> 59.6 | G13: {=INDEX(Macrobond!$IR:$IR,Engine!F$9)} -> 59.7 | H13: {=INDEX(Macrobond!$IR:$IR,Engine!G$9)} -> 59.7 | I13: {=INDEX(Macrobond!$IR:$IR,Engine!H$9)} -> 59.6 | J13: {=INDEX(Macrobond!$IR:$IR,Engine!I$9)} -> 59.7 | ... O13: {=INDEX(Macrobond!$IR:$IR,Engine!N$9)} -> 59.2 | P13: =$O13-$N13 -> 0.1 | Q13: =$O13-$L13 -> -0.1 | R13: =$O13-$C13 -> -0.5 | T13: Gap (HH − CES) | U13: =U11-U12 -> 1149 | V13: =V11-V12 -> 1389 | W13: =W11-W12 -> 1061 | X13: =X11-X12 -> 1229 | Y13: =Y11-Y12 -> 1225 | Z13: =Z11-Z12 -> 1710 | AA13: =AA11-AA12 -> 2337 | AB13: =AB11-AB12 -> 2337 | ... AG13: =AG11-AG12 -> -908 | AH13: =$AG13 -> -908 | AK13: Goods-producing | AL13: {=INDEX(Macrobond!$QI:$QI,Engine!B$9)/1000} -> 21538 | AM13: {=INDEX(Macrobond!$QI:$QI,Engine!C$9)/1000} -> 21519 | AN13: {=INDEX(Macrobond!$QI:$QI,Engine!D$9)/1000} -> 21496 | AO13: {=INDEX(Macrobond!$QI:$QI,Engine!E$9)/1000} -> 21461 | AP13: {=INDEX(Macrobond!$QI:$QI,Engine!F$9)/1000} -> 21472 | AQ13: {=INDEX(Macrobond!$QI:$QI,Engine!G$9)/1000} -> 21452 | AR13: {=INDEX(Macrobond!$QI:$QI,Engine!H$9)/1000} -> 21477 | AS13: {=INDEX(Macrobond!$QI:$QI,Engine!I$9)/1000} -> 21456 | ... AX13: {=INDEX(Macrobond!$QI:$QI,Engine!N$9)/1000} -> 21555 | AY13: =AX13-AW13 -> 28 | AZ13: =(AX13-AU13)/3 -> 25 | BA13: =AX13-AL13 -> 17 | BB13: =IF($AY$11=0,"",AY13/$AY$11) -> 0.1627907
B14: Labor force participation rate (%) | C14: {=INDEX(Macrobond!$IP:$IP,Engine!B$9)} -> 62.4 | D14: {=INDEX(Macrobond!$IP:$IP,Engine!C$9)} -> 62.3 | E14: {=INDEX(Macrobond!$IP:$IP,Engine!D$9)} -> 62.2 | F14: {=INDEX(Macrobond!$IP:$IP,Engine!E$9)} -> 62.3 | G14: {=INDEX(Macrobond!$IP:$IP,Engine!F$9)} -> 62.5 | H14: {=INDEX(Macrobond!$IP:$IP,Engine!G$9)} -> 62.5 | I14: {=INDEX(Macrobond!$IP:$IP,Engine!H$9)} -> 62.5 | J14: {=INDEX(Macrobond!$IP:$IP,Engine!I$9)} -> 62.4 | ... O14: {=INDEX(Macrobond!$IP:$IP,Engine!N$9)} -> 61.8 | P14: =$O14-$N14 -> 0 | Q14: =$O14-$L14 -> -0.2 | R14: =$O14-$C14 -> -0.6 | AK14: Mining & logging | AL14: {=INDEX(Macrobond!$QJ:$QJ,Engine!B$9)/1000} -> 618 | AM14: {=INDEX(Macrobond!$QJ:$QJ,Engine!C$9)/1000} -> 616 | AN14: {=INDEX(Macrobond!$QJ:$QJ,Engine!D$9)/1000} -> 610 | AO14: {=INDEX(Macrobond!$QJ:$QJ,Engine!E$9)/1000} -> 607 | AP14: {=INDEX(Macrobond!$QJ:$QJ,Engine!F$9)/1000} -> 605 | AQ14: {=INDEX(Macrobond!$QJ:$QJ,Engine!G$9)/1000} -> 606 | AR14: {=INDEX(Macrobond!$QJ:$QJ,Engine!H$9)/1000} -> 605 | AS14: {=INDEX(Macrobond!$QJ:$QJ,Engine!I$9)/1000} -> 604 | ... AX14: {=INDEX(Macrobond!$QJ:$QJ,Engine!N$9)/1000} -> 613 | AY14: =AX14-AW14 -> 4 | AZ14: =(AX14-AU14)/3 -> 4 | BA14: =AX14-AL14 -> -5 | BB14: =IF($AY$11=0,"",AY14/$AY$11) -> 0.023255814
B15: Civilian labor force (000s) | C15: {=INDEX(Macrobond!$IO:$IO,Engine!B$9)/1000} -> 170492 | D15: {=INDEX(Macrobond!$IO:$IO,Engine!C$9)/1000} -> 170380 | E15: {=INDEX(Macrobond!$IO:$IO,Engine!D$9)/1000} -> 170412 | F15: {=INDEX(Macrobond!$IO:$IO,Engine!E$9)/1000} -> 170750 | G15: {=INDEX(Macrobond!$IO:$IO,Engine!F$9)/1000} -> 171261 | H15: {=INDEX(Macrobond!$IO:$IO,Engine!G$9)/1000} -> 171261 | I15: {=INDEX(Macrobond!$IO:$IO,Engine!H$9)/1000} -> 171541 | J15: {=INDEX(Macrobond!$IO:$IO,Engine!I$9)/1000} -> 171495 | ... O15: {=INDEX(Macrobond!$IO:$IO,Engine!N$9)/1000} -> 170078 | P15: =$O15-$N15 -> 83 | Q15: =$O15-$L15 -> -405 | R15: =$O15-$C15 -> -414 | AK15: Construction | AL15: {=INDEX(Macrobond!$QS:$QS,Engine!B$9)/1000} -> 8269 | AM15: {=INDEX(Macrobond!$QS:$QS,Engine!C$9)/1000} -> 8267 | AN15: {=INDEX(Macrobond!$QS:$QS,Engine!D$9)/1000} -> 8261 | AO15: {=INDEX(Macrobond!$QS:$QS,Engine!E$9)/1000} -> 8239 | AP15: {=INDEX(Macrobond!$QS:$QS,Engine!F$9)/1000} -> 8255 | AQ15: {=INDEX(Macrobond!$QS:$QS,Engine!G$9)/1000} -> 8243 | AR15: {=INDEX(Macrobond!$QS:$QS,Engine!H$9)/1000} -> 8279 | AS15: {=INDEX(Macrobond!$QS:$QS,Engine!I$9)/1000} -> 8272 | ... AX15: {=INDEX(Macrobond!$QS:$QS,Engine!N$9)/1000} -> 8337 | AY15: =AX15-AW15 -> 17 | AZ15: =(AX15-AU15)/3 -> 13.666667 | BA15: =AX15-AL15 -> 68 | BB15: =IF($AY$11=0,"",AY15/$AY$11) -> 0.098837209
B16: Employed (000s) | C16: {=INDEX(Macrobond!$IQ:$IQ,Engine!B$9)/1000} -> 163244 | D16: {=INDEX(Macrobond!$IQ:$IQ,Engine!C$9)/1000} -> 163327 | E16: {=INDEX(Macrobond!$IQ:$IQ,Engine!D$9)/1000} -> 163140 | F16: {=INDEX(Macrobond!$IQ:$IQ,Engine!E$9)/1000} -> 163370 | G16: {=INDEX(Macrobond!$IQ:$IQ,Engine!F$9)/1000} -> 163656 | H16: {=INDEX(Macrobond!$IQ:$IQ,Engine!G$9)/1000} -> 163656 | I16: {=INDEX(Macrobond!$IQ:$IQ,Engine!H$9)/1000} -> 163760 | J16: {=INDEX(Macrobond!$IQ:$IQ,Engine!I$9)/1000} -> 163992 | ... O16: {=INDEX(Macrobond!$IQ:$IQ,Engine!N$9)/1000} -> 162771 | P16: =$O16-$N16 -> 149 | Q16: =$O16-$L16 -> -141 | R16: =$O16-$C16 -> -473 | AK16: Manufacturing | AL16: {=INDEX(Macrobond!$RA:$RA,Engine!B$9)/1000} -> 12651 | AM16: {=INDEX(Macrobond!$RA:$RA,Engine!C$9)/1000} -> 12636 | AN16: {=INDEX(Macrobond!$RA:$RA,Engine!D$9)/1000} -> 12625 | AO16: {=INDEX(Macrobond!$RA:$RA,Engine!E$9)/1000} -> 12615 | AP16: {=INDEX(Macrobond!$RA:$RA,Engine!F$9)/1000} -> 12612 | AQ16: {=INDEX(Macrobond!$RA:$RA,Engine!G$9)/1000} -> 12603 | AR16: {=INDEX(Macrobond!$RA:$RA,Engine!H$9)/1000} -> 12593 | AS16: {=INDEX(Macrobond!$RA:$RA,Engine!I$9)/1000} -> 12580 | ... AX16: {=INDEX(Macrobond!$RA:$RA,Engine!N$9)/1000} -> 12605 | AY16: =AX16-AW16 -> 7 | AZ16: =(AX16-AU16)/3 -> 7.3333333 | BA16: =AX16-AL16 -> -46 | BB16: =IF($AY$11=0,"",AY16/$AY$11) -> 0.040697674
B17: Unemployed (000s) | C17: {=INDEX(Macrobond!$IS:$IS,Engine!B$9)/1000} -> 7248 | D17: {=INDEX(Macrobond!$IS:$IS,Engine!C$9)/1000} -> 7054 | E17: {=INDEX(Macrobond!$IS:$IS,Engine!D$9)/1000} -> 7272 | F17: {=INDEX(Macrobond!$IS:$IS,Engine!E$9)/1000} -> 7380 | G17: {=INDEX(Macrobond!$IS:$IS,Engine!F$9)/1000} -> 7605 | H17: {=INDEX(Macrobond!$IS:$IS,Engine!G$9)/1000} -> 7605 | I17: {=INDEX(Macrobond!$IS:$IS,Engine!H$9)/1000} -> 7781 | J17: {=INDEX(Macrobond!$IS:$IS,Engine!I$9)/1000} -> 7503 | ... O17: {=INDEX(Macrobond!$IS:$IS,Engine!N$9)/1000} -> 7307 | P17: =$O17-$N17 -> -66 | Q17: =$O17-$L17 -> -264 | R17: =$O17-$C17 -> 59 | AK17: Private services | AL17: {=INDEX(Macrobond!$SD:$SD,Engine!B$9)/1000} -> 113399 | AM17: {=INDEX(Macrobond!$SD:$SD,Engine!C$9)/1000} -> 113373 | AN17: {=INDEX(Macrobond!$SD:$SD,Engine!D$9)/1000} -> 113461 | AO17: {=INDEX(Macrobond!$SD:$SD,Engine!E$9)/1000} -> 113476 | AP17: {=INDEX(Macrobond!$SD:$SD,Engine!F$9)/1000} -> 113533 | AQ17: {=INDEX(Macrobond!$SD:$SD,Engine!G$9)/1000} -> 113566 | AR17: {=INDEX(Macrobond!$SD:$SD,Engine!H$9)/1000} -> 113613 | AS17: {=INDEX(Macrobond!$SD:$SD,Engine!I$9)/1000} -> 113627 | ... AX17: {=INDEX(Macrobond!$SD:$SD,Engine!N$9)/1000} -> 114059 | AY17: =AX17-AW17 -> 92 | AZ17: =(AX17-AU17)/3 -> 141.33333 | BA17: =AX17-AL17 -> 660 | BB17: =IF($AY$11=0,"",AY17/$AY$11) -> 0.53488372
B18: Not in labor force (000s) | C18: {=INDEX(Macrobond!$IU:$IU,Engine!B$9)/1000} -> 102893 | D18: {=INDEX(Macrobond!$IU:$IU,Engine!C$9)/1000} -> 103205 | E18: {=INDEX(Macrobond!$IU:$IU,Engine!D$9)/1000} -> 103373 | F18: {=INDEX(Macrobond!$IU:$IU,Engine!E$9)/1000} -> 103251 | G18: {=INDEX(Macrobond!$IU:$IU,Engine!F$9)/1000} -> 102964 | H18: {=INDEX(Macrobond!$IU:$IU,Engine!G$9)/1000} -> 102964 | I18: {=INDEX(Macrobond!$IU:$IU,Engine!H$9)/1000} -> 103092 | J18: {=INDEX(Macrobond!$IU:$IU,Engine!I$9)/1000} -> 103321 | ... O18: {=INDEX(Macrobond!$IU:$IU,Engine!N$9)/1000} -> 104976 | P18: =$O18-$N18 -> 17 | Q18: =$O18-$L18 -> 693 | R18: =$O18-$C18 -> 2083 | AK18: Trade, transp & util | AL18: {=INDEX(Macrobond!$SE:$SE,Engine!B$9)/1000} -> 28765 | AM18: {=INDEX(Macrobond!$SE:$SE,Engine!C$9)/1000} -> 28741 | AN18: {=INDEX(Macrobond!$SE:$SE,Engine!D$9)/1000} -> 28744 | AO18: {=INDEX(Macrobond!$SE:$SE,Engine!E$9)/1000} -> 28743 | AP18: {=INDEX(Macrobond!$SE:$SE,Engine!F$9)/1000} -> 28725 | AQ18: {=INDEX(Macrobond!$SE:$SE,Engine!G$9)/1000} -> 28714 | AR18: {=INDEX(Macrobond!$SE:$SE,Engine!H$9)/1000} -> 28649 | AS18: {=INDEX(Macrobond!$SE:$SE,Engine!I$9)/1000} -> 28616 | ... AX18: {=INDEX(Macrobond!$SE:$SE,Engine!N$9)/1000} -> 28709 | AY18: =AX18-AW18 -> -3 | AZ18: =(AX18-AU18)/3 -> 30.333333 | BA18: =AX18-AL18 -> -56 | BB18: =IF($AY$11=0,"",AY18/$AY$11) -> -0.01744186
B19: NILF – want a job now (000s) | C19: {=INDEX(Macrobond!$IV:$IV,Engine!B$9)/1000} -> 6008 | D19: {=INDEX(Macrobond!$IV:$IV,Engine!C$9)/1000} -> 6032 | E19: {=INDEX(Macrobond!$IV:$IV,Engine!D$9)/1000} -> 6186 | F19: {=INDEX(Macrobond!$IV:$IV,Engine!E$9)/1000} -> 6347 | G19: {=INDEX(Macrobond!$IV:$IV,Engine!F$9)/1000} -> 5943 | H19: {=INDEX(Macrobond!$IV:$IV,Engine!G$9)/1000} -> 5943 | I19: {=INDEX(Macrobond!$IV:$IV,Engine!H$9)/1000} -> 6139 | J19: {=INDEX(Macrobond!$IV:$IV,Engine!I$9)/1000} -> 6208 | ... O19: {=INDEX(Macrobond!$IV:$IV,Engine!N$9)/1000} -> 6187 | P19: =$O19-$N19 -> 76 | Q19: =$O19-$L19 -> 213 | R19: =$O19-$C19 -> 179 | AK19: Information | AL19: {=INDEX(Macrobond!$TM:$TM,Engine!B$9)/1000} -> 2864 | AM19: {=INDEX(Macrobond!$TM:$TM,Engine!C$9)/1000} -> 2863 | AN19: {=INDEX(Macrobond!$TM:$TM,Engine!D$9)/1000} -> 2861 | AO19: {=INDEX(Macrobond!$TM:$TM,Engine!E$9)/1000} -> 2860 | AP19: {=INDEX(Macrobond!$TM:$TM,Engine!F$9)/1000} -> 2859 | AQ19: {=INDEX(Macrobond!$TM:$TM,Engine!G$9)/1000} -> 2853 | AR19: {=INDEX(Macrobond!$TM:$TM,Engine!H$9)/1000} -> 2848 | AS19: {=INDEX(Macrobond!$TM:$TM,Engine!I$9)/1000} -> 2842 | ... AX19: {=INDEX(Macrobond!$TM:$TM,Engine!N$9)/1000} -> 2783 | AY19: =AX19-AW19 -> -2 | AZ19: =(AX19-AU19)/3 -> -3 | BA19: =AX19-AL19 -> -81 | BB19: =IF($AY$11=0,"",AY19/$AY$11) -> -0.011627907
AK20: Financial activities | AL20: {=INDEX(Macrobond!$TT:$TT,Engine!B$9)/1000} -> 9211 | AM20: {=INDEX(Macrobond!$TT:$TT,Engine!C$9)/1000} -> 9204 | AN20: {=INDEX(Macrobond!$TT:$TT,Engine!D$9)/1000} -> 9204 | AO20: {=INDEX(Macrobond!$TT:$TT,Engine!E$9)/1000} -> 9185 | AP20: {=INDEX(Macrobond!$TT:$TT,Engine!F$9)/1000} -> 9189 | AQ20: {=INDEX(Macrobond!$TT:$TT,Engine!G$9)/1000} -> 9184 | AR20: {=INDEX(Macrobond!$TT:$TT,Engine!H$9)/1000} -> 9185 | AS20: {=INDEX(Macrobond!$TT:$TT,Engine!I$9)/1000} -> 9186 | ... AX20: {=INDEX(Macrobond!$TT:$TT,Engine!N$9)/1000} -> 9104 | AY20: =AX20-AW20 -> -22 | AZ20: =(AX20-AU20)/3 -> -15 | BA20: =AX20-AL20 -> -107 | BB20: =IF($AY$11=0,"",AY20/$AY$11) -> -0.12790698
B21: 3-digit rounding watch | C21: =TEXT(((ROUND($O$12,1)+0.05)-$O$12)*100,"0.0")&" bp to round UP to "&TEXT(ROUND($O$12,1)+0.1,"0.0")&"%" -> 5.4 bp to round UP to 4.4% | H21: =TEXT(($O$12-(ROUND($O$12,1)-0.05))*100,"0.0")&" bp to round DOWN to "&TEXT(ROUND($O$12,1)-0.1,"0.0")&"%" -> 4.6 bp to round DOWN to 4.2% | AK21: Prof & business svcs | AL21: {=INDEX(Macrobond!$UH:$UH,Engine!B$9)/1000} -> 22450 | AM21: {=INDEX(Macrobond!$UH:$UH,Engine!C$9)/1000} -> 22419 | AN21: {=INDEX(Macrobond!$UH:$UH,Engine!D$9)/1000} -> 22403 | AO21: {=INDEX(Macrobond!$UH:$UH,Engine!E$9)/1000} -> 22375 | AP21: {=INDEX(Macrobond!$UH:$UH,Engine!F$9)/1000} -> 22359 | AQ21: {=INDEX(Macrobond!$UH:$UH,Engine!G$9)/1000} -> 22335 | AR21: {=INDEX(Macrobond!$UH:$UH,Engine!H$9)/1000} -> 22391 | AS21: {=INDEX(Macrobond!$UH:$UH,Engine!I$9)/1000} -> 22372 | ... AX21: {=INDEX(Macrobond!$UH:$UH,Engine!N$9)/1000} -> 22468 | AY21: =AX21-AW21 -> 6 | AZ21: =(AX21-AU21)/3 -> 18.666667 | BA21: =AX21-AL21 -> 18 | BB21: =IF($AY$11=0,"",AY21/$AY$11) -> 0.034883721
AK22: Education & health | AL22: {=INDEX(Macrobond!$VF:$VF,Engine!B$9)/1000} -> 27276 | AM22: {=INDEX(Macrobond!$VF:$VF,Engine!C$9)/1000} -> 27325 | AN22: {=INDEX(Macrobond!$VF:$VF,Engine!D$9)/1000} -> 27412 | AO22: {=INDEX(Macrobond!$VF:$VF,Engine!E$9)/1000} -> 27435 | AP22: {=INDEX(Macrobond!$VF:$VF,Engine!F$9)/1000} -> 27489 | AQ22: {=INDEX(Macrobond!$VF:$VF,Engine!G$9)/1000} -> 27533 | AR22: {=INDEX(Macrobond!$VF:$VF,Engine!H$9)/1000} -> 27589 | AS22: {=INDEX(Macrobond!$VF:$VF,Engine!I$9)/1000} -> 27627 | ... AX22: {=INDEX(Macrobond!$VF:$VF,Engine!N$9)/1000} -> 27886 | AY22: =AX22-AW22 -> 40 | AZ22: =(AX22-AU22)/3 -> 63 | BA22: =AX22-AL22 -> 610 | BB22: =IF($AY$11=0,"",AY22/$AY$11) -> 0.23255814
B23: Labor-force accounting — MoM change (000s) | C23: =Engine!B$10 -> 45778 | D23: =Engine!C$10 -> 45809 | E23: =Engine!D$10 -> 45839 | F23: =Engine!E$10 -> 45870 | G23: =Engine!F$10 -> 45901 | H23: =Engine!G$10 -> 45931 | I23: =Engine!H$10 -> 45962 | J23: =Engine!I$10 -> 45992 | ... O23: =Engine!N$10 -> 46143 | P23: Latest | Q23: 3M avg | R23: 12M sum | AK23: Leisure & hospitality | AL23: {=INDEX(Macrobond!$WB:$WB,Engine!B$9)/1000} -> 16839 | AM23: {=INDEX(Macrobond!$WB:$WB,Engine!C$9)/1000} -> 16837 | AN23: {=INDEX(Macrobond!$WB:$WB,Engine!D$9)/1000} -> 16848 | AO23: {=INDEX(Macrobond!$WB:$WB,Engine!E$9)/1000} -> 16870 | AP23: {=INDEX(Macrobond!$WB:$WB,Engine!F$9)/1000} -> 16907 | AQ23: {=INDEX(Macrobond!$WB:$WB,Engine!G$9)/1000} -> 16948 | AR23: {=INDEX(Macrobond!$WB:$WB,Engine!H$9)/1000} -> 16936 | AS23: {=INDEX(Macrobond!$WB:$WB,Engine!I$9)/1000} -> 16961 | ... AX23: {=INDEX(Macrobond!$WB:$WB,Engine!N$9)/1000} -> 17079 | AY23: =AX23-AW23 -> 70 | AZ23: =(AX23-AU23)/3 -> 48 | BA23: =AX23-AL23 -> 240 | BB23: =IF($AY$11=0,"",AY23/$AY$11) -> 0.40697674
B24: Δ Civilian labor force | C24: {=(INDEX(Macrobond!$IO:$IO,Engine!B$9)-INDEX(Macrobond!$IO:$IO,Engine!B$9-1))/1000} -> -562 | D24: {=(INDEX(Macrobond!$IO:$IO,Engine!C$9)-INDEX(Macrobond!$IO:$IO,Engine!C$9-1))/1000} -> -112 | E24: {=(INDEX(Macrobond!$IO:$IO,Engine!D$9)-INDEX(Macrobond!$IO:$IO,Engine!D$9-1))/1000} -> 32 | F24: {=(INDEX(Macrobond!$IO:$IO,Engine!E$9)-INDEX(Macrobond!$IO:$IO,Engine!E$9-1))/1000} -> 338 | G24: {=(INDEX(Macrobond!$IO:$IO,Engine!F$9)-INDEX(Macrobond!$IO:$IO,Engine!F$9-1))/1000} -> 511 | H24: {=(INDEX(Macrobond!$IO:$IO,Engine!G$9)-INDEX(Macrobond!$IO:$IO,Engine!G$9-1))/1000} -> 0 | I24: {=(INDEX(Macrobond!$IO:$IO,Engine!H$9)-INDEX(Macrobond!$IO:$IO,Engine!H$9-1))/1000} -> 280 | J24: {=(INDEX(Macrobond!$IO:$IO,Engine!I$9)-INDEX(Macrobond!$IO:$IO,Engine!I$9-1))/1000} -> -46 | ... O24: {=(INDEX(Macrobond!$IO:$IO,Engine!N$9)-INDEX(Macrobond!$IO:$IO,Engine!N$9-1))/1000} -> 83 | P24: =$O24 -> 83 | Q24: =AVERAGE($M24:$O24) -> -135 | R24: =SUM($D24:$O24) -> -414 | AK24: Other services | AL24: {=INDEX(Macrobond!$WJ:$WJ,Engine!B$9)/1000} -> 5994 | AM24: {=INDEX(Macrobond!$WJ:$WJ,Engine!C$9)/1000} -> 5984 | AN24: {=INDEX(Macrobond!$WJ:$WJ,Engine!D$9)/1000} -> 5989 | AO24: {=INDEX(Macrobond!$WJ:$WJ,Engine!E$9)/1000} -> 6008 | AP24: {=INDEX(Macrobond!$WJ:$WJ,Engine!F$9)/1000} -> 6005 | AQ24: {=INDEX(Macrobond!$WJ:$WJ,Engine!G$9)/1000} -> 5999 | AR24: {=INDEX(Macrobond!$WJ:$WJ,Engine!H$9)/1000} -> 6015 | AS24: {=INDEX(Macrobond!$WJ:$WJ,Engine!I$9)/1000} -> 6023 | ... AX24: {=INDEX(Macrobond!$WJ:$WJ,Engine!N$9)/1000} -> 6030 | AY24: =AX24-AW24 -> 3 | AZ24: =(AX24-AU24)/3 -> -0.66666667 | BA24: =AX24-AL24 -> 36 | BB24: =IF($AY$11=0,"",AY24/$AY$11) -> 0.01744186
B25: = Δ Employed | C25: {=(INDEX(Macrobond!$IQ:$IQ,Engine!B$9)-INDEX(Macrobond!$IQ:$IQ,Engine!B$9-1))/1000} -> -654 | D25: {=(INDEX(Macrobond!$IQ:$IQ,Engine!C$9)-INDEX(Macrobond!$IQ:$IQ,Engine!C$9-1))/1000} -> 83 | E25: {=(INDEX(Macrobond!$IQ:$IQ,Engine!D$9)-INDEX(Macrobond!$IQ:$IQ,Engine!D$9-1))/1000} -> -187 | F25: {=(INDEX(Macrobond!$IQ:$IQ,Engine!E$9)-INDEX(Macrobond!$IQ:$IQ,Engine!E$9-1))/1000} -> 230 | G25: {=(INDEX(Macrobond!$IQ:$IQ,Engine!F$9)-INDEX(Macrobond!$IQ:$IQ,Engine!F$9-1))/1000} -> 286 | H25: {=(INDEX(Macrobond!$IQ:$IQ,Engine!G$9)-INDEX(Macrobond!$IQ:$IQ,Engine!G$9-1))/1000} -> 0 | I25: {=(INDEX(Macrobond!$IQ:$IQ,Engine!H$9)-INDEX(Macrobond!$IQ:$IQ,Engine!H$9-1))/1000} -> 104 | J25: {=(INDEX(Macrobond!$IQ:$IQ,Engine!I$9)-INDEX(Macrobond!$IQ:$IQ,Engine!I$9-1))/1000} -> 232 | ... O25: {=(INDEX(Macrobond!$IQ:$IQ,Engine!N$9)-INDEX(Macrobond!$IQ:$IQ,Engine!N$9-1))/1000} -> 149 | P25: =$O25 -> 149 | Q25: =AVERAGE($M25:$O25) -> -47 | R25: =SUM($D25:$O25) -> -473 | AK25: Government | AL25: {=INDEX(Macrobond!$WN:$WN,Engine!B$9)/1000} -> 23561 | AM25: {=INDEX(Macrobond!$WN:$WN,Engine!C$9)/1000} -> 23586 | AN25: {=INDEX(Macrobond!$WN:$WN,Engine!D$9)/1000} -> 23585 | AO25: {=INDEX(Macrobond!$WN:$WN,Engine!E$9)/1000} -> 23535 | AP25: {=INDEX(Macrobond!$WN:$WN,Engine!F$9)/1000} -> 23543 | AQ25: {=INDEX(Macrobond!$WN:$WN,Engine!G$9)/1000} -> 23390 | AR25: {=INDEX(Macrobond!$WN:$WN,Engine!H$9)/1000} -> 23359 | AS25: {=INDEX(Macrobond!$WN:$WN,Engine!I$9)/1000} -> 23349 | ... AX25: {=INDEX(Macrobond!$WN:$WN,Engine!N$9)/1000} -> 23387 | AY25: =AX25-AW25 -> 52 | AZ25: =(AX25-AU25)/3 -> 22 | BA25: =AX25-AL25 -> -174 | BB25: =IF($AY$11=0,"",AY25/$AY$11) -> 0.30232558
B26: + Δ Unemployed | C26: {=(INDEX(Macrobond!$IS:$IS,Engine!B$9)-INDEX(Macrobond!$IS:$IS,Engine!B$9-1))/1000} -> 93 | D26: {=(INDEX(Macrobond!$IS:$IS,Engine!C$9)-INDEX(Macrobond!$IS:$IS,Engine!C$9-1))/1000} -> -194 | E26: {=(INDEX(Macrobond!$IS:$IS,Engine!D$9)-INDEX(Macrobond!$IS:$IS,Engine!D$9-1))/1000} -> 218 | F26: {=(INDEX(Macrobond!$IS:$IS,Engine!E$9)-INDEX(Macrobond!$IS:$IS,Engine!E$9-1))/1000} -> 108 | G26: {=(INDEX(Macrobond!$IS:$IS,Engine!F$9)-INDEX(Macrobond!$IS:$IS,Engine!F$9-1))/1000} -> 225 | H26: {=(INDEX(Macrobond!$IS:$IS,Engine!G$9)-INDEX(Macrobond!$IS:$IS,Engine!G$9-1))/1000} -> 0 | I26: {=(INDEX(Macrobond!$IS:$IS,Engine!H$9)-INDEX(Macrobond!$IS:$IS,Engine!H$9-1))/1000} -> 176 | J26: {=(INDEX(Macrobond!$IS:$IS,Engine!I$9)-INDEX(Macrobond!$IS:$IS,Engine!I$9-1))/1000} -> -278 | ... O26: {=(INDEX(Macrobond!$IS:$IS,Engine!N$9)-INDEX(Macrobond!$IS:$IS,Engine!N$9-1))/1000} -> -66 | P26: =$O26 -> -66 | Q26: =AVERAGE($M26:$O26) -> -88 | R26: =SUM($D26:$O26) -> 59
B27: Δ Not in labor force | C27: {=(INDEX(Macrobond!$IU:$IU,Engine!B$9)-INDEX(Macrobond!$IU:$IU,Engine!B$9-1))/1000} -> 750 | D27: {=(INDEX(Macrobond!$IU:$IU,Engine!C$9)-INDEX(Macrobond!$IU:$IU,Engine!C$9-1))/1000} -> 312 | E27: {=(INDEX(Macrobond!$IU:$IU,Engine!D$9)-INDEX(Macrobond!$IU:$IU,Engine!D$9-1))/1000} -> 168 | F27: {=(INDEX(Macrobond!$IU:$IU,Engine!E$9)-INDEX(Macrobond!$IU:$IU,Engine!E$9-1))/1000} -> -122 | G27: {=(INDEX(Macrobond!$IU:$IU,Engine!F$9)-INDEX(Macrobond!$IU:$IU,Engine!F$9-1))/1000} -> -287 | H27: {=(INDEX(Macrobond!$IU:$IU,Engine!G$9)-INDEX(Macrobond!$IU:$IU,Engine!G$9-1))/1000} -> 0 | I27: {=(INDEX(Macrobond!$IU:$IU,Engine!H$9)-INDEX(Macrobond!$IU:$IU,Engine!H$9-1))/1000} -> 128 | J27: {=(INDEX(Macrobond!$IU:$IU,Engine!I$9)-INDEX(Macrobond!$IU:$IU,Engine!I$9-1))/1000} -> 229 | ... O27: {=(INDEX(Macrobond!$IU:$IU,Engine!N$9)-INDEX(Macrobond!$IU:$IU,Engine!N$9-1))/1000} -> 17 | P27: =$O27 -> 17 | Q27: =AVERAGE($M27:$O27) -> 231 | R27: =SUM($D27:$O27) -> 2083 | AK27: Avg weekly hours, SA | AL27: =Engine!B$10 -> 45778 | AM27: =Engine!C$10 -> 45809 | AN27: =Engine!D$10 -> 45839 | AO27: =Engine!E$10 -> 45870 | AP27: =Engine!F$10 -> 45901 | AQ27: =Engine!G$10 -> 45931 | AR27: =Engine!H$10 -> 45962 | AS27: =Engine!I$10 -> 45992 | ... AX27: =Engine!N$10 -> 46143 | AY27: MoM | AZ27: 3M | BA27: YoY
B28: check: ΔLF − (ΔEmp+ΔUnemp) | C28: =$C24-($C25+$C26) -> -1 | D28: =$C24-($C25+$C26) -> -1 | E28: =$C24-($C25+$C26) -> -1 | F28: =$C24-($C25+$C26) -> -1 | G28: =$C24-($C25+$C26) -> -1 | H28: =$C24-($C25+$C26) -> -1 | I28: =$C24-($C25+$C26) -> -1 | J28: =$C24-($C25+$C26) -> -1 | ... O28: =$C24-($C25+$C26) -> -1 | AK28: Total private | AL28: {=INDEX(Macrobond!$GZ:$GZ,Engine!B$9)} -> 34.2 | AM28: {=INDEX(Macrobond!$GZ:$GZ,Engine!C$9)} -> 34.2 | AN28: {=INDEX(Macrobond!$GZ:$GZ,Engine!D$9)} -> 34.2 | AO28: {=INDEX(Macrobond!$GZ:$GZ,Engine!E$9)} -> 34.2 | AP28: {=INDEX(Macrobond!$GZ:$GZ,Engine!F$9)} -> 34.2 | AQ28: {=INDEX(Macrobond!$GZ:$GZ,Engine!G$9)} -> 34.2 | AR28: {=INDEX(Macrobond!$GZ:$GZ,Engine!H$9)} -> 34.3 | AS28: {=INDEX(Macrobond!$GZ:$GZ,Engine!I$9)} -> 34.2 | ... AX28: {=INDEX(Macrobond!$GZ:$GZ,Engine!N$9)} -> 34.3 | AY28: =AX28-AW28 -> 0 | AZ28: =AX28-AU28 -> 0 | BA28: =AX28-AL28 -> 0.1
AK29: Goods-producing | AL29: {=INDEX(Macrobond!$HA:$HA,Engine!B$9)} -> 39.8 | AM29: {=INDEX(Macrobond!$HA:$HA,Engine!C$9)} -> 39.8 | AN29: {=INDEX(Macrobond!$HA:$HA,Engine!D$9)} -> 39.9 | AO29: {=INDEX(Macrobond!$HA:$HA,Engine!E$9)} -> 39.7 | AP29: {=INDEX(Macrobond!$HA:$HA,Engine!F$9)} -> 39.7 | AQ29: {=INDEX(Macrobond!$HA:$HA,Engine!G$9)} -> 39.7 | AR29: {=INDEX(Macrobond!$HA:$HA,Engine!H$9)} -> 39.9 | AS29: {=INDEX(Macrobond!$HA:$HA,Engine!I$9)} -> 39.7 | ... AX29: {=INDEX(Macrobond!$HA:$HA,Engine!N$9)} -> 40.1 | AY29: =AX29-AW29 -> 0 | AZ29: =AX29-AU29 -> 0 | BA29: =AX29-AL29 -> 0.3
B30: Unemployment by reason (000s) — mix shift at right | C30: =Engine!B$10 -> 45778 | D30: =Engine!C$10 -> 45809 | E30: =Engine!D$10 -> 45839 | F30: =Engine!E$10 -> 45870 | G30: =Engine!F$10 -> 45901 | H30: =Engine!G$10 -> 45931 | I30: =Engine!H$10 -> 45962 | J30: =Engine!I$10 -> 45992 | ... O30: =Engine!N$10 -> 46143 | P30: Share now | Q30: Share 3M ago | R30: Share 12M ago | AK30: Manufacturing | AL30: {=INDEX(Macrobond!$HD:$HD,Engine!B$9)} -> 40.1 | AM30: {=INDEX(Macrobond!$HD:$HD,Engine!C$9)} -> 40.1 | AN30: {=INDEX(Macrobond!$HD:$HD,Engine!D$9)} -> 40.2 | AO30: {=INDEX(Macrobond!$HD:$HD,Engine!E$9)} -> 40 | AP30: {=INDEX(Macrobond!$HD:$HD,Engine!F$9)} -> 40 | AQ30: {=INDEX(Macrobond!$HD:$HD,Engine!G$9)} -> 40 | AR30: {=INDEX(Macrobond!$HD:$HD,Engine!H$9)} -> 40.1 | AS30: {=INDEX(Macrobond!$HD:$HD,Engine!I$9)} -> 40 | ... AX30: {=INDEX(Macrobond!$HD:$HD,Engine!N$9)} -> 40.4 | AY30: =AX30-AW30 -> 0 | AZ30: =AX30-AU30 -> 0.2 | BA30: =AX30-AL30 -> 0.3
B31: Permanent job losers | C31: {=INDEX(Macrobond!$G:$G,Engine!B$9)/1000} -> 1913 | D31: {=INDEX(Macrobond!$G:$G,Engine!C$9)/1000} -> 1892 | E31: {=INDEX(Macrobond!$G:$G,Engine!D$9)/1000} -> 1894 | F31: {=INDEX(Macrobond!$G:$G,Engine!E$9)/1000} -> 1931 | G31: {=INDEX(Macrobond!$G:$G,Engine!F$9)/1000} -> 2012 | H31: {=INDEX(Macrobond!$G:$G,Engine!G$9)/1000} -> 2012 | I31: {=INDEX(Macrobond!$G:$G,Engine!H$9)/1000} -> 1936 | J31: {=INDEX(Macrobond!$G:$G,Engine!I$9)/1000} -> 1969 | ... O31: {=INDEX(Macrobond!$G:$G,Engine!N$9)/1000} -> 1927 | P31: =$O31/$O$37 -> 0.26371972 | Q31: =$L31/$L$37 -> 0.26905297 | R31: =$C31/$C$37 -> 0.26393488 | AK31: Trade, transp & util | AL31: {=INDEX(Macrobond!$HH:$HH,Engine!B$9)} -> 34 | AM31: {=INDEX(Macrobond!$HH:$HH,Engine!C$9)} -> 34 | AN31: {=INDEX(Macrobond!$HH:$HH,Engine!D$9)} -> 34.1 | AO31: {=INDEX(Macrobond!$HH:$HH,Engine!E$9)} -> 34.1 | AP31: {=INDEX(Macrobond!$HH:$HH,Engine!F$9)} -> 34 | AQ31: {=INDEX(Macrobond!$HH:$HH,Engine!G$9)} -> 34.1 | AR31: {=INDEX(Macrobond!$HH:$HH,Engine!H$9)} -> 34 | AS31: {=INDEX(Macrobond!$HH:$HH,Engine!I$9)} -> 34 | ... AX31: {=INDEX(Macrobond!$HH:$HH,Engine!N$9)} -> 34.2 | AY31: =AX31-AW31 -> 0.1 | AZ31: =AX31-AU31 -> 0.1 | BA31: =AX31-AL31 -> 0.2
B32: Job losers on temporary layoff | C32: {=INDEX(Macrobond!$D:$D,Engine!B$9)/1000} -> 879 | D32: {=INDEX(Macrobond!$D:$D,Engine!C$9)/1000} -> 867 | E32: {=INDEX(Macrobond!$D:$D,Engine!D$9)/1000} -> 940 | F32: {=INDEX(Macrobond!$D:$D,Engine!E$9)/1000} -> 890 | G32: {=INDEX(Macrobond!$D:$D,Engine!F$9)/1000} -> 844 | H32: {=INDEX(Macrobond!$D:$D,Engine!G$9)/1000} -> 844 | I32: {=INDEX(Macrobond!$D:$D,Engine!H$9)/1000} -> 1002 | J32: {=INDEX(Macrobond!$D:$D,Engine!I$9)/1000} -> 929 | ... O32: {=INDEX(Macrobond!$D:$D,Engine!N$9)/1000} -> 778 | P32: =$O32/$O$37 -> 0.10647324 | Q32: =$L32/$L$37 -> 0.12217673 | R32: =$C32/$C$37 -> 0.12127483 | AK32: Prof & business svcs | AL32: {=INDEX(Macrobond!$HO:$HO,Engine!B$9)} -> 36.5 | AM32: {=INDEX(Macrobond!$HO:$HO,Engine!C$9)} -> 36.4 | AN32: {=INDEX(Macrobond!$HO:$HO,Engine!D$9)} -> 36.4 | AO32: {=INDEX(Macrobond!$HO:$HO,Engine!E$9)} -> 36.5 | AP32: {=INDEX(Macrobond!$HO:$HO,Engine!F$9)} -> 36.5 | AQ32: {=INDEX(Macrobond!$HO:$HO,Engine!G$9)} -> 36.6 | AR32: {=INDEX(Macrobond!$HO:$HO,Engine!H$9)} -> 36.6 | AS32: {=INDEX(Macrobond!$HO:$HO,Engine!I$9)} -> 36.5 | ... AX32: {=INDEX(Macrobond!$HO:$HO,Engine!N$9)} -> 36.7 | AY32: =AX32-AW32 -> 0.1 | AZ32: =AX32-AU32 -> 0.1 | BA32: =AX32-AL32 -> 0.2
B33: Persons who completed temp jobs | C33: {=INDEX(Macrobond!$H:$H,Engine!B$9)/1000} -> 666 | D33: {=INDEX(Macrobond!$H:$H,Engine!C$9)/1000} -> 546 | E33: {=INDEX(Macrobond!$H:$H,Engine!D$9)/1000} -> 578 | F33: {=INDEX(Macrobond!$H:$H,Engine!E$9)/1000} -> 627 | G33: {=INDEX(Macrobond!$H:$H,Engine!F$9)/1000} -> 668 | H33: {=INDEX(Macrobond!$H:$H,Engine!G$9)/1000} -> 668 | I33: {=INDEX(Macrobond!$H:$H,Engine!H$9)/1000} -> 623 | J33: {=INDEX(Macrobond!$H:$H,Engine!I$9)/1000} -> 575 | ... O33: {=INDEX(Macrobond!$H:$H,Engine!N$9)/1000} -> 680 | P33: =$O33/$O$37 -> 0.093061448 | Q33: =$L33/$L$37 -> 0.08691058 | R33: =$C33/$C$37 -> 0.091887417 | AK33: Leisure & hospitality | AL33: {=INDEX(Macrobond!$HQ:$HQ,Engine!B$9)} -> 25.6 | AM33: {=INDEX(Macrobond!$HQ:$HQ,Engine!C$9)} -> 25.5 | AN33: {=INDEX(Macrobond!$HQ:$HQ,Engine!D$9)} -> 25.5 | AO33: {=INDEX(Macrobond!$HQ:$HQ,Engine!E$9)} -> 25.5 | AP33: {=INDEX(Macrobond!$HQ:$HQ,Engine!F$9)} -> 25.5 | AQ33: {=INDEX(Macrobond!$HQ:$HQ,Engine!G$9)} -> 25.6 | AR33: {=INDEX(Macrobond!$HQ:$HQ,Engine!H$9)} -> 25.6 | AS33: {=INDEX(Macrobond!$HQ:$HQ,Engine!I$9)} -> 25.6 | ... AX33: {=INDEX(Macrobond!$HQ:$HQ,Engine!N$9)} -> 25.4 | AY33: =AX33-AW33 -> -0.1 | AZ33: =AX33-AU33 -> -0.1 | BA33: =AX33-AL33 -> -0.2
B34: Job leavers | C34: {=INDEX(Macrobond!$I:$I,Engine!B$9)/1000} -> 706 | D34: {=INDEX(Macrobond!$I:$I,Engine!C$9)/1000} -> 825 | E34: {=INDEX(Macrobond!$I:$I,Engine!D$9)/1000} -> 785 | F34: {=INDEX(Macrobond!$I:$I,Engine!E$9)/1000} -> 785 | G34: {=INDEX(Macrobond!$I:$I,Engine!F$9)/1000} -> 860 | H34: {=INDEX(Macrobond!$I:$I,Engine!G$9)/1000} -> 860 | I34: {=INDEX(Macrobond!$I:$I,Engine!H$9)/1000} -> 861 | J34: {=INDEX(Macrobond!$I:$I,Engine!I$9)/1000} -> 832 | ... O34: {=INDEX(Macrobond!$I:$I,Engine!N$9)/1000} -> 916 | P34: =$O34/$O$37 -> 0.12535924 | Q34: =$L34/$L$37 -> 0.11451592 | R34: =$C34/$C$37 -> 0.097406181
B35: Reentrants | C35: {=INDEX(Macrobond!$J:$J,Engine!B$9)/1000} -> 2291 | D35: {=INDEX(Macrobond!$J:$J,Engine!C$9)/1000} -> 2160 | E35: {=INDEX(Macrobond!$J:$J,Engine!D$9)/1000} -> 2199 | F35: {=INDEX(Macrobond!$J:$J,Engine!E$9)/1000} -> 2302 | G35: {=INDEX(Macrobond!$J:$J,Engine!F$9)/1000} -> 2336 | H35: {=INDEX(Macrobond!$J:$J,Engine!G$9)/1000} -> 2336 | I35: {=INDEX(Macrobond!$J:$J,Engine!H$9)/1000} -> 2600 | J35: {=INDEX(Macrobond!$J:$J,Engine!I$9)/1000} -> 2337 | ... O35: {=INDEX(Macrobond!$J:$J,Engine!N$9)/1000} -> 2209 | P35: =$O35/$O$37 -> 0.30231285 | Q35: =$L35/$L$37 -> 0.30643244 | R35: =$C35/$C$37 -> 0.3160872 | AK35: Avg weekly earnings, SA (USD) | AL35: =Engine!B$10 -> 45778 | AM35: =Engine!C$10 -> 45809 | AN35: =Engine!D$10 -> 45839 | AO35: =Engine!E$10 -> 45870 | AP35: =Engine!F$10 -> 45901 | AQ35: =Engine!G$10 -> 45931 | AR35: =Engine!H$10 -> 45962 | AS35: =Engine!I$10 -> 45992 | ... AX35: =Engine!N$10 -> 46143 | AY35: MoM% | AZ35: 3M% | BA35: YoY%
B36: New entrants | C36: {=INDEX(Macrobond!$K:$K,Engine!B$9)/1000} -> 734 | D36: {=INDEX(Macrobond!$K:$K,Engine!C$9)/1000} -> 723 | E36: {=INDEX(Macrobond!$K:$K,Engine!D$9)/1000} -> 982 | F36: {=INDEX(Macrobond!$K:$K,Engine!E$9)/1000} -> 792 | G36: {=INDEX(Macrobond!$K:$K,Engine!F$9)/1000} -> 813 | H36: {=INDEX(Macrobond!$K:$K,Engine!G$9)/1000} -> 813 | I36: {=INDEX(Macrobond!$K:$K,Engine!H$9)/1000} -> 774 | J36: {=INDEX(Macrobond!$K:$K,Engine!I$9)/1000} -> 840 | ... O36: {=INDEX(Macrobond!$K:$K,Engine!N$9)/1000} -> 818 | P36: =$O36/$O$37 -> 0.11194745 | Q36: =$L36/$L$37 -> 0.10632677 | R36: =$C36/$C$37 -> 0.10126932 | AK36: Total private | AL36: {=INDEX(Macrobond!$HV:$HV,Engine!B$9)} -> 1240.78 | AM36: {=INDEX(Macrobond!$HV:$HV,Engine!C$9)} -> 1243.51 | AN36: {=INDEX(Macrobond!$HV:$HV,Engine!D$9)} -> 1247.27 | AO36: {=INDEX(Macrobond!$HV:$HV,Engine!E$9)} -> 1252.4 | AP36: {=INDEX(Macrobond!$HV:$HV,Engine!F$9)} -> 1255.14 | AQ36: {=INDEX(Macrobond!$HV:$HV,Engine!G$9)} -> 1260.27 | AR36: {=INDEX(Macrobond!$HV:$HV,Engine!H$9)} -> 1269.1 | AS36: {=INDEX(Macrobond!$HV:$HV,Engine!I$9)} -> 1266.08 | ... AX36: {=INDEX(Macrobond!$HV:$HV,Engine!N$9)} -> 1287.28 | AY36: =AX36/AW36-1 -> 0.0032108233 | AZ36: =AX36/AU36-1 -> 0.0069776902 | BA36: =AX36/AL36-1 -> 0.037476426
B37: Total unemployed (memo) | C37: {=INDEX(Macrobond!$IS:$IS,Engine!B$9)/1000} -> 7248 | D37: {=INDEX(Macrobond!$IS:$IS,Engine!C$9)/1000} -> 7054 | E37: {=INDEX(Macrobond!$IS:$IS,Engine!D$9)/1000} -> 7272 | F37: {=INDEX(Macrobond!$IS:$IS,Engine!E$9)/1000} -> 7380 | G37: {=INDEX(Macrobond!$IS:$IS,Engine!F$9)/1000} -> 7605 | H37: {=INDEX(Macrobond!$IS:$IS,Engine!G$9)/1000} -> 7605 | I37: {=INDEX(Macrobond!$IS:$IS,Engine!H$9)/1000} -> 7781 | J37: {=INDEX(Macrobond!$IS:$IS,Engine!I$9)/1000} -> 7503 | ... O37: {=INDEX(Macrobond!$IS:$IS,Engine!N$9)/1000} -> 7307 | P37: =$O37/$O$37 -> 1 | Q37: =$L37/$L$37 -> 1 | R37: =$C37/$C$37 -> 1 | AK37: Goods-producing | AL37: {=INDEX(Macrobond!$HW:$HW,Engine!B$9)} -> 1473.79 | AM37: {=INDEX(Macrobond!$HW:$HW,Engine!C$9)} -> 1477.77 | AN37: {=INDEX(Macrobond!$HW:$HW,Engine!D$9)} -> 1486.28 | AO37: {=INDEX(Macrobond!$HW:$HW,Engine!E$9)} -> 1484.38 | AP37: {=INDEX(Macrobond!$HW:$HW,Engine!F$9)} -> 1487.56 | AQ37: {=INDEX(Macrobond!$HW:$HW,Engine!G$9)} -> 1493.91 | AR37: {=INDEX(Macrobond!$HW:$HW,Engine!H$9)} -> 1506.62 | AS37: {=INDEX(Macrobond!$HW:$HW,Engine!I$9)} -> 1503.44 | ... AX37: {=INDEX(Macrobond!$HW:$HW,Engine!N$9)} -> 1546.66 | AY37: =AX37/AW37-1 -> 0.0028594586 | AZ37: =AX37/AU37-1 -> 0.010479414 | BA37: =AX37/AL37-1 -> 0.049443951
AK38: Manufacturing | AL38: {=INDEX(Macrobond!$HZ:$HZ,Engine!B$9)} -> 1415.93 | AM38: {=INDEX(Macrobond!$HZ:$HZ,Engine!C$9)} -> 1418.34 | AN38: {=INDEX(Macrobond!$HZ:$HZ,Engine!D$9)} -> 1427.5 | AO38: {=INDEX(Macrobond!$HZ:$HZ,Engine!E$9)} -> 1423.2 | AP38: {=INDEX(Macrobond!$HZ:$HZ,Engine!F$9)} -> 1428 | AQ38: {=INDEX(Macrobond!$HZ:$HZ,Engine!G$9)} -> 1434.8 | AR38: {=INDEX(Macrobond!$HZ:$HZ,Engine!H$9)} -> 1443.2 | AS38: {=INDEX(Macrobond!$HZ:$HZ,Engine!I$9)} -> 1443.2 | ... AX38: {=INDEX(Macrobond!$HZ:$HZ,Engine!N$9)} -> 1483.08 | AY38: =AX38/AW38-1 -> 0.001363888 | AZ38: =AX38/AU38-1 -> 0.013808378 | BA38: =AX38/AL38-1 -> 0.047424661
B39: Duration of unemployment | C39: =Engine!B$10 -> 45778 | D39: =Engine!C$10 -> 45809 | E39: =Engine!D$10 -> 45839 | F39: =Engine!E$10 -> 45870 | G39: =Engine!F$10 -> 45901 | H39: =Engine!G$10 -> 45931 | I39: =Engine!H$10 -> 45962 | J39: =Engine!I$10 -> 45992 | ... O39: =Engine!N$10 -> 46143 | P39: MoM | Q39: 3M | R39: YoY | AK39: Trade, transp & util | AL39: {=INDEX(Macrobond!$ID:$ID,Engine!B$9)} -> 1047.88 | AM39: {=INDEX(Macrobond!$ID:$ID,Engine!C$9)} -> 1049.24 | AN39: {=INDEX(Macrobond!$ID:$ID,Engine!D$9)} -> 1057.1 | AO39: {=INDEX(Macrobond!$ID:$ID,Engine!E$9)} -> 1060.51 | AP39: {=INDEX(Macrobond!$ID:$ID,Engine!F$9)} -> 1060.46 | AQ39: {=INDEX(Macrobond!$ID:$ID,Engine!G$9)} -> 1067.67 | AR39: {=INDEX(Macrobond!$ID:$ID,Engine!H$9)} -> 1070.32 | AS39: {=INDEX(Macrobond!$ID:$ID,Engine!I$9)} -> 1073.04 | ... AX39: {=INDEX(Macrobond!$ID:$ID,Engine!N$9)} -> 1091.66 | AY39: =AX39/AW39-1 -> 0.0051284884 | AZ39: =AX39/AU39-1 -> 0.008937236 | BA39: =AX39/AL39-1 -> 0.041779593
B40: Mean duration (weeks) | C40: {=INDEX(Macrobond!$AA:$AA,Engine!B$9)} -> 21.9 | D40: {=INDEX(Macrobond!$AA:$AA,Engine!C$9)} -> 23.1 | E40: {=INDEX(Macrobond!$AA:$AA,Engine!D$9)} -> 24 | F40: {=INDEX(Macrobond!$AA:$AA,Engine!E$9)} -> 24.5 | G40: {=INDEX(Macrobond!$AA:$AA,Engine!F$9)} -> 24.1 | H40: {=INDEX(Macrobond!$AA:$AA,Engine!G$9)} -> 24.1 | I40: {=INDEX(Macrobond!$AA:$AA,Engine!H$9)} -> 23.1 | J40: {=INDEX(Macrobond!$AA:$AA,Engine!I$9)} -> 24.4 | ... O40: {=INDEX(Macrobond!$AA:$AA,Engine!N$9)} -> 26 | P40: =$O40-$N40 -> 1.6 | Q40: =$O40-$L40 -> 0.3 | R40: =$O40-$C40 -> 4.1 | AK40: Prof & business svcs | AL40: {=INDEX(Macrobond!$IK:$IK,Engine!B$9)} -> 1606 | AM40: {=INDEX(Macrobond!$IK:$IK,Engine!C$9)} -> 1609.24 | AN40: {=INDEX(Macrobond!$IK:$IK,Engine!D$9)} -> 1616.16 | AO40: {=INDEX(Macrobond!$IK:$IK,Engine!E$9)} -> 1628.63 | AP40: {=INDEX(Macrobond!$IK:$IK,Engine!F$9)} -> 1633.01 | AQ40: {=INDEX(Macrobond!$IK:$IK,Engine!G$9)} -> 1643.34 | AR40: {=INDEX(Macrobond!$IK:$IK,Engine!H$9)} -> 1644.07 | AS40: {=INDEX(Macrobond!$IK:$IK,Engine!I$9)} -> 1641.04 | ... AX40: {=INDEX(Macrobond!$IK:$IK,Engine!N$9)} -> 1672.79 | AY40: =AX40/AW40-1 -> 0.0062681593 | AZ40: =AX40/AU40-1 -> 0.010718709 | BA40: =AX40/AL40-1 -> 0.041587796
B41: Median duration (weeks) | C41: {=INDEX(Macrobond!$AB:$AB,Engine!B$9)} -> 9.5 | D41: {=INDEX(Macrobond!$AB:$AB,Engine!C$9)} -> 10.1 | E41: {=INDEX(Macrobond!$AB:$AB,Engine!D$9)} -> 10.2 | F41: {=INDEX(Macrobond!$AB:$AB,Engine!E$9)} -> 9.9 | G41: {=INDEX(Macrobond!$AB:$AB,Engine!F$9)} -> 10.1 | H41: {=INDEX(Macrobond!$AB:$AB,Engine!G$9)} -> 10.1 | I41: {=INDEX(Macrobond!$AB:$AB,Engine!H$9)} -> 9.8 | J41: {=INDEX(Macrobond!$AB:$AB,Engine!I$9)} -> 11.4 | ... O41: {=INDEX(Macrobond!$AB:$AB,Engine!N$9)} -> 11.6 | P41: =$O41-$N41 -> 0.6 | Q41: =$O41-$L41 -> 0.5 | R41: =$O41-$C41 -> 2.1 | AK41: Leisure & hospitality | AL41: {=INDEX(Macrobond!$IM:$IM,Engine!B$9)} -> 580.61 | AM41: {=INDEX(Macrobond!$IM:$IM,Engine!C$9)} -> 579.87 | AN41: {=INDEX(Macrobond!$IM:$IM,Engine!D$9)} -> 581.66 | AO41: {=INDEX(Macrobond!$IM:$IM,Engine!E$9)} -> 584.46 | AP41: {=INDEX(Macrobond!$IM:$IM,Engine!F$9)} -> 586.5 | AQ41: {=INDEX(Macrobond!$IM:$IM,Engine!G$9)} -> 589.06 | AR41: {=INDEX(Macrobond!$IM:$IM,Engine!H$9)} -> 593.15 | AS41: {=INDEX(Macrobond!$IM:$IM,Engine!I$9)} -> 595.2 | ... AX41: {=INDEX(Macrobond!$IM:$IM,Engine!N$9)} -> 598.93 | AY41: =AX41/AW41-1 -> -0.0013838869 | AZ41: =AX41/AU41-1 -> 0.0037372214 | BA41: =AX41/AL41-1 -> 0.031553022
B42: Less than 5 weeks (000s) | C42: {=INDEX(Macrobond!$V:$V,Engine!B$9)/1000} -> 2456 | D42: {=INDEX(Macrobond!$V:$V,Engine!C$9)/1000} -> 2254 | E42: {=INDEX(Macrobond!$V:$V,Engine!D$9)/1000} -> 2304 | F42: {=INDEX(Macrobond!$V:$V,Engine!E$9)/1000} -> 2475 | G42: {=INDEX(Macrobond!$V:$V,Engine!F$9)/1000} -> 2232 | H42: {=INDEX(Macrobond!$V:$V,Engine!G$9)/1000} -> 2232 | I42: {=INDEX(Macrobond!$V:$V,Engine!H$9)/1000} -> 2540 | J42: {=INDEX(Macrobond!$V:$V,Engine!I$9)/1000} -> 2289 | ... O42: {=INDEX(Macrobond!$V:$V,Engine!N$9)/1000} -> 2210 | P42: =$O42-$N42 -> -286 | Q42: =$O42-$L42 -> -109 | R42: =$O42-$C42 -> -246
B43: 5 to 14 weeks (000s) | C43: {=INDEX(Macrobond!$W:$W,Engine!B$9)/1000} -> 2203 | D43: {=INDEX(Macrobond!$W:$W,Engine!C$9)/1000} -> 2129 | E43: {=INDEX(Macrobond!$W:$W,Engine!D$9)/1000} -> 2041 | F43: {=INDEX(Macrobond!$W:$W,Engine!E$9)/1000} -> 2058 | G43: {=INDEX(Macrobond!$W:$W,Engine!F$9)/1000} -> 2356 | H43: {=INDEX(Macrobond!$W:$W,Engine!G$9)/1000} -> 2356 | I43: {=INDEX(Macrobond!$W:$W,Engine!H$9)/1000} -> 2190 | J43: {=INDEX(Macrobond!$W:$W,Engine!I$9)/1000} -> 2069 | ... O43: {=INDEX(Macrobond!$W:$W,Engine!N$9)/1000} -> 1946 | P43: =$O43-$N43 -> 87 | Q43: =$O43-$L43 -> -132 | R43: =$O43-$C43 -> -257 | AK43: Aggregate labor input & income (total private, SA) | AY43: YoY | AZ43: 3M ann
B44: 15 to 26 weeks (000s) | C44: {=INDEX(Macrobond!$Y:$Y,Engine!B$9)/1000} -> 1042 | D44: {=INDEX(Macrobond!$Y:$Y,Engine!C$9)/1000} -> 1064 | E44: {=INDEX(Macrobond!$Y:$Y,Engine!D$9)/1000} -> 1166 | F44: {=INDEX(Macrobond!$Y:$Y,Engine!E$9)/1000} -> 1051 | G44: {=INDEX(Macrobond!$Y:$Y,Engine!F$9)/1000} -> 1286 | H44: {=INDEX(Macrobond!$Y:$Y,Engine!G$9)/1000} -> 1286 | I44: {=INDEX(Macrobond!$Y:$Y,Engine!H$9)/1000} -> 1190 | J44: {=INDEX(Macrobond!$Y:$Y,Engine!I$9)/1000} -> 1195 | ... O44: {=INDEX(Macrobond!$Y:$Y,Engine!N$9)/1000} -> 1077 | P44: =$O44-$N44 -> 20 | Q44: =$O44-$L44 -> -129 | R44: =$O44-$C44 -> 35 | AK44: Aggregate weekly hours (emp × hrs) | AY44: {=(INDEX(Macrobond!$QH:$QH,Engine!$B$3)*INDEX(Macrobond!$GZ:$GZ,Engine!$B$3))/(INDEX(Macrobond!$QH:$QH,Engine!$B$3-12)*INDEX(Macrobond!$GZ:$GZ,Engine!$B$3-12))-1} -> 0.0079558028 | AZ44: {=((INDEX(Macrobond!$QH:$QH,Engine!$B$3)*INDEX(Macrobond!$GZ:$GZ,Engine!$B$3))/(INDEX(Macrobond!$QH:$QH,Engine!$B$3-3)*INDEX(Macrobond!$GZ:$GZ,Engine!$B$3-3)))^4-1} -> 0.014854639
B45: 27 weeks & over (000s) | C45: {=INDEX(Macrobond!$Z:$Z,Engine!B$9)/1000} -> 1464 | D45: {=INDEX(Macrobond!$Z:$Z,Engine!C$9)/1000} -> 1651 | E45: {=INDEX(Macrobond!$Z:$Z,Engine!D$9)/1000} -> 1822 | F45: {=INDEX(Macrobond!$Z:$Z,Engine!E$9)/1000} -> 1924 | G45: {=INDEX(Macrobond!$Z:$Z,Engine!F$9)/1000} -> 1815 | H45: {=INDEX(Macrobond!$Z:$Z,Engine!G$9)/1000} -> 1815 | I45: {=INDEX(Macrobond!$Z:$Z,Engine!H$9)/1000} -> 1910 | J45: {=INDEX(Macrobond!$Z:$Z,Engine!I$9)/1000} -> 1948 | ... O45: {=INDEX(Macrobond!$Z:$Z,Engine!N$9)/1000} -> 1988 | P45: =$O45-$N45 -> 155 | Q45: =$O45-$L45 -> 89 | R45: =$O45-$C45 -> 524 | AK45: Aggregate weekly payrolls (emp × earnings) | AY45: {=(INDEX(Macrobond!$QH:$QH,Engine!$B$3)*INDEX(Macrobond!$HV:$HV,Engine!$B$3))/(INDEX(Macrobond!$QH:$QH,Engine!$B$3-12)*INDEX(Macrobond!$HV:$HV,Engine!$B$3-12))-1} -> 0.042681607 | AZ45: {=((INDEX(Macrobond!$QH:$QH,Engine!$B$3)*INDEX(Macrobond!$HV:$HV,Engine!$B$3))/(INDEX(Macrobond!$QH:$QH,Engine!$B$3-3)*INDEX(Macrobond!$HV:$HV,Engine!$B$3-3)))^4-1} -> 0.043477854
B46: 27+ wks as % of unemployed | C46: {=INDEX(Macrobond!$Z:$Z,Engine!B$9)/INDEX(Macrobond!$IS:$IS,Engine!B$9)*100} -> 20.198675 | D46: {=INDEX(Macrobond!$Z:$Z,Engine!C$9)/INDEX(Macrobond!$IS:$IS,Engine!C$9)*100} -> 23.40516 | E46: {=INDEX(Macrobond!$Z:$Z,Engine!D$9)/INDEX(Macrobond!$IS:$IS,Engine!D$9)*100} -> 25.055006 | F46: {=INDEX(Macrobond!$Z:$Z,Engine!E$9)/INDEX(Macrobond!$IS:$IS,Engine!E$9)*100} -> 26.070461 | G46: {=INDEX(Macrobond!$Z:$Z,Engine!F$9)/INDEX(Macrobond!$IS:$IS,Engine!F$9)*100} -> 23.865878 | H46: {=INDEX(Macrobond!$Z:$Z,Engine!G$9)/INDEX(Macrobond!$IS:$IS,Engine!G$9)*100} -> 23.865878 | I46: {=INDEX(Macrobond!$Z:$Z,Engine!H$9)/INDEX(Macrobond!$IS:$IS,Engine!H$9)*100} -> 24.546973 | J46: {=INDEX(Macrobond!$Z:$Z,Engine!I$9)/INDEX(Macrobond!$IS:$IS,Engine!I$9)*100} -> 25.962948 | ... O46: {=INDEX(Macrobond!$Z:$Z,Engine!N$9)/INDEX(Macrobond!$IS:$IS,Engine!N$9)*100} -> 27.206788 | P46: =$O46-$N46 -> 2.3458088 | Q46: =$O46-$L46 -> 2.1242362 | R46: =$O46-$C46 -> 7.0081125 | AK46: Nominal labor-income proxy; real needs CPI (not in tab).
B48: Group performance (rates, %) — more demographics pending data | C48: =Engine!B$10 -> 45778 | D48: =Engine!C$10 -> 45809 | E48: =Engine!D$10 -> 45839 | F48: =Engine!E$10 -> 45870 | G48: =Engine!F$10 -> 45901 | H48: =Engine!G$10 -> 45931 | I48: =Engine!H$10 -> 45962 | J48: =Engine!I$10 -> 45992 | ... O48: =Engine!N$10 -> 46143 | P48: MoM | Q48: 3M | R48: YoY | AK48: Leading indicators (SA) | AL48: =Engine!B$10 -> 45778 | AM48: =Engine!C$10 -> 45809 | AN48: =Engine!D$10 -> 45839 | AO48: =Engine!E$10 -> 45870 | AP48: =Engine!F$10 -> 45901 | AQ48: =Engine!G$10 -> 45931 | AR48: =Engine!H$10 -> 45962 | AS48: =Engine!I$10 -> 45992 | ... AX48: =Engine!N$10 -> 46143 | AY48: MoM | AZ48: 3M | BA48: YoY
B49: U-rate: Total (16+) | C49: {=INDEX(Macrobond!$IT:$IT,Engine!B$9)} -> 4.3 | D49: {=INDEX(Macrobond!$IT:$IT,Engine!C$9)} -> 4.1 | E49: {=INDEX(Macrobond!$IT:$IT,Engine!D$9)} -> 4.3 | F49: {=INDEX(Macrobond!$IT:$IT,Engine!E$9)} -> 4.3 | G49: {=INDEX(Macrobond!$IT:$IT,Engine!F$9)} -> 4.4 | H49: {=INDEX(Macrobond!$IT:$IT,Engine!G$9)} -> 4.4 | I49: {=INDEX(Macrobond!$IT:$IT,Engine!H$9)} -> 4.5 | J49: {=INDEX(Macrobond!$IT:$IT,Engine!I$9)} -> 4.4 | ... O49: {=INDEX(Macrobond!$IT:$IT,Engine!N$9)} -> 4.3 | P49: =$O49-$N49 -> 0 | Q49: =$O49-$L49 -> -0.1 | R49: =$O49-$C49 -> 0 | AK49: Temp help services (000s) | AL49: {=INDEX(Macrobond!$UY:$UY,Engine!B$9)/1000} -> 2513.1 | AM49: {=INDEX(Macrobond!$UY:$UY,Engine!C$9)/1000} -> 2504.6 | AN49: {=INDEX(Macrobond!$UY:$UY,Engine!D$9)/1000} -> 2494.2 | AO49: {=INDEX(Macrobond!$UY:$UY,Engine!E$9)/1000} -> 2483.3 | AP49: {=INDEX(Macrobond!$UY:$UY,Engine!F$9)/1000} -> 2471.6 | AQ49: {=INDEX(Macrobond!$UY:$UY,Engine!G$9)/1000} -> 2451.8 | AR49: {=INDEX(Macrobond!$UY:$UY,Engine!H$9)/1000} -> 2465.5 | AS49: {=INDEX(Macrobond!$UY:$UY,Engine!I$9)/1000} -> 2451.4 | ... AX49: {=INDEX(Macrobond!$UY:$UY,Engine!N$9)/1000} -> 2490 | AY49: =AX49-AW49 -> 1.4 | AZ49: =AX49-AU49 -> 18.1 | BA49: =AX49-AL49 -> -23.1
B50: U-rate: Men 16+ | C50: {=INDEX(Macrobond!$JB:$JB,Engine!B$9)} -> 4.3 | D50: {=INDEX(Macrobond!$JB:$JB,Engine!C$9)} -> 4.3 | E50: {=INDEX(Macrobond!$JB:$JB,Engine!D$9)} -> 4.4 | F50: {=INDEX(Macrobond!$JB:$JB,Engine!E$9)} -> 4.4 | G50: {=INDEX(Macrobond!$JB:$JB,Engine!F$9)} -> 4.4 | H50: {=INDEX(Macrobond!$JB:$JB,Engine!G$9)} -> 4.4 | I50: {=INDEX(Macrobond!$JB:$JB,Engine!H$9)} -> 4.5 | J50: {=INDEX(Macrobond!$JB:$JB,Engine!I$9)} -> 4.4 | ... O50: {=INDEX(Macrobond!$JB:$JB,Engine!N$9)} -> 4.4 | P50: =$O50-$N50 -> 0 | Q50: =$O50-$L50 -> 0 | R50: =$O50-$C50 -> 0.1 | AK50: Residential building (000s) | AL50: {=INDEX(Macrobond!$QU:$QU,Engine!B$9)/1000} -> 932.9 | AM50: {=INDEX(Macrobond!$QU:$QU,Engine!C$9)/1000} -> 930.6 | AN50: {=INDEX(Macrobond!$QU:$QU,Engine!D$9)/1000} -> 928.1 | AO50: {=INDEX(Macrobond!$QU:$QU,Engine!E$9)/1000} -> 922.8 | AP50: {=INDEX(Macrobond!$QU:$QU,Engine!F$9)/1000} -> 926.7 | AQ50: {=INDEX(Macrobond!$QU:$QU,Engine!G$9)/1000} -> 925.3 | AR50: {=INDEX(Macrobond!$QU:$QU,Engine!H$9)/1000} -> 928.4 | AS50: {=INDEX(Macrobond!$QU:$QU,Engine!I$9)/1000} -> 925.1 | ... AX50: {=INDEX(Macrobond!$QU:$QU,Engine!N$9)/1000} -> 924.7 | AY50: =AX50-AW50 -> -1.7 | AZ50: =AX50-AU50 -> -2.1 | BA50: =AX50-AL50 -> -8.2
B51: U-rate: Men 20+ | C51: {=INDEX(Macrobond!$JI:$JI,Engine!B$9)} -> 3.9 | D51: {=INDEX(Macrobond!$JI:$JI,Engine!C$9)} -> 3.9 | E51: {=INDEX(Macrobond!$JI:$JI,Engine!D$9)} -> 4 | F51: {=INDEX(Macrobond!$JI:$JI,Engine!E$9)} -> 4.1 | G51: {=INDEX(Macrobond!$JI:$JI,Engine!F$9)} -> 4.1 | H51: {=INDEX(Macrobond!$JI:$JI,Engine!G$9)} -> 4.1 | I51: {=INDEX(Macrobond!$JI:$JI,Engine!H$9)} -> 4.1 | J51: {=INDEX(Macrobond!$JI:$JI,Engine!I$9)} -> 3.9 | ... O51: {=INDEX(Macrobond!$JI:$JI,Engine!N$9)} -> 4 | P51: =$O51-$N51 -> 0 | Q51: =$O51-$L51 -> 0 | R51: =$O51-$C51 -> 0.1 | AK51: Manufacturing workweek (hrs) | AL51: {=INDEX(Macrobond!$HD:$HD,Engine!B$9)} -> 40.1 | AM51: {=INDEX(Macrobond!$HD:$HD,Engine!C$9)} -> 40.1 | AN51: {=INDEX(Macrobond!$HD:$HD,Engine!D$9)} -> 40.2 | AO51: {=INDEX(Macrobond!$HD:$HD,Engine!E$9)} -> 40 | AP51: {=INDEX(Macrobond!$HD:$HD,Engine!F$9)} -> 40 | AQ51: {=INDEX(Macrobond!$HD:$HD,Engine!G$9)} -> 40 | AR51: {=INDEX(Macrobond!$HD:$HD,Engine!H$9)} -> 40.1 | AS51: {=INDEX(Macrobond!$HD:$HD,Engine!I$9)} -> 40 | ... AX51: {=INDEX(Macrobond!$HD:$HD,Engine!N$9)} -> 40.4 | AY51: =AX51-AW51 -> 0 | AZ51: =AX51-AU51 -> 0.2 | BA51: =AX51-AL51 -> 0.3
B52: EPOP: Total (16+) | C52: {=INDEX(Macrobond!$IR:$IR,Engine!B$9)} -> 59.7 | D52: {=INDEX(Macrobond!$IR:$IR,Engine!C$9)} -> 59.7 | E52: {=INDEX(Macrobond!$IR:$IR,Engine!D$9)} -> 59.6 | F52: {=INDEX(Macrobond!$IR:$IR,Engine!E$9)} -> 59.6 | G52: {=INDEX(Macrobond!$IR:$IR,Engine!F$9)} -> 59.7 | H52: {=INDEX(Macrobond!$IR:$IR,Engine!G$9)} -> 59.7 | I52: {=INDEX(Macrobond!$IR:$IR,Engine!H$9)} -> 59.6 | J52: {=INDEX(Macrobond!$IR:$IR,Engine!I$9)} -> 59.7 | ... O52: {=INDEX(Macrobond!$IR:$IR,Engine!N$9)} -> 59.2 | P52: =$O52-$N52 -> 0.1 | Q52: =$O52-$L52 -> -0.1 | R52: =$O52-$C52 -> -0.5
B53: EPOP: Men 16+ | C53: {=INDEX(Macrobond!$IZ:$IZ,Engine!B$9)} -> 64.8 | D53: {=INDEX(Macrobond!$IZ:$IZ,Engine!C$9)} -> 64.9 | E53: {=INDEX(Macrobond!$IZ:$IZ,Engine!D$9)} -> 64.7 | F53: {=INDEX(Macrobond!$IZ:$IZ,Engine!E$9)} -> 65 | G53: {=INDEX(Macrobond!$IZ:$IZ,Engine!F$9)} -> 64.8 | H53: {=INDEX(Macrobond!$IZ:$IZ,Engine!G$9)} -> 64.8 | I53: {=INDEX(Macrobond!$IZ:$IZ,Engine!H$9)} -> 64.7 | J53: {=INDEX(Macrobond!$IZ:$IZ,Engine!I$9)} -> 64.8 | ... O53: {=INDEX(Macrobond!$IZ:$IZ,Engine!N$9)} -> 64.2 | P53: =$O53-$N53 -> 0.1 | Q53: =$O53-$L53 -> -0.1 | R53: =$O53-$C53 -> -0.6
B54: EPOP: Men 20+ | C54: {=INDEX(Macrobond!$JG:$JG,Engine!B$9)} -> 67.4 | D54: {=INDEX(Macrobond!$JG:$JG,Engine!C$9)} -> 67.4 | E54: {=INDEX(Macrobond!$JG:$JG,Engine!D$9)} -> 67.2 | F54: {=INDEX(Macrobond!$JG:$JG,Engine!E$9)} -> 67.5 | G54: {=INDEX(Macrobond!$JG:$JG,Engine!F$9)} -> 67.3 | H54: {=INDEX(Macrobond!$JG:$JG,Engine!G$9)} -> 67.3 | I54: {=INDEX(Macrobond!$JG:$JG,Engine!H$9)} -> 67.3 | J54: {=INDEX(Macrobond!$JG:$JG,Engine!I$9)} -> 67.4 | ... O54: {=INDEX(Macrobond!$JG:$JG,Engine!N$9)} -> 66.7 | P54: =$O54-$N54 -> 0.1 | Q54: =$O54-$L54 -> -0.1 | R54: =$O54-$C54 -> -0.7 | AK54: TOP / BOTTOM DETAILED INDUSTRIES (SA, ranked by MoM %)
AK55: TOP 10 — fastest MoM growth | AY55: MoM% | AZ55: MoM k | BA55: YoY% | BB55: 12M k | BC55: row
B56: Recession & underemployment signals | C56: value | P56: MoM | R56: status | AK56: 1 | AL56: {=INDEX(Engine!$A$21:$A$153,BC56)} -> Trade, Transportation & Utilities, Transportation & Warehousing, Transit & Ground Passenger Transportation | AY56: =_xlfn.AGGREGATE(14,6,Engine!$G$21:$G$153,AK56) -> 0.019321686 | AZ56: {=INDEX(Engine!$K$21:$K$153,BC56)} -> 9.4 | BA56: {=INDEX(Engine!$O$21:$O$153,BC56)} -> 0.012454063 | BB56: {=(INDEX(Engine!$C$21:$C$153,BC56)-INDEX(Engine!$N$21:$N$153,BC56))/1000} -> 6.1 | BC56: =MATCH(AY56,Engine!$G$21:$G$153,0) -> 63
B57: Sahm gap (pp) — trigger ≥ 0.50 | C57: =Engine!$B$18 -> 0.1 | R57: =IF(Engine!$B$18>=0.5,"TRIGGERED","No trigger") -> No trigger | AK57: =AK56+1 -> 2 | AL57: {=INDEX(Engine!$A$21:$A$153,BC57)} -> Mining & Logging, Support Activities for Mining | AY57: =_xlfn.AGGREGATE(14,6,Engine!$G$21:$G$153,AK57) -> 0.011671687 | AZ57: {=INDEX(Engine!$K$21:$K$153,BC57)} -> 3.1 | BA57: {=INDEX(Engine!$O$21:$O$153,BC57)} -> -0.0011152416 | BB57: {=(INDEX(Engine!$C$21:$C$153,BC57)-INDEX(Engine!$N$21:$N$153,BC57))/1000} -> -0.3 | BC57: =MATCH(AY57,Engine!$G$21:$G$153,0) -> 7
B58: U-6 underemployment rate (%) | C58: {=INDEX(Macrobond!$QE:$QE,Engine!$B$3)} -> 8.1 | P58: {=INDEX(Macrobond!$QE:$QE,Engine!$B$3)-INDEX(Macrobond!$QE:$QE,Engine!$B$3-1)} -> -0.1 | R58: {="U-3 gap: "&TEXT(INDEX(Macrobond!$QE:$QE,Engine!$B$3)-INDEX(Macrobond!$IT:$IT,Engine!$B$3),"0.0")&"pp"} -> U-3 gap: 3.8pp | AK58: =AK57+1 -> 3 | AL58: {=INDEX(Engine!$A$21:$A$153,BC58)} -> Leisure & Hospitality, Performing Arts & Spectator Sports | AY58: =_xlfn.AGGREGATE(14,6,Engine!$G$21:$G$153,AK58) -> 0.01112772 | AZ58: {=INDEX(Engine!$K$21:$K$153,BC58)} -> 6.7 | BA58: {=INDEX(Engine!$O$21:$O$153,BC58)} -> 0.02422611 | BB58: {=(INDEX(Engine!$C$21:$C$153,BC58)-INDEX(Engine!$N$21:$N$153,BC58))/1000} -> 14.4 | BC58: =MATCH(AY58,Engine!$G$21:$G$153,0) -> 116
B59: Note: PTER (part-time for economic reasons) not in data yet; U-6 shown as the underemployment proxy. | AK59: =AK58+1 -> 4 | AL59: {=INDEX(Engine!$A$21:$A$153,BC59)} -> Mining & Logging, Mining, Except Oil & Gas | AY59: =_xlfn.AGGREGATE(14,6,Engine!$G$21:$G$153,AK59) -> 0.0084745763 | AZ59: {=INDEX(Engine!$K$21:$K$153,BC59)} -> 1.6 | BA59: {=INDEX(Engine!$O$21:$O$153,BC59)} -> 0.0058108822 | BB59: {=(INDEX(Engine!$C$21:$C$153,BC59)-INDEX(Engine!$N$21:$N$153,BC59))/1000} -> 1.1 | BC59: =MATCH(AY59,Engine!$G$21:$G$153,0) -> 5
AK60: =AK59+1 -> 5 | AL60: {=INDEX(Engine!$A$21:$A$153,BC60)} -> Mining & Logging, Mining | AY60: =_xlfn.AGGREGATE(14,6,Engine!$G$21:$G$153,AK60) -> 0.0084225303 | AZ60: {=INDEX(Engine!$K$21:$K$153,BC60)} -> 4.8 | BA60: {=INDEX(Engine!$O$21:$O$153,BC60)} -> -0.0038134859 | BB60: {=(INDEX(Engine!$C$21:$C$153,BC60)-INDEX(Engine!$N$21:$N$153,BC60))/1000} -> -2.2 | BC60: =MATCH(AY60,Engine!$G$21:$G$153,0) -> 3
AK61: =AK60+1 -> 6 | AL61: {=INDEX(Engine!$A$21:$A$153,BC61)} -> Information, Data Processing, Hosting & Related Services | AY61: =_xlfn.AGGREGATE(14,6,Engine!$G$21:$G$153,AK61) -> 0.0080017301 | AZ61: {=INDEX(Engine!$K$21:$K$153,BC61)} -> 3.7 | BA61: {=INDEX(Engine!$O$21:$O$153,BC61)} -> -0.031379884 | BB61: {=(INDEX(Engine!$C$21:$C$153,BC61)-INDEX(Engine!$N$21:$N$153,BC61))/1000} -> -15.1 | BC61: =MATCH(AY61,Engine!$G$21:$G$153,0) -> 74
AK62: =AK61+1 -> 7 | AL62: {=INDEX(Engine!$A$21:$A$153,BC62)} -> Government, Local Government, Excluding Education | AY62: =_xlfn.AGGREGATE(14,6,Engine!$G$21:$G$153,AK62) -> 0.006259263 | AZ62: {=INDEX(Engine!$K$21:$K$153,BC62)} -> 43.5 | BA62: {=INDEX(Engine!$O$21:$O$153,BC62)} -> 0.015494083 | BB62: {=(INDEX(Engine!$C$21:$C$153,BC62)-INDEX(Engine!$N$21:$N$153,BC62))/1000} -> 106.7 | BC62: =MATCH(AY62,Engine!$G$21:$G$153,0) -> 133
AK63: =AK62+1 -> 8 | AL63: {=INDEX(Engine!$A$21:$A$153,BC63)} -> Trade, Transportation & Utilities, Transportation & Warehousing, Scenic & Sightseeing Transportation | AY63: =_xlfn.AGGREGATE(14,6,Engine!$G$21:$G$153,AK63) -> 0.0062111801 | AZ63: {=INDEX(Engine!$K$21:$K$153,BC63)} -> 0.2 | BA63: {=INDEX(Engine!$O$21:$O$153,BC63)} -> -0.049853372 | BB63: {=(INDEX(Engine!$C$21:$C$153,BC63)-INDEX(Engine!$N$21:$N$153,BC63))/1000} -> -1.7 | BC63: =MATCH(AY63,Engine!$G$21:$G$153,0) -> 65
AK64: =AK63+1 -> 9 | AL64: {=INDEX(Engine!$A$21:$A$153,BC64)} -> Education & Health Services, Home Health Care Services | AY64: =_xlfn.AGGREGATE(14,6,Engine!$G$21:$G$153,AK64) -> 0.005827942 | AZ64: {=INDEX(Engine!$K$21:$K$153,BC64)} -> 10.9 | BA64: {=INDEX(Engine!$O$21:$O$153,BC64)} -> 0.060547976 | BB64: {=(INDEX(Engine!$C$21:$C$153,BC64)-INDEX(Engine!$N$21:$N$153,BC64))/1000} -> 107.4 | BC64: =MATCH(AY64,Engine!$G$21:$G$153,0) -> 110
AK65: =AK64+1 -> 10 | AL65: {=INDEX(Engine!$A$21:$A$153,BC65)} -> Education & Health Services, Medical & Diagnostic Laboratories | AY65: =_xlfn.AGGREGATE(14,6,Engine!$G$21:$G$153,AK65) -> 0.0058045792 | AZ65: {=INDEX(Engine!$K$21:$K$153,BC65)} -> 1.8 | BA65: {=INDEX(Engine!$O$21:$O$153,BC65)} -> 0.017618271 | BB65: {=(INDEX(Engine!$C$21:$C$153,BC65)-INDEX(Engine!$N$21:$N$153,BC65))/1000} -> 5.4 | BC65: =MATCH(AY65,Engine!$G$21:$G$153,0) -> 109
AK66: BOTTOM 10 — weakest MoM | AY66: MoM% | AZ66: MoM k | BA66: YoY% | BB66: 12M k | BC66: row
AK67: 1 | AL67: {=INDEX(Engine!$A$21:$A$153,BC67)} -> Trade, Transportation & Utilities, Transportation & Warehousing, Water Transportation | AY67: =_xlfn.AGGREGATE(15,6,Engine!$G$21:$G$153,AK67) -> -0.018413598 | AZ67: {=INDEX(Engine!$K$21:$K$153,BC67)} -> -1.3 | BA67: {=INDEX(Engine!$O$21:$O$153,BC67)} -> -0.012820513 | BB67: {=(INDEX(Engine!$C$21:$C$153,BC67)-INDEX(Engine!$N$21:$N$153,BC67))/1000} -> -0.9 | BC67: =MATCH(AY67,Engine!$G$21:$G$153,0) -> 61
AK68: =AK67+1 -> 2 | AL68: {=INDEX(Engine!$A$21:$A$153,BC68)} -> Trade, Transportation & Utilities, Transportation & Warehousing, Air Transportation | AY68: =_xlfn.AGGREGATE(15,6,Engine!$G$21:$G$153,AK68) -> -0.015109413 | AZ68: {=INDEX(Engine!$K$21:$K$153,BC68)} -> -8.7 | BA68: {=INDEX(Engine!$O$21:$O$153,BC68)} -> -0.010987095 | BB68: {=(INDEX(Engine!$C$21:$C$153,BC68)-INDEX(Engine!$N$21:$N$153,BC68))/1000} -> -6.3 | BC68: =MATCH(AY68,Engine!$G$21:$G$153,0) -> 59
AK69: =AK68+1 -> 3 | AL69: {=INDEX(Engine!$A$21:$A$153,BC69)} -> Mining & Logging, Logging | AY69: =_xlfn.AGGREGATE(15,6,Engine!$G$21:$G$153,AK69) -> -0.012755102 | AZ69: {=INDEX(Engine!$K$21:$K$153,BC69)} -> -0.5 | BA69: {=INDEX(Engine!$O$21:$O$153,BC69)} -> -0.065217391 | BB69: {=(INDEX(Engine!$C$21:$C$153,BC69)-INDEX(Engine!$N$21:$N$153,BC69))/1000} -> -2.7 | BC69: =MATCH(AY69,Engine!$G$21:$G$153,0) -> 2
AK70: =AK69+1 -> 4 | AL70: {=INDEX(Engine!$A$21:$A$153,BC70)} -> Information, Broadcasting | AY70: =_xlfn.AGGREGATE(15,6,Engine!$G$21:$G$153,AK70) -> -0.011862396 | AZ70: {=INDEX(Engine!$K$21:$K$153,BC70)} -> -4 | BA70: {=INDEX(Engine!$O$21:$O$153,BC70)} -> -0.026300409 | BB70: {=(INDEX(Engine!$C$21:$C$153,BC70)-INDEX(Engine!$N$21:$N$153,BC70))/1000} -> -9 | BC70: =MATCH(AY70,Engine!$G$21:$G$153,0) -> 72
AK71: =AK70+1 -> 5 | AL71: {=INDEX(Engine!$A$21:$A$153,BC71)} -> Financial Activities, Lessors of Nonfinancial Intangible Assets | AY71: =_xlfn.AGGREGATE(15,6,Engine!$G$21:$G$153,AK71) -> -0.0093457944 | AZ71: {=INDEX(Engine!$K$21:$K$153,BC71)} -> -0.2 | BA71: {=INDEX(Engine!$O$21:$O$153,BC71)} -> -0.03196347 | BB71: {=(INDEX(Engine!$C$21:$C$153,BC71)-INDEX(Engine!$N$21:$N$153,BC71))/1000} -> -0.7 | BC71: =MATCH(AY71,Engine!$G$21:$G$153,0) -> 87
AK72: =AK71+1 -> 6 | AL72: {=INDEX(Engine!$A$21:$A$153,BC72)} -> Manufacturing, Non-Durable Goods, Plastics & Rubber Products | AY72: =_xlfn.AGGREGATE(15,6,Engine!$G$21:$G$153,AK72) -> -0.008766887 | AZ72: {=INDEX(Engine!$K$21:$K$153,BC72)} -> -6.1 | BA72: {=INDEX(Engine!$O$21:$O$153,BC72)} -> -0.023779193 | BB72: {=(INDEX(Engine!$C$21:$C$153,BC72)-INDEX(Engine!$N$21:$N$153,BC72))/1000} -> -16.8 | BC72: =MATCH(AY72,Engine!$G$21:$G$153,0) -> 38
AK73: =AK72+1 -> 7 | AL73: {=INDEX(Engine!$A$21:$A$153,BC73)} -> Trade, Transportation & Utilities, Wholesale Trade, Electronic Markets & Agents & Brokers | AY73: =_xlfn.AGGREGATE(15,6,Engine!$G$21:$G$153,AK73) -> -0.0083691473 | AZ73: {=INDEX(Engine!$K$21:$K$153,BC73)} -> -3.7 | BA73: {=INDEX(Engine!$O$21:$O$153,BC73)} -> -0.021646954 | BB73: {=(INDEX(Engine!$C$21:$C$153,BC73)-INDEX(Engine!$N$21:$N$153,BC73))/1000} -> -9.7 | BC73: =MATCH(AY73,Engine!$G$21:$G$153,0) -> 42
AK74: =AK73+1 -> 8 | AL74: {=INDEX(Engine!$A$21:$A$153,BC74)} -> Information, Motion Picture & Sound Recording Industries | AY74: =_xlfn.AGGREGATE(15,6,Engine!$G$21:$G$153,AK74) -> -0.0081595648 | AZ74: {=INDEX(Engine!$K$21:$K$153,BC74)} -> -2.7 | BA74: {=INDEX(Engine!$O$21:$O$153,BC74)} -> -0.07523246 | BB74: {=(INDEX(Engine!$C$21:$C$153,BC74)-INDEX(Engine!$N$21:$N$153,BC74))/1000} -> -26.7 | BC74: =MATCH(AY74,Engine!$G$21:$G$153,0) -> 70
AK75: =AK74+1 -> 9 | AL75: {=INDEX(Engine!$A$21:$A$153,BC75)} -> Manufacturing, Non-Durable Goods, Textile Product Mills | AY75: =_xlfn.AGGREGATE(15,6,Engine!$G$21:$G$153,AK75) -> -0.0074626866 | AZ75: {=INDEX(Engine!$K$21:$K$153,BC75)} -> -0.7 | BA75: {=INDEX(Engine!$O$21:$O$153,BC75)} -> -0.0064034152 | BB75: {=(INDEX(Engine!$C$21:$C$153,BC75)-INDEX(Engine!$N$21:$N$153,BC75))/1000} -> -0.6 | BC75: =MATCH(AY75,Engine!$G$21:$G$153,0) -> 32
AK76: =AK75+1 -> 10 | AL76: {=INDEX(Engine!$A$21:$A$153,BC76)} -> Manufacturing, Non-Durable Goods, Textile Mills | AY76: =_xlfn.AGGREGATE(15,6,Engine!$G$21:$G$153,AK76) -> -0.0063371356 | AZ76: {=INDEX(Engine!$K$21:$K$153,BC76)} -> -0.5 | BA76: {=INDEX(Engine!$O$21:$O$153,BC76)} -> -0.043902439 | BB76: {=(INDEX(Engine!$C$21:$C$153,BC76)-INDEX(Engine!$N$21:$N$153,BC76))/1000} -> -3.6 | BC76: =MATCH(AY76,Engine!$G$21:$G$153,0) -> 31
AK78: Employment breadth — % of 133 detailed SA industries adding jobs
AK79: 1-month | AY79: =Engine!$B$13 -> 0.57894737 | BA79: =IF(AY79>0.5,"expansion","contraction") -> expansion
AK80: 3-month | AY80: =Engine!$B$14 -> 0.59398496 | BA80: =IF(AY80>0.5,"expansion","contraction") -> expansion
AK81: 6-month | AY81: =Engine!$B$15 -> 0.54135338 | BA81: =IF(AY81>0.5,"expansion","contraction") -> expansion
AK83: SA vs NSA check — total nonfarm payrolls MoM (000s) | AL83: =Engine!B$10 -> 45778 | AM83: =Engine!C$10 -> 45809 | AN83: =Engine!D$10 -> 45839 | AO83: =Engine!E$10 -> 45870 | AP83: =Engine!F$10 -> 45901 | AQ83: =Engine!G$10 -> 45931 | AR83: =Engine!H$10 -> 45962 | AS83: =Engine!I$10 -> 45992 | ... AX83: =Engine!N$10 -> 46143
AK84: SA MoM (k) | AL84: {=(INDEX(Macrobond!$QG:$QG,Engine!B$9)-INDEX(Macrobond!$QG:$QG,Engine!B$9-1))/1000} -> 13 | AM84: {=(INDEX(Macrobond!$QG:$QG,Engine!C$9)-INDEX(Macrobond!$QG:$QG,Engine!C$9-1))/1000} -> -20 | AN84: {=(INDEX(Macrobond!$QG:$QG,Engine!D$9)-INDEX(Macrobond!$QG:$QG,Engine!D$9-1))/1000} -> 64 | AO84: {=(INDEX(Macrobond!$QG:$QG,Engine!E$9)-INDEX(Macrobond!$QG:$QG,Engine!E$9-1))/1000} -> -70 | AP84: {=(INDEX(Macrobond!$QG:$QG,Engine!F$9)-INDEX(Macrobond!$QG:$QG,Engine!F$9-1))/1000} -> 76 | AQ84: {=(INDEX(Macrobond!$QG:$QG,Engine!G$9)-INDEX(Macrobond!$QG:$QG,Engine!G$9-1))/1000} -> -140 | AR84: {=(INDEX(Macrobond!$QG:$QG,Engine!H$9)-INDEX(Macrobond!$QG:$QG,Engine!H$9-1))/1000} -> 41 | AS84: {=(INDEX(Macrobond!$QG:$QG,Engine!I$9)-INDEX(Macrobond!$QG:$QG,Engine!I$9-1))/1000} -> -17 | ... AX84: {=(INDEX(Macrobond!$QG:$QG,Engine!N$9)-INDEX(Macrobond!$QG:$QG,Engine!N$9-1))/1000} -> 172
AK85: NSA MoM (k) | AL85: {=(INDEX(Macrobond!$AI:$AI,Engine!B$9)-INDEX(Macrobond!$AI:$AI,Engine!B$9-1))/1000} -> 664 | AM85: {=(INDEX(Macrobond!$AI:$AI,Engine!C$9)-INDEX(Macrobond!$AI:$AI,Engine!C$9-1))/1000} -> 267 | AN85: {=(INDEX(Macrobond!$AI:$AI,Engine!D$9)-INDEX(Macrobond!$AI:$AI,Engine!D$9-1))/1000} -> -1032 | AO85: {=(INDEX(Macrobond!$AI:$AI,Engine!E$9)-INDEX(Macrobond!$AI:$AI,Engine!E$9-1))/1000} -> 157 | AP85: {=(INDEX(Macrobond!$AI:$AI,Engine!F$9)-INDEX(Macrobond!$AI:$AI,Engine!F$9-1))/1000} -> 305 | AQ85: {=(INDEX(Macrobond!$AI:$AI,Engine!G$9)-INDEX(Macrobond!$AI:$AI,Engine!G$9-1))/1000} -> 626 | AR85: {=(INDEX(Macrobond!$AI:$AI,Engine!H$9)-INDEX(Macrobond!$AI:$AI,Engine!H$9-1))/1000} -> 216 | AS85: {=(INDEX(Macrobond!$AI:$AI,Engine!I$9)-INDEX(Macrobond!$AI:$AI,Engine!I$9-1))/1000} -> -213 | ... AX85: {=(INDEX(Macrobond!$AI:$AI,Engine!N$9)-INDEX(Macrobond!$AI:$AI,Engine!N$9-1))/1000} -> 741
AK86: Seasonal gap (NSA−SA) | AL86: =AL85-AL84 -> 651 | AM86: =AM85-AM84 -> 287 | AN86: =AN85-AN84 -> -1096 | AO86: =AO85-AO84 -> 227 | AP86: =AP85-AP84 -> 229 | AQ86: =AQ85-AQ84 -> 766 | AR86: =AR85-AR84 -> 175 | AS86: =AS85-AS84 -> -196 | ... AX86: =AX85-AX84 -> 569
AK87: Large gaps flag seasonal distortion in the raw print; SA is the clean read.

Sheet Macrobond
C4: United States
D5: Unemployment, National, By Reason, Number of Job Losers & Persons Who Completed Temporary Jobs, on Temporary Layoff, SA | E5: Unemployment, National, By Reason, Number of Job Losers & Persons Who Completed Temporary Jobs, Total, SA | F5: Unemployment, National, By Reason, Number of Job Losers & Persons Who Completed Temporary Jobs, Not on Temporary Layoff, Total, SA | G5: Unemployment, National, By Reason, Number of Job Losers & Persons Who Completed Temporary Jobs, Not on Temporary Layoff, Permanent Job Losers, SA | H5: Unemployment, National, By Reason, Number of Job Losers & Persons Who Completed Temporary Jobs, Not on Temporary Layoff, Persons Who Completed Temporary Jobs, SA | I5: Unemployment, National, By Reason, Number of Job Leavers, SA | J5: Unemployment, National, By Reason, Number of Re-Entrants, SA | K5: Unemployment, National, By Reason, Number of New Entrants, SA | L5: Unemployment, National, By Reason, Percent Distribution, Job Losers & Persons Who Completed Temporary Jobs, Total, SA | M5: Unemployment, National, By Reason, Percent Distribution, Job Losers & Persons Who Completed Temporary Jobs, on Temporary Layoff, SA | N5: Unemployment, National, By Reason, Percent Distribution, Job Losers & Persons Who Completed Temporary Jobs, Not on Temporary Layoff, SA | O5: Unemployment, National, By Reason, Percent Distribution, Job Leavers, SA | P5: Unemployment, National, By Reason, Percent Distribution, Re-Entrants, SA | Q5: Unemployment, National, By Reason, Percent Distribution, New Entrants, SA | R5: Unemployment, National, By Reason, Unemployed as A Percent of the Civilian Labor Force, Job Losers & Persons Who Completed Temporary Jobs (U-2), SA | S5: Unemployment, National, By Reason, Unemployed as A Percent of the Civilian Labor Force, Job Leavers, SA | T5: Unemployment, National, By Reason, Unemployed as A Percent of the Civilian Labor Force, Re-Entrants, SA | U5: Unemployment, National, By Reason, Unemployed as A Percent of the Civilian Labor Force, New Entrants, SA | V5: Unemployment, National, By Duration, Less than 5 Weeks, SA | W5: Unemployment, National, By Duration, 5 to 14 Weeks, SA | X5: Unemployment, National, By Duration, 15 Weeks & Over, Total, SA | Y5: Unemployment, National, By Duration, 15 to 26 Weeks, SA | Z5: Unemployment, National, By Duration, 27 Weeks & Over, SA | AA5: Unemployment, National, By Duration, Average (Mean), SA | AB5: Unemployment, National, By Duration, Median, SA | AC5: Unemployment, National, By Duration, Less than 5 Weeks, Percent Distribution, SA | AD5: Unemployment, National, By Duration, 5 to 14 Weeks, Percent Distribution, SA | AE5: Unemployment, National, By Duration, 15 Weeks & Over, Total, Percent Distribution, SA | AF5: Unemployment, National, By Duration, 15 to 26 Weeks, Percent Distribution, SA | AG5: Unemployment, National, By Duration, 27 Weeks & Over, Percent Distribution, SA | AH5: Employment, Payroll, Nonfarm, Private, Payroll, Total | AI5: Employment, Payroll, Nonfarm, Payroll, Total | AJ5: Employment, Payroll, Nonfarm, Goods-Producing, Payroll, Total | AK5: Employment, Payroll, Mining & Logging, Nonfarm, Payroll, Total | AL5: Employment, Payroll, Mining & Logging, Nonfarm, Logging, Payroll | AM5: Employment, Payroll, Mining & Logging, Nonfarm, Mining, Payroll | AN5: Employment, Payroll, Mining & Logging, Nonfarm, Oil & Gas Extraction, Payroll | AO5: Employment, Payroll, Mining & Logging, Nonfarm, Mining, Except Oil & Gas, Payroll | AP5: Employment, Payroll, Mining & Logging, Nonfarm, Coal Mining, Payroll | AQ5: BLS, CES National, All Employees, 10_212200 Metal Ore Mining | AR5: BLS, CES National, All Employees, 10_212300 Nonmetallic Mineral Mining & Quarrying | AS5: Employment, Payroll, Mining & Logging, Nonfarm, Support Activities for Mining, Payroll | AT5: Employment, Payroll, Construction, Nonfarm, Payroll, Total | AU5: Employment, Payroll, Construction, Nonfarm, Construction of Buildings, Payroll | AV5: Employment, Payroll, Construction, Nonfarm, Residential Building, Payroll | AW5: Employment, Payroll, Construction, Nonfarm, Nonresidential Building, Payroll | AX5: Employment, Payroll, Construction, Nonfarm, Heavy & Civil Engineering Construction, Payroll | AY5: Employment, Payroll, Construction, Nonfarm, Specialty Trade Contractors, Payroll | AZ5: Employment, Payroll, Construction, Nonfarm, Residential Specialty Trade Contractors, Payroll | BA5: Employment, Payroll, Construction, Nonfarm, Nonresidential Specialty Trade Contractors, Payroll | BB5: Employment, Payroll, Manufacturing, Total, Nonfarm, Payroll | BC5: Employment, Payroll, Manufacturing, Durable Goods, Nonfarm, Total, Payroll | BD5: Employment, Payroll, Manufacturing, Durable Goods, Nonfarm, Wood Products, Payroll | BE5: Employment, Payroll, Manufacturing, Durable Goods, Nonfarm, Nonmetallic Mineral Products, Payroll | BF5: Employment, Payroll, Manufacturing, Durable Goods, Nonfarm, Primary Metals, Payroll | BG5: Employment, Payroll, Manufacturing, Durable Goods, Nonfarm, Fabricated Metal Products, Payroll | BH5: Employment, Payroll, Manufacturing, Durable Goods, Nonfarm, Machinery, Payroll | BI5: Employment, Payroll, Manufacturing, Durable Goods, Nonfarm, Computer & Electronic Products, Payroll | BJ5: Employment, Payroll, Manufacturing, Durable Goods, Nonfarm, Computer & Peripheral Equipment, Payroll | BK5: Employment, Payroll, Manufacturing, Durable Goods, Nonfarm, Communications Equipment, Payroll | BL5: Employment, Payroll, Manufacturing, Durable Goods, Nonfarm, Semiconductors & Electronic Components, Payroll | BM5: Employment, Payroll, Manufacturing, Durable Goods, Nonfarm, Electronic Instruments, Payroll | BN5: BLS, CES National, All Employees, 31_334600 Manufacturing & Reproducing Magnetic & Optical Media & Audio & Video Equipment Manufacturing | BO5: Employment, Payroll, Manufacturing, Durable Goods, Nonfarm, Electrical Equipment & Appliances, Payroll | BP5: Employment, Payroll, Manufacturing, Durable Goods, Nonfarm, Transportation Equipment, Payroll | BQ5: Employment, Payroll, Manufacturing, Durable Goods, Nonfarm, Motor Vehicles & Parts, Payroll | BR5: Employment, Payroll, Manufacturing, Durable Goods, Nonfarm, Furniture & Related Products, Payroll | BS5: Employment, Payroll, Manufacturing, Durable Goods, Nonfarm, Miscellaneous Manufacturing, Payroll | BT5: Employment, Payroll, Manufacturing, Non-Durable Goods, Nonfarm, Total, Payroll | BU5: Employment, Payroll, Manufacturing, Non-Durable Goods, Nonfarm, Food Manufacturing, Payroll | BV5: Employment, Payroll, Manufacturing, Non-Durable Goods, Nonfarm, Textile Mills, Payroll | BW5: Employment, Payroll, Manufacturing, Non-Durable Goods, Nonfarm, Textile Product Mills, Payroll | BX5: Employment, Payroll, Manufacturing, Non-Durable Goods, Nonfarm, Apparel, Payroll | BY5: Employment, Payroll, Manufacturing, Non-Durable Goods, Nonfarm, Paper & Paper Products, Payroll | BZ5: Employment, Payroll, Manufacturing, Non-Durable Goods, Nonfarm, Printing & Related Support Activities, Payroll | CA5: Employment, Payroll, Manufacturing, Non-Durable Goods, Nonfarm, Petroleum & Coal Products, Payroll | CB5: Employment, Payroll, Manufacturing, Non-Durable Goods, Nonfarm, Chemicals, Payroll | CC5: Employment, Payroll, Manufacturing, Non-Durable Goods, Nonfarm, Plastics & Rubber Products, Payroll | CD5: BLS, CES National, All Employees, 32_329000 Beverage, Tobacco, & Leather & Allied Product Manufacturing | CE5: Employment, Payroll, Nonfarm, Private Service-Providing, Payroll, Total | CF5: Employment, Payroll, Trade, Transportation & Utilities, Total, Nonfarm, Payroll | CG5: Employment, Payroll, Trade, Transportation & Utilities, Wholesale Trade, Nonfarm, Total, Payroll | CH5: Employment, Payroll, Trade, Transportation & Utilities, Wholesale Trade, Nonfarm, Durable Goods, Payroll | CI5: Employment, Payroll, Trade, Transportation & Utilities, Wholesale Trade, Nonfarm, Non-Durable Goods, Payroll | CJ5: Employment, Payroll, Trade, Transportation & Utilities, Wholesale Trade, Nonfarm, Electronic Markets & Agents & Brokers, Payroll | CK5: Employment, Payroll, Trade, Transportation & Utilities, Retail Trade, Nonfarm, Total, Payroll | CL5: Employment, Payroll, Trade, Transportation & Utilities, Retail Trade, Nonfarm, Motor Vehicle & Parts Dealers, Payroll | CM5: Employment, Payroll, Trade, Transportation & Utilities, Retail Trade, Nonfarm, Automobile Dealers, Payroll | CN5: BLS, CES National, All Employees, 42_441200 Other Motor Vehicle Dealers | CO5: BLS, CES National, All Employees, 42_441300 Automotive Parts, Accessories, & Tire Retailers | CP5: Employment, Payroll, Trade, Transportation & Utilities, Retail Trade, Nonfarm, Building Material & Garden Supply Stores, Payroll | CQ5: Employment, Payroll, Trade, Transportation & Utilities, Retail Trade, Nonfarm, Food & Beverage Stores, Payroll | CR5: Employment, Payroll, Trade, Transportation & Utilities, Retail Trade, Nonfarm, Furniture, Home Furnishings, Electronics, & Appliance Retailers, Payroll | CS5: Employment, Payroll, Trade, Transportation & Utilities, Retail Trade, Nonfarm, Furniture & Home Furnishings Retailers, Payroll | CT5: Employment, Payroll, Trade, Transportation & Utilities, Retail Trade, Nonfarm, Electronics & Appliance Retailers, Payroll | CU5: Employment, Payroll, Trade, Transportation & Utilities, Retail Trade, Nonfarm, General Merchandise Retailers, Payroll | CV5: Employment, Payroll, Trade, Transportation & Utilities, Retail Trade, Nonfarm, Department Stores, Payroll | CW5: Employment, Payroll, Trade, Transportation & Utilities, Retail Trade, Nonfarm, Warehouse Clubs, Supercenters, & Other General Merchandise Retailers, Payroll | CX5: Employment, Payroll, Trade, Transportation & Utilities, Retail Trade, Nonfarm, Health & Personal Care Retailers, Payroll | CY5: Employment, Payroll, Trade, Transportation & Utilities, Retail Trade, Nonfarm, Gasoline Stations & Fuel Dealers, Payroll | CZ5: Employment, Payroll, Trade, Transportation & Utilities, Retail Trade, Nonfarm, Clothing, Clothing Accessories, Shoe, & Jewelry Retailers, Payroll | DA5: Employment, Payroll, Trade, Transportation & Utilities, Retail Trade, Nonfarm, Sporting Goods, Hobby, Musical Instrument, Book, & Miscellaneous Retailers, Payroll | DB5: Employment, Payroll, Trade, Transportation & Utilities, Transportation & Warehousing, Nonfarm, Total, Payroll | DC5: Employment, Payroll, Trade, Transportation & Utilities, Transportation & Warehousing, Nonfarm, Air Transportation, Payroll | DD5: Employment, Payroll, Trade, Transportation & Utilities, Transportation & Warehousing, Nonfarm, Rail Transportation, Payroll | DE5: Employment, Payroll, Trade, Transportation & Utilities, Transportation & Warehousing, Nonfarm, Water Transportation, Payroll | DF5: Employment, Payroll, Trade, Transportation & Utilities, Transportation & Warehousing, Nonfarm, Truck Transportation, Payroll | DG5: Employment, Payroll, Trade, Transportation & Utilities, Transportation & Warehousing, Nonfarm, Transit & Ground Passenger Transportation, Payroll | DH5: Employment, Payroll, Trade, Transportation & Utilities, Transportation & Warehousing, Nonfarm, Pipeline Transportation, Payroll | DI5: Employment, Payroll, Trade, Transportation & Utilities, Transportation & Warehousing, Nonfarm, Scenic & Sightseeing Transportation, Payroll | DJ5: Employment, Payroll, Trade, Transportation & Utilities, Transportation & Warehousing, Nonfarm, Support Activities for Transportation, Payroll | DK5: Employment, Payroll, Trade, Transportation & Utilities, Transportation & Warehousing, Nonfarm, Couriers & Messengers, Payroll | DL5: Employment, Payroll, Trade, Transportation & Utilities, Transportation & Warehousing, Nonfarm, Warehousing & Storage, Payroll | DM5: Employment, Payroll, Trade, Transportation & Utilities, Utilities, Nonfarm, Total, Payroll | DN5: Employment, Payroll, Information, Nonfarm, Payroll, Total | DO5: Employment, Payroll, Information, Nonfarm, Motion Picture & Sound Recording Industries, Payroll | DP5: Employment, Payroll, Information, Nonfarm, Publishing Industries, Payroll | DQ5: Employment, Payroll, Information, Nonfarm, Broadcasting, Payroll | DR5: Employment, Payroll, Information, Nonfarm, Telecommunications, Payroll | DS5: Employment, Payroll, Information, Nonfarm, Data Processing, Hosting & Related Services, Payroll | DT5: Employment, Payroll, Information, Nonfarm, Other Information Services, Payroll | DU5: Employment, Payroll, Financial Activities, Nonfarm, Payroll, Total | DV5: Employment, Payroll, Financial Activities, Nonfarm, Finance & Insurance, Payroll | DW5: Employment, Payroll, Financial Activities, Nonfarm, Monetary Authorities - Central Bank, Payroll | DX5: Employment, Payroll, Financial Activities, Nonfarm, Credit Intermediation & Related Activities, Payroll | DY5: Employment, Payroll, Financial Activities, Nonfarm, Depository Credit Intermediation, Payroll | DZ5: Employment, Payroll, Financial Activities, Nonfarm, Commercial Banking, Payroll | EA5: BLS, CES National, All Employees, 55_522200 Nondepository Credit Intermediation | EB5: Employment, Payroll, Financial Activities, Nonfarm, Activities Related to Credit Intermediation, Payroll | EC5: Employment, Payroll, Financial Activities, Nonfarm, Securities, Commodity Contracts, Investments, Payroll | ED5: Employment, Payroll, Financial Activities, Nonfarm, Insurance Carriers & Related Activities, Payroll | EE5: Employment, Payroll, Financial Activities, Nonfarm, Real Estate & Rental & Leasing, Payroll | EF5: Employment, Payroll, Financial Activities, Nonfarm, Real Estate, Payroll | EG5: Employment, Payroll, Financial Activities, Nonfarm, Rental & Leasing Services, Payroll | EH5: Employment, Payroll, Financial Activities, Nonfarm, Lessors of Nonfinancial Intangible Assets, Payroll | EI5: Employment, Payroll, Professional & Business Services, Nonfarm, Payroll, Total | EJ5: Employment, Payroll, Professional & Business Services, Nonfarm, Professional & Technical Services, Payroll | EK5: Employment, Payroll, Professional & Business Services, Nonfarm, Legal Services, Payroll | EL5: Employment, Payroll, Professional & Business Services, Nonfarm, Accounting & Bookkeeping Services, Payroll | EM5: Employment, Payroll, Professional & Business Services, Nonfarm, Architectural & Engineering Services, Payroll | EN5: BLS, CES National, All Employees, 60_541400 Specialized Design Services | EO5: Employment, Payroll, Professional & Business Services, Nonfarm, Computer Systems Design & Related Services, Payroll | EP5: Employment, Payroll, Professional & Business Services, Nonfarm, Management & Technical Consulting Services, Payroll | EQ5: BLS, CES National, All Employees, 60_541700 Scientific Research & Development Services | ER5: BLS, CES National, All Employees, 60_541800 Advertising, Public Relations, & Related Services | ES5: BLS, CES National, All Employees, 60_541900 Other Professional, Scientific, & Technical Services | ET5: Employment, Payroll, Professional & Business Services, Nonfarm, Management of Companies & Enterprises, Payroll | EU5: Employment, Payroll, Professional & Business Services, Nonfarm, Administrative & Waste Services, Payroll | EV5: Employment, Payroll, Professional & Business Services, Nonfarm, Administrative & Support Services, Payroll | EW5: BLS, CES National, All Employees, 60_561100 Office Administrative Services | EX5: BLS, CES National, All Employees, 60_561200 Facilities Support Services | EY5: Employment, Payroll, Professional & Business Services, Nonfarm, Employment Services, Payroll | EZ5: Employment, Payroll, Professional & Business Services, Nonfarm, Temporary Help Services, Payroll | FA5: Employment, Payroll, Professional & Business Services, Nonfarm, Business Support Services, Payroll | FB5: BLS, CES National, All Employees, 60_561500 Travel Arrangement & Reservation Services | FC5: BLS, CES National, All Employees, 60_561600 Investigation & Security Services | FD5: Employment, Payroll, Professional & Business Services, Nonfarm, Services to Buildings & Dwellings, Payroll | FE5: BLS, CES National, All Employees, 60_561900 Other Support Services | FF5: Employment, Payroll, Professional & Business Services, Nonfarm, Waste Management & Remediation Services, Payroll | FG5: Employment, Payroll, Education & Health Services, Nonfarm, Payroll, Total | FH5: Employment, Payroll, Education & Health Services, Nonfarm, Educational Services, Payroll | FI5: Employment, Payroll, Education & Health Services, Nonfarm, Health Care & Social Assistance, Payroll | FJ5: Employment, Payroll, Education & Health Services, Nonfarm, Health Care, Payroll | FK5: Employment, Payroll, Education & Health Services, Nonfarm, Ambulatory Health Care Services, Payroll | FL5: Employment, Payroll, Education & Health Services, Nonfarm, Offices of Physicians, Payroll | FM5: BLS, CES National, All Employees, 65_621200 Offices of Dentists | FN5: BLS, CES National, All Employees, 65_621300 Offices of Other Health Practitioners | FO5: Employment, Payroll, Education & Health Services, Nonfarm, Outpatient Care Centers, Payroll | FP5: Employment, Payroll, Education & Health Services, Nonfarm, Medical & Diagnostic Laboratories, Payroll | FQ5: Employment, Payroll, Education & Health Services, Nonfarm, Home Health Care Services, Payroll | FR5: BLS, CES National, All Employees, 65_621900 Other Ambulatory Health Care Services | FS5: Employment, Payroll, Education & Health Services, Nonfarm, Hospitals, Payroll | FT5: Employment, Payroll, Education & Health Services, Nonfarm, Nursing & Residential Care Facilities, Payroll | FU5: Employment, Payroll, Education & Health Services, Nonfarm, Nursing Care Facilities, Payroll | FV5: BLS, CES National, All Employees, 65_623200 Residential Intellectual & Developmental Disability, Mental Health, & Substance Abuse Facilities | FW5: BLS, CES National, All Employees, 65_623300 Continuing Care Retirement Communities & Assisted Living Facilities for the Elderly | FX5: BLS, CES National, All Employees, 65_623900 Other Residential Care Facilities | FY5: Employment, Payroll, Education & Health Services, Nonfarm, Social Assistance, Payroll | FZ5: BLS, CES National, All Employees, 65_624100 Individual & Family Services | GA5: BLS, CES National, All Employees, 65_624200 Community Food & Housing, & Emergency & Other Relief Services | GB5: BLS, CES National, All Employees, 65_624300 Vocational Rehabilitation Services | GC5: Employment, Payroll, Education & Health Services, Nonfarm, Child Day Care Services, Payroll | GD5: Employment, Payroll, Leisure & Hospitality, Nonfarm, Payroll, Total | GE5: Employment, Payroll, Leisure & Hospitality, Nonfarm, Arts, Entertainment, & Recreation, Payroll | GF5: Employment, Payroll, Leisure & Hospitality, Nonfarm, Performing Arts & Spectator Sports, Payroll | GG5: Employment, Payroll, Leisure & Hospitality, Nonfarm, Museums, Historical Sites, Zoos, & Parks, Payroll | GH5: Employment, Payroll, Leisure & Hospitality, Nonfarm, Amusements, Gambling, & Recreation, Payroll | GI5: Employment, Payroll, Leisure & Hospitality, Nonfarm, Accommodation & Food Services, Payroll | GJ5: Employment, Payroll, Leisure & Hospitality, Nonfarm, Accommodation, Payroll | GK5: Employment, Payroll, Leisure & Hospitality, Nonfarm, Food Services & Drinking Places, Payroll | GL5: Employment, Payroll, Other Services, Nonfarm, Payroll, Total | GM5: Employment, Payroll, Other Services, Nonfarm, Repair & Maintenance, Payroll | GN5: Employment, Payroll, Other Services, Nonfarm, Personal & Laundry Services, Payroll | GO5: Employment, Payroll, Other Services, Nonfarm, Membership Associations & Organizations, Payroll | GP5: Employment, Payroll, Government, Nonfarm, Payroll, Total | GQ5: Employment, Payroll, Government, Nonfarm, Federal, Payroll | GR5: Employment, Payroll, Government, Nonfarm, Federal, Except U.S. Postal Service, Payroll | GS5: Employment, Payroll, Government, Nonfarm, U.S. Postal Service, Payroll | GT5: Employment, Payroll, Government, Nonfarm, State Government, Payroll | GU5: Employment, Payroll, Government, Nonfarm, State Government Education, Payroll | GV5: Employment, Payroll, Government, Nonfarm, State Government, Excluding Education, Payroll | GW5: Employment, Payroll, Government, Nonfarm, Local Government, Payroll | GX5: Employment, Payroll, Government, Nonfarm, Local Government Education, Payroll | GY5: Employment, Payroll, Government, Nonfarm, Local Government, Excluding Education, Payroll | GZ5: Productivity, Costs & Hours Worked, Hours Worked, Average Weekly, All Employees, Total Private, SA | HA5: Productivity, Costs & Hours Worked, Hours Worked, Average Weekly, All Employees, Goods-Producing, SA | HB5: Productivity, Costs & Hours Worked, Hours Worked, Average Weekly, All Employees, Mining & Logging, SA | HC5: Productivity, Costs & Hours Worked, Hours Worked, Average Weekly, All Employees, Construction, SA | HD5: Productivity, Costs & Hours Worked, Hours Worked, Average Weekly, All Employees, Manufacturing, SA | HE5: Productivity, Costs & Hours Worked, Hours Worked, Average Weekly, All Employees, Manufacturing, Durable Goods, SA | HF5: Productivity, Costs & Hours Worked, Hours Worked, Average Weekly, All Employees, Manufacturing, Non-Durable Goods, SA | HG5: Productivity, Costs & Hours Worked, Hours Worked, Average Weekly, All Employees, Service-Providing, SA | HH5: Productivity, Costs & Hours Worked, Hours Worked, Average Weekly, All Employees, Trade, Transportation & Utilities, SA | HI5: Productivity, Costs & Hours Worked, Hours Worked, Average Weekly, All Employees, Wholesale Trade, SA | HJ5: Productivity, Costs & Hours Worked, Hours Worked, Average Weekly, All Employees, Retail Trade, SA | HK5: Productivity, Costs & Hours Worked, Hours Worked, Average Weekly, All Employees, Transportation & Warehousing, SA | HL5: Productivity, Costs & Hours Worked, Hours Worked, Average Weekly, All Employees, Utilities, SA | HM5: Productivity, Costs & Hours Worked, Hours Worked, Average Weekly, All Employees, Information, SA | HN5: Productivity, Costs & Hours Worked, Hours Worked, Average Weekly, All Employees, Financial Activities, SA | HO5: Productivity, Costs & Hours Worked, Hours Worked, Average Weekly, All Employees, Professional & Business Services, SA | HP5: Productivity, Costs & Hours Worked, Hours Worked, Average Weekly, All Employees, Education & Health Services, SA | HQ5: Productivity, Costs & Hours Worked, Hours Worked, Average Weekly, All Employees, Leisure & Hospitality, SA | HR5: Productivity, Costs & Hours Worked, Hours Worked, Average Weekly, All Employees, Other Services, SA | HS5: Productivity, Costs & Hours Worked, Hours Worked, Overtime Hours, Average Weekly, All Employees, Manufacturing, Total, SA | HT5: Productivity, Costs & Hours Worked, Hours Worked, Overtime Hours, Average Weekly, All Employees, Manufacturing, Durable Goods, SA | HU5: Productivity, Costs & Hours Worked, Hours Worked, Overtime Hours, Average Weekly, All Employees, Manufacturing, Non-Durable Goods, SA | HV5: Income & Earnings, Earnings, Average Weekly Earnings, All Employees, Total Private, SA, USD | HW5: Income & Earnings, Earnings, Average Weekly Earnings, All Employees, Goods-Producing, SA, USD | HX5: Income & Earnings, Earnings, Average Weekly Earnings, All Employees, Mining & Logging, SA, USD | HY5: Income & Earnings, Earnings, Average Weekly Earnings, All Employees, Construction, SA, USD | HZ5: Income & Earnings, Earnings, Average Weekly Earnings, All Employees, Manufacturing, SA, USD | IA5: Income & Earnings, Earnings, Average Weekly Earnings, All Employees, Durable Goods, SA, USD | IB5: Income & Earnings, Earnings, Average Weekly Earnings, All Employees, Non-Durable Goods, SA, USD | IC5: Income & Earnings, Earnings, Average Weekly Earnings, All Employees, Private Service-Providing, SA, USD | ID5: Income & Earnings, Earnings, Average Weekly Earnings, All Employees, Trade, Transportation & Utilities, SA, USD | IE5: Income & Earnings, Earnings, Average Weekly Earnings, All Employees, Wholesale Trade, SA, USD | IF5: Income & Earnings, Earnings, Average Weekly Earnings, All Employees, Retail Trade, SA, USD | IG5: Income & Earnings, Earnings, Average Weekly Earnings, All Employees, Transportation & Warehousing, SA, USD | IH5: Income & Earnings, Earnings, Average Weekly Earnings, All Employees, Utilities, SA, USD | II5: Income & Earnings, Earnings, Average Weekly Earnings, All Employees, Information, SA, USD | IJ5: Income & Earnings, Earnings, Average Weekly Earnings, All Employees, Financial Activities, SA, USD | IK5: Income & Earnings, Earnings, Average Weekly Earnings, All Employees, Professional & Business Services, SA, USD | IL5: Income & Earnings, Earnings, Average Weekly Earnings, All Employees, Private Education & Health Services, SA, USD | IM5: Income & Earnings, Earnings, Average Weekly Earnings, All Employees, Leisure & Hospitality, SA, USD | IN5: Income & Earnings, Earnings, Average Weekly Earnings, All Employees, Other Services, SA, USD | IO5: Labor Force Statistics, Civilian Labor Force, Women & Men, 16 Years & Over, SA | IP5: Labor Force Statistics, Civilian Labor Force Participation Rate, Women & Men, 16 Years & Over, SA | IQ5: Employment, National, 16 Years & Over, SA | IR5: Labor Force Statistics, Employment to Population Ratio, Women & Men, 16 Years & Over, SA | IS5: Unemployment, National, 16 Years & Over, SA | IT5: Unemployment, National, 16 Years & Over, Rate, SA | IU5: Labor Force Statistics, Persons Not in Labor Force, Women & Men, 16 Years & Over, Total, SA | IV5: Labor Force Statistics, Persons Not in Labor Force, Women & Men, 16 Years & Over, Persons Who Currently Want a Job, SA | IW5: Labor Force Statistics, Civilian Labor Force, Men, 16 Years & Over, SA | IX5: Labor Force Statistics, Civilian Labor Force Participation Rate, Men, 16 Years & Over, SA | IY5: Employment, National, By Gender, Men, 16 Years & Over, SA | IZ5: Labor Force Statistics, Employment to Population Ratio, Men, 16 Years & Over, SA | JA5: Unemployment, National, By Age & Gender, Men, 16 Years & Over, SA | JB5: Unemployment, National, By Age & Gender, Men, 16 Years & Over, Rate, SA | JC5: Labor Force Statistics, Persons Not in Labor Force, Men, 16 Years & Over, SA | JD5: Labor Force Statistics, Civilian Labor Force, Men, 20 Years & Over, SA | JE5: Labor Force Statistics, Civilian Labor Force Participation Rate, Men, 20 Years & Over, SA | JF5: Employment, National, By Gender, Men, 20 Years & Over, SA | JG5: Labor Force Statistics, Employment to Population Ratio, Men, 20 Years & Over, SA | JH5: Unemployment, National, By Age & Gender, Men, 20 Years & Over, SA | JI5: Unemployment, National, By Age & Gender, Men, 20 Years & Over, Rate, SA | JJ5: Labor Force Statistics, Persons Not in Labor Force, Men, 20 Years & Over, SA | JK5: BLS, CPS, Labor Force Statistics, Multiple Jobholders, SA | JL5: BLS, CPS, Labor Force Statistics, Multiple Jobholders as a Percent of Employed, SA | JM5: Employment, Payroll, Nonfarm, Payroll, Total | JN5: Employment, Payroll, Nonfarm, Private, Payroll, Total | JO5: Employment, Payroll, Nonfarm, Goods-Producing, Payroll, Total | JP5: Employment, Payroll, Mining & Logging, Nonfarm, Payroll, Total | JQ5: Employment, Payroll, Mining & Logging, Nonfarm, Logging, Payroll | JR5: Employment, Payroll, Mining & Logging, Nonfarm, Mining, Payroll | JS5: Employment, Payroll, Mining & Logging, Nonfarm, Oil & Gas Extraction, Payroll | JT5: Employment, Payroll, Mining & Logging, Nonfarm, Mining, Except Oil & Gas, Payroll | JU5: Employment, Payroll, Mining & Logging, Nonfarm, Coal Mining, Payroll | JV5: BLS, CES National, All Employees, 10_212200 Metal Ore Mining | JW5: BLS, CES National, All Employees, 10_212300 Nonmetallic Mineral Mining & Quarrying | JX5: Employment, Payroll, Mining & Logging, Nonfarm, Support Activities for Mining, Payroll | JY5: Employment, Payroll, Construction, Nonfarm, Payroll, Total | JZ5: Employment, Payroll, Construction, Nonfarm, Construction of Buildings, Payroll | KA5: Employment, Payroll, Construction, Nonfarm, Residential Building, Payroll | KB5: Employment, Payroll, Construction, Nonfarm, Nonresidential Building, Payroll | KC5: Employment, Payroll, Construction, Nonfarm, Heavy & Civil Engineering Construction, Payroll | KD5: Employment, Payroll, Construction, Nonfarm, Specialty Trade Contractors, Payroll | KE5: Employment, Payroll, Construction, Nonfarm, Residential Specialty Trade Contractors, Payroll | KF5: Employment, Payroll, Construction, Nonfarm, Nonresidential Specialty Trade Contractors, Payroll | KG5: Employment, Payroll, Manufacturing, Total, Nonfarm, Payroll | KH5: Employment, Payroll, Manufacturing, Durable Goods, Nonfarm, Total, Payroll | KI5: Employment, Payroll, Manufacturing, Durable Goods, Nonfarm, Wood Products, Payroll | KJ5: Employment, Payroll, Manufacturing, Durable Goods, Nonfarm, Nonmetallic Mineral Products, Payroll | KK5: Employment, Payroll, Manufacturing, Durable Goods, Nonfarm, Primary Metals, Payroll | KL5: Employment, Payroll, Manufacturing, Durable Goods, Nonfarm, Fabricated Metal Products, Payroll | KM5: Employment, Payroll, Manufacturing, Durable Goods, Nonfarm, Machinery, Payroll | KN5: Employment, Payroll, Manufacturing, Durable Goods, Nonfarm, Computer & Electronic Products, Payroll | KO5: Employment, Payroll, Manufacturing, Durable Goods, Nonfarm, Computer & Peripheral Equipment, Payroll | KP5: Employment, Payroll, Manufacturing, Durable Goods, Nonfarm, Communications Equipment, Payroll | KQ5: Employment, Payroll, Manufacturing, Durable Goods, Nonfarm, Semiconductors & Electronic Components, Payroll | KR5: Employment, Payroll, Manufacturing, Durable Goods, Nonfarm, Electronic Instruments, Payroll | KS5: BLS, CES National, All Employees, 31_334600 Manufacturing & Reproducing Magnetic & Optical Media & Audio & Video Equipment Manufacturing | KT5: Employment, Payroll, Manufacturing, Durable Goods, Nonfarm, Electrical Equipment & Appliances, Payroll | KU5: Employment, Payroll, Manufacturing, Durable Goods, Nonfarm, Transportation Equipment, Payroll | KV5: Employment, Payroll, Manufacturing, Durable Goods, Nonfarm, Motor Vehicles & Parts, Payroll | KW5: Employment, Payroll, Manufacturing, Durable Goods, Nonfarm, Furniture & Related Products, Payroll | KX5: Employment, Payroll, Manufacturing, Durable Goods, Nonfarm, Miscellaneous Manufacturing, Payroll | KY5: Employment, Payroll, Manufacturing, Non-Durable Goods, Nonfarm, Total, Payroll | KZ5: Employment, Payroll, Manufacturing, Non-Durable Goods, Nonfarm, Food Manufacturing, Payroll | LA5: Employment, Payroll, Manufacturing, Non-Durable Goods, Nonfarm, Textile Mills, Payroll | LB5: Employment, Payroll, Manufacturing, Non-Durable Goods, Nonfarm, Textile Product Mills, Payroll | LC5: Employment, Payroll, Manufacturing, Non-Durable Goods, Nonfarm, Apparel, Payroll | LD5: Employment, Payroll, Manufacturing, Non-Durable Goods, Nonfarm, Paper & Paper Products, Payroll | LE5: Employment, Payroll, Manufacturing, Non-Durable Goods, Nonfarm, Printing & Related Support Activities, Payroll | LF5: Employment, Payroll, Manufacturing, Non-Durable Goods, Nonfarm, Petroleum & Coal Products, Payroll | LG5: Employment, Payroll, Manufacturing, Non-Durable Goods, Nonfarm, Chemicals, Payroll | LH5: Employment, Payroll, Manufacturing, Non-Durable Goods, Nonfarm, Plastics & Rubber Products, Payroll | LI5: BLS, CES National, All Employees, 32_329000 Beverage, Tobacco, & Leather & Allied Product Manufacturing | LJ5: Employment, Payroll, Nonfarm, Private Service-Providing, Payroll, Total | LK5: Employment, Payroll, Trade, Transportation & Utilities, Total, Nonfarm, Payroll | LL5: Employment, Payroll, Trade, Transportation & Utilities, Wholesale Trade, Nonfarm, Total, Payroll | LM5: Employment, Payroll, Trade, Transportation & Utilities, Wholesale Trade, Nonfarm, Durable Goods, Payroll | LN5: Employment, Payroll, Trade, Transportation & Utilities, Wholesale Trade, Nonfarm, Non-Durable Goods, Payroll | LO5: Employment, Payroll, Trade, Transportation & Utilities, Wholesale Trade, Nonfarm, Electronic Markets & Agents & Brokers, Payroll | LP5: Employment, Payroll, Trade, Transportation & Utilities, Retail Trade, Nonfarm, Total, Payroll | LQ5: Employment, Payroll, Trade, Transportation & Utilities, Retail Trade, Nonfarm, Motor Vehicle & Parts Dealers, Payroll | LR5: Employment, Payroll, Trade, Transportation & Utilities, Retail Trade, Nonfarm, Automobile Dealers, Payroll | LS5: BLS, CES National, All Employees, 42_441200 Other Motor Vehicle Dealers | LT5: BLS, CES National, All Employees, 42_441300 Automotive Parts, Accessories, & Tire Retailers | LU5: Employment, Payroll, Trade, Transportation & Utilities, Retail Trade, Nonfarm, Building Material & Garden Supply Stores, Payroll | LV5: Employment, Payroll, Trade, Transportation & Utilities, Retail Trade, Nonfarm, Food & Beverage Stores, Payroll | LW5: Employment, Payroll, Trade, Transportation & Utilities, Retail Trade, Nonfarm, Furniture, Home Furnishings, Electronics, & Appliance Retailers, Payroll | LX5: Employment, Payroll, Trade, Transportation & Utilities, Retail Trade, Nonfarm, Furniture & Home Furnishings Retailers, Payroll | LY5: Employment, Payroll, Trade, Transportation & Utilities, Retail Trade, Nonfarm, Electronics & Appliance Retailers, Payroll | LZ5: Employment, Payroll, Trade, Transportation & Utilities, Retail Trade, Nonfarm, General Merchandise Retailers, Payroll | MA5: Employment, Payroll, Trade, Transportation & Utilities, Retail Trade, Nonfarm, Department Stores, Payroll | MB5: Employment, Payroll, Trade, Transportation & Utilities, Retail Trade, Nonfarm, Warehouse Clubs, Supercenters, & Other General Merchandise Retailers, Payroll | MC5: Employment, Payroll, Trade, Transportation & Utilities, Retail Trade, Nonfarm, Health & Personal Care Retailers, Payroll | MD5: Employment, Payroll, Trade, Transportation & Utilities, Retail Trade, Nonfarm, Gasoline Stations & Fuel Dealers, Payroll | ME5: Employment, Payroll, Trade, Transportation & Utilities, Retail Trade, Nonfarm, Clothing, Clothing Accessories, Shoe, & Jewelry Retailers, Payroll | MF5: Employment, Payroll, Trade, Transportation & Utilities, Retail Trade, Nonfarm, Sporting Goods, Hobby, Musical Instrument, Book, & Miscellaneous Retailers, Payroll | MG5: Employment, Payroll, Trade, Transportation & Utilities, Transportation & Warehousing, Nonfarm, Total, Payroll | MH5: Employment, Payroll, Trade, Transportation & Utilities, Transportation & Warehousing, Nonfarm, Air Transportation, Payroll | MI5: Employment, Payroll, Trade, Transportation & Utilities, Transportation & Warehousing, Nonfarm, Rail Transportation, Payroll | MJ5: Employment, Payroll, Trade, Transportation & Utilities, Transportation & Warehousing, Nonfarm, Water Transportation, Payroll | MK5: Employment, Payroll, Trade, Transportation & Utilities, Transportation & Warehousing, Nonfarm, Truck Transportation, Payroll | ML5: Employment, Payroll, Trade, Transportation & Utilities, Transportation & Warehousing, Nonfarm, Transit & Ground Passenger Transportation, Payroll | MM5: Employment, Payroll, Trade, Transportation & Utilities, Transportation & Warehousing, Nonfarm, Pipeline Transportation, Payroll | MN5: Employment, Payroll, Trade, Transportation & Utilities, Transportation & Warehousing, Nonfarm, Scenic & Sightseeing Transportation, Payroll | MO5: Employment, Payroll, Trade, Transportation & Utilities, Transportation & Warehousing, Nonfarm, Support Activities for Transportation, Payroll | MP5: Employment, Payroll, Trade, Transportation & Utilities, Transportation & Warehousing, Nonfarm, Couriers & Messengers, Payroll | MQ5: Employment, Payroll, Trade, Transportation & Utilities, Transportation & Warehousing, Nonfarm, Warehousing & Storage, Payroll | MR5: Employment, Payroll, Trade, Transportation & Utilities, Utilities, Nonfarm, Total, Payroll | MS5: Employment, Payroll, Information, Nonfarm, Payroll, Total | MT5: Employment, Payroll, Information, Nonfarm, Motion Picture & Sound Recording Industries, Payroll | MU5: Employment, Payroll, Information, Nonfarm, Publishing Industries, Payroll | MV5: Employment, Payroll, Information, Nonfarm, Broadcasting, Payroll | MW5: Employment, Payroll, Information, Nonfarm, Telecommunications, Payroll | MX5: Employment, Payroll, Information, Nonfarm, Data Processing, Hosting & Related Services, Payroll | MY5: Employment, Payroll, Information, Nonfarm, Other Information Services, Payroll | MZ5: Employment, Payroll, Financial Activities, Nonfarm, Payroll, Total | NA5: Employment, Payroll, Financial Activities, Nonfarm, Finance & Insurance, Payroll | NB5: Employment, Payroll, Financial Activities, Nonfarm, Monetary Authorities - Central Bank, Payroll | NC5: Employment, Payroll, Financial Activities, Nonfarm, Credit Intermediation & Related Activities, Payroll | ND5: Employment, Payroll, Financial Activities, Nonfarm, Depository Credit Intermediation, Payroll | NE5: Employment, Payroll, Financial Activities, Nonfarm, Commercial Banking, Payroll | NF5: BLS, CES National, All Employees, 55_522200 Nondepository Credit Intermediation | NG5: Employment, Payroll, Financial Activities, Nonfarm, Activities Related to Credit Intermediation, Payroll | NH5: Employment, Payroll, Financial Activities, Nonfarm, Securities, Commodity Contracts, Investments, Payroll | NI5: Employment, Payroll, Financial Activities, Nonfarm, Insurance Carriers & Related Activities, Payroll | NJ5: Employment, Payroll, Financial Activities, Nonfarm, Real Estate & Rental & Leasing, Payroll | NK5: Employment, Payroll, Financial Activities, Nonfarm, Real Estate, Payroll | NL5: Employment, Payroll, Financial Activities, Nonfarm, Rental & Leasing Services, Payroll | NM5: Employment, Payroll, Financial Activities, Nonfarm, Lessors of Nonfinancial Intangible Assets, Payroll | NN5: Employment, Payroll, Professional & Business Services, Nonfarm, Payroll, Total | NO5: Employment, Payroll, Professional & Business Services, Nonfarm, Professional & Technical Services, Payroll | NP5: Employment, Payroll, Professional & Business Services, Nonfarm, Legal Services, Payroll | NQ5: Employment, Payroll, Professional & Business Services, Nonfarm, Accounting & Bookkeeping Services, Payroll | NR5: Employment, Payroll, Professional & Business Services, Nonfarm, Architectural & Engineering Services, Payroll | NS5: BLS, CES National, All Employees, 60_541400 Specialized Design Services | NT5: Employment, Payroll, Professional & Business Services, Nonfarm, Computer Systems Design & Related Services, Payroll | NU5: Employment, Payroll, Professional & Business Services, Nonfarm, Management & Technical Consulting Services, Payroll | NV5: BLS, CES National, All Employees, 60_541700 Scientific Research & Development Services | NW5: BLS, CES National, All Employees, 60_541800 Advertising, Public Relations, & Related Services | NX5: BLS, CES National, All Employees, 60_541900 Other Professional, Scientific, & Technical Services | NY5: Employment, Payroll, Professional & Business Services, Nonfarm, Management of Companies & Enterprises, Payroll | NZ5: Employment, Payroll, Professional & Business Services, Nonfarm, Administrative & Waste Services, Payroll | OA5: Employment, Payroll, Professional & Business Services, Nonfarm, Administrative & Support Services, Payroll | OB5: BLS, CES National, All Employees, 60_561100 Office Administrative Services | OC5: BLS, CES National, All Employees, 60_561200 Facilities Support Services | OD5: Employment, Payroll, Professional & Business Services, Nonfarm, Employment Services, Payroll | OE5: Employment, Payroll, Professional & Business Services, Nonfarm, Temporary Help Services, Payroll | OF5: Employment, Payroll, Professional & Business Services, Nonfarm, Business Support Services, Payroll | OG5: BLS, CES National, All Employees, 60_561500 Travel Arrangement & Reservation Services | OH5: BLS, CES National, All Employees, 60_561600 Investigation & Security Services | OI5: Employment, Payroll, Professional & Business Services, Nonfarm, Services to Buildings & Dwellings, Payroll | OJ5: BLS, CES National, All Employees, 60_561900 Other Support Services | OK5: Employment, Payroll, Professional & Business Services, Nonfarm, Waste Management & Remediation Services, Payroll | OL5: Employment, Payroll, Education & Health Services, Nonfarm, Payroll, Total | OM5: Employment, Payroll, Education & Health Services, Nonfarm, Educational Services, Payroll | ON5: Employment, Payroll, Education & Health Services, Nonfarm, Health Care & Social Assistance, Payroll | OO5: Employment, Payroll, Education & Health Services, Nonfarm, Health Care, Payroll | OP5: Employment, Payroll, Education & Health Services, Nonfarm, Ambulatory Health Care Services, Payroll | OQ5: Employment, Payroll, Education & Health Services, Nonfarm, Offices of Physicians, Payroll | OR5: BLS, CES National, All Employees, 65_621200 Offices of Dentists | OS5: BLS, CES National, All Employees, 65_621300 Offices of Other Health Practitioners | OT5: Employment, Payroll, Education & Health Services, Nonfarm, Outpatient Care Centers, Payroll | OU5: Employment, Payroll, Education & Health Services, Nonfarm, Medical & Diagnostic Laboratories, Payroll | OV5: Employment, Payroll, Education & Health Services, Nonfarm, Home Health Care Services, Payroll | OW5: BLS, CES National, All Employees, 65_621900 Other Ambulatory Health Care Services | OX5: Employment, Payroll, Education & Health Services, Nonfarm, Hospitals, Payroll | OY5: Employment, Payroll, Education & Health Services, Nonfarm, Nursing & Residential Care Facilities, Payroll | OZ5: Employment, Payroll, Education & Health Services, Nonfarm, Nursing Care Facilities, Payroll | PA5: BLS, CES National, All Employees, 65_623200 Residential Intellectual & Developmental Disability, Mental Health, & Substance Abuse Facilities | PB5: BLS, CES National, All Employees, 65_623300 Continuing Care Retirement Communities & Assisted Living Facilities for the Elderly | PC5: BLS, CES National, All Employees, 65_623900 Other Residential Care Facilities | PD5: Employment, Payroll, Education & Health Services, Nonfarm, Social Assistance, Payroll | PE5: BLS, CES National, All Employees, 65_624100 Individual & Family Services | PF5: BLS, CES National, All Employees, 65_624200 Community Food & Housing, & Emergency & Other Relief Services | PG5: BLS, CES National, All Employees, 65_624300 Vocational Rehabilitation Services | PH5: Employment, Payroll, Education & Health Services, Nonfarm, Child Day Care Services, Payroll | PI5: Employment, Payroll, Leisure & Hospitality, Nonfarm, Payroll, Total | PJ5: Employment, Payroll, Leisure & Hospitality, Nonfarm, Arts, Entertainment, & Recreation, Payroll | PK5: Employment, Payroll, Leisure & Hospitality, Nonfarm, Performing Arts & Spectator Sports, Payroll | PL5: Employment, Payroll, Leisure & Hospitality, Nonfarm, Museums, Historical Sites, Zoos, & Parks, Payroll | PM5: Employment, Payroll, Leisure & Hospitality, Nonfarm, Amusements, Gambling, & Recreation, Payroll | PN5: Employment, Payroll, Leisure & Hospitality, Nonfarm, Accommodation & Food Services, Payroll | PO5: Employment, Payroll, Leisure & Hospitality, Nonfarm, Accommodation, Payroll | PP5: Employment, Payroll, Leisure & Hospitality, Nonfarm, Food Services & Drinking Places, Payroll | PQ5: Employment, Payroll, Other Services, Nonfarm, Payroll, Total | PR5: Employment, Payroll, Other Services, Nonfarm, Repair & Maintenance, Payroll | PS5: Employment, Payroll, Other Services, Nonfarm, Personal & Laundry Services, Payroll | PT5: Employment, Payroll, Other Services, Nonfarm, Membership Associations & Organizations, Payroll | PU5: Employment, Payroll, Government, Nonfarm, Payroll, Total | PV5: Employment, Payroll, Government, Nonfarm, Federal, Payroll | PW5: Employment, Payroll, Government, Nonfarm, Federal, Except U.S. Postal Service, Payroll | PX5: Employment, Payroll, Government, Nonfarm, U.S. Postal Service, Payroll | PY5: Employment, Payroll, Government, Nonfarm, State Government, Payroll | PZ5: Employment, Payroll, Government, Nonfarm, State Government Education, Payroll | QA5: Employment, Payroll, Government, Nonfarm, State Government, Excluding Education, Payroll | QB5: Employment, Payroll, Government, Nonfarm, Local Government, Payroll | QC5: Employment, Payroll, Government, Nonfarm, Local Government Education, Payroll | QD5: Employment, Payroll, Government, Nonfarm, Local Government, Excluding Education, Payroll | QE5: Labor Market Dynamics, Underemployment, Special Unemployment Rate (U-6), SA | QF5: Employment, Payroll, Education & Health Services, Nonfarm, Social Assistance, Payroll, SA | QG5: Employment, Payroll, Nonfarm, Payroll, Total, SA | QH5: Employment, Payroll, Nonfarm, Private, Payroll, Total, SA | QI5: Employment, Payroll, Nonfarm, Goods-Producing, Payroll, Total, SA | QJ5: Employment, Payroll, Mining & Logging, Nonfarm, Payroll, Total, SA | QK5: Employment, Payroll, Mining & Logging, Nonfarm, Logging, Payroll, SA | QL5: Employment, Payroll, Mining & Logging, Nonfarm, Mining, Payroll, SA | QM5: Employment, Payroll, Mining & Logging, Nonfarm, Oil & Gas Extraction, Payroll, SA | QN5: Employment, Payroll, Mining & Logging, Nonfarm, Mining, Except Oil & Gas, Payroll, SA | QO5: Employment, Payroll, Mining & Logging, Nonfarm, Coal Mining, Payroll, SA | QP5: BLS, CES National, All Employees, 10_212200 Metal Ore Mining, SA | QQ5: BLS, CES National, All Employees, 10_212300 Nonmetallic Mineral Mining & Quarrying, SA | QR5: Employment, Payroll, Mining & Logging, Nonfarm, Support Activities for Mining, Payroll, SA | QS5: Employment, Payroll, Construction, Nonfarm, Payroll, Total, SA | QT5: Employment, Payroll, Construction, Nonfarm, Construction of Buildings, Payroll, SA | QU5: Employment, Payroll, Construction, Nonfarm, Residential Building, Payroll, SA | QV5: Employment, Payroll, Construction, Nonfarm, Nonresidential Building, Payroll, SA | QW5: Employment, Payroll, Construction, Nonfarm, Heavy & Civil Engineering Construction, Payroll, SA | QX5: Employment, Payroll, Construction, Nonfarm, Specialty Trade Contractors, Payroll, SA | QY5: Employment, Payroll, Construction, Nonfarm, Residential Specialty Trade Contractors, Payroll, SA | QZ5: Employment, Payroll, Construction, Nonfarm, Nonresidential Specialty Trade Contractors, Payroll, SA | RA5: Employment, Payroll, Manufacturing, Total, Nonfarm, Payroll, SA | RB5: Employment, Payroll, Manufacturing, Durable Goods, Nonfarm, Total, Payroll, SA | RC5: Employment, Payroll, Manufacturing, Durable Goods, Nonfarm, Wood Products, Payroll, SA | RD5: Employment, Payroll, Manufacturing, Durable Goods, Nonfarm, Nonmetallic Mineral Products, Payroll, SA | RE5: Employment, Payroll, Manufacturing, Durable Goods, Nonfarm, Primary Metals, Payroll, SA | RF5: Employment, Payroll, Manufacturing, Durable Goods, Nonfarm, Fabricated Metal Products, Payroll, SA | RG5: Employment, Payroll, Manufacturing, Durable Goods, Nonfarm, Machinery, Payroll, SA | RH5: Employment, Payroll, Manufacturing, Durable Goods, Nonfarm, Computer & Electronic Products, Payroll, SA | RI5: Employment, Payroll, Manufacturing, Durable Goods, Nonfarm, Computer & Peripheral Equipment, Payroll, SA | RJ5: Employment, Payroll, Manufacturing, Durable Goods, Nonfarm, Communications Equipment, Payroll, SA | RK5: Employment, Payroll, Manufacturing, Durable Goods, Nonfarm, Semiconductors & Electronic Components, Payroll, SA | RL5: Employment, Payroll, Manufacturing, Durable Goods, Nonfarm, Electronic Instruments, Payroll, SA | RM5: BLS, CES National, All Employees, 31_334600 Manufacturing & Reproducing Magnetic & Optical Media & Audio & Video Equipment Manufacturing, SA | RN5: Employment, Payroll, Manufacturing, Durable Goods, Nonfarm, Electrical Equipment & Appliances, Payroll, SA | RO5: Employment, Payroll, Manufacturing, Durable Goods, Nonfarm, Transportation Equipment, Payroll, SA | RP5: Employment, Payroll, Manufacturing, Durable Goods, Nonfarm, Motor Vehicles & Parts, Payroll, SA | RQ5: Employment, Payroll, Manufacturing, Durable Goods, Nonfarm, Furniture & Related Products, Payroll, SA | RR5: Employment, Payroll, Manufacturing, Durable Goods, Nonfarm, Miscellaneous Manufacturing, Payroll, SA | RS5: Employment, Payroll, Manufacturing, Non-Durable Goods, Nonfarm, Total, Payroll, SA | RT5: Employment, Payroll, Manufacturing, Non-Durable Goods, Nonfarm, Food Manufacturing, Payroll, SA | RU5: Employment, Payroll, Manufacturing, Non-Durable Goods, Nonfarm, Textile Mills, Payroll, SA | RV5: Employment, Payroll, Manufacturing, Non-Durable Goods, Nonfarm, Textile Product Mills, Payroll, SA | RW5: Employment, Payroll, Manufacturing, Non-Durable Goods, Nonfarm, Apparel, Payroll, SA | RX5: Employment, Payroll, Manufacturing, Non-Durable Goods, Nonfarm, Paper & Paper Products, Payroll, SA | RY5: Employment, Payroll, Manufacturing, Non-Durable Goods, Nonfarm, Printing & Related Support Activities, Payroll, SA | RZ5: Employment, Payroll, Manufacturing, Non-Durable Goods, Nonfarm, Petroleum & Coal Products, Payroll, SA | SA5: Employment, Payroll, Manufacturing, Non-Durable Goods, Nonfarm, Chemicals, Payroll, SA | SB5: Employment, Payroll, Manufacturing, Non-Durable Goods, Nonfarm, Plastics & Rubber Products, Payroll, SA | SC5: BLS, CES National, All Employees, 32_329000 Beverage, Tobacco, & Leather & Allied Product Manufacturing, SA | SD5: Employment, Payroll, Nonfarm, Private Service-Providing, Payroll, Total, SA | SE5: Employment, Payroll, Trade, Transportation & Utilities, Total, Nonfarm, Payroll, SA | SF5: Employment, Payroll, Trade, Transportation & Utilities, Wholesale Trade, Nonfarm, Total, Payroll, SA | SG5: Employment, Payroll, Trade, Transportation & Utilities, Wholesale Trade, Nonfarm, Durable Goods, Payroll, SA | SH5: Employment, Payroll, Trade, Transportation & Utilities, Wholesale Trade, Nonfarm, Non-Durable Goods, Payroll, SA | SI5: Employment, Payroll, Trade, Transportation & Utilities, Wholesale Trade, Nonfarm, Electronic Markets & Agents & Brokers, Payroll, SA | SJ5: Employment, Payroll, Trade, Transportation & Utilities, Retail Trade, Nonfarm, Total, Payroll, SA | SK5: Employment, Payroll, Trade, Transportation & Utilities, Retail Trade, Nonfarm, Motor Vehicle & Parts Dealers, Payroll, SA | SL5: Employment, Payroll, Trade, Transportation & Utilities, Retail Trade, Nonfarm, Automobile Dealers, Payroll, SA | SM5: BLS, CES National, All Employees, 42_441200 Other Motor Vehicle Dealers, SA | SN5: BLS, CES National, All Employees, 42_441300 Automotive Parts, Accessories, & Tire Retailers, SA | SO5: Employment, Payroll, Trade, Transportation & Utilities, Retail Trade, Nonfarm, Building Material & Garden Supply Stores, Payroll, SA | SP5: Employment, Payroll, Trade, Transportation & Utilities, Retail Trade, Nonfarm, Food & Beverage Stores, Payroll, SA | SQ5: Employment, Payroll, Trade, Transportation & Utilities, Retail Trade, Nonfarm, Furniture, Home Furnishings, Electronics, & Appliance Retailers, Payroll, SA | SR5: Employment, Payroll, Trade, Transportation & Utilities, Retail Trade, Nonfarm, Furniture & Home Furnishings Retailers, Payroll, SA | SS5: Employment, Payroll, Trade, Transportation & Utilities, Retail Trade, Nonfarm, Electronics & Appliance Retailers, Payroll, SA | ST5: Employment, Payroll, Trade, Transportation & Utilities, Retail Trade, Nonfarm, General Merchandise Retailers, Payroll, SA | SU5: Employment, Payroll, Trade, Transportation & Utilities, Retail Trade, Nonfarm, Department Stores, Payroll, SA | SV5: Employment, Payroll, Trade, Transportation & Utilities, Retail Trade, Nonfarm, Warehouse Clubs, Supercenters, & Other General Merchandise Retailers, Payroll, SA | SW5: Employment, Payroll, Trade, Transportation & Utilities, Retail Trade, Nonfarm, Health & Personal Care Retailers, Payroll, SA | SX5: Employment, Payroll, Trade, Transportation & Utilities, Retail Trade, Nonfarm, Gasoline Stations & Fuel Dealers, Payroll, SA | SY5: Employment, Payroll, Trade, Transportation & Utilities, Retail Trade, Nonfarm, Clothing, Clothing Accessories, Shoe, & Jewelry Retailers, Payroll, SA | SZ5: Employment, Payroll, Trade, Transportation & Utilities, Retail Trade, Nonfarm, Sporting Goods, Hobby, Musical Instrument, Book, & Miscellaneous Retailers, Payroll, SA | TA5: Employment, Payroll, Trade, Transportation & Utilities, Transportation & Warehousing, Nonfarm, Total, Payroll, SA | TB5: Employment, Payroll, Trade, Transportation & Utilities, Transportation & Warehousing, Nonfarm, Air Transportation, Payroll, SA | TC5: Employment, Payroll, Trade, Transportation & Utilities, Transportation & Warehousing, Nonfarm, Rail Transportation, Payroll, SA | TD5: Employment, Payroll, Trade, Transportation & Utilities, Transportation & Warehousing, Nonfarm, Water Transportation, Payroll, SA | TE5: Employment, Payroll, Trade, Transportation & Utilities, Transportation & Warehousing, Nonfarm, Truck Transportation, Payroll, SA | TF5: Employment, Payroll, Trade, Transportation & Utilities, Transportation & Warehousing, Nonfarm, Transit & Ground Passenger Transportation, Payroll, SA | TG5: Employment, Payroll, Trade, Transportation & Utilities, Transportation & Warehousing, Nonfarm, Pipeline Transportation, Payroll, SA | TH5: Employment, Payroll, Trade, Transportation & Utilities, Transportation & Warehousing, Nonfarm, Scenic & Sightseeing Transportation, Payroll, SA | TI5: Employment, Payroll, Trade, Transportation & Utilities, Transportation & Warehousing, Nonfarm, Support Activities for Transportation, Payroll, SA | TJ5: Employment, Payroll, Trade, Transportation & Utilities, Transportation & Warehousing, Nonfarm, Couriers & Messengers, Payroll, SA | TK5: Employment, Payroll, Trade, Transportation & Utilities, Transportation & Warehousing, Nonfarm, Warehousing & Storage, Payroll, SA | TL5: Employment, Payroll, Trade, Transportation & Utilities, Utilities, Nonfarm, Total, Payroll, SA | TM5: Employment, Payroll, Information, Nonfarm, Payroll, Total, SA | TN5: Employment, Payroll, Information, Nonfarm, Motion Picture & Sound Recording Industries, Payroll, SA | TO5: Employment, Payroll, Information, Nonfarm, Publishing Industries, Payroll, SA | TP5: Employment, Payroll, Information, Nonfarm, Broadcasting, Payroll, SA | TQ5: Employment, Payroll, Information, Nonfarm, Telecommunications, Payroll, SA | TR5: Employment, Payroll, Information, Nonfarm, Data Processing, Hosting & Related Services, Payroll, SA | TS5: Employment, Payroll, Information, Nonfarm, Other Information Services, Payroll, SA | TT5: Employment, Payroll, Financial Activities, Nonfarm, Payroll, Total, SA | TU5: Employment, Payroll, Financial Activities, Nonfarm, Finance & Insurance, Payroll, SA | TV5: Employment, Payroll, Financial Activities, Nonfarm, Monetary Authorities - Central Bank, Payroll, SA | TW5: Employment, Payroll, Financial Activities, Nonfarm, Credit Intermediation & Related Activities, Payroll, SA | TX5: Employment, Payroll, Financial Activities, Nonfarm, Depository Credit Intermediation, Payroll, SA | TY5: Employment, Payroll, Financial Activities, Nonfarm, Commercial Banking, Payroll, SA | TZ5: BLS, CES National, All Employees, 55_522200 Nondepository Credit Intermediation, SA | UA5: Employment, Payroll, Financial Activities, Nonfarm, Activities Related to Credit Intermediation, Payroll, SA | UB5: Employment, Payroll, Financial Activities, Nonfarm, Securities, Commodity Contracts, Investments, Payroll, SA | UC5: Employment, Payroll, Financial Activities, Nonfarm, Insurance Carriers & Related Activities, Payroll, SA | UD5: Employment, Payroll, Financial Activities, Nonfarm, Real Estate & Rental & Leasing, Payroll, SA | UE5: Employment, Payroll, Financial Activities, Nonfarm, Real Estate, Payroll, SA | UF5: Employment, Payroll, Financial Activities, Nonfarm, Rental & Leasing Services, Payroll, SA | UG5: Employment, Payroll, Financial Activities, Nonfarm, Lessors of Nonfinancial Intangible Assets, Payroll, SA | UH5: Employment, Payroll, Professional & Business Services, Nonfarm, Payroll, Total, SA | UI5: Employment, Payroll, Professional & Business Services, Nonfarm, Professional & Technical Services, Payroll, SA | UJ5: Employment, Payroll, Professional & Business Services, Nonfarm, Legal Services, Payroll, SA | UK5: Employment, Payroll, Professional & Business Services, Nonfarm, Accounting & Bookkeeping Services, Payroll, SA | UL5: Employment, Payroll, Professional & Business Services, Nonfarm, Architectural & Engineering Services, Payroll, SA | UM5: BLS, CES National, All Employees, 60_541400 Specialized Design Services, SA | UN5: Employment, Payroll, Professional & Business Services, Nonfarm, Computer Systems Design & Related Services, Payroll, SA | UO5: Employment, Payroll, Professional & Business Services, Nonfarm, Management & Technical Consulting Services, Payroll, SA | UP5: BLS, CES National, All Employees, 60_541700 Scientific Research & Development Services, SA | UQ5: BLS, CES National, All Employees, 60_541800 Advertising, Public Relations, & Related Services, SA | UR5: BLS, CES National, All Employees, 60_541900 Other Professional, Scientific, & Technical Services, SA | US5: Employment, Payroll, Professional & Business Services, Nonfarm, Management of Companies & Enterprises, Payroll, SA | UT5: Employment, Payroll, Professional & Business Services, Nonfarm, Administrative & Waste Services, Payroll, SA | UU5: Employment, Payroll, Professional & Business Services, Nonfarm, Administrative & Support Services, Payroll, SA | UV5: BLS, CES National, All Employees, 60_561100 Office Administrative Services, SA | UW5: BLS, CES National, All Employees, 60_561200 Facilities Support Services, SA | UX5: Employment, Payroll, Professional & Business Services, Nonfarm, Employment Services, Payroll, SA | UY5: Employment, Payroll, Professional & Business Services, Nonfarm, Temporary Help Services, Payroll, SA | UZ5: Employment, Payroll, Professional & Business Services, Nonfarm, Business Support Services, Payroll, SA | VA5: BLS, CES National, All Employees, 60_561500 Travel Arrangement & Reservation Services, SA | VB5: BLS, CES National, All Employees, 60_561600 Investigation & Security Services, SA | VC5: Employment, Payroll, Professional & Business Services, Nonfarm, Services to Buildings & Dwellings, Payroll, SA | VD5: BLS, CES National, All Employees, 60_561900 Other Support Services, SA | VE5: Employment, Payroll, Professional & Business Services, Nonfarm, Waste Management & Remediation Services, Payroll, SA | VF5: Employment, Payroll, Education & Health Services, Nonfarm, Payroll, Total, SA | VG5: Employment, Payroll, Education & Health Services, Nonfarm, Educational Services, Payroll, SA | VH5: Employment, Payroll, Education & Health Services, Nonfarm, Health Care & Social Assistance, Payroll, SA | VI5: Employment, Payroll, Education & Health Services, Nonfarm, Health Care, Payroll, SA | VJ5: Employment, Payroll, Education & Health Services, Nonfarm, Ambulatory Health Care Services, Payroll, SA | VK5: Employment, Payroll, Education & Health Services, Nonfarm, Offices of Physicians, Payroll, SA | VL5: BLS, CES National, All Employees, 65_621200 Offices of Dentists, SA | VM5: BLS, CES National, All Employees, 65_621300 Offices of Other Health Practitioners, SA | VN5: Employment, Payroll, Education & Health Services, Nonfarm, Outpatient Care Centers, Payroll, SA | VO5: Employment, Payroll, Education & Health Services, Nonfarm, Medical & Diagnostic Laboratories, Payroll, SA | VP5: Employment, Payroll, Education & Health Services, Nonfarm, Home Health Care Services, Payroll, SA | VQ5: BLS, CES National, All Employees, 65_621900 Other Ambulatory Health Care Services, SA | VR5: Employment, Payroll, Education & Health Services, Nonfarm, Hospitals, Payroll, SA | VS5: Employment, Payroll, Education & Health Services, Nonfarm, Nursing & Residential Care Facilities, Payroll, SA | VT5: Employment, Payroll, Education & Health Services, Nonfarm, Nursing Care Facilities, Payroll, SA | VU5: BLS, CES National, All Employees, 65_623200 Residential Intellectual & Developmental Disability, Mental Health, & Substance Abuse Facilities, SA | VV5: BLS, CES National, All Employees, 65_623300 Continuing Care Retirement Communities & Assisted Living Facilities for the Elderly, SA | VW5: BLS, CES National, All Employees, 65_623900 Other Residential Care Facilities, SA | VX5: BLS, CES National, All Employees, 65_624100 Individual & Family Services, SA | VY5: BLS, CES National, All Employees, 65_624200 Community Food & Housing, & Emergency & Other Relief Services, SA | VZ5: BLS, CES National, All Employees, 65_624300 Vocational Rehabilitation Services, SA | WA5: Employment, Payroll, Education & Health Services, Nonfarm, Child Day Care Services, Payroll, SA | WB5: Employment, Payroll, Leisure & Hospitality, Nonfarm, Payroll, Total, SA | WC5: Employment, Payroll, Leisure & Hospitality, Nonfarm, Arts, Entertainment, & Recreation, Payroll, SA | WD5: Employment, Payroll, Leisure & Hospitality, Nonfarm, Performing Arts & Spectator Sports, Payroll, SA | WE5: Employment, Payroll, Leisure & Hospitality, Nonfarm, Museums, Historical Sites, Zoos, & Parks, Payroll, SA | WF5: Employment, Payroll, Leisure & Hospitality, Nonfarm, Amusements, Gambling, & Recreation, Payroll, SA | WG5: Employment, Payroll, Leisure & Hospitality, Nonfarm, Accommodation & Food Services, Payroll, SA | WH5: Employment, Payroll, Leisure & Hospitality, Nonfarm, Accommodation, Payroll, SA | WI5: Employment, Payroll, Leisure & Hospitality, Nonfarm, Food Services & Drinking Places, Payroll, SA | WJ5: Employment, Payroll, Other Services, Nonfarm, Payroll, Total, SA | WK5: Employment, Payroll, Other Services, Nonfarm, Repair & Maintenance, Payroll, SA | WL5: Employment, Payroll, Other Services, Nonfarm, Personal & Laundry Services, Payroll, SA | WM5: Employment, Payroll, Other Services, Nonfarm, Membership Associations & Organizations, Payroll, SA | WN5: Employment, Payroll, Government, Nonfarm, Payroll, Total, SA | WO5: Employment, Payroll, Government, Nonfarm, Federal, Payroll, SA | WP5: Employment, Payroll, Government, Nonfarm, Federal, Except U.S. Postal Service, Payroll, SA | WQ5: Employment, Payroll, Government, Nonfarm, U.S. Postal Service, Payroll, SA | WR5: Employment, Payroll, Government, Nonfarm, State Government, Payroll, SA | WS5: Employment, Payroll, Government, Nonfarm, State Government Education, Payroll, SA | WT5: Employment, Payroll, Government, Nonfarm, State Government, Excluding Education, Payroll, SA | WU5: Employment, Payroll, Government, Nonfarm, Local Government, Payroll, SA | WV5: Employment, Payroll, Government, Nonfarm, Local Government Education, Payroll, SA | WW5: Employment, Payroll, Government, Nonfarm, Local Government, Excluding Education, Payroll, SA
C6: 14246 | AH6: 25338000 | AI6: 29296000 | AJ6: 10806000 | AK6: 885000 | AT6: 981000 | BB6: 8940000 | BC6: 4345000 | BT6: 4595000 | CE6: 14532000 | CF6: 6470000 | CG6: 1474800 | CK6: 3009000 | DN6: 1088000 | DU6: 1363000 | EI6: 1910000 | FG6: 1359000 | GD6: 1807000 | GL6: 535000 | GP6: 3958000 | GQ6: 900000 | GR6: 584900 | GS6: 315200 | JM6: 29296000 | JN6: 25338000 | JO6: 10806000 | JP6: 885000 | JY6: 981000 | KG6: 8940000 | KH6: 4345000 | KY6: 4595000 | LJ6: 14532000 | LK6: 6470000 | LL6: 1474800 | LP6: 3009000 | MS6: 1088000 | MZ6: 1363000 | NN6: 1910000 | OL6: 1359000 | PI6: 1807000 | PQ6: 535000 | PU6: 3958000 | PV6: 900000 | PW6: 584900 | PX6: 315200 | QG6: 29923000 | QH6: 25935000 | QI6: 11098000 | QJ6: 882000 | QS6: 1139000 | RA6: 9077000 | RB6: 4380000 | RS6: 4697000 | SD6: 14837000 | SE6: 6627000 | SF6: 1472300 | SJ6: 3107800 | TM6: 1112000 | TT6: 1371000 | UH6: 1943000 | VF6: 1381000 | WB6: 1860000 | WJ6: 543000 | WN6: 3988000 | WO6: 912000 | WP6: 593800 | WQ6: 315900
C7: 14277 | AH7: 25447000 | AI7: 29394000 | AJ7: 10917000 | AK7: 882000 | AT7: 970000 | BB7: 9065000 | BC7: 4400000 | BT7: 4665000 | CE7: 14530000 | CF7: 6462000 | CG7: 1470600 | CK7: 3002100 | DN7: 1095000 | DU7: 1360000 | EI7: 1915000 | FG7: 1359000 | GD7: 1804000 | GL7: 535000 | GP7: 3947000 | GQ7: 909000 | GR7: 596300 | GS7: 313100 | JM7: 29394000 | JN7: 25447000 | JO7: 10917000 | JP7: 882000 | JY7: 970000 | KG7: 9065000 | KH7: 4400000 | KY7: 4665000 | LJ7: 14530000 | LK7: 6462000 | LL7: 1470600 | LP7: 3002100 | MS7: 1095000 | MZ7: 1360000 | NN7: 1915000 | OL7: 1359000 | PI7: 1804000 | PQ7: 535000 | PU7: 3947000 | PV7: 909000 | PW7: 596300 | PX7: 313100 | QG7: 30100000 | QH7: 26099000 | QI7: 11221000 | QJ7: 884000 | QS7: 1162000 | RA7: 9175000 | RB7: 4454000 | RS7: 4721000 | SD7: 14878000 | SE7: 6643000 | SF7: 1473300 | SJ7: 3121800 | TM7: 1118000 | TT7: 1372000 | UH7: 1950000 | VF7: 1384000 | WB7: 1867000 | WJ7: 544000 | WN7: 4001000 | WO7: 925000 | WP7: 606300 | WQ7: 315300
C8: 14305 | AH8: 25833000 | AI8: 29804000 | AJ8: 11150000 | AK8: 883000 | AT8: 1091000 | BB8: 9176000 | BC8: 4462000 | BT8: 4714000 | CE8: 14683000 | CF8: 6521000 | CG8: 1463200 | CK8: 3051800 | DN8: 1106000 | DU8: 1372000 | EI8: 1936000 | FG8: 1373000 | GD8: 1834000 | GL8: 541000 | GP8: 3971000 | GQ8: 913000 | GR8: 601500 | GS8: 311100 | JM8: 29804000 | JN8: 25833000 | JO8: 11150000 | JP8: 883000 | JY8: 1091000 | KG8: 9176000 | KH8: 4462000 | KY8: 4714000 | LJ8: 14683000 | LK8: 6521000 | LL8: 1463200 | LP8: 3051800 | MS8: 1106000 | MZ8: 1372000 | NN8: 1936000 | OL8: 1373000 | PI8: 1834000 | PQ8: 541000 | PU8: 3971000 | PV8: 913000 | PW8: 601500 | PX8: 311100 | QG8: 30280000 | QH8: 26278000 | QI8: 11383000 | QJ8: 883000 | QS8: 1225000 | RA8: 9275000 | RB8: 4518000 | RS8: 4757000 | SD8: 14895000 | SE8: 6625000 | SF8: 1463400 | SJ8: 3139700 | TM8: 1126000 | TT8: 1376000 | UH8: 1958000 | VF8: 1387000 | WB8: 1877000 | WJ8: 546000 | WN8: 4002000 | WO8: 929000 | WP8: 610200 | WQ8: 314000
C9: 14336 | AH9: 25801000 | AI9: 29786000 | AJ9: 10978000 | AK9: 614000 | AT9: 1181000 | BB9: 9183000 | BC9: 4502000 | BT9: 4681000 | CE9: 14823000 | CF9: 6588000 | CG9: 1461700 | CK9: 3097800 | DN9: 1114000 | DU9: 1374000 | EI9: 1947000 | FG9: 1390000 | GD9: 1863000 | GL9: 547000 | GP9: 3985000 | GQ9: 919000 | GR9: 605800 | GS9: 313100 | JM9: 29786000 | JN9: 25801000 | JO9: 10978000 | JP9: 614000 | JY9: 1181000 | KG9: 9183000 | KH9: 4502000 | KY9: 4681000 | LJ9: 14823000 | LK9: 6588000 | LL9: 1461700 | LP9: 3097800 | MS9: 1114000 | MZ9: 1374000 | NN9: 1947000 | OL9: 1390000 | PI9: 1863000 | PQ9: 547000 | PU9: 3985000 | PV9: 919000 | PW9: 605800 | PX9: 313100 | QG9: 30094000 | QH9: 26092000 | QI9: 11182000 | QJ9: 624000 | QS9: 1249000 | RA9: 9309000 | RB9: 4550000 | RS9: 4759000 | SD9: 14910000 | SE9: 6634000 | SF9: 1473500 | SJ9: 3154800 | TM9: 1127000 | TT9: 1370000 | UH9: 1957000 | VF9: 1389000 | WB9: 1887000 | WJ9: 546000 | WN9: 4002000 | WO9: 933000 | WP9: 611500 | WQ9: 316800
C10: 14366 | AH10: 26113000 | AI10: 30145000 | AJ10: 11143000 | AK10: 719000 | AT10: 1286000 | BB10: 9138000 | BC10: 4493000 | BT10: 4645000 | CE10: 14970000 | CF10: 6627000 | CG10: 1460000 | CK10: 3123000 | DN10: 1119000 | DU10: 1393000 | EI10: 1975000 | FG10: 1417000 | GD10: 1882000 | GL10: 557000 | GP10: 4032000 | GQ10: 937000 | GR10: 624600 | GS10: 312100 | JM10: 30145000 | JN10: 26113000 | JO10: 11143000 | JP10: 719000 | JY10: 1286000 | KG10: 9138000 | KH10: 4493000 | KY10: 4645000 | LJ10: 14970000 | LK10: 6627000 | LL10: 1460000 | LP10: 3123000 | MS10: 1119000 | MZ10: 1393000 | NN10: 1975000 | OL10: 1417000 | PI10: 1882000 | PQ10: 557000 | PU10: 4032000 | PV10: 937000 | PW10: 624600 | PX10: 312100 | QG10: 30299000 | QH10: 26293000 | QI10: 11298000 | QJ10: 737000 | QS10: 1262000 | RA10: 9299000 | RB10: 4544000 | RS10: 4755000 | SD10: 14995000 | SE10: 6686000 | SF10: 1480600 | SJ10: 3151700 | TM10: 1125000 | TT10: 1379000 | UH10: 1968000 | VF10: 1399000 | WB10: 1888000 | WJ10: 550000 | WN10: 4006000 | WO10: 941000 | WP10: 623700 | WQ10: 315300
C11: 14397 | AH11: 26485000 | AI11: 30520000 | AJ11: 11362000 | AK11: 852000 | AT11: 1328000 | BB11: 9182000 | BC11: 4523000 | BT11: 4659000 | CE11: 15123000 | CF11: 6701000 | CG11: 1473600 | CK11: 3140700 | DN11: 1136000 | DU11: 1399000 | EI11: 1999000 | FG11: 1431000 | GD11: 1894000 | GL11: 563000 | GP11: 4035000 | GQ11: 961000 | GR11: 644700 | GS11: 316200 | JM11: 30520000 | JN11: 26485000 | JO11: 11362000 | JP11: 852000 | JY11: 1328000 | KG11: 9182000 | KH11: 4523000 | KY11: 4659000 | LJ11: 15123000 | LK11: 6701000 | LL11: 1473600 | LP11: 3140700 | MS11: 1136000 | MZ11: 1399000 | NN11: 1999000 | OL11: 1431000 | PI11: 1894000 | PQ11: 563000 | PU11: 4035000 | PV11: 961000 | PW11: 644700 | PX11: 316200 | QG11: 30502000 | QH11: 26499000 | QI11: 11447000 | QJ11: 868000 | QS11: 1264000 | RA11: 9315000 | RB11: 4561000 | RS11: 4754000 | SD11: 15052000 | SE11: 6706000 | SF11: 1484500 | SJ11: 3152900 | TM11: 1131000 | TT11: 1381000 | UH11: 1980000 | VF11: 1406000 | WB11: 1895000 | WJ11: 553000 | WN11: 4003000 | WO11: 948000 | WP11: 628500 | WQ11: 317200
C12: 14427 | AH12: 26481000 | AI12: 30472000 | AJ12: 11409000 | AK12: 847000 | AT12: 1341000 | BB12: 9221000 | BC12: 4478000 | BT12: 4743000 | CE12: 15072000 | CF12: 6663000 | CG12: 1471800 | CK12: 3100000 | DN12: 1139000 | DU12: 1402000 | EI12: 2000000 | FG12: 1432000 | GD12: 1873000 | GL12: 563000 | GP12: 3991000 | GQ12: 962000 | GR12: 641700 | GS12: 320200 | JM12: 30472000 | JN12: 26481000 | JO12: 11409000 | JP12: 847000 | JY12: 1341000 | KG12: 9221000 | KH12: 4478000 | KY12: 4743000 | LJ12: 15072000 | LK12: 6663000 | LL12: 1471800 | LP12: 3100000 | MS12: 1139000 | MZ12: 1402000 | NN12: 2000000 | OL12: 1432000 | PI12: 1873000 | PQ12: 563000 | PU12: 3991000 | PV12: 962000 | PW12: 641700 | PX12: 320200 | QG12: 30419000 | QH12: 26400000 | QI12: 11304000 | QJ12: 852000 | QS12: 1221000 | RA12: 9231000 | RB12: 4470000 | RS12: 4761000 | SD12: 15096000 | SE12: 6731000 | SF12: 1491200 | SJ12: 3165800 | TM12: 1131000 | TT12: 1386000 | UH12: 1985000 | VF12: 1411000 | WB12: 1897000 | WJ12: 555000 | WN12: 4019000 | WO12: 954000 | WP12: 631600 | WQ12: 319500
C13: 14458 | AH13: 26848000 | AI13: 30870000 | AJ13: 11729000 | AK13: 864000 | AT13: 1368000 | BB13: 9497000 | BC13: 4546000 | BT13: 4951000 | CE13: 15119000 | CF13: 6680000 | CG13: 1491300 | CK13: 3091900 | DN13: 1152000 | DU13: 1406000 | EI13: 2015000 | FG13: 1434000 | GD13: 1868000 | GL13: 564000 | GP13: 4022000 | GQ13: 968000 | GR13: 648000 | GS13: 320200 | JM13: 30870000 | JN13: 26848000 | JO13: 11729000 | JP13: 864000 | JY13: 1368000 | KG13: 9497000 | KH13: 4546000 | KY13: 4951000 | LJ13: 15119000 | LK13: 6680000 | LL13: 1491300 | LP13: 3091900 | MS13: 1152000 | MZ13: 1406000 | NN13: 2015000 | OL13: 1434000 | PI13: 1868000 | PQ13: 564000 | PU13: 4022000 | PV13: 968000 | PW13: 648000 | PX13: 320200 | QG13: 30663000 | QH13: 26617000 | QI13: 11495000 | QJ13: 859000 | QS13: 1236000 | RA13: 9400000 | RB13: 4578000 | RS13: 4822000 | SD13: 15122000 | SE13: 6740000 | SF13: 1493000 | SJ13: 3165900 | TM13: 1134000 | TT13: 1392000 | UH13: 1990000 | VF13: 1412000 | WB13: 1899000 | WJ13: 555000 | WN13: 4046000 | WO13: 962000 | WP13: 638800 | WQ13: 319800
C14: 14489 | AH14: 27468000 | AI14: 31608000 | AJ14: 12067000 | AK14: 894000 | AT14: 1342000 | BB14: 9831000 | BC14: 4787000 | BT14: 5044000 | CE14: 15401000 | CF14: 6844000 | CG14: 1520400 | CK14: 3191400 | DN14: 1178000 | DU14: 1406000 | EI14: 2043000 | FG14: 1443000 | GD14: 1920000 | GL14: 567000 | GP14: 4140000 | GQ14: 972000 | GR14: 651200 | GS14: 321200 | JM14: 31608000 | JN14: 27468000 | JO14: 12067000 | JP14: 894000 | JY14: 1342000 | KG14: 9831000 | KH14: 4787000 | KY14: 5044000 | LJ14: 15401000 | LK14: 6844000 | LL14: 1520400 | LP14: 3191400 | MS14: 1178000 | MZ14: 1406000 | NN14: 2043000 | OL14: 1443000 | PI14: 1920000 | PQ14: 567000 | PU14: 4140000 | PV14: 972000 | PW14: 651200 | PX14: 321200 | QG14: 31031000 | QH14: 26955000 | QI14: 11692000 | QJ14: 885000 | QS14: 1203000 | RA14: 9604000 | RB14: 4740000 | RS14: 4864000 | SD14: 15263000 | SE14: 6793000 | SF14: 1518900 | SJ14: 3185000 | TM14: 1152000 | TT14: 1406000 | UH14: 2010000 | VF14: 1424000 | WB14: 1918000 | WJ14: 560000 | WN14: 4076000 | WO14: 970000 | WP14: 644000 | WQ14: 320500
C15: 14519 | AH15: 27830000 | AI15: 31975000 | AJ15: 12330000 | AK15: 941000 | AT15: 1291000 | BB15: 10098000 | BC15: 5048000 | BT15: 5050000 | CE15: 15500000 | CF15: 6965000 | CG15: 1553600 | CK15: 3241900 | DN15: 1200000 | DU15: 1390000 | EI15: 2037000 | FG15: 1414000 | GD15: 1938000 | GL15: 556000 | GP15: 4145000 | GQ15: 968000 | GR15: 651000 | GS15: 317200 | JM15: 31975000 | JN15: 27830000 | JO15: 12330000 | JP15: 941000 | JY15: 1291000 | KG15: 10098000 | KH15: 5048000 | KY15: 5050000 | LJ15: 15500000 | LK15: 6965000 | LL15: 1553600 | LP15: 3241900 | MS15: 1200000 | MZ15: 1390000 | NN15: 2037000 | OL15: 1414000 | PI15: 1938000 | PQ15: 556000 | PU15: 4145000 | PV15: 968000 | PW15: 651000 | PX15: 317200 | QG15: 31411000 | QH15: 27322000 | QI15: 11984000 | QJ15: 925000 | QS15: 1186000 | RA15: 9873000 | RB15: 4945000 | RS15: 4928000 | SD15: 15338000 | SE15: 6858000 | SF15: 1540500 | SJ15: 3186100 | TM15: 1179000 | TT15: 1398000 | UH15: 2021000 | VF15: 1415000 | WB15: 1910000 | WJ15: 557000 | WN15: 4089000 | WO15: 968000 | WP15: 644600 | WQ15: 320700
C16: 14550 | AH16: 27740000 | AI16: 31837000 | AJ16: 12231000 | AK16: 952000 | AT16: 1218000 | BB16: 10061000 | BC16: 5113000 | BT16: 4948000 | CE16: 15509000 | CF16: 6994000 | CG16: 1553700 | CK16: 3296200 | DN16: 1189000 | DU16: 1383000 | EI16: 2024000 | FG16: 1403000 | GD16: 1964000 | GL16: 552000 | GP16: 4097000 | GQ16: 966000 | GR16: 647900 | GS16: 318200 | JM16: 31837000 | JN16: 27740000 | JO16: 12231000 | JP16: 952000 | JY16: 1218000 | KG16: 10061000 | KH16: 5113000 | KY16: 4948000 | LJ16: 15509000 | LK16: 6994000 | LL16: 1553700 | LP16: 3296200 | MS16: 1189000 | MZ16: 1383000 | NN16: 2024000 | OL16: 1403000 | PI16: 1964000 | PQ16: 552000 | PU16: 4097000 | PV16: 966000 | PW16: 647900 | PX16: 318200 | QG16: 31470000 | QH16: 27361000 | QI16: 12007000 | QJ16: 939000 | QS16: 1172000 | RA16: 9896000 | RB16: 5007000 | RS16: 4889000 | SD16: 15354000 | SE16: 6855000 | SF16: 1531700 | SJ16: 3192000 | TM16: 1179000 | TT16: 1400000 | UH16: 2027000 | VF16: 1421000 | WB16: 1913000 | WJ16: 559000 | WN16: 4109000 | WO16: 975000 | WP16: 650800 | WQ16: 318900
C17: 14580 | AH17: 27886000 | AI17: 32037000 | AJ17: 12015000 | AK17: 938000 | AT17: 1066000 | BB17: 10011000 | BC17: 5149000 | BT17: 4862000 | CE17: 15871000 | CF17: 7233000 | CG17: 1562600 | CK17: 3554200 | DN17: 1176000 | DU17: 1386000 | EI17: 2022000 | FG17: 1403000 | GD17: 2099000 | GL17: 552000 | GP17: 4151000 | GQ17: 1021000 | GR17: 653100 | GS17: 367500 | JM17: 32037000 | JN17: 27886000 | JO17: 12015000 | JP17: 938000 | JY17: 1066000 | KG17: 10011000 | KH17: 5149000 | KY17: 4862000 | LJ17: 15871000 | LK17: 7233000 | LL17: 1562600 | LP17: 3554200 | MS17: 1176000 | MZ17: 1386000 | NN17: 2022000 | OL17: 1403000 | PI17: 2099000 | PQ17: 552000 | PU17: 4151000 | PV17: 1021000 | PW17: 653100 | PX17: 367500 | QG17: 31542000 | QH17: 27408000 | QI17: 12021000 | QJ17: 930000 | QS17: 1142000 | RA17: 9949000 | RB17: 5097000 | RS17: 4852000 | SD17: 15387000 | SE17: 6851000 | SF17: 1534900 | SJ17: 3178100 | TM17: 1178000 | TT17: 1405000 | UH17: 2033000 | VF17: 1428000 | WB17: 1930000 | WJ17: 562000 | WN17: 4134000 | WO17: 977000 | WP17: 666200 | WQ17: 349900
... C101: 17137 | AH101: 38351000 | AI101: 44140000 | AJ101: 17129000 | AK101: 935000 | AT101: 1892000 | BB101: 14302000 | BC101: 8166000 | BT101: 6136000 | CE101: 21222000 | CF101: 9675000 | CG101: 2094100 | CK101: 4669800 | DN101: 1642000 | DU101: 1660000 | EI101: 2777000 | FG101: 1934000 | GD101: 2777000 | GL101: 757000 | GP101: 5789000 | GQ101: 2350000 | GR101: 1637900 | GS101: 711900 | JM101: 44140000 | JN101: 38351000 | JO101: 17129000 | JP101: 935000 | JY101: 1892000 | KG101: 14302000 | KH101: 8166000 | KY101: 6136000 | LJ101: 21222000 | LK101: 9675000 | LL101: 2094100 | LP101: 4669800 | MS101: 1642000 | MZ101: 1660000 | NN101: 2777000 | OL101: 1934000 | PI101: 2777000 | PQ101: 757000 | PU101: 5789000 | PV101: 2350000 | PW101: 1637900 | PX101: 711900 | QG101: 43379000 | QH101: 37751000 | QI101: 17164000 | QJ101: 932000 | QS101: 1931000 | RA101: 14301000 | RB101: 8198000 | RS101: 6103000 | SD101: 20587000 | SE101: 9209000 | SF101: 2052800 | SJ101: 4265600 | TM101: 1646000 | TT101: 1668000 | UH101: 2779000 | VF101: 1956000 | WB101: 2564000 | WJ101: 765000 | WN101: 5628000 | WO101: 2163000 | WP101: 1668700 | WQ101: 679200
C102: 17168 | AH102: 37510000 | AI102: 43108000 | AJ102: 16991000 | AK102: 957000 | AL102: 89800 | AT102: 1769000 | BB102: 14265000 | BC102: 8105000 | BT102: 6160000 | CE102: 20519000 | CF102: 9204000 | CG102: 2070600 | CK102: 4233500 | DD102: 1499800 | DN102: 1640000 | DU102: 1634000 | EI102: 2774000 | FG102: 1952000 | GD102: 2552000 | GL102: 763000 | GP102: 5598000 | GQ102: 2106000 | GR102: 1662300 | GS102: 444000 | JM102: 43108000 | JN102: 37510000 | JO102: 16991000 | JP102: 957000 | JQ102: 89800 | JY102: 1769000 | KG102: 14265000 | KH102: 8105000 | KY102: 6160000 | LJ102: 20519000 | LK102: 9204000 | LL102: 2070600 | LP102: 4233500 | MI102: 1499800 | MS102: 1640000 | MZ102: 1634000 | NN102: 2774000 | OL102: 1952000 | PI102: 2552000 | PQ102: 763000 | PU102: 5598000 | PV102: 2106000 | PW102: 1662300 | PX102: 444000 | QG102: 43535000 | QH102: 37916000 | QI102: 17213000 | QJ102: 958000 | QK102: 100400 | QS102: 1927000 | RA102: 14328000 | RB102: 8150000 | RS102: 6178000 | SD102: 20703000 | SE102: 9259000 | SF102: 2047800 | SJ102: 4282100 | TC102: 1532000 | TM102: 1653000 | TT102: 1648000 | UH102: 2805000 | VF102: 1976000 | WB102: 2587000 | WJ102: 775000 | WN102: 5619000 | WO102: 2143000 | WP102: 1681600 | WQ102: 447800
C103: 17199 | AH103: 37495000 | AI103: 43100000 | AJ103: 17018000 | AK103: 958000 | AL103: 89700 | AT103: 1747000 | BB103: 14313000 | BC103: 8162000 | BT103: 6151000 | CE103: 20477000 | CF103: 9166000 | CG103: 2064700 | CK103: 4202300 | DD103: 1490100 | DN103: 1642000 | DU103: 1635000 | EI103: 2777000 | FG103: 1955000 | GD103: 2537000 | GL103: 765000 | GP103: 5605000 | GQ103: 2094000 | GR103: 1648700 | GS103: 445100 | JM103: 43100000 | JN103: 37495000 | JO103: 17018000 | JP103: 958000 | JQ103: 89700 | JY103: 1747000 | KG103: 14313000 | KH103: 8162000 | KY103: 6151000 | LJ103: 20477000 | LK103: 9166000 | LL103: 2064700 | LP103: 4202300 | MI103: 1490100 | MS103: 1642000 | MZ103: 1635000 | NN103: 2777000 | OL103: 1955000 | PI103: 2537000 | PQ103: 765000 | PU103: 5605000 | PV103: 2094000 | PW103: 1648700 | PX103: 445100 | QG103: 43557000 | QH103: 37951000 | QI103: 17200000 | QJ103: 962000 | QK103: 100500 | QS103: 1960000 | RA103: 14278000 | RB103: 8136000 | RS103: 6142000 | SD103: 20751000 | SE103: 9276000 | SF103: 2051700 | SJ103: 4296000 | TC103: 1530700 | TM103: 1652000 | TT103: 1647000 | UH103: 2813000 | VF103: 1986000 | WB103: 2600000 | WJ103: 777000 | WN103: 5606000 | WO103: 2110000 | WP103: 1642800 | WQ103: 448000
C104: 17227 | AH104: 37720000 | AI104: 43349000 | AJ104: 17068000 | AK104: 960000 | AL104: 91200 | AT104: 1794000 | BB104: 14314000 | BC104: 8182000 | BT104: 6132000 | CE104: 20652000 | CF104: 9248000 | CG104: 2061500 | CK104: 4269000 | DD104: 1492000 | DN104: 1649000 | DU104: 1643000 | EI104: 2794000 | FG104: 1971000 | GD104: 2576000 | GL104: 771000 | GP104: 5629000 | GQ104: 2072000 | GR104: 1624700 | GS104: 447100 | JM104: 43349000 | JN104: 37720000 | JO104: 17068000 | JP104: 960000 | JQ104: 91200 | JY104: 1794000 | KG104: 14314000 | KH104: 8182000 | KY104: 6132000 | LJ104: 20652000 | LK104: 9248000 | LL104: 2061500 | LP104: 4269000 | MI104: 1492000 | MS104: 1649000 | MZ104: 1643000 | NN104: 2794000 | OL104: 1971000 | PI104: 2576000 | PQ104: 771000 | PU104: 5629000 | PV104: 2072000 | PW104: 1624700 | PX104: 447100 | QG104: 43607000 | QH104: 38019000 | QI104: 17196000 | QJ104: 965000 | QK104: 99500 | QS104: 1972000 | RA104: 14259000 | RB104: 8100000 | RS104: 6159000 | SD104: 20823000 | SE104: 9313000 | SF104: 2059200 | SJ104: 4326200 | TC104: 1527800 | TM104: 1662000 | TT104: 1649000 | UH104: 2817000 | VF104: 1992000 | WB104: 2612000 | WJ104: 778000 | WN104: 5588000 | WO104: 2077000 | WP104: 1611700 | WQ104: 449400
C105: 17258 | AH105: 37686000 | AI105: 43309000 | AJ105: 17060000 | AK105: 940000 | AL105: 90800 | AT105: 1908000 | BB105: 14212000 | BC105: 8150000 | BT105: 6062000 | CE105: 20626000 | CF105: 9177000 | CG105: 2042900 | CK105: 4302600 | DD105: 1510500 | DN105: 1617000 | DU105: 1659000 | EI105: 2799000 | FG105: 1993000 | GD105: 2601000 | GL105: 780000 | GP105: 5623000 | GQ105: 2043000 | GR105: 1593300 | GS105: 450100 | JM105: 43309000 | JN105: 37686000 | JO105: 17060000 | JP105: 940000 | JQ105: 90800 | JY105: 1908000 | KG105: 14212000 | KH105: 8150000 | KY105: 6062000 | LJ105: 20626000 | LK105: 9177000 | LL105: 2042900 | LP105: 4302600 | MI105: 1510500 | MS105: 1617000 | MZ105: 1659000 | NN105: 2799000 | OL105: 1993000 | PI105: 2601000 | PQ105: 780000 | PU105: 5623000 | PV105: 2043000 | PW105: 1593300 | PX105: 450100 | QG105: 43499000 | QH105: 37941000 | QI105: 17178000 | QJ105: 946000 | QK105: 102100 | QS105: 1992000 | RA105: 14240000 | RB105: 8093000 | RS105: 6147000 | SD105: 20763000 | SE105: 9263000 | SF105: 2062200 | SJ105: 4334800 | TC105: 1527000 | TM105: 1631000 | TT105: 1657000 | UH105: 2814000 | VF105: 1997000 | WB105: 2620000 | WJ105: 781000 | WN105: 5558000 | WO105: 2035000 | WP105: 1574400 | WQ105: 449800
C106: 17288 | AH106: 37772000 | AI106: 43392000 | AJ106: 17005000 | AK106: 967000 | AL106: 96000 | AT106: 2004000 | BB106: 14034000 | BC106: 8035000 | BT106: 5999000 | CE106: 20767000 | CF106: 9234000 | CG106: 2026000 | CK106: 4314300 | DD106: 1528000 | DN106: 1632000 | DU106: 1664000 | EI106: 2820000 | FG106: 2016000 | GD106: 2613000 | GL106: 788000 | GP106: 5620000 | GQ106: 2015000 | GR106: 1566000 | GS106: 449100 | JM106: 43392000 | JN106: 37772000 | JO106: 17005000 | JP106: 967000 | JQ106: 96000 | JY106: 2004000 | KG106: 14034000 | KH106: 8035000 | KY106: 5999000 | LJ106: 20767000 | LK106: 9234000 | LL106: 2026000 | LP106: 4314300 | MI106: 1528000 | MS106: 1632000 | MZ106: 1664000 | NN106: 2820000 | OL106: 2016000 | PI106: 2613000 | PQ106: 788000 | PU106: 5620000 | PV106: 2015000 | PW106: 1566000 | PX106: 449100 | QG106: 43638000 | QH106: 38087000 | QI106: 17176000 | QJ106: 972000 | QK106: 96000 | QS106: 2015000 | RA106: 14189000 | RB106: 8041000 | RS106: 6148000 | SD106: 20911000 | SE106: 9359000 | SF106: 2068300 | SJ106: 4368600 | TC106: 1518700 | TM106: 1643000 | TT106: 1661000 | UH106: 2823000 | VF106: 2005000 | WB106: 2637000 | WJ106: 783000 | WN106: 5551000 | WO106: 2002000 | WP106: 1547700 | WQ106: 451400
C107: 17319 | AH107: 38249000 | AI107: 43764000 | AJ107: 17223000 | AK107: 981000 | AL107: 96000 | AT107: 2154000 | BB107: 14088000 | BC107: 8071000 | BT107: 6017000 | CE107: 21026000 | CF107: 9360000 | CG107: 2049600 | CK107: 4331600 | DD107: 1537800 | DN107: 1663000 | DU107: 1678000 | EI107: 2858000 | FG107: 2042000 | GD107: 2627000 | GL107: 798000 | GP107: 5515000 | GQ107: 1947000 | GR107: 1499900 | GS107: 447100 | JM107: 43764000 | JN107: 38249000 | JO107: 17223000 | JP107: 981000 | JQ107: 96000 | JY107: 2154000 | KG107: 14088000 | KH107: 8071000 | KY107: 6017000 | LJ107: 21026000 | LK107: 9360000 | LL107: 2049600 | LP107: 4331600 | MI107: 1537800 | MS107: 1663000 | MZ107: 1678000 | NN107: 2858000 | OL107: 2042000 | PI107: 2627000 | PQ107: 798000 | PU107: 5515000 | PV107: 1947000 | PW107: 1499900 | PX107: 447100 | QG107: 43810000 | QH107: 38286000 | QI107: 17253000 | QJ107: 977000 | QK107: 92500 | QS107: 2076000 | RA107: 14200000 | RB107: 8073000 | RS107: 6127000 | SD107: 21033000 | SE107: 9431000 | SF107: 2085600 | SJ107: 4391000 | TC107: 1516900 | TM107: 1657000 | TT107: 1663000 | UH107: 2834000 | VF107: 2013000 | WB107: 2649000 | WJ107: 786000 | WN107: 5524000 | WO107: 1946000 | WP107: 1480300 | WQ107: 448800
C108: 17349 | AH108: 38186000 | AI108: 43604000 | AJ108: 17129000 | AK108: 957000 | AL108: 96000 | AT108: 2199000 | BB108: 13973000 | BC108: 7869000 | BT108: 6104000 | CE108: 21057000 | CF108: 9371000 | CG108: 2072200 | CK108: 4313800 | DD108: 1543600 | DN108: 1661000 | DU108: 1701000 | EI108: 2860000 | FG108: 2047000 | GD108: 2617000 | GL108: 800000 | GP108: 5418000 | GQ108: 1905000 | GR108: 1458900 | GS108: 446100 | JM108: 43604000 | JN108: 38186000 | JO108: 17129000 | JP108: 957000 | JQ108: 96000 | JY108: 2199000 | KG108: 13973000 | KH108: 7869000 | KY108: 6104000 | LJ108: 21057000 | LK108: 9371000 | LL108: 2072200 | LP108: 4313800 | MI108: 1543600 | MS108: 1661000 | MZ108: 1701000 | NN108: 2860000 | OL108: 2047000 | PI108: 2617000 | PQ108: 800000 | PU108: 5418000 | PV108: 1905000 | PW108: 1458900 | PX108: 446100 | QG108: 43743000 | QH108: 38219000 | QI108: 17106000 | QJ108: 953000 | QK108: 89700 | QS108: 2077000 | RA108: 14076000 | RB108: 7908000 | RS108: 6168000 | SD108: 21113000 | SE108: 9472000 | SF108: 2101400 | SJ108: 4410600 | TC108: 1524200 | TM108: 1654000 | TT108: 1680000 | UH108: 2839000 | VF108: 2020000 | WB108: 2659000 | WJ108: 789000 | WN108: 5524000 | WO108: 1909000 | WP108: 1444500 | WQ108: 446500
C109: 17380 | AH109: 38660000 | AI109: 44066000 | AJ109: 17556000 | AK109: 994000 | AL109: 93400 | AT109: 2264000 | BB109: 14298000 | BC109: 7957000 | BT109: 6341000 | CE109: 21104000 | CF109: 9403000 | CG109: 2101700 | CK109: 4300800 | DD109: 1542700 | DN109: 1679000 | DU109: 1701000 | EI109: 2873000 | FG109: 2043000 | GD109: 2607000 | GL109: 798000 | GP109: 5406000 | GQ109: 1883000 | GR109: 1439900 | GS109: 443000 | JM109: 44066000 | JN109: 38660000 | JO109: 17556000 | JP109: 994000 | JQ109: 93400 | JY109: 2264000 | KG109: 14298000 | KH109: 7957000 | KY109: 6341000 | LJ109: 21104000 | LK109: 9403000 | LL109: 2101700 | LP109: 4300800 | MI109: 1542700 | MS109: 1679000 | MZ109: 1701000 | NN109: 2873000 | OL109: 2043000 | PI109: 2607000 | PQ109: 798000 | PU109: 5406000 | PV109: 1883000 | PW109: 1439900 | PX109: 443000 | QG109: 43960000 | QH109: 38441000 | QI109: 17280000 | QJ109: 985000 | QK109: 86500 | QS109: 2095000 | RA109: 14200000 | RB109: 7973000 | RS109: 6227000 | SD109: 21161000 | SE109: 9492000 | SF109: 2111600 | SJ109: 4416400 | TC109: 1517400 | TM109: 1659000 | TT109: 1682000 | UH109: 2847000 | VF109: 2024000 | WB109: 2666000 | WJ109: 791000 | WN109: 5519000 | WO109: 1896000 | WP109: 1429800 | WQ109: 445400
C110: 17411 | AH110: 39077000 | AI110: 44591000 | AJ110: 17746000 | AK110: 994000 | AL110: 94100 | AT110: 2263000 | BB110: 14489000 | BC110: 8042000 | BT110: 6447000 | CE110: 21331000 | CF110: 9543000 | CG110: 2145900 | CK110: 4408000 | DD110: 1526100 | DN110: 1683000 | DU110: 1687000 | EI110: 2893000 | FG110: 2057000 | GD110: 2664000 | GL110: 804000 | GP110: 5514000 | GQ110: 1864000 | GR110: 1421000 | GS110: 443000 | JM110: 44591000 | JN110: 39077000 | JO110: 17746000 | JP110: 994000 | JQ110: 94100 | JY110: 2263000 | KG110: 14489000 | KH110: 8042000 | KY110: 6447000 | LJ110: 21331000 | LK110: 9543000 | LL110: 2145900 | LP110: 4408000 | MI110: 1526100 | MS110: 1683000 | MZ110: 1687000 | NN110: 2893000 | OL110: 2057000 | PI110: 2664000 | PQ110: 804000 | PU110: 5514000 | PV110: 1864000 | PW110: 1421000 | PX110: 443000 | QG110: 44203000 | QH110: 38664000 | QI110: 17398000 | QJ110: 989000 | QK110: 87000 | QS110: 2094000 | RA110: 14315000 | RB110: 8043000 | RS110: 6272000 | SD110: 21266000 | SE110: 9557000 | SF110: 2141400 | SJ110: 4440200 | TC110: 1508100 | TM110: 1665000 | TT110: 1689000 | UH110: 2859000 | VF110: 2030000 | WB110: 2673000 | WJ110: 793000 | WN110: 5539000 | WO110: 1901000 | WP110: 1431900 | WQ110: 447000
C111: 17441 | AH111: 39197000 | AI111: 44741000 | AJ111: 17714000 | AK111: 997000 | AL111: 93800 | AT111: 2236000 | BB111: 14481000 | BC111: 8088000 | BT111: 6393000 | CE111: 21483000 | CF111: 9671000 | CG111: 2175600 | CK111: 4519400 | DD111: 1517300 | DN111: 1677000 | DU111: 1690000 | EI111: 2884000 | FG111: 2044000 | GD111: 2718000 | GL111: 799000 | GP111: 5544000 | GQ111: 1868000 | GR111: 1421200 | GS111: 447100 | JM111: 44741000 | JN111: 39197000 | JO111: 17714000 | JP111: 997000 | JQ111: 93800 | JY111: 2236000 | KG111: 14481000 | KH111: 8088000 | KY111: 6393000 | LJ111: 21483000 | LK111: 9671000 | LL111: 2175600 | LP111: 4519400 | MI111: 1517300 | MS111: 1677000 | MZ111: 1690000 | NN111: 2884000 | OL111: 2044000 | PI111: 2718000 | PQ111: 799000 | PU111: 5544000 | PV111: 1868000 | PW111: 1421200 | PX111: 447100 | QG111: 44411000 | QH111: 38845000 | QI111: 17499000 | QJ111: 997000 | QK111: 86000 | QS111: 2109000 | RA111: 14393000 | RB111: 8114000 | RS111: 6279000 | SD111: 21346000 | SE111: 9589000 | SF111: 2150100 | SJ111: 4469700 | TC111: 1502700 | TM111: 1667000 | TT111: 1694000 | UH111: 2870000 | VF111: 2039000 | WB111: 2690000 | WJ111: 797000 | WN111: 5566000 | WO111: 1912000 | WP111: 1436200 | WQ111: 451100
C112: 17472 | AH112: 39283000 | AI112: 44807000 | AJ112: 17645000 | AK112: 1001000 | AL112: 90200 | AT112: 2172000 | BB112: 14472000 | BC112: 8122000 | BT112: 6350000 | CE112: 21638000 | CF112: 9790000 | CG112: 2194300 | CK112: 4624400 | DD112: 1500800 | DN112: 1675000 | DU112: 1692000 | EI112: 2879000 | FG112: 2036000 | GD112: 2770000 | GL112: 796000 | GP112: 5524000 | GQ112: 1871000 | GR112: 1416300 | GS112: 455100 | JM112: 44807000 | JN112: 39283000 | JO112: 17645000 | JP112: 1001000 | JQ112: 90200 | JY112: 2172000 | KG112: 14472000 | KH112: 8122000 | KY112: 6350000 | LJ112: 21638000 | LK112: 9790000 | LL112: 2194300 | LP112: 4624400 | MI112: 1500800 | MS112: 1675000 | MZ112: 1692000 | NN112: 2879000 | OL112: 2036000 | PI112: 2770000 | PQ112: 796000 | PU112: 5524000 | PV112: 1871000 | PW112: 1416300 | PX112: 455100 | QG112: 44484000 | QH112: 38899000 | QI112: 17517000 | QJ112: 1002000 | QK112: 85300 | QS112: 2101000 | RA112: 14414000 | RB112: 8123000 | RS112: 6291000 | SD112: 21382000 | SE112: 9596000 | SF112: 2152800 | SJ112: 4478700 | TC112: 1493600 | TM112: 1668000 | TT112: 1701000 | UH112: 2877000 | VF112: 2044000 | WB112: 2697000 | WJ112: 799000 | WN112: 5585000 | WO112: 1916000 | WP112: 1440200 | WQ112: 453400
C113: 17502 | AH113: 39708000 | AI113: 45514000 | AJ113: 17616000 | AK113: 1008000 | AL113: 89000 | AT113: 2101000 | BB113: 14507000 | BC113: 8165000 | BT113: 6342000 | CE113: 22092000 | CF113: 10093000 | CG113: 2194800 | CK113: 4905800 | DD113: 1503700 | DN113: 1681000 | DU113: 1698000 | EI113: 2884000 | FG113: 2027000 | GD113: 2916000 | GL113: 793000 | GP113: 5806000 | GQ113: 2146000 | GR113: 1416200 | GS113: 730000 | JM113: 45514000 | JN113: 39708000 | JO113: 17616000 | JP113: 1008000 | JQ113: 89000 | JY113: 2101000 | KG113: 14507000 | KH113: 8165000 | KY113: 6342000 | LJ113: 22092000 | LK113: 10093000 | LL113: 2194800 | LP113: 4905800 | MI113: 1503700 | MS113: 1681000 | MZ113: 1698000 | NN113: 2884000 | OL113: 2027000 | PI113: 2916000 | PQ113: 793000 | PU113: 5806000 | PV113: 2146000 | PW113: 1416200 | PX113: 730000 | QG113: 44581000 | QH113: 38976000 | QI113: 17563000 | QJ113: 1005000 | QK113: 89800 | QS113: 2130000 | RA113: 14428000 | RB113: 8130000 | RS113: 6298000 | SD113: 21413000 | SE113: 9600000 | SF113: 2153800 | SJ113: 4481800 | TC113: 1494900 | TM113: 1679000 | TT113: 1707000 | UH113: 2882000 | VF113: 2049000 | WB113: 2695000 | WJ113: 801000 | WN113: 5605000 | WO113: 1948000 | WP113: 1432100 | WQ113: 696900
C114: 17533 | V114: 1188000 | W114: 507000 | X114: 311000 | Y114: 183000 | Z114: 128000 | AA114: 8.9 | AC114: 59.2 | AD114: 25.3 | AE114: 15.5 | AF114: 9.1 | AG114: 6.4 | AH114: 38617000 | AI114: 44224000 | AJ114: 17408000 | AK114: 1006000 | AL114: 79500 | AT114: 2000000 | BB114: 14402000 | BC114: 8121000 | BT114: 6281000 | CE114: 21209000 | CF114: 9537000 | CG114: 2183900 | CK114: 4431300 | DD114: 1472500 | DN114: 1655000 | DU114: 1697000 | EI114: 2850000 | FG114: 2017000 | GD114: 2664000 | GL114: 789000 | GP114: 5607000 | GQ114: 1857000 | GR114: 1405600 | GS114: 451100 | IO114: 60095000 | IP114: 58.6 | IQ114: 58061000 | IR114: 56.6 | IS114: 2034000 | IT114: 3.4 | IW114: 43214000 | IX114: 86.7 | IY114: 41736000 | IZ114: 83.8 | JA114: 1478000 | JB114: 3.4 | JD114: 40619000 | JE114: 88.7 | JF114: 39386000 | JG114: 86 | JH114: 1233000 | JI114: 3 | JM114: 44224000 | JN114: 38617000 | JO114: 17408000 | JP114: 1006000 | JQ114: 79500 | JY114: 2000000 | KG114: 14402000 | KH114: 8121000 | KY114: 6281000 | LJ114: 21209000 | LK114: 9537000 | LL114: 2183900 | LP114: 4431300 | MI114: 1472500 | MS114: 1655000 | MZ114: 1697000 | NN114: 2850000 | OL114: 2017000 | PI114: 2664000 | PQ114: 789000 | PU114: 5607000 | PV114: 1857000 | PW114: 1405600 | PX114: 451100 | QG114: 44679000 | QH114: 39055000 | QI114: 17625000 | QJ114: 1008000 | QK114: 88900 | QS114: 2179000 | RA114: 14438000 | RB114: 8132000 | RS114: 6306000 | SD114: 21430000 | SE114: 9609000 | SF114: 2164100 | SJ114: 4490500 | TC114: 1504300 | TM114: 1669000 | TT114: 1714000 | UH114: 2885000 | VF114: 2047000 | WB114: 2704000 | WJ114: 802000 | WN114: 5624000 | WO114: 1889000 | WP114: 1419900 | WQ114: 454900
C115: 17564 | V115: 1377000 | W115: 677000 | X115: 283000 | Y115: 162000 | Z115: 121000 | AA115: 8.4 | AC115: 58.9 | AD115: 29 | AE115: 12.1 | AF115: 6.9 | AG115: 5.2 | AH115: 38344000 | AI115: 43956000 | AJ115: 17203000 | AK115: 997000 | AL115: 81400 | AT115: 1862000 | BB115: 14344000 | BC115: 8063000 | BT115: 6281000 | CE115: 21141000 | CF115: 9497000 | CG115: 2185500 | CK115: 4380300 | DD115: 1464700 | DN115: 1656000 | DU115: 1708000 | EI115: 2843000 | FG115: 2013000 | GD115: 2636000 | GL115: 788000 | GP115: 5612000 | GQ115: 1868000 | GR115: 1411100 | GS115: 457100 | IO115: 60524000 | IP115: 58.9 | IQ115: 58196000 | IR115: 56.7 | IS115: 2328000 | IT115: 3.8 | IW115: 43400000 | IX115: 87 | IY115: 41835000 | IZ115: 83.9 | JA115: 1565000 | JB115: 3.6 | JD115: 40761000 | JE115: 89 | JF115: 39480000 | JG115: 86.2 | JH115: 1281000 | JI115: 3.1 | JM115: 43956000 | JN115: 38344000 | JO115: 17203000 | JP115: 997000 | JQ115: 81400 | JY115: 1862000 | KG115: 14344000 | KH115: 8063000 | KY115: 6281000 | LJ115: 21141000 | LK115: 9497000 | LL115: 2185500 | LP115: 4380300 | MI115: 1464700 | MS115: 1656000 | MZ115: 1708000 | NN115: 2843000 | OL115: 2013000 | PI115: 2636000 | PQ115: 788000 | PU115: 5612000 | PV115: 1868000 | PW115: 1411100 | PX115: 457100 | QG115: 44533000 | QH115: 38918000 | QI115: 17447000 | QJ115: 1003000 | QK115: 91400 | QS115: 2105000 | RA115: 14339000 | RB115: 8052000 | RS115: 6287000 | SD115: 21471000 | SE115: 9635000 | SF115: 2177300 | SJ115: 4489400 | TC115: 1504700 | TM115: 1670000 | TT115: 1722000 | UH115: 2885000 | VF115: 2051000 | WB115: 2706000 | WJ115: 802000 | WN115: 5615000 | WO115: 1884000 | WP115: 1409200 | WQ115: 460100
C116: 17593 | V116: 1279000 | W116: 830000 | X116: 292000 | Y116: 182000 | Z116: 110000 | AA116: 8.7 | AC116: 53.3 | AD116: 34.6 | AE116: 12.2 | AF116: 7.6 | AG116: 4.6 | AH116: 38624000 | AI116: 44291000 | AJ116: 17333000 | AK116: 1011000 | AL116: 78300 | AT116: 1949000 | BB116: 14373000 | BC116: 8108000 | BT116: 6265000 | CE116: 21291000 | CF116: 9553000 | CG116: 2176300 | CK116: 4431600 | DD116: 1469600 | DN116: 1663000 | DU116: 1719000 | EI116: 2863000 | FG116: 2031000 | GD116: 2668000 | GL116: 794000 | GP116: 5667000 | GQ116: 1878000 | GR116: 1413500 | GS116: 464200 | IO116: 60070000 | IP116: 58.5 | IQ116: 57671000 | IR116: 56.1 | IS116: 2399000 | IT116: 4 | IW116: 43080000 | IX116: 86.3 | IY116: 41431000 | IZ116: 83 | JA116: 1649000 | JB116: 3.8 | JD116: 40432000 | JE116: 88.2 | JF116: 39098000 | JG116: 85.3 | JH116: 1334000 | JI116: 3.3 | JM116: 44291000 | JN116: 38624000 | JO116: 17333000 | JP116: 1011000 | JQ116: 78300 | JY116: 1949000 | KG116: 14373000 | KH116: 8108000 | KY116: 6265000 | LJ116: 21291000 | LK116: 9553000 | LL116: 2176300 | LP116: 4431600 | MI116: 1469600 | MS116: 1663000 | MZ116: 1719000 | NN116: 2863000 | OL116: 2031000 | PI116: 2668000 | PQ116: 794000 | PU116: 5667000 | PV116: 1878000 | PW116: 1413500 | PX116: 464200 | QG116: 44683000 | QH116: 39060000 | QI116: 17544000 | QJ116: 1017000 | QK116: 85700 | QS116: 2163000 | RA116: 14364000 | RB116: 8049000 | RS116: 6315000 | SD116: 21516000 | SE116: 9642000 | SF116: 2181600 | SJ116: 4503400 | TC116: 1504600 | TM116: 1678000 | TT116: 1727000 | UH116: 2894000 | VF116: 2058000 | WB116: 2713000 | WJ116: 804000 | WN116: 5623000 | WO116: 1884000 | WP116: 1406700 | WQ116: 466300
C117: 17624 | V117: 1461000 | W117: 694000 | X117: 324000 | Y117: 215000 | Z117: 109000 | AA117: 8.5 | AC117: 58.9 | AD117: 28 | AE117: 13.1 | AF117: 8.7 | AG117: 4.4 | AH117: 38368000 | AI117: 44082000 | AJ117: 17083000 | AK117: 911000 | AL117: 73600 | AT117: 2090000 | BB117: 14082000 | BC117: 7995000 | BT117: 6087000 | CE117: 21285000 | CF117: 9492000 | CG117: 2161100 | CK117: 4432800 | DD117: 1410200 | DN117: 1637000 | DU117: 1733000 | EI117: 2872000 | FG117: 2065000 | GD117: 2678000 | GL117: 808000 | GP117: 5714000 | GQ117: 1892000 | GR117: 1425200 | GS117: 467200 | IO117: 60677000 | IP117: 59 | IQ117: 58291000 | IR117: 56.7 | IS117: 2386000 | IT117: 3.9 | IW117: 43215000 | IX117: 86.6 | IY117: 41585000 | IZ117: 83.3 | JA117: 1630000 | JB117: 3.8 | JD117: 40524000 | JE117: 88.3 | JF117: 39157000 | JG117: 85.4 | JH117: 1367000 | JI117: 3.4 | JM117: 44082000 | JN117: 38368000 | JO117: 17083000 | JP117: 911000 | JQ117: 73600 | JY117: 2090000 | KG117: 14082000 | KH117: 7995000 | KY117: 6087000 | LJ117: 21285000 | LK117: 9492000 | LL117: 2161100 | LP117: 4432800 | MI117: 1410200 | MS117: 1637000 | MZ117: 1733000 | NN117: 2872000 | OL117: 2065000 | PI117: 2678000 | PQ117: 808000 | PU117: 5714000 | PV117: 1892000 | PW117: 1425200 | PX117: 467200 | QG117: 44379000 | QH117: 38736000 | QI117: 17302000 | QJ117: 917000 | QK117: 82900 | QS117: 2202000 | RA117: 14183000 | RB117: 7980000 | RS117: 6203000 | SD117: 21434000 | SE117: 9583000 | SF117: 2187100 | SJ117: 4469800 | TC117: 1424400 | TM117: 1653000 | TT117: 1732000 | UH117: 2891000 | VF117: 2069000 | WB117: 2697000 | WJ117: 809000 | WN117: 5643000 | WO117: 1889000 | WP117: 1411900 | WQ117: 466800
C118: 17654 | V118: 1146000 | W118: 671000 | X118: 329000 | Y118: 220000 | Z118: 109000 | AA118: 9.1 | AC118: 53.4 | AD118: 31.3 | AE118: 15.3 | AF118: 10.3 | AG118: 5.1 | AH118: 38728000 | AI118: 44471000 | AJ118: 17272000 | AK118: 1023000 | AL118: 77000 | AT118: 2230000 | BB118: 14019000 | BC118: 7934000 | BT118: 6085000 | CE118: 21456000 | CF118: 9564000 | CG118: 2157600 | CK118: 4456500 | DD118: 1469600 | DN118: 1653000 | DU118: 1739000 | EI118: 2900000 | FG118: 2088000 | GD118: 2696000 | GL118: 816000 | GP118: 5743000 | GQ118: 1903000 | GR118: 1436700 | GS118: 466200 | IO118: 59972000 | IP118: 58.3 | IQ118: 57854000 | IR118: 56.2 | IS118: 2118000 | IT118: 3.5 | IW118: 43002000 | IX118: 86.1 | IY118: 41510000 | IZ118: 83.1 | JA118: 1492000 | JB118: 3.5 | JD118: 40435000 | JE118: 88.1 | JF118: 39139000 | JG118: 85.3 | JH118: 1296000 | JI118: 3.2 | JM118: 44471000 | JN118: 38728000 | JO118: 17272000 | JP118: 1023000 | JQ118: 77000 | JY118: 2230000 | KG118: 14019000 | KH118: 7934000 | KY118: 6085000 | LJ118: 21456000 | LK118: 9564000 | LL118: 2157600 | LP118: 4456500 | MI118: 1469600 | MS118: 1653000 | MZ118: 1739000 | NN118: 2900000 | OL118: 2088000 | PI118: 2696000 | PQ118: 816000 | PU118: 5743000 | PV118: 1903000 | PW118: 1436700 | PX118: 466200 | QG118: 44796000 | QH118: 39115000 | QI118: 17508000 | QJ118: 1028000 | QK118: 76900 | QS118: 2245000 | RA118: 14235000 | RB118: 7969000 | RS118: 6266000 | SD118: 21607000 | SE118: 9697000 | SF118: 2202600 | SJ118: 4512000 | TC118: 1460700 | TM118: 1664000 | TT118: 1737000 | UH118: 2904000 | VF118: 2074000 | WB118: 2720000 | WJ118: 811000 | WN118: 5681000 | WO118: 1901000 | WP118: 1423800 | WQ118: 468200
C119: 17685 | V119: 1287000 | W119: 611000 | X119: 322000 | Y119: 204000 | Z119: 118000 | AA119: 8.8 | AC119: 58 | AD119: 27.5 | AE119: 14.5 | AF119: 9.2 | AG119: 5.3 | AH119: 39240000 | AI119: 44951000 | AJ119: 17578000 | AK119: 1039000 | AL119: 88300 | AT119: 2366000 | BB119: 14173000 | BC119: 7923000 | BT119: 6250000 | CE119: 21662000 | CF119: 9642000 | CG119: 2174500 | CK119: 4477200 | DD119: 1499800 | DN119: 1673000 | DU119: 1761000 | EI119: 2935000 | FG119: 2113000 | GD119: 2712000 | GL119: 826000 | GP119: 5711000 | GQ119: 1935000 | GR119: 1459100 | GS119: 476300 | IO119: 60957000 | IP119: 59.2 | IQ119: 58743000 | IR119: 57 | IS119: 2214000 | IT119: 3.6 | IW119: 43257000 | IX119: 86.6 | IY119: 41809000 | IZ119: 83.7 | JA119: 1448000 | JB119: 3.3 | JD119: 40591000 | JE119: 88.5 | JF119: 39392000 | JG119: 85.9 | JH119: 1199000 | JI119: 3 | JM119: 44951000 | JN119: 39240000 | JO119: 17578000 | JP119: 1039000 | JQ119: 88300 | JY119: 2366000 | KG119: 14173000 | KH119: 7923000 | KY119: 6250000 | LJ119: 21662000 | LK119: 9642000 | LL119: 2174500 | LP119: 4477200 | MI119: 1499800 | MS119: 1673000 | MZ119: 1761000 | NN119: 2935000 | OL119: 2113000 | PI119: 2712000 | PQ119: 826000 | PU119: 5711000 | PV119: 1935000 | PW119: 1459100 | PX119: 476300 | QG119: 45034000 | QH119: 39298000 | QI119: 17633000 | QJ119: 1035000 | QK119: 84700 | QS119: 2280000 | RA119: 14318000 | RB119: 7943000 | RS119: 6375000 | SD119: 21665000 | SE119: 9711000 | SF119: 2211400 | SJ119: 4530000 | TC119: 1480000 | TM119: 1670000 | TT119: 1747000 | UH119: 2912000 | VF119: 2082000 | WB119: 2729000 | WJ119: 814000 | WN119: 5736000 | WO119: 1942000 | WP119: 1446300 | WQ119: 477700
C120: 17715 | V120: 1259000 | W120: 643000 | X120: 295000 | Y120: 188000 | Z120: 107000 | AA120: 8.6 | AC120: 57.3 | AD120: 29.3 | AE120: 13.4 | AF120: 8.6 | AG120: 4.9 | AH120: 39355000 | AI120: 44989000 | AJ120: 17665000 | AK120: 1009000 | AL120: 95400 | AT120: 2426000 | BB120: 14230000 | BC120: 7957000 | BT120: 6273000 | CE120: 21690000 | CF120: 9652000 | CG120: 2195600 | CK120: 4450400 | DD120: 1508600 | DN120: 1681000 | DU120: 1775000 | EI120: 2942000 | FG120: 2116000 | GD120: 2697000 | GL120: 827000 | GP120: 5634000 | GQ120: 1949000 | GR120: 1470700 | GS120: 478300 | IO120: 61181000 | IP120: 59.3 | IQ120: 58968000 | IR120: 57.1 | IS120: 2213000 | IT120: 3.6 | IW120: 43429000 | IX120: 86.7 | IY120: 41969000 | IZ120: 83.8 | JA120: 1460000 | JB120: 3.4 | JD120: 40798000 | JE120: 88.7 | JF120: 39607000 | JG120: 86.1 | JH120: 1191000 | JI120: 2.9 | JM120: 44989000 | JN120: 39355000 | JO120: 17665000 | JP120: 1009000 | JQ120: 95400 | JY120: 2426000 | KG120: 14230000 | KH120: 7957000 | KY120: 6273000 | LJ120: 21690000 | LK120: 9652000 | LL120: 2195600 | LP120: 4450400 | MI120: 1508600 | MS120: 1681000 | MZ120: 1775000 | NN120: 2942000 | OL120: 2116000 | PI120: 2697000 | PQ120: 827000 | PU120: 5634000 | PV120: 1949000 | PW120: 1470700 | PX120: 478300 | QG120: 45160000 | QH120: 39386000 | QI120: 17649000 | QJ120: 1006000 | QK120: 89000 | QS120: 2284000 | RA120: 14359000 | RB120: 8023000 | RS120: 6336000 | SD120: 21737000 | SE120: 9752000 | SF120: 2223800 | SJ120: 4543900 | TC120: 1490200 | TM120: 1677000 | TT120: 1753000 | UH120: 2920000 | VF120: 2084000 | WB120: 2736000 | WJ120: 815000 | WN120: 5774000 | WO120: 1964000 | WP120: 1461300 | WQ120: 479000
C121: 17746 | V121: 1511000 | W121: 591000 | X121: 332000 | Y121: 204000 | Z121: 128000 | AA121: 8.8 | AC121: 62.1 | AD121: 24.3 | AE121: 13.6 | AF121: 8.4 | AG121: 5.3 | AH121: 39674000 | AI121: 45338000 | AJ121: 17968000 | AK121: 1042000 | AL121: 97500 | AT121: 2463000 | BB121: 14463000 | BC121: 8005000 | BT121: 6458000 | CE121: 21706000 | CF121: 9670000 | CG121: 2231100 | CK121: 4433100 | DD121: 1502700 | DN121: 1691000 | DU121: 1775000 | EI121: 2949000 | FG121: 2111000 | GD121: 2684000 | GL121: 826000 | GP121: 5664000 | GQ121: 1965000 | GR121: 1484500 | GS121: 480300 | IO121: 60806000 | IP121: 58.9 | IQ121: 58456000 | IR121: 56.6 | IS121: 2350000 | IT121: 3.9 | IW121: 43403000 | IX121: 86.7 | IY121: 41825000 | IZ121: 83.5 | JA121: 1578000 | JB121: 3.6 | JD121: 40819000 | JE121: 88.8 | JF121: 39510000 | JG121: 86 | JH121: 1309000 | JI121: 3.2 | JM121: 45338000 | JN121: 39674000 | JO121: 17968000 | JP121: 1042000 | JQ121: 97500 | JY121: 2463000 | KG121: 14463000 | KH121: 8005000 | KY121: 6458000 | LJ121: 21706000 | LK121: 9670000 | LL121: 2231100 | LP121: 4433100 | MI121: 1502700 | MS121: 1691000 | MZ121: 1775000 | NN121: 2949000 | OL121: 2111000 | PI121: 2684000 | PQ121: 826000 | PU121: 5664000 | PV121: 1965000 | PW121: 1484500 | PX121: 480300 | QG121: 45178000 | QH121: 39387000 | QI121: 17655000 | QJ121: 1033000 | QK121: 90000 | QS121: 2269000 | RA121: 14353000 | RB121: 8037000 | RS121: 6316000 | SD121: 21732000 | SE121: 9746000 | SF121: 2234400 | SJ121: 4545200 | TC121: 1478500 | TM121: 1670000 | TT121: 1753000 | UH121: 2920000 | VF121: 2088000 | WB121: 2739000 | WJ121: 816000 | WN121: 5791000 | WO121: 1981000 | WP121: 1474800 | WQ121: 483200
C122: 17777 | V122: 1245000 | W122: 759000 | X122: 298000 | Y122: 171000 | Z122: 127000 | AA122: 8.5 | AC122: 54.1 | AD122: 33 | AE122: 12.9 | AF122: 7.4 | AG122: 5.5 | AH122: 40012000 | AI122: 45796000 | AJ122: 18158000 | AK122: 1042000 | AL122: 96200 | AT122: 2449000 | BB122: 14667000 | BC122: 8089000 | BT122: 6578000 | CE122: 21854000 | CF122: 9760000 | CG122: 2253200 | CK122: 4520800 | DD122: 1498800 | DN122: 1693000 | DU122: 1758000 | EI122: 2963000 | FG122: 2120000 | GD122: 2731000 | GL122: 829000 | GP122: 5784000 | GQ122: 1964000 | GR122: 1482400 | GS122: 481300 | IO122: 60815000 | IP122: 58.9 | IQ122: 58513000 | IR122: 56.6 | IS122: 2302000 | IT122: 3.8 | IW122: 43240000 | IX122: 86.3 | IY122: 41652000 | IZ122: 83.2 | JA122: 1588000 | JB122: 3.7 | JD122: 40664000 | JE122: 88.5 | JF122: 39324000 | JG122: 85.6 | JH122: 1340000 | JI122: 3.3 | JM122: 45796000 | JN122: 40012000 | JO122: 18158000 | JP122: 1042000 | JQ122: 96200 | JY122: 2449000 | KG122: 14667000 | KH122: 8089000 | KY122: 6578000 | LJ122: 21854000 | LK122: 9760000 | LL122: 2253200 | LP122: 4520800 | MI122: 1498800 | MS122: 1693000 | MZ122: 1758000 | NN122: 2963000 | OL122: 2120000 | PI122: 2731000 | PQ122: 829000 | PU122: 5784000 | PV122: 1964000 | PW122: 1482400 | PX122: 481300 | QG122: 45294000 | QH122: 39489000 | QI122: 17741000 | QJ122: 1036000 | QK122: 88900 | QS122: 2264000 | RA122: 14441000 | RB122: 8073000 | RS122: 6368000 | SD122: 21748000 | SE122: 9753000 | SF122: 2241100 | SJ122: 4544700 | TC122: 1480700 | TM122: 1671000 | TT122: 1758000 | UH122: 2923000 | VF122: 2090000 | WB122: 2736000 | WJ122: 817000 | WN122: 5805000 | WO122: 1998000 | WP122: 1487300 | WQ122: 485900
C123: 17807 | V123: 1210000 | W123: 655000 | X123: 324000 | Y123: 188000 | Z123: 136000 | AA123: 9.5 | AC123: 55.3 | AD123: 29.9 | AE123: 14.8 | AF123: 8.6 | AG123: 6.2 | AH123: 39881000 | AI123: 45693000 | AJ123: 17987000 | AK123: 1031000 | AL123: 97500 | AT123: 2413000 | BB123: 14543000 | BC123: 8108000 | BT123: 6435000 | CE123: 21894000 | CF123: 9855000 | CG123: 2275200 | CK123: 4597700 | DD123: 1494000 | DN123: 1684000 | DU123: 1745000 | EI123: 2936000 | FG123: 2093000 | GD123: 2763000 | GL123: 818000 | GP123: 5812000 | GQ123: 1967000 | GR123: 1489600 | GS123: 477300 | IO123: 60646000 | IP123: 58.7 | IQ123: 58387000 | IR123: 56.5 | IS123: 2259000 | IT123: 3.7 | IW123: 43396000 | IX123: 86.6 | IY123: 41823000 | IZ123: 83.5 | JA123: 1573000 | JB123: 3.6 | JD123: 40857000 | JE123: 88.8 | JF123: 39522000 | JG123: 85.9 | JH123: 1335000 | JI123: 3.3 | JM123: 45693000 | JN123: 39881000 | JO123: 17987000 | JP123: 1031000 | JQ123: 97500 | JY123: 2413000 | KG123: 14543000 | KH123: 8108000 | KY123: 6435000 | LJ123: 21894000 | LK123: 9855000 | LL123: 2275200 | LP123: 4597700 | MI123: 1494000 | MS123: 1684000 | MZ123: 1745000 | NN123: 2936000 | OL123: 2093000 | PI123: 2763000 | PQ123: 818000 | PU123: 5812000 | PV123: 1967000 | PW123: 1489600 | PX123: 477300 | QG123: 45245000 | QH123: 39416000 | QI123: 17683000 | QJ123: 1030000 | QK123: 89500 | QS123: 2263000 | RA123: 14390000 | RB123: 8102000 | RS123: 6288000 | SD123: 21733000 | SE123: 9759000 | SF123: 2242800 | SJ123: 4544500 | TC123: 1479600 | TM123: 1670000 | TT123: 1749000 | UH123: 2917000 | VF123: 2087000 | WB123: 2735000 | WJ123: 816000 | WN123: 5829000 | WO123: 2011000 | WP123: 1501400 | WQ123: 482100
C124: 17838 | V124: 1251000 | W124: 682000 | X124: 282000 | Y124: 187000 | Z124: 95000 | AA124: 7.8 | AC124: 56.5 | AD124: 30.8 | AE124: 12.7 | AF124: 8.4 | AG124: 4.3 | AH124: 39763000 | AI124: 45588000 | AJ124: 17781000 | AK124: 1026000 | AL124: 92700 | AT124: 2367000 | BB124: 14388000 | BC124: 8065000 | BT124: 6323000 | CE124: 21982000 | CF124: 9944000 | CG124: 2287900 | CK124: 4691100 | DD124: 1477400 | DN124: 1671000 | DU124: 1744000 | EI124: 2920000 | FG124: 2080000 | GD124: 2809000 | GL124: 814000 | GP124: 5825000 | GQ124: 1989000 | GR124: 1495500 | GS124: 493400 | IO124: 60702000 | IP124: 58.7 | IQ124: 58417000 | IR124: 56.5 | IS124: 2285000 | IT124: 3.8 | IW124: 43337000 | IX124: 86.5 | IY124: 41735000 | IZ124: 83.3 | JA124: 1602000 | JB124: 3.7 | JD124: 40816000 | JE124: 88.7 | JF124: 39459000 | JG124: 85.7 | JH124: 1357000 | JI124: 3.3 | JM124: 45588000 | JN124: 39763000 | JO124: 17781000 | JP124: 1026000 | JQ124: 92700 | JY124: 2367000 | KG124: 14388000 | KH124: 8065000 | KY124: 6323000 | LJ124: 21982000 | LK124: 9944000 | LL124: 2287900 | LP124: 4691100 | MI124: 1477400 | MS124: 1671000 | MZ124: 1744000 | NN124: 2920000 | OL124: 2080000 | PI124: 2809000 | PQ124: 814000 | PU124: 5825000 | PV124: 1989000 | PW124: 1495500 | PX124: 493400 | QG124: 45192000 | QH124: 39323000 | QI124: 17599000 | QJ124: 1027000 | QK124: 87700 | QS124: 2280000 | RA124: 14292000 | RB124: 8041000 | RS124: 6251000 | SD124: 21724000 | SE124: 9753000 | SF124: 2245000 | SJ124: 4547200 | TC124: 1470400 | TM124: 1663000 | TT124: 1752000 | UH124: 2915000 | VF124: 2088000 | WB124: 2737000 | WJ124: 816000 | WN124: 5869000 | WO124: 2029000 | WP124: 1512800 | WQ124: 491300
C125: 17868 | V125: 1432000 | W125: 696000 | X125: 305000 | Y125: 206000 | Z125: 99000 | AA125: 8.1 | AC125: 58.9 | AD125: 28.6 | AE125: 12.5 | AF125: 8.5 | AG125: 4.1 | AH125: 39946000 | AI125: 46074000 | AJ125: 17508000 | AK125: 1027000 | AL125: 82600 | AT125: 2278000 | BB125: 14203000 | BC125: 7971000 | BT125: 6232000 | CE125: 22438000 | CF125: 10255000 | CG125: 2276500 | CK125: 4994300 | DD125: 1464700 | DN125: 1668000 | DU125: 1746000 | EI125: 2917000 | FG125: 2073000 | GD125: 2968000 | GL125: 811000 | GP125: 6128000 | GQ125: 2285000 | GR125: 1504300 | GS125: 780400 | IO125: 61169000 | IP125: 59.1 | IQ125: 58740000 | IR125: 56.8 | IS125: 2429000 | IT125: 4 | IW125: 43544000 | IX125: 86.9 | IY125: 41861000 | IZ125: 83.5 | JA125: 1683000 | JB125: 3.9 | JD125: 40989000 | JE125: 89 | JF125: 39539000 | JG125: 85.8 | JH125: 1450000 | JI125: 3.5 | JM125: 46074000 | JN125: 39946000 | JO125: 17508000 | JP125: 1027000 | JQ125: 82600 | JY125: 2278000 | KG125: 14203000 | KH125: 7971000 | KY125: 6232000 | LJ125: 22438000 | LK125: 10255000 | LL125: 2276500 | LP125: 4994300 | MI125: 1464700 | MS125: 1668000 | MZ125: 1746000 | NN125: 2917000 | OL125: 2073000 | PI125: 2968000 | PQ125: 811000 | PU125: 6128000 | PV125: 2285000 | PW125: 1504300 | PX125: 780400 | QG125: 45032000 | QH125: 39144000 | QI125: 17417000 | QJ125: 1025000 | QK125: 83500 | QS125: 2306000 | RA125: 14086000 | RB125: 7898000 | RS125: 6188000 | SD125: 21727000 | SE125: 9739000 | SF125: 2236800 | SJ125: 4552600 | TC125: 1456700 | TM125: 1662000 | TT125: 1754000 | UH125: 2914000 | VF125: 2096000 | WB125: 2743000 | WJ125: 819000 | WN125: 5888000 | WO125: 2049000 | WP125: 1512600 | WQ125: 744600
... C149: 18598 | V149: 1459000 | W149: 725000 | X149: 482000 | Y149: 265000 | Z149: 217000 | AA149: 10.7 | AC149: 54.7 | AD149: 27.2 | AE149: 18.1 | AF149: 9.9 | AG149: 8.1 | AH149: 41316000 | AI149: 47931000 | AJ149: 18321000 | AK149: 962000 | AL149: 98600 | AT149: 2495000 | BB149: 14864000 | BC149: 8500000 | BT149: 6364000 | CE149: 22995000 | CF149: 10397000 | CG149: 2312000 | CK149: 5115100 | DD149: 1422900 | DN149: 1695000 | DU149: 1844000 | EI149: 3015000 | FG149: 2153000 | GD149: 3048000 | GL149: 843000 | GP149: 6615000 | GQ149: 2474000 | GR149: 1652200 | GS149: 821300 | IO149: 62068000 | IP149: 59.2 | IQ149: 59429000 | IR149: 56.7 | IS149: 2639000 | IT149: 4.3 | IW149: 43396000 | IX149: 86.3 | IY149: 41735000 | IZ149: 83 | JA149: 1661000 | JB149: 3.8 | JD149: 40963000 | JE149: 88.2 | JF149: 39536000 | JG149: 85.1 | JH149: 1427000 | JI149: 3.5 | JM149: 47931000 | JN149: 41316000 | JO149: 18321000 | JP149: 962000 | JQ149: 98600 | JY149: 2495000 | KG149: 14864000 | KH149: 8500000 | KY149: 6364000 | LJ149: 22995000 | LK149: 10397000 | LL149: 2312000 | LP149: 5115100 | MI149: 1422900 | MS149: 1695000 | MZ149: 1844000 | NN149: 3015000 | OL149: 2153000 | PI149: 3048000 | PQ149: 843000 | PU149: 6615000 | PV149: 2474000 | PW149: 1652200 | PX149: 821300 | QG149: 46861000 | QH149: 40547000 | QI149: 18283000 | QJ149: 959000 | QK149: 100800 | QS149: 2542000 | RA149: 14782000 | RB149: 8444000 | RS149: 6338000 | SD149: 22264000 | SE149: 9857000 | SF149: 2272900 | SJ149: 4651900 | TC149: 1414800 | TM149: 1689000 | TT149: 1852000 | UH149: 3017000 | VF149: 2178000 | WB149: 2818000 | WJ149: 853000 | WN149: 6314000 | WO149: 2190000 | WP149: 1655500 | WQ149: 782300
C150: 18629 | V150: 1115000 | W150: 687000 | X150: 438000 | Y150: 259000 | Z150: 179000 | AA150: 10.6 | AC150: 49.8 | AD150: 30.7 | AE150: 19.6 | AF150: 11.6 | AG150: 8 | AH150: 40337000 | AI150: 46686000 | AJ150: 18217000 | AK150: 956000 | AL150: 91800 | AT150: 2372000 | BB150: 14889000 | BC150: 8545000 | BE150: 519300 | BT150: 6344000 | CE150: 22120000 | CF150: 9836000 | CG150: 2288400 | CK150: 4616700 | DD150: 1391800 | DN150: 1685000 | DU150: 1837000 | EI150: 2990000 | FG150: 2146000 | GD150: 2785000 | GL150: 841000 | GP150: 6349000 | GQ150: 2180000 | GR150: 1698500 | GS150: 481300 | IO150: 61941000 | IP150: 59.1 | IQ150: 59636000 | IR150: 56.9 | IS150: 2305000 | IT150: 3.7 | IW150: 43193000 | IX150: 86 | IY150: 41754000 | IZ150: 83.1 | JA150: 1439000 | JB150: 3.3 | JD150: 40831000 | JE150: 88 | JF150: 39595000 | JG150: 85.4 | JH150: 1236000 | JI150: 3 | JM150: 46686000 | JN150: 40337000 | JO150: 18217000 | JP150: 956000 | JQ150: 91800 | JY150: 2372000 | KG150: 14889000 | KH150: 8545000 | KJ150: 519300 | KY150: 6344000 | LJ150: 22120000 | LK150: 9836000 | LL150: 2288400 | LP150: 4616700 | MI150: 1391800 | MS150: 1685000 | MZ150: 1837000 | NN150: 2990000 | OL150: 2146000 | PI150: 2785000 | PQ150: 841000 | PU150: 6349000 | PV150: 2180000 | PW150: 1698500 | PX150: 481300 | QG150: 47288000 | QH150: 40936000 | QI150: 18518000 | QJ150: 959000 | QK150: 103400 | QS150: 2609000 | RA150: 14950000 | RB150: 8546000 | RD150: 529700 | RS150: 6404000 | SD150: 22418000 | SE150: 9941000 | SF150: 2282100 | SJ150: 4696600 | TC150: 1421700 | TM150: 1701000 | TT150: 1857000 | UH150: 3037000 | VF150: 2187000 | WB150: 2838000 | WJ150: 857000 | WN150: 6352000 | WO150: 2225000 | WP150: 1716100 | WQ150: 484800
C151: 18660 | V151: 1107000 | W151: 608000 | X151: 386000 | Y151: 188000 | Z151: 198000 | AA151: 10.8 | AC151: 52.7 | AD151: 28.9 | AE151: 18.4 | AF151: 8.9 | AG151: 9.4 | AH151: 40449000 | AI151: 46833000 | AJ151: 18320000 | AK151: 956000 | AL151: 90600 | AT151: 2317000 | BB151: 15047000 | BC151: 8659000 | BE151: 518800 | BT151: 6388000 | CE151: 22129000 | CF151: 9827000 | CG151: 2293600 | CK151: 4592700 | DD151: 1391600 | DN151: 1695000 | DU151: 1846000 | EI151: 2998000 | FG151: 2148000 | GD151: 2773000 | GL151: 842000 | GP151: 6384000 | GQ151: 2247000 | GR151: 1763600 | GS151: 483300 | IO151: 61778000 | IP151: 59.1 | IQ151: 59661000 | IR151: 57 | IS151: 2117000 | IT151: 3.4 | IW151: 43108000 | IX151: 86.3 | IY151: 41826000 | IZ151: 83.7 | JA151: 1282000 | JB151: 3 | JD151: 40791000 | JE151: 88.4 | JF151: 39695000 | JG151: 86 | JH151: 1096000 | JI151: 2.7 | JM151: 46833000 | JN151: 40449000 | JO151: 18320000 | JP151: 956000 | JQ151: 90600 | JY151: 2317000 | KG151: 15047000 | KH151: 8659000 | KJ151: 518800 | KY151: 6388000 | LJ151: 22129000 | LK151: 9827000 | LL151: 2293600 | LP151: 4592700 | MI151: 1391600 | MS151: 1695000 | MZ151: 1846000 | NN151: 2998000 | OL151: 2148000 | PI151: 2773000 | PQ151: 842000 | PU151: 6384000 | PV151: 2247000 | PW151: 1763600 | PX151: 483300 | QG151: 47577000 | QH151: 41195000 | QI151: 18666000 | QJ151: 962000 | QK151: 103900 | QS151: 2628000 | RA151: 15076000 | RB151: 8645000 | RD151: 530000 | RS151: 6431000 | SD151: 22529000 | SE151: 9996000 | SF151: 2294600 | SJ151: 4722400 | TC151: 1428700 | TM151: 1713000 | TT151: 1864000 | UH151: 3049000 | VF151: 2195000 | WB151: 2853000 | WJ151: 859000 | WN151: 6382000 | WO151: 2273000 | WP151: 1769000 | WQ151: 485500
C152: 18688 | V152: 1215000 | W152: 558000 | X152: 355000 | Y152: 202000 | Z152: 153000 | AA152: 10.1 | AC152: 57.1 | AD152: 26.2 | AE152: 16.7 | AF152: 9.5 | AG152: 7.2 | AH152: 40851000 | AI152: 47312000 | AJ152: 18451000 | AK152: 955000 | AL152: 88100 | AT152: 2411000 | BB152: 15085000 | BC152: 8747000 | BE152: 527200 | BT152: 6338000 | CE152: 22400000 | CF152: 9960000 | CG152: 2293900 | CK152: 4693500 | DD152: 1413300 | DN152: 1708000 | DU152: 1858000 | EI152: 3024000 | FG152: 2169000 | GD152: 2831000 | GL152: 850000 | GP152: 6461000 | GQ152: 2299000 | GR152: 1816600 | GS152: 482800 | IO152: 62526000 | IP152: 59.8 | IQ152: 60401000 | IR152: 57.7 | IS152: 2125000 | IT152: 3.4 | IW152: 43373000 | IX152: 86.9 | IY152: 42188000 | IZ152: 84.5 | JA152: 1185000 | JB152: 2.7 | JD152: 41020000 | JE152: 88.8 | JF152: 40013000 | JG152: 86.6 | JH152: 1007000 | JI152: 2.5 | JM152: 47312000 | JN152: 40851000 | JO152: 18451000 | JP152: 955000 | JQ152: 88100 | JY152: 2411000 | KG152: 15085000 | KH152: 8747000 | KJ152: 527200 | KY152: 6338000 | LJ152: 22400000 | LK152: 9960000 | LL152: 2293900 | LP152: 4693500 | MI152: 1413300 | MS152: 1708000 | MZ152: 1858000 | NN152: 3024000 | OL152: 2169000 | PI152: 2831000 | PQ152: 850000 | PU152: 6461000 | PV152: 2299000 | PW152: 1816600 | PX152: 482800 | QG152: 47873000 | QH152: 41463000 | QI152: 18754000 | QJ152: 959000 | QK152: 99900 | QS152: 2670000 | RA152: 15125000 | RB152: 8718000 | RD152: 532500 | RS152: 6407000 | SD152: 22709000 | SE152: 10092000 | SF152: 2303700 | SJ152: 4799200 | TC152: 1446000 | TM152: 1722000 | TT152: 1869000 | UH152: 3065000 | VF152: 2204000 | WB152: 2894000 | WJ152: 863000 | WN152: 6410000 | WO152: 2315000 | WP152: 1816200 | WQ152: 484800
C153: 18719 | V153: 1160000 | W153: 503000 | X153: 294000 | Y153: 154000 | Z153: 140000 | AA153: 10.6 | AC153: 59.3 | AD153: 25.7 | AE153: 15 | AF153: 7.9 | AG153: 7.2 | AH153: 40988000 | AI153: 47505000 | AJ153: 18537000 | AK153: 942000 | AL153: 97800 | AT153: 2563000 | BB153: 15032000 | BC153: 8774000 | BE153: 531800 | BT153: 6258000 | CE153: 22451000 | CF153: 9926000 | CG153: 2287000 | CK153: 4651000 | DD153: 1424400 | DN153: 1713000 | DU153: 1871000 | EI153: 3054000 | FG153: 2206000 | GD153: 2818000 | GL153: 863000 | GP153: 6517000 | GQ153: 2346000 | GR153: 1859000 | GS153: 486500 | IO153: 61808000 | IP153: 59.1 | IQ153: 59889000 | IR153: 57.3 | IS153: 1919000 | IT153: 3.1 | IW153: 42966000 | IX153: 86.3 | IY153: 41877000 | IZ153: 84.1 | JA153: 1089000 | JB153: 2.5 | JD153: 40714000 | JE153: 88.3 | JF153: 39804000 | JG153: 86.3 | JH153: 910000 | JI153: 2.2 | JM153: 47505000 | JN153: 40988000 | JO153: 18537000 | JP153: 942000 | JQ153: 97800 | JY153: 2563000 | KG153: 15032000 | KH153: 8774000 | KJ153: 531800 | KY153: 6258000 | LJ153: 22451000 | LK153: 9926000 | LL153: 2287000 | LP153: 4651000 | MI153: 1424400 | MS153: 1713000 | MZ153: 1871000 | NN153: 3054000 | OL153: 2206000 | PI153: 2818000 | PQ153: 863000 | PU153: 6517000 | PV153: 2346000 | PW153: 1859000 | PX153: 486500 | QG153: 47861000 | QH153: 41410000 | QI153: 18810000 | QJ153: 948000 | QK153: 111100 | QS153: 2696000 | RA153: 15166000 | RB153: 8763000 | RD153: 533400 | RS153: 6403000 | SD153: 22600000 | SE153: 10031000 | SF153: 2312800 | SJ153: 4676400 | TC153: 1436400 | TM153: 1726000 | TT153: 1873000 | UH153: 3070000 | VF153: 2208000 | WB153: 2828000 | WJ153: 864000 | WN153: 6451000 | WO153: 2357000 | WP153: 1852700 | WQ153: 487200
C154: 18749 | V154: 1125000 | W154: 490000 | X154: 269000 | Y154: 139000 | Z154: 130000 | AA154: 9.9 | AC154: 59.7 | AD154: 26 | AE154: 14.3 | AF154: 7.4 | AG154: 6.9 | AH154: 41186000 | AI154: 47624000 | AJ154: 18605000 | AK154: 948000 | AL154: 110100 | AT154: 2697000 | BB154: 14960000 | BC154: 8754000 | BE154: 532200 | BT154: 6206000 | CE154: 22581000 | CF154: 9965000 | CG154: 2277800 | CK154: 4696000 | DD154: 1425000 | DN154: 1712000 | DU154: 1879000 | EI154: 3074000 | FG154: 2230000 | GD154: 2848000 | GL154: 873000 | GP154: 6438000 | GQ154: 2380000 | GR154: 1894600 | GS154: 485500 | IO154: 62044000 | IP154: 59.4 | IQ154: 60188000 | IR154: 57.6 | IS154: 1856000 | IT154: 3 | IW154: 43031000 | IX154: 86.6 | IY154: 41972000 | IZ154: 84.5 | JA154: 1059000 | JB154: 2.5 | JD154: 40650000 | JE154: 88.4 | JF154: 39752000 | JG154: 86.5 | JH154: 898000 | JI154: 2.2 | JM154: 47624000 | JN154: 41186000 | JO154: 18605000 | JP154: 948000 | JQ154: 110100 | JY154: 2697000 | KG154: 14960000 | KH154: 8754000 | KJ154: 532200 | KY154: 6206000 | LJ154: 22581000 | LK154: 9965000 | LL154: 2277800 | LP154: 4696000 | MI154: 1425000 | MS154: 1712000 | MZ154: 1879000 | NN154: 3074000 | OL154: 2230000 | PI154: 2848000 | PQ154: 873000 | PU154: 6438000 | PV154: 2380000 | PW154: 1894600 | PX154: 485500 | QG154: 47952000 | QH154: 41535000 | QI154: 18829000 | QJ154: 954000 | QK154: 109100 | QS154: 2711000 | RA154: 15164000 | RB154: 8771000 | RD154: 533800 | RS154: 6393000 | SD154: 22706000 | SE154: 10080000 | SF154: 2314800 | SJ154: 4756000 | TC154: 1421000 | TM154: 1723000 | TT154: 1879000 | UH154: 3073000 | VF154: 2212000 | WB154: 2873000 | WJ154: 866000 | WN154: 6417000 | WO154: 2403000 | WP154: 1889200 | WQ154: 487500
C155: 18780 | V155: 1125000 | W155: 656000 | X155: 258000 | Y155: 143000 | Z155: 115000 | AA155: 8.7 | AC155: 55.2 | AD155: 32.2 | AE155: 12.7 | AF155: 7 | AG155: 5.6 | AH155: 41606000 | AI155: 48059000 | AJ155: 18844000 | AK155: 963000 | AL155: 115300 | AT155: 2793000 | BB155: 15088000 | BC155: 8796000 | BE155: 534000 | BT155: 6292000 | CE155: 22762000 | CF155: 10029000 | CG155: 2291500 | CK155: 4726300 | DD155: 1430100 | DN155: 1725000 | DU155: 1899000 | EI155: 3104000 | FG155: 2254000 | GD155: 2869000 | GL155: 882000 | GP155: 6453000 | GQ155: 2422000 | GR155: 1938400 | GS155: 483700 | IO155: 61615000 | IP155: 59 | IQ155: 59620000 | IR155: 57.1 | IS155: 1995000 | IT155: 3.2 | IW155: 42858000 | IX155: 86.4 | IY155: 41672000 | IZ155: 84 | JA155: 1186000 | JB155: 2.8 | JD155: 40532000 | JE155: 88.4 | JF155: 39538000 | JG155: 86.2 | JH155: 994000 | JI155: 2.5 | JM155: 48059000 | JN155: 41606000 | JO155: 18844000 | JP155: 963000 | JQ155: 115300 | JY155: 2793000 | KG155: 15088000 | KH155: 8796000 | KJ155: 534000 | KY155: 6292000 | LJ155: 22762000 | LK155: 10029000 | LL155: 2291500 | LP155: 4726300 | MI155: 1430100 | MS155: 1725000 | MZ155: 1899000 | NN155: 3104000 | OL155: 2254000 | PI155: 2869000 | PQ155: 882000 | PU155: 6453000 | PV155: 2422000 | PW155: 1938400 | PX155: 483700 | QG155: 48064000 | QH155: 41565000 | QI155: 18826000 | QJ155: 958000 | QK155: 106000 | QS155: 2692000 | RA155: 15176000 | RB155: 8789000 | RD155: 531400 | RS155: 6387000 | SD155: 22739000 | SE155: 10083000 | SF155: 2317700 | SJ155: 4767000 | TC155: 1416900 | TM155: 1725000 | TT155: 1886000 | UH155: 3077000 | VF155: 2219000 | WB155: 2880000 | WJ155: 869000 | WN155: 6499000 | WO155: 2436000 | WP155: 1920300 | WQ155: 485400
C156: 18810 | V156: 1183000 | W156: 480000 | X156: 260000 | Y156: 133000 | Z156: 127000 | AA156: 9.2 | AC156: 61.5 | AD156: 25 | AE156: 13.5 | AF156: 6.9 | AG156: 6.6 | AH156: 41546000 | AI156: 47888000 | AJ156: 18786000 | AK156: 946000 | AL156: 112000 | AT156: 2867000 | BB156: 14973000 | BC156: 8664000 | BE156: 526600 | BT156: 6309000 | CE156: 22760000 | CF156: 10005000 | CG156: 2306400 | CK156: 4683600 | DD156: 1429300 | DN156: 1723000 | DU156: 1920000 | EI156: 3111000 | FG156: 2266000 | GD156: 2848000 | GL156: 887000 | GP156: 6342000 | GQ156: 2444000 | GR156: 1954400 | GS156: 489800 | IO156: 62106000 | IP156: 59.4 | IQ156: 60156000 | IR156: 57.6 | IS156: 1950000 | IT156: 3.1 | IW156: 42786000 | IX156: 86.3 | IY156: 41614000 | IZ156: 83.9 | JA156: 1172000 | JB156: 2.7 | JD156: 40444000 | JE156: 88.2 | JF156: 39483000 | JG156: 86.1 | JH156: 961000 | JI156: 2.4 | JM156: 47888000 | JN156: 41546000 | JO156: 18786000 | JP156: 946000 | JQ156: 112000 | JY156: 2867000 | KG156: 14973000 | KH156: 8664000 | KJ156: 526600 | KY156: 6309000 | LJ156: 22760000 | LK156: 10005000 | LL156: 2306400 | LP156: 4683600 | MI156: 1429300 | MS156: 1723000 | MZ156: 1920000 | NN156: 3111000 | OL156: 2266000 | PI156: 2848000 | PQ156: 887000 | PU156: 6342000 | PV156: 2444000 | PW156: 1954400 | PX156: 489800 | QG156: 48061000 | QH156: 41523000 | QI156: 18747000 | QJ156: 945000 | QK156: 102300 | QS156: 2692000 | RA156: 15110000 | RB156: 8761000 | RD156: 528200 | RS156: 6349000 | SD156: 22776000 | SE156: 10100000 | SF156: 2324300 | SJ156: 4771500 | TC156: 1413200 | TM156: 1722000 | TT156: 1892000 | UH156: 3082000 | VF156: 2226000 | WB156: 2883000 | WJ156: 871000 | WN156: 6538000 | WO156: 2466000 | WP156: 1939300 | WQ156: 491700
C157: 18841 | V157: 1184000 | W157: 522000 | X157: 249000 | Y157: 132000 | Z157: 117000 | AA157: 9.1 | AC157: 60.6 | AD157: 26.7 | AE157: 12.7 | AF157: 6.8 | AG157: 6 | AH157: 41874000 | AI157: 48195000 | AJ157: 19079000 | AK157: 966000 | AL157: 112800 | AT157: 2929000 | BB157: 15184000 | BC157: 8716000 | BE157: 532100 | BT157: 6468000 | CE157: 22795000 | CF157: 10007000 | CG157: 2312400 | CK157: 4669200 | DD157: 1430000 | DN157: 1735000 | DU157: 1928000 | EI157: 3125000 | FG157: 2270000 | GD157: 2841000 | GL157: 889000 | GP157: 6321000 | GQ157: 2452000 | GR157: 1961200 | GS157: 490300 | IO157: 61927000 | IP157: 59.2 | IQ157: 59994000 | IR157: 57.4 | IS157: 1933000 | IT157: 3.1 | IW157: 42879000 | IX157: 86.5 | IY157: 41689000 | IZ157: 84.1 | JA157: 1190000 | JB157: 2.8 | JD157: 40510000 | JE157: 88.4 | JF157: 39508000 | JG157: 86.2 | JH157: 1002000 | JI157: 2.5 | JM157: 48195000 | JN157: 41874000 | JO157: 19079000 | JP157: 966000 | JQ157: 112800 | JY157: 2929000 | KG157: 15184000 | KH157: 8716000 | KJ157: 532100 | KY157: 6468000 | LJ157: 22795000 | LK157: 10007000 | LL157: 2312400 | LP157: 4669200 | MI157: 1430000 | MS157: 1735000 | MZ157: 1928000 | NN157: 3125000 | OL157: 2270000 | PI157: 2841000 | PQ157: 889000 | PU157: 6321000 | PV157: 2452000 | PW157: 1961200 | PX157: 490300 | QG157: 48012000 | QH157: 41493000 | QI157: 18709000 | QJ157: 959000 | QK157: 101400 | QS157: 2689000 | RA157: 15061000 | RB157: 8768000 | RD157: 525900 | RS157: 6293000 | SD157: 22784000 | SE157: 10083000 | SF157: 2315800 | SJ157: 4775900 | TC157: 1408000 | TM157: 1717000 | TT157: 1899000 | UH157: 3087000 | VF157: 2235000 | WB157: 2888000 | WJ157: 875000 | WN157: 6519000 | WO157: 2473000 | WP157: 1949200 | WQ157: 493500
C158: 18872 | V158: 1294000 | W158: 549000 | X158: 223000 | Y158: 105000 | Z158: 118000 | AA158: 9.1 | AC158: 62.6 | AD158: 26.6 | AE158: 10.8 | AF158: 5.1 | AG158: 5.7 | AH158: 41975000 | AI158: 48486000 | AJ158: 19072000 | AK158: 959000 | AL158: 118600 | AT158: 2890000 | BB158: 15223000 | BC158: 8749000 | BE158: 529600 | BT158: 6474000 | CE158: 22903000 | CF158: 10102000 | CG158: 2315900 | CK158: 4760100 | DD158: 1419500 | DN158: 1736000 | DU158: 1908000 | EI158: 3122000 | FG158: 2262000 | GD158: 2887000 | GL158: 886000 | GP158: 6511000 | GQ158: 2440000 | GR158: 1950000 | GS158: 490000 | IO158: 61780000 | IP158: 59.1 | IQ158: 59713000 | IR158: 57.1 | IS158: 2067000 | IT158: 3.3 | IW158: 42827000 | IX158: 86.4 | IY158: 41625000 | IZ158: 84 | JA158: 1202000 | JB158: 2.8 | JD158: 40429000 | JE158: 88.2 | JF158: 39416000 | JG158: 86 | JH158: 1013000 | JI158: 2.5 | JM158: 48486000 | JN158: 41975000 | JO158: 19072000 | JP158: 959000 | JQ158: 118600 | JY158: 2890000 | KG158: 15223000 | KH158: 8749000 | KJ158: 529600 | KY158: 6474000 | LJ158: 22903000 | LK158: 10102000 | LL158: 2315900 | LP158: 4760100 | MI158: 1419500 | MS158: 1736000 | MZ158: 1908000 | NN158: 3122000 | OL158: 2262000 | PI158: 2887000 | PQ158: 886000 | PU158: 6511000 | PV158: 2440000 | PW158: 1950000 | PX158: 490000 | QG158: 47954000 | QH158: 41402000 | QI158: 18622000 | QJ158: 952000 | QK158: 109100 | QS158: 2674000 | RA158: 14996000 | RB158: 8755000 | RD158: 521700 | RS158: 6241000 | SD158: 22780000 | SE158: 10084000 | SF158: 2309600 | SJ158: 4774400 | TC158: 1398900 | TM158: 1714000 | TT158: 1906000 | UH158: 3082000 | VF158: 2233000 | WB158: 2887000 | WJ158: 874000 | WN158: 6552000 | WO158: 2478000 | WP158: 1953200 | WQ158: 494400
C159: 18902 | V159: 1279000 | W159: 627000 | X159: 269000 | Y159: 170000 | Z159: 99000 | AA159: 8.9 | AC159: 58.8 | AD159: 28.8 | AE159: 12.4 | AF159: 7.8 | AG159: 4.6 | AH159: 41958000 | AI159: 48550000 | AJ159: 18999000 | AK159: 958000 | AL159: 117900 | AT159: 2888000 | BB159: 15153000 | BC159: 8782000 | BE159: 526600 | BT159: 6371000 | CE159: 22959000 | CF159: 10189000 | CG159: 2352300 | CK159: 4818700 | DD159: 1402500 | DN159: 1729000 | DU159: 1903000 | EI159: 3105000 | FG159: 2244000 | GD159: 2911000 | GL159: 878000 | GP159: 6592000 | GQ159: 2445000 | GR159: 1954700 | GS159: 490500 | IO159: 62204000 | IP159: 59.4 | IQ159: 60010000 | IR159: 57.3 | IS159: 2194000 | IT159: 3.5 | IW159: 43038000 | IX159: 86.8 | IY159: 41705000 | IZ159: 84.1 | JA159: 1333000 | JB159: 3.1 | JD159: 40702000 | JE159: 88.6 | JF159: 39555000 | JG159: 86.1 | JH159: 1147000 | JI159: 2.8 | JM159: 48550000 | JN159: 41958000 | JO159: 18999000 | JP159: 958000 | JQ159: 117900 | JY159: 2888000 | KG159: 15153000 | KH159: 8782000 | KJ159: 526600 | KY159: 6371000 | LJ159: 22959000 | LK159: 10189000 | LL159: 2352300 | LP159: 4818700 | MI159: 1402500 | MS159: 1729000 | MZ159: 1903000 | NN159: 3105000 | OL159: 2244000 | PI159: 2911000 | PQ159: 878000 | PU159: 6592000 | PV159: 2445000 | PW159: 1954700 | PX159: 490500 | QG159: 48006000 | QH159: 41429000 | QI159: 18630000 | QJ159: 958000 | QK159: 110100 | QS159: 2699000 | RA159: 14973000 | RB159: 8755000 | RD159: 517900 | RS159: 6218000 | SD159: 22799000 | SE159: 10094000 | SF159: 2328700 | SJ159: 4774300 | TC159: 1384400 | TM159: 1713000 | TT159: 1906000 | UH159: 3085000 | VF159: 2238000 | WB159: 2887000 | WJ159: 876000 | WN159: 6577000 | WO159: 2493000 | WP159: 1966200 | WQ159: 495900
C160: 18933 | V160: 1233000 | W160: 630000 | X160: 316000 | Y160: 161000 | Z160: 155000 | AA160: 9.7 | AC160: 56.6 | AD160: 28.9 | AE160: 14.5 | AF160: 7.4 | AG160: 7.1 | AH160: 41970000 | AI160: 48621000 | AJ160: 18810000 | AK160: 961000 | AL160: 115100 | AT160: 2760000 | BB160: 15089000 | BC160: 8819000 | BE160: 518700 | BT160: 6270000 | CE160: 23160000 | CF160: 10349000 | CG160: 2392900 | CK160: 4934800 | DD160: 1390600 | DN160: 1726000 | DU160: 1912000 | EI160: 3098000 | FG160: 2233000 | GD160: 2967000 | GL160: 875000 | GP160: 6651000 | GQ160: 2461000 | GR160: 1959000 | GS160: 501900 | IO160: 62014000 | IP160: 59.2 | IQ160: 59836000 | IR160: 57.1 | IS160: 2178000 | IT160: 3.5 | IW160: 42906000 | IX160: 86.5 | IY160: 41591000 | IZ160: 83.8 | JA160: 1315000 | JB160: 3.1 | JD160: 40591000 | JE160: 88.4 | JF160: 39504000 | JG160: 86 | JH160: 1087000 | JI160: 2.7 | JM160: 48621000 | JN160: 41970000 | JO160: 18810000 | JP160: 961000 | JQ160: 115100 | JY160: 2760000 | KG160: 15089000 | KH160: 8819000 | KJ160: 518700 | KY160: 6270000 | LJ160: 23160000 | LK160: 10349000 | LL160: 2392900 | LP160: 4934800 | MI160: 1390600 | MS160: 1726000 | MZ160: 1912000 | NN160: 3098000 | OL160: 2233000 | PI160: 2967000 | PQ160: 875000 | PU160: 6651000 | PV160: 2461000 | PW160: 1959000 | PX160: 501900 | QG160: 48147000 | QH160: 41521000 | QI160: 18617000 | QJ160: 958000 | QK160: 110000 | QS160: 2660000 | RA160: 14999000 | RB160: 8782000 | RD160: 512800 | RS160: 6217000 | SD160: 22904000 | SE160: 10149000 | SF160: 2352900 | SJ160: 4794300 | TC160: 1380400 | TM160: 1718000 | TT160: 1921000 | UH160: 3095000 | VF160: 2244000 | WB160: 2898000 | WJ160: 879000 | WN160: 6626000 | WO160: 2505000 | WP160: 1975600 | WQ160: 499600
