Workbook
Name Ann3_Core: OFFSET('Calc Engine'!$AV$6,PPI_N-24,0,24,1)
Name Ann3_Headline: OFFSET('Calc Engine'!$AS$6,PPI_N-24,0,24,1)
Name Ann6_Core: OFFSET('Calc Engine'!$BJ$6,PPI_N-24,0,24,1)
Name Ann6_Headline: OFFSET('Calc Engine'!$BG$6,PPI_N-24,0,24,1)
Name ChartDates: OFFSET('Calc Engine'!$P$6,PPI_N-24,0,24,1)
Name Macrobond_Object1: 'Macrobond Imports'!$A$3:$GW$953
Name MM_Core: OFFSET('Calc Engine'!$T$6,PPI_N-24,0,24,1)
Name MM_Headline: OFFSET('Calc Engine'!$Q$6,PPI_N-24,0,24,1)
Name PPI_N: COUNT('Calc Engine'!$A$6:$A$960)
Name Transport_YY: OFFSET('Calc Engine'!$CB$6,PPI_N-24,0,24,1)
Name UnprocEnergy_YY: OFFSET('Calc Engine'!$CA$6,PPI_N-24,0,24,1)
Name YY_Core: OFFSET('Calc Engine'!$AH$6,PPI_N-24,0,24,1)
Name YY_Headline: OFFSET('Calc Engine'!$AE$6,PPI_N-24,0,24,1)

Sheet Dashboard
A1: US PPI — MORNING DASHBOARD | J1: Latest data: | L1: {=INDEX('Calc Engine'!A6:A960,PPI_N)} -> 46113
A2: Final Demand – Intermediate Demand (FD-ID) system | Source: BLS via Macrobond | Auto-refresh on import
A4: HEADLINE READ — latest month | J4: MOMENTUM & BASE EFFECTS
A5: Series | B5: Index | C5: M/M | D5: Y/Y | E5: 3m ann. | F5: 6m ann. | G5: Prior M/M | H5: Momentum | J5: Series | K5: M/M | L5: 3m ann. | M5: 6m ann. | N5: Y/Y | O5: 3m vs 6m
A6: Headline Final Demand | B6: {=INDEX('Calc Engine'!B:B,PPI_N+5)} -> 156.496 | C6: {=INDEX('Calc Engine'!Q:Q,PPI_N+5)} -> 0.013758972 | D6: {=INDEX('Calc Engine'!AE:AE,PPI_N+5)} -> 0.059876062 | E6: {=INDEX('Calc Engine'!AS:AS,PPI_N+5)} -> 0.110898 | F6: {=INDEX('Calc Engine'!BG:BG,PPI_N+5)} -> 0.082145374 | G6: {=INDEX('Calc Engine'!Q:Q,PPI_N+4)} -> 0.0069928245 | H6: =IF(OR(E6="",F6=""),"",IF(E6>F6,"▲ ACCEL","▼ decel")) -> ▲ ACCEL | J6: Headline FD | K6: =C6 -> 0.013758972 | L6: =E6 -> 0.110898 | M6: =F6 -> 0.082145374 | N6: =D6 -> 0.059876062 | O6: =IF(OR(L6="",M6=""),"",IF(L6>M6,"▲ ACCEL","▼ decel")) -> ▲ ACCEL
A7: Core FD (ex Food & Energy) | B7: {=INDEX('Calc Engine'!E:E,PPI_N+5)} -> 154.056 | C7: {=INDEX('Calc Engine'!T:T,PPI_N+5)} -> 0.010329156 | D7: {=INDEX('Calc Engine'!AH:AH,PPI_N+5)} -> 0.05240291 | E7: {=INDEX('Calc Engine'!AV:AV,PPI_N+5)} -> 0.067041328 | F7: {=INDEX('Calc Engine'!BJ:BJ,PPI_N+5)} -> 0.065881647 | G7: {=INDEX('Calc Engine'!T:T,PPI_N+4)} -> 0.0022742959 | H7: =IF(OR(E7="",F7=""),"",IF(E7>F7,"▲ ACCEL","▼ decel")) -> ▲ ACCEL | J7: Core (ex F&E) | K7: =C7 -> 0.010329156 | L7: =E7 -> 0.067041328 | M7: =F7 -> 0.065881647 | N7: =D7 -> 0.05240291 | O7: =IF(OR(L7="",M7=""),"",IF(L7>M7,"▲ ACCEL","▼ decel")) -> ▲ ACCEL
A8: FD ex Food | B8: {=INDEX('Calc Engine'!F:F,PPI_N+5)} -> 153.992 | C8: {=INDEX('Calc Engine'!U:U,PPI_N+5)} -> 0.014413322 | D8: {=INDEX('Calc Engine'!AI:AI,PPI_N+5)} -> 0.061984497 | E8: {=INDEX('Calc Engine'!AW:AW,PPI_N+5)} -> 0.11276566 | F8: {=INDEX('Calc Engine'!BK:BK,PPI_N+5)} -> 0.086558325 | G8: {=INDEX('Calc Engine'!U:U,PPI_N+4)} -> 0.0077537906 | H8: =IF(OR(E8="",F8=""),"",IF(E8>F8,"▲ ACCEL","▼ decel")) -> ▲ ACCEL | J8: FD ex Food, Energy & Trade | K8: =C11 -> 0.0056604983 | L8: =E11 -> 0.052884395 | M8: =F11 -> 0.044492549 | N8: =D11 -> 0.044357194 | O8: =IF(OR(L8="",M8=""),"",IF(L8>M8,"▲ ACCEL","▼ decel")) -> ▲ ACCEL
A9: FD ex Energy | B9: {=INDEX('Calc Engine'!G:G,PPI_N+5)} -> 154.102 | C9: {=INDEX('Calc Engine'!V:V,PPI_N+5)} -> 0.0098691971 | D9: {=INDEX('Calc Engine'!AJ:AJ,PPI_N+5)} -> 0.050736051 | E9: {=INDEX('Calc Engine'!AX:AX,PPI_N+5)} -> 0.067696342 | F9: {=INDEX('Calc Engine'!BL:BL,PPI_N+5)} -> 0.062455932 | G9: {=INDEX('Calc Engine'!V:V,PPI_N+4)} -> 0.0017922441 | H9: =IF(OR(E9="",F9=""),"",IF(E9>F9,"▲ ACCEL","▼ decel")) -> ▲ ACCEL | J9: FD Goods | K9: =C12 -> 0.019600916 | L9: =E12 -> 0.21435262 | M9: =F12 -> 0.1145686 | N9: =D12 -> 0.073903846 | O9: =IF(OR(L9="",M9=""),"",IF(L9>M9,"▲ ACCEL","▼ decel")) -> ▲ ACCEL
A10: FD ex Trade Services | B10: {=INDEX('Calc Engine'!H:H,PPI_N+5)} -> 151.521 | C10: {=INDEX('Calc Engine'!W:W,PPI_N+5)} -> 0.010577917 | D10: {=INDEX('Calc Engine'!AK:AK,PPI_N+5)} -> 0.05473416 | E10: {=INDEX('Calc Engine'!AY:AY,PPI_N+5)} -> 0.10915644 | F10: {=INDEX('Calc Engine'!BM:BM,PPI_N+5)} -> 0.067358836 | G10: {=INDEX('Calc Engine'!W:W,PPI_N+4)} -> 0.0080341536 | H10: =IF(OR(E10="",F10=""),"",IF(E10>F10,"▲ ACCEL","▼ decel")) -> ▲ ACCEL | J10: FD Services | K10: =C13 -> 0.011797935 | L10: =E13 -> 0.073285997 | M10: =F13 -> 0.070819385 | N10: =D13 -> 0.054866574 | O10: =IF(OR(L10="",M10=""),"",IF(L10>M10,"▲ ACCEL","▼ decel")) -> ▲ ACCEL
A11: FD ex Food, Energy & Trade | B11: {=INDEX('Calc Engine'!I:I,PPI_N+5)} -> 141.242 | C11: {=INDEX('Calc Engine'!X:X,PPI_N+5)} -> 0.0056604983 | D11: {=INDEX('Calc Engine'!AL:AL,PPI_N+5)} -> 0.044357194 | E11: {=INDEX('Calc Engine'!AZ:AZ,PPI_N+5)} -> 0.052884395 | F11: {=INDEX('Calc Engine'!BN:BN,PPI_N+5)} -> 0.044492549 | G11: {=INDEX('Calc Engine'!X:X,PPI_N+4)} -> 0.0021334589 | H11: =IF(OR(E11="",F11=""),"",IF(E11>F11,"▲ ACCEL","▼ decel")) -> ▲ ACCEL
A12: FD Goods | B12: {=INDEX('Calc Engine'!C:C,PPI_N+5)} -> 155.846 | C12: {=INDEX('Calc Engine'!R:R,PPI_N+5)} -> 0.019600916 | D12: {=INDEX('Calc Engine'!AF:AF,PPI_N+5)} -> 0.073903846 | E12: {=INDEX('Calc Engine'!AT:AT,PPI_N+5)} -> 0.21435262 | F12: {=INDEX('Calc Engine'!BH:BH,PPI_N+5)} -> 0.1145686 | G12: {=INDEX('Calc Engine'!R:R,PPI_N+4)} -> 0.019027174 | H12: =IF(OR(E12="",F12=""),"",IF(E12>F12,"▲ ACCEL","▼ decel")) -> ▲ ACCEL
A13: FD Services | B13: {=INDEX('Calc Engine'!D:D,PPI_N+5)} -> 155.827 | C13: {=INDEX('Calc Engine'!S:S,PPI_N+5)} -> 0.011797935 | D13: {=INDEX('Calc Engine'!AG:AG,PPI_N+5)} -> 0.054866574 | E13: {=INDEX('Calc Engine'!AU:AU,PPI_N+5)} -> 0.073285997 | F13: {=INDEX('Calc Engine'!BI:BI,PPI_N+5)} -> 0.070819385 | G13: {=INDEX('Calc Engine'!S:S,PPI_N+4)} -> 0.0020886335 | H13: =IF(OR(E13="",F13=""),"",IF(E13>F13,"▲ ACCEL","▼ decel")) -> ▲ ACCEL
A14: FD Trade Services | B14: {=INDEX('Calc Engine'!J:J,PPI_N+5)} -> 170.285 | C14: {=INDEX('Calc Engine'!Y:Y,PPI_N+5)} -> 0.026771986 | D14: {=INDEX('Calc Engine'!AM:AM,PPI_N+5)} -> 0.081181468 | E14: {=INDEX('Calc Engine'!BA:BA,PPI_N+5)} -> 0.11781475 | F14: {=INDEX('Calc Engine'!BO:BO,PPI_N+5)} -> 0.14522898 | G14: {=INDEX('Calc Engine'!Y:Y,PPI_N+4)} -> 0.0027753256 | H14: =IF(OR(E14="",F14=""),"",IF(E14>F14,"▲ ACCEL","▼ decel")) -> ▼ decel
A17: SURPRISE MATRIX vs STREET CONSENSUS
A18: Enter consensus (blue) from Bloomberg/survey. Surprise = Actual − Consensus, shown in bp.
A19: Metric | B19: Actual | C19: Consensus | D19: Surprise (bp) | E19: Signal
A20: Headline M/M | B20: =C6 -> 0.013758972 | D20: =IF(C20="","",(B20-C20)*10000) | E20: =IF(C20="","set cons.",IF(D20>0,"HOT ▲",IF(D20<0,"COOL ▼","in line"))) -> set cons.
A21: Headline Y/Y | B21: =D6 -> 0.059876062 | D21: =IF(C21="","",(B21-C21)*10000) | E21: =IF(C21="","set cons.",IF(D21>0,"HOT ▲",IF(D21<0,"COOL ▼","in line"))) -> set cons.
A22: Core M/M | B22: =C7 -> 0.010329156 | D22: =IF(C22="","",(B22-C22)*10000) | E22: =IF(C22="","set cons.",IF(D22>0,"HOT ▲",IF(D22<0,"COOL ▼","in line"))) -> set cons.
A23: Core Y/Y | B23: =D7 -> 0.05240291 | D23: =IF(C23="","",(B23-C23)*10000) | E23: =IF(C23="","set cons.",IF(D23>0,"HOT ▲",IF(D23<0,"COOL ▼","in line"))) -> set cons.
A26: MARGIN & PIPELINE TRACKER
A27: Trade services = wholesale/retail margins. Spread = Intermediate (input) − Final (output) inflation. Positive & widening spread → margin squeeze.
A28: Series | B28: M/M | C28: 3m ann. | D28: Y/Y
A29: Final Demand Trade Services | B29: {=INDEX('Calc Engine'!Y:Y,PPI_N+5)} -> 0.026771986 | C29: {=INDEX('Calc Engine'!BA:BA,PPI_N+5)} -> 0.11781475 | D29: {=INDEX('Calc Engine'!AM:AM,PPI_N+5)} -> 0.081181468
A30: Intermediate Processed Goods | B30: {=INDEX('Calc Engine'!Z:Z,PPI_N+5)} -> 0.026788339 | C30: {=INDEX('Calc Engine'!BB:BB,PPI_N+5)} -> 0.318865 | D30: {=INDEX('Calc Engine'!AN:AN,PPI_N+5)} -> 0.093267012
A31: Intermediate Unprocessed Goods | B31: {=INDEX('Calc Engine'!AA:AA,PPI_N+5)} -> 0.040827942 | C31: {=INDEX('Calc Engine'!BC:BC,PPI_N+5)} -> 0.6677408 | D31: {=INDEX('Calc Engine'!AO:AO,PPI_N+5)} -> 0.21226575
A32: SPREAD: Processed Interm − FD Goods | B32: {=INDEX('Calc Engine'!Z:Z,PPI_N+5)-INDEX('Calc Engine'!R:R,PPI_N+5)} -> 0.0071874235 | C32: {=INDEX('Calc Engine'!BB:BB,PPI_N+5)-INDEX('Calc Engine'!AT:AT,PPI_N+5)} -> 0.10451238 | D32: {=INDEX('Calc Engine'!AN:AN,PPI_N+5)-INDEX('Calc Engine'!AF:AF,PPI_N+5)} -> 0.019363166 | E32: =IF(D32="","",IF(D32>0,"⚠ Input>Output: margin squeeze","Output>Input: margin relief")) -> ⚠ Input>Output: margin squeeze
A33: SPREAD: Unprocessed − Processed | B33: {=INDEX('Calc Engine'!AA:AA,PPI_N+5)-INDEX('Calc Engine'!Z:Z,PPI_N+5)} -> 0.014039603 | C33: {=INDEX('Calc Engine'!BC:BC,PPI_N+5)-INDEX('Calc Engine'!BB:BB,PPI_N+5)} -> 0.3488758 | D33: {=INDEX('Calc Engine'!AO:AO,PPI_N+5)-INDEX('Calc Engine'!AN:AN,PPI_N+5)} -> 0.11899874 | E33: =IF(D33="","",IF(D33>0,"⚠ Early-stage pressure building","Early-stage easing")) -> ⚠ Early-stage pressure building
A75: CONTRIBUTION DECOMPOSITION — bp to Headline FD M/M
A76: Contribution = FD relative-importance weight × component M/M. M/M pulled live from Calc Engine where available (green). Weights = BLS FD-ID relative importance (Dec-2025 reweight); adjust in blue cells if BLS updates.
A77: Component | B77: FD weight | C77: M/M % | D77: Contrib (bp) | E77: % of headline
A78: Final Demand Goods | B78: 0.333 | C78: =C12 -> 0.019600916 | D78: =IF(OR(B78="",C78=""),"",B78*C78*10000) -> 65.27105 | E78: =IF(D78="","",D78/$D$83) -> 0.46598893
A79: Final Demand Services — of which: | B79: 0.634 | C79: =C13 -> 0.011797935 | D79: =IF(OR(B79="",C79=""),"",B79*C79*10000) -> 74.798909 | E79: =IF(D79="","",D79/$D$83) -> 0.53401107
A80: Trade services (margins) | B80: 0.195 | C80: =C14 -> 0.026771986 | D80: =IF(OR(B80="",C80=""),"",B80*C80*10000) -> 52.205372 | E80: =IF(D80="","",D80/$D$83) -> 0.37270927
A81: Transportation & warehousing | B81: 0.05 | D81: =IF(OR(B81="",C81=""),"",B81*C81*10000) | E81: =IF(D81="","",D81/$D$83)
A82: Services less trade & transport | B82: 0.389 | D82: =IF(OR(B82="",C82=""),"",B82*C82*10000) | E82: =IF(D82="","",D82/$D$83)
A83: TOTAL (Goods + Services + resid.) | B83: =B78+B79 -> 0.967 | C83: =C6 -> 0.013758972 | D83: =D78+D79 -> 140.06996 | E83: =IF(D83="","",D83/D83) -> 1
A84: Headline FD M/M (actual, for tie-out) | D84: =C6*10000 -> 137.58972 | E84: bp
A85: Note: Trade/Transport/Other are sub-rows of Services (not added to total). Weighted contributions are approximate — BLS does not publish exact bp contributions; small residual vs actual headline is expected.
A87: TOP MOVERS — April 2026 commodity detail
A88: From BLS release tables 2–9. M/M % are published values (blue inputs) — replace each release. Sorted largest gain → largest decline.
A89: Commodity / Service detail | B89: Category | C89: M/M % | D89: Direction
A90: Chicken eggs | B90: Goods – Foods | C90: -0.497 | D90: =IF(C90="","",IF(C90>0,"▲ up",IF(C90<0,"▼ down","flat"))) -> ▼ down
A91: Gasoline | B91: Goods – Energy | C91: 0.156 | D91: =IF(C91="","",IF(C91>0,"▲ up",IF(C91<0,"▼ down","flat"))) -> ▲ up
A92: Truck transportation of freight | B92: Services – Transport | D92: =IF(C92="","",IF(C92>0,"▲ up",IF(C92<0,"▼ down","flat")))
A93: Machinery & equipment wholesaling | B93: Services – Trade | C93: 0.035 | D93: =IF(C93="","",IF(C93>0,"▲ up",IF(C93<0,"▼ down","flat"))) -> ▲ up
A94: Jet fuel | B94: Goods – Energy | D94: =IF(C94="","",IF(C94>0,"▲ up",IF(C94<0,"▼ down","flat")))
A95: Diesel fuel | B95: Goods – Energy | D95: =IF(C95="","",IF(C95>0,"▲ up",IF(C95<0,"▼ down","flat")))
A96: Fresh & dry vegetables | B96: Goods – Foods | D96: =IF(C96="","",IF(C96>0,"▲ up",IF(C96<0,"▼ down","flat")))
A97: Industrial chemicals | B97: Goods – Core | D97: =IF(C97="","",IF(C97>0,"▲ up",IF(C97<0,"▼ down","flat")))
A98: Fuels & lubricants retailing | B98: Services – Trade | D98: =IF(C98="","",IF(C98>0,"▲ up",IF(C98<0,"▼ down","flat")))
A99: Health, beauty & optical retailing | B99: Services – Trade | D99: =IF(C99="","",IF(C99>0,"▲ up",IF(C99<0,"▼ down","flat")))
A100: Chemicals & allied products wholesaling | B100: Services – Trade | D100: =IF(C100="","",IF(C100>0,"▲ up",IF(C100<0,"▼ down","flat")))
A101: Legal services | B101: Services – Other | D101: =IF(C101="","",IF(C101>0,"▲ up",IF(C101<0,"▼ down","flat")))
A102: Portfolio management | B102: Services – Other | C102: -0.024 | D102: =IF(C102="","",IF(C102>0,"▲ up",IF(C102<0,"▼ down","flat"))) -> ▼ down
A103: Food retailing (margins) | B103: Services – Trade | D103: =IF(C103="","",IF(C103>0,"▲ up",IF(C103<0,"▼ down","flat")))
A104: Metals, minerals & ores wholesaling | B104: Services – Trade | D104: =IF(C104="","",IF(C104>0,"▲ up",IF(C104<0,"▼ down","flat")))
A105: Residential natural gas | B105: Goods – Energy | D105: =IF(C105="","",IF(C105>0,"▲ up",IF(C105<0,"▼ down","flat")))
A106: Nonferrous scrap | B106: Goods – Core | D106: =IF(C106="","",IF(C106>0,"▲ up",IF(C106<0,"▼ down","flat")))
A108: TRADE MARGIN SPIKE TABLE — auto-ranked subcomponents (M/M)
A109: Live from Macrobond FP–GP via Calc Engine. Auto-sorts largest margin gain → largest decline each release. WH = wholesaling, RT = retailing.
A110: Rank | B110: Subcomponent | C110: Type | D110: M/M %
A111: 1 | B111: =INDEX('Calc Engine'!$DA$6:$DA$31,MATCH(LARGE('Calc Engine'!$DG$6:$DG$31,1),'Calc Engine'!$DG$6:$DG$31,0)) -> Fuels & Lubricants Retailing | C111: =INDEX('Calc Engine'!$DF$6:$DF$31,MATCH(LARGE('Calc Engine'!$DG$6:$DG$31,1),'Calc Engine'!$DG$6:$DG$31,0)) -> RT | D111: =LARGE('Calc Engine'!$DE$6:$DE$31,1) -> 0.26533704
A112: 2 | B112: =INDEX('Calc Engine'!$DA$6:$DA$31,MATCH(LARGE('Calc Engine'!$DG$6:$DG$31,2),'Calc Engine'!$DG$6:$DG$31,0)) -> Chemicals & Allied Products Wholesaling | C112: =INDEX('Calc Engine'!$DF$6:$DF$31,MATCH(LARGE('Calc Engine'!$DG$6:$DG$31,2),'Calc Engine'!$DG$6:$DG$31,0)) -> WH | D112: =LARGE('Calc Engine'!$DE$6:$DE$31,2) -> 0.0734104
A113: 3 | B113: =INDEX('Calc Engine'!$DA$6:$DA$31,MATCH(LARGE('Calc Engine'!$DG$6:$DG$31,3),'Calc Engine'!$DG$6:$DG$31,0)) -> Health & Beauty Retailing | C113: =INDEX('Calc Engine'!$DF$6:$DF$31,MATCH(LARGE('Calc Engine'!$DG$6:$DG$31,3),'Calc Engine'!$DG$6:$DG$31,0)) -> RT | D113: =LARGE('Calc Engine'!$DE$6:$DE$31,3) -> 0.069186908
A114: 4 | B114: =INDEX('Calc Engine'!$DA$6:$DA$31,MATCH(LARGE('Calc Engine'!$DG$6:$DG$31,4),'Calc Engine'!$DG$6:$DG$31,0)) -> Machinery & Vehicle Wholesaling | C114: =INDEX('Calc Engine'!$DF$6:$DF$31,MATCH(LARGE('Calc Engine'!$DG$6:$DG$31,4),'Calc Engine'!$DG$6:$DG$31,0)) -> WH | D114: =LARGE('Calc Engine'!$DE$6:$DE$31,4) -> 0.053658061
A115: 5 | B115: =INDEX('Calc Engine'!$DA$6:$DA$31,MATCH(LARGE('Calc Engine'!$DG$6:$DG$31,5),'Calc Engine'!$DG$6:$DG$31,0)) -> Professional & Commercial Equip Wholesaling | C115: =INDEX('Calc Engine'!$DF$6:$DF$31,MATCH(LARGE('Calc Engine'!$DG$6:$DG$31,5),'Calc Engine'!$DG$6:$DG$31,0)) -> WH | D115: =LARGE('Calc Engine'!$DE$6:$DE$31,5) -> 0.035503068
A116: 6 | B116: =INDEX('Calc Engine'!$DA$6:$DA$31,MATCH(LARGE('Calc Engine'!$DG$6:$DG$31,6),'Calc Engine'!$DG$6:$DG$31,0)) -> Automobile Retailing (partial) | C116: =INDEX('Calc Engine'!$DF$6:$DF$31,MATCH(LARGE('Calc Engine'!$DG$6:$DG$31,6),'Calc Engine'!$DG$6:$DG$31,0)) -> RT | D116: =LARGE('Calc Engine'!$DE$6:$DE$31,6) -> 0.029153142
A117: 7 | B117: =INDEX('Calc Engine'!$DA$6:$DA$31,MATCH(LARGE('Calc Engine'!$DG$6:$DG$31,7),'Calc Engine'!$DG$6:$DG$31,0)) -> Autos & Auto Parts Retailing | C117: =INDEX('Calc Engine'!$DF$6:$DF$31,MATCH(LARGE('Calc Engine'!$DG$6:$DG$31,7),'Calc Engine'!$DG$6:$DG$31,0)) -> RT | D117: =LARGE('Calc Engine'!$DE$6:$DE$31,7) -> 0.023777679
A118: 8 | B118: =INDEX('Calc Engine'!$DA$6:$DA$31,MATCH(LARGE('Calc Engine'!$DG$6:$DG$31,8),'Calc Engine'!$DG$6:$DG$31,0)) -> Sporting Goods Retailing | C118: =INDEX('Calc Engine'!$DF$6:$DF$31,MATCH(LARGE('Calc Engine'!$DG$6:$DG$31,8),'Calc Engine'!$DG$6:$DG$31,0)) -> RT | D118: =LARGE('Calc Engine'!$DE$6:$DE$31,8) -> 0.022476264
A119: 9 | B119: =INDEX('Calc Engine'!$DA$6:$DA$31,MATCH(LARGE('Calc Engine'!$DG$6:$DG$31,9),'Calc Engine'!$DG$6:$DG$31,0)) -> Automotive Parts Retailing | C119: =INDEX('Calc Engine'!$DF$6:$DF$31,MATCH(LARGE('Calc Engine'!$DG$6:$DG$31,9),'Calc Engine'!$DG$6:$DG$31,0)) -> RT | D119: =LARGE('Calc Engine'!$DE$6:$DE$31,9) -> 0.016791926
A120: 10 | B120: =INDEX('Calc Engine'!$DA$6:$DA$31,MATCH(LARGE('Calc Engine'!$DG$6:$DG$31,10),'Calc Engine'!$DG$6:$DG$31,0)) -> Apparel/Jewelry/Footwear Retailing | C120: =INDEX('Calc Engine'!$DF$6:$DF$31,MATCH(LARGE('Calc Engine'!$DG$6:$DG$31,10),'Calc Engine'!$DG$6:$DG$31,0)) -> RT | D120: =LARGE('Calc Engine'!$DE$6:$DE$31,10) -> 0.01247746
A121: — largest declines —
A122: =COUNT('Calc Engine'!$DE$6:$DE$31)-1+1 -> 25 | B122: =INDEX('Calc Engine'!$DA$6:$DA$31,MATCH(SMALL('Calc Engine'!$DG$6:$DG$31,1),'Calc Engine'!$DG$6:$DG$31,0)) -> Paper & Plastics Wholesaling | C122: =INDEX('Calc Engine'!$DF$6:$DF$31,MATCH(SMALL('Calc Engine'!$DG$6:$DG$31,1),'Calc Engine'!$DG$6:$DG$31,0)) -> WH | D122: =SMALL('Calc Engine'!$DE$6:$DE$31,1) -> -0.027073735
A123: =COUNT('Calc Engine'!$DE$6:$DE$31)-2+1 -> 24 | B123: =INDEX('Calc Engine'!$DA$6:$DA$31,MATCH(SMALL('Calc Engine'!$DG$6:$DG$31,2),'Calc Engine'!$DG$6:$DG$31,0)) -> RVs/Trailers/Campers Retailing | C123: =INDEX('Calc Engine'!$DF$6:$DF$31,MATCH(SMALL('Calc Engine'!$DG$6:$DG$31,2),'Calc Engine'!$DG$6:$DG$31,0)) -> RT | D123: =SMALL('Calc Engine'!$DE$6:$DE$31,2) -> -0.026460299
A124: =COUNT('Calc Engine'!$DE$6:$DE$31)-3+1 -> 23 | B124: =INDEX('Calc Engine'!$DA$6:$DA$31,MATCH(SMALL('Calc Engine'!$DG$6:$DG$31,3),'Calc Engine'!$DG$6:$DG$31,0)) -> TV/Video/Photo Retailing | C124: =INDEX('Calc Engine'!$DF$6:$DF$31,MATCH(SMALL('Calc Engine'!$DG$6:$DG$31,3),'Calc Engine'!$DG$6:$DG$31,0)) -> RT | D124: =SMALL('Calc Engine'!$DE$6:$DE$31,3) -> -0.019297661
A125: =COUNT('Calc Engine'!$DE$6:$DE$31)-4+1 -> 22 | B125: =INDEX('Calc Engine'!$DA$6:$DA$31,MATCH(SMALL('Calc Engine'!$DG$6:$DG$31,4),'Calc Engine'!$DG$6:$DG$31,0)) -> Apparel Wholesaling | C125: =INDEX('Calc Engine'!$DF$6:$DF$31,MATCH(SMALL('Calc Engine'!$DG$6:$DG$31,4),'Calc Engine'!$DG$6:$DG$31,0)) -> WH | D125: =SMALL('Calc Engine'!$DE$6:$DE$31,4) -> -0.012730328
A126: =COUNT('Calc Engine'!$DE$6:$DE$31)-5+1 -> 21 | B126: =INDEX('Calc Engine'!$DA$6:$DA$31,MATCH(SMALL('Calc Engine'!$DG$6:$DG$31,5),'Calc Engine'!$DG$6:$DG$31,0)) -> Food & Alcohol Retailing | C126: =INDEX('Calc Engine'!$DF$6:$DF$31,MATCH(SMALL('Calc Engine'!$DG$6:$DG$31,5),'Calc Engine'!$DG$6:$DG$31,0)) -> RT | D126: =SMALL('Calc Engine'!$DE$6:$DE$31,5) -> -0.011009156

Sheet Calc Engine
A1: PPI CALC ENGINE — live links to Macrobond Imports (row N here = row N+? mirrored)
A2: Raw indices pulled from Macrobond. Transformations (M/M, Y/Y, 3m/6m ann.) reference these columns. Series labels in row 4, BLS code in row 3. | Q2: M/M % CHANGE (SA) | AE2: Y/Y % CHANGE (NSA-on-SA index) | AS2: 3-MONTH ANNUALIZED % | BG2: 6-MONTH ANNUALIZED %
A3: Macrobond col → | B3: B | C3: C | D3: Z | E3: BH | F3: BJ | G3: BK | H3: BL | I3: BS | J3: AA | K3: DF | L3: EA | M3: FA | N3: FC | BX3: FG | BY3: AI
A4: Date | B4: Headline FD | C4: FD Goods | D4: FD Services | E4: Core (ex F&E) | F4: FD ex Food | G4: FD ex Energy | H4: FD ex Trade Svcs | I4: FD ex F,E,Trade | J4: FD Trade Svcs | K4: Interm Processed | L4: Interm Unprocessed | M4: Proc Energy Gds | N4: Proc ex F&E | P4: Date | Q4: Headline FD | R4: FD Goods | S4: FD Services | T4: Core (ex F&E) | U4: FD ex Food | V4: FD ex Energy | W4: FD ex Trade Svcs | X4: FD ex F,E,Trade | Y4: FD Trade Svcs | Z4: Interm Processed | AA4: Interm Unprocessed | AB4: Proc Energy Gds | AC4: Proc ex F&E | AE4: Headline FD | AF4: FD Goods | AG4: FD Services | AH4: Core (ex F&E) | AI4: FD ex Food | AJ4: FD ex Energy | AK4: FD ex Trade Svcs | AL4: FD ex F,E,Trade | AM4: FD Trade Svcs | AN4: Interm Processed | AO4: Interm Unprocessed | AP4: Proc Energy Gds | AQ4: Proc ex F&E | AS4: Headline FD | AT4: FD Goods | AU4: FD Services | AV4: Core (ex F&E) | AW4: FD ex Food | AX4: FD ex Energy | AY4: FD ex Trade Svcs | AZ4: FD ex F,E,Trade | BA4: FD Trade Svcs | BB4: Interm Processed | BC4: Interm Unprocessed | BD4: Proc Energy Gds | BE4: Proc ex F&E | BG4: Headline FD | BH4: FD Goods | BI4: FD Services | BJ4: Core (ex F&E) | BK4: FD ex Food | BL4: FD ex Energy | BM4: FD ex Trade Svcs | BN4: FD ex F,E,Trade | BO4: FD Trade Svcs | BP4: Interm Processed | BQ4: Interm Unprocessed | BR4: Proc Energy Gds | BS4: Proc ex F&E | BX4: Unproc Energy (FG) | BY4: FD Transport&Whse (AI) | CA4: Unproc Energy Y/Y | CB4: Transport&Whse Y/Y
CB5: ChartDate | CC5: Headline M/M | CD5: Core M/M | CE5: Headline Y/Y | CF5: Core Y/Y | CG5: Headline 3m ann | CH5: Headline 6m ann | CK5: Date | CL5: Unproc Energy Y/Y | CM5: Transport&Whse Y/Y | DA5: Subcomponent | DB5: MBcol | DC5: Index | DD5: Prior | DE5: M/M | DF5: Type
A6: =IF('Macrobond Imports'!A5="","",'Macrobond Imports'!A5) -> 17258 | B6: =IF('Macrobond Imports'!B5="","",'Macrobond Imports'!B5) | C6: =IF('Macrobond Imports'!C5="","",'Macrobond Imports'!C5) | D6: =IF('Macrobond Imports'!Z5="","",'Macrobond Imports'!Z5) | E6: =IF('Macrobond Imports'!BH5="","",'Macrobond Imports'!BH5) | F6: =IF('Macrobond Imports'!BJ5="","",'Macrobond Imports'!BJ5) | G6: =IF('Macrobond Imports'!BK5="","",'Macrobond Imports'!BK5) | H6: =IF('Macrobond Imports'!BL5="","",'Macrobond Imports'!BL5) | I6: =IF('Macrobond Imports'!BS5="","",'Macrobond Imports'!BS5) | J6: =IF('Macrobond Imports'!AA5="","",'Macrobond Imports'!AA5) | K6: =IF('Macrobond Imports'!DF5="","",'Macrobond Imports'!DF5) -> 23.1 | L6: =IF('Macrobond Imports'!EA5="","",'Macrobond Imports'!EA5) -> 30.7 | M6: =IF('Macrobond Imports'!FA5="","",'Macrobond Imports'!FA5) | N6: =IF('Macrobond Imports'!FC5="","",'Macrobond Imports'!FC5) | P6: =A6 -> 17258 | Q6: =IF(OR(B6="",N(B5)=0),"",B6/B5-1) | R6: =IF(OR(C6="",N(C5)=0),"",C6/C5-1) | S6: =IF(OR(D6="",N(D5)=0),"",D6/D5-1) | T6: =IF(OR(E6="",N(E5)=0),"",E6/E5-1) | U6: =IF(OR(F6="",N(F5)=0),"",F6/F5-1) | V6: =IF(OR(G6="",N(G5)=0),"",G6/G5-1) | W6: =IF(OR(H6="",N(H5)=0),"",H6/H5-1) | X6: =IF(OR(I6="",N(I5)=0),"",I6/I5-1) | ... AC6: =IF(OR(N6="",N(N5)=0),"",N6/N5-1) | AE6: =IFERROR(IF(OR(B6="",OFFSET(B6,-12,0)=""),"",B6/OFFSET(B6,-12,0)-1),"") | AF6: =IFERROR(IF(OR(C6="",OFFSET(C6,-12,0)=""),"",C6/OFFSET(C6,-12,0)-1),"") | AG6: =IFERROR(IF(OR(D6="",OFFSET(D6,-12,0)=""),"",D6/OFFSET(D6,-12,0)-1),"") | AH6: =IFERROR(IF(OR(E6="",OFFSET(E6,-12,0)=""),"",E6/OFFSET(E6,-12,0)-1),"") | AI6: =IFERROR(IF(OR(F6="",OFFSET(F6,-12,0)=""),"",F6/OFFSET(F6,-12,0)-1),"") | AJ6: =IFERROR(IF(OR(G6="",OFFSET(G6,-12,0)=""),"",G6/OFFSET(G6,-12,0)-1),"") | AK6: =IFERROR(IF(OR(H6="",OFFSET(H6,-12,0)=""),"",H6/OFFSET(H6,-12,0)-1),"") | AL6: =IFERROR(IF(OR(I6="",OFFSET(I6,-12,0)=""),"",I6/OFFSET(I6,-12,0)-1),"") | ... AQ6: =IFERROR(IF(OR(N6="",OFFSET(N6,-12,0)=""),"",N6/OFFSET(N6,-12,0)-1),"") | AS6: =IFERROR(IF(OR(B6="",OFFSET(B6,-3,0)=""),"",(B6/OFFSET(B6,-3,0))^4-1),"") | AT6: =IFERROR(IF(OR(C6="",OFFSET(C6,-3,0)=""),"",(C6/OFFSET(C6,-3,0))^4-1),"") | AU6: =IFERROR(IF(OR(D6="",OFFSET(D6,-3,0)=""),"",(D6/OFFSET(D6,-3,0))^4-1),"") | AV6: =IFERROR(IF(OR(E6="",OFFSET(E6,-3,0)=""),"",(E6/OFFSET(E6,-3,0))^4-1),"") | AW6: =IFERROR(IF(OR(F6="",OFFSET(F6,-3,0)=""),"",(F6/OFFSET(F6,-3,0))^4-1),"") | AX6: =IFERROR(IF(OR(G6="",OFFSET(G6,-3,0)=""),"",(G6/OFFSET(G6,-3,0))^4-1),"") | AY6: =IFERROR(IF(OR(H6="",OFFSET(H6,-3,0)=""),"",(H6/OFFSET(H6,-3,0))^4-1),"") | AZ6: =IFERROR(IF(OR(I6="",OFFSET(I6,-3,0)=""),"",(I6/OFFSET(I6,-3,0))^4-1),"") | ... BE6: =IFERROR(IF(OR(N6="",OFFSET(N6,-3,0)=""),"",(N6/OFFSET(N6,-3,0))^4-1),"") | BG6: =IFERROR(IF(OR(B6="",OFFSET(B6,-6,0)=""),"",(B6/OFFSET(B6,-6,0))^2-1),"") | BH6: =IFERROR(IF(OR(C6="",OFFSET(C6,-6,0)=""),"",(C6/OFFSET(C6,-6,0))^2-1),"") | BI6: =IFERROR(IF(OR(D6="",OFFSET(D6,-6,0)=""),"",(D6/OFFSET(D6,-6,0))^2-1),"") | BJ6: =IFERROR(IF(OR(E6="",OFFSET(E6,-6,0)=""),"",(E6/OFFSET(E6,-6,0))^2-1),"") | BK6: =IFERROR(IF(OR(F6="",OFFSET(F6,-6,0)=""),"",(F6/OFFSET(F6,-6,0))^2-1),"") | BL6: =IFERROR(IF(OR(G6="",OFFSET(G6,-6,0)=""),"",(G6/OFFSET(G6,-6,0))^2-1),"") | BM6: =IFERROR(IF(OR(H6="",OFFSET(H6,-6,0)=""),"",(H6/OFFSET(H6,-6,0))^2-1),"") | BN6: =IFERROR(IF(OR(I6="",OFFSET(I6,-6,0)=""),"",(I6/OFFSET(I6,-6,0))^2-1),"") | ... BS6: =IFERROR(IF(OR(N6="",OFFSET(N6,-6,0)=""),"",(N6/OFFSET(N6,-6,0))^2-1),"") | BX6: =IF('Macrobond Imports'!FG5="","",'Macrobond Imports'!FG5) | BY6: =IF('Macrobond Imports'!AI5="","",'Macrobond Imports'!AI5) | CA6: =IFERROR(IF(OR(BX6="",OFFSET(BX6,-12,0)=""),"",BX6/OFFSET(BX6,-12,0)-1),"") | CB6: =IFERROR(IF(OR(BY6="",OFFSET(BY6,-12,0)=""),"",BY6/OFFSET(BY6,-12,0)-1),"") | CC6: {=INDEX(MM_Headline,ROW()-5)} -> 0.00018724384 | CD6: {=INDEX(MM_Core,ROW()-5)} -> 0.0026260578 | CE6: {=INDEX(YY_Headline,ROW()-5)} -> 0.025673119 | CF6: {=INDEX(YY_Core,ROW()-5)} -> 0.026970311 | CG6: {=INDEX(Ann3_Headline,ROW()-5)} -> 0.024440283 | CH6: {=INDEX(Ann6_Headline,ROW()-5)} -> 0.026733575 | CK6: {=INDEX(ChartDates,ROW()-5)} -> 45413 | CL6: {=INDEX(UnprocEnergy_YY,ROW()-5)} -> 0.05107398 | CM6: {=INDEX(Transport_YY,ROW()-5)} -> 0.0022079796 | DA6: Machinery & Vehicle Wholesaling | DB6: FQ | DC6: =INDEX('Macrobond Imports'!FQ:FQ,MATCH(MAX('Macrobond Imports'!$A:$A),'Macrobond Imports'!$A:$A,0)) -> 162.021 | DD6: {=INDEX('Macrobond Imports'!FQ:FQ,MATCH(MAX('Macrobond Imports'!$A:$A),'Macrobond Imports'!$A:$A,0)-1)} -> 153.77 | DE6: =IFERROR(IF(OR(DC6="",DD6="",DC6=0,DD6=0),"",DC6/DD6-1),"") -> 0.053658061 | DF6: WH | DG6: =IF(DE6="","",DE6+ROW()*0.000000001) -> 0.053658067
A7: =IF('Macrobond Imports'!A6="","",'Macrobond Imports'!A6) -> 17288 | B7: =IF('Macrobond Imports'!B6="","",'Macrobond Imports'!B6) | C7: =IF('Macrobond Imports'!C6="","",'Macrobond Imports'!C6) | D7: =IF('Macrobond Imports'!Z6="","",'Macrobond Imports'!Z6) | E7: =IF('Macrobond Imports'!BH6="","",'Macrobond Imports'!BH6) | F7: =IF('Macrobond Imports'!BJ6="","",'Macrobond Imports'!BJ6) | G7: =IF('Macrobond Imports'!BK6="","",'Macrobond Imports'!BK6) | H7: =IF('Macrobond Imports'!BL6="","",'Macrobond Imports'!BL6) | I7: =IF('Macrobond Imports'!BS6="","",'Macrobond Imports'!BS6) | J7: =IF('Macrobond Imports'!AA6="","",'Macrobond Imports'!AA6) | K7: =IF('Macrobond Imports'!DF6="","",'Macrobond Imports'!DF6) -> 23 | L7: =IF('Macrobond Imports'!EA6="","",'Macrobond Imports'!EA6) -> 30.4 | M7: =IF('Macrobond Imports'!FA6="","",'Macrobond Imports'!FA6) | N7: =IF('Macrobond Imports'!FC6="","",'Macrobond Imports'!FC6) | P7: =A7 -> 17288 | Q7: =IF(OR(B7="",N(B6)=0),"",B7/B6-1) | R7: =IF(OR(C7="",N(C6)=0),"",C7/C6-1) | S7: =IF(OR(D7="",N(D6)=0),"",D7/D6-1) | T7: =IF(OR(E7="",N(E6)=0),"",E7/E6-1) | U7: =IF(OR(F7="",N(F6)=0),"",F7/F6-1) | V7: =IF(OR(G7="",N(G6)=0),"",G7/G6-1) | W7: =IF(OR(H7="",N(H6)=0),"",H7/H6-1) | X7: =IF(OR(I7="",N(I6)=0),"",I7/I6-1) | ... AC7: =IF(OR(N7="",N(N6)=0),"",N7/N6-1) | AE7: =IFERROR(IF(OR(B7="",OFFSET(B7,-12,0)=""),"",B7/OFFSET(B7,-12,0)-1),"") | AF7: =IFERROR(IF(OR(C7="",OFFSET(C7,-12,0)=""),"",C7/OFFSET(C7,-12,0)-1),"") | AG7: =IFERROR(IF(OR(D7="",OFFSET(D7,-12,0)=""),"",D7/OFFSET(D7,-12,0)-1),"") | AH7: =IFERROR(IF(OR(E7="",OFFSET(E7,-12,0)=""),"",E7/OFFSET(E7,-12,0)-1),"") | AI7: =IFERROR(IF(OR(F7="",OFFSET(F7,-12,0)=""),"",F7/OFFSET(F7,-12,0)-1),"") | AJ7: =IFERROR(IF(OR(G7="",OFFSET(G7,-12,0)=""),"",G7/OFFSET(G7,-12,0)-1),"") | AK7: =IFERROR(IF(OR(H7="",OFFSET(H7,-12,0)=""),"",H7/OFFSET(H7,-12,0)-1),"") | AL7: =IFERROR(IF(OR(I7="",OFFSET(I7,-12,0)=""),"",I7/OFFSET(I7,-12,0)-1),"") | ... AQ7: =IFERROR(IF(OR(N7="",OFFSET(N7,-12,0)=""),"",N7/OFFSET(N7,-12,0)-1),"") | AS7: =IFERROR(IF(OR(B7="",OFFSET(B7,-3,0)=""),"",(B7/OFFSET(B7,-3,0))^4-1),"") | AT7: =IFERROR(IF(OR(C7="",OFFSET(C7,-3,0)=""),"",(C7/OFFSET(C7,-3,0))^4-1),"") | AU7: =IFERROR(IF(OR(D7="",OFFSET(D7,-3,0)=""),"",(D7/OFFSET(D7,-3,0))^4-1),"") | AV7: =IFERROR(IF(OR(E7="",OFFSET(E7,-3,0)=""),"",(E7/OFFSET(E7,-3,0))^4-1),"") | AW7: =IFERROR(IF(OR(F7="",OFFSET(F7,-3,0)=""),"",(F7/OFFSET(F7,-3,0))^4-1),"") | AX7: =IFERROR(IF(OR(G7="",OFFSET(G7,-3,0)=""),"",(G7/OFFSET(G7,-3,0))^4-1),"") | AY7: =IFERROR(IF(OR(H7="",OFFSET(H7,-3,0)=""),"",(H7/OFFSET(H7,-3,0))^4-1),"") | AZ7: =IFERROR(IF(OR(I7="",OFFSET(I7,-3,0)=""),"",(I7/OFFSET(I7,-3,0))^4-1),"") | ... BE7: =IFERROR(IF(OR(N7="",OFFSET(N7,-3,0)=""),"",(N7/OFFSET(N7,-3,0))^4-1),"") | BG7: =IFERROR(IF(OR(B7="",OFFSET(B7,-6,0)=""),"",(B7/OFFSET(B7,-6,0))^2-1),"") | BH7: =IFERROR(IF(OR(C7="",OFFSET(C7,-6,0)=""),"",(C7/OFFSET(C7,-6,0))^2-1),"") | BI7: =IFERROR(IF(OR(D7="",OFFSET(D7,-6,0)=""),"",(D7/OFFSET(D7,-6,0))^2-1),"") | BJ7: =IFERROR(IF(OR(E7="",OFFSET(E7,-6,0)=""),"",(E7/OFFSET(E7,-6,0))^2-1),"") | BK7: =IFERROR(IF(OR(F7="",OFFSET(F7,-6,0)=""),"",(F7/OFFSET(F7,-6,0))^2-1),"") | BL7: =IFERROR(IF(OR(G7="",OFFSET(G7,-6,0)=""),"",(G7/OFFSET(G7,-6,0))^2-1),"") | BM7: =IFERROR(IF(OR(H7="",OFFSET(H7,-6,0)=""),"",(H7/OFFSET(H7,-6,0))^2-1),"") | BN7: =IFERROR(IF(OR(I7="",OFFSET(I7,-6,0)=""),"",(I7/OFFSET(I7,-6,0))^2-1),"") | ... BS7: =IFERROR(IF(OR(N7="",OFFSET(N7,-6,0)=""),"",(N7/OFFSET(N7,-6,0))^2-1),"") | BX7: =IF('Macrobond Imports'!FG6="","",'Macrobond Imports'!FG6) | BY7: =IF('Macrobond Imports'!AI6="","",'Macrobond Imports'!AI6) | CA7: =IFERROR(IF(OR(BX7="",OFFSET(BX7,-12,0)=""),"",BX7/OFFSET(BX7,-12,0)-1),"") | CB7: =IFERROR(IF(OR(BY7="",OFFSET(BY7,-12,0)=""),"",BY7/OFFSET(BY7,-12,0)-1),"") | CC7: {=INDEX(MM_Headline,ROW()-5)} -> 0.0044722099 | CD7: {=INDEX(MM_Core,ROW()-5)} -> 0.0059826839 | CE7: {=INDEX(YY_Headline,ROW()-5)} -> 0.029645055 | CF7: {=INDEX(YY_Core,ROW()-5)} -> 0.032883448 | CG7: {=INDEX(Ann3_Headline,ROW()-5)} -> 0.038102035 | CH7: {=INDEX(Ann6_Headline,ROW()-5)} -> 0.038402071 | CK7: {=INDEX(ChartDates,ROW()-5)} -> 45444 | CL7: {=INDEX(UnprocEnergy_YY,ROW()-5)} -> 0.11386231 | CM7: {=INDEX(Transport_YY,ROW()-5)} -> 0.0043137044 | DA7: Parts & Supplies Machinery Wholesaling | DB7: FP | DC7: =INDEX('Macrobond Imports'!FP:FP,MATCH(MAX('Macrobond Imports'!$A:$A),'Macrobond Imports'!$A:$A,0)) -> 235.79 | DD7: {=INDEX('Macrobond Imports'!FP:FP,MATCH(MAX('Macrobond Imports'!$A:$A),'Macrobond Imports'!$A:$A,0)-1)} -> 233.95 | DE7: =IFERROR(IF(OR(DC7="",DD7="",DC7=0,DD7=0),"",DC7/DD7-1),"") -> 0.0078649284 | DF7: WH | DG7: =IF(DE7="","",DE7+ROW()*0.000000001) -> 0.0078649354
A8: =IF('Macrobond Imports'!A7="","",'Macrobond Imports'!A7) -> 17319 | B8: =IF('Macrobond Imports'!B7="","",'Macrobond Imports'!B7) | C8: =IF('Macrobond Imports'!C7="","",'Macrobond Imports'!C7) | D8: =IF('Macrobond Imports'!Z7="","",'Macrobond Imports'!Z7) | E8: =IF('Macrobond Imports'!BH7="","",'Macrobond Imports'!BH7) | F8: =IF('Macrobond Imports'!BJ7="","",'Macrobond Imports'!BJ7) | G8: =IF('Macrobond Imports'!BK7="","",'Macrobond Imports'!BK7) | H8: =IF('Macrobond Imports'!BL7="","",'Macrobond Imports'!BL7) | I8: =IF('Macrobond Imports'!BS7="","",'Macrobond Imports'!BS7) | J8: =IF('Macrobond Imports'!AA7="","",'Macrobond Imports'!AA7) | K8: =IF('Macrobond Imports'!DF7="","",'Macrobond Imports'!DF7) -> 23.2 | L8: =IF('Macrobond Imports'!EA7="","",'Macrobond Imports'!EA7) -> 30.6 | M8: =IF('Macrobond Imports'!FA7="","",'Macrobond Imports'!FA7) | N8: =IF('Macrobond Imports'!FC7="","",'Macrobond Imports'!FC7) | P8: =A8 -> 17319 | Q8: =IF(OR(B8="",N(B7)=0),"",B8/B7-1) | R8: =IF(OR(C8="",N(C7)=0),"",C8/C7-1) | S8: =IF(OR(D8="",N(D7)=0),"",D8/D7-1) | T8: =IF(OR(E8="",N(E7)=0),"",E8/E7-1) | U8: =IF(OR(F8="",N(F7)=0),"",F8/F7-1) | V8: =IF(OR(G8="",N(G7)=0),"",G8/G7-1) | W8: =IF(OR(H8="",N(H7)=0),"",H8/H7-1) | X8: =IF(OR(I8="",N(I7)=0),"",I8/I7-1) | ... AC8: =IF(OR(N8="",N(N7)=0),"",N8/N7-1) | AE8: =IFERROR(IF(OR(B8="",OFFSET(B8,-12,0)=""),"",B8/OFFSET(B8,-12,0)-1),"") | AF8: =IFERROR(IF(OR(C8="",OFFSET(C8,-12,0)=""),"",C8/OFFSET(C8,-12,0)-1),"") | AG8: =IFERROR(IF(OR(D8="",OFFSET(D8,-12,0)=""),"",D8/OFFSET(D8,-12,0)-1),"") | AH8: =IFERROR(IF(OR(E8="",OFFSET(E8,-12,0)=""),"",E8/OFFSET(E8,-12,0)-1),"") | AI8: =IFERROR(IF(OR(F8="",OFFSET(F8,-12,0)=""),"",F8/OFFSET(F8,-12,0)-1),"") | AJ8: =IFERROR(IF(OR(G8="",OFFSET(G8,-12,0)=""),"",G8/OFFSET(G8,-12,0)-1),"") | AK8: =IFERROR(IF(OR(H8="",OFFSET(H8,-12,0)=""),"",H8/OFFSET(H8,-12,0)-1),"") | AL8: =IFERROR(IF(OR(I8="",OFFSET(I8,-12,0)=""),"",I8/OFFSET(I8,-12,0)-1),"") | ... AQ8: =IFERROR(IF(OR(N8="",OFFSET(N8,-12,0)=""),"",N8/OFFSET(N8,-12,0)-1),"") | AS8: =IFERROR(IF(OR(B8="",OFFSET(B8,-3,0)=""),"",(B8/OFFSET(B8,-3,0))^4-1),"") | AT8: =IFERROR(IF(OR(C8="",OFFSET(C8,-3,0)=""),"",(C8/OFFSET(C8,-3,0))^4-1),"") | AU8: =IFERROR(IF(OR(D8="",OFFSET(D8,-3,0)=""),"",(D8/OFFSET(D8,-3,0))^4-1),"") | AV8: =IFERROR(IF(OR(E8="",OFFSET(E8,-3,0)=""),"",(E8/OFFSET(E8,-3,0))^4-1),"") | AW8: =IFERROR(IF(OR(F8="",OFFSET(F8,-3,0)=""),"",(F8/OFFSET(F8,-3,0))^4-1),"") | AX8: =IFERROR(IF(OR(G8="",OFFSET(G8,-3,0)=""),"",(G8/OFFSET(G8,-3,0))^4-1),"") | AY8: =IFERROR(IF(OR(H8="",OFFSET(H8,-3,0)=""),"",(H8/OFFSET(H8,-3,0))^4-1),"") | AZ8: =IFERROR(IF(OR(I8="",OFFSET(I8,-3,0)=""),"",(I8/OFFSET(I8,-3,0))^4-1),"") | ... BE8: =IFERROR(IF(OR(N8="",OFFSET(N8,-3,0)=""),"",(N8/OFFSET(N8,-3,0))^4-1),"") | BG8: =IFERROR(IF(OR(B8="",OFFSET(B8,-6,0)=""),"",(B8/OFFSET(B8,-6,0))^2-1),"") | BH8: =IFERROR(IF(OR(C8="",OFFSET(C8,-6,0)=""),"",(C8/OFFSET(C8,-6,0))^2-1),"") | BI8: =IFERROR(IF(OR(D8="",OFFSET(D8,-6,0)=""),"",(D8/OFFSET(D8,-6,0))^2-1),"") | BJ8: =IFERROR(IF(OR(E8="",OFFSET(E8,-6,0)=""),"",(E8/OFFSET(E8,-6,0))^2-1),"") | BK8: =IFERROR(IF(OR(F8="",OFFSET(F8,-6,0)=""),"",(F8/OFFSET(F8,-6,0))^2-1),"") | BL8: =IFERROR(IF(OR(G8="",OFFSET(G8,-6,0)=""),"",(G8/OFFSET(G8,-6,0))^2-1),"") | BM8: =IFERROR(IF(OR(H8="",OFFSET(H8,-6,0)=""),"",(H8/OFFSET(H8,-6,0))^2-1),"") | BN8: =IFERROR(IF(OR(I8="",OFFSET(I8,-6,0)=""),"",(I8/OFFSET(I8,-6,0))^2-1),"") | ... BS8: =IFERROR(IF(OR(N8="",OFFSET(N8,-6,0)=""),"",(N8/OFFSET(N8,-6,0))^2-1),"") | BX8: =IF('Macrobond Imports'!FG7="","",'Macrobond Imports'!FG7) | BY8: =IF('Macrobond Imports'!AI7="","",'Macrobond Imports'!AI7) | CA8: =IFERROR(IF(OR(BX8="",OFFSET(BX8,-12,0)=""),"",BX8/OFFSET(BX8,-12,0)-1),"") | CB8: =IFERROR(IF(OR(BY8="",OFFSET(BY8,-12,0)=""),"",BY8/OFFSET(BY8,-12,0)-1),"") | CC8: {=INDEX(MM_Headline,ROW()-5)} -> 0.00036584777 | CD8: {=INDEX(MM_Core,ROW()-5)} -> -0.00053747304 | CE8: {=INDEX(YY_Headline,ROW()-5)} -> 0.024292328 | CF8: {=INDEX(YY_Core,ROW()-5)} -> 0.025966954 | CG8: {=INDEX(Ann3_Headline,ROW()-5)} -> 0.02026356 | CH8: {=INDEX(Ann6_Headline,ROW()-5)} -> 0.033179511 | CK8: {=INDEX(ChartDates,ROW()-5)} -> 45474 | CL8: {=INDEX(UnprocEnergy_YY,ROW()-5)} -> 0.044292007 | CM8: {=INDEX(Transport_YY,ROW()-5)} -> 0.014167746 | DA8: Professional & Commercial Equip Wholesaling | DB8: FR | DC8: =INDEX('Macrobond Imports'!FR:FR,MATCH(MAX('Macrobond Imports'!$A:$A),'Macrobond Imports'!$A:$A,0)) -> 112.233 | DD8: {=INDEX('Macrobond Imports'!FR:FR,MATCH(MAX('Macrobond Imports'!$A:$A),'Macrobond Imports'!$A:$A,0)-1)} -> 108.385 | DE8: =IFERROR(IF(OR(DC8="",DD8="",DC8=0,DD8=0),"",DC8/DD8-1),"") -> 0.035503068 | DF8: WH | DG8: =IF(DE8="","",DE8+ROW()*0.000000001) -> 0.035503076
A9: =IF('Macrobond Imports'!A8="","",'Macrobond Imports'!A8) -> 17349 | B9: =IF('Macrobond Imports'!B8="","",'Macrobond Imports'!B8) | C9: =IF('Macrobond Imports'!C8="","",'Macrobond Imports'!C8) | D9: =IF('Macrobond Imports'!Z8="","",'Macrobond Imports'!Z8) | E9: =IF('Macrobond Imports'!BH8="","",'Macrobond Imports'!BH8) | F9: =IF('Macrobond Imports'!BJ8="","",'Macrobond Imports'!BJ8) | G9: =IF('Macrobond Imports'!BK8="","",'Macrobond Imports'!BK8) | H9: =IF('Macrobond Imports'!BL8="","",'Macrobond Imports'!BL8) | I9: =IF('Macrobond Imports'!BS8="","",'Macrobond Imports'!BS8) | J9: =IF('Macrobond Imports'!AA8="","",'Macrobond Imports'!AA8) | K9: =IF('Macrobond Imports'!DF8="","",'Macrobond Imports'!DF8) -> 23.2 | L9: =IF('Macrobond Imports'!EA8="","",'Macrobond Imports'!EA8) -> 31 | M9: =IF('Macrobond Imports'!FA8="","",'Macrobond Imports'!FA8) | N9: =IF('Macrobond Imports'!FC8="","",'Macrobond Imports'!FC8) | P9: =A9 -> 17349 | Q9: =IF(OR(B9="",N(B8)=0),"",B9/B8-1) | R9: =IF(OR(C9="",N(C8)=0),"",C9/C8-1) | S9: =IF(OR(D9="",N(D8)=0),"",D9/D8-1) | T9: =IF(OR(E9="",N(E8)=0),"",E9/E8-1) | U9: =IF(OR(F9="",N(F8)=0),"",F9/F8-1) | V9: =IF(OR(G9="",N(G8)=0),"",G9/G8-1) | W9: =IF(OR(H9="",N(H8)=0),"",H9/H8-1) | X9: =IF(OR(I9="",N(I8)=0),"",I9/I8-1) | ... AC9: =IF(OR(N9="",N(N8)=0),"",N9/N8-1) | AE9: =IFERROR(IF(OR(B9="",OFFSET(B9,-12,0)=""),"",B9/OFFSET(B9,-12,0)-1),"") | AF9: =IFERROR(IF(OR(C9="",OFFSET(C9,-12,0)=""),"",C9/OFFSET(C9,-12,0)-1),"") | AG9: =IFERROR(IF(OR(D9="",OFFSET(D9,-12,0)=""),"",D9/OFFSET(D9,-12,0)-1),"") | AH9: =IFERROR(IF(OR(E9="",OFFSET(E9,-12,0)=""),"",E9/OFFSET(E9,-12,0)-1),"") | AI9: =IFERROR(IF(OR(F9="",OFFSET(F9,-12,0)=""),"",F9/OFFSET(F9,-12,0)-1),"") | AJ9: =IFERROR(IF(OR(G9="",OFFSET(G9,-12,0)=""),"",G9/OFFSET(G9,-12,0)-1),"") | AK9: =IFERROR(IF(OR(H9="",OFFSET(H9,-12,0)=""),"",H9/OFFSET(H9,-12,0)-1),"") | AL9: =IFERROR(IF(OR(I9="",OFFSET(I9,-12,0)=""),"",I9/OFFSET(I9,-12,0)-1),"") | ... AQ9: =IFERROR(IF(OR(N9="",OFFSET(N9,-12,0)=""),"",N9/OFFSET(N9,-12,0)-1),"") | AS9: =IFERROR(IF(OR(B9="",OFFSET(B9,-3,0)=""),"",(B9/OFFSET(B9,-3,0))^4-1),"") | AT9: =IFERROR(IF(OR(C9="",OFFSET(C9,-3,0)=""),"",(C9/OFFSET(C9,-3,0))^4-1),"") | AU9: =IFERROR(IF(OR(D9="",OFFSET(D9,-3,0)=""),"",(D9/OFFSET(D9,-3,0))^4-1),"") | AV9: =IFERROR(IF(OR(E9="",OFFSET(E9,-3,0)=""),"",(E9/OFFSET(E9,-3,0))^4-1),"") | AW9: =IFERROR(IF(OR(F9="",OFFSET(F9,-3,0)=""),"",(F9/OFFSET(F9,-3,0))^4-1),"") | AX9: =IFERROR(IF(OR(G9="",OFFSET(G9,-3,0)=""),"",(G9/OFFSET(G9,-3,0))^4-1),"") | AY9: =IFERROR(IF(OR(H9="",OFFSET(H9,-3,0)=""),"",(H9/OFFSET(H9,-3,0))^4-1),"") | AZ9: =IFERROR(IF(OR(I9="",OFFSET(I9,-3,0)=""),"",(I9/OFFSET(I9,-3,0))^4-1),"") | ... BE9: =IFERROR(IF(OR(N9="",OFFSET(N9,-3,0)=""),"",(N9/OFFSET(N9,-3,0))^4-1),"") | BG9: =IFERROR(IF(OR(B9="",OFFSET(B9,-6,0)=""),"",(B9/OFFSET(B9,-6,0))^2-1),"") | BH9: =IFERROR(IF(OR(C9="",OFFSET(C9,-6,0)=""),"",(C9/OFFSET(C9,-6,0))^2-1),"") | BI9: =IFERROR(IF(OR(D9="",OFFSET(D9,-6,0)=""),"",(D9/OFFSET(D9,-6,0))^2-1),"") | BJ9: =IFERROR(IF(OR(E9="",OFFSET(E9,-6,0)=""),"",(E9/OFFSET(E9,-6,0))^2-1),"") | BK9: =IFERROR(IF(OR(F9="",OFFSET(F9,-6,0)=""),"",(F9/OFFSET(F9,-6,0))^2-1),"") | BL9: =IFERROR(IF(OR(G9="",OFFSET(G9,-6,0)=""),"",(G9/OFFSET(G9,-6,0))^2-1),"") | BM9: =IFERROR(IF(OR(H9="",OFFSET(H9,-6,0)=""),"",(H9/OFFSET(H9,-6,0))^2-1),"") | BN9: =IFERROR(IF(OR(I9="",OFFSET(I9,-6,0)=""),"",(I9/OFFSET(I9,-6,0))^2-1),"") | ... BS9: =IFERROR(IF(OR(N9="",OFFSET(N9,-6,0)=""),"",(N9/OFFSET(N9,-6,0))^2-1),"") | BX9: =IF('Macrobond Imports'!FG8="","",'Macrobond Imports'!FG8) | BY9: =IF('Macrobond Imports'!AI8="","",'Macrobond Imports'!AI8) | CA9: =IFERROR(IF(OR(BX9="",OFFSET(BX9,-12,0)=""),"",BX9/OFFSET(BX9,-12,0)-1),"") | CB9: =IFERROR(IF(OR(BY9="",OFFSET(BY9,-12,0)=""),"",BY9/OFFSET(BY9,-12,0)-1),"") | CC9: {=INDEX(MM_Headline,ROW()-5)} -> 0.0033604284 | CD9: {=INDEX(MM_Core,ROW()-5)} -> 0.004357968 | CE9: {=INDEX(YY_Headline,ROW()-5)} -> 0.021066084 | CF9: {=INDEX(YY_Core,ROW()-5)} -> 0.028396942 | CG9: {=INDEX(Ann3_Headline,ROW()-5)} -> 0.03327282 | CH9: {=INDEX(Ann6_Headline,ROW()-5)} -> 0.028847073 | CK9: {=INDEX(ChartDates,ROW()-5)} -> 45505 | CL9: {=INDEX(UnprocEnergy_YY,ROW()-5)} -> -0.081049979 | CM9: {=INDEX(Transport_YY,ROW()-5)} -> 0.0058462281 | DA9: Furnishings Wholesaling | DB9: FS | DC9: =INDEX('Macrobond Imports'!FS:FS,MATCH(MAX('Macrobond Imports'!$A:$A),'Macrobond Imports'!$A:$A,0)) -> 147.646 | DD9: {=INDEX('Macrobond Imports'!FS:FS,MATCH(MAX('Macrobond Imports'!$A:$A),'Macrobond Imports'!$A:$A,0)-1)} -> 147.479 | DE9: =IFERROR(IF(OR(DC9="",DD9="",DC9=0,DD9=0),"",DC9/DD9-1),"") -> 0.0011323646 | DF9: WH | DG9: =IF(DE9="","",DE9+ROW()*0.000000001) -> 0.0011323736
A10: =IF('Macrobond Imports'!A9="","",'Macrobond Imports'!A9) -> 17380 | B10: =IF('Macrobond Imports'!B9="","",'Macrobond Imports'!B9) | C10: =IF('Macrobond Imports'!C9="","",'Macrobond Imports'!C9) | D10: =IF('Macrobond Imports'!Z9="","",'Macrobond Imports'!Z9) | E10: =IF('Macrobond Imports'!BH9="","",'Macrobond Imports'!BH9) | F10: =IF('Macrobond Imports'!BJ9="","",'Macrobond Imports'!BJ9) | G10: =IF('Macrobond Imports'!BK9="","",'Macrobond Imports'!BK9) | H10: =IF('Macrobond Imports'!BL9="","",'Macrobond Imports'!BL9) | I10: =IF('Macrobond Imports'!BS9="","",'Macrobond Imports'!BS9) | J10: =IF('Macrobond Imports'!AA9="","",'Macrobond Imports'!AA9) | K10: =IF('Macrobond Imports'!DF9="","",'Macrobond Imports'!DF9) -> 23.3 | L10: =IF('Macrobond Imports'!EA9="","",'Macrobond Imports'!EA9) -> 31.6 | M10: =IF('Macrobond Imports'!FA9="","",'Macrobond Imports'!FA9) | N10: =IF('Macrobond Imports'!FC9="","",'Macrobond Imports'!FC9) | P10: =A10 -> 17380 | Q10: =IF(OR(B10="",N(B9)=0),"",B10/B9-1) | R10: =IF(OR(C10="",N(C9)=0),"",C10/C9-1) | S10: =IF(OR(D10="",N(D9)=0),"",D10/D9-1) | T10: =IF(OR(E10="",N(E9)=0),"",E10/E9-1) | U10: =IF(OR(F10="",N(F9)=0),"",F10/F9-1) | V10: =IF(OR(G10="",N(G9)=0),"",G10/G9-1) | W10: =IF(OR(H10="",N(H9)=0),"",H10/H9-1) | X10: =IF(OR(I10="",N(I9)=0),"",I10/I9-1) | ... AC10: =IF(OR(N10="",N(N9)=0),"",N10/N9-1) | AE10: =IFERROR(IF(OR(B10="",OFFSET(B10,-12,0)=""),"",B10/OFFSET(B10,-12,0)-1),"") | AF10: =IFERROR(IF(OR(C10="",OFFSET(C10,-12,0)=""),"",C10/OFFSET(C10,-12,0)-1),"") | AG10: =IFERROR(IF(OR(D10="",OFFSET(D10,-12,0)=""),"",D10/OFFSET(D10,-12,0)-1),"") | AH10: =IFERROR(IF(OR(E10="",OFFSET(E10,-12,0)=""),"",E10/OFFSET(E10,-12,0)-1),"") | AI10: =IFERROR(IF(OR(F10="",OFFSET(F10,-12,0)=""),"",F10/OFFSET(F10,-12,0)-1),"") | AJ10: =IFERROR(IF(OR(G10="",OFFSET(G10,-12,0)=""),"",G10/OFFSET(G10,-12,0)-1),"") | AK10: =IFERROR(IF(OR(H10="",OFFSET(H10,-12,0)=""),"",H10/OFFSET(H10,-12,0)-1),"") | AL10: =IFERROR(IF(OR(I10="",OFFSET(I10,-12,0)=""),"",I10/OFFSET(I10,-12,0)-1),"") | ... AQ10: =IFERROR(IF(OR(N10="",OFFSET(N10,-12,0)=""),"",N10/OFFSET(N10,-12,0)-1),"") | AS10: =IFERROR(IF(OR(B10="",OFFSET(B10,-3,0)=""),"",(B10/OFFSET(B10,-3,0))^4-1),"") | AT10: =IFERROR(IF(OR(C10="",OFFSET(C10,-3,0)=""),"",(C10/OFFSET(C10,-3,0))^4-1),"") | AU10: =IFERROR(IF(OR(D10="",OFFSET(D10,-3,0)=""),"",(D10/OFFSET(D10,-3,0))^4-1),"") | AV10: =IFERROR(IF(OR(E10="",OFFSET(E10,-3,0)=""),"",(E10/OFFSET(E10,-3,0))^4-1),"") | AW10: =IFERROR(IF(OR(F10="",OFFSET(F10,-3,0)=""),"",(F10/OFFSET(F10,-3,0))^4-1),"") | AX10: =IFERROR(IF(OR(G10="",OFFSET(G10,-3,0)=""),"",(G10/OFFSET(G10,-3,0))^4-1),"") | AY10: =IFERROR(IF(OR(H10="",OFFSET(H10,-3,0)=""),"",(H10/OFFSET(H10,-3,0))^4-1),"") | AZ10: =IFERROR(IF(OR(I10="",OFFSET(I10,-3,0)=""),"",(I10/OFFSET(I10,-3,0))^4-1),"") | ... BE10: =IFERROR(IF(OR(N10="",OFFSET(N10,-3,0)=""),"",(N10/OFFSET(N10,-3,0))^4-1),"") | BG10: =IFERROR(IF(OR(B10="",OFFSET(B10,-6,0)=""),"",(B10/OFFSET(B10,-6,0))^2-1),"") | BH10: =IFERROR(IF(OR(C10="",OFFSET(C10,-6,0)=""),"",(C10/OFFSET(C10,-6,0))^2-1),"") | BI10: =IFERROR(IF(OR(D10="",OFFSET(D10,-6,0)=""),"",(D10/OFFSET(D10,-6,0))^2-1),"") | BJ10: =IFERROR(IF(OR(E10="",OFFSET(E10,-6,0)=""),"",(E10/OFFSET(E10,-6,0))^2-1),"") | BK10: =IFERROR(IF(OR(F10="",OFFSET(F10,-6,0)=""),"",(F10/OFFSET(F10,-6,0))^2-1),"") | BL10: =IFERROR(IF(OR(G10="",OFFSET(G10,-6,0)=""),"",(G10/OFFSET(G10,-6,0))^2-1),"") | BM10: =IFERROR(IF(OR(H10="",OFFSET(H10,-6,0)=""),"",(H10/OFFSET(H10,-6,0))^2-1),"") | BN10: =IFERROR(IF(OR(I10="",OFFSET(I10,-6,0)=""),"",(I10/OFFSET(I10,-6,0))^2-1),"") | ... BS10: =IFERROR(IF(OR(N10="",OFFSET(N10,-6,0)=""),"",(N10/OFFSET(N10,-6,0))^2-1),"") | BX10: =IF('Macrobond Imports'!FG9="","",'Macrobond Imports'!FG9) | BY10: =IF('Macrobond Imports'!AI9="","",'Macrobond Imports'!AI9) | CA10: =IFERROR(IF(OR(BX10="",OFFSET(BX10,-12,0)=""),"",BX10/OFFSET(BX10,-12,0)-1),"") | CB10: =IFERROR(IF(OR(BY10="",OFFSET(BY10,-12,0)=""),"",BY10/OFFSET(BY10,-12,0)-1),"") | CC10: {=INDEX(MM_Headline,ROW()-5)} -> 0.0027095984 | CD10: {=INDEX(MM_Core,ROW()-5)} -> 0.0043946874 | CE10: {=INDEX(YY_Headline,ROW()-5)} -> 0.021429973 | CF10: {=INDEX(YY_Core,ROW()-5)} -> 0.033064176 | CG10: {=INDEX(Ann3_Headline,ROW()-5)} -> 0.026039288 | CH10: {=INDEX(Ann6_Headline,ROW()-5)} -> 0.032053038 | CK10: {=INDEX(ChartDates,ROW()-5)} -> 45536 | CL10: {=INDEX(UnprocEnergy_YY,ROW()-5)} -> -0.22155365 | CM10: {=INDEX(Transport_YY,ROW()-5)} -> 0.0020138629 | DA10: Chemicals & Allied Products Wholesaling | DB10: FT | DC10: =INDEX('Macrobond Imports'!FT:FT,MATCH(MAX('Macrobond Imports'!$A:$A),'Macrobond Imports'!$A:$A,0)) -> 145.504 | DD10: {=INDEX('Macrobond Imports'!FT:FT,MATCH(MAX('Macrobond Imports'!$A:$A),'Macrobond Imports'!$A:$A,0)-1)} -> 135.553 | DE10: =IFERROR(IF(OR(DC10="",DD10="",DC10=0,DD10=0),"",DC10/DD10-1),"") -> 0.0734104 | DF10: WH | DG10: =IF(DE10="","",DE10+ROW()*0.000000001) -> 0.07341041
A11: =IF('Macrobond Imports'!A10="","",'Macrobond Imports'!A10) -> 17411 | B11: =IF('Macrobond Imports'!B10="","",'Macrobond Imports'!B10) | C11: =IF('Macrobond Imports'!C10="","",'Macrobond Imports'!C10) | D11: =IF('Macrobond Imports'!Z10="","",'Macrobond Imports'!Z10) | E11: =IF('Macrobond Imports'!BH10="","",'Macrobond Imports'!BH10) | F11: =IF('Macrobond Imports'!BJ10="","",'Macrobond Imports'!BJ10) | G11: =IF('Macrobond Imports'!BK10="","",'Macrobond Imports'!BK10) | H11: =IF('Macrobond Imports'!BL10="","",'Macrobond Imports'!BL10) | I11: =IF('Macrobond Imports'!BS10="","",'Macrobond Imports'!BS10) | J11: =IF('Macrobond Imports'!AA10="","",'Macrobond Imports'!AA10) | K11: =IF('Macrobond Imports'!DF10="","",'Macrobond Imports'!DF10) -> 23.7 | L11: =IF('Macrobond Imports'!EA10="","",'Macrobond Imports'!EA10) -> 32.4 | M11: =IF('Macrobond Imports'!FA10="","",'Macrobond Imports'!FA10) | N11: =IF('Macrobond Imports'!FC10="","",'Macrobond Imports'!FC10) | P11: =A11 -> 17411 | Q11: =IF(OR(B11="",N(B10)=0),"",B11/B10-1) | R11: =IF(OR(C11="",N(C10)=0),"",C11/C10-1) | S11: =IF(OR(D11="",N(D10)=0),"",D11/D10-1) | T11: =IF(OR(E11="",N(E10)=0),"",E11/E10-1) | U11: =IF(OR(F11="",N(F10)=0),"",F11/F10-1) | V11: =IF(OR(G11="",N(G10)=0),"",G11/G10-1) | W11: =IF(OR(H11="",N(H10)=0),"",H11/H10-1) | X11: =IF(OR(I11="",N(I10)=0),"",I11/I10-1) | ... AC11: =IF(OR(N11="",N(N10)=0),"",N11/N10-1) | AE11: =IFERROR(IF(OR(B11="",OFFSET(B11,-12,0)=""),"",B11/OFFSET(B11,-12,0)-1),"") | AF11: =IFERROR(IF(OR(C11="",OFFSET(C11,-12,0)=""),"",C11/OFFSET(C11,-12,0)-1),"") | AG11: =IFERROR(IF(OR(D11="",OFFSET(D11,-12,0)=""),"",D11/OFFSET(D11,-12,0)-1),"") | AH11: =IFERROR(IF(OR(E11="",OFFSET(E11,-12,0)=""),"",E11/OFFSET(E11,-12,0)-1),"") | AI11: =IFERROR(IF(OR(F11="",OFFSET(F11,-12,0)=""),"",F11/OFFSET(F11,-12,0)-1),"") | AJ11: =IFERROR(IF(OR(G11="",OFFSET(G11,-12,0)=""),"",G11/OFFSET(G11,-12,0)-1),"") | AK11: =IFERROR(IF(OR(H11="",OFFSET(H11,-12,0)=""),"",H11/OFFSET(H11,-12,0)-1),"") | AL11: =IFERROR(IF(OR(I11="",OFFSET(I11,-12,0)=""),"",I11/OFFSET(I11,-12,0)-1),"") | ... AQ11: =IFERROR(IF(OR(N11="",OFFSET(N11,-12,0)=""),"",N11/OFFSET(N11,-12,0)-1),"") | AS11: =IFERROR(IF(OR(B11="",OFFSET(B11,-3,0)=""),"",(B11/OFFSET(B11,-3,0))^4-1),"") | AT11: =IFERROR(IF(OR(C11="",OFFSET(C11,-3,0)=""),"",(C11/OFFSET(C11,-3,0))^4-1),"") | AU11: =IFERROR(IF(OR(D11="",OFFSET(D11,-3,0)=""),"",(D11/OFFSET(D11,-3,0))^4-1),"") | AV11: =IFERROR(IF(OR(E11="",OFFSET(E11,-3,0)=""),"",(E11/OFFSET(E11,-3,0))^4-1),"") | AW11: =IFERROR(IF(OR(F11="",OFFSET(F11,-3,0)=""),"",(F11/OFFSET(F11,-3,0))^4-1),"") | AX11: =IFERROR(IF(OR(G11="",OFFSET(G11,-3,0)=""),"",(G11/OFFSET(G11,-3,0))^4-1),"") | AY11: =IFERROR(IF(OR(H11="",OFFSET(H11,-3,0)=""),"",(H11/OFFSET(H11,-3,0))^4-1),"") | AZ11: =IFERROR(IF(OR(I11="",OFFSET(I11,-3,0)=""),"",(I11/OFFSET(I11,-3,0))^4-1),"") | ... BE11: =IFERROR(IF(OR(N11="",OFFSET(N11,-3,0)=""),"",(N11/OFFSET(N11,-3,0))^4-1),"") | BG11: =IFERROR(IF(OR(B11="",OFFSET(B11,-6,0)=""),"",(B11/OFFSET(B11,-6,0))^2-1),"") | BH11: =IFERROR(IF(OR(C11="",OFFSET(C11,-6,0)=""),"",(C11/OFFSET(C11,-6,0))^2-1),"") | BI11: =IFERROR(IF(OR(D11="",OFFSET(D11,-6,0)=""),"",(D11/OFFSET(D11,-6,0))^2-1),"") | BJ11: =IFERROR(IF(OR(E11="",OFFSET(E11,-6,0)=""),"",(E11/OFFSET(E11,-6,0))^2-1),"") | BK11: =IFERROR(IF(OR(F11="",OFFSET(F11,-6,0)=""),"",(F11/OFFSET(F11,-6,0))^2-1),"") | BL11: =IFERROR(IF(OR(G11="",OFFSET(G11,-6,0)=""),"",(G11/OFFSET(G11,-6,0))^2-1),"") | BM11: =IFERROR(IF(OR(H11="",OFFSET(H11,-6,0)=""),"",(H11/OFFSET(H11,-6,0))^2-1),"") | BN11: =IFERROR(IF(OR(I11="",OFFSET(I11,-6,0)=""),"",(I11/OFFSET(I11,-6,0))^2-1),"") | ... BS11: =IFERROR(IF(OR(N11="",OFFSET(N11,-6,0)=""),"",(N11/OFFSET(N11,-6,0))^2-1),"") | BX11: =IF('Macrobond Imports'!FG10="","",'Macrobond Imports'!FG10) | BY11: =IF('Macrobond Imports'!AI10="","",'Macrobond Imports'!AI10) | CA11: =IFERROR(IF(OR(BX11="",OFFSET(BX11,-12,0)=""),"",BX11/OFFSET(BX11,-12,0)-1),"") | CB11: =IFERROR(IF(OR(BY11="",OFFSET(BY11,-12,0)=""),"",BY11/OFFSET(BY11,-12,0)-1),"") | CC11: {=INDEX(MM_Headline,ROW()-5)} -> 0.0033675576 | CD11: {=INDEX(MM_Core,ROW()-5)} -> 0.0032608244 | CE11: {=INDEX(YY_Headline,ROW()-5)} -> 0.028436052 | CF11: {=INDEX(YY_Core,ROW()-5)} -> 0.035951217 | CG11: {=INDEX(Ann3_Headline,ROW()-5)} -> 0.038409812 | CH11: {=INDEX(Ann6_Headline,ROW()-5)} -> 0.029296697 | CK11: {=INDEX(ChartDates,ROW()-5)} -> 45566 | CL11: {=INDEX(UnprocEnergy_YY,ROW()-5)} -> -0.14423618 | CM11: {=INDEX(Transport_YY,ROW()-5)} -> 0.00089952026 | DA11: Paper & Plastics Wholesaling | DB11: FU | DC11: =INDEX('Macrobond Imports'!FU:FU,MATCH(MAX('Macrobond Imports'!$A:$A),'Macrobond Imports'!$A:$A,0)) -> 210.55 | DD11: {=INDEX('Macrobond Imports'!FU:FU,MATCH(MAX('Macrobond Imports'!$A:$A),'Macrobond Imports'!$A:$A,0)-1)} -> 216.409 | DE11: =IFERROR(IF(OR(DC11="",DD11="",DC11=0,DD11=0),"",DC11/DD11-1),"") -> -0.027073735 | DF11: WH | DG11: =IF(DE11="","",DE11+ROW()*0.000000001) -> -0.027073724
A12: =IF('Macrobond Imports'!A11="","",'Macrobond Imports'!A11) -> 17441 | B12: =IF('Macrobond Imports'!B11="","",'Macrobond Imports'!B11) | C12: =IF('Macrobond Imports'!C11="","",'Macrobond Imports'!C11) | D12: =IF('Macrobond Imports'!Z11="","",'Macrobond Imports'!Z11) | E12: =IF('Macrobond Imports'!BH11="","",'Macrobond Imports'!BH11) | F12: =IF('Macrobond Imports'!BJ11="","",'Macrobond Imports'!BJ11) | G12: =IF('Macrobond Imports'!BK11="","",'Macrobond Imports'!BK11) | H12: =IF('Macrobond Imports'!BL11="","",'Macrobond Imports'!BL11) | I12: =IF('Macrobond Imports'!BS11="","",'Macrobond Imports'!BS11) | J12: =IF('Macrobond Imports'!AA11="","",'Macrobond Imports'!AA11) | K12: =IF('Macrobond Imports'!DF11="","",'Macrobond Imports'!DF11) -> 24 | L12: =IF('Macrobond Imports'!EA11="","",'Macrobond Imports'!EA11) -> 33.7 | M12: =IF('Macrobond Imports'!FA11="","",'Macrobond Imports'!FA11) | N12: =IF('Macrobond Imports'!FC11="","",'Macrobond Imports'!FC11) | P12: =A12 -> 17441 | Q12: =IF(OR(B12="",N(B11)=0),"",B12/B11-1) | R12: =IF(OR(C12="",N(C11)=0),"",C12/C11-1) | S12: =IF(OR(D12="",N(D11)=0),"",D12/D11-1) | T12: =IF(OR(E12="",N(E11)=0),"",E12/E11-1) | U12: =IF(OR(F12="",N(F11)=0),"",F12/F11-1) | V12: =IF(OR(G12="",N(G11)=0),"",G12/G11-1) | W12: =IF(OR(H12="",N(H11)=0),"",H12/H11-1) | X12: =IF(OR(I12="",N(I11)=0),"",I12/I11-1) | ... AC12: =IF(OR(N12="",N(N11)=0),"",N12/N11-1) | AE12: =IFERROR(IF(OR(B12="",OFFSET(B12,-12,0)=""),"",B12/OFFSET(B12,-12,0)-1),"") | AF12: =IFERROR(IF(OR(C12="",OFFSET(C12,-12,0)=""),"",C12/OFFSET(C12,-12,0)-1),"") | AG12: =IFERROR(IF(OR(D12="",OFFSET(D12,-12,0)=""),"",D12/OFFSET(D12,-12,0)-1),"") | AH12: =IFERROR(IF(OR(E12="",OFFSET(E12,-12,0)=""),"",E12/OFFSET(E12,-12,0)-1),"") | AI12: =IFERROR(IF(OR(F12="",OFFSET(F12,-12,0)=""),"",F12/OFFSET(F12,-12,0)-1),"") | AJ12: =IFERROR(IF(OR(G12="",OFFSET(G12,-12,0)=""),"",G12/OFFSET(G12,-12,0)-1),"") | AK12: =IFERROR(IF(OR(H12="",OFFSET(H12,-12,0)=""),"",H12/OFFSET(H12,-12,0)-1),"") | AL12: =IFERROR(IF(OR(I12="",OFFSET(I12,-12,0)=""),"",I12/OFFSET(I12,-12,0)-1),"") | ... AQ12: =IFERROR(IF(OR(N12="",OFFSET(N12,-12,0)=""),"",N12/OFFSET(N12,-12,0)-1),"") | AS12: =IFERROR(IF(OR(B12="",OFFSET(B12,-3,0)=""),"",(B12/OFFSET(B12,-3,0))^4-1),"") | AT12: =IFERROR(IF(OR(C12="",OFFSET(C12,-3,0)=""),"",(C12/OFFSET(C12,-3,0))^4-1),"") | AU12: =IFERROR(IF(OR(D12="",OFFSET(D12,-3,0)=""),"",(D12/OFFSET(D12,-3,0))^4-1),"") | AV12: =IFERROR(IF(OR(E12="",OFFSET(E12,-3,0)=""),"",(E12/OFFSET(E12,-3,0))^4-1),"") | AW12: =IFERROR(IF(OR(F12="",OFFSET(F12,-3,0)=""),"",(F12/OFFSET(F12,-3,0))^4-1),"") | AX12: =IFERROR(IF(OR(G12="",OFFSET(G12,-3,0)=""),"",(G12/OFFSET(G12,-3,0))^4-1),"") | AY12: =IFERROR(IF(OR(H12="",OFFSET(H12,-3,0)=""),"",(H12/OFFSET(H12,-3,0))^4-1),"") | AZ12: =IFERROR(IF(OR(I12="",OFFSET(I12,-3,0)=""),"",(I12/OFFSET(I12,-3,0))^4-1),"") | ... BE12: =IFERROR(IF(OR(N12="",OFFSET(N12,-3,0)=""),"",(N12/OFFSET(N12,-3,0))^4-1),"") | BG12: =IFERROR(IF(OR(B12="",OFFSET(B12,-6,0)=""),"",(B12/OFFSET(B12,-6,0))^2-1),"") | BH12: =IFERROR(IF(OR(C12="",OFFSET(C12,-6,0)=""),"",(C12/OFFSET(C12,-6,0))^2-1),"") | BI12: =IFERROR(IF(OR(D12="",OFFSET(D12,-6,0)=""),"",(D12/OFFSET(D12,-6,0))^2-1),"") | BJ12: =IFERROR(IF(OR(E12="",OFFSET(E12,-6,0)=""),"",(E12/OFFSET(E12,-6,0))^2-1),"") | BK12: =IFERROR(IF(OR(F12="",OFFSET(F12,-6,0)=""),"",(F12/OFFSET(F12,-6,0))^2-1),"") | BL12: =IFERROR(IF(OR(G12="",OFFSET(G12,-6,0)=""),"",(G12/OFFSET(G12,-6,0))^2-1),"") | BM12: =IFERROR(IF(OR(H12="",OFFSET(H12,-6,0)=""),"",(H12/OFFSET(H12,-6,0))^2-1),"") | BN12: =IFERROR(IF(OR(I12="",OFFSET(I12,-6,0)=""),"",(I12/OFFSET(I12,-6,0))^2-1),"") | ... BS12: =IFERROR(IF(OR(N12="",OFFSET(N12,-6,0)=""),"",(N12/OFFSET(N12,-6,0))^2-1),"") | BX12: =IF('Macrobond Imports'!FG11="","",'Macrobond Imports'!FG11) | BY12: =IF('Macrobond Imports'!AI11="","",'Macrobond Imports'!AI11) | CA12: =IFERROR(IF(OR(BX12="",OFFSET(BX12,-12,0)=""),"",BX12/OFFSET(BX12,-12,0)-1),"") | CB12: =IFERROR(IF(OR(BY12="",OFFSET(BY12,-12,0)=""),"",BY12/OFFSET(BY12,-12,0)-1),"") | CC12: {=INDEX(MM_Headline,ROW()-5)} -> 0.0010458392 | CD12: {=INDEX(MM_Core,ROW()-5)} -> -3.4503461e-05 | CE12: {=INDEX(YY_Headline,ROW()-5)} -> 0.02889682 | CF12: {=INDEX(YY_Core,ROW()-5)} -> 0.033713316 | CG12: {=INDEX(Ann3_Headline,ROW()-5)} -> 0.028861146 | CH12: {=INDEX(Ann6_Headline,ROW()-5)} -> 0.031064624 | CK12: {=INDEX(ChartDates,ROW()-5)} -> 45597 | CL12: {=INDEX(UnprocEnergy_YY,ROW()-5)} -> -0.12329211 | CM12: {=INDEX(Transport_YY,ROW()-5)} -> -0.0012733418 | DA12: Apparel Wholesaling | DB12: FV | DC12: =INDEX('Macrobond Imports'!FV:FV,MATCH(MAX('Macrobond Imports'!$A:$A),'Macrobond Imports'!$A:$A,0)) -> 132.77 | DD12: {=INDEX('Macrobond Imports'!FV:FV,MATCH(MAX('Macrobond Imports'!$A:$A),'Macrobond Imports'!$A:$A,0)-1)} -> 134.482 | DE12: =IFERROR(IF(OR(DC12="",DD12="",DC12=0,DD12=0),"",DC12/DD12-1),"") -> -0.012730328 | DF12: WH | DG12: =IF(DE12="","",DE12+ROW()*0.000000001) -> -0.012730316
A13: =IF('Macrobond Imports'!A12="","",'Macrobond Imports'!A12) -> 17472 | B13: =IF('Macrobond Imports'!B12="","",'Macrobond Imports'!B12) | C13: =IF('Macrobond Imports'!C12="","",'Macrobond Imports'!C12) | D13: =IF('Macrobond Imports'!Z12="","",'Macrobond Imports'!Z12) | E13: =IF('Macrobond Imports'!BH12="","",'Macrobond Imports'!BH12) | F13: =IF('Macrobond Imports'!BJ12="","",'Macrobond Imports'!BJ12) | G13: =IF('Macrobond Imports'!BK12="","",'Macrobond Imports'!BK12) | H13: =IF('Macrobond Imports'!BL12="","",'Macrobond Imports'!BL12) | I13: =IF('Macrobond Imports'!BS12="","",'Macrobond Imports'!BS12) | J13: =IF('Macrobond Imports'!AA12="","",'Macrobond Imports'!AA12) | K13: =IF('Macrobond Imports'!DF12="","",'Macrobond Imports'!DF12) -> 24.3 | L13: =IF('Macrobond Imports'!EA12="","",'Macrobond Imports'!EA12) -> 33.9 | M13: =IF('Macrobond Imports'!FA12="","",'Macrobond Imports'!FA12) | N13: =IF('Macrobond Imports'!FC12="","",'Macrobond Imports'!FC12) | P13: =A13 -> 17472 | Q13: =IF(OR(B13="",N(B12)=0),"",B13/B12-1) | R13: =IF(OR(C13="",N(C12)=0),"",C13/C12-1) | S13: =IF(OR(D13="",N(D12)=0),"",D13/D12-1) | T13: =IF(OR(E13="",N(E12)=0),"",E13/E12-1) | U13: =IF(OR(F13="",N(F12)=0),"",F13/F12-1) | V13: =IF(OR(G13="",N(G12)=0),"",G13/G12-1) | W13: =IF(OR(H13="",N(H12)=0),"",H13/H12-1) | X13: =IF(OR(I13="",N(I12)=0),"",I13/I12-1) | ... AC13: =IF(OR(N13="",N(N12)=0),"",N13/N12-1) | AE13: =IFERROR(IF(OR(B13="",OFFSET(B13,-12,0)=""),"",B13/OFFSET(B13,-12,0)-1),"") | AF13: =IFERROR(IF(OR(C13="",OFFSET(C13,-12,0)=""),"",C13/OFFSET(C13,-12,0)-1),"") | AG13: =IFERROR(IF(OR(D13="",OFFSET(D13,-12,0)=""),"",D13/OFFSET(D13,-12,0)-1),"") | AH13: =IFERROR(IF(OR(E13="",OFFSET(E13,-12,0)=""),"",E13/OFFSET(E13,-12,0)-1),"") | AI13: =IFERROR(IF(OR(F13="",OFFSET(F13,-12,0)=""),"",F13/OFFSET(F13,-12,0)-1),"") | AJ13: =IFERROR(IF(OR(G13="",OFFSET(G13,-12,0)=""),"",G13/OFFSET(G13,-12,0)-1),"") | AK13: =IFERROR(IF(OR(H13="",OFFSET(H13,-12,0)=""),"",H13/OFFSET(H13,-12,0)-1),"") | AL13: =IFERROR(IF(OR(I13="",OFFSET(I13,-12,0)=""),"",I13/OFFSET(I13,-12,0)-1),"") | ... AQ13: =IFERROR(IF(OR(N13="",OFFSET(N13,-12,0)=""),"",N13/OFFSET(N13,-12,0)-1),"") | AS13: =IFERROR(IF(OR(B13="",OFFSET(B13,-3,0)=""),"",(B13/OFFSET(B13,-3,0))^4-1),"") | AT13: =IFERROR(IF(OR(C13="",OFFSET(C13,-3,0)=""),"",(C13/OFFSET(C13,-3,0))^4-1),"") | AU13: =IFERROR(IF(OR(D13="",OFFSET(D13,-3,0)=""),"",(D13/OFFSET(D13,-3,0))^4-1),"") | AV13: =IFERROR(IF(OR(E13="",OFFSET(E13,-3,0)=""),"",(E13/OFFSET(E13,-3,0))^4-1),"") | AW13: =IFERROR(IF(OR(F13="",OFFSET(F13,-3,0)=""),"",(F13/OFFSET(F13,-3,0))^4-1),"") | AX13: =IFERROR(IF(OR(G13="",OFFSET(G13,-3,0)=""),"",(G13/OFFSET(G13,-3,0))^4-1),"") | AY13: =IFERROR(IF(OR(H13="",OFFSET(H13,-3,0)=""),"",(H13/OFFSET(H13,-3,0))^4-1),"") | AZ13: =IFERROR(IF(OR(I13="",OFFSET(I13,-3,0)=""),"",(I13/OFFSET(I13,-3,0))^4-1),"") | ... BE13: =IFERROR(IF(OR(N13="",OFFSET(N13,-3,0)=""),"",(N13/OFFSET(N13,-3,0))^4-1),"") | BG13: =IFERROR(IF(OR(B13="",OFFSET(B13,-6,0)=""),"",(B13/OFFSET(B13,-6,0))^2-1),"") | BH13: =IFERROR(IF(OR(C13="",OFFSET(C13,-6,0)=""),"",(C13/OFFSET(C13,-6,0))^2-1),"") | BI13: =IFERROR(IF(OR(D13="",OFFSET(D13,-6,0)=""),"",(D13/OFFSET(D13,-6,0))^2-1),"") | BJ13: =IFERROR(IF(OR(E13="",OFFSET(E13,-6,0)=""),"",(E13/OFFSET(E13,-6,0))^2-1),"") | BK13: =IFERROR(IF(OR(F13="",OFFSET(F13,-6,0)=""),"",(F13/OFFSET(F13,-6,0))^2-1),"") | BL13: =IFERROR(IF(OR(G13="",OFFSET(G13,-6,0)=""),"",(G13/OFFSET(G13,-6,0))^2-1),"") | BM13: =IFERROR(IF(OR(H13="",OFFSET(H13,-6,0)=""),"",(H13/OFFSET(H13,-6,0))^2-1),"") | BN13: =IFERROR(IF(OR(I13="",OFFSET(I13,-6,0)=""),"",(I13/OFFSET(I13,-6,0))^2-1),"") | ... BS13: =IFERROR(IF(OR(N13="",OFFSET(N13,-6,0)=""),"",(N13/OFFSET(N13,-6,0))^2-1),"") | BX13: =IF('Macrobond Imports'!FG12="","",'Macrobond Imports'!FG12) | BY13: =IF('Macrobond Imports'!AI12="","",'Macrobond Imports'!AI12) | CA13: =IFERROR(IF(OR(BX13="",OFFSET(BX13,-12,0)=""),"",BX13/OFFSET(BX13,-12,0)-1),"") | CB13: =IFERROR(IF(OR(BY13="",OFFSET(BY13,-12,0)=""),"",BY13/OFFSET(BY13,-12,0)-1),"") | CC13: {=INDEX(MM_Headline,ROW()-5)} -> 0.0041311874 | CD13: {=INDEX(MM_Core,ROW()-5)} -> 0.0031813288 | CE13: {=INDEX(YY_Headline,ROW()-5)} -> 0.03437555 | CF13: {=INDEX(YY_Core,ROW()-5)} -> 0.037327491 | CG13: {=INDEX(Ann3_Headline,ROW()-5)} -> 0.034708227 | CH13: {=INDEX(Ann6_Headline,ROW()-5)} -> 0.030364641 | CK13: {=INDEX(ChartDates,ROW()-5)} -> 45627 | CL13: {=INDEX(UnprocEnergy_YY,ROW()-5)} -> 0.024996944 | CM13: {=INDEX(Transport_YY,ROW()-5)} -> 0.029559592 | DA13: Food & Alcohol Wholesaling | DB13: FW | DC13: =INDEX('Macrobond Imports'!FW:FW,MATCH(MAX('Macrobond Imports'!$A:$A),'Macrobond Imports'!$A:$A,0)) -> 160.521 | DD13: {=INDEX('Macrobond Imports'!FW:FW,MATCH(MAX('Macrobond Imports'!$A:$A),'Macrobond Imports'!$A:$A,0)-1)} -> 160.745 | DE13: =IFERROR(IF(OR(DC13="",DD13="",DC13=0,DD13=0),"",DC13/DD13-1),"") -> -0.0013935115 | DF13: WH | DG13: =IF(DE13="","",DE13+ROW()*0.000000001) -> -0.0013934985
A14: =IF('Macrobond Imports'!A13="","",'Macrobond Imports'!A13) -> 17502 | B14: =IF('Macrobond Imports'!B13="","",'Macrobond Imports'!B13) | C14: =IF('Macrobond Imports'!C13="","",'Macrobond Imports'!C13) | D14: =IF('Macrobond Imports'!Z13="","",'Macrobond Imports'!Z13) | E14: =IF('Macrobond Imports'!BH13="","",'Macrobond Imports'!BH13) | F14: =IF('Macrobond Imports'!BJ13="","",'Macrobond Imports'!BJ13) | G14: =IF('Macrobond Imports'!BK13="","",'Macrobond Imports'!BK13) | H14: =IF('Macrobond Imports'!BL13="","",'Macrobond Imports'!BL13) | I14: =IF('Macrobond Imports'!BS13="","",'Macrobond Imports'!BS13) | J14: =IF('Macrobond Imports'!AA13="","",'Macrobond Imports'!AA13) | K14: =IF('Macrobond Imports'!DF13="","",'Macrobond Imports'!DF13) -> 24.5 | L14: =IF('Macrobond Imports'!EA13="","",'Macrobond Imports'!EA13) -> 35.3 | M14: =IF('Macrobond Imports'!FA13="","",'Macrobond Imports'!FA13) | N14: =IF('Macrobond Imports'!FC13="","",'Macrobond Imports'!FC13) | P14: =A14 -> 17502 | Q14: =IF(OR(B14="",N(B13)=0),"",B14/B13-1) | R14: =IF(OR(C14="",N(C13)=0),"",C14/C13-1) | S14: =IF(OR(D14="",N(D13)=0),"",D14/D13-1) | T14: =IF(OR(E14="",N(E13)=0),"",E14/E13-1) | U14: =IF(OR(F14="",N(F13)=0),"",F14/F13-1) | V14: =IF(OR(G14="",N(G13)=0),"",G14/G13-1) | W14: =IF(OR(H14="",N(H13)=0),"",H14/H13-1) | X14: =IF(OR(I14="",N(I13)=0),"",I14/I13-1) | ... AC14: =IF(OR(N14="",N(N13)=0),"",N14/N13-1) | AE14: =IFERROR(IF(OR(B14="",OFFSET(B14,-12,0)=""),"",B14/OFFSET(B14,-12,0)-1),"") | AF14: =IFERROR(IF(OR(C14="",OFFSET(C14,-12,0)=""),"",C14/OFFSET(C14,-12,0)-1),"") | AG14: =IFERROR(IF(OR(D14="",OFFSET(D14,-12,0)=""),"",D14/OFFSET(D14,-12,0)-1),"") | AH14: =IFERROR(IF(OR(E14="",OFFSET(E14,-12,0)=""),"",E14/OFFSET(E14,-12,0)-1),"") | AI14: =IFERROR(IF(OR(F14="",OFFSET(F14,-12,0)=""),"",F14/OFFSET(F14,-12,0)-1),"") | AJ14: =IFERROR(IF(OR(G14="",OFFSET(G14,-12,0)=""),"",G14/OFFSET(G14,-12,0)-1),"") | AK14: =IFERROR(IF(OR(H14="",OFFSET(H14,-12,0)=""),"",H14/OFFSET(H14,-12,0)-1),"") | AL14: =IFERROR(IF(OR(I14="",OFFSET(I14,-12,0)=""),"",I14/OFFSET(I14,-12,0)-1),"") | ... AQ14: =IFERROR(IF(OR(N14="",OFFSET(N14,-12,0)=""),"",N14/OFFSET(N14,-12,0)-1),"") | AS14: =IFERROR(IF(OR(B14="",OFFSET(B14,-3,0)=""),"",(B14/OFFSET(B14,-3,0))^4-1),"") | AT14: =IFERROR(IF(OR(C14="",OFFSET(C14,-3,0)=""),"",(C14/OFFSET(C14,-3,0))^4-1),"") | AU14: =IFERROR(IF(OR(D14="",OFFSET(D14,-3,0)=""),"",(D14/OFFSET(D14,-3,0))^4-1),"") | AV14: =IFERROR(IF(OR(E14="",OFFSET(E14,-3,0)=""),"",(E14/OFFSET(E14,-3,0))^4-1),"") | AW14: =IFERROR(IF(OR(F14="",OFFSET(F14,-3,0)=""),"",(F14/OFFSET(F14,-3,0))^4-1),"") | AX14: =IFERROR(IF(OR(G14="",OFFSET(G14,-3,0)=""),"",(G14/OFFSET(G14,-3,0))^4-1),"") | AY14: =IFERROR(IF(OR(H14="",OFFSET(H14,-3,0)=""),"",(H14/OFFSET(H14,-3,0))^4-1),"") | AZ14: =IFERROR(IF(OR(I14="",OFFSET(I14,-3,0)=""),"",(I14/OFFSET(I14,-3,0))^4-1),"") | ... BE14: =IFERROR(IF(OR(N14="",OFFSET(N14,-3,0)=""),"",(N14/OFFSET(N14,-3,0))^4-1),"") | BG14: =IFERROR(IF(OR(B14="",OFFSET(B14,-6,0)=""),"",(B14/OFFSET(B14,-6,0))^2-1),"") | BH14: =IFERROR(IF(OR(C14="",OFFSET(C14,-6,0)=""),"",(C14/OFFSET(C14,-6,0))^2-1),"") | BI14: =IFERROR(IF(OR(D14="",OFFSET(D14,-6,0)=""),"",(D14/OFFSET(D14,-6,0))^2-1),"") | BJ14: =IFERROR(IF(OR(E14="",OFFSET(E14,-6,0)=""),"",(E14/OFFSET(E14,-6,0))^2-1),"") | BK14: =IFERROR(IF(OR(F14="",OFFSET(F14,-6,0)=""),"",(F14/OFFSET(F14,-6,0))^2-1),"") | BL14: =IFERROR(IF(OR(G14="",OFFSET(G14,-6,0)=""),"",(G14/OFFSET(G14,-6,0))^2-1),"") | BM14: =IFERROR(IF(OR(H14="",OFFSET(H14,-6,0)=""),"",(H14/OFFSET(H14,-6,0))^2-1),"") | BN14: =IFERROR(IF(OR(I14="",OFFSET(I14,-6,0)=""),"",(I14/OFFSET(I14,-6,0))^2-1),"") | ... BS14: =IFERROR(IF(OR(N14="",OFFSET(N14,-6,0)=""),"",(N14/OFFSET(N14,-6,0))^2-1),"") | BX14: =IF('Macrobond Imports'!FG13="","",'Macrobond Imports'!FG13) | BY14: =IF('Macrobond Imports'!AI13="","",'Macrobond Imports'!AI13) | CA14: =IFERROR(IF(OR(BX14="",OFFSET(BX14,-12,0)=""),"",BX14/OFFSET(BX14,-12,0)-1),"") | CB14: =IFERROR(IF(OR(BY14="",OFFSET(BY14,-12,0)=""),"",BY14/OFFSET(BY14,-12,0)-1),"") | CC14: {=INDEX(MM_Headline,ROW()-5)} -> 0.0062766912 | CD14: {=INDEX(MM_Core,ROW()-5)} -> 0.005572027 | CE14: {=INDEX(YY_Headline,ROW()-5)} -> 0.037867523 | CF14: {=INDEX(YY_Core,ROW()-5)} -> 0.039096098 | CG14: {=INDEX(Ann3_Headline,ROW()-5)} -> 0.046760524 | CH14: {=INDEX(Ann6_Headline,ROW()-5)} -> 0.042576807 | CK14: {=INDEX(ChartDates,ROW()-5)} -> 45658 | CL14: {=INDEX(UnprocEnergy_YY,ROW()-5)} -> 0.081114412 | CM14: {=INDEX(Transport_YY,ROW()-5)} -> 0.036323725 | DA14: Food & Alcohol Retailing | DB14: FX | DC14: =INDEX('Macrobond Imports'!FX:FX,MATCH(MAX('Macrobond Imports'!$A:$A),'Macrobond Imports'!$A:$A,0)) -> 196.376 | DD14: {=INDEX('Macrobond Imports'!FX:FX,MATCH(MAX('Macrobond Imports'!$A:$A),'Macrobond Imports'!$A:$A,0)-1)} -> 198.562 | DE14: =IFERROR(IF(OR(DC14="",DD14="",DC14=0,DD14=0),"",DC14/DD14-1),"") -> -0.011009156 | DF14: RT | DG14: =IF(DE14="","",DE14+ROW()*0.000000001) -> -0.011009142
A15: =IF('Macrobond Imports'!A14="","",'Macrobond Imports'!A14) -> 17533 | B15: =IF('Macrobond Imports'!B14="","",'Macrobond Imports'!B14) | C15: =IF('Macrobond Imports'!C14="","",'Macrobond Imports'!C14) | D15: =IF('Macrobond Imports'!Z14="","",'Macrobond Imports'!Z14) | E15: =IF('Macrobond Imports'!BH14="","",'Macrobond Imports'!BH14) | F15: =IF('Macrobond Imports'!BJ14="","",'Macrobond Imports'!BJ14) | G15: =IF('Macrobond Imports'!BK14="","",'Macrobond Imports'!BK14) | H15: =IF('Macrobond Imports'!BL14="","",'Macrobond Imports'!BL14) | I15: =IF('Macrobond Imports'!BS14="","",'Macrobond Imports'!BS14) | J15: =IF('Macrobond Imports'!AA14="","",'Macrobond Imports'!AA14) | K15: =IF('Macrobond Imports'!DF14="","",'Macrobond Imports'!DF14) -> 25 | L15: =IF('Macrobond Imports'!EA14="","",'Macrobond Imports'!EA14) -> 36.2 | M15: =IF('Macrobond Imports'!FA14="","",'Macrobond Imports'!FA14) | N15: =IF('Macrobond Imports'!FC14="","",'Macrobond Imports'!FC14) | P15: =A15 -> 17533 | Q15: =IF(OR(B15="",N(B14)=0),"",B15/B14-1) | R15: =IF(OR(C15="",N(C14)=0),"",C15/C14-1) | S15: =IF(OR(D15="",N(D14)=0),"",D15/D14-1) | T15: =IF(OR(E15="",N(E14)=0),"",E15/E14-1) | U15: =IF(OR(F15="",N(F14)=0),"",F15/F14-1) | V15: =IF(OR(G15="",N(G14)=0),"",G15/G14-1) | W15: =IF(OR(H15="",N(H14)=0),"",H15/H14-1) | X15: =IF(OR(I15="",N(I14)=0),"",I15/I14-1) | ... AC15: =IF(OR(N15="",N(N14)=0),"",N15/N14-1) | AE15: =IFERROR(IF(OR(B15="",OFFSET(B15,-12,0)=""),"",B15/OFFSET(B15,-12,0)-1),"") | AF15: =IFERROR(IF(OR(C15="",OFFSET(C15,-12,0)=""),"",C15/OFFSET(C15,-12,0)-1),"") | AG15: =IFERROR(IF(OR(D15="",OFFSET(D15,-12,0)=""),"",D15/OFFSET(D15,-12,0)-1),"") | AH15: =IFERROR(IF(OR(E15="",OFFSET(E15,-12,0)=""),"",E15/OFFSET(E15,-12,0)-1),"") | AI15: =IFERROR(IF(OR(F15="",OFFSET(F15,-12,0)=""),"",F15/OFFSET(F15,-12,0)-1),"") | AJ15: =IFERROR(IF(OR(G15="",OFFSET(G15,-12,0)=""),"",G15/OFFSET(G15,-12,0)-1),"") | AK15: =IFERROR(IF(OR(H15="",OFFSET(H15,-12,0)=""),"",H15/OFFSET(H15,-12,0)-1),"") | AL15: =IFERROR(IF(OR(I15="",OFFSET(I15,-12,0)=""),"",I15/OFFSET(I15,-12,0)-1),"") | ... AQ15: =IFERROR(IF(OR(N15="",OFFSET(N15,-12,0)=""),"",N15/OFFSET(N15,-12,0)-1),"") | AS15: =IFERROR(IF(OR(B15="",OFFSET(B15,-3,0)=""),"",(B15/OFFSET(B15,-3,0))^4-1),"") | AT15: =IFERROR(IF(OR(C15="",OFFSET(C15,-3,0)=""),"",(C15/OFFSET(C15,-3,0))^4-1),"") | AU15: =IFERROR(IF(OR(D15="",OFFSET(D15,-3,0)=""),"",(D15/OFFSET(D15,-3,0))^4-1),"") | AV15: =IFERROR(IF(OR(E15="",OFFSET(E15,-3,0)=""),"",(E15/OFFSET(E15,-3,0))^4-1),"") | AW15: =IFERROR(IF(OR(F15="",OFFSET(F15,-3,0)=""),"",(F15/OFFSET(F15,-3,0))^4-1),"") | AX15: =IFERROR(IF(OR(G15="",OFFSET(G15,-3,0)=""),"",(G15/OFFSET(G15,-3,0))^4-1),"") | AY15: =IFERROR(IF(OR(H15="",OFFSET(H15,-3,0)=""),"",(H15/OFFSET(H15,-3,0))^4-1),"") | AZ15: =IFERROR(IF(OR(I15="",OFFSET(I15,-3,0)=""),"",(I15/OFFSET(I15,-3,0))^4-1),"") | ... BE15: =IFERROR(IF(OR(N15="",OFFSET(N15,-3,0)=""),"",(N15/OFFSET(N15,-3,0))^4-1),"") | BG15: =IFERROR(IF(OR(B15="",OFFSET(B15,-6,0)=""),"",(B15/OFFSET(B15,-6,0))^2-1),"") | BH15: =IFERROR(IF(OR(C15="",OFFSET(C15,-6,0)=""),"",(C15/OFFSET(C15,-6,0))^2-1),"") | BI15: =IFERROR(IF(OR(D15="",OFFSET(D15,-6,0)=""),"",(D15/OFFSET(D15,-6,0))^2-1),"") | BJ15: =IFERROR(IF(OR(E15="",OFFSET(E15,-6,0)=""),"",(E15/OFFSET(E15,-6,0))^2-1),"") | BK15: =IFERROR(IF(OR(F15="",OFFSET(F15,-6,0)=""),"",(F15/OFFSET(F15,-6,0))^2-1),"") | BL15: =IFERROR(IF(OR(G15="",OFFSET(G15,-6,0)=""),"",(G15/OFFSET(G15,-6,0))^2-1),"") | BM15: =IFERROR(IF(OR(H15="",OFFSET(H15,-6,0)=""),"",(H15/OFFSET(H15,-6,0))^2-1),"") | BN15: =IFERROR(IF(OR(I15="",OFFSET(I15,-6,0)=""),"",(I15/OFFSET(I15,-6,0))^2-1),"") | ... BS15: =IFERROR(IF(OR(N15="",OFFSET(N15,-6,0)=""),"",(N15/OFFSET(N15,-6,0))^2-1),"") | BX15: =IF('Macrobond Imports'!FG14="","",'Macrobond Imports'!FG14) | BY15: =IF('Macrobond Imports'!AI14="","",'Macrobond Imports'!AI14) | CA15: =IFERROR(IF(OR(BX15="",OFFSET(BX15,-12,0)=""),"",BX15/OFFSET(BX15,-12,0)-1),"") | CB15: =IFERROR(IF(OR(BY15="",OFFSET(BY15,-12,0)=""),"",BY15/OFFSET(BY15,-12,0)-1),"") | CC15: {=INDEX(MM_Headline,ROW()-5)} -> 0.0017435378 | CD15: {=INDEX(MM_Core,ROW()-5)} -> 0.001710232 | CE15: {=INDEX(YY_Headline,ROW()-5)} -> 0.034020201 | CF15: {=INDEX(YY_Core,ROW()-5)} -> 0.037186834 | CG15: {=INDEX(Ann3_Headline,ROW()-5)} -> 0.049681818 | CH15: {=INDEX(Ann6_Headline,ROW()-5)} -> 0.039219341 | CK15: {=INDEX(ChartDates,ROW()-5)} -> 45689 | CL15: {=INDEX(UnprocEnergy_YY,ROW()-5)} -> 0.046994028 | CM15: {=INDEX(Transport_YY,ROW()-5)} -> 0.02536203 | DA15: Health & Beauty Retailing | DB15: FY | DC15: =INDEX('Macrobond Imports'!FY:FY,MATCH(MAX('Macrobond Imports'!$A:$A),'Macrobond Imports'!$A:$A,0)) -> 166.698 | DD15: {=INDEX('Macrobond Imports'!FY:FY,MATCH(MAX('Macrobond Imports'!$A:$A),'Macrobond Imports'!$A:$A,0)-1)} -> 155.911 | DE15: =IFERROR(IF(OR(DC15="",DD15="",DC15=0,DD15=0),"",DC15/DD15-1),"") -> 0.069186908 | DF15: RT | DG15: =IF(DE15="","",DE15+ROW()*0.000000001) -> 0.069186923
A16: =IF('Macrobond Imports'!A15="","",'Macrobond Imports'!A15) -> 17564 | B16: =IF('Macrobond Imports'!B15="","",'Macrobond Imports'!B15) | C16: =IF('Macrobond Imports'!C15="","",'Macrobond Imports'!C15) | D16: =IF('Macrobond Imports'!Z15="","",'Macrobond Imports'!Z15) | E16: =IF('Macrobond Imports'!BH15="","",'Macrobond Imports'!BH15) | F16: =IF('Macrobond Imports'!BJ15="","",'Macrobond Imports'!BJ15) | G16: =IF('Macrobond Imports'!BK15="","",'Macrobond Imports'!BK15) | H16: =IF('Macrobond Imports'!BL15="","",'Macrobond Imports'!BL15) | I16: =IF('Macrobond Imports'!BS15="","",'Macrobond Imports'!BS15) | J16: =IF('Macrobond Imports'!AA15="","",'Macrobond Imports'!AA15) | K16: =IF('Macrobond Imports'!DF15="","",'Macrobond Imports'!DF15) -> 24.7 | L16: =IF('Macrobond Imports'!EA15="","",'Macrobond Imports'!EA15) -> 34.4 | M16: =IF('Macrobond Imports'!FA15="","",'Macrobond Imports'!FA15) | N16: =IF('Macrobond Imports'!FC15="","",'Macrobond Imports'!FC15) | P16: =A16 -> 17564 | Q16: =IF(OR(B16="",N(B15)=0),"",B16/B15-1) | R16: =IF(OR(C16="",N(C15)=0),"",C16/C15-1) | S16: =IF(OR(D16="",N(D15)=0),"",D16/D15-1) | T16: =IF(OR(E16="",N(E15)=0),"",E16/E15-1) | U16: =IF(OR(F16="",N(F15)=0),"",F16/F15-1) | V16: =IF(OR(G16="",N(G15)=0),"",G16/G15-1) | W16: =IF(OR(H16="",N(H15)=0),"",H16/H15-1) | X16: =IF(OR(I16="",N(I15)=0),"",I16/I15-1) | ... AC16: =IF(OR(N16="",N(N15)=0),"",N16/N15-1) | AE16: =IFERROR(IF(OR(B16="",OFFSET(B16,-12,0)=""),"",B16/OFFSET(B16,-12,0)-1),"") | AF16: =IFERROR(IF(OR(C16="",OFFSET(C16,-12,0)=""),"",C16/OFFSET(C16,-12,0)-1),"") | AG16: =IFERROR(IF(OR(D16="",OFFSET(D16,-12,0)=""),"",D16/OFFSET(D16,-12,0)-1),"") | AH16: =IFERROR(IF(OR(E16="",OFFSET(E16,-12,0)=""),"",E16/OFFSET(E16,-12,0)-1),"") | AI16: =IFERROR(IF(OR(F16="",OFFSET(F16,-12,0)=""),"",F16/OFFSET(F16,-12,0)-1),"") | AJ16: =IFERROR(IF(OR(G16="",OFFSET(G16,-12,0)=""),"",G16/OFFSET(G16,-12,0)-1),"") | AK16: =IFERROR(IF(OR(H16="",OFFSET(H16,-12,0)=""),"",H16/OFFSET(H16,-12,0)-1),"") | AL16: =IFERROR(IF(OR(I16="",OFFSET(I16,-12,0)=""),"",I16/OFFSET(I16,-12,0)-1),"") | ... AQ16: =IFERROR(IF(OR(N16="",OFFSET(N16,-12,0)=""),"",N16/OFFSET(N16,-12,0)-1),"") | AS16: =IFERROR(IF(OR(B16="",OFFSET(B16,-3,0)=""),"",(B16/OFFSET(B16,-3,0))^4-1),"") | AT16: =IFERROR(IF(OR(C16="",OFFSET(C16,-3,0)=""),"",(C16/OFFSET(C16,-3,0))^4-1),"") | AU16: =IFERROR(IF(OR(D16="",OFFSET(D16,-3,0)=""),"",(D16/OFFSET(D16,-3,0))^4-1),"") | AV16: =IFERROR(IF(OR(E16="",OFFSET(E16,-3,0)=""),"",(E16/OFFSET(E16,-3,0))^4-1),"") | AW16: =IFERROR(IF(OR(F16="",OFFSET(F16,-3,0)=""),"",(F16/OFFSET(F16,-3,0))^4-1),"") | AX16: =IFERROR(IF(OR(G16="",OFFSET(G16,-3,0)=""),"",(G16/OFFSET(G16,-3,0))^4-1),"") | AY16: =IFERROR(IF(OR(H16="",OFFSET(H16,-3,0)=""),"",(H16/OFFSET(H16,-3,0))^4-1),"") | AZ16: =IFERROR(IF(OR(I16="",OFFSET(I16,-3,0)=""),"",(I16/OFFSET(I16,-3,0))^4-1),"") | ... BE16: =IFERROR(IF(OR(N16="",OFFSET(N16,-3,0)=""),"",(N16/OFFSET(N16,-3,0))^4-1),"") | BG16: =IFERROR(IF(OR(B16="",OFFSET(B16,-6,0)=""),"",(B16/OFFSET(B16,-6,0))^2-1),"") | BH16: =IFERROR(IF(OR(C16="",OFFSET(C16,-6,0)=""),"",(C16/OFFSET(C16,-6,0))^2-1),"") | BI16: =IFERROR(IF(OR(D16="",OFFSET(D16,-6,0)=""),"",(D16/OFFSET(D16,-6,0))^2-1),"") | BJ16: =IFERROR(IF(OR(E16="",OFFSET(E16,-6,0)=""),"",(E16/OFFSET(E16,-6,0))^2-1),"") | BK16: =IFERROR(IF(OR(F16="",OFFSET(F16,-6,0)=""),"",(F16/OFFSET(F16,-6,0))^2-1),"") | BL16: =IFERROR(IF(OR(G16="",OFFSET(G16,-6,0)=""),"",(G16/OFFSET(G16,-6,0))^2-1),"") | BM16: =IFERROR(IF(OR(H16="",OFFSET(H16,-6,0)=""),"",(H16/OFFSET(H16,-6,0))^2-1),"") | BN16: =IFERROR(IF(OR(I16="",OFFSET(I16,-6,0)=""),"",(I16/OFFSET(I16,-6,0))^2-1),"") | ... BS16: =IFERROR(IF(OR(N16="",OFFSET(N16,-6,0)=""),"",(N16/OFFSET(N16,-6,0))^2-1),"") | BX16: =IF('Macrobond Imports'!FG15="","",'Macrobond Imports'!FG15) | BY16: =IF('Macrobond Imports'!AI15="","",'Macrobond Imports'!AI15) | CA16: =IFERROR(IF(OR(BX16="",OFFSET(BX16,-12,0)=""),"",BX16/OFFSET(BX16,-12,0)-1),"") | CB16: =IFERROR(IF(OR(BY16="",OFFSET(BY16,-12,0)=""),"",BY16/OFFSET(BY16,-12,0)-1),"") | CC16: {=INDEX(MM_Headline,ROW()-5)} -> -0.0012008122 | CD16: {=INDEX(MM_Core,ROW()-5)} -> 0.0017892631 | CE16: {=INDEX(YY_Headline,ROW()-5)} -> 0.031591196 | CF16: {=INDEX(YY_Core,ROW()-5)} -> 0.037807665 | CG16: {=INDEX(Ann3_Headline,ROW()-5)} -> 0.02756327 | CH16: {=INDEX(Ann6_Headline,ROW()-5)} -> 0.03112956 | CK16: {=INDEX(ChartDates,ROW()-5)} -> 45717 | CL16: {=INDEX(UnprocEnergy_YY,ROW()-5)} -> 0.051587704 | CM16: {=INDEX(Transport_YY,ROW()-5)} -> 0.0048533404 | DA16: Apparel/Jewelry/Footwear Retailing | DB16: FZ | DC16: =INDEX('Macrobond Imports'!FZ:FZ,MATCH(MAX('Macrobond Imports'!$A:$A),'Macrobond Imports'!$A:$A,0)) -> 146.547 | DD16: {=INDEX('Macrobond Imports'!FZ:FZ,MATCH(MAX('Macrobond Imports'!$A:$A),'Macrobond Imports'!$A:$A,0)-1)} -> 144.741 | DE16: =IFERROR(IF(OR(DC16="",DD16="",DC16=0,DD16=0),"",DC16/DD16-1),"") -> 0.01247746 | DF16: RT | DG16: =IF(DE16="","",DE16+ROW()*0.000000001) -> 0.012477476
A17: =IF('Macrobond Imports'!A16="","",'Macrobond Imports'!A16) -> 17593 | B17: =IF('Macrobond Imports'!B16="","",'Macrobond Imports'!B16) | C17: =IF('Macrobond Imports'!C16="","",'Macrobond Imports'!C16) | D17: =IF('Macrobond Imports'!Z16="","",'Macrobond Imports'!Z16) | E17: =IF('Macrobond Imports'!BH16="","",'Macrobond Imports'!BH16) | F17: =IF('Macrobond Imports'!BJ16="","",'Macrobond Imports'!BJ16) | G17: =IF('Macrobond Imports'!BK16="","",'Macrobond Imports'!BK16) | H17: =IF('Macrobond Imports'!BL16="","",'Macrobond Imports'!BL16) | I17: =IF('Macrobond Imports'!BS16="","",'Macrobond Imports'!BS16) | J17: =IF('Macrobond Imports'!AA16="","",'Macrobond Imports'!AA16) | K17: =IF('Macrobond Imports'!DF16="","",'Macrobond Imports'!DF16) -> 24.8 | L17: =IF('Macrobond Imports'!EA16="","",'Macrobond Imports'!EA16) -> 33.5 | M17: =IF('Macrobond Imports'!FA16="","",'Macrobond Imports'!FA16) | N17: =IF('Macrobond Imports'!FC16="","",'Macrobond Imports'!FC16) | P17: =A17 -> 17593 | Q17: =IF(OR(B17="",N(B16)=0),"",B17/B16-1) | R17: =IF(OR(C17="",N(C16)=0),"",C17/C16-1) | S17: =IF(OR(D17="",N(D16)=0),"",D17/D16-1) | T17: =IF(OR(E17="",N(E16)=0),"",E17/E16-1) | U17: =IF(OR(F17="",N(F16)=0),"",F17/F16-1) | V17: =IF(OR(G17="",N(G16)=0),"",G17/G16-1) | W17: =IF(OR(H17="",N(H16)=0),"",H17/H16-1) | X17: =IF(OR(I17="",N(I16)=0),"",I17/I16-1) | ... AC17: =IF(OR(N17="",N(N16)=0),"",N17/N16-1) | AE17: =IFERROR(IF(OR(B17="",OFFSET(B17,-12,0)=""),"",B17/OFFSET(B17,-12,0)-1),"") | AF17: =IFERROR(IF(OR(C17="",OFFSET(C17,-12,0)=""),"",C17/OFFSET(C17,-12,0)-1),"") | AG17: =IFERROR(IF(OR(D17="",OFFSET(D17,-12,0)=""),"",D17/OFFSET(D17,-12,0)-1),"") | AH17: =IFERROR(IF(OR(E17="",OFFSET(E17,-12,0)=""),"",E17/OFFSET(E17,-12,0)-1),"") | AI17: =IFERROR(IF(OR(F17="",OFFSET(F17,-12,0)=""),"",F17/OFFSET(F17,-12,0)-1),"") | AJ17: =IFERROR(IF(OR(G17="",OFFSET(G17,-12,0)=""),"",G17/OFFSET(G17,-12,0)-1),"") | AK17: =IFERROR(IF(OR(H17="",OFFSET(H17,-12,0)=""),"",H17/OFFSET(H17,-12,0)-1),"") | AL17: =IFERROR(IF(OR(I17="",OFFSET(I17,-12,0)=""),"",I17/OFFSET(I17,-12,0)-1),"") | ... AQ17: =IFERROR(IF(OR(N17="",OFFSET(N17,-12,0)=""),"",N17/OFFSET(N17,-12,0)-1),"") | AS17: =IFERROR(IF(OR(B17="",OFFSET(B17,-3,0)=""),"",(B17/OFFSET(B17,-3,0))^4-1),"") | AT17: =IFERROR(IF(OR(C17="",OFFSET(C17,-3,0)=""),"",(C17/OFFSET(C17,-3,0))^4-1),"") | AU17: =IFERROR(IF(OR(D17="",OFFSET(D17,-3,0)=""),"",(D17/OFFSET(D17,-3,0))^4-1),"") | AV17: =IFERROR(IF(OR(E17="",OFFSET(E17,-3,0)=""),"",(E17/OFFSET(E17,-3,0))^4-1),"") | AW17: =IFERROR(IF(OR(F17="",OFFSET(F17,-3,0)=""),"",(F17/OFFSET(F17,-3,0))^4-1),"") | AX17: =IFERROR(IF(OR(G17="",OFFSET(G17,-3,0)=""),"",(G17/OFFSET(G17,-3,0))^4-1),"") | AY17: =IFERROR(IF(OR(H17="",OFFSET(H17,-3,0)=""),"",(H17/OFFSET(H17,-3,0))^4-1),"") | AZ17: =IFERROR(IF(OR(I17="",OFFSET(I17,-3,0)=""),"",(I17/OFFSET(I17,-3,0))^4-1),"") | ... BE17: =IFERROR(IF(OR(N17="",OFFSET(N17,-3,0)=""),"",(N17/OFFSET(N17,-3,0))^4-1),"") | BG17: =IFERROR(IF(OR(B17="",OFFSET(B17,-6,0)=""),"",(B17/OFFSET(B17,-6,0))^2-1),"") | BH17: =IFERROR(IF(OR(C17="",OFFSET(C17,-6,0)=""),"",(C17/OFFSET(C17,-6,0))^2-1),"") | BI17: =IFERROR(IF(OR(D17="",OFFSET(D17,-6,0)=""),"",(D17/OFFSET(D17,-6,0))^2-1),"") | BJ17: =IFERROR(IF(OR(E17="",OFFSET(E17,-6,0)=""),"",(E17/OFFSET(E17,-6,0))^2-1),"") | BK17: =IFERROR(IF(OR(F17="",OFFSET(F17,-6,0)=""),"",(F17/OFFSET(F17,-6,0))^2-1),"") | BL17: =IFERROR(IF(OR(G17="",OFFSET(G17,-6,0)=""),"",(G17/OFFSET(G17,-6,0))^2-1),"") | BM17: =IFERROR(IF(OR(H17="",OFFSET(H17,-6,0)=""),"",(H17/OFFSET(H17,-6,0))^2-1),"") | BN17: =IFERROR(IF(OR(I17="",OFFSET(I17,-6,0)=""),"",(I17/OFFSET(I17,-6,0))^2-1),"") | ... BS17: =IFERROR(IF(OR(N17="",OFFSET(N17,-6,0)=""),"",(N17/OFFSET(N17,-6,0))^2-1),"") | BX17: =IF('Macrobond Imports'!FG16="","",'Macrobond Imports'!FG16) | BY17: =IF('Macrobond Imports'!AI16="","",'Macrobond Imports'!AI16) | CA17: =IFERROR(IF(OR(BX17="",OFFSET(BX17,-12,0)=""),"",BX17/OFFSET(BX17,-12,0)-1),"") | CB17: =IFERROR(IF(OR(BY17="",OFFSET(BY17,-12,0)=""),"",BY17/OFFSET(BY17,-12,0)-1),"") | CC17: {=INDEX(MM_Headline,ROW()-5)} -> -0.0027016987 | CD17: {=INDEX(MM_Core,ROW()-5)} -> -0.0020860175 | CE17: {=INDEX(YY_Headline,ROW()-5)} -> 0.023981081 | CF17: {=INDEX(YY_Core,ROW()-5)} -> 0.030604486 | CG17: {=INDEX(Ann3_Headline,ROW()-5)} -> -0.0086220911 | CH17: {=INDEX(Ann6_Headline,ROW()-5)} -> 0.018692917 | CK17: {=INDEX(ChartDates,ROW()-5)} -> 45748 | CL17: {=INDEX(UnprocEnergy_YY,ROW()-5)} -> -0.077681589 | CM17: {=INDEX(Transport_YY,ROW()-5)} -> 0.010710057 | DA17: Computer HW & Software Retailing | DB17: GA | DC17: =INDEX('Macrobond Imports'!GA:GA,MATCH(MAX('Macrobond Imports'!$A:$A),'Macrobond Imports'!$A:$A,0)) -> 123.701 | DD17: {=INDEX('Macrobond Imports'!GA:GA,MATCH(MAX('Macrobond Imports'!$A:$A),'Macrobond Imports'!$A:$A,0)-1)} -> 123.598 | DE17: =IFERROR(IF(OR(DC17="",DD17="",DC17=0,DD17=0),"",DC17/DD17-1),"") -> 0.00083334682 | DF17: RT | DG17: =IF(DE17="","",DE17+ROW()*0.000000001) -> 0.00083336382
A18: =IF('Macrobond Imports'!A17="","",'Macrobond Imports'!A17) -> 17624 | B18: =IF('Macrobond Imports'!B17="","",'Macrobond Imports'!B17) | C18: =IF('Macrobond Imports'!C17="","",'Macrobond Imports'!C17) | D18: =IF('Macrobond Imports'!Z17="","",'Macrobond Imports'!Z17) | E18: =IF('Macrobond Imports'!BH17="","",'Macrobond Imports'!BH17) | F18: =IF('Macrobond Imports'!BJ17="","",'Macrobond Imports'!BJ17) | G18: =IF('Macrobond Imports'!BK17="","",'Macrobond Imports'!BK17) | H18: =IF('Macrobond Imports'!BL17="","",'Macrobond Imports'!BL17) | I18: =IF('Macrobond Imports'!BS17="","",'Macrobond Imports'!BS17) | J18: =IF('Macrobond Imports'!AA17="","",'Macrobond Imports'!AA17) | K18: =IF('Macrobond Imports'!DF17="","",'Macrobond Imports'!DF17) -> 25.1 | L18: =IF('Macrobond Imports'!EA17="","",'Macrobond Imports'!EA17) -> 34.2 | M18: =IF('Macrobond Imports'!FA17="","",'Macrobond Imports'!FA17) | N18: =IF('Macrobond Imports'!FC17="","",'Macrobond Imports'!FC17) | P18: =A18 -> 17624 | Q18: =IF(OR(B18="",N(B17)=0),"",B18/B17-1) | R18: =IF(OR(C18="",N(C17)=0),"",C18/C17-1) | S18: =IF(OR(D18="",N(D17)=0),"",D18/D17-1) | T18: =IF(OR(E18="",N(E17)=0),"",E18/E17-1) | U18: =IF(OR(F18="",N(F17)=0),"",F18/F17-1) | V18: =IF(OR(G18="",N(G17)=0),"",G18/G17-1) | W18: =IF(OR(H18="",N(H17)=0),"",H18/H17-1) | X18: =IF(OR(I18="",N(I17)=0),"",I18/I17-1) | ... AC18: =IF(OR(N18="",N(N17)=0),"",N18/N17-1) | AE18: =IFERROR(IF(OR(B18="",OFFSET(B18,-12,0)=""),"",B18/OFFSET(B18,-12,0)-1),"") | AF18: =IFERROR(IF(OR(C18="",OFFSET(C18,-12,0)=""),"",C18/OFFSET(C18,-12,0)-1),"") | AG18: =IFERROR(IF(OR(D18="",OFFSET(D18,-12,0)=""),"",D18/OFFSET(D18,-12,0)-1),"") | AH18: =IFERROR(IF(OR(E18="",OFFSET(E18,-12,0)=""),"",E18/OFFSET(E18,-12,0)-1),"") | AI18: =IFERROR(IF(OR(F18="",OFFSET(F18,-12,0)=""),"",F18/OFFSET(F18,-12,0)-1),"") | AJ18: =IFERROR(IF(OR(G18="",OFFSET(G18,-12,0)=""),"",G18/OFFSET(G18,-12,0)-1),"") | AK18: =IFERROR(IF(OR(H18="",OFFSET(H18,-12,0)=""),"",H18/OFFSET(H18,-12,0)-1),"") | AL18: =IFERROR(IF(OR(I18="",OFFSET(I18,-12,0)=""),"",I18/OFFSET(I18,-12,0)-1),"") | ... AQ18: =IFERROR(IF(OR(N18="",OFFSET(N18,-12,0)=""),"",N18/OFFSET(N18,-12,0)-1),"") | AS18: =IFERROR(IF(OR(B18="",OFFSET(B18,-3,0)=""),"",(B18/OFFSET(B18,-3,0))^4-1),"") | AT18: =IFERROR(IF(OR(C18="",OFFSET(C18,-3,0)=""),"",(C18/OFFSET(C18,-3,0))^4-1),"") | AU18: =IFERROR(IF(OR(D18="",OFFSET(D18,-3,0)=""),"",(D18/OFFSET(D18,-3,0))^4-1),"") | AV18: =IFERROR(IF(OR(E18="",OFFSET(E18,-3,0)=""),"",(E18/OFFSET(E18,-3,0))^4-1),"") | AW18: =IFERROR(IF(OR(F18="",OFFSET(F18,-3,0)=""),"",(F18/OFFSET(F18,-3,0))^4-1),"") | AX18: =IFERROR(IF(OR(G18="",OFFSET(G18,-3,0)=""),"",(G18/OFFSET(G18,-3,0))^4-1),"") | AY18: =IFERROR(IF(OR(H18="",OFFSET(H18,-3,0)=""),"",(H18/OFFSET(H18,-3,0))^4-1),"") | AZ18: =IFERROR(IF(OR(I18="",OFFSET(I18,-3,0)=""),"",(I18/OFFSET(I18,-3,0))^4-1),"") | ... BE18: =IFERROR(IF(OR(N18="",OFFSET(N18,-3,0)=""),"",(N18/OFFSET(N18,-3,0))^4-1),"") | BG18: =IFERROR(IF(OR(B18="",OFFSET(B18,-6,0)=""),"",(B18/OFFSET(B18,-6,0))^2-1),"") | BH18: =IFERROR(IF(OR(C18="",OFFSET(C18,-6,0)=""),"",(C18/OFFSET(C18,-6,0))^2-1),"") | BI18: =IFERROR(IF(OR(D18="",OFFSET(D18,-6,0)=""),"",(D18/OFFSET(D18,-6,0))^2-1),"") | BJ18: =IFERROR(IF(OR(E18="",OFFSET(E18,-6,0)=""),"",(E18/OFFSET(E18,-6,0))^2-1),"") | BK18: =IFERROR(IF(OR(F18="",OFFSET(F18,-6,0)=""),"",(F18/OFFSET(F18,-6,0))^2-1),"") | BL18: =IFERROR(IF(OR(G18="",OFFSET(G18,-6,0)=""),"",(G18/OFFSET(G18,-6,0))^2-1),"") | BM18: =IFERROR(IF(OR(H18="",OFFSET(H18,-6,0)=""),"",(H18/OFFSET(H18,-6,0))^2-1),"") | BN18: =IFERROR(IF(OR(I18="",OFFSET(I18,-6,0)=""),"",(I18/OFFSET(I18,-6,0))^2-1),"") | ... BS18: =IFERROR(IF(OR(N18="",OFFSET(N18,-6,0)=""),"",(N18/OFFSET(N18,-6,0))^2-1),"") | BX18: =IF('Macrobond Imports'!FG17="","",'Macrobond Imports'!FG17) | BY18: =IF('Macrobond Imports'!AI17="","",'Macrobond Imports'!AI17) | CA18: =IFERROR(IF(OR(BX18="",OFFSET(BX18,-12,0)=""),"",BX18/OFFSET(BX18,-12,0)-1),"") | CB18: =IFERROR(IF(OR(BY18="",OFFSET(BY18,-12,0)=""),"",BY18/OFFSET(BY18,-12,0)-1),"") | CC18: {=INDEX(MM_Headline,ROW()-5)} -> 0.003372727 | CD18: {=INDEX(MM_Core,ROW()-5)} -> 0.0038391912 | CE18: {=INDEX(YY_Headline,ROW()-5)} -> 0.027242345 | CF18: {=INDEX(YY_Core,ROW()-5)} -> 0.031851472 | CG18: {=INDEX(Ann3_Headline,ROW()-5)} -> -0.0021570166 | CH18: {=INDEX(Ann6_Headline,ROW()-5)} -> 0.023434237 | CK18: {=INDEX(ChartDates,ROW()-5)} -> 45778 | CL18: {=INDEX(UnprocEnergy_YY,ROW()-5)} -> -0.088520483 | CM18: {=INDEX(Transport_YY,ROW()-5)} -> 0.017698582 | DA18: TV/Video/Photo Retailing | DB18: GB | DC18: =INDEX('Macrobond Imports'!GB:GB,MATCH(MAX('Macrobond Imports'!$A:$A),'Macrobond Imports'!$A:$A,0)) -> 53.005 | DD18: {=INDEX('Macrobond Imports'!GB:GB,MATCH(MAX('Macrobond Imports'!$A:$A),'Macrobond Imports'!$A:$A,0)-1)} -> 54.048 | DE18: =IFERROR(IF(OR(DC18="",DD18="",DC18=0,DD18=0),"",DC18/DD18-1),"") -> -0.019297661 | DF18: RT | DG18: =IF(DE18="","",DE18+ROW()*0.000000001) -> -0.019297643
A19: =IF('Macrobond Imports'!A18="","",'Macrobond Imports'!A18) -> 17654 | B19: =IF('Macrobond Imports'!B18="","",'Macrobond Imports'!B18) | C19: =IF('Macrobond Imports'!C18="","",'Macrobond Imports'!C18) | D19: =IF('Macrobond Imports'!Z18="","",'Macrobond Imports'!Z18) | E19: =IF('Macrobond Imports'!BH18="","",'Macrobond Imports'!BH18) | F19: =IF('Macrobond Imports'!BJ18="","",'Macrobond Imports'!BJ18) | G19: =IF('Macrobond Imports'!BK18="","",'Macrobond Imports'!BK18) | H19: =IF('Macrobond Imports'!BL18="","",'Macrobond Imports'!BL18) | I19: =IF('Macrobond Imports'!BS18="","",'Macrobond Imports'!BS18) | J19: =IF('Macrobond Imports'!AA18="","",'Macrobond Imports'!AA18) | K19: =IF('Macrobond Imports'!DF18="","",'Macrobond Imports'!DF18) -> 25.1 | L19: =IF('Macrobond Imports'!EA18="","",'Macrobond Imports'!EA18) -> 35.3 | M19: =IF('Macrobond Imports'!FA18="","",'Macrobond Imports'!FA18) | N19: =IF('Macrobond Imports'!FC18="","",'Macrobond Imports'!FC18) | P19: =A19 -> 17654 | Q19: =IF(OR(B19="",N(B18)=0),"",B19/B18-1) | R19: =IF(OR(C19="",N(C18)=0),"",C19/C18-1) | S19: =IF(OR(D19="",N(D18)=0),"",D19/D18-1) | T19: =IF(OR(E19="",N(E18)=0),"",E19/E18-1) | U19: =IF(OR(F19="",N(F18)=0),"",F19/F18-1) | V19: =IF(OR(G19="",N(G18)=0),"",G19/G18-1) | W19: =IF(OR(H19="",N(H18)=0),"",H19/H18-1) | X19: =IF(OR(I19="",N(I18)=0),"",I19/I18-1) | ... AC19: =IF(OR(N19="",N(N18)=0),"",N19/N18-1) | AE19: =IFERROR(IF(OR(B19="",OFFSET(B19,-12,0)=""),"",B19/OFFSET(B19,-12,0)-1),"") | AF19: =IFERROR(IF(OR(C19="",OFFSET(C19,-12,0)=""),"",C19/OFFSET(C19,-12,0)-1),"") | AG19: =IFERROR(IF(OR(D19="",OFFSET(D19,-12,0)=""),"",D19/OFFSET(D19,-12,0)-1),"") | AH19: =IFERROR(IF(OR(E19="",OFFSET(E19,-12,0)=""),"",E19/OFFSET(E19,-12,0)-1),"") | AI19: =IFERROR(IF(OR(F19="",OFFSET(F19,-12,0)=""),"",F19/OFFSET(F19,-12,0)-1),"") | AJ19: =IFERROR(IF(OR(G19="",OFFSET(G19,-12,0)=""),"",G19/OFFSET(G19,-12,0)-1),"") | AK19: =IFERROR(IF(OR(H19="",OFFSET(H19,-12,0)=""),"",H19/OFFSET(H19,-12,0)-1),"") | AL19: =IFERROR(IF(OR(I19="",OFFSET(I19,-12,0)=""),"",I19/OFFSET(I19,-12,0)-1),"") | ... AQ19: =IFERROR(IF(OR(N19="",OFFSET(N19,-12,0)=""),"",N19/OFFSET(N19,-12,0)-1),"") | AS19: =IFERROR(IF(OR(B19="",OFFSET(B19,-3,0)=""),"",(B19/OFFSET(B19,-3,0))^4-1),"") | AT19: =IFERROR(IF(OR(C19="",OFFSET(C19,-3,0)=""),"",(C19/OFFSET(C19,-3,0))^4-1),"") | AU19: =IFERROR(IF(OR(D19="",OFFSET(D19,-3,0)=""),"",(D19/OFFSET(D19,-3,0))^4-1),"") | AV19: =IFERROR(IF(OR(E19="",OFFSET(E19,-3,0)=""),"",(E19/OFFSET(E19,-3,0))^4-1),"") | AW19: =IFERROR(IF(OR(F19="",OFFSET(F19,-3,0)=""),"",(F19/OFFSET(F19,-3,0))^4-1),"") | AX19: =IFERROR(IF(OR(G19="",OFFSET(G19,-3,0)=""),"",(G19/OFFSET(G19,-3,0))^4-1),"") | AY19: =IFERROR(IF(OR(H19="",OFFSET(H19,-3,0)=""),"",(H19/OFFSET(H19,-3,0))^4-1),"") | AZ19: =IFERROR(IF(OR(I19="",OFFSET(I19,-3,0)=""),"",(I19/OFFSET(I19,-3,0))^4-1),"") | ... BE19: =IFERROR(IF(OR(N19="",OFFSET(N19,-3,0)=""),"",(N19/OFFSET(N19,-3,0))^4-1),"") | BG19: =IFERROR(IF(OR(B19="",OFFSET(B19,-6,0)=""),"",(B19/OFFSET(B19,-6,0))^2-1),"") | BH19: =IFERROR(IF(OR(C19="",OFFSET(C19,-6,0)=""),"",(C19/OFFSET(C19,-6,0))^2-1),"") | BI19: =IFERROR(IF(OR(D19="",OFFSET(D19,-6,0)=""),"",(D19/OFFSET(D19,-6,0))^2-1),"") | BJ19: =IFERROR(IF(OR(E19="",OFFSET(E19,-6,0)=""),"",(E19/OFFSET(E19,-6,0))^2-1),"") | BK19: =IFERROR(IF(OR(F19="",OFFSET(F19,-6,0)=""),"",(F19/OFFSET(F19,-6,0))^2-1),"") | BL19: =IFERROR(IF(OR(G19="",OFFSET(G19,-6,0)=""),"",(G19/OFFSET(G19,-6,0))^2-1),"") | BM19: =IFERROR(IF(OR(H19="",OFFSET(H19,-6,0)=""),"",(H19/OFFSET(H19,-6,0))^2-1),"") | BN19: =IFERROR(IF(OR(I19="",OFFSET(I19,-6,0)=""),"",(I19/OFFSET(I19,-6,0))^2-1),"") | ... BS19: =IFERROR(IF(OR(N19="",OFFSET(N19,-6,0)=""),"",(N19/OFFSET(N19,-6,0))^2-1),"") | BX19: =IF('Macrobond Imports'!FG18="","",'Macrobond Imports'!FG18) | BY19: =IF('Macrobond Imports'!AI18="","",'Macrobond Imports'!AI18) | CA19: =IFERROR(IF(OR(BX19="",OFFSET(BX19,-12,0)=""),"",BX19/OFFSET(BX19,-12,0)-1),"") | CB19: =IFERROR(IF(OR(BY19="",OFFSET(BY19,-12,0)=""),"",BY19/OFFSET(BY19,-12,0)-1),"") | CC19: {=INDEX(MM_Headline,ROW()-5)} -> 0.0016199469 | CD19: {=INDEX(MM_Core,ROW()-5)} -> 0.0011432693 | CE19: {=INDEX(YY_Headline,ROW()-5)} -> 0.024325425 | CF19: {=INDEX(YY_Core,ROW()-5)} -> 0.026887612 | CG19: {=INDEX(Ann3_Headline,ROW()-5)} -> 0.00916306 | CH19: {=INDEX(Ann6_Headline,ROW()-5)} -> 0.018321606 | CK19: {=INDEX(ChartDates,ROW()-5)} -> 45809 | CL19: {=INDEX(UnprocEnergy_YY,ROW()-5)} -> -0.070849163 | CM19: {=INDEX(Transport_YY,ROW()-5)} -> 0.01093865 | DA19: Autos & Auto Parts Retailing | DB19: GC | DC19: =INDEX('Macrobond Imports'!GC:GC,MATCH(MAX('Macrobond Imports'!$A:$A),'Macrobond Imports'!$A:$A,0)) -> 124.002 | DD19: {=INDEX('Macrobond Imports'!GC:GC,MATCH(MAX('Macrobond Imports'!$A:$A),'Macrobond Imports'!$A:$A,0)-1)} -> 121.122 | DE19: =IFERROR(IF(OR(DC19="",DD19="",DC19=0,DD19=0),"",DC19/DD19-1),"") -> 0.023777679 | DF19: RT | DG19: =IF(DE19="","",DE19+ROW()*0.000000001) -> 0.023777698
A20: =IF('Macrobond Imports'!A19="","",'Macrobond Imports'!A19) -> 17685 | B20: =IF('Macrobond Imports'!B19="","",'Macrobond Imports'!B19) | C20: =IF('Macrobond Imports'!C19="","",'Macrobond Imports'!C19) | D20: =IF('Macrobond Imports'!Z19="","",'Macrobond Imports'!Z19) | E20: =IF('Macrobond Imports'!BH19="","",'Macrobond Imports'!BH19) | F20: =IF('Macrobond Imports'!BJ19="","",'Macrobond Imports'!BJ19) | G20: =IF('Macrobond Imports'!BK19="","",'Macrobond Imports'!BK19) | H20: =IF('Macrobond Imports'!BL19="","",'Macrobond Imports'!BL19) | I20: =IF('Macrobond Imports'!BS19="","",'Macrobond Imports'!BS19) | J20: =IF('Macrobond Imports'!AA19="","",'Macrobond Imports'!AA19) | K20: =IF('Macrobond Imports'!DF19="","",'Macrobond Imports'!DF19) -> 25.4 | L20: =IF('Macrobond Imports'!EA19="","",'Macrobond Imports'!EA19) -> 36.2 | M20: =IF('Macrobond Imports'!FA19="","",'Macrobond Imports'!FA19) | N20: =IF('Macrobond Imports'!FC19="","",'Macrobond Imports'!FC19) | P20: =A20 -> 17685 | Q20: =IF(OR(B20="",N(B19)=0),"",B20/B19-1) | R20: =IF(OR(C20="",N(C19)=0),"",C20/C19-1) | S20: =IF(OR(D20="",N(D19)=0),"",D20/D19-1) | T20: =IF(OR(E20="",N(E19)=0),"",E20/E19-1) | U20: =IF(OR(F20="",N(F19)=0),"",F20/F19-1) | V20: =IF(OR(G20="",N(G19)=0),"",G20/G19-1) | W20: =IF(OR(H20="",N(H19)=0),"",H20/H19-1) | X20: =IF(OR(I20="",N(I19)=0),"",I20/I19-1) | ... AC20: =IF(OR(N20="",N(N19)=0),"",N20/N19-1) | AE20: =IFERROR(IF(OR(B20="",OFFSET(B20,-12,0)=""),"",B20/OFFSET(B20,-12,0)-1),"") | AF20: =IFERROR(IF(OR(C20="",OFFSET(C20,-12,0)=""),"",C20/OFFSET(C20,-12,0)-1),"") | AG20: =IFERROR(IF(OR(D20="",OFFSET(D20,-12,0)=""),"",D20/OFFSET(D20,-12,0)-1),"") | AH20: =IFERROR(IF(OR(E20="",OFFSET(E20,-12,0)=""),"",E20/OFFSET(E20,-12,0)-1),"") | AI20: =IFERROR(IF(OR(F20="",OFFSET(F20,-12,0)=""),"",F20/OFFSET(F20,-12,0)-1),"") | AJ20: =IFERROR(IF(OR(G20="",OFFSET(G20,-12,0)=""),"",G20/OFFSET(G20,-12,0)-1),"") | AK20: =IFERROR(IF(OR(H20="",OFFSET(H20,-12,0)=""),"",H20/OFFSET(H20,-12,0)-1),"") | AL20: =IFERROR(IF(OR(I20="",OFFSET(I20,-12,0)=""),"",I20/OFFSET(I20,-12,0)-1),"") | ... AQ20: =IFERROR(IF(OR(N20="",OFFSET(N20,-12,0)=""),"",N20/OFFSET(N20,-12,0)-1),"") | AS20: =IFERROR(IF(OR(B20="",OFFSET(B20,-3,0)=""),"",(B20/OFFSET(B20,-3,0))^4-1),"") | AT20: =IFERROR(IF(OR(C20="",OFFSET(C20,-3,0)=""),"",(C20/OFFSET(C20,-3,0))^4-1),"") | AU20: =IFERROR(IF(OR(D20="",OFFSET(D20,-3,0)=""),"",(D20/OFFSET(D20,-3,0))^4-1),"") | AV20: =IFERROR(IF(OR(E20="",OFFSET(E20,-3,0)=""),"",(E20/OFFSET(E20,-3,0))^4-1),"") | AW20: =IFERROR(IF(OR(F20="",OFFSET(F20,-3,0)=""),"",(F20/OFFSET(F20,-3,0))^4-1),"") | AX20: =IFERROR(IF(OR(G20="",OFFSET(G20,-3,0)=""),"",(G20/OFFSET(G20,-3,0))^4-1),"") | AY20: =IFERROR(IF(OR(H20="",OFFSET(H20,-3,0)=""),"",(H20/OFFSET(H20,-3,0))^4-1),"") | AZ20: =IFERROR(IF(OR(I20="",OFFSET(I20,-3,0)=""),"",(I20/OFFSET(I20,-3,0))^4-1),"") | ... BE20: =IFERROR(IF(OR(N20="",OFFSET(N20,-3,0)=""),"",(N20/OFFSET(N20,-3,0))^4-1),"") | BG20: =IFERROR(IF(OR(B20="",OFFSET(B20,-6,0)=""),"",(B20/OFFSET(B20,-6,0))^2-1),"") | BH20: =IFERROR(IF(OR(C20="",OFFSET(C20,-6,0)=""),"",(C20/OFFSET(C20,-6,0))^2-1),"") | BI20: =IFERROR(IF(OR(D20="",OFFSET(D20,-6,0)=""),"",(D20/OFFSET(D20,-6,0))^2-1),"") | BJ20: =IFERROR(IF(OR(E20="",OFFSET(E20,-6,0)=""),"",(E20/OFFSET(E20,-6,0))^2-1),"") | BK20: =IFERROR(IF(OR(F20="",OFFSET(F20,-6,0)=""),"",(F20/OFFSET(F20,-6,0))^2-1),"") | BL20: =IFERROR(IF(OR(G20="",OFFSET(G20,-6,0)=""),"",(G20/OFFSET(G20,-6,0))^2-1),"") | BM20: =IFERROR(IF(OR(H20="",OFFSET(H20,-6,0)=""),"",(H20/OFFSET(H20,-6,0))^2-1),"") | BN20: =IFERROR(IF(OR(I20="",OFFSET(I20,-6,0)=""),"",(I20/OFFSET(I20,-6,0))^2-1),"") | ... BS20: =IFERROR(IF(OR(N20="",OFFSET(N20,-6,0)=""),"",(N20/OFFSET(N20,-6,0))^2-1),"") | BX20: =IF('Macrobond Imports'!FG19="","",'Macrobond Imports'!FG19) | BY20: =IF('Macrobond Imports'!AI19="","",'Macrobond Imports'!AI19) | CA20: =IFERROR(IF(OR(BX20="",OFFSET(BX20,-12,0)=""),"",BX20/OFFSET(BX20,-12,0)-1),"") | CB20: =IFERROR(IF(OR(BY20="",OFFSET(BY20,-12,0)=""),"",BY20/OFFSET(BY20,-12,0)-1),"") | CC20: {=INDEX(MM_Headline,ROW()-5)} -> 0.0081135903 | CD20: {=INDEX(MM_Core,ROW()-5)} -> 0.0079257724 | CE20: {=INDEX(YY_Headline,ROW()-5)} -> 0.032258732 | CF20: {=INDEX(YY_Core,ROW()-5)} -> 0.035583088 | CG20: {=INDEX(Ann3_Headline,ROW()-5)} -> 0.053656148 | CH20: {=INDEX(Ann6_Headline,ROW()-5)} -> 0.022042772 | CK20: {=INDEX(ChartDates,ROW()-5)} -> 45839 | CL20: {=INDEX(UnprocEnergy_YY,ROW()-5)} -> -0.082762121 | CM20: {=INDEX(Transport_YY,ROW()-5)} -> 0.013262073 | DA20: Automobile Retailing (partial) | DB20: GD | DC20: =INDEX('Macrobond Imports'!GD:GD,MATCH(MAX('Macrobond Imports'!$A:$A),'Macrobond Imports'!$A:$A,0)) -> 102.41 | DD20: {=INDEX('Macrobond Imports'!GD:GD,MATCH(MAX('Macrobond Imports'!$A:$A),'Macrobond Imports'!$A:$A,0)-1)} -> 99.509 | DE20: =IFERROR(IF(OR(DC20="",DD20="",DC20=0,DD20=0),"",DC20/DD20-1),"") -> 0.029153142 | DF20: RT | DG20: =IF(DE20="","",DE20+ROW()*0.000000001) -> 0.029153162
A21: =IF('Macrobond Imports'!A20="","",'Macrobond Imports'!A20) -> 17715 | B21: =IF('Macrobond Imports'!B20="","",'Macrobond Imports'!B20) | C21: =IF('Macrobond Imports'!C20="","",'Macrobond Imports'!C20) | D21: =IF('Macrobond Imports'!Z20="","",'Macrobond Imports'!Z20) | E21: =IF('Macrobond Imports'!BH20="","",'Macrobond Imports'!BH20) | F21: =IF('Macrobond Imports'!BJ20="","",'Macrobond Imports'!BJ20) | G21: =IF('Macrobond Imports'!BK20="","",'Macrobond Imports'!BK20) | H21: =IF('Macrobond Imports'!BL20="","",'Macrobond Imports'!BL20) | I21: =IF('Macrobond Imports'!BS20="","",'Macrobond Imports'!BS20) | J21: =IF('Macrobond Imports'!AA20="","",'Macrobond Imports'!AA20) | K21: =IF('Macrobond Imports'!DF20="","",'Macrobond Imports'!DF20) -> 25.4 | L21: =IF('Macrobond Imports'!EA20="","",'Macrobond Imports'!EA20) -> 36.1 | M21: =IF('Macrobond Imports'!FA20="","",'Macrobond Imports'!FA20) | N21: =IF('Macrobond Imports'!FC20="","",'Macrobond Imports'!FC20) | P21: =A21 -> 17715 | Q21: =IF(OR(B21="",N(B20)=0),"",B21/B20-1) | R21: =IF(OR(C21="",N(C20)=0),"",C21/C20-1) | S21: =IF(OR(D21="",N(D20)=0),"",D21/D20-1) | T21: =IF(OR(E21="",N(E20)=0),"",E21/E20-1) | U21: =IF(OR(F21="",N(F20)=0),"",F21/F20-1) | V21: =IF(OR(G21="",N(G20)=0),"",G21/G20-1) | W21: =IF(OR(H21="",N(H20)=0),"",H21/H20-1) | X21: =IF(OR(I21="",N(I20)=0),"",I21/I20-1) | ... AC21: =IF(OR(N21="",N(N20)=0),"",N21/N20-1) | AE21: =IFERROR(IF(OR(B21="",OFFSET(B21,-12,0)=""),"",B21/OFFSET(B21,-12,0)-1),"") | AF21: =IFERROR(IF(OR(C21="",OFFSET(C21,-12,0)=""),"",C21/OFFSET(C21,-12,0)-1),"") | AG21: =IFERROR(IF(OR(D21="",OFFSET(D21,-12,0)=""),"",D21/OFFSET(D21,-12,0)-1),"") | AH21: =IFERROR(IF(OR(E21="",OFFSET(E21,-12,0)=""),"",E21/OFFSET(E21,-12,0)-1),"") | AI21: =IFERROR(IF(OR(F21="",OFFSET(F21,-12,0)=""),"",F21/OFFSET(F21,-12,0)-1),"") | AJ21: =IFERROR(IF(OR(G21="",OFFSET(G21,-12,0)=""),"",G21/OFFSET(G21,-12,0)-1),"") | AK21: =IFERROR(IF(OR(H21="",OFFSET(H21,-12,0)=""),"",H21/OFFSET(H21,-12,0)-1),"") | AL21: =IFERROR(IF(OR(I21="",OFFSET(I21,-12,0)=""),"",I21/OFFSET(I21,-12,0)-1),"") | ... AQ21: =IFERROR(IF(OR(N21="",OFFSET(N21,-12,0)=""),"",N21/OFFSET(N21,-12,0)-1),"") | AS21: =IFERROR(IF(OR(B21="",OFFSET(B21,-3,0)=""),"",(B21/OFFSET(B21,-3,0))^4-1),"") | AT21: =IFERROR(IF(OR(C21="",OFFSET(C21,-3,0)=""),"",(C21/OFFSET(C21,-3,0))^4-1),"") | AU21: =IFERROR(IF(OR(D21="",OFFSET(D21,-3,0)=""),"",(D21/OFFSET(D21,-3,0))^4-1),"") | AV21: =IFERROR(IF(OR(E21="",OFFSET(E21,-3,0)=""),"",(E21/OFFSET(E21,-3,0))^4-1),"") | AW21: =IFERROR(IF(OR(F21="",OFFSET(F21,-3,0)=""),"",(F21/OFFSET(F21,-3,0))^4-1),"") | AX21: =IFERROR(IF(OR(G21="",OFFSET(G21,-3,0)=""),"",(G21/OFFSET(G21,-3,0))^4-1),"") | AY21: =IFERROR(IF(OR(H21="",OFFSET(H21,-3,0)=""),"",(H21/OFFSET(H21,-3,0))^4-1),"") | AZ21: =IFERROR(IF(OR(I21="",OFFSET(I21,-3,0)=""),"",(I21/OFFSET(I21,-3,0))^4-1),"") | ... BE21: =IFERROR(IF(OR(N21="",OFFSET(N21,-3,0)=""),"",(N21/OFFSET(N21,-3,0))^4-1),"") | BG21: =IFERROR(IF(OR(B21="",OFFSET(B21,-6,0)=""),"",(B21/OFFSET(B21,-6,0))^2-1),"") | BH21: =IFERROR(IF(OR(C21="",OFFSET(C21,-6,0)=""),"",(C21/OFFSET(C21,-6,0))^2-1),"") | BI21: =IFERROR(IF(OR(D21="",OFFSET(D21,-6,0)=""),"",(D21/OFFSET(D21,-6,0))^2-1),"") | BJ21: =IFERROR(IF(OR(E21="",OFFSET(E21,-6,0)=""),"",(E21/OFFSET(E21,-6,0))^2-1),"") | BK21: =IFERROR(IF(OR(F21="",OFFSET(F21,-6,0)=""),"",(F21/OFFSET(F21,-6,0))^2-1),"") | BL21: =IFERROR(IF(OR(G21="",OFFSET(G21,-6,0)=""),"",(G21/OFFSET(G21,-6,0))^2-1),"") | BM21: =IFERROR(IF(OR(H21="",OFFSET(H21,-6,0)=""),"",(H21/OFFSET(H21,-6,0))^2-1),"") | BN21: =IFERROR(IF(OR(I21="",OFFSET(I21,-6,0)=""),"",(I21/OFFSET(I21,-6,0))^2-1),"") | ... BS21: =IFERROR(IF(OR(N21="",OFFSET(N21,-6,0)=""),"",(N21/OFFSET(N21,-6,0))^2-1),"") | BX21: =IF('Macrobond Imports'!FG20="","",'Macrobond Imports'!FG20) | BY21: =IF('Macrobond Imports'!AI20="","",'Macrobond Imports'!AI20) | CA21: =IFERROR(IF(OR(BX21="",OFFSET(BX21,-12,0)=""),"",BX21/OFFSET(BX21,-12,0)-1),"") | CB21: =IFERROR(IF(OR(BY21="",OFFSET(BY21,-12,0)=""),"",BY21/OFFSET(BY21,-12,0)-1),"") | CC21: {=INDEX(MM_Headline,ROW()-5)} -> -0.001804849 | CD21: {=INDEX(MM_Core,ROW()-5)} -> -0.0018883067 | CE21: {=INDEX(YY_Headline,ROW()-5)} -> 0.026944687 | CF21: {=INDEX(YY_Core,ROW()-5)} -> 0.029142619 | CG21: {=INDEX(Ann3_Headline,ROW()-5)} -> 0.032075718 | CH21: {=INDEX(Ann6_Headline,ROW()-5)} -> 0.014815014 | CK21: {=INDEX(ChartDates,ROW()-5)} -> 45870 | CL21: {=INDEX(UnprocEnergy_YY,ROW()-5)} -> -0.058878233 | CM21: {=INDEX(Transport_YY,ROW()-5)} -> 0.02769483 | DA21: Automotive Parts Retailing | DB21: GE | DC21: =INDEX('Macrobond Imports'!GE:GE,MATCH(MAX('Macrobond Imports'!$A:$A),'Macrobond Imports'!$A:$A,0)) -> 180.749 | DD21: {=INDEX('Macrobond Imports'!GE:GE,MATCH(MAX('Macrobond Imports'!$A:$A),'Macrobond Imports'!$A:$A,0)-1)} -> 177.764 | DE21: =IFERROR(IF(OR(DC21="",DD21="",DC21=0,DD21=0),"",DC21/DD21-1),"") -> 0.016791926 | DF21: RT | DG21: =IF(DE21="","",DE21+ROW()*0.000000001) -> 0.016791947
A22: =IF('Macrobond Imports'!A21="","",'Macrobond Imports'!A21) -> 17746 | B22: =IF('Macrobond Imports'!B21="","",'Macrobond Imports'!B21) | C22: =IF('Macrobond Imports'!C21="","",'Macrobond Imports'!C21) | D22: =IF('Macrobond Imports'!Z21="","",'Macrobond Imports'!Z21) | E22: =IF('Macrobond Imports'!BH21="","",'Macrobond Imports'!BH21) | F22: =IF('Macrobond Imports'!BJ21="","",'Macrobond Imports'!BJ21) | G22: =IF('Macrobond Imports'!BK21="","",'Macrobond Imports'!BK21) | H22: =IF('Macrobond Imports'!BL21="","",'Macrobond Imports'!BL21) | I22: =IF('Macrobond Imports'!BS21="","",'Macrobond Imports'!BS21) | J22: =IF('Macrobond Imports'!AA21="","",'Macrobond Imports'!AA21) | K22: =IF('Macrobond Imports'!DF21="","",'Macrobond Imports'!DF21) -> 25.5 | L22: =IF('Macrobond Imports'!EA21="","",'Macrobond Imports'!EA21) -> 35.5 | M22: =IF('Macrobond Imports'!FA21="","",'Macrobond Imports'!FA21) | N22: =IF('Macrobond Imports'!FC21="","",'Macrobond Imports'!FC21) | P22: =A22 -> 17746 | Q22: =IF(OR(B22="",N(B21)=0),"",B22/B21-1) | R22: =IF(OR(C22="",N(C21)=0),"",C22/C21-1) | S22: =IF(OR(D22="",N(D21)=0),"",D22/D21-1) | T22: =IF(OR(E22="",N(E21)=0),"",E22/E21-1) | U22: =IF(OR(F22="",N(F21)=0),"",F22/F21-1) | V22: =IF(OR(G22="",N(G21)=0),"",G22/G21-1) | W22: =IF(OR(H22="",N(H21)=0),"",H22/H21-1) | X22: =IF(OR(I22="",N(I21)=0),"",I22/I21-1) | ... AC22: =IF(OR(N22="",N(N21)=0),"",N22/N21-1) | AE22: =IFERROR(IF(OR(B22="",OFFSET(B22,-12,0)=""),"",B22/OFFSET(B22,-12,0)-1),"") | AF22: =IFERROR(IF(OR(C22="",OFFSET(C22,-12,0)=""),"",C22/OFFSET(C22,-12,0)-1),"") | AG22: =IFERROR(IF(OR(D22="",OFFSET(D22,-12,0)=""),"",D22/OFFSET(D22,-12,0)-1),"") | AH22: =IFERROR(IF(OR(E22="",OFFSET(E22,-12,0)=""),"",E22/OFFSET(E22,-12,0)-1),"") | AI22: =IFERROR(IF(OR(F22="",OFFSET(F22,-12,0)=""),"",F22/OFFSET(F22,-12,0)-1),"") | AJ22: =IFERROR(IF(OR(G22="",OFFSET(G22,-12,0)=""),"",G22/OFFSET(G22,-12,0)-1),"") | AK22: =IFERROR(IF(OR(H22="",OFFSET(H22,-12,0)=""),"",H22/OFFSET(H22,-12,0)-1),"") | AL22: =IFERROR(IF(OR(I22="",OFFSET(I22,-12,0)=""),"",I22/OFFSET(I22,-12,0)-1),"") | ... AQ22: =IFERROR(IF(OR(N22="",OFFSET(N22,-12,0)=""),"",N22/OFFSET(N22,-12,0)-1),"") | AS22: =IFERROR(IF(OR(B22="",OFFSET(B22,-3,0)=""),"",(B22/OFFSET(B22,-3,0))^4-1),"") | AT22: =IFERROR(IF(OR(C22="",OFFSET(C22,-3,0)=""),"",(C22/OFFSET(C22,-3,0))^4-1),"") | AU22: =IFERROR(IF(OR(D22="",OFFSET(D22,-3,0)=""),"",(D22/OFFSET(D22,-3,0))^4-1),"") | AV22: =IFERROR(IF(OR(E22="",OFFSET(E22,-3,0)=""),"",(E22/OFFSET(E22,-3,0))^4-1),"") | AW22: =IFERROR(IF(OR(F22="",OFFSET(F22,-3,0)=""),"",(F22/OFFSET(F22,-3,0))^4-1),"") | AX22: =IFERROR(IF(OR(G22="",OFFSET(G22,-3,0)=""),"",(G22/OFFSET(G22,-3,0))^4-1),"") | AY22: =IFERROR(IF(OR(H22="",OFFSET(H22,-3,0)=""),"",(H22/OFFSET(H22,-3,0))^4-1),"") | AZ22: =IFERROR(IF(OR(I22="",OFFSET(I22,-3,0)=""),"",(I22/OFFSET(I22,-3,0))^4-1),"") | ... BE22: =IFERROR(IF(OR(N22="",OFFSET(N22,-3,0)=""),"",(N22/OFFSET(N22,-3,0))^4-1),"") | BG22: =IFERROR(IF(OR(B22="",OFFSET(B22,-6,0)=""),"",(B22/OFFSET(B22,-6,0))^2-1),"") | BH22: =IFERROR(IF(OR(C22="",OFFSET(C22,-6,0)=""),"",(C22/OFFSET(C22,-6,0))^2-1),"") | BI22: =IFERROR(IF(OR(D22="",OFFSET(D22,-6,0)=""),"",(D22/OFFSET(D22,-6,0))^2-1),"") | BJ22: =IFERROR(IF(OR(E22="",OFFSET(E22,-6,0)=""),"",(E22/OFFSET(E22,-6,0))^2-1),"") | BK22: =IFERROR(IF(OR(F22="",OFFSET(F22,-6,0)=""),"",(F22/OFFSET(F22,-6,0))^2-1),"") | BL22: =IFERROR(IF(OR(G22="",OFFSET(G22,-6,0)=""),"",(G22/OFFSET(G22,-6,0))^2-1),"") | BM22: =IFERROR(IF(OR(H22="",OFFSET(H22,-6,0)=""),"",(H22/OFFSET(H22,-6,0))^2-1),"") | BN22: =IFERROR(IF(OR(I22="",OFFSET(I22,-6,0)=""),"",(I22/OFFSET(I22,-6,0))^2-1),"") | ... BS22: =IFERROR(IF(OR(N22="",OFFSET(N22,-6,0)=""),"",(N22/OFFSET(N22,-6,0))^2-1),"") | BX22: =IF('Macrobond Imports'!FG21="","",'Macrobond Imports'!FG21) | BY22: =IF('Macrobond Imports'!AI21="","",'Macrobond Imports'!AI21) | CA22: =IFERROR(IF(OR(BX22="",OFFSET(BX22,-12,0)=""),"",BX22/OFFSET(BX22,-12,0)-1),"") | CB22: =IFERROR(IF(OR(BY22="",OFFSET(BY22,-12,0)=""),"",BY22/OFFSET(BY22,-12,0)-1),"") | CC22: {=INDEX(MM_Headline,ROW()-5)} -> 0.0061475822 | CD22: {=INDEX(MM_Core,ROW()-5)} -> 0.0051756407 | CE22: {=INDEX(YY_Headline,ROW()-5)} -> 0.030465765 | CF22: {=INDEX(YY_Core,ROW()-5)} -> 0.029942814 | CG22: {=INDEX(Ann3_Headline,ROW()-5)} -> 0.050863851 | CH22: {=INDEX(Ann6_Headline,ROW()-5)} -> 0.029802398 | CK22: {=INDEX(ChartDates,ROW()-5)} -> 45901 | CL22: {=INDEX(UnprocEnergy_YY,ROW()-5)} -> 0.011620909 | CM22: {=INDEX(Transport_YY,ROW()-5)} -> 0.036363636 | DA22: Mobile Homes Retailing | DB22: GF | DC22: =INDEX('Macrobond Imports'!GF:GF,MATCH(MAX('Macrobond Imports'!$A:$A),'Macrobond Imports'!$A:$A,0)) -> 0 | DD22: {=INDEX('Macrobond Imports'!GF:GF,MATCH(MAX('Macrobond Imports'!$A:$A),'Macrobond Imports'!$A:$A,0)-1)} -> 0 | DE22: =IFERROR(IF(OR(DC22="",DD22="",DC22=0,DD22=0),"",DC22/DD22-1),"") | DF22: RT | DG22: =IF(DE22="","",DE22+ROW()*0.000000001)
A23: =IF('Macrobond Imports'!A22="","",'Macrobond Imports'!A22) -> 17777 | B23: =IF('Macrobond Imports'!B22="","",'Macrobond Imports'!B22) | C23: =IF('Macrobond Imports'!C22="","",'Macrobond Imports'!C22) | D23: =IF('Macrobond Imports'!Z22="","",'Macrobond Imports'!Z22) | E23: =IF('Macrobond Imports'!BH22="","",'Macrobond Imports'!BH22) | F23: =IF('Macrobond Imports'!BJ22="","",'Macrobond Imports'!BJ22) | G23: =IF('Macrobond Imports'!BK22="","",'Macrobond Imports'!BK22) | H23: =IF('Macrobond Imports'!BL22="","",'Macrobond Imports'!BL22) | I23: =IF('Macrobond Imports'!BS22="","",'Macrobond Imports'!BS22) | J23: =IF('Macrobond Imports'!AA22="","",'Macrobond Imports'!AA22) | K23: =IF('Macrobond Imports'!DF22="","",'Macrobond Imports'!DF22) -> 25.5 | L23: =IF('Macrobond Imports'!EA22="","",'Macrobond Imports'!EA22) -> 34.9 | M23: =IF('Macrobond Imports'!FA22="","",'Macrobond Imports'!FA22) | N23: =IF('Macrobond Imports'!FC22="","",'Macrobond Imports'!FC22) | P23: =A23 -> 17777 | Q23: =IF(OR(B23="",N(B22)=0),"",B23/B22-1) | R23: =IF(OR(C23="",N(C22)=0),"",C23/C22-1) | S23: =IF(OR(D23="",N(D22)=0),"",D23/D22-1) | T23: =IF(OR(E23="",N(E22)=0),"",E23/E22-1) | U23: =IF(OR(F23="",N(F22)=0),"",F23/F22-1) | V23: =IF(OR(G23="",N(G22)=0),"",G23/G22-1) | W23: =IF(OR(H23="",N(H22)=0),"",H23/H22-1) | X23: =IF(OR(I23="",N(I22)=0),"",I23/I22-1) | ... AC23: =IF(OR(N23="",N(N22)=0),"",N23/N22-1) | AE23: =IFERROR(IF(OR(B23="",OFFSET(B23,-12,0)=""),"",B23/OFFSET(B23,-12,0)-1),"") | AF23: =IFERROR(IF(OR(C23="",OFFSET(C23,-12,0)=""),"",C23/OFFSET(C23,-12,0)-1),"") | AG23: =IFERROR(IF(OR(D23="",OFFSET(D23,-12,0)=""),"",D23/OFFSET(D23,-12,0)-1),"") | AH23: =IFERROR(IF(OR(E23="",OFFSET(E23,-12,0)=""),"",E23/OFFSET(E23,-12,0)-1),"") | AI23: =IFERROR(IF(OR(F23="",OFFSET(F23,-12,0)=""),"",F23/OFFSET(F23,-12,0)-1),"") | AJ23: =IFERROR(IF(OR(G23="",OFFSET(G23,-12,0)=""),"",G23/OFFSET(G23,-12,0)-1),"") | AK23: =IFERROR(IF(OR(H23="",OFFSET(H23,-12,0)=""),"",H23/OFFSET(H23,-12,0)-1),"") | AL23: =IFERROR(IF(OR(I23="",OFFSET(I23,-12,0)=""),"",I23/OFFSET(I23,-12,0)-1),"") | ... AQ23: =IFERROR(IF(OR(N23="",OFFSET(N23,-12,0)=""),"",N23/OFFSET(N23,-12,0)-1),"") | AS23: =IFERROR(IF(OR(B23="",OFFSET(B23,-3,0)=""),"",(B23/OFFSET(B23,-3,0))^4-1),"") | AT23: =IFERROR(IF(OR(C23="",OFFSET(C23,-3,0)=""),"",(C23/OFFSET(C23,-3,0))^4-1),"") | AU23: =IFERROR(IF(OR(D23="",OFFSET(D23,-3,0)=""),"",(D23/OFFSET(D23,-3,0))^4-1),"") | AV23: =IFERROR(IF(OR(E23="",OFFSET(E23,-3,0)=""),"",(E23/OFFSET(E23,-3,0))^4-1),"") | AW23: =IFERROR(IF(OR(F23="",OFFSET(F23,-3,0)=""),"",(F23/OFFSET(F23,-3,0))^4-1),"") | AX23: =IFERROR(IF(OR(G23="",OFFSET(G23,-3,0)=""),"",(G23/OFFSET(G23,-3,0))^4-1),"") | AY23: =IFERROR(IF(OR(H23="",OFFSET(H23,-3,0)=""),"",(H23/OFFSET(H23,-3,0))^4-1),"") | AZ23: =IFERROR(IF(OR(I23="",OFFSET(I23,-3,0)=""),"",(I23/OFFSET(I23,-3,0))^4-1),"") | ... BE23: =IFERROR(IF(OR(N23="",OFFSET(N23,-3,0)=""),"",(N23/OFFSET(N23,-3,0))^4-1),"") | BG23: =IFERROR(IF(OR(B23="",OFFSET(B23,-6,0)=""),"",(B23/OFFSET(B23,-6,0))^2-1),"") | BH23: =IFERROR(IF(OR(C23="",OFFSET(C23,-6,0)=""),"",(C23/OFFSET(C23,-6,0))^2-1),"") | BI23: =IFERROR(IF(OR(D23="",OFFSET(D23,-6,0)=""),"",(D23/OFFSET(D23,-6,0))^2-1),"") | BJ23: =IFERROR(IF(OR(E23="",OFFSET(E23,-6,0)=""),"",(E23/OFFSET(E23,-6,0))^2-1),"") | BK23: =IFERROR(IF(OR(F23="",OFFSET(F23,-6,0)=""),"",(F23/OFFSET(F23,-6,0))^2-1),"") | BL23: =IFERROR(IF(OR(G23="",OFFSET(G23,-6,0)=""),"",(G23/OFFSET(G23,-6,0))^2-1),"") | BM23: =IFERROR(IF(OR(H23="",OFFSET(H23,-6,0)=""),"",(H23/OFFSET(H23,-6,0))^2-1),"") | BN23: =IFERROR(IF(OR(I23="",OFFSET(I23,-6,0)=""),"",(I23/OFFSET(I23,-6,0))^2-1),"") | ... BS23: =IFERROR(IF(OR(N23="",OFFSET(N23,-6,0)=""),"",(N23/OFFSET(N23,-6,0))^2-1),"") | BX23: =IF('Macrobond Imports'!FG22="","",'Macrobond Imports'!FG22) | BY23: =IF('Macrobond Imports'!AI22="","",'Macrobond Imports'!AI22) | CA23: =IFERROR(IF(OR(BX23="",OFFSET(BX23,-12,0)=""),"",BX23/OFFSET(BX23,-12,0)-1),"") | CB23: =IFERROR(IF(OR(BY23="",OFFSET(BY23,-12,0)=""),"",BY23/OFFSET(BY23,-12,0)-1),"") | CC23: {=INDEX(MM_Headline,ROW()-5)} -> 0.0012912243 | CD23: {=INDEX(MM_Core,ROW()-5)} -> 0.0030383082 | CE23: {=INDEX(YY_Headline,ROW()-5)} -> 0.028333356 | CF23: {=INDEX(YY_Core,ROW()-5)} -> 0.02971438 | CG23: {=INDEX(Ann3_Headline,ROW()-5)} -> 0.022704612 | CH23: {=INDEX(Ann6_Headline,ROW()-5)} -> 0.038065028 | CK23: {=INDEX(ChartDates,ROW()-5)} -> 45931 | CL23: {=INDEX(UnprocEnergy_YY,ROW()-5)} -> -0.098214819 | CM23: {=INDEX(Transport_YY,ROW()-5)} -> 0.033691709 | DA23: RVs/Trailers/Campers Retailing | DB23: GG | DC23: =INDEX('Macrobond Imports'!GG:GG,MATCH(MAX('Macrobond Imports'!$A:$A),'Macrobond Imports'!$A:$A,0)) -> 141.651 | DD23: {=INDEX('Macrobond Imports'!GG:GG,MATCH(MAX('Macrobond Imports'!$A:$A),'Macrobond Imports'!$A:$A,0)-1)} -> 145.501 | DE23: =IFERROR(IF(OR(DC23="",DD23="",DC23=0,DD23=0),"",DC23/DD23-1),"") -> -0.026460299 | DF23: RT | DG23: =IF(DE23="","",DE23+ROW()*0.000000001) -> -0.026460276
A24: =IF('Macrobond Imports'!A23="","",'Macrobond Imports'!A23) -> 17807 | B24: =IF('Macrobond Imports'!B23="","",'Macrobond Imports'!B23) | C24: =IF('Macrobond Imports'!C23="","",'Macrobond Imports'!C23) | D24: =IF('Macrobond Imports'!Z23="","",'Macrobond Imports'!Z23) | E24: =IF('Macrobond Imports'!BH23="","",'Macrobond Imports'!BH23) | F24: =IF('Macrobond Imports'!BJ23="","",'Macrobond Imports'!BJ23) | G24: =IF('Macrobond Imports'!BK23="","",'Macrobond Imports'!BK23) | H24: =IF('Macrobond Imports'!BL23="","",'Macrobond Imports'!BL23) | I24: =IF('Macrobond Imports'!BS23="","",'Macrobond Imports'!BS23) | J24: =IF('Macrobond Imports'!AA23="","",'Macrobond Imports'!AA23) | K24: =IF('Macrobond Imports'!DF23="","",'Macrobond Imports'!DF23) -> 25.5 | L24: =IF('Macrobond Imports'!EA23="","",'Macrobond Imports'!EA23) -> 33.8 | M24: =IF('Macrobond Imports'!FA23="","",'Macrobond Imports'!FA23) | N24: =IF('Macrobond Imports'!FC23="","",'Macrobond Imports'!FC23) | P24: =A24 -> 17807 | Q24: =IF(OR(B24="",N(B23)=0),"",B24/B23-1) | R24: =IF(OR(C24="",N(C23)=0),"",C24/C23-1) | S24: =IF(OR(D24="",N(D23)=0),"",D24/D23-1) | T24: =IF(OR(E24="",N(E23)=0),"",E24/E23-1) | U24: =IF(OR(F24="",N(F23)=0),"",F24/F23-1) | V24: =IF(OR(G24="",N(G23)=0),"",G24/G23-1) | W24: =IF(OR(H24="",N(H23)=0),"",H24/H23-1) | X24: =IF(OR(I24="",N(I23)=0),"",I24/I23-1) | ... AC24: =IF(OR(N24="",N(N23)=0),"",N24/N23-1) | AE24: =IFERROR(IF(OR(B24="",OFFSET(B24,-12,0)=""),"",B24/OFFSET(B24,-12,0)-1),"") | AF24: =IFERROR(IF(OR(C24="",OFFSET(C24,-12,0)=""),"",C24/OFFSET(C24,-12,0)-1),"") | AG24: =IFERROR(IF(OR(D24="",OFFSET(D24,-12,0)=""),"",D24/OFFSET(D24,-12,0)-1),"") | AH24: =IFERROR(IF(OR(E24="",OFFSET(E24,-12,0)=""),"",E24/OFFSET(E24,-12,0)-1),"") | AI24: =IFERROR(IF(OR(F24="",OFFSET(F24,-12,0)=""),"",F24/OFFSET(F24,-12,0)-1),"") | AJ24: =IFERROR(IF(OR(G24="",OFFSET(G24,-12,0)=""),"",G24/OFFSET(G24,-12,0)-1),"") | AK24: =IFERROR(IF(OR(H24="",OFFSET(H24,-12,0)=""),"",H24/OFFSET(H24,-12,0)-1),"") | AL24: =IFERROR(IF(OR(I24="",OFFSET(I24,-12,0)=""),"",I24/OFFSET(I24,-12,0)-1),"") | ... AQ24: =IFERROR(IF(OR(N24="",OFFSET(N24,-12,0)=""),"",N24/OFFSET(N24,-12,0)-1),"") | AS24: =IFERROR(IF(OR(B24="",OFFSET(B24,-3,0)=""),"",(B24/OFFSET(B24,-3,0))^4-1),"") | AT24: =IFERROR(IF(OR(C24="",OFFSET(C24,-3,0)=""),"",(C24/OFFSET(C24,-3,0))^4-1),"") | AU24: =IFERROR(IF(OR(D24="",OFFSET(D24,-3,0)=""),"",(D24/OFFSET(D24,-3,0))^4-1),"") | AV24: =IFERROR(IF(OR(E24="",OFFSET(E24,-3,0)=""),"",(E24/OFFSET(E24,-3,0))^4-1),"") | AW24: =IFERROR(IF(OR(F24="",OFFSET(F24,-3,0)=""),"",(F24/OFFSET(F24,-3,0))^4-1),"") | AX24: =IFERROR(IF(OR(G24="",OFFSET(G24,-3,0)=""),"",(G24/OFFSET(G24,-3,0))^4-1),"") | AY24: =IFERROR(IF(OR(H24="",OFFSET(H24,-3,0)=""),"",(H24/OFFSET(H24,-3,0))^4-1),"") | AZ24: =IFERROR(IF(OR(I24="",OFFSET(I24,-3,0)=""),"",(I24/OFFSET(I24,-3,0))^4-1),"") | ... BE24: =IFERROR(IF(OR(N24="",OFFSET(N24,-3,0)=""),"",(N24/OFFSET(N24,-3,0))^4-1),"") | BG24: =IFERROR(IF(OR(B24="",OFFSET(B24,-6,0)=""),"",(B24/OFFSET(B24,-6,0))^2-1),"") | BH24: =IFERROR(IF(OR(C24="",OFFSET(C24,-6,0)=""),"",(C24/OFFSET(C24,-6,0))^2-1),"") | BI24: =IFERROR(IF(OR(D24="",OFFSET(D24,-6,0)=""),"",(D24/OFFSET(D24,-6,0))^2-1),"") | BJ24: =IFERROR(IF(OR(E24="",OFFSET(E24,-6,0)=""),"",(E24/OFFSET(E24,-6,0))^2-1),"") | BK24: =IFERROR(IF(OR(F24="",OFFSET(F24,-6,0)=""),"",(F24/OFFSET(F24,-6,0))^2-1),"") | BL24: =IFERROR(IF(OR(G24="",OFFSET(G24,-6,0)=""),"",(G24/OFFSET(G24,-6,0))^2-1),"") | BM24: =IFERROR(IF(OR(H24="",OFFSET(H24,-6,0)=""),"",(H24/OFFSET(H24,-6,0))^2-1),"") | BN24: =IFERROR(IF(OR(I24="",OFFSET(I24,-6,0)=""),"",(I24/OFFSET(I24,-6,0))^2-1),"") | ... BS24: =IFERROR(IF(OR(N24="",OFFSET(N24,-6,0)=""),"",(N24/OFFSET(N24,-6,0))^2-1),"") | BX24: =IF('Macrobond Imports'!FG23="","",'Macrobond Imports'!FG23) | BY24: =IF('Macrobond Imports'!AI23="","",'Macrobond Imports'!AI23) | CA24: =IFERROR(IF(OR(BX24="",OFFSET(BX24,-12,0)=""),"",BX24/OFFSET(BX24,-12,0)-1),"") | CB24: =IFERROR(IF(OR(BY24="",OFFSET(BY24,-12,0)=""),"",BY24/OFFSET(BY24,-12,0)-1),"") | CC24: {=INDEX(MM_Headline,ROW()-5)} -> 0.0040880357 | CD24: {=INDEX(MM_Core,ROW()-5)} -> 0.0025130848 | CE24: {=INDEX(YY_Headline,ROW()-5)} -> 0.03145848 | CF24: {=INDEX(YY_Core,ROW()-5)} -> 0.032337759 | CG24: {=INDEX(Ann3_Headline,ROW()-5)} -> 0.047069622 | CH24: {=INDEX(Ann6_Headline,ROW()-5)} -> 0.039545637 | CK24: {=INDEX(ChartDates,ROW()-5)} -> 45962 | CL24: {=INDEX(UnprocEnergy_YY,ROW()-5)} -> -0.034029714 | CM24: {=INDEX(Transport_YY,ROW()-5)} -> 0.044757289 | DA24: Sporting Goods Retailing | DB24: GH | DC24: =INDEX('Macrobond Imports'!GH:GH,MATCH(MAX('Macrobond Imports'!$A:$A),'Macrobond Imports'!$A:$A,0)) -> 116.094 | DD24: {=INDEX('Macrobond Imports'!GH:GH,MATCH(MAX('Macrobond Imports'!$A:$A),'Macrobond Imports'!$A:$A,0)-1)} -> 113.542 | DE24: =IFERROR(IF(OR(DC24="",DD24="",DC24=0,DD24=0),"",DC24/DD24-1),"") -> 0.022476264 | DF24: RT | DG24: =IF(DE24="","",DE24+ROW()*0.000000001) -> 0.022476288
A25: =IF('Macrobond Imports'!A24="","",'Macrobond Imports'!A24) -> 17838 | B25: =IF('Macrobond Imports'!B24="","",'Macrobond Imports'!B24) | C25: =IF('Macrobond Imports'!C24="","",'Macrobond Imports'!C24) | D25: =IF('Macrobond Imports'!Z24="","",'Macrobond Imports'!Z24) | E25: =IF('Macrobond Imports'!BH24="","",'Macrobond Imports'!BH24) | F25: =IF('Macrobond Imports'!BJ24="","",'Macrobond Imports'!BJ24) | G25: =IF('Macrobond Imports'!BK24="","",'Macrobond Imports'!BK24) | H25: =IF('Macrobond Imports'!BL24="","",'Macrobond Imports'!BL24) | I25: =IF('Macrobond Imports'!BS24="","",'Macrobond Imports'!BS24) | J25: =IF('Macrobond Imports'!AA24="","",'Macrobond Imports'!AA24) | K25: =IF('Macrobond Imports'!DF24="","",'Macrobond Imports'!DF24) -> 25.4 | L25: =IF('Macrobond Imports'!EA24="","",'Macrobond Imports'!EA24) -> 33.5 | M25: =IF('Macrobond Imports'!FA24="","",'Macrobond Imports'!FA24) | N25: =IF('Macrobond Imports'!FC24="","",'Macrobond Imports'!FC24) | P25: =A25 -> 17838 | Q25: =IF(OR(B25="",N(B24)=0),"",B25/B24-1) | R25: =IF(OR(C25="",N(C24)=0),"",C25/C24-1) | S25: =IF(OR(D25="",N(D24)=0),"",D25/D24-1) | T25: =IF(OR(E25="",N(E24)=0),"",E25/E24-1) | U25: =IF(OR(F25="",N(F24)=0),"",F25/F24-1) | V25: =IF(OR(G25="",N(G24)=0),"",G25/G24-1) | W25: =IF(OR(H25="",N(H24)=0),"",H25/H24-1) | X25: =IF(OR(I25="",N(I24)=0),"",I25/I24-1) | ... AC25: =IF(OR(N25="",N(N24)=0),"",N25/N24-1) | AE25: =IFERROR(IF(OR(B25="",OFFSET(B25,-12,0)=""),"",B25/OFFSET(B25,-12,0)-1),"") | AF25: =IFERROR(IF(OR(C25="",OFFSET(C25,-12,0)=""),"",C25/OFFSET(C25,-12,0)-1),"") | AG25: =IFERROR(IF(OR(D25="",OFFSET(D25,-12,0)=""),"",D25/OFFSET(D25,-12,0)-1),"") | AH25: =IFERROR(IF(OR(E25="",OFFSET(E25,-12,0)=""),"",E25/OFFSET(E25,-12,0)-1),"") | AI25: =IFERROR(IF(OR(F25="",OFFSET(F25,-12,0)=""),"",F25/OFFSET(F25,-12,0)-1),"") | AJ25: =IFERROR(IF(OR(G25="",OFFSET(G25,-12,0)=""),"",G25/OFFSET(G25,-12,0)-1),"") | AK25: =IFERROR(IF(OR(H25="",OFFSET(H25,-12,0)=""),"",H25/OFFSET(H25,-12,0)-1),"") | AL25: =IFERROR(IF(OR(I25="",OFFSET(I25,-12,0)=""),"",I25/OFFSET(I25,-12,0)-1),"") | ... AQ25: =IFERROR(IF(OR(N25="",OFFSET(N25,-12,0)=""),"",N25/OFFSET(N25,-12,0)-1),"") | AS25: =IFERROR(IF(OR(B25="",OFFSET(B25,-3,0)=""),"",(B25/OFFSET(B25,-3,0))^4-1),"") | AT25: =IFERROR(IF(OR(C25="",OFFSET(C25,-3,0)=""),"",(C25/OFFSET(C25,-3,0))^4-1),"") | AU25: =IFERROR(IF(OR(D25="",OFFSET(D25,-3,0)=""),"",(D25/OFFSET(D25,-3,0))^4-1),"") | AV25: =IFERROR(IF(OR(E25="",OFFSET(E25,-3,0)=""),"",(E25/OFFSET(E25,-3,0))^4-1),"") | AW25: =IFERROR(IF(OR(F25="",OFFSET(F25,-3,0)=""),"",(F25/OFFSET(F25,-3,0))^4-1),"") | AX25: =IFERROR(IF(OR(G25="",OFFSET(G25,-3,0)=""),"",(G25/OFFSET(G25,-3,0))^4-1),"") | AY25: =IFERROR(IF(OR(H25="",OFFSET(H25,-3,0)=""),"",(H25/OFFSET(H25,-3,0))^4-1),"") | AZ25: =IFERROR(IF(OR(I25="",OFFSET(I25,-3,0)=""),"",(I25/OFFSET(I25,-3,0))^4-1),"") | ... BE25: =IFERROR(IF(OR(N25="",OFFSET(N25,-3,0)=""),"",(N25/OFFSET(N25,-3,0))^4-1),"") | BG25: =IFERROR(IF(OR(B25="",OFFSET(B25,-6,0)=""),"",(B25/OFFSET(B25,-6,0))^2-1),"") | BH25: =IFERROR(IF(OR(C25="",OFFSET(C25,-6,0)=""),"",(C25/OFFSET(C25,-6,0))^2-1),"") | BI25: =IFERROR(IF(OR(D25="",OFFSET(D25,-6,0)=""),"",(D25/OFFSET(D25,-6,0))^2-1),"") | BJ25: =IFERROR(IF(OR(E25="",OFFSET(E25,-6,0)=""),"",(E25/OFFSET(E25,-6,0))^2-1),"") | BK25: =IFERROR(IF(OR(F25="",OFFSET(F25,-6,0)=""),"",(F25/OFFSET(F25,-6,0))^2-1),"") | BL25: =IFERROR(IF(OR(G25="",OFFSET(G25,-6,0)=""),"",(G25/OFFSET(G25,-6,0))^2-1),"") | BM25: =IFERROR(IF(OR(H25="",OFFSET(H25,-6,0)=""),"",(H25/OFFSET(H25,-6,0))^2-1),"") | BN25: =IFERROR(IF(OR(I25="",OFFSET(I25,-6,0)=""),"",(I25/OFFSET(I25,-6,0))^2-1),"") | ... BS25: =IFERROR(IF(OR(N25="",OFFSET(N25,-6,0)=""),"",(N25/OFFSET(N25,-6,0))^2-1),"") | BX25: =IF('Macrobond Imports'!FG24="","",'Macrobond Imports'!FG24) | BY25: =IF('Macrobond Imports'!AI24="","",'Macrobond Imports'!AI24) | CA25: =IFERROR(IF(OR(BX25="",OFFSET(BX25,-12,0)=""),"",BX25/OFFSET(BX25,-12,0)-1),"") | CB25: =IFERROR(IF(OR(BY25="",OFFSET(BY25,-12,0)=""),"",BY25/OFFSET(BY25,-12,0)-1),"") | CC25: {=INDEX(MM_Headline,ROW()-5)} -> 0.0035616402 | CD25: {=INDEX(MM_Core,ROW()-5)} -> 0.0050536786 | CE25: {=INDEX(YY_Headline,ROW()-5)} -> 0.030873433 | CF25: {=INDEX(YY_Core,ROW()-5)} -> 0.034264527 | CG25: {=INDEX(Ann3_Headline,ROW()-5)} -> 0.036346581 | CH25: {=INDEX(Ann6_Headline,ROW()-5)} -> 0.043579972 | CK25: {=INDEX(ChartDates,ROW()-5)} -> 45992 | CL25: {=INDEX(UnprocEnergy_YY,ROW()-5)} -> -0.043403651 | CM25: {=INDEX(Transport_YY,ROW()-5)} -> 0.021815077 | DA25: Lawn/Garden/Farm Equip Retailing | DB25: GI | DC25: =INDEX('Macrobond Imports'!GI:GI,MATCH(MAX('Macrobond Imports'!$A:$A),'Macrobond Imports'!$A:$A,0)) -> 184.818 | DD25: {=INDEX('Macrobond Imports'!GI:GI,MATCH(MAX('Macrobond Imports'!$A:$A),'Macrobond Imports'!$A:$A,0)-1)} -> 184.553 | DE25: =IFERROR(IF(OR(DC25="",DD25="",DC25=0,DD25=0),"",DC25/DD25-1),"") -> 0.0014359019 | DF25: RT | DG25: =IF(DE25="","",DE25+ROW()*0.000000001) -> 0.0014359269
A26: =IF('Macrobond Imports'!A25="","",'Macrobond Imports'!A25) -> 17868 | B26: =IF('Macrobond Imports'!B25="","",'Macrobond Imports'!B25) | C26: =IF('Macrobond Imports'!C25="","",'Macrobond Imports'!C25) | D26: =IF('Macrobond Imports'!Z25="","",'Macrobond Imports'!Z25) | E26: =IF('Macrobond Imports'!BH25="","",'Macrobond Imports'!BH25) | F26: =IF('Macrobond Imports'!BJ25="","",'Macrobond Imports'!BJ25) | G26: =IF('Macrobond Imports'!BK25="","",'Macrobond Imports'!BK25) | H26: =IF('Macrobond Imports'!BL25="","",'Macrobond Imports'!BL25) | I26: =IF('Macrobond Imports'!BS25="","",'Macrobond Imports'!BS25) | J26: =IF('Macrobond Imports'!AA25="","",'Macrobond Imports'!AA25) | K26: =IF('Macrobond Imports'!DF25="","",'Macrobond Imports'!DF25) -> 25.2 | L26: =IF('Macrobond Imports'!EA25="","",'Macrobond Imports'!EA25) -> 33 | M26: =IF('Macrobond Imports'!FA25="","",'Macrobond Imports'!FA25) | N26: =IF('Macrobond Imports'!FC25="","",'Macrobond Imports'!FC25) | P26: =A26 -> 17868 | Q26: =IF(OR(B26="",N(B25)=0),"",B26/B25-1) | R26: =IF(OR(C26="",N(C25)=0),"",C26/C25-1) | S26: =IF(OR(D26="",N(D25)=0),"",D26/D25-1) | T26: =IF(OR(E26="",N(E25)=0),"",E26/E25-1) | U26: =IF(OR(F26="",N(F25)=0),"",F26/F25-1) | V26: =IF(OR(G26="",N(G25)=0),"",G26/G25-1) | W26: =IF(OR(H26="",N(H25)=0),"",H26/H25-1) | X26: =IF(OR(I26="",N(I25)=0),"",I26/I25-1) | ... AC26: =IF(OR(N26="",N(N25)=0),"",N26/N25-1) | AE26: =IFERROR(IF(OR(B26="",OFFSET(B26,-12,0)=""),"",B26/OFFSET(B26,-12,0)-1),"") | AF26: =IFERROR(IF(OR(C26="",OFFSET(C26,-12,0)=""),"",C26/OFFSET(C26,-12,0)-1),"") | AG26: =IFERROR(IF(OR(D26="",OFFSET(D26,-12,0)=""),"",D26/OFFSET(D26,-12,0)-1),"") | AH26: =IFERROR(IF(OR(E26="",OFFSET(E26,-12,0)=""),"",E26/OFFSET(E26,-12,0)-1),"") | AI26: =IFERROR(IF(OR(F26="",OFFSET(F26,-12,0)=""),"",F26/OFFSET(F26,-12,0)-1),"") | AJ26: =IFERROR(IF(OR(G26="",OFFSET(G26,-12,0)=""),"",G26/OFFSET(G26,-12,0)-1),"") | AK26: =IFERROR(IF(OR(H26="",OFFSET(H26,-12,0)=""),"",H26/OFFSET(H26,-12,0)-1),"") | AL26: =IFERROR(IF(OR(I26="",OFFSET(I26,-12,0)=""),"",I26/OFFSET(I26,-12,0)-1),"") | ... AQ26: =IFERROR(IF(OR(N26="",OFFSET(N26,-12,0)=""),"",N26/OFFSET(N26,-12,0)-1),"") | AS26: =IFERROR(IF(OR(B26="",OFFSET(B26,-3,0)=""),"",(B26/OFFSET(B26,-3,0))^4-1),"") | AT26: =IFERROR(IF(OR(C26="",OFFSET(C26,-3,0)=""),"",(C26/OFFSET(C26,-3,0))^4-1),"") | AU26: =IFERROR(IF(OR(D26="",OFFSET(D26,-3,0)=""),"",(D26/OFFSET(D26,-3,0))^4-1),"") | AV26: =IFERROR(IF(OR(E26="",OFFSET(E26,-3,0)=""),"",(E26/OFFSET(E26,-3,0))^4-1),"") | AW26: =IFERROR(IF(OR(F26="",OFFSET(F26,-3,0)=""),"",(F26/OFFSET(F26,-3,0))^4-1),"") | AX26: =IFERROR(IF(OR(G26="",OFFSET(G26,-3,0)=""),"",(G26/OFFSET(G26,-3,0))^4-1),"") | AY26: =IFERROR(IF(OR(H26="",OFFSET(H26,-3,0)=""),"",(H26/OFFSET(H26,-3,0))^4-1),"") | AZ26: =IFERROR(IF(OR(I26="",OFFSET(I26,-3,0)=""),"",(I26/OFFSET(I26,-3,0))^4-1),"") | ... BE26: =IFERROR(IF(OR(N26="",OFFSET(N26,-3,0)=""),"",(N26/OFFSET(N26,-3,0))^4-1),"") | BG26: =IFERROR(IF(OR(B26="",OFFSET(B26,-6,0)=""),"",(B26/OFFSET(B26,-6,0))^2-1),"") | BH26: =IFERROR(IF(OR(C26="",OFFSET(C26,-6,0)=""),"",(C26/OFFSET(C26,-6,0))^2-1),"") | BI26: =IFERROR(IF(OR(D26="",OFFSET(D26,-6,0)=""),"",(D26/OFFSET(D26,-6,0))^2-1),"") | BJ26: =IFERROR(IF(OR(E26="",OFFSET(E26,-6,0)=""),"",(E26/OFFSET(E26,-6,0))^2-1),"") | BK26: =IFERROR(IF(OR(F26="",OFFSET(F26,-6,0)=""),"",(F26/OFFSET(F26,-6,0))^2-1),"") | BL26: =IFERROR(IF(OR(G26="",OFFSET(G26,-6,0)=""),"",(G26/OFFSET(G26,-6,0))^2-1),"") | BM26: =IFERROR(IF(OR(H26="",OFFSET(H26,-6,0)=""),"",(H26/OFFSET(H26,-6,0))^2-1),"") | BN26: =IFERROR(IF(OR(I26="",OFFSET(I26,-6,0)=""),"",(I26/OFFSET(I26,-6,0))^2-1),"") | ... BS26: =IFERROR(IF(OR(N26="",OFFSET(N26,-6,0)=""),"",(N26/OFFSET(N26,-6,0))^2-1),"") | BX26: =IF('Macrobond Imports'!FG25="","",'Macrobond Imports'!FG25) | BY26: =IF('Macrobond Imports'!AI25="","",'Macrobond Imports'!AI25) | CA26: =IFERROR(IF(OR(BX26="",OFFSET(BX26,-12,0)=""),"",BX26/OFFSET(BX26,-12,0)-1),"") | CB26: =IFERROR(IF(OR(BY26="",OFFSET(BY26,-12,0)=""),"",BY26/OFFSET(BY26,-12,0)-1),"") | CC26: {=INDEX(MM_Headline,ROW()-5)} -> 0.0055609795 | CD26: {=INDEX(MM_Core,ROW()-5)} -> 0.0081609578 | CE26: {=INDEX(YY_Headline,ROW()-5)} -> 0.030140226 | CF26: {=INDEX(YY_Core,ROW()-5)} -> 0.036927329 | CG26: {=INDEX(Ann3_Headline,ROW()-5)} -> 0.054136931 | CH26: {=INDEX(Ann6_Headline,ROW()-5)} -> 0.038301835 | CK26: {=INDEX(ChartDates,ROW()-5)} -> 46023 | CL26: {=INDEX(UnprocEnergy_YY,ROW()-5)} -> -0.04204017 | CM26: {=INDEX(Transport_YY,ROW()-5)} -> 0.025198054 | DA26: Furniture Retailing | DB26: GJ | DC26: =INDEX('Macrobond Imports'!GJ:GJ,MATCH(MAX('Macrobond Imports'!$A:$A),'Macrobond Imports'!$A:$A,0)) -> 132.372 | DD26: {=INDEX('Macrobond Imports'!GJ:GJ,MATCH(MAX('Macrobond Imports'!$A:$A),'Macrobond Imports'!$A:$A,0)-1)} -> 132.724 | DE26: =IFERROR(IF(OR(DC26="",DD26="",DC26=0,DD26=0),"",DC26/DD26-1),"") -> -0.0026521202 | DF26: RT | DG26: =IF(DE26="","",DE26+ROW()*0.000000001) -> -0.0026520942
A27: =IF('Macrobond Imports'!A26="","",'Macrobond Imports'!A26) -> 17899 | B27: =IF('Macrobond Imports'!B26="","",'Macrobond Imports'!B26) | C27: =IF('Macrobond Imports'!C26="","",'Macrobond Imports'!C26) | D27: =IF('Macrobond Imports'!Z26="","",'Macrobond Imports'!Z26) | E27: =IF('Macrobond Imports'!BH26="","",'Macrobond Imports'!BH26) | F27: =IF('Macrobond Imports'!BJ26="","",'Macrobond Imports'!BJ26) | G27: =IF('Macrobond Imports'!BK26="","",'Macrobond Imports'!BK26) | H27: =IF('Macrobond Imports'!BL26="","",'Macrobond Imports'!BL26) | I27: =IF('Macrobond Imports'!BS26="","",'Macrobond Imports'!BS26) | J27: =IF('Macrobond Imports'!AA26="","",'Macrobond Imports'!AA26) | K27: =IF('Macrobond Imports'!DF26="","",'Macrobond Imports'!DF26) -> 25.2 | L27: =IF('Macrobond Imports'!EA26="","",'Macrobond Imports'!EA26) -> 32 | M27: =IF('Macrobond Imports'!FA26="","",'Macrobond Imports'!FA26) | N27: =IF('Macrobond Imports'!FC26="","",'Macrobond Imports'!FC26) | P27: =A27 -> 17899 | Q27: =IF(OR(B27="",N(B26)=0),"",B27/B26-1) | R27: =IF(OR(C27="",N(C26)=0),"",C27/C26-1) | S27: =IF(OR(D27="",N(D26)=0),"",D27/D26-1) | T27: =IF(OR(E27="",N(E26)=0),"",E27/E26-1) | U27: =IF(OR(F27="",N(F26)=0),"",F27/F26-1) | V27: =IF(OR(G27="",N(G26)=0),"",G27/G26-1) | W27: =IF(OR(H27="",N(H26)=0),"",H27/H26-1) | X27: =IF(OR(I27="",N(I26)=0),"",I27/I26-1) | ... AC27: =IF(OR(N27="",N(N26)=0),"",N27/N26-1) | AE27: =IFERROR(IF(OR(B27="",OFFSET(B27,-12,0)=""),"",B27/OFFSET(B27,-12,0)-1),"") | AF27: =IFERROR(IF(OR(C27="",OFFSET(C27,-12,0)=""),"",C27/OFFSET(C27,-12,0)-1),"") | AG27: =IFERROR(IF(OR(D27="",OFFSET(D27,-12,0)=""),"",D27/OFFSET(D27,-12,0)-1),"") | AH27: =IFERROR(IF(OR(E27="",OFFSET(E27,-12,0)=""),"",E27/OFFSET(E27,-12,0)-1),"") | AI27: =IFERROR(IF(OR(F27="",OFFSET(F27,-12,0)=""),"",F27/OFFSET(F27,-12,0)-1),"") | AJ27: =IFERROR(IF(OR(G27="",OFFSET(G27,-12,0)=""),"",G27/OFFSET(G27,-12,0)-1),"") | AK27: =IFERROR(IF(OR(H27="",OFFSET(H27,-12,0)=""),"",H27/OFFSET(H27,-12,0)-1),"") | AL27: =IFERROR(IF(OR(I27="",OFFSET(I27,-12,0)=""),"",I27/OFFSET(I27,-12,0)-1),"") | ... AQ27: =IFERROR(IF(OR(N27="",OFFSET(N27,-12,0)=""),"",N27/OFFSET(N27,-12,0)-1),"") | AS27: =IFERROR(IF(OR(B27="",OFFSET(B27,-3,0)=""),"",(B27/OFFSET(B27,-3,0))^4-1),"") | AT27: =IFERROR(IF(OR(C27="",OFFSET(C27,-3,0)=""),"",(C27/OFFSET(C27,-3,0))^4-1),"") | AU27: =IFERROR(IF(OR(D27="",OFFSET(D27,-3,0)=""),"",(D27/OFFSET(D27,-3,0))^4-1),"") | AV27: =IFERROR(IF(OR(E27="",OFFSET(E27,-3,0)=""),"",(E27/OFFSET(E27,-3,0))^4-1),"") | AW27: =IFERROR(IF(OR(F27="",OFFSET(F27,-3,0)=""),"",(F27/OFFSET(F27,-3,0))^4-1),"") | AX27: =IFERROR(IF(OR(G27="",OFFSET(G27,-3,0)=""),"",(G27/OFFSET(G27,-3,0))^4-1),"") | AY27: =IFERROR(IF(OR(H27="",OFFSET(H27,-3,0)=""),"",(H27/OFFSET(H27,-3,0))^4-1),"") | AZ27: =IFERROR(IF(OR(I27="",OFFSET(I27,-3,0)=""),"",(I27/OFFSET(I27,-3,0))^4-1),"") | ... BE27: =IFERROR(IF(OR(N27="",OFFSET(N27,-3,0)=""),"",(N27/OFFSET(N27,-3,0))^4-1),"") | BG27: =IFERROR(IF(OR(B27="",OFFSET(B27,-6,0)=""),"",(B27/OFFSET(B27,-6,0))^2-1),"") | BH27: =IFERROR(IF(OR(C27="",OFFSET(C27,-6,0)=""),"",(C27/OFFSET(C27,-6,0))^2-1),"") | BI27: =IFERROR(IF(OR(D27="",OFFSET(D27,-6,0)=""),"",(D27/OFFSET(D27,-6,0))^2-1),"") | BJ27: =IFERROR(IF(OR(E27="",OFFSET(E27,-6,0)=""),"",(E27/OFFSET(E27,-6,0))^2-1),"") | BK27: =IFERROR(IF(OR(F27="",OFFSET(F27,-6,0)=""),"",(F27/OFFSET(F27,-6,0))^2-1),"") | BL27: =IFERROR(IF(OR(G27="",OFFSET(G27,-6,0)=""),"",(G27/OFFSET(G27,-6,0))^2-1),"") | BM27: =IFERROR(IF(OR(H27="",OFFSET(H27,-6,0)=""),"",(H27/OFFSET(H27,-6,0))^2-1),"") | BN27: =IFERROR(IF(OR(I27="",OFFSET(I27,-6,0)=""),"",(I27/OFFSET(I27,-6,0))^2-1),"") | ... BS27: =IFERROR(IF(OR(N27="",OFFSET(N27,-6,0)=""),"",(N27/OFFSET(N27,-6,0))^2-1),"") | BX27: =IF('Macrobond Imports'!FG26="","",'Macrobond Imports'!FG26) | BY27: =IF('Macrobond Imports'!AI26="","",'Macrobond Imports'!AI26) | CA27: =IFERROR(IF(OR(BX27="",OFFSET(BX27,-12,0)=""),"",BX27/OFFSET(BX27,-12,0)-1),"") | CB27: =IFERROR(IF(OR(BY27="",OFFSET(BY27,-12,0)=""),"",BY27/OFFSET(BY27,-12,0)-1),"") | CC27: {=INDEX(MM_Headline,ROW()-5)} -> 0.0056745498 | CD27: {=INDEX(MM_Core,ROW()-5)} -> 0.0036812973 | CE27: {=INDEX(YY_Headline,ROW()-5)} -> 0.034182672 | CF27: {=INDEX(YY_Core,ROW()-5)} -> 0.038967691 | CG27: {=INDEX(Ann3_Headline,ROW()-5)} -> 0.060815114 | CH27: {=INDEX(Ann6_Headline,ROW()-5)} -> 0.05391996 | CK27: {=INDEX(ChartDates,ROW()-5)} -> 46054 | CL27: {=INDEX(UnprocEnergy_YY,ROW()-5)} -> 0.15644317 | CM27: {=INDEX(Transport_YY,ROW()-5)} -> 0.033305692 | DA27: Flooring Retailing | DB27: GK | DC27: =INDEX('Macrobond Imports'!GK:GK,MATCH(MAX('Macrobond Imports'!$A:$A),'Macrobond Imports'!$A:$A,0)) -> 153.994 | DD27: {=INDEX('Macrobond Imports'!GK:GK,MATCH(MAX('Macrobond Imports'!$A:$A),'Macrobond Imports'!$A:$A,0)-1)} -> 153.994 | DE27: =IFERROR(IF(OR(DC27="",DD27="",DC27=0,DD27=0),"",DC27/DD27-1),"") -> 0 | DF27: RT | DG27: =IF(DE27="","",DE27+ROW()*0.000000001) -> 2.7e-08
A28: =IF('Macrobond Imports'!A27="","",'Macrobond Imports'!A27) -> 17930 | B28: =IF('Macrobond Imports'!B27="","",'Macrobond Imports'!B27) | C28: =IF('Macrobond Imports'!C27="","",'Macrobond Imports'!C27) | D28: =IF('Macrobond Imports'!Z27="","",'Macrobond Imports'!Z27) | E28: =IF('Macrobond Imports'!BH27="","",'Macrobond Imports'!BH27) | F28: =IF('Macrobond Imports'!BJ27="","",'Macrobond Imports'!BJ27) | G28: =IF('Macrobond Imports'!BK27="","",'Macrobond Imports'!BK27) | H28: =IF('Macrobond Imports'!BL27="","",'Macrobond Imports'!BL27) | I28: =IF('Macrobond Imports'!BS27="","",'Macrobond Imports'!BS27) | J28: =IF('Macrobond Imports'!AA27="","",'Macrobond Imports'!AA27) | K28: =IF('Macrobond Imports'!DF27="","",'Macrobond Imports'!DF27) -> 24.8 | L28: =IF('Macrobond Imports'!EA27="","",'Macrobond Imports'!EA27) -> 30.9 | M28: =IF('Macrobond Imports'!FA27="","",'Macrobond Imports'!FA27) | N28: =IF('Macrobond Imports'!FC27="","",'Macrobond Imports'!FC27) | P28: =A28 -> 17930 | Q28: =IF(OR(B28="",N(B27)=0),"",B28/B27-1) | R28: =IF(OR(C28="",N(C27)=0),"",C28/C27-1) | S28: =IF(OR(D28="",N(D27)=0),"",D28/D27-1) | T28: =IF(OR(E28="",N(E27)=0),"",E28/E27-1) | U28: =IF(OR(F28="",N(F27)=0),"",F28/F27-1) | V28: =IF(OR(G28="",N(G27)=0),"",G28/G27-1) | W28: =IF(OR(H28="",N(H27)=0),"",H28/H27-1) | X28: =IF(OR(I28="",N(I27)=0),"",I28/I27-1) | ... AC28: =IF(OR(N28="",N(N27)=0),"",N28/N27-1) | AE28: =IFERROR(IF(OR(B28="",OFFSET(B28,-12,0)=""),"",B28/OFFSET(B28,-12,0)-1),"") | AF28: =IFERROR(IF(OR(C28="",OFFSET(C28,-12,0)=""),"",C28/OFFSET(C28,-12,0)-1),"") | AG28: =IFERROR(IF(OR(D28="",OFFSET(D28,-12,0)=""),"",D28/OFFSET(D28,-12,0)-1),"") | AH28: =IFERROR(IF(OR(E28="",OFFSET(E28,-12,0)=""),"",E28/OFFSET(E28,-12,0)-1),"") | AI28: =IFERROR(IF(OR(F28="",OFFSET(F28,-12,0)=""),"",F28/OFFSET(F28,-12,0)-1),"") | AJ28: =IFERROR(IF(OR(G28="",OFFSET(G28,-12,0)=""),"",G28/OFFSET(G28,-12,0)-1),"") | AK28: =IFERROR(IF(OR(H28="",OFFSET(H28,-12,0)=""),"",H28/OFFSET(H28,-12,0)-1),"") | AL28: =IFERROR(IF(OR(I28="",OFFSET(I28,-12,0)=""),"",I28/OFFSET(I28,-12,0)-1),"") | ... AQ28: =IFERROR(IF(OR(N28="",OFFSET(N28,-12,0)=""),"",N28/OFFSET(N28,-12,0)-1),"") | AS28: =IFERROR(IF(OR(B28="",OFFSET(B28,-3,0)=""),"",(B28/OFFSET(B28,-3,0))^4-1),"") | AT28: =IFERROR(IF(OR(C28="",OFFSET(C28,-3,0)=""),"",(C28/OFFSET(C28,-3,0))^4-1),"") | AU28: =IFERROR(IF(OR(D28="",OFFSET(D28,-3,0)=""),"",(D28/OFFSET(D28,-3,0))^4-1),"") | AV28: =IFERROR(IF(OR(E28="",OFFSET(E28,-3,0)=""),"",(E28/OFFSET(E28,-3,0))^4-1),"") | AW28: =IFERROR(IF(OR(F28="",OFFSET(F28,-3,0)=""),"",(F28/OFFSET(F28,-3,0))^4-1),"") | AX28: =IFERROR(IF(OR(G28="",OFFSET(G28,-3,0)=""),"",(G28/OFFSET(G28,-3,0))^4-1),"") | AY28: =IFERROR(IF(OR(H28="",OFFSET(H28,-3,0)=""),"",(H28/OFFSET(H28,-3,0))^4-1),"") | AZ28: =IFERROR(IF(OR(I28="",OFFSET(I28,-3,0)=""),"",(I28/OFFSET(I28,-3,0))^4-1),"") | ... BE28: =IFERROR(IF(OR(N28="",OFFSET(N28,-3,0)=""),"",(N28/OFFSET(N28,-3,0))^4-1),"") | BG28: =IFERROR(IF(OR(B28="",OFFSET(B28,-6,0)=""),"",(B28/OFFSET(B28,-6,0))^2-1),"") | BH28: =IFERROR(IF(OR(C28="",OFFSET(C28,-6,0)=""),"",(C28/OFFSET(C28,-6,0))^2-1),"") | BI28: =IFERROR(IF(OR(D28="",OFFSET(D28,-6,0)=""),"",(D28/OFFSET(D28,-6,0))^2-1),"") | BJ28: =IFERROR(IF(OR(E28="",OFFSET(E28,-6,0)=""),"",(E28/OFFSET(E28,-6,0))^2-1),"") | BK28: =IFERROR(IF(OR(F28="",OFFSET(F28,-6,0)=""),"",(F28/OFFSET(F28,-6,0))^2-1),"") | BL28: =IFERROR(IF(OR(G28="",OFFSET(G28,-6,0)=""),"",(G28/OFFSET(G28,-6,0))^2-1),"") | BM28: =IFERROR(IF(OR(H28="",OFFSET(H28,-6,0)=""),"",(H28/OFFSET(H28,-6,0))^2-1),"") | BN28: =IFERROR(IF(OR(I28="",OFFSET(I28,-6,0)=""),"",(I28/OFFSET(I28,-6,0))^2-1),"") | ... BS28: =IFERROR(IF(OR(N28="",OFFSET(N28,-6,0)=""),"",(N28/OFFSET(N28,-6,0))^2-1),"") | BX28: =IF('Macrobond Imports'!FG27="","",'Macrobond Imports'!FG27) | BY28: =IF('Macrobond Imports'!AI27="","",'Macrobond Imports'!AI27) | CA28: =IFERROR(IF(OR(BX28="",OFFSET(BX28,-12,0)=""),"",BX28/OFFSET(BX28,-12,0)-1),"") | CB28: =IFERROR(IF(OR(BY28="",OFFSET(BY28,-12,0)=""),"",BY28/OFFSET(BY28,-12,0)-1),"") | CC28: {=INDEX(MM_Headline,ROW()-5)} -> 0.0069928245 | CD28: {=INDEX(MM_Core,ROW()-5)} -> 0.0022742959 | CE28: {=INDEX(YY_Headline,ROW()-5)} -> 0.042666577 | CF28: {=INDEX(YY_Core,ROW()-5)} -> 0.039470724 | CG28: {=INDEX(Ann3_Headline,ROW()-5)} -> 0.075397425 | CH28: {=INDEX(Ann6_Headline,ROW()-5)} -> 0.055691453 | CK28: {=INDEX(ChartDates,ROW()-5)} -> 46082 | CL28: {=INDEX(UnprocEnergy_YY,ROW()-5)} -> 0.26688046 | CM28: {=INDEX(Transport_YY,ROW()-5)} -> 0.069773265 | DA28: Hardware & Building Materials Retailing | DB28: GL | DC28: =INDEX('Macrobond Imports'!GL:GL,MATCH(MAX('Macrobond Imports'!$A:$A),'Macrobond Imports'!$A:$A,0)) -> 194.602 | DD28: {=INDEX('Macrobond Imports'!GL:GL,MATCH(MAX('Macrobond Imports'!$A:$A),'Macrobond Imports'!$A:$A,0)-1)} -> 193.39 | DE28: =IFERROR(IF(OR(DC28="",DD28="",DC28=0,DD28=0),"",DC28/DD28-1),"") -> 0.0062671286 | DF28: RT | DG28: =IF(DE28="","",DE28+ROW()*0.000000001) -> 0.0062671566
A29: =IF('Macrobond Imports'!A28="","",'Macrobond Imports'!A28) -> 17958 | B29: =IF('Macrobond Imports'!B28="","",'Macrobond Imports'!B28) | C29: =IF('Macrobond Imports'!C28="","",'Macrobond Imports'!C28) | D29: =IF('Macrobond Imports'!Z28="","",'Macrobond Imports'!Z28) | E29: =IF('Macrobond Imports'!BH28="","",'Macrobond Imports'!BH28) | F29: =IF('Macrobond Imports'!BJ28="","",'Macrobond Imports'!BJ28) | G29: =IF('Macrobond Imports'!BK28="","",'Macrobond Imports'!BK28) | H29: =IF('Macrobond Imports'!BL28="","",'Macrobond Imports'!BL28) | I29: =IF('Macrobond Imports'!BS28="","",'Macrobond Imports'!BS28) | J29: =IF('Macrobond Imports'!AA28="","",'Macrobond Imports'!AA28) | K29: =IF('Macrobond Imports'!DF28="","",'Macrobond Imports'!DF28) -> 24.7 | L29: =IF('Macrobond Imports'!EA28="","",'Macrobond Imports'!EA28) -> 30.8 | M29: =IF('Macrobond Imports'!FA28="","",'Macrobond Imports'!FA28) | N29: =IF('Macrobond Imports'!FC28="","",'Macrobond Imports'!FC28) | P29: =A29 -> 17958 | Q29: =IF(OR(B29="",N(B28)=0),"",B29/B28-1) | R29: =IF(OR(C29="",N(C28)=0),"",C29/C28-1) | S29: =IF(OR(D29="",N(D28)=0),"",D29/D28-1) | T29: =IF(OR(E29="",N(E28)=0),"",E29/E28-1) | U29: =IF(OR(F29="",N(F28)=0),"",F29/F28-1) | V29: =IF(OR(G29="",N(G28)=0),"",G29/G28-1) | W29: =IF(OR(H29="",N(H28)=0),"",H29/H28-1) | X29: =IF(OR(I29="",N(I28)=0),"",I29/I28-1) | ... AC29: =IF(OR(N29="",N(N28)=0),"",N29/N28-1) | AE29: =IFERROR(IF(OR(B29="",OFFSET(B29,-12,0)=""),"",B29/OFFSET(B29,-12,0)-1),"") | AF29: =IFERROR(IF(OR(C29="",OFFSET(C29,-12,0)=""),"",C29/OFFSET(C29,-12,0)-1),"") | AG29: =IFERROR(IF(OR(D29="",OFFSET(D29,-12,0)=""),"",D29/OFFSET(D29,-12,0)-1),"") | AH29: =IFERROR(IF(OR(E29="",OFFSET(E29,-12,0)=""),"",E29/OFFSET(E29,-12,0)-1),"") | AI29: =IFERROR(IF(OR(F29="",OFFSET(F29,-12,0)=""),"",F29/OFFSET(F29,-12,0)-1),"") | AJ29: =IFERROR(IF(OR(G29="",OFFSET(G29,-12,0)=""),"",G29/OFFSET(G29,-12,0)-1),"") | AK29: =IFERROR(IF(OR(H29="",OFFSET(H29,-12,0)=""),"",H29/OFFSET(H29,-12,0)-1),"") | AL29: =IFERROR(IF(OR(I29="",OFFSET(I29,-12,0)=""),"",I29/OFFSET(I29,-12,0)-1),"") | ... AQ29: =IFERROR(IF(OR(N29="",OFFSET(N29,-12,0)=""),"",N29/OFFSET(N29,-12,0)-1),"") | AS29: =IFERROR(IF(OR(B29="",OFFSET(B29,-3,0)=""),"",(B29/OFFSET(B29,-3,0))^4-1),"") | AT29: =IFERROR(IF(OR(C29="",OFFSET(C29,-3,0)=""),"",(C29/OFFSET(C29,-3,0))^4-1),"") | AU29: =IFERROR(IF(OR(D29="",OFFSET(D29,-3,0)=""),"",(D29/OFFSET(D29,-3,0))^4-1),"") | AV29: =IFERROR(IF(OR(E29="",OFFSET(E29,-3,0)=""),"",(E29/OFFSET(E29,-3,0))^4-1),"") | AW29: =IFERROR(IF(OR(F29="",OFFSET(F29,-3,0)=""),"",(F29/OFFSET(F29,-3,0))^4-1),"") | AX29: =IFERROR(IF(OR(G29="",OFFSET(G29,-3,0)=""),"",(G29/OFFSET(G29,-3,0))^4-1),"") | AY29: =IFERROR(IF(OR(H29="",OFFSET(H29,-3,0)=""),"",(H29/OFFSET(H29,-3,0))^4-1),"") | AZ29: =IFERROR(IF(OR(I29="",OFFSET(I29,-3,0)=""),"",(I29/OFFSET(I29,-3,0))^4-1),"") | ... BE29: =IFERROR(IF(OR(N29="",OFFSET(N29,-3,0)=""),"",(N29/OFFSET(N29,-3,0))^4-1),"") | BG29: =IFERROR(IF(OR(B29="",OFFSET(B29,-6,0)=""),"",(B29/OFFSET(B29,-6,0))^2-1),"") | BH29: =IFERROR(IF(OR(C29="",OFFSET(C29,-6,0)=""),"",(C29/OFFSET(C29,-6,0))^2-1),"") | BI29: =IFERROR(IF(OR(D29="",OFFSET(D29,-6,0)=""),"",(D29/OFFSET(D29,-6,0))^2-1),"") | BJ29: =IFERROR(IF(OR(E29="",OFFSET(E29,-6,0)=""),"",(E29/OFFSET(E29,-6,0))^2-1),"") | BK29: =IFERROR(IF(OR(F29="",OFFSET(F29,-6,0)=""),"",(F29/OFFSET(F29,-6,0))^2-1),"") | BL29: =IFERROR(IF(OR(G29="",OFFSET(G29,-6,0)=""),"",(G29/OFFSET(G29,-6,0))^2-1),"") | BM29: =IFERROR(IF(OR(H29="",OFFSET(H29,-6,0)=""),"",(H29/OFFSET(H29,-6,0))^2-1),"") | BN29: =IFERROR(IF(OR(I29="",OFFSET(I29,-6,0)=""),"",(I29/OFFSET(I29,-6,0))^2-1),"") | ... BS29: =IFERROR(IF(OR(N29="",OFFSET(N29,-6,0)=""),"",(N29/OFFSET(N29,-6,0))^2-1),"") | BX29: =IF('Macrobond Imports'!FG28="","",'Macrobond Imports'!FG28) | BY29: =IF('Macrobond Imports'!AI28="","",'Macrobond Imports'!AI28) | CA29: =IFERROR(IF(OR(BX29="",OFFSET(BX29,-12,0)=""),"",BX29/OFFSET(BX29,-12,0)-1),"") | CB29: =IFERROR(IF(OR(BY29="",OFFSET(BY29,-12,0)=""),"",BY29/OFFSET(BY29,-12,0)-1),"") | CC29: {=INDEX(MM_Headline,ROW()-5)} -> 0.013758972 | CD29: {=INDEX(MM_Core,ROW()-5)} -> 0.010329156 | CE29: {=INDEX(YY_Headline,ROW()-5)} -> 0.059876062 | CF29: {=INDEX(YY_Core,ROW()-5)} -> 0.05240291 | CG29: {=INDEX(Ann3_Headline,ROW()-5)} -> 0.110898 | CH29: {=INDEX(Ann6_Headline,ROW()-5)} -> 0.082145374 | CK29: {=INDEX(ChartDates,ROW()-5)} -> 46113 | CL29: {=INDEX(UnprocEnergy_YY,ROW()-5)} -> 0.48862085 | CM29: {=INDEX(Transport_YY,ROW()-5)} -> 0.12251211 | DA29: Major Appliance Retailing | DB29: GM | DC29: =INDEX('Macrobond Imports'!GM:GM,MATCH(MAX('Macrobond Imports'!$A:$A),'Macrobond Imports'!$A:$A,0)) -> 138.799 | DD29: {=INDEX('Macrobond Imports'!GM:GM,MATCH(MAX('Macrobond Imports'!$A:$A),'Macrobond Imports'!$A:$A,0)-1)} -> 138.799 | DE29: =IFERROR(IF(OR(DC29="",DD29="",DC29=0,DD29=0),"",DC29/DD29-1),"") -> 0 | DF29: RT | DG29: =IF(DE29="","",DE29+ROW()*0.000000001) -> 2.9e-08
A30: =IF('Macrobond Imports'!A29="","",'Macrobond Imports'!A29) -> 17989 | B30: =IF('Macrobond Imports'!B29="","",'Macrobond Imports'!B29) | C30: =IF('Macrobond Imports'!C29="","",'Macrobond Imports'!C29) | D30: =IF('Macrobond Imports'!Z29="","",'Macrobond Imports'!Z29) | E30: =IF('Macrobond Imports'!BH29="","",'Macrobond Imports'!BH29) | F30: =IF('Macrobond Imports'!BJ29="","",'Macrobond Imports'!BJ29) | G30: =IF('Macrobond Imports'!BK29="","",'Macrobond Imports'!BK29) | H30: =IF('Macrobond Imports'!BL29="","",'Macrobond Imports'!BL29) | I30: =IF('Macrobond Imports'!BS29="","",'Macrobond Imports'!BS29) | J30: =IF('Macrobond Imports'!AA29="","",'Macrobond Imports'!AA29) | K30: =IF('Macrobond Imports'!DF29="","",'Macrobond Imports'!DF29) -> 24.5 | L30: =IF('Macrobond Imports'!EA29="","",'Macrobond Imports'!EA29) -> 30.2 | M30: =IF('Macrobond Imports'!FA29="","",'Macrobond Imports'!FA29) | N30: =IF('Macrobond Imports'!FC29="","",'Macrobond Imports'!FC29) | P30: =A30 -> 17989 | Q30: =IF(OR(B30="",N(B29)=0),"",B30/B29-1) | R30: =IF(OR(C30="",N(C29)=0),"",C30/C29-1) | S30: =IF(OR(D30="",N(D29)=0),"",D30/D29-1) | T30: =IF(OR(E30="",N(E29)=0),"",E30/E29-1) | U30: =IF(OR(F30="",N(F29)=0),"",F30/F29-1) | V30: =IF(OR(G30="",N(G29)=0),"",G30/G29-1) | W30: =IF(OR(H30="",N(H29)=0),"",H30/H29-1) | X30: =IF(OR(I30="",N(I29)=0),"",I30/I29-1) | ... AC30: =IF(OR(N30="",N(N29)=0),"",N30/N29-1) | AE30: =IFERROR(IF(OR(B30="",OFFSET(B30,-12,0)=""),"",B30/OFFSET(B30,-12,0)-1),"") | AF30: =IFERROR(IF(OR(C30="",OFFSET(C30,-12,0)=""),"",C30/OFFSET(C30,-12,0)-1),"") | AG30: =IFERROR(IF(OR(D30="",OFFSET(D30,-12,0)=""),"",D30/OFFSET(D30,-12,0)-1),"") | AH30: =IFERROR(IF(OR(E30="",OFFSET(E30,-12,0)=""),"",E30/OFFSET(E30,-12,0)-1),"") | AI30: =IFERROR(IF(OR(F30="",OFFSET(F30,-12,0)=""),"",F30/OFFSET(F30,-12,0)-1),"") | AJ30: =IFERROR(IF(OR(G30="",OFFSET(G30,-12,0)=""),"",G30/OFFSET(G30,-12,0)-1),"") | AK30: =IFERROR(IF(OR(H30="",OFFSET(H30,-12,0)=""),"",H30/OFFSET(H30,-12,0)-1),"") | AL30: =IFERROR(IF(OR(I30="",OFFSET(I30,-12,0)=""),"",I30/OFFSET(I30,-12,0)-1),"") | ... AQ30: =IFERROR(IF(OR(N30="",OFFSET(N30,-12,0)=""),"",N30/OFFSET(N30,-12,0)-1),"") | AS30: =IFERROR(IF(OR(B30="",OFFSET(B30,-3,0)=""),"",(B30/OFFSET(B30,-3,0))^4-1),"") | AT30: =IFERROR(IF(OR(C30="",OFFSET(C30,-3,0)=""),"",(C30/OFFSET(C30,-3,0))^4-1),"") | AU30: =IFERROR(IF(OR(D30="",OFFSET(D30,-3,0)=""),"",(D30/OFFSET(D30,-3,0))^4-1),"") | AV30: =IFERROR(IF(OR(E30="",OFFSET(E30,-3,0)=""),"",(E30/OFFSET(E30,-3,0))^4-1),"") | AW30: =IFERROR(IF(OR(F30="",OFFSET(F30,-3,0)=""),"",(F30/OFFSET(F30,-3,0))^4-1),"") | AX30: =IFERROR(IF(OR(G30="",OFFSET(G30,-3,0)=""),"",(G30/OFFSET(G30,-3,0))^4-1),"") | AY30: =IFERROR(IF(OR(H30="",OFFSET(H30,-3,0)=""),"",(H30/OFFSET(H30,-3,0))^4-1),"") | AZ30: =IFERROR(IF(OR(I30="",OFFSET(I30,-3,0)=""),"",(I30/OFFSET(I30,-3,0))^4-1),"") | ... BE30: =IFERROR(IF(OR(N30="",OFFSET(N30,-3,0)=""),"",(N30/OFFSET(N30,-3,0))^4-1),"") | BG30: =IFERROR(IF(OR(B30="",OFFSET(B30,-6,0)=""),"",(B30/OFFSET(B30,-6,0))^2-1),"") | BH30: =IFERROR(IF(OR(C30="",OFFSET(C30,-6,0)=""),"",(C30/OFFSET(C30,-6,0))^2-1),"") | BI30: =IFERROR(IF(OR(D30="",OFFSET(D30,-6,0)=""),"",(D30/OFFSET(D30,-6,0))^2-1),"") | BJ30: =IFERROR(IF(OR(E30="",OFFSET(E30,-6,0)=""),"",(E30/OFFSET(E30,-6,0))^2-1),"") | BK30: =IFERROR(IF(OR(F30="",OFFSET(F30,-6,0)=""),"",(F30/OFFSET(F30,-6,0))^2-1),"") | BL30: =IFERROR(IF(OR(G30="",OFFSET(G30,-6,0)=""),"",(G30/OFFSET(G30,-6,0))^2-1),"") | BM30: =IFERROR(IF(OR(H30="",OFFSET(H30,-6,0)=""),"",(H30/OFFSET(H30,-6,0))^2-1),"") | BN30: =IFERROR(IF(OR(I30="",OFFSET(I30,-6,0)=""),"",(I30/OFFSET(I30,-6,0))^2-1),"") | ... BS30: =IFERROR(IF(OR(N30="",OFFSET(N30,-6,0)=""),"",(N30/OFFSET(N30,-6,0))^2-1),"") | BX30: =IF('Macrobond Imports'!FG29="","",'Macrobond Imports'!FG29) | BY30: =IF('Macrobond Imports'!AI29="","",'Macrobond Imports'!AI29) | CA30: =IFERROR(IF(OR(BX30="",OFFSET(BX30,-12,0)=""),"",BX30/OFFSET(BX30,-12,0)-1),"") | CB30: =IFERROR(IF(OR(BY30="",OFFSET(BY30,-12,0)=""),"",BY30/OFFSET(BY30,-12,0)-1),"") | DA30: Fuels & Lubricants Retailing | DB30: GN | DC30: =INDEX('Macrobond Imports'!GN:GN,MATCH(MAX('Macrobond Imports'!$A:$A),'Macrobond Imports'!$A:$A,0)) -> 425.958 | DD30: {=INDEX('Macrobond Imports'!GN:GN,MATCH(MAX('Macrobond Imports'!$A:$A),'Macrobond Imports'!$A:$A,0)-1)} -> 336.636 | DE30: =IFERROR(IF(OR(DC30="",DD30="",DC30=0,DD30=0),"",DC30/DD30-1),"") -> 0.26533704 | DF30: RT | DG30: =IF(DE30="","",DE30+ROW()*0.000000001) -> 0.26533707
A31: =IF('Macrobond Imports'!A30="","",'Macrobond Imports'!A30) -> 18019 | B31: =IF('Macrobond Imports'!B30="","",'Macrobond Imports'!B30) | C31: =IF('Macrobond Imports'!C30="","",'Macrobond Imports'!C30) | D31: =IF('Macrobond Imports'!Z30="","",'Macrobond Imports'!Z30) | E31: =IF('Macrobond Imports'!BH30="","",'Macrobond Imports'!BH30) | F31: =IF('Macrobond Imports'!BJ30="","",'Macrobond Imports'!BJ30) | G31: =IF('Macrobond Imports'!BK30="","",'Macrobond Imports'!BK30) | H31: =IF('Macrobond Imports'!BL30="","",'Macrobond Imports'!BL30) | I31: =IF('Macrobond Imports'!BS30="","",'Macrobond Imports'!BS30) | J31: =IF('Macrobond Imports'!AA30="","",'Macrobond Imports'!AA30) | K31: =IF('Macrobond Imports'!DF30="","",'Macrobond Imports'!DF30) -> 24.3 | L31: =IF('Macrobond Imports'!EA30="","",'Macrobond Imports'!EA30) -> 30.1 | M31: =IF('Macrobond Imports'!FA30="","",'Macrobond Imports'!FA30) | N31: =IF('Macrobond Imports'!FC30="","",'Macrobond Imports'!FC30) | P31: =A31 -> 18019 | Q31: =IF(OR(B31="",N(B30)=0),"",B31/B30-1) | R31: =IF(OR(C31="",N(C30)=0),"",C31/C30-1) | S31: =IF(OR(D31="",N(D30)=0),"",D31/D30-1) | T31: =IF(OR(E31="",N(E30)=0),"",E31/E30-1) | U31: =IF(OR(F31="",N(F30)=0),"",F31/F30-1) | V31: =IF(OR(G31="",N(G30)=0),"",G31/G30-1) | W31: =IF(OR(H31="",N(H30)=0),"",H31/H30-1) | X31: =IF(OR(I31="",N(I30)=0),"",I31/I30-1) | ... AC31: =IF(OR(N31="",N(N30)=0),"",N31/N30-1) | AE31: =IFERROR(IF(OR(B31="",OFFSET(B31,-12,0)=""),"",B31/OFFSET(B31,-12,0)-1),"") | AF31: =IFERROR(IF(OR(C31="",OFFSET(C31,-12,0)=""),"",C31/OFFSET(C31,-12,0)-1),"") | AG31: =IFERROR(IF(OR(D31="",OFFSET(D31,-12,0)=""),"",D31/OFFSET(D31,-12,0)-1),"") | AH31: =IFERROR(IF(OR(E31="",OFFSET(E31,-12,0)=""),"",E31/OFFSET(E31,-12,0)-1),"") | AI31: =IFERROR(IF(OR(F31="",OFFSET(F31,-12,0)=""),"",F31/OFFSET(F31,-12,0)-1),"") | AJ31: =IFERROR(IF(OR(G31="",OFFSET(G31,-12,0)=""),"",G31/OFFSET(G31,-12,0)-1),"") | AK31: =IFERROR(IF(OR(H31="",OFFSET(H31,-12,0)=""),"",H31/OFFSET(H31,-12,0)-1),"") | AL31: =IFERROR(IF(OR(I31="",OFFSET(I31,-12,0)=""),"",I31/OFFSET(I31,-12,0)-1),"") | ... AQ31: =IFERROR(IF(OR(N31="",OFFSET(N31,-12,0)=""),"",N31/OFFSET(N31,-12,0)-1),"") | AS31: =IFERROR(IF(OR(B31="",OFFSET(B31,-3,0)=""),"",(B31/OFFSET(B31,-3,0))^4-1),"") | AT31: =IFERROR(IF(OR(C31="",OFFSET(C31,-3,0)=""),"",(C31/OFFSET(C31,-3,0))^4-1),"") | AU31: =IFERROR(IF(OR(D31="",OFFSET(D31,-3,0)=""),"",(D31/OFFSET(D31,-3,0))^4-1),"") | AV31: =IFERROR(IF(OR(E31="",OFFSET(E31,-3,0)=""),"",(E31/OFFSET(E31,-3,0))^4-1),"") | AW31: =IFERROR(IF(OR(F31="",OFFSET(F31,-3,0)=""),"",(F31/OFFSET(F31,-3,0))^4-1),"") | AX31: =IFERROR(IF(OR(G31="",OFFSET(G31,-3,0)=""),"",(G31/OFFSET(G31,-3,0))^4-1),"") | AY31: =IFERROR(IF(OR(H31="",OFFSET(H31,-3,0)=""),"",(H31/OFFSET(H31,-3,0))^4-1),"") | AZ31: =IFERROR(IF(OR(I31="",OFFSET(I31,-3,0)=""),"",(I31/OFFSET(I31,-3,0))^4-1),"") | ... BE31: =IFERROR(IF(OR(N31="",OFFSET(N31,-3,0)=""),"",(N31/OFFSET(N31,-3,0))^4-1),"") | BG31: =IFERROR(IF(OR(B31="",OFFSET(B31,-6,0)=""),"",(B31/OFFSET(B31,-6,0))^2-1),"") | BH31: =IFERROR(IF(OR(C31="",OFFSET(C31,-6,0)=""),"",(C31/OFFSET(C31,-6,0))^2-1),"") | BI31: =IFERROR(IF(OR(D31="",OFFSET(D31,-6,0)=""),"",(D31/OFFSET(D31,-6,0))^2-1),"") | BJ31: =IFERROR(IF(OR(E31="",OFFSET(E31,-6,0)=""),"",(E31/OFFSET(E31,-6,0))^2-1),"") | BK31: =IFERROR(IF(OR(F31="",OFFSET(F31,-6,0)=""),"",(F31/OFFSET(F31,-6,0))^2-1),"") | BL31: =IFERROR(IF(OR(G31="",OFFSET(G31,-6,0)=""),"",(G31/OFFSET(G31,-6,0))^2-1),"") | BM31: =IFERROR(IF(OR(H31="",OFFSET(H31,-6,0)=""),"",(H31/OFFSET(H31,-6,0))^2-1),"") | BN31: =IFERROR(IF(OR(I31="",OFFSET(I31,-6,0)=""),"",(I31/OFFSET(I31,-6,0))^2-1),"") | ... BS31: =IFERROR(IF(OR(N31="",OFFSET(N31,-6,0)=""),"",(N31/OFFSET(N31,-6,0))^2-1),"") | BX31: =IF('Macrobond Imports'!FG30="","",'Macrobond Imports'!FG30) | BY31: =IF('Macrobond Imports'!AI30="","",'Macrobond Imports'!AI30) | CA31: =IFERROR(IF(OR(BX31="",OFFSET(BX31,-12,0)=""),"",BX31/OFFSET(BX31,-12,0)-1),"") | CB31: =IFERROR(IF(OR(BY31="",OFFSET(BY31,-12,0)=""),"",BY31/OFFSET(BY31,-12,0)-1),"") | DA31: Cleaning Supplies & Paper Retailing | DB31: GO | DC31: =INDEX('Macrobond Imports'!GO:GO,MATCH(MAX('Macrobond Imports'!$A:$A),'Macrobond Imports'!$A:$A,0)) -> 234.248 | DD31: {=INDEX('Macrobond Imports'!GO:GO,MATCH(MAX('Macrobond Imports'!$A:$A),'Macrobond Imports'!$A:$A,0)-1)} -> 232.735 | DE31: =IFERROR(IF(OR(DC31="",DD31="",DC31=0,DD31=0),"",DC31/DD31-1),"") -> 0.006500956 | DF31: RT | DG31: =IF(DE31="","",DE31+ROW()*0.000000001) -> 0.006500987
A32: =IF('Macrobond Imports'!A31="","",'Macrobond Imports'!A31) -> 18050 | B32: =IF('Macrobond Imports'!B31="","",'Macrobond Imports'!B31) | C32: =IF('Macrobond Imports'!C31="","",'Macrobond Imports'!C31) | D32: =IF('Macrobond Imports'!Z31="","",'Macrobond Imports'!Z31) | E32: =IF('Macrobond Imports'!BH31="","",'Macrobond Imports'!BH31) | F32: =IF('Macrobond Imports'!BJ31="","",'Macrobond Imports'!BJ31) | G32: =IF('Macrobond Imports'!BK31="","",'Macrobond Imports'!BK31) | H32: =IF('Macrobond Imports'!BL31="","",'Macrobond Imports'!BL31) | I32: =IF('Macrobond Imports'!BS31="","",'Macrobond Imports'!BS31) | J32: =IF('Macrobond Imports'!AA31="","",'Macrobond Imports'!AA31) | K32: =IF('Macrobond Imports'!DF31="","",'Macrobond Imports'!DF31) -> 24.1 | L32: =IF('Macrobond Imports'!EA31="","",'Macrobond Imports'!EA31) -> 29.7 | M32: =IF('Macrobond Imports'!FA31="","",'Macrobond Imports'!FA31) | N32: =IF('Macrobond Imports'!FC31="","",'Macrobond Imports'!FC31) | P32: =A32 -> 18050 | Q32: =IF(OR(B32="",N(B31)=0),"",B32/B31-1) | R32: =IF(OR(C32="",N(C31)=0),"",C32/C31-1) | S32: =IF(OR(D32="",N(D31)=0),"",D32/D31-1) | T32: =IF(OR(E32="",N(E31)=0),"",E32/E31-1) | U32: =IF(OR(F32="",N(F31)=0),"",F32/F31-1) | V32: =IF(OR(G32="",N(G31)=0),"",G32/G31-1) | W32: =IF(OR(H32="",N(H31)=0),"",H32/H31-1) | X32: =IF(OR(I32="",N(I31)=0),"",I32/I31-1) | ... AC32: =IF(OR(N32="",N(N31)=0),"",N32/N31-1) | AE32: =IFERROR(IF(OR(B32="",OFFSET(B32,-12,0)=""),"",B32/OFFSET(B32,-12,0)-1),"") | AF32: =IFERROR(IF(OR(C32="",OFFSET(C32,-12,0)=""),"",C32/OFFSET(C32,-12,0)-1),"") | AG32: =IFERROR(IF(OR(D32="",OFFSET(D32,-12,0)=""),"",D32/OFFSET(D32,-12,0)-1),"") | AH32: =IFERROR(IF(OR(E32="",OFFSET(E32,-12,0)=""),"",E32/OFFSET(E32,-12,0)-1),"") | AI32: =IFERROR(IF(OR(F32="",OFFSET(F32,-12,0)=""),"",F32/OFFSET(F32,-12,0)-1),"") | AJ32: =IFERROR(IF(OR(G32="",OFFSET(G32,-12,0)=""),"",G32/OFFSET(G32,-12,0)-1),"") | AK32: =IFERROR(IF(OR(H32="",OFFSET(H32,-12,0)=""),"",H32/OFFSET(H32,-12,0)-1),"") | AL32: =IFERROR(IF(OR(I32="",OFFSET(I32,-12,0)=""),"",I32/OFFSET(I32,-12,0)-1),"") | ... AQ32: =IFERROR(IF(OR(N32="",OFFSET(N32,-12,0)=""),"",N32/OFFSET(N32,-12,0)-1),"") | AS32: =IFERROR(IF(OR(B32="",OFFSET(B32,-3,0)=""),"",(B32/OFFSET(B32,-3,0))^4-1),"") | AT32: =IFERROR(IF(OR(C32="",OFFSET(C32,-3,0)=""),"",(C32/OFFSET(C32,-3,0))^4-1),"") | AU32: =IFERROR(IF(OR(D32="",OFFSET(D32,-3,0)=""),"",(D32/OFFSET(D32,-3,0))^4-1),"") | AV32: =IFERROR(IF(OR(E32="",OFFSET(E32,-3,0)=""),"",(E32/OFFSET(E32,-3,0))^4-1),"") | AW32: =IFERROR(IF(OR(F32="",OFFSET(F32,-3,0)=""),"",(F32/OFFSET(F32,-3,0))^4-1),"") | AX32: =IFERROR(IF(OR(G32="",OFFSET(G32,-3,0)=""),"",(G32/OFFSET(G32,-3,0))^4-1),"") | AY32: =IFERROR(IF(OR(H32="",OFFSET(H32,-3,0)=""),"",(H32/OFFSET(H32,-3,0))^4-1),"") | AZ32: =IFERROR(IF(OR(I32="",OFFSET(I32,-3,0)=""),"",(I32/OFFSET(I32,-3,0))^4-1),"") | ... BE32: =IFERROR(IF(OR(N32="",OFFSET(N32,-3,0)=""),"",(N32/OFFSET(N32,-3,0))^4-1),"") | BG32: =IFERROR(IF(OR(B32="",OFFSET(B32,-6,0)=""),"",(B32/OFFSET(B32,-6,0))^2-1),"") | BH32: =IFERROR(IF(OR(C32="",OFFSET(C32,-6,0)=""),"",(C32/OFFSET(C32,-6,0))^2-1),"") | BI32: =IFERROR(IF(OR(D32="",OFFSET(D32,-6,0)=""),"",(D32/OFFSET(D32,-6,0))^2-1),"") | BJ32: =IFERROR(IF(OR(E32="",OFFSET(E32,-6,0)=""),"",(E32/OFFSET(E32,-6,0))^2-1),"") | BK32: =IFERROR(IF(OR(F32="",OFFSET(F32,-6,0)=""),"",(F32/OFFSET(F32,-6,0))^2-1),"") | BL32: =IFERROR(IF(OR(G32="",OFFSET(G32,-6,0)=""),"",(G32/OFFSET(G32,-6,0))^2-1),"") | BM32: =IFERROR(IF(OR(H32="",OFFSET(H32,-6,0)=""),"",(H32/OFFSET(H32,-6,0))^2-1),"") | BN32: =IFERROR(IF(OR(I32="",OFFSET(I32,-6,0)=""),"",(I32/OFFSET(I32,-6,0))^2-1),"") | ... BS32: =IFERROR(IF(OR(N32="",OFFSET(N32,-6,0)=""),"",(N32/OFFSET(N32,-6,0))^2-1),"") | BX32: =IF('Macrobond Imports'!FG31="","",'Macrobond Imports'!FG31) | BY32: =IF('Macrobond Imports'!AI31="","",'Macrobond Imports'!AI31) | CA32: =IFERROR(IF(OR(BX32="",OFFSET(BX32,-12,0)=""),"",BX32/OFFSET(BX32,-12,0)-1),"") | CB32: =IFERROR(IF(OR(BY32="",OFFSET(BY32,-12,0)=""),"",BY32/OFFSET(BY32,-12,0)-1),"") | DA32: Book Retailing | DB32: GP | DC32: =INDEX('Macrobond Imports'!GP:GP,MATCH(MAX('Macrobond Imports'!$A:$A),'Macrobond Imports'!$A:$A,0)) -> 151.368 | DD32: {=INDEX('Macrobond Imports'!GP:GP,MATCH(MAX('Macrobond Imports'!$A:$A),'Macrobond Imports'!$A:$A,0)-1)} -> 154.894 | DE32: =IF(OR(DC32="",DD32=""),"",DC32/DD32-1) -> -0.022763955 | DF32: RT
A33: =IF('Macrobond Imports'!A32="","",'Macrobond Imports'!A32) -> 18080 | B33: =IF('Macrobond Imports'!B32="","",'Macrobond Imports'!B32) | C33: =IF('Macrobond Imports'!C32="","",'Macrobond Imports'!C32) | D33: =IF('Macrobond Imports'!Z32="","",'Macrobond Imports'!Z32) | E33: =IF('Macrobond Imports'!BH32="","",'Macrobond Imports'!BH32) | F33: =IF('Macrobond Imports'!BJ32="","",'Macrobond Imports'!BJ32) | G33: =IF('Macrobond Imports'!BK32="","",'Macrobond Imports'!BK32) | H33: =IF('Macrobond Imports'!BL32="","",'Macrobond Imports'!BL32) | I33: =IF('Macrobond Imports'!BS32="","",'Macrobond Imports'!BS32) | J33: =IF('Macrobond Imports'!AA32="","",'Macrobond Imports'!AA32) | K33: =IF('Macrobond Imports'!DF32="","",'Macrobond Imports'!DF32) -> 24.1 | L33: =IF('Macrobond Imports'!EA32="","",'Macrobond Imports'!EA32) -> 29.2 | M33: =IF('Macrobond Imports'!FA32="","",'Macrobond Imports'!FA32) | N33: =IF('Macrobond Imports'!FC32="","",'Macrobond Imports'!FC32) | P33: =A33 -> 18080 | Q33: =IF(OR(B33="",N(B32)=0),"",B33/B32-1) | R33: =IF(OR(C33="",N(C32)=0),"",C33/C32-1) | S33: =IF(OR(D33="",N(D32)=0),"",D33/D32-1) | T33: =IF(OR(E33="",N(E32)=0),"",E33/E32-1) | U33: =IF(OR(F33="",N(F32)=0),"",F33/F32-1) | V33: =IF(OR(G33="",N(G32)=0),"",G33/G32-1) | W33: =IF(OR(H33="",N(H32)=0),"",H33/H32-1) | X33: =IF(OR(I33="",N(I32)=0),"",I33/I32-1) | ... AC33: =IF(OR(N33="",N(N32)=0),"",N33/N32-1) | AE33: =IFERROR(IF(OR(B33="",OFFSET(B33,-12,0)=""),"",B33/OFFSET(B33,-12,0)-1),"") | AF33: =IFERROR(IF(OR(C33="",OFFSET(C33,-12,0)=""),"",C33/OFFSET(C33,-12,0)-1),"") | AG33: =IFERROR(IF(OR(D33="",OFFSET(D33,-12,0)=""),"",D33/OFFSET(D33,-12,0)-1),"") | AH33: =IFERROR(IF(OR(E33="",OFFSET(E33,-12,0)=""),"",E33/OFFSET(E33,-12,0)-1),"") | AI33: =IFERROR(IF(OR(F33="",OFFSET(F33,-12,0)=""),"",F33/OFFSET(F33,-12,0)-1),"") | AJ33: =IFERROR(IF(OR(G33="",OFFSET(G33,-12,0)=""),"",G33/OFFSET(G33,-12,0)-1),"") | AK33: =IFERROR(IF(OR(H33="",OFFSET(H33,-12,0)=""),"",H33/OFFSET(H33,-12,0)-1),"") | AL33: =IFERROR(IF(OR(I33="",OFFSET(I33,-12,0)=""),"",I33/OFFSET(I33,-12,0)-1),"") | ... AQ33: =IFERROR(IF(OR(N33="",OFFSET(N33,-12,0)=""),"",N33/OFFSET(N33,-12,0)-1),"") | AS33: =IFERROR(IF(OR(B33="",OFFSET(B33,-3,0)=""),"",(B33/OFFSET(B33,-3,0))^4-1),"") | AT33: =IFERROR(IF(OR(C33="",OFFSET(C33,-3,0)=""),"",(C33/OFFSET(C33,-3,0))^4-1),"") | AU33: =IFERROR(IF(OR(D33="",OFFSET(D33,-3,0)=""),"",(D33/OFFSET(D33,-3,0))^4-1),"") | AV33: =IFERROR(IF(OR(E33="",OFFSET(E33,-3,0)=""),"",(E33/OFFSET(E33,-3,0))^4-1),"") | AW33: =IFERROR(IF(OR(F33="",OFFSET(F33,-3,0)=""),"",(F33/OFFSET(F33,-3,0))^4-1),"") | AX33: =IFERROR(IF(OR(G33="",OFFSET(G33,-3,0)=""),"",(G33/OFFSET(G33,-3,0))^4-1),"") | AY33: =IFERROR(IF(OR(H33="",OFFSET(H33,-3,0)=""),"",(H33/OFFSET(H33,-3,0))^4-1),"") | AZ33: =IFERROR(IF(OR(I33="",OFFSET(I33,-3,0)=""),"",(I33/OFFSET(I33,-3,0))^4-1),"") | ... BE33: =IFERROR(IF(OR(N33="",OFFSET(N33,-3,0)=""),"",(N33/OFFSET(N33,-3,0))^4-1),"") | BG33: =IFERROR(IF(OR(B33="",OFFSET(B33,-6,0)=""),"",(B33/OFFSET(B33,-6,0))^2-1),"") | BH33: =IFERROR(IF(OR(C33="",OFFSET(C33,-6,0)=""),"",(C33/OFFSET(C33,-6,0))^2-1),"") | BI33: =IFERROR(IF(OR(D33="",OFFSET(D33,-6,0)=""),"",(D33/OFFSET(D33,-6,0))^2-1),"") | BJ33: =IFERROR(IF(OR(E33="",OFFSET(E33,-6,0)=""),"",(E33/OFFSET(E33,-6,0))^2-1),"") | BK33: =IFERROR(IF(OR(F33="",OFFSET(F33,-6,0)=""),"",(F33/OFFSET(F33,-6,0))^2-1),"") | BL33: =IFERROR(IF(OR(G33="",OFFSET(G33,-6,0)=""),"",(G33/OFFSET(G33,-6,0))^2-1),"") | BM33: =IFERROR(IF(OR(H33="",OFFSET(H33,-6,0)=""),"",(H33/OFFSET(H33,-6,0))^2-1),"") | BN33: =IFERROR(IF(OR(I33="",OFFSET(I33,-6,0)=""),"",(I33/OFFSET(I33,-6,0))^2-1),"") | ... BS33: =IFERROR(IF(OR(N33="",OFFSET(N33,-6,0)=""),"",(N33/OFFSET(N33,-6,0))^2-1),"") | BX33: =IF('Macrobond Imports'!FG32="","",'Macrobond Imports'!FG32) | BY33: =IF('Macrobond Imports'!AI32="","",'Macrobond Imports'!AI32) | CA33: =IFERROR(IF(OR(BX33="",OFFSET(BX33,-12,0)=""),"",BX33/OFFSET(BX33,-12,0)-1),"") | CB33: =IFERROR(IF(OR(BY33="",OFFSET(BY33,-12,0)=""),"",BY33/OFFSET(BY33,-12,0)-1),"")
A34: =IF('Macrobond Imports'!A33="","",'Macrobond Imports'!A33) -> 18111 | B34: =IF('Macrobond Imports'!B33="","",'Macrobond Imports'!B33) | C34: =IF('Macrobond Imports'!C33="","",'Macrobond Imports'!C33) | D34: =IF('Macrobond Imports'!Z33="","",'Macrobond Imports'!Z33) | E34: =IF('Macrobond Imports'!BH33="","",'Macrobond Imports'!BH33) | F34: =IF('Macrobond Imports'!BJ33="","",'Macrobond Imports'!BJ33) | G34: =IF('Macrobond Imports'!BK33="","",'Macrobond Imports'!BK33) | H34: =IF('Macrobond Imports'!BL33="","",'Macrobond Imports'!BL33) | I34: =IF('Macrobond Imports'!BS33="","",'Macrobond Imports'!BS33) | J34: =IF('Macrobond Imports'!AA33="","",'Macrobond Imports'!AA33) | K34: =IF('Macrobond Imports'!DF33="","",'Macrobond Imports'!DF33) -> 23.9 | L34: =IF('Macrobond Imports'!EA33="","",'Macrobond Imports'!EA33) -> 29.2 | M34: =IF('Macrobond Imports'!FA33="","",'Macrobond Imports'!FA33) | N34: =IF('Macrobond Imports'!FC33="","",'Macrobond Imports'!FC33) | P34: =A34 -> 18111 | Q34: =IF(OR(B34="",N(B33)=0),"",B34/B33-1) | R34: =IF(OR(C34="",N(C33)=0),"",C34/C33-1) | S34: =IF(OR(D34="",N(D33)=0),"",D34/D33-1) | T34: =IF(OR(E34="",N(E33)=0),"",E34/E33-1) | U34: =IF(OR(F34="",N(F33)=0),"",F34/F33-1) | V34: =IF(OR(G34="",N(G33)=0),"",G34/G33-1) | W34: =IF(OR(H34="",N(H33)=0),"",H34/H33-1) | X34: =IF(OR(I34="",N(I33)=0),"",I34/I33-1) | ... AC34: =IF(OR(N34="",N(N33)=0),"",N34/N33-1) | AE34: =IFERROR(IF(OR(B34="",OFFSET(B34,-12,0)=""),"",B34/OFFSET(B34,-12,0)-1),"") | AF34: =IFERROR(IF(OR(C34="",OFFSET(C34,-12,0)=""),"",C34/OFFSET(C34,-12,0)-1),"") | AG34: =IFERROR(IF(OR(D34="",OFFSET(D34,-12,0)=""),"",D34/OFFSET(D34,-12,0)-1),"") | AH34: =IFERROR(IF(OR(E34="",OFFSET(E34,-12,0)=""),"",E34/OFFSET(E34,-12,0)-1),"") | AI34: =IFERROR(IF(OR(F34="",OFFSET(F34,-12,0)=""),"",F34/OFFSET(F34,-12,0)-1),"") | AJ34: =IFERROR(IF(OR(G34="",OFFSET(G34,-12,0)=""),"",G34/OFFSET(G34,-12,0)-1),"") | AK34: =IFERROR(IF(OR(H34="",OFFSET(H34,-12,0)=""),"",H34/OFFSET(H34,-12,0)-1),"") | AL34: =IFERROR(IF(OR(I34="",OFFSET(I34,-12,0)=""),"",I34/OFFSET(I34,-12,0)-1),"") | ... AQ34: =IFERROR(IF(OR(N34="",OFFSET(N34,-12,0)=""),"",N34/OFFSET(N34,-12,0)-1),"") | AS34: =IFERROR(IF(OR(B34="",OFFSET(B34,-3,0)=""),"",(B34/OFFSET(B34,-3,0))^4-1),"") | AT34: =IFERROR(IF(OR(C34="",OFFSET(C34,-3,0)=""),"",(C34/OFFSET(C34,-3,0))^4-1),"") | AU34: =IFERROR(IF(OR(D34="",OFFSET(D34,-3,0)=""),"",(D34/OFFSET(D34,-3,0))^4-1),"") | AV34: =IFERROR(IF(OR(E34="",OFFSET(E34,-3,0)=""),"",(E34/OFFSET(E34,-3,0))^4-1),"") | AW34: =IFERROR(IF(OR(F34="",OFFSET(F34,-3,0)=""),"",(F34/OFFSET(F34,-3,0))^4-1),"") | AX34: =IFERROR(IF(OR(G34="",OFFSET(G34,-3,0)=""),"",(G34/OFFSET(G34,-3,0))^4-1),"") | AY34: =IFERROR(IF(OR(H34="",OFFSET(H34,-3,0)=""),"",(H34/OFFSET(H34,-3,0))^4-1),"") | AZ34: =IFERROR(IF(OR(I34="",OFFSET(I34,-3,0)=""),"",(I34/OFFSET(I34,-3,0))^4-1),"") | ... BE34: =IFERROR(IF(OR(N34="",OFFSET(N34,-3,0)=""),"",(N34/OFFSET(N34,-3,0))^4-1),"") | BG34: =IFERROR(IF(OR(B34="",OFFSET(B34,-6,0)=""),"",(B34/OFFSET(B34,-6,0))^2-1),"") | BH34: =IFERROR(IF(OR(C34="",OFFSET(C34,-6,0)=""),"",(C34/OFFSET(C34,-6,0))^2-1),"") | BI34: =IFERROR(IF(OR(D34="",OFFSET(D34,-6,0)=""),"",(D34/OFFSET(D34,-6,0))^2-1),"") | BJ34: =IFERROR(IF(OR(E34="",OFFSET(E34,-6,0)=""),"",(E34/OFFSET(E34,-6,0))^2-1),"") | BK34: =IFERROR(IF(OR(F34="",OFFSET(F34,-6,0)=""),"",(F34/OFFSET(F34,-6,0))^2-1),"") | BL34: =IFERROR(IF(OR(G34="",OFFSET(G34,-6,0)=""),"",(G34/OFFSET(G34,-6,0))^2-1),"") | BM34: =IFERROR(IF(OR(H34="",OFFSET(H34,-6,0)=""),"",(H34/OFFSET(H34,-6,0))^2-1),"") | BN34: =IFERROR(IF(OR(I34="",OFFSET(I34,-6,0)=""),"",(I34/OFFSET(I34,-6,0))^2-1),"") | ... BS34: =IFERROR(IF(OR(N34="",OFFSET(N34,-6,0)=""),"",(N34/OFFSET(N34,-6,0))^2-1),"") | BX34: =IF('Macrobond Imports'!FG33="","",'Macrobond Imports'!FG33) | BY34: =IF('Macrobond Imports'!AI33="","",'Macrobond Imports'!AI33) | CA34: =IFERROR(IF(OR(BX34="",OFFSET(BX34,-12,0)=""),"",BX34/OFFSET(BX34,-12,0)-1),"") | CB34: =IFERROR(IF(OR(BY34="",OFFSET(BY34,-12,0)=""),"",BY34/OFFSET(BY34,-12,0)-1),"")
A35: =IF('Macrobond Imports'!A34="","",'Macrobond Imports'!A34) -> 18142 | B35: =IF('Macrobond Imports'!B34="","",'Macrobond Imports'!B34) | C35: =IF('Macrobond Imports'!C34="","",'Macrobond Imports'!C34) | D35: =IF('Macrobond Imports'!Z34="","",'Macrobond Imports'!Z34) | E35: =IF('Macrobond Imports'!BH34="","",'Macrobond Imports'!BH34) | F35: =IF('Macrobond Imports'!BJ34="","",'Macrobond Imports'!BJ34) | G35: =IF('Macrobond Imports'!BK34="","",'Macrobond Imports'!BK34) | H35: =IF('Macrobond Imports'!BL34="","",'Macrobond Imports'!BL34) | I35: =IF('Macrobond Imports'!BS34="","",'Macrobond Imports'!BS34) | J35: =IF('Macrobond Imports'!AA34="","",'Macrobond Imports'!AA34) | K35: =IF('Macrobond Imports'!DF34="","",'Macrobond Imports'!DF34) -> 23.9 | L35: =IF('Macrobond Imports'!EA34="","",'Macrobond Imports'!EA34) -> 29.5 | M35: =IF('Macrobond Imports'!FA34="","",'Macrobond Imports'!FA34) | N35: =IF('Macrobond Imports'!FC34="","",'Macrobond Imports'!FC34) | P35: =A35 -> 18142 | Q35: =IF(OR(B35="",N(B34)=0),"",B35/B34-1) | R35: =IF(OR(C35="",N(C34)=0),"",C35/C34-1) | S35: =IF(OR(D35="",N(D34)=0),"",D35/D34-1) | T35: =IF(OR(E35="",N(E34)=0),"",E35/E34-1) | U35: =IF(OR(F35="",N(F34)=0),"",F35/F34-1) | V35: =IF(OR(G35="",N(G34)=0),"",G35/G34-1) | W35: =IF(OR(H35="",N(H34)=0),"",H35/H34-1) | X35: =IF(OR(I35="",N(I34)=0),"",I35/I34-1) | ... AC35: =IF(OR(N35="",N(N34)=0),"",N35/N34-1) | AE35: =IFERROR(IF(OR(B35="",OFFSET(B35,-12,0)=""),"",B35/OFFSET(B35,-12,0)-1),"") | AF35: =IFERROR(IF(OR(C35="",OFFSET(C35,-12,0)=""),"",C35/OFFSET(C35,-12,0)-1),"") | AG35: =IFERROR(IF(OR(D35="",OFFSET(D35,-12,0)=""),"",D35/OFFSET(D35,-12,0)-1),"") | AH35: =IFERROR(IF(OR(E35="",OFFSET(E35,-12,0)=""),"",E35/OFFSET(E35,-12,0)-1),"") | AI35: =IFERROR(IF(OR(F35="",OFFSET(F35,-12,0)=""),"",F35/OFFSET(F35,-12,0)-1),"") | AJ35: =IFERROR(IF(OR(G35="",OFFSET(G35,-12,0)=""),"",G35/OFFSET(G35,-12,0)-1),"") | AK35: =IFERROR(IF(OR(H35="",OFFSET(H35,-12,0)=""),"",H35/OFFSET(H35,-12,0)-1),"") | AL35: =IFERROR(IF(OR(I35="",OFFSET(I35,-12,0)=""),"",I35/OFFSET(I35,-12,0)-1),"") | ... AQ35: =IFERROR(IF(OR(N35="",OFFSET(N35,-12,0)=""),"",N35/OFFSET(N35,-12,0)-1),"") | AS35: =IFERROR(IF(OR(B35="",OFFSET(B35,-3,0)=""),"",(B35/OFFSET(B35,-3,0))^4-1),"") | AT35: =IFERROR(IF(OR(C35="",OFFSET(C35,-3,0)=""),"",(C35/OFFSET(C35,-3,0))^4-1),"") | AU35: =IFERROR(IF(OR(D35="",OFFSET(D35,-3,0)=""),"",(D35/OFFSET(D35,-3,0))^4-1),"") | AV35: =IFERROR(IF(OR(E35="",OFFSET(E35,-3,0)=""),"",(E35/OFFSET(E35,-3,0))^4-1),"") | AW35: =IFERROR(IF(OR(F35="",OFFSET(F35,-3,0)=""),"",(F35/OFFSET(F35,-3,0))^4-1),"") | AX35: =IFERROR(IF(OR(G35="",OFFSET(G35,-3,0)=""),"",(G35/OFFSET(G35,-3,0))^4-1),"") | AY35: =IFERROR(IF(OR(H35="",OFFSET(H35,-3,0)=""),"",(H35/OFFSET(H35,-3,0))^4-1),"") | AZ35: =IFERROR(IF(OR(I35="",OFFSET(I35,-3,0)=""),"",(I35/OFFSET(I35,-3,0))^4-1),"") | ... BE35: =IFERROR(IF(OR(N35="",OFFSET(N35,-3,0)=""),"",(N35/OFFSET(N35,-3,0))^4-1),"") | BG35: =IFERROR(IF(OR(B35="",OFFSET(B35,-6,0)=""),"",(B35/OFFSET(B35,-6,0))^2-1),"") | BH35: =IFERROR(IF(OR(C35="",OFFSET(C35,-6,0)=""),"",(C35/OFFSET(C35,-6,0))^2-1),"") | BI35: =IFERROR(IF(OR(D35="",OFFSET(D35,-6,0)=""),"",(D35/OFFSET(D35,-6,0))^2-1),"") | BJ35: =IFERROR(IF(OR(E35="",OFFSET(E35,-6,0)=""),"",(E35/OFFSET(E35,-6,0))^2-1),"") | BK35: =IFERROR(IF(OR(F35="",OFFSET(F35,-6,0)=""),"",(F35/OFFSET(F35,-6,0))^2-1),"") | BL35: =IFERROR(IF(OR(G35="",OFFSET(G35,-6,0)=""),"",(G35/OFFSET(G35,-6,0))^2-1),"") | BM35: =IFERROR(IF(OR(H35="",OFFSET(H35,-6,0)=""),"",(H35/OFFSET(H35,-6,0))^2-1),"") | BN35: =IFERROR(IF(OR(I35="",OFFSET(I35,-6,0)=""),"",(I35/OFFSET(I35,-6,0))^2-1),"") | ... BS35: =IFERROR(IF(OR(N35="",OFFSET(N35,-6,0)=""),"",(N35/OFFSET(N35,-6,0))^2-1),"") | BX35: =IF('Macrobond Imports'!FG34="","",'Macrobond Imports'!FG34) | BY35: =IF('Macrobond Imports'!AI34="","",'Macrobond Imports'!AI34) | CA35: =IFERROR(IF(OR(BX35="",OFFSET(BX35,-12,0)=""),"",BX35/OFFSET(BX35,-12,0)-1),"") | CB35: =IFERROR(IF(OR(BY35="",OFFSET(BY35,-12,0)=""),"",BY35/OFFSET(BY35,-12,0)-1),"")
A36: =IF('Macrobond Imports'!A35="","",'Macrobond Imports'!A35) -> 18172 | B36: =IF('Macrobond Imports'!B35="","",'Macrobond Imports'!B35) | C36: =IF('Macrobond Imports'!C35="","",'Macrobond Imports'!C35) | D36: =IF('Macrobond Imports'!Z35="","",'Macrobond Imports'!Z35) | E36: =IF('Macrobond Imports'!BH35="","",'Macrobond Imports'!BH35) | F36: =IF('Macrobond Imports'!BJ35="","",'Macrobond Imports'!BJ35) | G36: =IF('Macrobond Imports'!BK35="","",'Macrobond Imports'!BK35) | H36: =IF('Macrobond Imports'!BL35="","",'Macrobond Imports'!BL35) | I36: =IF('Macrobond Imports'!BS35="","",'Macrobond Imports'!BS35) | J36: =IF('Macrobond Imports'!AA35="","",'Macrobond Imports'!AA35) | K36: =IF('Macrobond Imports'!DF35="","",'Macrobond Imports'!DF35) -> 23.8 | L36: =IF('Macrobond Imports'!EA35="","",'Macrobond Imports'!EA35) -> 29.5 | M36: =IF('Macrobond Imports'!FA35="","",'Macrobond Imports'!FA35) | N36: =IF('Macrobond Imports'!FC35="","",'Macrobond Imports'!FC35) | P36: =A36 -> 18172 | Q36: =IF(OR(B36="",N(B35)=0),"",B36/B35-1) | R36: =IF(OR(C36="",N(C35)=0),"",C36/C35-1) | S36: =IF(OR(D36="",N(D35)=0),"",D36/D35-1) | T36: =IF(OR(E36="",N(E35)=0),"",E36/E35-1) | U36: =IF(OR(F36="",N(F35)=0),"",F36/F35-1) | V36: =IF(OR(G36="",N(G35)=0),"",G36/G35-1) | W36: =IF(OR(H36="",N(H35)=0),"",H36/H35-1) | X36: =IF(OR(I36="",N(I35)=0),"",I36/I35-1) | ... AC36: =IF(OR(N36="",N(N35)=0),"",N36/N35-1) | AE36: =IFERROR(IF(OR(B36="",OFFSET(B36,-12,0)=""),"",B36/OFFSET(B36,-12,0)-1),"") | AF36: =IFERROR(IF(OR(C36="",OFFSET(C36,-12,0)=""),"",C36/OFFSET(C36,-12,0)-1),"") | AG36: =IFERROR(IF(OR(D36="",OFFSET(D36,-12,0)=""),"",D36/OFFSET(D36,-12,0)-1),"") | AH36: =IFERROR(IF(OR(E36="",OFFSET(E36,-12,0)=""),"",E36/OFFSET(E36,-12,0)-1),"") | AI36: =IFERROR(IF(OR(F36="",OFFSET(F36,-12,0)=""),"",F36/OFFSET(F36,-12,0)-1),"") | AJ36: =IFERROR(IF(OR(G36="",OFFSET(G36,-12,0)=""),"",G36/OFFSET(G36,-12,0)-1),"") | AK36: =IFERROR(IF(OR(H36="",OFFSET(H36,-12,0)=""),"",H36/OFFSET(H36,-12,0)-1),"") | AL36: =IFERROR(IF(OR(I36="",OFFSET(I36,-12,0)=""),"",I36/OFFSET(I36,-12,0)-1),"") | ... AQ36: =IFERROR(IF(OR(N36="",OFFSET(N36,-12,0)=""),"",N36/OFFSET(N36,-12,0)-1),"") | AS36: =IFERROR(IF(OR(B36="",OFFSET(B36,-3,0)=""),"",(B36/OFFSET(B36,-3,0))^4-1),"") | AT36: =IFERROR(IF(OR(C36="",OFFSET(C36,-3,0)=""),"",(C36/OFFSET(C36,-3,0))^4-1),"") | AU36: =IFERROR(IF(OR(D36="",OFFSET(D36,-3,0)=""),"",(D36/OFFSET(D36,-3,0))^4-1),"") | AV36: =IFERROR(IF(OR(E36="",OFFSET(E36,-3,0)=""),"",(E36/OFFSET(E36,-3,0))^4-1),"") | AW36: =IFERROR(IF(OR(F36="",OFFSET(F36,-3,0)=""),"",(F36/OFFSET(F36,-3,0))^4-1),"") | AX36: =IFERROR(IF(OR(G36="",OFFSET(G36,-3,0)=""),"",(G36/OFFSET(G36,-3,0))^4-1),"") | AY36: =IFERROR(IF(OR(H36="",OFFSET(H36,-3,0)=""),"",(H36/OFFSET(H36,-3,0))^4-1),"") | AZ36: =IFERROR(IF(OR(I36="",OFFSET(I36,-3,0)=""),"",(I36/OFFSET(I36,-3,0))^4-1),"") | ... BE36: =IFERROR(IF(OR(N36="",OFFSET(N36,-3,0)=""),"",(N36/OFFSET(N36,-3,0))^4-1),"") | BG36: =IFERROR(IF(OR(B36="",OFFSET(B36,-6,0)=""),"",(B36/OFFSET(B36,-6,0))^2-1),"") | BH36: =IFERROR(IF(OR(C36="",OFFSET(C36,-6,0)=""),"",(C36/OFFSET(C36,-6,0))^2-1),"") | BI36: =IFERROR(IF(OR(D36="",OFFSET(D36,-6,0)=""),"",(D36/OFFSET(D36,-6,0))^2-1),"") | BJ36: =IFERROR(IF(OR(E36="",OFFSET(E36,-6,0)=""),"",(E36/OFFSET(E36,-6,0))^2-1),"") | BK36: =IFERROR(IF(OR(F36="",OFFSET(F36,-6,0)=""),"",(F36/OFFSET(F36,-6,0))^2-1),"") | BL36: =IFERROR(IF(OR(G36="",OFFSET(G36,-6,0)=""),"",(G36/OFFSET(G36,-6,0))^2-1),"") | BM36: =IFERROR(IF(OR(H36="",OFFSET(H36,-6,0)=""),"",(H36/OFFSET(H36,-6,0))^2-1),"") | BN36: =IFERROR(IF(OR(I36="",OFFSET(I36,-6,0)=""),"",(I36/OFFSET(I36,-6,0))^2-1),"") | ... BS36: =IFERROR(IF(OR(N36="",OFFSET(N36,-6,0)=""),"",(N36/OFFSET(N36,-6,0))^2-1),"") | BX36: =IF('Macrobond Imports'!FG35="","",'Macrobond Imports'!FG35) | BY36: =IF('Macrobond Imports'!AI35="","",'Macrobond Imports'!AI35) | CA36: =IFERROR(IF(OR(BX36="",OFFSET(BX36,-12,0)=""),"",BX36/OFFSET(BX36,-12,0)-1),"") | CB36: =IFERROR(IF(OR(BY36="",OFFSET(BY36,-12,0)=""),"",BY36/OFFSET(BY36,-12,0)-1),"")
A37: =IF('Macrobond Imports'!A36="","",'Macrobond Imports'!A36) -> 18203 | B37: =IF('Macrobond Imports'!B36="","",'Macrobond Imports'!B36) | C37: =IF('Macrobond Imports'!C36="","",'Macrobond Imports'!C36) | D37: =IF('Macrobond Imports'!Z36="","",'Macrobond Imports'!Z36) | E37: =IF('Macrobond Imports'!BH36="","",'Macrobond Imports'!BH36) | F37: =IF('Macrobond Imports'!BJ36="","",'Macrobond Imports'!BJ36) | G37: =IF('Macrobond Imports'!BK36="","",'Macrobond Imports'!BK36) | H37: =IF('Macrobond Imports'!BL36="","",'Macrobond Imports'!BL36) | I37: =IF('Macrobond Imports'!BS36="","",'Macrobond Imports'!BS36) | J37: =IF('Macrobond Imports'!AA36="","",'Macrobond Imports'!AA36) | K37: =IF('Macrobond Imports'!DF36="","",'Macrobond Imports'!DF36) -> 23.7 | L37: =IF('Macrobond Imports'!EA36="","",'Macrobond Imports'!EA36) -> 29.6 | M37: =IF('Macrobond Imports'!FA36="","",'Macrobond Imports'!FA36) | N37: =IF('Macrobond Imports'!FC36="","",'Macrobond Imports'!FC36) | P37: =A37 -> 18203 | Q37: =IF(OR(B37="",N(B36)=0),"",B37/B36-1) | R37: =IF(OR(C37="",N(C36)=0),"",C37/C36-1) | S37: =IF(OR(D37="",N(D36)=0),"",D37/D36-1) | T37: =IF(OR(E37="",N(E36)=0),"",E37/E36-1) | U37: =IF(OR(F37="",N(F36)=0),"",F37/F36-1) | V37: =IF(OR(G37="",N(G36)=0),"",G37/G36-1) | W37: =IF(OR(H37="",N(H36)=0),"",H37/H36-1) | X37: =IF(OR(I37="",N(I36)=0),"",I37/I36-1) | ... AC37: =IF(OR(N37="",N(N36)=0),"",N37/N36-1) | AE37: =IFERROR(IF(OR(B37="",OFFSET(B37,-12,0)=""),"",B37/OFFSET(B37,-12,0)-1),"") | AF37: =IFERROR(IF(OR(C37="",OFFSET(C37,-12,0)=""),"",C37/OFFSET(C37,-12,0)-1),"") | AG37: =IFERROR(IF(OR(D37="",OFFSET(D37,-12,0)=""),"",D37/OFFSET(D37,-12,0)-1),"") | AH37: =IFERROR(IF(OR(E37="",OFFSET(E37,-12,0)=""),"",E37/OFFSET(E37,-12,0)-1),"") | AI37: =IFERROR(IF(OR(F37="",OFFSET(F37,-12,0)=""),"",F37/OFFSET(F37,-12,0)-1),"") | AJ37: =IFERROR(IF(OR(G37="",OFFSET(G37,-12,0)=""),"",G37/OFFSET(G37,-12,0)-1),"") | AK37: =IFERROR(IF(OR(H37="",OFFSET(H37,-12,0)=""),"",H37/OFFSET(H37,-12,0)-1),"") | AL37: =IFERROR(IF(OR(I37="",OFFSET(I37,-12,0)=""),"",I37/OFFSET(I37,-12,0)-1),"") | ... AQ37: =IFERROR(IF(OR(N37="",OFFSET(N37,-12,0)=""),"",N37/OFFSET(N37,-12,0)-1),"") | AS37: =IFERROR(IF(OR(B37="",OFFSET(B37,-3,0)=""),"",(B37/OFFSET(B37,-3,0))^4-1),"") | AT37: =IFERROR(IF(OR(C37="",OFFSET(C37,-3,0)=""),"",(C37/OFFSET(C37,-3,0))^4-1),"") | AU37: =IFERROR(IF(OR(D37="",OFFSET(D37,-3,0)=""),"",(D37/OFFSET(D37,-3,0))^4-1),"") | AV37: =IFERROR(IF(OR(E37="",OFFSET(E37,-3,0)=""),"",(E37/OFFSET(E37,-3,0))^4-1),"") | AW37: =IFERROR(IF(OR(F37="",OFFSET(F37,-3,0)=""),"",(F37/OFFSET(F37,-3,0))^4-1),"") | AX37: =IFERROR(IF(OR(G37="",OFFSET(G37,-3,0)=""),"",(G37/OFFSET(G37,-3,0))^4-1),"") | AY37: =IFERROR(IF(OR(H37="",OFFSET(H37,-3,0)=""),"",(H37/OFFSET(H37,-3,0))^4-1),"") | AZ37: =IFERROR(IF(OR(I37="",OFFSET(I37,-3,0)=""),"",(I37/OFFSET(I37,-3,0))^4-1),"") | ... BE37: =IFERROR(IF(OR(N37="",OFFSET(N37,-3,0)=""),"",(N37/OFFSET(N37,-3,0))^4-1),"") | BG37: =IFERROR(IF(OR(B37="",OFFSET(B37,-6,0)=""),"",(B37/OFFSET(B37,-6,0))^2-1),"") | BH37: =IFERROR(IF(OR(C37="",OFFSET(C37,-6,0)=""),"",(C37/OFFSET(C37,-6,0))^2-1),"") | BI37: =IFERROR(IF(OR(D37="",OFFSET(D37,-6,0)=""),"",(D37/OFFSET(D37,-6,0))^2-1),"") | BJ37: =IFERROR(IF(OR(E37="",OFFSET(E37,-6,0)=""),"",(E37/OFFSET(E37,-6,0))^2-1),"") | BK37: =IFERROR(IF(OR(F37="",OFFSET(F37,-6,0)=""),"",(F37/OFFSET(F37,-6,0))^2-1),"") | BL37: =IFERROR(IF(OR(G37="",OFFSET(G37,-6,0)=""),"",(G37/OFFSET(G37,-6,0))^2-1),"") | BM37: =IFERROR(IF(OR(H37="",OFFSET(H37,-6,0)=""),"",(H37/OFFSET(H37,-6,0))^2-1),"") | BN37: =IFERROR(IF(OR(I37="",OFFSET(I37,-6,0)=""),"",(I37/OFFSET(I37,-6,0))^2-1),"") | ... BS37: =IFERROR(IF(OR(N37="",OFFSET(N37,-6,0)=""),"",(N37/OFFSET(N37,-6,0))^2-1),"") | BX37: =IF('Macrobond Imports'!FG36="","",'Macrobond Imports'!FG36) | BY37: =IF('Macrobond Imports'!AI36="","",'Macrobond Imports'!AI36) | CA37: =IFERROR(IF(OR(BX37="",OFFSET(BX37,-12,0)=""),"",BX37/OFFSET(BX37,-12,0)-1),"") | CB37: =IFERROR(IF(OR(BY37="",OFFSET(BY37,-12,0)=""),"",BY37/OFFSET(BY37,-12,0)-1),"")
A38: =IF('Macrobond Imports'!A37="","",'Macrobond Imports'!A37) -> 18233 | B38: =IF('Macrobond Imports'!B37="","",'Macrobond Imports'!B37) | C38: =IF('Macrobond Imports'!C37="","",'Macrobond Imports'!C37) | D38: =IF('Macrobond Imports'!Z37="","",'Macrobond Imports'!Z37) | E38: =IF('Macrobond Imports'!BH37="","",'Macrobond Imports'!BH37) | F38: =IF('Macrobond Imports'!BJ37="","",'Macrobond Imports'!BJ37) | G38: =IF('Macrobond Imports'!BK37="","",'Macrobond Imports'!BK37) | H38: =IF('Macrobond Imports'!BL37="","",'Macrobond Imports'!BL37) | I38: =IF('Macrobond Imports'!BS37="","",'Macrobond Imports'!BS37) | J38: =IF('Macrobond Imports'!AA37="","",'Macrobond Imports'!AA37) | K38: =IF('Macrobond Imports'!DF37="","",'Macrobond Imports'!DF37) -> 23.8 | L38: =IF('Macrobond Imports'!EA37="","",'Macrobond Imports'!EA37) -> 29.6 | M38: =IF('Macrobond Imports'!FA37="","",'Macrobond Imports'!FA37) | N38: =IF('Macrobond Imports'!FC37="","",'Macrobond Imports'!FC37) | P38: =A38 -> 18233 | Q38: =IF(OR(B38="",N(B37)=0),"",B38/B37-1) | R38: =IF(OR(C38="",N(C37)=0),"",C38/C37-1) | S38: =IF(OR(D38="",N(D37)=0),"",D38/D37-1) | T38: =IF(OR(E38="",N(E37)=0),"",E38/E37-1) | U38: =IF(OR(F38="",N(F37)=0),"",F38/F37-1) | V38: =IF(OR(G38="",N(G37)=0),"",G38/G37-1) | W38: =IF(OR(H38="",N(H37)=0),"",H38/H37-1) | X38: =IF(OR(I38="",N(I37)=0),"",I38/I37-1) | ... AC38: =IF(OR(N38="",N(N37)=0),"",N38/N37-1) | AE38: =IFERROR(IF(OR(B38="",OFFSET(B38,-12,0)=""),"",B38/OFFSET(B38,-12,0)-1),"") | AF38: =IFERROR(IF(OR(C38="",OFFSET(C38,-12,0)=""),"",C38/OFFSET(C38,-12,0)-1),"") | AG38: =IFERROR(IF(OR(D38="",OFFSET(D38,-12,0)=""),"",D38/OFFSET(D38,-12,0)-1),"") | AH38: =IFERROR(IF(OR(E38="",OFFSET(E38,-12,0)=""),"",E38/OFFSET(E38,-12,0)-1),"") | AI38: =IFERROR(IF(OR(F38="",OFFSET(F38,-12,0)=""),"",F38/OFFSET(F38,-12,0)-1),"") | AJ38: =IFERROR(IF(OR(G38="",OFFSET(G38,-12,0)=""),"",G38/OFFSET(G38,-12,0)-1),"") | AK38: =IFERROR(IF(OR(H38="",OFFSET(H38,-12,0)=""),"",H38/OFFSET(H38,-12,0)-1),"") | AL38: =IFERROR(IF(OR(I38="",OFFSET(I38,-12,0)=""),"",I38/OFFSET(I38,-12,0)-1),"") | ... AQ38: =IFERROR(IF(OR(N38="",OFFSET(N38,-12,0)=""),"",N38/OFFSET(N38,-12,0)-1),"") | AS38: =IFERROR(IF(OR(B38="",OFFSET(B38,-3,0)=""),"",(B38/OFFSET(B38,-3,0))^4-1),"") | AT38: =IFERROR(IF(OR(C38="",OFFSET(C38,-3,0)=""),"",(C38/OFFSET(C38,-3,0))^4-1),"") | AU38: =IFERROR(IF(OR(D38="",OFFSET(D38,-3,0)=""),"",(D38/OFFSET(D38,-3,0))^4-1),"") | AV38: =IFERROR(IF(OR(E38="",OFFSET(E38,-3,0)=""),"",(E38/OFFSET(E38,-3,0))^4-1),"") | AW38: =IFERROR(IF(OR(F38="",OFFSET(F38,-3,0)=""),"",(F38/OFFSET(F38,-3,0))^4-1),"") | AX38: =IFERROR(IF(OR(G38="",OFFSET(G38,-3,0)=""),"",(G38/OFFSET(G38,-3,0))^4-1),"") | AY38: =IFERROR(IF(OR(H38="",OFFSET(H38,-3,0)=""),"",(H38/OFFSET(H38,-3,0))^4-1),"") | AZ38: =IFERROR(IF(OR(I38="",OFFSET(I38,-3,0)=""),"",(I38/OFFSET(I38,-3,0))^4-1),"") | ... BE38: =IFERROR(IF(OR(N38="",OFFSET(N38,-3,0)=""),"",(N38/OFFSET(N38,-3,0))^4-1),"") | BG38: =IFERROR(IF(OR(B38="",OFFSET(B38,-6,0)=""),"",(B38/OFFSET(B38,-6,0))^2-1),"") | BH38: =IFERROR(IF(OR(C38="",OFFSET(C38,-6,0)=""),"",(C38/OFFSET(C38,-6,0))^2-1),"") | BI38: =IFERROR(IF(OR(D38="",OFFSET(D38,-6,0)=""),"",(D38/OFFSET(D38,-6,0))^2-1),"") | BJ38: =IFERROR(IF(OR(E38="",OFFSET(E38,-6,0)=""),"",(E38/OFFSET(E38,-6,0))^2-1),"") | BK38: =IFERROR(IF(OR(F38="",OFFSET(F38,-6,0)=""),"",(F38/OFFSET(F38,-6,0))^2-1),"") | BL38: =IFERROR(IF(OR(G38="",OFFSET(G38,-6,0)=""),"",(G38/OFFSET(G38,-6,0))^2-1),"") | BM38: =IFERROR(IF(OR(H38="",OFFSET(H38,-6,0)=""),"",(H38/OFFSET(H38,-6,0))^2-1),"") | BN38: =IFERROR(IF(OR(I38="",OFFSET(I38,-6,0)=""),"",(I38/OFFSET(I38,-6,0))^2-1),"") | ... BS38: =IFERROR(IF(OR(N38="",OFFSET(N38,-6,0)=""),"",(N38/OFFSET(N38,-6,0))^2-1),"") | BX38: =IF('Macrobond Imports'!FG37="","",'Macrobond Imports'!FG37) | BY38: =IF('Macrobond Imports'!AI37="","",'Macrobond Imports'!AI37) | CA38: =IFERROR(IF(OR(BX38="",OFFSET(BX38,-12,0)=""),"",BX38/OFFSET(BX38,-12,0)-1),"") | CB38: =IFERROR(IF(OR(BY38="",OFFSET(BY38,-12,0)=""),"",BY38/OFFSET(BY38,-12,0)-1),"")
A39: =IF('Macrobond Imports'!A38="","",'Macrobond Imports'!A38) -> 18264 | B39: =IF('Macrobond Imports'!B38="","",'Macrobond Imports'!B38) | C39: =IF('Macrobond Imports'!C38="","",'Macrobond Imports'!C38) | D39: =IF('Macrobond Imports'!Z38="","",'Macrobond Imports'!Z38) | E39: =IF('Macrobond Imports'!BH38="","",'Macrobond Imports'!BH38) | F39: =IF('Macrobond Imports'!BJ38="","",'Macrobond Imports'!BJ38) | G39: =IF('Macrobond Imports'!BK38="","",'Macrobond Imports'!BK38) | H39: =IF('Macrobond Imports'!BL38="","",'Macrobond Imports'!BL38) | I39: =IF('Macrobond Imports'!BS38="","",'Macrobond Imports'!BS38) | J39: =IF('Macrobond Imports'!AA38="","",'Macrobond Imports'!AA38) | K39: =IF('Macrobond Imports'!DF38="","",'Macrobond Imports'!DF38) -> 23.8 | L39: =IF('Macrobond Imports'!EA38="","",'Macrobond Imports'!EA38) -> 29.6 | M39: =IF('Macrobond Imports'!FA38="","",'Macrobond Imports'!FA38) | N39: =IF('Macrobond Imports'!FC38="","",'Macrobond Imports'!FC38) | P39: =A39 -> 18264 | Q39: =IF(OR(B39="",N(B38)=0),"",B39/B38-1) | R39: =IF(OR(C39="",N(C38)=0),"",C39/C38-1) | S39: =IF(OR(D39="",N(D38)=0),"",D39/D38-1) | T39: =IF(OR(E39="",N(E38)=0),"",E39/E38-1) | U39: =IF(OR(F39="",N(F38)=0),"",F39/F38-1) | V39: =IF(OR(G39="",N(G38)=0),"",G39/G38-1) | W39: =IF(OR(H39="",N(H38)=0),"",H39/H38-1) | X39: =IF(OR(I39="",N(I38)=0),"",I39/I38-1) | ... AC39: =IF(OR(N39="",N(N38)=0),"",N39/N38-1) | AE39: =IFERROR(IF(OR(B39="",OFFSET(B39,-12,0)=""),"",B39/OFFSET(B39,-12,0)-1),"") | AF39: =IFERROR(IF(OR(C39="",OFFSET(C39,-12,0)=""),"",C39/OFFSET(C39,-12,0)-1),"") | AG39: =IFERROR(IF(OR(D39="",OFFSET(D39,-12,0)=""),"",D39/OFFSET(D39,-12,0)-1),"") | AH39: =IFERROR(IF(OR(E39="",OFFSET(E39,-12,0)=""),"",E39/OFFSET(E39,-12,0)-1),"") | AI39: =IFERROR(IF(OR(F39="",OFFSET(F39,-12,0)=""),"",F39/OFFSET(F39,-12,0)-1),"") | AJ39: =IFERROR(IF(OR(G39="",OFFSET(G39,-12,0)=""),"",G39/OFFSET(G39,-12,0)-1),"") | AK39: =IFERROR(IF(OR(H39="",OFFSET(H39,-12,0)=""),"",H39/OFFSET(H39,-12,0)-1),"") | AL39: =IFERROR(IF(OR(I39="",OFFSET(I39,-12,0)=""),"",I39/OFFSET(I39,-12,0)-1),"") | ... AQ39: =IFERROR(IF(OR(N39="",OFFSET(N39,-12,0)=""),"",N39/OFFSET(N39,-12,0)-1),"") | AS39: =IFERROR(IF(OR(B39="",OFFSET(B39,-3,0)=""),"",(B39/OFFSET(B39,-3,0))^4-1),"") | AT39: =IFERROR(IF(OR(C39="",OFFSET(C39,-3,0)=""),"",(C39/OFFSET(C39,-3,0))^4-1),"") | AU39: =IFERROR(IF(OR(D39="",OFFSET(D39,-3,0)=""),"",(D39/OFFSET(D39,-3,0))^4-1),"") | AV39: =IFERROR(IF(OR(E39="",OFFSET(E39,-3,0)=""),"",(E39/OFFSET(E39,-3,0))^4-1),"") | AW39: =IFERROR(IF(OR(F39="",OFFSET(F39,-3,0)=""),"",(F39/OFFSET(F39,-3,0))^4-1),"") | AX39: =IFERROR(IF(OR(G39="",OFFSET(G39,-3,0)=""),"",(G39/OFFSET(G39,-3,0))^4-1),"") | AY39: =IFERROR(IF(OR(H39="",OFFSET(H39,-3,0)=""),"",(H39/OFFSET(H39,-3,0))^4-1),"") | AZ39: =IFERROR(IF(OR(I39="",OFFSET(I39,-3,0)=""),"",(I39/OFFSET(I39,-3,0))^4-1),"") | ... BE39: =IFERROR(IF(OR(N39="",OFFSET(N39,-3,0)=""),"",(N39/OFFSET(N39,-3,0))^4-1),"") | BG39: =IFERROR(IF(OR(B39="",OFFSET(B39,-6,0)=""),"",(B39/OFFSET(B39,-6,0))^2-1),"") | BH39: =IFERROR(IF(OR(C39="",OFFSET(C39,-6,0)=""),"",(C39/OFFSET(C39,-6,0))^2-1),"") | BI39: =IFERROR(IF(OR(D39="",OFFSET(D39,-6,0)=""),"",(D39/OFFSET(D39,-6,0))^2-1),"") | BJ39: =IFERROR(IF(OR(E39="",OFFSET(E39,-6,0)=""),"",(E39/OFFSET(E39,-6,0))^2-1),"") | BK39: =IFERROR(IF(OR(F39="",OFFSET(F39,-6,0)=""),"",(F39/OFFSET(F39,-6,0))^2-1),"") | BL39: =IFERROR(IF(OR(G39="",OFFSET(G39,-6,0)=""),"",(G39/OFFSET(G39,-6,0))^2-1),"") | BM39: =IFERROR(IF(OR(H39="",OFFSET(H39,-6,0)=""),"",(H39/OFFSET(H39,-6,0))^2-1),"") | BN39: =IFERROR(IF(OR(I39="",OFFSET(I39,-6,0)=""),"",(I39/OFFSET(I39,-6,0))^2-1),"") | ... BS39: =IFERROR(IF(OR(N39="",OFFSET(N39,-6,0)=""),"",(N39/OFFSET(N39,-6,0))^2-1),"") | BX39: =IF('Macrobond Imports'!FG38="","",'Macrobond Imports'!FG38) | BY39: =IF('Macrobond Imports'!AI38="","",'Macrobond Imports'!AI38) | CA39: =IFERROR(IF(OR(BX39="",OFFSET(BX39,-12,0)=""),"",BX39/OFFSET(BX39,-12,0)-1),"") | CB39: =IFERROR(IF(OR(BY39="",OFFSET(BY39,-12,0)=""),"",BY39/OFFSET(BY39,-12,0)-1),"")
A40: =IF('Macrobond Imports'!A39="","",'Macrobond Imports'!A39) -> 18295 | B40: =IF('Macrobond Imports'!B39="","",'Macrobond Imports'!B39) | C40: =IF('Macrobond Imports'!C39="","",'Macrobond Imports'!C39) | D40: =IF('Macrobond Imports'!Z39="","",'Macrobond Imports'!Z39) | E40: =IF('Macrobond Imports'!BH39="","",'Macrobond Imports'!BH39) | F40: =IF('Macrobond Imports'!BJ39="","",'Macrobond Imports'!BJ39) | G40: =IF('Macrobond Imports'!BK39="","",'Macrobond Imports'!BK39) | H40: =IF('Macrobond Imports'!BL39="","",'Macrobond Imports'!BL39) | I40: =IF('Macrobond Imports'!BS39="","",'Macrobond Imports'!BS39) | J40: =IF('Macrobond Imports'!AA39="","",'Macrobond Imports'!AA39) | K40: =IF('Macrobond Imports'!DF39="","",'Macrobond Imports'!DF39) -> 23.9 | L40: =IF('Macrobond Imports'!EA39="","",'Macrobond Imports'!EA39) -> 30.5 | M40: =IF('Macrobond Imports'!FA39="","",'Macrobond Imports'!FA39) | N40: =IF('Macrobond Imports'!FC39="","",'Macrobond Imports'!FC39) | P40: =A40 -> 18295 | Q40: =IF(OR(B40="",N(B39)=0),"",B40/B39-1) | R40: =IF(OR(C40="",N(C39)=0),"",C40/C39-1) | S40: =IF(OR(D40="",N(D39)=0),"",D40/D39-1) | T40: =IF(OR(E40="",N(E39)=0),"",E40/E39-1) | U40: =IF(OR(F40="",N(F39)=0),"",F40/F39-1) | V40: =IF(OR(G40="",N(G39)=0),"",G40/G39-1) | W40: =IF(OR(H40="",N(H39)=0),"",H40/H39-1) | X40: =IF(OR(I40="",N(I39)=0),"",I40/I39-1) | ... AC40: =IF(OR(N40="",N(N39)=0),"",N40/N39-1) | AE40: =IFERROR(IF(OR(B40="",OFFSET(B40,-12,0)=""),"",B40/OFFSET(B40,-12,0)-1),"") | AF40: =IFERROR(IF(OR(C40="",OFFSET(C40,-12,0)=""),"",C40/OFFSET(C40,-12,0)-1),"") | AG40: =IFERROR(IF(OR(D40="",OFFSET(D40,-12,0)=""),"",D40/OFFSET(D40,-12,0)-1),"") | AH40: =IFERROR(IF(OR(E40="",OFFSET(E40,-12,0)=""),"",E40/OFFSET(E40,-12,0)-1),"") | AI40: =IFERROR(IF(OR(F40="",OFFSET(F40,-12,0)=""),"",F40/OFFSET(F40,-12,0)-1),"") | AJ40: =IFERROR(IF(OR(G40="",OFFSET(G40,-12,0)=""),"",G40/OFFSET(G40,-12,0)-1),"") | AK40: =IFERROR(IF(OR(H40="",OFFSET(H40,-12,0)=""),"",H40/OFFSET(H40,-12,0)-1),"") | AL40: =IFERROR(IF(OR(I40="",OFFSET(I40,-12,0)=""),"",I40/OFFSET(I40,-12,0)-1),"") | ... AQ40: =IFERROR(IF(OR(N40="",OFFSET(N40,-12,0)=""),"",N40/OFFSET(N40,-12,0)-1),"") | AS40: =IFERROR(IF(OR(B40="",OFFSET(B40,-3,0)=""),"",(B40/OFFSET(B40,-3,0))^4-1),"") | AT40: =IFERROR(IF(OR(C40="",OFFSET(C40,-3,0)=""),"",(C40/OFFSET(C40,-3,0))^4-1),"") | AU40: =IFERROR(IF(OR(D40="",OFFSET(D40,-3,0)=""),"",(D40/OFFSET(D40,-3,0))^4-1),"") | AV40: =IFERROR(IF(OR(E40="",OFFSET(E40,-3,0)=""),"",(E40/OFFSET(E40,-3,0))^4-1),"") | AW40: =IFERROR(IF(OR(F40="",OFFSET(F40,-3,0)=""),"",(F40/OFFSET(F40,-3,0))^4-1),"") | AX40: =IFERROR(IF(OR(G40="",OFFSET(G40,-3,0)=""),"",(G40/OFFSET(G40,-3,0))^4-1),"") | AY40: =IFERROR(IF(OR(H40="",OFFSET(H40,-3,0)=""),"",(H40/OFFSET(H40,-3,0))^4-1),"") | AZ40: =IFERROR(IF(OR(I40="",OFFSET(I40,-3,0)=""),"",(I40/OFFSET(I40,-3,0))^4-1),"") | ... BE40: =IFERROR(IF(OR(N40="",OFFSET(N40,-3,0)=""),"",(N40/OFFSET(N40,-3,0))^4-1),"") | BG40: =IFERROR(IF(OR(B40="",OFFSET(B40,-6,0)=""),"",(B40/OFFSET(B40,-6,0))^2-1),"") | BH40: =IFERROR(IF(OR(C40="",OFFSET(C40,-6,0)=""),"",(C40/OFFSET(C40,-6,0))^2-1),"") | BI40: =IFERROR(IF(OR(D40="",OFFSET(D40,-6,0)=""),"",(D40/OFFSET(D40,-6,0))^2-1),"") | BJ40: =IFERROR(IF(OR(E40="",OFFSET(E40,-6,0)=""),"",(E40/OFFSET(E40,-6,0))^2-1),"") | BK40: =IFERROR(IF(OR(F40="",OFFSET(F40,-6,0)=""),"",(F40/OFFSET(F40,-6,0))^2-1),"") | BL40: =IFERROR(IF(OR(G40="",OFFSET(G40,-6,0)=""),"",(G40/OFFSET(G40,-6,0))^2-1),"") | BM40: =IFERROR(IF(OR(H40="",OFFSET(H40,-6,0)=""),"",(H40/OFFSET(H40,-6,0))^2-1),"") | BN40: =IFERROR(IF(OR(I40="",OFFSET(I40,-6,0)=""),"",(I40/OFFSET(I40,-6,0))^2-1),"") | ... BS40: =IFERROR(IF(OR(N40="",OFFSET(N40,-6,0)=""),"",(N40/OFFSET(N40,-6,0))^2-1),"") | BX40: =IF('Macrobond Imports'!FG39="","",'Macrobond Imports'!FG39) | BY40: =IF('Macrobond Imports'!AI39="","",'Macrobond Imports'!AI39) | CA40: =IFERROR(IF(OR(BX40="",OFFSET(BX40,-12,0)=""),"",BX40/OFFSET(BX40,-12,0)-1),"") | CB40: =IFERROR(IF(OR(BY40="",OFFSET(BY40,-12,0)=""),"",BY40/OFFSET(BY40,-12,0)-1),"")
A41: =IF('Macrobond Imports'!A40="","",'Macrobond Imports'!A40) -> 18323 | B41: =IF('Macrobond Imports'!B40="","",'Macrobond Imports'!B40) | C41: =IF('Macrobond Imports'!C40="","",'Macrobond Imports'!C40) | D41: =IF('Macrobond Imports'!Z40="","",'Macrobond Imports'!Z40) | E41: =IF('Macrobond Imports'!BH40="","",'Macrobond Imports'!BH40) | F41: =IF('Macrobond Imports'!BJ40="","",'Macrobond Imports'!BJ40) | G41: =IF('Macrobond Imports'!BK40="","",'Macrobond Imports'!BK40) | H41: =IF('Macrobond Imports'!BL40="","",'Macrobond Imports'!BL40) | I41: =IF('Macrobond Imports'!BS40="","",'Macrobond Imports'!BS40) | J41: =IF('Macrobond Imports'!AA40="","",'Macrobond Imports'!AA40) | K41: =IF('Macrobond Imports'!DF40="","",'Macrobond Imports'!DF40) -> 24.1 | L41: =IF('Macrobond Imports'!EA40="","",'Macrobond Imports'!EA40) -> 30.3 | M41: =IF('Macrobond Imports'!FA40="","",'Macrobond Imports'!FA40) | N41: =IF('Macrobond Imports'!FC40="","",'Macrobond Imports'!FC40) | P41: =A41 -> 18323 | Q41: =IF(OR(B41="",N(B40)=0),"",B41/B40-1) | R41: =IF(OR(C41="",N(C40)=0),"",C41/C40-1) | S41: =IF(OR(D41="",N(D40)=0),"",D41/D40-1) | T41: =IF(OR(E41="",N(E40)=0),"",E41/E40-1) | U41: =IF(OR(F41="",N(F40)=0),"",F41/F40-1) | V41: =IF(OR(G41="",N(G40)=0),"",G41/G40-1) | W41: =IF(OR(H41="",N(H40)=0),"",H41/H40-1) | X41: =IF(OR(I41="",N(I40)=0),"",I41/I40-1) | ... AC41: =IF(OR(N41="",N(N40)=0),"",N41/N40-1) | AE41: =IFERROR(IF(OR(B41="",OFFSET(B41,-12,0)=""),"",B41/OFFSET(B41,-12,0)-1),"") | AF41: =IFERROR(IF(OR(C41="",OFFSET(C41,-12,0)=""),"",C41/OFFSET(C41,-12,0)-1),"") | AG41: =IFERROR(IF(OR(D41="",OFFSET(D41,-12,0)=""),"",D41/OFFSET(D41,-12,0)-1),"") | AH41: =IFERROR(IF(OR(E41="",OFFSET(E41,-12,0)=""),"",E41/OFFSET(E41,-12,0)-1),"") | AI41: =IFERROR(IF(OR(F41="",OFFSET(F41,-12,0)=""),"",F41/OFFSET(F41,-12,0)-1),"") | AJ41: =IFERROR(IF(OR(G41="",OFFSET(G41,-12,0)=""),"",G41/OFFSET(G41,-12,0)-1),"") | AK41: =IFERROR(IF(OR(H41="",OFFSET(H41,-12,0)=""),"",H41/OFFSET(H41,-12,0)-1),"") | AL41: =IFERROR(IF(OR(I41="",OFFSET(I41,-12,0)=""),"",I41/OFFSET(I41,-12,0)-1),"") | ... AQ41: =IFERROR(IF(OR(N41="",OFFSET(N41,-12,0)=""),"",N41/OFFSET(N41,-12,0)-1),"") | AS41: =IFERROR(IF(OR(B41="",OFFSET(B41,-3,0)=""),"",(B41/OFFSET(B41,-3,0))^4-1),"") | AT41: =IFERROR(IF(OR(C41="",OFFSET(C41,-3,0)=""),"",(C41/OFFSET(C41,-3,0))^4-1),"") | AU41: =IFERROR(IF(OR(D41="",OFFSET(D41,-3,0)=""),"",(D41/OFFSET(D41,-3,0))^4-1),"") | AV41: =IFERROR(IF(OR(E41="",OFFSET(E41,-3,0)=""),"",(E41/OFFSET(E41,-3,0))^4-1),"") | AW41: =IFERROR(IF(OR(F41="",OFFSET(F41,-3,0)=""),"",(F41/OFFSET(F41,-3,0))^4-1),"") | AX41: =IFERROR(IF(OR(G41="",OFFSET(G41,-3,0)=""),"",(G41/OFFSET(G41,-3,0))^4-1),"") | AY41: =IFERROR(IF(OR(H41="",OFFSET(H41,-3,0)=""),"",(H41/OFFSET(H41,-3,0))^4-1),"") | AZ41: =IFERROR(IF(OR(I41="",OFFSET(I41,-3,0)=""),"",(I41/OFFSET(I41,-3,0))^4-1),"") | ... BE41: =IFERROR(IF(OR(N41="",OFFSET(N41,-3,0)=""),"",(N41/OFFSET(N41,-3,0))^4-1),"") | BG41: =IFERROR(IF(OR(B41="",OFFSET(B41,-6,0)=""),"",(B41/OFFSET(B41,-6,0))^2-1),"") | BH41: =IFERROR(IF(OR(C41="",OFFSET(C41,-6,0)=""),"",(C41/OFFSET(C41,-6,0))^2-1),"") | BI41: =IFERROR(IF(OR(D41="",OFFSET(D41,-6,0)=""),"",(D41/OFFSET(D41,-6,0))^2-1),"") | BJ41: =IFERROR(IF(OR(E41="",OFFSET(E41,-6,0)=""),"",(E41/OFFSET(E41,-6,0))^2-1),"") | BK41: =IFERROR(IF(OR(F41="",OFFSET(F41,-6,0)=""),"",(F41/OFFSET(F41,-6,0))^2-1),"") | BL41: =IFERROR(IF(OR(G41="",OFFSET(G41,-6,0)=""),"",(G41/OFFSET(G41,-6,0))^2-1),"") | BM41: =IFERROR(IF(OR(H41="",OFFSET(H41,-6,0)=""),"",(H41/OFFSET(H41,-6,0))^2-1),"") | BN41: =IFERROR(IF(OR(I41="",OFFSET(I41,-6,0)=""),"",(I41/OFFSET(I41,-6,0))^2-1),"") | ... BS41: =IFERROR(IF(OR(N41="",OFFSET(N41,-6,0)=""),"",(N41/OFFSET(N41,-6,0))^2-1),"") | BX41: =IF('Macrobond Imports'!FG40="","",'Macrobond Imports'!FG40) | BY41: =IF('Macrobond Imports'!AI40="","",'Macrobond Imports'!AI40) | CA41: =IFERROR(IF(OR(BX41="",OFFSET(BX41,-12,0)=""),"",BX41/OFFSET(BX41,-12,0)-1),"") | CB41: =IFERROR(IF(OR(BY41="",OFFSET(BY41,-12,0)=""),"",BY41/OFFSET(BY41,-12,0)-1),"")
A42: =IF('Macrobond Imports'!A41="","",'Macrobond Imports'!A41) -> 18354 | B42: =IF('Macrobond Imports'!B41="","",'Macrobond Imports'!B41) | C42: =IF('Macrobond Imports'!C41="","",'Macrobond Imports'!C41) | D42: =IF('Macrobond Imports'!Z41="","",'Macrobond Imports'!Z41) | E42: =IF('Macrobond Imports'!BH41="","",'Macrobond Imports'!BH41) | F42: =IF('Macrobond Imports'!BJ41="","",'Macrobond Imports'!BJ41) | G42: =IF('Macrobond Imports'!BK41="","",'Macrobond Imports'!BK41) | H42: =IF('Macrobond Imports'!BL41="","",'Macrobond Imports'!BL41) | I42: =IF('Macrobond Imports'!BS41="","",'Macrobond Imports'!BS41) | J42: =IF('Macrobond Imports'!AA41="","",'Macrobond Imports'!AA41) | K42: =IF('Macrobond Imports'!DF41="","",'Macrobond Imports'!DF41) -> 24.2 | L42: =IF('Macrobond Imports'!EA41="","",'Macrobond Imports'!EA41) -> 30.5 | M42: =IF('Macrobond Imports'!FA41="","",'Macrobond Imports'!FA41) | N42: =IF('Macrobond Imports'!FC41="","",'Macrobond Imports'!FC41) | P42: =A42 -> 18354 | Q42: =IF(OR(B42="",N(B41)=0),"",B42/B41-1) | R42: =IF(OR(C42="",N(C41)=0),"",C42/C41-1) | S42: =IF(OR(D42="",N(D41)=0),"",D42/D41-1) | T42: =IF(OR(E42="",N(E41)=0),"",E42/E41-1) | U42: =IF(OR(F42="",N(F41)=0),"",F42/F41-1) | V42: =IF(OR(G42="",N(G41)=0),"",G42/G41-1) | W42: =IF(OR(H42="",N(H41)=0),"",H42/H41-1) | X42: =IF(OR(I42="",N(I41)=0),"",I42/I41-1) | ... AC42: =IF(OR(N42="",N(N41)=0),"",N42/N41-1) | AE42: =IFERROR(IF(OR(B42="",OFFSET(B42,-12,0)=""),"",B42/OFFSET(B42,-12,0)-1),"") | AF42: =IFERROR(IF(OR(C42="",OFFSET(C42,-12,0)=""),"",C42/OFFSET(C42,-12,0)-1),"") | AG42: =IFERROR(IF(OR(D42="",OFFSET(D42,-12,0)=""),"",D42/OFFSET(D42,-12,0)-1),"") | AH42: =IFERROR(IF(OR(E42="",OFFSET(E42,-12,0)=""),"",E42/OFFSET(E42,-12,0)-1),"") | AI42: =IFERROR(IF(OR(F42="",OFFSET(F42,-12,0)=""),"",F42/OFFSET(F42,-12,0)-1),"") | AJ42: =IFERROR(IF(OR(G42="",OFFSET(G42,-12,0)=""),"",G42/OFFSET(G42,-12,0)-1),"") | AK42: =IFERROR(IF(OR(H42="",OFFSET(H42,-12,0)=""),"",H42/OFFSET(H42,-12,0)-1),"") | AL42: =IFERROR(IF(OR(I42="",OFFSET(I42,-12,0)=""),"",I42/OFFSET(I42,-12,0)-1),"") | ... AQ42: =IFERROR(IF(OR(N42="",OFFSET(N42,-12,0)=""),"",N42/OFFSET(N42,-12,0)-1),"") | AS42: =IFERROR(IF(OR(B42="",OFFSET(B42,-3,0)=""),"",(B42/OFFSET(B42,-3,0))^4-1),"") | AT42: =IFERROR(IF(OR(C42="",OFFSET(C42,-3,0)=""),"",(C42/OFFSET(C42,-3,0))^4-1),"") | AU42: =IFERROR(IF(OR(D42="",OFFSET(D42,-3,0)=""),"",(D42/OFFSET(D42,-3,0))^4-1),"") | AV42: =IFERROR(IF(OR(E42="",OFFSET(E42,-3,0)=""),"",(E42/OFFSET(E42,-3,0))^4-1),"") | AW42: =IFERROR(IF(OR(F42="",OFFSET(F42,-3,0)=""),"",(F42/OFFSET(F42,-3,0))^4-1),"") | AX42: =IFERROR(IF(OR(G42="",OFFSET(G42,-3,0)=""),"",(G42/OFFSET(G42,-3,0))^4-1),"") | AY42: =IFERROR(IF(OR(H42="",OFFSET(H42,-3,0)=""),"",(H42/OFFSET(H42,-3,0))^4-1),"") | AZ42: =IFERROR(IF(OR(I42="",OFFSET(I42,-3,0)=""),"",(I42/OFFSET(I42,-3,0))^4-1),"") | ... BE42: =IFERROR(IF(OR(N42="",OFFSET(N42,-3,0)=""),"",(N42/OFFSET(N42,-3,0))^4-1),"") | BG42: =IFERROR(IF(OR(B42="",OFFSET(B42,-6,0)=""),"",(B42/OFFSET(B42,-6,0))^2-1),"") | BH42: =IFERROR(IF(OR(C42="",OFFSET(C42,-6,0)=""),"",(C42/OFFSET(C42,-6,0))^2-1),"") | BI42: =IFERROR(IF(OR(D42="",OFFSET(D42,-6,0)=""),"",(D42/OFFSET(D42,-6,0))^2-1),"") | BJ42: =IFERROR(IF(OR(E42="",OFFSET(E42,-6,0)=""),"",(E42/OFFSET(E42,-6,0))^2-1),"") | BK42: =IFERROR(IF(OR(F42="",OFFSET(F42,-6,0)=""),"",(F42/OFFSET(F42,-6,0))^2-1),"") | BL42: =IFERROR(IF(OR(G42="",OFFSET(G42,-6,0)=""),"",(G42/OFFSET(G42,-6,0))^2-1),"") | BM42: =IFERROR(IF(OR(H42="",OFFSET(H42,-6,0)=""),"",(H42/OFFSET(H42,-6,0))^2-1),"") | BN42: =IFERROR(IF(OR(I42="",OFFSET(I42,-6,0)=""),"",(I42/OFFSET(I42,-6,0))^2-1),"") | ... BS42: =IFERROR(IF(OR(N42="",OFFSET(N42,-6,0)=""),"",(N42/OFFSET(N42,-6,0))^2-1),"") | BX42: =IF('Macrobond Imports'!FG41="","",'Macrobond Imports'!FG41) | BY42: =IF('Macrobond Imports'!AI41="","",'Macrobond Imports'!AI41) | CA42: =IFERROR(IF(OR(BX42="",OFFSET(BX42,-12,0)=""),"",BX42/OFFSET(BX42,-12,0)-1),"") | CB42: =IFERROR(IF(OR(BY42="",OFFSET(BY42,-12,0)=""),"",BY42/OFFSET(BY42,-12,0)-1),"")
A43: =IF('Macrobond Imports'!A42="","",'Macrobond Imports'!A42) -> 18384 | B43: =IF('Macrobond Imports'!B42="","",'Macrobond Imports'!B42) | C43: =IF('Macrobond Imports'!C42="","",'Macrobond Imports'!C42) | D43: =IF('Macrobond Imports'!Z42="","",'Macrobond Imports'!Z42) | E43: =IF('Macrobond Imports'!BH42="","",'Macrobond Imports'!BH42) | F43: =IF('Macrobond Imports'!BJ42="","",'Macrobond Imports'!BJ42) | G43: =IF('Macrobond Imports'!BK42="","",'Macrobond Imports'!BK42) | H43: =IF('Macrobond Imports'!BL42="","",'Macrobond Imports'!BL42) | I43: =IF('Macrobond Imports'!BS42="","",'Macrobond Imports'!BS42) | J43: =IF('Macrobond Imports'!AA42="","",'Macrobond Imports'!AA42) | K43: =IF('Macrobond Imports'!DF42="","",'Macrobond Imports'!DF42) -> 24.6 | L43: =IF('Macrobond Imports'!EA42="","",'Macrobond Imports'!EA42) -> 31.6 | M43: =IF('Macrobond Imports'!FA42="","",'Macrobond Imports'!FA42) | N43: =IF('Macrobond Imports'!FC42="","",'Macrobond Imports'!FC42) | P43: =A43 -> 18384 | Q43: =IF(OR(B43="",N(B42)=0),"",B43/B42-1) | R43: =IF(OR(C43="",N(C42)=0),"",C43/C42-1) | S43: =IF(OR(D43="",N(D42)=0),"",D43/D42-1) | T43: =IF(OR(E43="",N(E42)=0),"",E43/E42-1) | U43: =IF(OR(F43="",N(F42)=0),"",F43/F42-1) | V43: =IF(OR(G43="",N(G42)=0),"",G43/G42-1) | W43: =IF(OR(H43="",N(H42)=0),"",H43/H42-1) | X43: =IF(OR(I43="",N(I42)=0),"",I43/I42-1) | ... AC43: =IF(OR(N43="",N(N42)=0),"",N43/N42-1) | AE43: =IFERROR(IF(OR(B43="",OFFSET(B43,-12,0)=""),"",B43/OFFSET(B43,-12,0)-1),"") | AF43: =IFERROR(IF(OR(C43="",OFFSET(C43,-12,0)=""),"",C43/OFFSET(C43,-12,0)-1),"") | AG43: =IFERROR(IF(OR(D43="",OFFSET(D43,-12,0)=""),"",D43/OFFSET(D43,-12,0)-1),"") | AH43: =IFERROR(IF(OR(E43="",OFFSET(E43,-12,0)=""),"",E43/OFFSET(E43,-12,0)-1),"") | AI43: =IFERROR(IF(OR(F43="",OFFSET(F43,-12,0)=""),"",F43/OFFSET(F43,-12,0)-1),"") | AJ43: =IFERROR(IF(OR(G43="",OFFSET(G43,-12,0)=""),"",G43/OFFSET(G43,-12,0)-1),"") | AK43: =IFERROR(IF(OR(H43="",OFFSET(H43,-12,0)=""),"",H43/OFFSET(H43,-12,0)-1),"") | AL43: =IFERROR(IF(OR(I43="",OFFSET(I43,-12,0)=""),"",I43/OFFSET(I43,-12,0)-1),"") | ... AQ43: =IFERROR(IF(OR(N43="",OFFSET(N43,-12,0)=""),"",N43/OFFSET(N43,-12,0)-1),"") | AS43: =IFERROR(IF(OR(B43="",OFFSET(B43,-3,0)=""),"",(B43/OFFSET(B43,-3,0))^4-1),"") | AT43: =IFERROR(IF(OR(C43="",OFFSET(C43,-3,0)=""),"",(C43/OFFSET(C43,-3,0))^4-1),"") | AU43: =IFERROR(IF(OR(D43="",OFFSET(D43,-3,0)=""),"",(D43/OFFSET(D43,-3,0))^4-1),"") | AV43: =IFERROR(IF(OR(E43="",OFFSET(E43,-3,0)=""),"",(E43/OFFSET(E43,-3,0))^4-1),"") | AW43: =IFERROR(IF(OR(F43="",OFFSET(F43,-3,0)=""),"",(F43/OFFSET(F43,-3,0))^4-1),"") | AX43: =IFERROR(IF(OR(G43="",OFFSET(G43,-3,0)=""),"",(G43/OFFSET(G43,-3,0))^4-1),"") | AY43: =IFERROR(IF(OR(H43="",OFFSET(H43,-3,0)=""),"",(H43/OFFSET(H43,-3,0))^4-1),"") | AZ43: =IFERROR(IF(OR(I43="",OFFSET(I43,-3,0)=""),"",(I43/OFFSET(I43,-3,0))^4-1),"") | ... BE43: =IFERROR(IF(OR(N43="",OFFSET(N43,-3,0)=""),"",(N43/OFFSET(N43,-3,0))^4-1),"") | BG43: =IFERROR(IF(OR(B43="",OFFSET(B43,-6,0)=""),"",(B43/OFFSET(B43,-6,0))^2-1),"") | BH43: =IFERROR(IF(OR(C43="",OFFSET(C43,-6,0)=""),"",(C43/OFFSET(C43,-6,0))^2-1),"") | BI43: =IFERROR(IF(OR(D43="",OFFSET(D43,-6,0)=""),"",(D43/OFFSET(D43,-6,0))^2-1),"") | BJ43: =IFERROR(IF(OR(E43="",OFFSET(E43,-6,0)=""),"",(E43/OFFSET(E43,-6,0))^2-1),"") | BK43: =IFERROR(IF(OR(F43="",OFFSET(F43,-6,0)=""),"",(F43/OFFSET(F43,-6,0))^2-1),"") | BL43: =IFERROR(IF(OR(G43="",OFFSET(G43,-6,0)=""),"",(G43/OFFSET(G43,-6,0))^2-1),"") | BM43: =IFERROR(IF(OR(H43="",OFFSET(H43,-6,0)=""),"",(H43/OFFSET(H43,-6,0))^2-1),"") | BN43: =IFERROR(IF(OR(I43="",OFFSET(I43,-6,0)=""),"",(I43/OFFSET(I43,-6,0))^2-1),"") | ... BS43: =IFERROR(IF(OR(N43="",OFFSET(N43,-6,0)=""),"",(N43/OFFSET(N43,-6,0))^2-1),"") | BX43: =IF('Macrobond Imports'!FG42="","",'Macrobond Imports'!FG42) | BY43: =IF('Macrobond Imports'!AI42="","",'Macrobond Imports'!AI42) | CA43: =IFERROR(IF(OR(BX43="",OFFSET(BX43,-12,0)=""),"",BX43/OFFSET(BX43,-12,0)-1),"") | CB43: =IFERROR(IF(OR(BY43="",OFFSET(BY43,-12,0)=""),"",BY43/OFFSET(BY43,-12,0)-1),"")
